Workbook
Name BuildYear: Parameters!$B$5
Name Scenario: 'Funding Check'!$B$1

Sheet Parameters
A1: VERSION | B1: 2.1
A3: Parameter | B3: Value | D3: Link updated? | E3: No
A4: Token
A5: Year From | B5: 2023/24
A6: Api Url Root | B6: https://api.impplanner.co.uk
A7: Date Last Amended | B7: 45212
A8: Start Date | B8: 46054 | D8: Strand 2 Start Date
A9: Apprentice levy code - Teaching | B9: 675100 | D9: Finance code for Apprentice levy budget rows
A10: Apprentice levy code - Support | B10: 675110
A11: File Path - Pre 16
A12: File Path - Post 16

Sheet Notes
A1: Process Notes
A3: Updating API
A5: Step
A6: 1 | B6: Add API code to parameter tab
A28: 2 | B28: Navigate to the queries and connections in Data tab
A51: 3 | B51: This will bring up a side menu
A104: 4 | B104: Right click on the API folder and click "Refresh"
A147: 5 | B147: If the below pop-up appears please tick the "Ignore Privacy Levels" box and then click the "Save" button.
A164: 6 | B164: If the below pop-up appears please click the "Don't Update" button.
A174: Local Authorities and Schools
A176: Step
A177: 1 | B177: "LA" Column, of local authorities, needs to be updated with the code LAX with X being a count of each LA. E.g. LA0, LA1, LA2, LA3 etc.
A190: 2 | B190: London Weighting Type needs to be updated with the correct type from the drop down. This is based on the Local authority, whose weighting can be found in column "Teachers IL/OL/FRI" of the "Local Authorities - standard codes" document.
A206: #VALUE!
A250: 3 | B250: School Type needs to be updated with the correct type from the drop down. The type in the purple API section can be used but it is worth double checking them against the Funding statement as the trust may label a school as "Secondary" but it is actually a special school.
B267: Below is an extract of a funding statement which can help identify the school type by whether they have funding for Primary, KS3 and KS4
A279: Finance codes S3
A281: Step
A282: 1 | B282: Once Local authorities and Schools have been updated, you will then need to update Finance codes S3. This can be done by right clicking on the table, in tab "Finance codes S3", and clicking refresh.
A324: Staff Role Groups
A326: Step
A327: 1 | B327: The StfRoleGroup tab will need to be linked to the Strand 2 workbook. This is achieved by double clicking on the SRG query in "Queries & Connections".
A378: 2 | B378: Then double click on source and click browse.
A410: 3 | B410: This will bring up the file browser. Navigate to the strand 2 workbook in the relevant customer folder and click import.
A456: 4 | B456: Then click the save and load button
A479: 5 | B479: This should load the codes, used by the Strand 2 builder in staff role groups. This will need to be updated once the stand 2 builder has completed Staff role groups. You can do this by right clicking on the table and clicking refresh.
A510: Strand 3
A512: Step
A513: 1 | B513: To update the strand 3 tabs, navigate to the queries & connections in data
A535: 2 | B535: Navigate to the Template Prep Refresh folder
A573: 3 | B573: Right click on the folder and click refresh

Sheet Strand 3 Checklist
A1: Checklist
A2: Task | B2: Note | C2: Check
A3: Check for Month Profile Issue | C3: =SUM(MONTHPRF[Will import if zero]) -> 0
A4: Check for Calculator Issue | C4: =SUM(Calculators[Will import if 0]) -> 58
A5: Check for Statistics Issue | C5: =SUM(Statistics_import[Will Import if 0]) -> #N/A
A6: Check for Pupil Numbers Issue | C6: =SUM(Pupils_import[Will Import if 0]) -> #N/A
A7: Check for Funding Issue | C7: =SUM(Funding_import[Will Import if 0]) -> 0
A8: Check for Income Issue | C8: =SUM(Income_import[Will Import if 0]) -> #N/A
A9: Check for Expenditure Issue | C9: =SUM(Expenditure_import[Will Import if 0]) -> #N/A
A10: Check for Brought Forward Balances Issue | C10: =SUM(BF_import[Will Import if 0]) -> #N/A
A11: Check for Approved budget Issue | C11: =SUM(APBUD[Will Import if 0]) -> #N/A
A12: Check for Finance codes S3 Issue | C12: =SUM(FC_import[Will Import if 0]) -> 75
A13: Check Income built for all locations | C13: =COUNTA(SCHOOLS[SchoolCode])-COUNTA(_xlfn.UNIQUE(Income_import[SchoolCode])) -> 7
A14: Check Expenditure built for all locations | C14: =COUNTA(SCHOOLS[SchoolCode])-COUNTA(_xlfn.UNIQUE(Expenditure_import[SchoolCode])) -> 0
A15: Check Funding built for all Schools | C15: =COUNTA(SCHOOLS[SchoolCode])-COUNTA(_xlfn.UNIQUE(Funding_import[SchoolCode]))-1 -> 8
A16: Total Tab Check | C16: =SUM(C3:C11) -> #N/A
A17: Has Build Information Questions been reviewed?
A18: Refresh All Queries (twice) to update ScenarioSummary, ScenarioRows and ScenarioYearValues
A19: Has Scenario Summary been reviewed for reasonableness? | B19: Any remaining errors or unusual row/value variances
A20: Have you set up all Scenario's used in ScenarioApBud? | B20: Create scenario in planner "Scenario control"
A21: If requested, have we used month profiles? | B21: Month breakdown in budget or customer guidance on profiles
A22: Rows Missing Funds | C22: =IF(C23="Yes",COUNTBLANK(Income_import[FundCode])+COUNTBLANK(Expenditure_import[FundCode])+COUNTBLANK(BF_import[FundCode])+COUNTBLANK(APBUD[FundCode]),0) -> 0
A23: If Funds are used at Scenario Row Level then has the setting been changed on Planner? | B23: Planner - Setup - Options - SCENARIOROWFUNDS | C23: NA
A24: If Funds are used at Scenario Row Level have they been added to the budget and BFwd Balances rows? | B24: Funds column on Income, Expenditure, BF Balances and ScenarioApBud
A25: Have we completed any/all additional calcs requested by customer? | B25: Found in Build Information
A26: Have we Updated Finance code string for Levy_CALC and Levy_ALL? | B26: Create a string of finance codes used in StfRoleGroup Gross Finance code column for Levy_CALC and AnnualFTE Finance code column for LEVY_ALL.
A27: Update Finance codes used in ESFA_TOTAL, MPPFL_ADJ_CALC and ESFA_POST16_TOTAL | B27: ESFA_TOTAL should be all funding codes used for pre 16 GAG funding and ESFA_POST16_TOTAL should only be funding codes used for post 16 GAG funding. MPPFL_ADJ_CALC should be all finance codes used in pre 16 GAG funding
A28: Use Funding Check Tab to check funding statement total against budget values
A29: In ScenarioSummary Tab, Enter Customer Budget Values and check they match the scenario totals in ScenarioApBud | B29: Scenario Summary budget values. If they do not match provide reasonable explanation.
A30: Make sure the description used in Income for GAG funding has "GAG" at the start. | B30: E.g. GAG Pre 16 Funding
A31: Have we checked customers budget notes for relevant information? | B31: E.g. Pupil premium budget row has a note that it includes a recovery premium value of £5000. So we will need to make sure we have the recovery premium calculator attached to this finance code.
A32: Have we checked what has been changed since this templates version? | B32: E.g. In a later version of the template we added a calculator for MPPFL, which will need to be added to this template
A33: Have we removed unnecessary rows in the below sections?
A34: Finance codes | B34: E.g. FUNDED_KS5 but no 6th form in trust
A35: Calculators | B35: E.g. High needs calculator but no special provision
A36: Statistic's | B36: E.g. Paygrant Inner London but no schools in that area
A37: Funding | B37: E.g. Paygrant lines but no nursery/6th form/special schools
A38: Pupils | B38: E.g. PUPIL_CEN_12 but no 6th form at school.
A39: Have we updated generic titles/codes/descriptions in finance codes and calculators? | B39: E.g. Funding 01 changed to Funding Pre 16 GAG
A40: Have notes been added to Import Checklist Tab for any build specific potential import issues? | B40: Will not always be aware before import.
A41: Have we added any additional Departments or Budget Finance codes to Planner? | B41: For non-interface customers where we need to add additional codes, that are used in the budgets, but were not added in strand 1.
A42: Have we added the funding check tables to the system build notes? | B42: Copy table from tab "Funding Statement Check" and table from tab "Funding Check" to the system build notes
A43: Have we exported the Calculators tab as CSV and then changed the "CalculatorLockRows" to 0 for all rows? | B43: We need a copy of the calculators, with the lock status, that we can import after we have completed the system review.
A45: Reviewed by Builder | B45: Y/N
A46: Reviewed by Lead Consultant | B46: Y/N

Sheet Build Checks Dashboard
A1: BUILD CHECKS DASHBOARD
A3: CONFIGURATION | F3: SUMMARY STATUS
A4: Enter school codes below. All checks will automatically include listed schools.
F5: Check | G5: Passed | H5: Failed | I5: Status
A6: School Code | B6: School Name (auto) | F6: 1. Pupil Numbers (vs FS) | G6: =COUNTIF(N40:N59,"PASS") -> 10 | H6: =COUNTIF(N40:N59,"FAIL") -> 0 | I6: =IF(H6=0,"✓ ALL PASSED","⚠ CHECK") -> ✓ ALL PASSED
A7: TLT | B7: =IF(A7="","",IFERROR(VLOOKUP(A7,Schools!K:N,4,FALSE()),"Not found")) -> Together Learning Trust | F7: 2. Pupil Totals (vs Cust) | G7: =COUNTIF(L65:L144,"PASS") -> 40 | H7: =COUNTIF(L65:L144,"FAIL") -> 0 | I7: =IF(H7=0,"✓ ALL PASSED","⚠ CHECK") -> ✓ ALL PASSED
A8: BBP | B8: =IF(A8="","",IFERROR(VLOOKUP(A8,Schools!K:N,4,FALSE()),"Not found")) -> Bolton Brow Primary Academy | F8: 3. Funding Statement | G8: =COUNTIF(H150:H169,"PASS") -> 10 | H8: =COUNTIF(H150:H169,"FAIL") -> 0 | I8: =IF(H8=0,"✓ ALL PASSED","⚠ CHECK") -> ✓ ALL PASSED
A9: LCP | B9: =IF(A9="","",IFERROR(VLOOKUP(A9,Schools!K:N,4,FALSE()),"Not found")) -> Linthwaite Clough Primary School | F9: 4. Budget Values | G9: =COUNTIF(E175:E194,"PASS") -> 10 | H9: =COUNTIF(E175:E194,"FAIL") -> 0 | I9: =IF(H9=0,"✓ ALL PASSED","⚠ CHECK") -> ✓ ALL PASSED
A10: MMP | B10: =IF(A10="","",IFERROR(VLOOKUP(A10,Schools!K:N,4,FALSE()),"Not found")) -> Meltham Moor Primary School
A11: NIN | B11: =IF(A11="","",IFERROR(VLOOKUP(A11,Schools!K:N,4,FALSE()),"Not found")) -> Netherton Infant and Nursery School
A12: SRA | B12: =IF(A12="","",IFERROR(VLOOKUP(A12,Schools!K:N,4,FALSE()),"Not found")) -> Scout Road Academy
A13: BBS | B13: =IF(A13="","",IFERROR(VLOOKUP(A13,Schools!K:N,4,FALSE()),"Not found")) -> The Brooksbank School
A14: HHS | B14: =IF(A14="","",IFERROR(VLOOKUP(A14,Schools!K:N,4,FALSE()),"Not found")) -> Honley High School
A15: RVS | B15: =IF(A15="","",IFERROR(VLOOKUP(A15,Schools!K:N,4,FALSE()),"Not found")) -> Ryburn Valley High School
A16: CHS | B16: =IF(A16="","",IFERROR(VLOOKUP(A16,Schools!K:N,4,FALSE()),"Not found")) -> Castle Hill School
B17: =IF(A17="","",IFERROR(VLOOKUP(A17,Schools!K:N,4,FALSE()),"Not found"))
B18: =IF(A18="","",IFERROR(VLOOKUP(A18,Schools!K:N,4,FALSE()),"Not found"))
B19: =IF(A19="","",IFERROR(VLOOKUP(A19,Schools!K:N,4,FALSE()),"Not found"))
B20: =IF(A20="","",IFERROR(VLOOKUP(A20,Schools!K:N,4,FALSE()),"Not found"))
B21: =IF(A21="","",IFERROR(VLOOKUP(A21,Schools!K:N,4,FALSE()),"Not found"))
B22: =IF(A22="","",IFERROR(VLOOKUP(A22,Schools!K:N,4,FALSE()),"Not found"))
B23: =IF(A23="","",IFERROR(VLOOKUP(A23,Schools!K:N,4,FALSE()),"Not found"))
B24: =IF(A24="","",IFERROR(VLOOKUP(A24,Schools!K:N,4,FALSE()),"Not found"))
B25: =IF(A25="","",IFERROR(VLOOKUP(A25,Schools!K:N,4,FALSE()),"Not found"))
B26: =IF(A26="","",IFERROR(VLOOKUP(A26,Schools!K:N,4,FALSE()),"Not found"))
A28: Finance Code Config
A29: Pre-16 Code 1 | B29: 510100
A30: Pre-16 Code 2 | B30: 510150
A31: Pre-16 Code 3
A32: Post-16 Code 1 | B32: 510700
A33: Post-16 Code 2
A34: Post-16 Code 3
A37: 1. PUPIL NUMBER CHECKS (Autumn Census 24/25 vs Funding Statement 25/26)
A39: School | B39: Pri (Cen) | C39: Pri (FS) | D39: Pri Var | E39: KS3 (Cen) | F39: KS3 (FS) | G39: KS3 Var | H39: KS4 (Cen) | I39: KS4 (FS) | J39: KS4 Var | K39: KS5 (Cen) | L39: KS5 (FS) | M39: KS5 Var | N39: Status
A40: =IF($A$7="","",$A$7) -> TLT | B40: =IF($A$7="","",SUMIFS('Pupils Insert Table'!J:J,'Pupils Insert Table'!D:D,$A$7,'Pupils Insert Table'!E:E,"PUPIL_CEN_00")+SUMIFS('Pupils Insert Table'!J:J,'Pupils Insert Table'!D:D,$A$7,'Pupils Insert Table'!E:E,"PUPIL_CEN_01")+SUMIFS('Pupils Insert Table'!J:J,'Pupils Insert Table'!D:D,$A$7,'Pupils Insert Table'!E:E,"PUPIL_CEN_02")+SUMIFS('Pupils Insert Table'!J:J,'Pupils Insert Table'!D:D,$A$7,'Pupils Insert Table'!E:E,"PUPIL_CEN_03")+SUMIFS('Pupils Insert Table'!J:J,'Pupils Insert Table'!D:D,$A$7,'Pupils Insert Table'!E:E,"PUPIL_CEN_04")+SUMIFS('Pupils Insert Table'!J:J,'Pupils Insert Table'!D:D,$A$7,'Pupils Insert Table'!E:E,"PUPIL_CEN_05")+SUMIFS('Pupils Insert Table'!J:J,'Pupils Insert Table'!D:D,$A$7,'Pupils Insert Table'!E:E,"PUPIL_CEN_06")) -> 0 | D40: =IF($A$7="","",B40-C40) -> 0 | E40: =IF($A$7="","",SUMIFS('Pupils Insert Table'!J:J,'Pupils Insert Table'!D:D,$A$7,'Pupils Insert Table'!E:E,"PUPIL_CEN_07")+SUMIFS('Pupils Insert Table'!J:J,'Pupils Insert Table'!D:D,$A$7,'Pupils Insert Table'!E:E,"PUPIL_CEN_08")+SUMIFS('Pupils Insert Table'!J:J,'Pupils Insert Table'!D:D,$A$7,'Pupils Insert Table'!E:E,"PUPIL_CEN_09")) -> 0 | G40: =IF($A$7="","",E40-F40) -> 0 | H40: =IF($A$7="","",SUMIFS('Pupils Insert Table'!J:J,'Pupils Insert Table'!D:D,$A$7,'Pupils Insert Table'!E:E,"PUPIL_CEN_10")+SUMIFS('Pupils Insert Table'!J:J,'Pupils Insert Table'!D:D,$A$7,'Pupils Insert Table'!E:E,"PUPIL_CEN_11")) -> 0 | J40: =IF($A$7="","",H40-I40) -> 0 | K40: =IF($A$7="","",SUMIFS('Pupils Insert Table'!J:J,'Pupils Insert Table'!D:D,$A$7,'Pupils Insert Table'!E:E,"PUPIL_CEN_12")+SUMIFS('Pupils Insert Table'!J:J,'Pupils Insert Table'!D:D,$A$7,'Pupils Insert Table'!E:E,"PUPIL_CEN_13")) -> 0 | M40: =IF($A$7="","",K40-L40) -> 0 | N40: =IF($A$7="","",IF(AND(ABS(D40)<=10,ABS(G40)<=10,ABS(J40)<=10,ABS(M40)<=10),"PASS","FAIL")) -> PASS
A41: =IF($A$8="","",$A$8) -> BBP | B41: =IF($A$8="","",SUMIFS('Pupils Insert Table'!J:J,'Pupils Insert Table'!D:D,$A$8,'Pupils Insert Table'!E:E,"PUPIL_CEN_00")+SUMIFS('Pupils Insert Table'!J:J,'Pupils Insert Table'!D:D,$A$8,'Pupils Insert Table'!E:E,"PUPIL_CEN_01")+SUMIFS('Pupils Insert Table'!J:J,'Pupils Insert Table'!D:D,$A$8,'Pupils Insert Table'!E:E,"PUPIL_CEN_02")+SUMIFS('Pupils Insert Table'!J:J,'Pupils Insert Table'!D:D,$A$8,'Pupils Insert Table'!E:E,"PUPIL_CEN_03")+SUMIFS('Pupils Insert Table'!J:J,'Pupils Insert Table'!D:D,$A$8,'Pupils Insert Table'!E:E,"PUPIL_CEN_04")+SUMIFS('Pupils Insert Table'!J:J,'Pupils Insert Table'!D:D,$A$8,'Pupils Insert Table'!E:E,"PUPIL_CEN_05")+SUMIFS('Pupils Insert Table'!J:J,'Pupils Insert Table'!D:D,$A$8,'Pupils Insert Table'!E:E,"PUPIL_CEN_06")) -> 0 | D41: =IF($A$8="","",B41-C41) -> 0 | E41: =IF($A$8="","",SUMIFS('Pupils Insert Table'!J:J,'Pupils Insert Table'!D:D,$A$8,'Pupils Insert Table'!E:E,"PUPIL_CEN_07")+SUMIFS('Pupils Insert Table'!J:J,'Pupils Insert Table'!D:D,$A$8,'Pupils Insert Table'!E:E,"PUPIL_CEN_08")+SUMIFS('Pupils Insert Table'!J:J,'Pupils Insert Table'!D:D,$A$8,'Pupils Insert Table'!E:E,"PUPIL_CEN_09")) -> 0 | G41: =IF($A$8="","",E41-F41) -> 0 | H41: =IF($A$8="","",SUMIFS('Pupils Insert Table'!J:J,'Pupils Insert Table'!D:D,$A$8,'Pupils Insert Table'!E:E,"PUPIL_CEN_10")+SUMIFS('Pupils Insert Table'!J:J,'Pupils Insert Table'!D:D,$A$8,'Pupils Insert Table'!E:E,"PUPIL_CEN_11")) -> 0 | J41: =IF($A$8="","",H41-I41) -> 0 | K41: =IF($A$8="","",SUMIFS('Pupils Insert Table'!J:J,'Pupils Insert Table'!D:D,$A$8,'Pupils Insert Table'!E:E,"PUPIL_CEN_12")+SUMIFS('Pupils Insert Table'!J:J,'Pupils Insert Table'!D:D,$A$8,'Pupils Insert Table'!E:E,"PUPIL_CEN_13")) -> 0 | M41: =IF($A$8="","",K41-L41) -> 0 | N41: =IF($A$8="","",IF(AND(ABS(D41)<=10,ABS(G41)<=10,ABS(J41)<=10,ABS(M41)<=10),"PASS","FAIL")) -> PASS
A42: =IF($A$9="","",$A$9) -> LCP | B42: =IF($A$9="","",SUMIFS('Pupils Insert Table'!J:J,'Pupils Insert Table'!D:D,$A$9,'Pupils Insert Table'!E:E,"PUPIL_CEN_00")+SUMIFS('Pupils Insert Table'!J:J,'Pupils Insert Table'!D:D,$A$9,'Pupils Insert Table'!E:E,"PUPIL_CEN_01")+SUMIFS('Pupils Insert Table'!J:J,'Pupils Insert Table'!D:D,$A$9,'Pupils Insert Table'!E:E,"PUPIL_CEN_02")+SUMIFS('Pupils Insert Table'!J:J,'Pupils Insert Table'!D:D,$A$9,'Pupils Insert Table'!E:E,"PUPIL_CEN_03")+SUMIFS('Pupils Insert Table'!J:J,'Pupils Insert Table'!D:D,$A$9,'Pupils Insert Table'!E:E,"PUPIL_CEN_04")+SUMIFS('Pupils Insert Table'!J:J,'Pupils Insert Table'!D:D,$A$9,'Pupils Insert Table'!E:E,"PUPIL_CEN_05")+SUMIFS('Pupils Insert Table'!J:J,'Pupils Insert Table'!D:D,$A$9,'Pupils Insert Table'!E:E,"PUPIL_CEN_06")) -> 0 | D42: =IF($A$9="","",B42-C42) -> 0 | E42: =IF($A$9="","",SUMIFS('Pupils Insert Table'!J:J,'Pupils Insert Table'!D:D,$A$9,'Pupils Insert Table'!E:E,"PUPIL_CEN_07")+SUMIFS('Pupils Insert Table'!J:J,'Pupils Insert Table'!D:D,$A$9,'Pupils Insert Table'!E:E,"PUPIL_CEN_08")+SUMIFS('Pupils Insert Table'!J:J,'Pupils Insert Table'!D:D,$A$9,'Pupils Insert Table'!E:E,"PUPIL_CEN_09")) -> 0 | G42: =IF($A$9="","",E42-F42) -> 0 | H42: =IF($A$9="","",SUMIFS('Pupils Insert Table'!J:J,'Pupils Insert Table'!D:D,$A$9,'Pupils Insert Table'!E:E,"PUPIL_CEN_10")+SUMIFS('Pupils Insert Table'!J:J,'Pupils Insert Table'!D:D,$A$9,'Pupils Insert Table'!E:E,"PUPIL_CEN_11")) -> 0 | J42: =IF($A$9="","",H42-I42) -> 0 | K42: =IF($A$9="","",SUMIFS('Pupils Insert Table'!J:J,'Pupils Insert Table'!D:D,$A$9,'Pupils Insert Table'!E:E,"PUPIL_CEN_12")+SUMIFS('Pupils Insert Table'!J:J,'Pupils Insert Table'!D:D,$A$9,'Pupils Insert Table'!E:E,"PUPIL_CEN_13")) -> 0 | M42: =IF($A$9="","",K42-L42) -> 0 | N42: =IF($A$9="","",IF(AND(ABS(D42)<=10,ABS(G42)<=10,ABS(J42)<=10,ABS(M42)<=10),"PASS","FAIL")) -> PASS
A43: =IF($A$10="","",$A$10) -> MMP | B43: =IF($A$10="","",SUMIFS('Pupils Insert Table'!J:J,'Pupils Insert Table'!D:D,$A$10,'Pupils Insert Table'!E:E,"PUPIL_CEN_00")+SUMIFS('Pupils Insert Table'!J:J,'Pupils Insert Table'!D:D,$A$10,'Pupils Insert Table'!E:E,"PUPIL_CEN_01")+SUMIFS('Pupils Insert Table'!J:J,'Pupils Insert Table'!D:D,$A$10,'Pupils Insert Table'!E:E,"PUPIL_CEN_02")+SUMIFS('Pupils Insert Table'!J:J,'Pupils Insert Table'!D:D,$A$10,'Pupils Insert Table'!E:E,"PUPIL_CEN_03")+SUMIFS('Pupils Insert Table'!J:J,'Pupils Insert Table'!D:D,$A$10,'Pupils Insert Table'!E:E,"PUPIL_CEN_04")+SUMIFS('Pupils Insert Table'!J:J,'Pupils Insert Table'!D:D,$A$10,'Pupils Insert Table'!E:E,"PUPIL_CEN_05")+SUMIFS('Pupils Insert Table'!J:J,'Pupils Insert Table'!D:D,$A$10,'Pupils Insert Table'!E:E,"PUPIL_CEN_06")) -> 0 | D43: =IF($A$10="","",B43-C43) -> 0 | E43: =IF($A$10="","",SUMIFS('Pupils Insert Table'!J:J,'Pupils Insert Table'!D:D,$A$10,'Pupils Insert Table'!E:E,"PUPIL_CEN_07")+SUMIFS('Pupils Insert Table'!J:J,'Pupils Insert Table'!D:D,$A$10,'Pupils Insert Table'!E:E,"PUPIL_CEN_08")+SUMIFS('Pupils Insert Table'!J:J,'Pupils Insert Table'!D:D,$A$10,'Pupils Insert Table'!E:E,"PUPIL_CEN_09")) -> 0 | G43: =IF($A$10="","",E43-F43) -> 0 | H43: =IF($A$10="","",SUMIFS('Pupils Insert Table'!J:J,'Pupils Insert Table'!D:D,$A$10,'Pupils Insert Table'!E:E,"PUPIL_CEN_10")+SUMIFS('Pupils Insert Table'!J:J,'Pupils Insert Table'!D:D,$A$10,'Pupils Insert Table'!E:E,"PUPIL_CEN_11")) -> 0 | J43: =IF($A$10="","",H43-I43) -> 0 | K43: =IF($A$10="","",SUMIFS('Pupils Insert Table'!J:J,'Pupils Insert Table'!D:D,$A$10,'Pupils Insert Table'!E:E,"PUPIL_CEN_12")+SUMIFS('Pupils Insert Table'!J:J,'Pupils Insert Table'!D:D,$A$10,'Pupils Insert Table'!E:E,"PUPIL_CEN_13")) -> 0 | M43: =IF($A$10="","",K43-L43) -> 0 | N43: =IF($A$10="","",IF(AND(ABS(D43)<=10,ABS(G43)<=10,ABS(J43)<=10,ABS(M43)<=10),"PASS","FAIL")) -> PASS
A44: =IF($A$11="","",$A$11) -> NIN | B44: =IF($A$11="","",SUMIFS('Pupils Insert Table'!J:J,'Pupils Insert Table'!D:D,$A$11,'Pupils Insert Table'!E:E,"PUPIL_CEN_00")+SUMIFS('Pupils Insert Table'!J:J,'Pupils Insert Table'!D:D,$A$11,'Pupils Insert Table'!E:E,"PUPIL_CEN_01")+SUMIFS('Pupils Insert Table'!J:J,'Pupils Insert Table'!D:D,$A$11,'Pupils Insert Table'!E:E,"PUPIL_CEN_02")+SUMIFS('Pupils Insert Table'!J:J,'Pupils Insert Table'!D:D,$A$11,'Pupils Insert Table'!E:E,"PUPIL_CEN_03")+SUMIFS('Pupils Insert Table'!J:J,'Pupils Insert Table'!D:D,$A$11,'Pupils Insert Table'!E:E,"PUPIL_CEN_04")+SUMIFS('Pupils Insert Table'!J:J,'Pupils Insert Table'!D:D,$A$11,'Pupils Insert Table'!E:E,"PUPIL_CEN_05")+SUMIFS('Pupils Insert Table'!J:J,'Pupils Insert Table'!D:D,$A$11,'Pupils Insert Table'!E:E,"PUPIL_CEN_06")) -> 0 | D44: =IF($A$11="","",B44-C44) -> 0 | E44: =IF($A$11="","",SUMIFS('Pupils Insert Table'!J:J,'Pupils Insert Table'!D:D,$A$11,'Pupils Insert Table'!E:E,"PUPIL_CEN_07")+SUMIFS('Pupils Insert Table'!J:J,'Pupils Insert Table'!D:D,$A$11,'Pupils Insert Table'!E:E,"PUPIL_CEN_08")+SUMIFS('Pupils Insert Table'!J:J,'Pupils Insert Table'!D:D,$A$11,'Pupils Insert Table'!E:E,"PUPIL_CEN_09")) -> 0 | G44: =IF($A$11="","",E44-F44) -> 0 | H44: =IF($A$11="","",SUMIFS('Pupils Insert Table'!J:J,'Pupils Insert Table'!D:D,$A$11,'Pupils Insert Table'!E:E,"PUPIL_CEN_10")+SUMIFS('Pupils Insert Table'!J:J,'Pupils Insert Table'!D:D,$A$11,'Pupils Insert Table'!E:E,"PUPIL_CEN_11")) -> 0 | J44: =IF($A$11="","",H44-I44) -> 0 | K44: =IF($A$11="","",SUMIFS('Pupils Insert Table'!J:J,'Pupils Insert Table'!D:D,$A$11,'Pupils Insert Table'!E:E,"PUPIL_CEN_12")+SUMIFS('Pupils Insert Table'!J:J,'Pupils Insert Table'!D:D,$A$11,'Pupils Insert Table'!E:E,"PUPIL_CEN_13")) -> 0 | M44: =IF($A$11="","",K44-L44) -> 0 | N44: =IF($A$11="","",IF(AND(ABS(D44)<=10,ABS(G44)<=10,ABS(J44)<=10,ABS(M44)<=10),"PASS","FAIL")) -> PASS
A45: =IF($A$12="","",$A$12) -> SRA | B45: =IF($A$12="","",SUMIFS('Pupils Insert Table'!J:J,'Pupils Insert Table'!D:D,$A$12,'Pupils Insert Table'!E:E,"PUPIL_CEN_00")+SUMIFS('Pupils Insert Table'!J:J,'Pupils Insert Table'!D:D,$A$12,'Pupils Insert Table'!E:E,"PUPIL_CEN_01")+SUMIFS('Pupils Insert Table'!J:J,'Pupils Insert Table'!D:D,$A$12,'Pupils Insert Table'!E:E,"PUPIL_CEN_02")+SUMIFS('Pupils Insert Table'!J:J,'Pupils Insert Table'!D:D,$A$12,'Pupils Insert Table'!E:E,"PUPIL_CEN_03")+SUMIFS('Pupils Insert Table'!J:J,'Pupils Insert Table'!D:D,$A$12,'Pupils Insert Table'!E:E,"PUPIL_CEN_04")+SUMIFS('Pupils Insert Table'!J:J,'Pupils Insert Table'!D:D,$A$12,'Pupils Insert Table'!E:E,"PUPIL_CEN_05")+SUMIFS('Pupils Insert Table'!J:J,'Pupils Insert Table'!D:D,$A$12,'Pupils Insert Table'!E:E,"PUPIL_CEN_06")) -> 0 | D45: =IF($A$12="","",B45-C45) -> 0 | E45: =IF($A$12="","",SUMIFS('Pupils Insert Table'!J:J,'Pupils Insert Table'!D:D,$A$12,'Pupils Insert Table'!E:E,"PUPIL_CEN_07")+SUMIFS('Pupils Insert Table'!J:J,'Pupils Insert Table'!D:D,$A$12,'Pupils Insert Table'!E:E,"PUPIL_CEN_08")+SUMIFS('Pupils Insert Table'!J:J,'Pupils Insert Table'!D:D,$A$12,'Pupils Insert Table'!E:E,"PUPIL_CEN_09")) -> 0 | G45: =IF($A$12="","",E45-F45) -> 0 | H45: =IF($A$12="","",SUMIFS('Pupils Insert Table'!J:J,'Pupils Insert Table'!D:D,$A$12,'Pupils Insert Table'!E:E,"PUPIL_CEN_10")+SUMIFS('Pupils Insert Table'!J:J,'Pupils Insert Table'!D:D,$A$12,'Pupils Insert Table'!E:E,"PUPIL_CEN_11")) -> 0 | J45: =IF($A$12="","",H45-I45) -> 0 | K45: =IF($A$12="","",SUMIFS('Pupils Insert Table'!J:J,'Pupils Insert Table'!D:D,$A$12,'Pupils Insert Table'!E:E,"PUPIL_CEN_12")+SUMIFS('Pupils Insert Table'!J:J,'Pupils Insert Table'!D:D,$A$12,'Pupils Insert Table'!E:E,"PUPIL_CEN_13")) -> 0 | M45: =IF($A$12="","",K45-L45) -> 0 | N45: =IF($A$12="","",IF(AND(ABS(D45)<=10,ABS(G45)<=10,ABS(J45)<=10,ABS(M45)<=10),"PASS","FAIL")) -> PASS
A46: =IF($A$13="","",$A$13) -> BBS | B46: =IF($A$13="","",SUMIFS('Pupils Insert Table'!J:J,'Pupils Insert Table'!D:D,$A$13,'Pupils Insert Table'!E:E,"PUPIL_CEN_00")+SUMIFS('Pupils Insert Table'!J:J,'Pupils Insert Table'!D:D,$A$13,'Pupils Insert Table'!E:E,"PUPIL_CEN_01")+SUMIFS('Pupils Insert Table'!J:J,'Pupils Insert Table'!D:D,$A$13,'Pupils Insert Table'!E:E,"PUPIL_CEN_02")+SUMIFS('Pupils Insert Table'!J:J,'Pupils Insert Table'!D:D,$A$13,'Pupils Insert Table'!E:E,"PUPIL_CEN_03")+SUMIFS('Pupils Insert Table'!J:J,'Pupils Insert Table'!D:D,$A$13,'Pupils Insert Table'!E:E,"PUPIL_CEN_04")+SUMIFS('Pupils Insert Table'!J:J,'Pupils Insert Table'!D:D,$A$13,'Pupils Insert Table'!E:E,"PUPIL_CEN_05")+SUMIFS('Pupils Insert Table'!J:J,'Pupils Insert Table'!D:D,$A$13,'Pupils Insert Table'!E:E,"PUPIL_CEN_06")) -> 0 | D46: =IF($A$13="","",B46-C46) -> 0 | E46: =IF($A$13="","",SUMIFS('Pupils Insert Table'!J:J,'Pupils Insert Table'!D:D,$A$13,'Pupils Insert Table'!E:E,"PUPIL_CEN_07")+SUMIFS('Pupils Insert Table'!J:J,'Pupils Insert Table'!D:D,$A$13,'Pupils Insert Table'!E:E,"PUPIL_CEN_08")+SUMIFS('Pupils Insert Table'!J:J,'Pupils Insert Table'!D:D,$A$13,'Pupils Insert Table'!E:E,"PUPIL_CEN_09")) -> 0 | G46: =IF($A$13="","",E46-F46) -> 0 | H46: =IF($A$13="","",SUMIFS('Pupils Insert Table'!J:J,'Pupils Insert Table'!D:D,$A$13,'Pupils Insert Table'!E:E,"PUPIL_CEN_10")+SUMIFS('Pupils Insert Table'!J:J,'Pupils Insert Table'!D:D,$A$13,'Pupils Insert Table'!E:E,"PUPIL_CEN_11")) -> 0 | J46: =IF($A$13="","",H46-I46) -> 0 | K46: =IF($A$13="","",SUMIFS('Pupils Insert Table'!J:J,'Pupils Insert Table'!D:D,$A$13,'Pupils Insert Table'!E:E,"PUPIL_CEN_12")+SUMIFS('Pupils Insert Table'!J:J,'Pupils Insert Table'!D:D,$A$13,'Pupils Insert Table'!E:E,"PUPIL_CEN_13")) -> 0 | M46: =IF($A$13="","",K46-L46) -> 0 | N46: =IF($A$13="","",IF(AND(ABS(D46)<=10,ABS(G46)<=10,ABS(J46)<=10,ABS(M46)<=10),"PASS","FAIL")) -> PASS
A47: =IF($A$14="","",$A$14) -> HHS | B47: =IF($A$14="","",SUMIFS('Pupils Insert Table'!J:J,'Pupils Insert Table'!D:D,$A$14,'Pupils Insert Table'!E:E,"PUPIL_CEN_00")+SUMIFS('Pupils Insert Table'!J:J,'Pupils Insert Table'!D:D,$A$14,'Pupils Insert Table'!E:E,"PUPIL_CEN_01")+SUMIFS('Pupils Insert Table'!J:J,'Pupils Insert Table'!D:D,$A$14,'Pupils Insert Table'!E:E,"PUPIL_CEN_02")+SUMIFS('Pupils Insert Table'!J:J,'Pupils Insert Table'!D:D,$A$14,'Pupils Insert Table'!E:E,"PUPIL_CEN_03")+SUMIFS('Pupils Insert Table'!J:J,'Pupils Insert Table'!D:D,$A$14,'Pupils Insert Table'!E:E,"PUPIL_CEN_04")+SUMIFS('Pupils Insert Table'!J:J,'Pupils Insert Table'!D:D,$A$14,'Pupils Insert Table'!E:E,"PUPIL_CEN_05")+SUMIFS('Pupils Insert Table'!J:J,'Pupils Insert Table'!D:D,$A$14,'Pupils Insert Table'!E:E,"PUPIL_CEN_06")) -> 0 | D47: =IF($A$14="","",B47-C47) -> 0 | E47: =IF($A$14="","",SUMIFS('Pupils Insert Table'!J:J,'Pupils Insert Table'!D:D,$A$14,'Pupils Insert Table'!E:E,"PUPIL_CEN_07")+SUMIFS('Pupils Insert Table'!J:J,'Pupils Insert Table'!D:D,$A$14,'Pupils Insert Table'!E:E,"PUPIL_CEN_08")+SUMIFS('Pupils Insert Table'!J:J,'Pupils Insert Table'!D:D,$A$14,'Pupils Insert Table'!E:E,"PUPIL_CEN_09")) -> 0 | G47: =IF($A$14="","",E47-F47) -> 0 | H47: =IF($A$14="","",SUMIFS('Pupils Insert Table'!J:J,'Pupils Insert Table'!D:D,$A$14,'Pupils Insert Table'!E:E,"PUPIL_CEN_10")+SUMIFS('Pupils Insert Table'!J:J,'Pupils Insert Table'!D:D,$A$14,'Pupils Insert Table'!E:E,"PUPIL_CEN_11")) -> 0 | J47: =IF($A$14="","",H47-I47) -> 0 | K47: =IF($A$14="","",SUMIFS('Pupils Insert Table'!J:J,'Pupils Insert Table'!D:D,$A$14,'Pupils Insert Table'!E:E,"PUPIL_CEN_12")+SUMIFS('Pupils Insert Table'!J:J,'Pupils Insert Table'!D:D,$A$14,'Pupils Insert Table'!E:E,"PUPIL_CEN_13")) -> 0 | M47: =IF($A$14="","",K47-L47) -> 0 | N47: =IF($A$14="","",IF(AND(ABS(D47)<=10,ABS(G47)<=10,ABS(J47)<=10,ABS(M47)<=10),"PASS","FAIL")) -> PASS
A48: =IF($A$15="","",$A$15) -> RVS | B48: =IF($A$15="","",SUMIFS('Pupils Insert Table'!J:J,'Pupils Insert Table'!D:D,$A$15,'Pupils Insert Table'!E:E,"PUPIL_CEN_00")+SUMIFS('Pupils Insert Table'!J:J,'Pupils Insert Table'!D:D,$A$15,'Pupils Insert Table'!E:E,"PUPIL_CEN_01")+SUMIFS('Pupils Insert Table'!J:J,'Pupils Insert Table'!D:D,$A$15,'Pupils Insert Table'!E:E,"PUPIL_CEN_02")+SUMIFS('Pupils Insert Table'!J:J,'Pupils Insert Table'!D:D,$A$15,'Pupils Insert Table'!E:E,"PUPIL_CEN_03")+SUMIFS('Pupils Insert Table'!J:J,'Pupils Insert Table'!D:D,$A$15,'Pupils Insert Table'!E:E,"PUPIL_CEN_04")+SUMIFS('Pupils Insert Table'!J:J,'Pupils Insert Table'!D:D,$A$15,'Pupils Insert Table'!E:E,"PUPIL_CEN_05")+SUMIFS('Pupils Insert Table'!J:J,'Pupils Insert Table'!D:D,$A$15,'Pupils Insert Table'!E:E,"PUPIL_CEN_06")) -> 0 | D48: =IF($A$15="","",B48-C48) -> 0 | E48: =IF($A$15="","",SUMIFS('Pupils Insert Table'!J:J,'Pupils Insert Table'!D:D,$A$15,'Pupils Insert Table'!E:E,"PUPIL_CEN_07")+SUMIFS('Pupils Insert Table'!J:J,'Pupils Insert Table'!D:D,$A$15,'Pupils Insert Table'!E:E,"PUPIL_CEN_08")+SUMIFS('Pupils Insert Table'!J:J,'Pupils Insert Table'!D:D,$A$15,'Pupils Insert Table'!E:E,"PUPIL_CEN_09")) -> 0 | G48: =IF($A$15="","",E48-F48) -> 0 | H48: =IF($A$15="","",SUMIFS('Pupils Insert Table'!J:J,'Pupils Insert Table'!D:D,$A$15,'Pupils Insert Table'!E:E,"PUPIL_CEN_10")+SUMIFS('Pupils Insert Table'!J:J,'Pupils Insert Table'!D:D,$A$15,'Pupils Insert Table'!E:E,"PUPIL_CEN_11")) -> 0 | J48: =IF($A$15="","",H48-I48) -> 0 | K48: =IF($A$15="","",SUMIFS('Pupils Insert Table'!J:J,'Pupils Insert Table'!D:D,$A$15,'Pupils Insert Table'!E:E,"PUPIL_CEN_12")+SUMIFS('Pupils Insert Table'!J:J,'Pupils Insert Table'!D:D,$A$15,'Pupils Insert Table'!E:E,"PUPIL_CEN_13")) -> 0 | M48: =IF($A$15="","",K48-L48) -> 0 | N48: =IF($A$15="","",IF(AND(ABS(D48)<=10,ABS(G48)<=10,ABS(J48)<=10,ABS(M48)<=10),"PASS","FAIL")) -> PASS
A49: =IF($A$16="","",$A$16) -> CHS | B49: =IF($A$16="","",SUMIFS('Pupils Insert Table'!J:J,'Pupils Insert Table'!D:D,$A$16,'Pupils Insert Table'!E:E,"PUPIL_CEN_00")+SUMIFS('Pupils Insert Table'!J:J,'Pupils Insert Table'!D:D,$A$16,'Pupils Insert Table'!E:E,"PUPIL_CEN_01")+SUMIFS('Pupils Insert Table'!J:J,'Pupils Insert Table'!D:D,$A$16,'Pupils Insert Table'!E:E,"PUPIL_CEN_02")+SUMIFS('Pupils Insert Table'!J:J,'Pupils Insert Table'!D:D,$A$16,'Pupils Insert Table'!E:E,"PUPIL_CEN_03")+SUMIFS('Pupils Insert Table'!J:J,'Pupils Insert Table'!D:D,$A$16,'Pupils Insert Table'!E:E,"PUPIL_CEN_04")+SUMIFS('Pupils Insert Table'!J:J,'Pupils Insert Table'!D:D,$A$16,'Pupils Insert Table'!E:E,"PUPIL_CEN_05")+SUMIFS('Pupils Insert Table'!J:J,'Pupils Insert Table'!D:D,$A$16,'Pupils Insert Table'!E:E,"PUPIL_CEN_06")) -> 0 | D49: =IF($A$16="","",B49-C49) -> 0 | E49: =IF($A$16="","",SUMIFS('Pupils Insert Table'!J:J,'Pupils Insert Table'!D:D,$A$16,'Pupils Insert Table'!E:E,"PUPIL_CEN_07")+SUMIFS('Pupils Insert Table'!J:J,'Pupils Insert Table'!D:D,$A$16,'Pupils Insert Table'!E:E,"PUPIL_CEN_08")+SUMIFS('Pupils Insert Table'!J:J,'Pupils Insert Table'!D:D,$A$16,'Pupils Insert Table'!E:E,"PUPIL_CEN_09")) -> 0 | G49: =IF($A$16="","",E49-F49) -> 0 | H49: =IF($A$16="","",SUMIFS('Pupils Insert Table'!J:J,'Pupils Insert Table'!D:D,$A$16,'Pupils Insert Table'!E:E,"PUPIL_CEN_10")+SUMIFS('Pupils Insert Table'!J:J,'Pupils Insert Table'!D:D,$A$16,'Pupils Insert Table'!E:E,"PUPIL_CEN_11")) -> 0 | J49: =IF($A$16="","",H49-I49) -> 0 | K49: =IF($A$16="","",SUMIFS('Pupils Insert Table'!J:J,'Pupils Insert Table'!D:D,$A$16,'Pupils Insert Table'!E:E,"PUPIL_CEN_12")+SUMIFS('Pupils Insert Table'!J:J,'Pupils Insert Table'!D:D,$A$16,'Pupils Insert Table'!E:E,"PUPIL_CEN_13")) -> 0 | M49: =IF($A$16="","",K49-L49) -> 0 | N49: =IF($A$16="","",IF(AND(ABS(D49)<=10,ABS(G49)<=10,ABS(J49)<=10,ABS(M49)<=10),"PASS","FAIL")) -> PASS
A50: =IF($A$17="","",$A$17) | B50: =IF($A$17="","",SUMIFS('Pupils Insert Table'!J:J,'Pupils Insert Table'!D:D,$A$17,'Pupils Insert Table'!E:E,"PUPIL_CEN_00")+SUMIFS('Pupils Insert Table'!J:J,'Pupils Insert Table'!D:D,$A$17,'Pupils Insert Table'!E:E,"PUPIL_CEN_01")+SUMIFS('Pupils Insert Table'!J:J,'Pupils Insert Table'!D:D,$A$17,'Pupils Insert Table'!E:E,"PUPIL_CEN_02")+SUMIFS('Pupils Insert Table'!J:J,'Pupils Insert Table'!D:D,$A$17,'Pupils Insert Table'!E:E,"PUPIL_CEN_03")+SUMIFS('Pupils Insert Table'!J:J,'Pupils Insert Table'!D:D,$A$17,'Pupils Insert Table'!E:E,"PUPIL_CEN_04")+SUMIFS('Pupils Insert Table'!J:J,'Pupils Insert Table'!D:D,$A$17,'Pupils Insert Table'!E:E,"PUPIL_CEN_05")+SUMIFS('Pupils Insert Table'!J:J,'Pupils Insert Table'!D:D,$A$17,'Pupils Insert Table'!E:E,"PUPIL_CEN_06")) | D50: =IF($A$17="","",B50-C50) | E50: =IF($A$17="","",SUMIFS('Pupils Insert Table'!J:J,'Pupils Insert Table'!D:D,$A$17,'Pupils Insert Table'!E:E,"PUPIL_CEN_07")+SUMIFS('Pupils Insert Table'!J:J,'Pupils Insert Table'!D:D,$A$17,'Pupils Insert Table'!E:E,"PUPIL_CEN_08")+SUMIFS('Pupils Insert Table'!J:J,'Pupils Insert Table'!D:D,$A$17,'Pupils Insert Table'!E:E,"PUPIL_CEN_09")) | G50: =IF($A$17="","",E50-F50) | H50: =IF($A$17="","",SUMIFS('Pupils Insert Table'!J:J,'Pupils Insert Table'!D:D,$A$17,'Pupils Insert Table'!E:E,"PUPIL_CEN_10")+SUMIFS('Pupils Insert Table'!J:J,'Pupils Insert Table'!D:D,$A$17,'Pupils Insert Table'!E:E,"PUPIL_CEN_11")) | J50: =IF($A$17="","",H50-I50) | K50: =IF($A$17="","",SUMIFS('Pupils Insert Table'!J:J,'Pupils Insert Table'!D:D,$A$17,'Pupils Insert Table'!E:E,"PUPIL_CEN_12")+SUMIFS('Pupils Insert Table'!J:J,'Pupils Insert Table'!D:D,$A$17,'Pupils Insert Table'!E:E,"PUPIL_CEN_13")) | M50: =IF($A$17="","",K50-L50) | N50: =IF($A$17="","",IF(AND(ABS(D50)<=10,ABS(G50)<=10,ABS(J50)<=10,ABS(M50)<=10),"PASS","FAIL"))
A51: =IF($A$18="","",$A$18) | B51: =IF($A$18="","",SUMIFS('Pupils Insert Table'!J:J,'Pupils Insert Table'!D:D,$A$18,'Pupils Insert Table'!E:E,"PUPIL_CEN_00")+SUMIFS('Pupils Insert Table'!J:J,'Pupils Insert Table'!D:D,$A$18,'Pupils Insert Table'!E:E,"PUPIL_CEN_01")+SUMIFS('Pupils Insert Table'!J:J,'Pupils Insert Table'!D:D,$A$18,'Pupils Insert Table'!E:E,"PUPIL_CEN_02")+SUMIFS('Pupils Insert Table'!J:J,'Pupils Insert Table'!D:D,$A$18,'Pupils Insert Table'!E:E,"PUPIL_CEN_03")+SUMIFS('Pupils Insert Table'!J:J,'Pupils Insert Table'!D:D,$A$18,'Pupils Insert Table'!E:E,"PUPIL_CEN_04")+SUMIFS('Pupils Insert Table'!J:J,'Pupils Insert Table'!D:D,$A$18,'Pupils Insert Table'!E:E,"PUPIL_CEN_05")+SUMIFS('Pupils Insert Table'!J:J,'Pupils Insert Table'!D:D,$A$18,'Pupils Insert Table'!E:E,"PUPIL_CEN_06")) | D51: =IF($A$18="","",B51-C51) | E51: =IF($A$18="","",SUMIFS('Pupils Insert Table'!J:J,'Pupils Insert Table'!D:D,$A$18,'Pupils Insert Table'!E:E,"PUPIL_CEN_07")+SUMIFS('Pupils Insert Table'!J:J,'Pupils Insert Table'!D:D,$A$18,'Pupils Insert Table'!E:E,"PUPIL_CEN_08")+SUMIFS('Pupils Insert Table'!J:J,'Pupils Insert Table'!D:D,$A$18,'Pupils Insert Table'!E:E,"PUPIL_CEN_09")) | G51: =IF($A$18="","",E51-F51) | H51: =IF($A$18="","",SUMIFS('Pupils Insert Table'!J:J,'Pupils Insert Table'!D:D,$A$18,'Pupils Insert Table'!E:E,"PUPIL_CEN_10")+SUMIFS('Pupils Insert Table'!J:J,'Pupils Insert Table'!D:D,$A$18,'Pupils Insert Table'!E:E,"PUPIL_CEN_11")) | J51: =IF($A$18="","",H51-I51) | K51: =IF($A$18="","",SUMIFS('Pupils Insert Table'!J:J,'Pupils Insert Table'!D:D,$A$18,'Pupils Insert Table'!E:E,"PUPIL_CEN_12")+SUMIFS('Pupils Insert Table'!J:J,'Pupils Insert Table'!D:D,$A$18,'Pupils Insert Table'!E:E,"PUPIL_CEN_13")) | M51: =IF($A$18="","",K51-L51) | N51: =IF($A$18="","",IF(AND(ABS(D51)<=10,ABS(G51)<=10,ABS(J51)<=10,ABS(M51)<=10),"PASS","FAIL"))
A52: =IF($A$19="","",$A$19) | B52: =IF($A$19="","",SUMIFS('Pupils Insert Table'!J:J,'Pupils Insert Table'!D:D,$A$19,'Pupils Insert Table'!E:E,"PUPIL_CEN_00")+SUMIFS('Pupils Insert Table'!J:J,'Pupils Insert Table'!D:D,$A$19,'Pupils Insert Table'!E:E,"PUPIL_CEN_01")+SUMIFS('Pupils Insert Table'!J:J,'Pupils Insert Table'!D:D,$A$19,'Pupils Insert Table'!E:E,"PUPIL_CEN_02")+SUMIFS('Pupils Insert Table'!J:J,'Pupils Insert Table'!D:D,$A$19,'Pupils Insert Table'!E:E,"PUPIL_CEN_03")+SUMIFS('Pupils Insert Table'!J:J,'Pupils Insert Table'!D:D,$A$19,'Pupils Insert Table'!E:E,"PUPIL_CEN_04")+SUMIFS('Pupils Insert Table'!J:J,'Pupils Insert Table'!D:D,$A$19,'Pupils Insert Table'!E:E,"PUPIL_CEN_05")+SUMIFS('Pupils Insert Table'!J:J,'Pupils Insert Table'!D:D,$A$19,'Pupils Insert Table'!E:E,"PUPIL_CEN_06")) | D52: =IF($A$19="","",B52-C52) | E52: =IF($A$19="","",SUMIFS('Pupils Insert Table'!J:J,'Pupils Insert Table'!D:D,$A$19,'Pupils Insert Table'!E:E,"PUPIL_CEN_07")+SUMIFS('Pupils Insert Table'!J:J,'Pupils Insert Table'!D:D,$A$19,'Pupils Insert Table'!E:E,"PUPIL_CEN_08")+SUMIFS('Pupils Insert Table'!J:J,'Pupils Insert Table'!D:D,$A$19,'Pupils Insert Table'!E:E,"PUPIL_CEN_09")) | G52: =IF($A$19="","",E52-F52) | H52: =IF($A$19="","",SUMIFS('Pupils Insert Table'!J:J,'Pupils Insert Table'!D:D,$A$19,'Pupils Insert Table'!E:E,"PUPIL_CEN_10")+SUMIFS('Pupils Insert Table'!J:J,'Pupils Insert Table'!D:D,$A$19,'Pupils Insert Table'!E:E,"PUPIL_CEN_11")) | J52: =IF($A$19="","",H52-I52) | K52: =IF($A$19="","",SUMIFS('Pupils Insert Table'!J:J,'Pupils Insert Table'!D:D,$A$19,'Pupils Insert Table'!E:E,"PUPIL_CEN_12")+SUMIFS('Pupils Insert Table'!J:J,'Pupils Insert Table'!D:D,$A$19,'Pupils Insert Table'!E:E,"PUPIL_CEN_13")) | M52: =IF($A$19="","",K52-L52) | N52: =IF($A$19="","",IF(AND(ABS(D52)<=10,ABS(G52)<=10,ABS(J52)<=10,ABS(M52)<=10),"PASS","FAIL"))
A53: =IF($A$20="","",$A$20) | B53: =IF($A$20="","",SUMIFS('Pupils Insert Table'!J:J,'Pupils Insert Table'!D:D,$A$20,'Pupils Insert Table'!E:E,"PUPIL_CEN_00")+SUMIFS('Pupils Insert Table'!J:J,'Pupils Insert Table'!D:D,$A$20,'Pupils Insert Table'!E:E,"PUPIL_CEN_01")+SUMIFS('Pupils Insert Table'!J:J,'Pupils Insert Table'!D:D,$A$20,'Pupils Insert Table'!E:E,"PUPIL_CEN_02")+SUMIFS('Pupils Insert Table'!J:J,'Pupils Insert Table'!D:D,$A$20,'Pupils Insert Table'!E:E,"PUPIL_CEN_03")+SUMIFS('Pupils Insert Table'!J:J,'Pupils Insert Table'!D:D,$A$20,'Pupils Insert Table'!E:E,"PUPIL_CEN_04")+SUMIFS('Pupils Insert Table'!J:J,'Pupils Insert Table'!D:D,$A$20,'Pupils Insert Table'!E:E,"PUPIL_CEN_05")+SUMIFS('Pupils Insert Table'!J:J,'Pupils Insert Table'!D:D,$A$20,'Pupils Insert Table'!E:E,"PUPIL_CEN_06")) | D53: =IF($A$20="","",B53-C53) | E53: =IF($A$20="","",SUMIFS('Pupils Insert Table'!J:J,'Pupils Insert Table'!D:D,$A$20,'Pupils Insert Table'!E:E,"PUPIL_CEN_07")+SUMIFS('Pupils Insert Table'!J:J,'Pupils Insert Table'!D:D,$A$20,'Pupils Insert Table'!E:E,"PUPIL_CEN_08")+SUMIFS('Pupils Insert Table'!J:J,'Pupils Insert Table'!D:D,$A$20,'Pupils Insert Table'!E:E,"PUPIL_CEN_09")) | G53: =IF($A$20="","",E53-F53) | H53: =IF($A$20="","",SUMIFS('Pupils Insert Table'!J:J,'Pupils Insert Table'!D:D,$A$20,'Pupils Insert Table'!E:E,"PUPIL_CEN_10")+SUMIFS('Pupils Insert Table'!J:J,'Pupils Insert Table'!D:D,$A$20,'Pupils Insert Table'!E:E,"PUPIL_CEN_11")) | J53: =IF($A$20="","",H53-I53) | K53: =IF($A$20="","",SUMIFS('Pupils Insert Table'!J:J,'Pupils Insert Table'!D:D,$A$20,'Pupils Insert Table'!E:E,"PUPIL_CEN_12")+SUMIFS('Pupils Insert Table'!J:J,'Pupils Insert Table'!D:D,$A$20,'Pupils Insert Table'!E:E,"PUPIL_CEN_13")) | M53: =IF($A$20="","",K53-L53) | N53: =IF($A$20="","",IF(AND(ABS(D53)<=10,ABS(G53)<=10,ABS(J53)<=10,ABS(M53)<=10),"PASS","FAIL"))
A54: =IF($A$21="","",$A$21) | B54: =IF($A$21="","",SUMIFS('Pupils Insert Table'!J:J,'Pupils Insert Table'!D:D,$A$21,'Pupils Insert Table'!E:E,"PUPIL_CEN_00")+SUMIFS('Pupils Insert Table'!J:J,'Pupils Insert Table'!D:D,$A$21,'Pupils Insert Table'!E:E,"PUPIL_CEN_01")+SUMIFS('Pupils Insert Table'!J:J,'Pupils Insert Table'!D:D,$A$21,'Pupils Insert Table'!E:E,"PUPIL_CEN_02")+SUMIFS('Pupils Insert Table'!J:J,'Pupils Insert Table'!D:D,$A$21,'Pupils Insert Table'!E:E,"PUPIL_CEN_03")+SUMIFS('Pupils Insert Table'!J:J,'Pupils Insert Table'!D:D,$A$21,'Pupils Insert Table'!E:E,"PUPIL_CEN_04")+SUMIFS('Pupils Insert Table'!J:J,'Pupils Insert Table'!D:D,$A$21,'Pupils Insert Table'!E:E,"PUPIL_CEN_05")+SUMIFS('Pupils Insert Table'!J:J,'Pupils Insert Table'!D:D,$A$21,'Pupils Insert Table'!E:E,"PUPIL_CEN_06")) | D54: =IF($A$21="","",B54-C54) | E54: =IF($A$21="","",SUMIFS('Pupils Insert Table'!J:J,'Pupils Insert Table'!D:D,$A$21,'Pupils Insert Table'!E:E,"PUPIL_CEN_07")+SUMIFS('Pupils Insert Table'!J:J,'Pupils Insert Table'!D:D,$A$21,'Pupils Insert Table'!E:E,"PUPIL_CEN_08")+SUMIFS('Pupils Insert Table'!J:J,'Pupils Insert Table'!D:D,$A$21,'Pupils Insert Table'!E:E,"PUPIL_CEN_09")) | G54: =IF($A$21="","",E54-F54) | H54: =IF($A$21="","",SUMIFS('Pupils Insert Table'!J:J,'Pupils Insert Table'!D:D,$A$21,'Pupils Insert Table'!E:E,"PUPIL_CEN_10")+SUMIFS('Pupils Insert Table'!J:J,'Pupils Insert Table'!D:D,$A$21,'Pupils Insert Table'!E:E,"PUPIL_CEN_11")) | J54: =IF($A$21="","",H54-I54) | K54: =IF($A$21="","",SUMIFS('Pupils Insert Table'!J:J,'Pupils Insert Table'!D:D,$A$21,'Pupils Insert Table'!E:E,"PUPIL_CEN_12")+SUMIFS('Pupils Insert Table'!J:J,'Pupils Insert Table'!D:D,$A$21,'Pupils Insert Table'!E:E,"PUPIL_CEN_13")) | M54: =IF($A$21="","",K54-L54) | N54: =IF($A$21="","",IF(AND(ABS(D54)<=10,ABS(G54)<=10,ABS(J54)<=10,ABS(M54)<=10),"PASS","FAIL"))
A55: =IF($A$22="","",$A$22) | B55: =IF($A$22="","",SUMIFS('Pupils Insert Table'!J:J,'Pupils Insert Table'!D:D,$A$22,'Pupils Insert Table'!E:E,"PUPIL_CEN_00")+SUMIFS('Pupils Insert Table'!J:J,'Pupils Insert Table'!D:D,$A$22,'Pupils Insert Table'!E:E,"PUPIL_CEN_01")+SUMIFS('Pupils Insert Table'!J:J,'Pupils Insert Table'!D:D,$A$22,'Pupils Insert Table'!E:E,"PUPIL_CEN_02")+SUMIFS('Pupils Insert Table'!J:J,'Pupils Insert Table'!D:D,$A$22,'Pupils Insert Table'!E:E,"PUPIL_CEN_03")+SUMIFS('Pupils Insert Table'!J:J,'Pupils Insert Table'!D:D,$A$22,'Pupils Insert Table'!E:E,"PUPIL_CEN_04")+SUMIFS('Pupils Insert Table'!J:J,'Pupils Insert Table'!D:D,$A$22,'Pupils Insert Table'!E:E,"PUPIL_CEN_05")+SUMIFS('Pupils Insert Table'!J:J,'Pupils Insert Table'!D:D,$A$22,'Pupils Insert Table'!E:E,"PUPIL_CEN_06")) | D55: =IF($A$22="","",B55-C55) | E55: =IF($A$22="","",SUMIFS('Pupils Insert Table'!J:J,'Pupils Insert Table'!D:D,$A$22,'Pupils Insert Table'!E:E,"PUPIL_CEN_07")+SUMIFS('Pupils Insert Table'!J:J,'Pupils Insert Table'!D:D,$A$22,'Pupils Insert Table'!E:E,"PUPIL_CEN_08")+SUMIFS('Pupils Insert Table'!J:J,'Pupils Insert Table'!D:D,$A$22,'Pupils Insert Table'!E:E,"PUPIL_CEN_09")) | G55: =IF($A$22="","",E55-F55) | H55: =IF($A$22="","",SUMIFS('Pupils Insert Table'!J:J,'Pupils Insert Table'!D:D,$A$22,'Pupils Insert Table'!E:E,"PUPIL_CEN_10")+SUMIFS('Pupils Insert Table'!J:J,'Pupils Insert Table'!D:D,$A$22,'Pupils Insert Table'!E:E,"PUPIL_CEN_11")) | J55: =IF($A$22="","",H55-I55) | K55: =IF($A$22="","",SUMIFS('Pupils Insert Table'!J:J,'Pupils Insert Table'!D:D,$A$22,'Pupils Insert Table'!E:E,"PUPIL_CEN_12")+SUMIFS('Pupils Insert Table'!J:J,'Pupils Insert Table'!D:D,$A$22,'Pupils Insert Table'!E:E,"PUPIL_CEN_13")) | M55: =IF($A$22="","",K55-L55) | N55: =IF($A$22="","",IF(AND(ABS(D55)<=10,ABS(G55)<=10,ABS(J55)<=10,ABS(M55)<=10),"PASS","FAIL"))
A56: =IF($A$23="","",$A$23) | B56: =IF($A$23="","",SUMIFS('Pupils Insert Table'!J:J,'Pupils Insert Table'!D:D,$A$23,'Pupils Insert Table'!E:E,"PUPIL_CEN_00")+SUMIFS('Pupils Insert Table'!J:J,'Pupils Insert Table'!D:D,$A$23,'Pupils Insert Table'!E:E,"PUPIL_CEN_01")+SUMIFS('Pupils Insert Table'!J:J,'Pupils Insert Table'!D:D,$A$23,'Pupils Insert Table'!E:E,"PUPIL_CEN_02")+SUMIFS('Pupils Insert Table'!J:J,'Pupils Insert Table'!D:D,$A$23,'Pupils Insert Table'!E:E,"PUPIL_CEN_03")+SUMIFS('Pupils Insert Table'!J:J,'Pupils Insert Table'!D:D,$A$23,'Pupils Insert Table'!E:E,"PUPIL_CEN_04")+SUMIFS('Pupils Insert Table'!J:J,'Pupils Insert Table'!D:D,$A$23,'Pupils Insert Table'!E:E,"PUPIL_CEN_05")+SUMIFS('Pupils Insert Table'!J:J,'Pupils Insert Table'!D:D,$A$23,'Pupils Insert Table'!E:E,"PUPIL_CEN_06")) | D56: =IF($A$23="","",B56-C56) | E56: =IF($A$23="","",SUMIFS('Pupils Insert Table'!J:J,'Pupils Insert Table'!D:D,$A$23,'Pupils Insert Table'!E:E,"PUPIL_CEN_07")+SUMIFS('Pupils Insert Table'!J:J,'Pupils Insert Table'!D:D,$A$23,'Pupils Insert Table'!E:E,"PUPIL_CEN_08")+SUMIFS('Pupils Insert Table'!J:J,'Pupils Insert Table'!D:D,$A$23,'Pupils Insert Table'!E:E,"PUPIL_CEN_09")) | G56: =IF($A$23="","",E56-F56) | H56: =IF($A$23="","",SUMIFS('Pupils Insert Table'!J:J,'Pupils Insert Table'!D:D,$A$23,'Pupils Insert Table'!E:E,"PUPIL_CEN_10")+SUMIFS('Pupils Insert Table'!J:J,'Pupils Insert Table'!D:D,$A$23,'Pupils Insert Table'!E:E,"PUPIL_CEN_11")) | J56: =IF($A$23="","",H56-I56) | K56: =IF($A$23="","",SUMIFS('Pupils Insert Table'!J:J,'Pupils Insert Table'!D:D,$A$23,'Pupils Insert Table'!E:E,"PUPIL_CEN_12")+SUMIFS('Pupils Insert Table'!J:J,'Pupils Insert Table'!D:D,$A$23,'Pupils Insert Table'!E:E,"PUPIL_CEN_13")) | M56: =IF($A$23="","",K56-L56) | N56: =IF($A$23="","",IF(AND(ABS(D56)<=10,ABS(G56)<=10,ABS(J56)<=10,ABS(M56)<=10),"PASS","FAIL"))
A57: =IF($A$24="","",$A$24) | B57: =IF($A$24="","",SUMIFS('Pupils Insert Table'!J:J,'Pupils Insert Table'!D:D,$A$24,'Pupils Insert Table'!E:E,"PUPIL_CEN_00")+SUMIFS('Pupils Insert Table'!J:J,'Pupils Insert Table'!D:D,$A$24,'Pupils Insert Table'!E:E,"PUPIL_CEN_01")+SUMIFS('Pupils Insert Table'!J:J,'Pupils Insert Table'!D:D,$A$24,'Pupils Insert Table'!E:E,"PUPIL_CEN_02")+SUMIFS('Pupils Insert Table'!J:J,'Pupils Insert Table'!D:D,$A$24,'Pupils Insert Table'!E:E,"PUPIL_CEN_03")+SUMIFS('Pupils Insert Table'!J:J,'Pupils Insert Table'!D:D,$A$24,'Pupils Insert Table'!E:E,"PUPIL_CEN_04")+SUMIFS('Pupils Insert Table'!J:J,'Pupils Insert Table'!D:D,$A$24,'Pupils Insert Table'!E:E,"PUPIL_CEN_05")+SUMIFS('Pupils Insert Table'!J:J,'Pupils Insert Table'!D:D,$A$24,'Pupils Insert Table'!E:E,"PUPIL_CEN_06")) | D57: =IF($A$24="","",B57-C57) | E57: =IF($A$24="","",SUMIFS('Pupils Insert Table'!J:J,'Pupils Insert Table'!D:D,$A$24,'Pupils Insert Table'!E:E,"PUPIL_CEN_07")+SUMIFS('Pupils Insert Table'!J:J,'Pupils Insert Table'!D:D,$A$24,'Pupils Insert Table'!E:E,"PUPIL_CEN_08")+SUMIFS('Pupils Insert Table'!J:J,'Pupils Insert Table'!D:D,$A$24,'Pupils Insert Table'!E:E,"PUPIL_CEN_09")) | G57: =IF($A$24="","",E57-F57) | H57: =IF($A$24="","",SUMIFS('Pupils Insert Table'!J:J,'Pupils Insert Table'!D:D,$A$24,'Pupils Insert Table'!E:E,"PUPIL_CEN_10")+SUMIFS('Pupils Insert Table'!J:J,'Pupils Insert Table'!D:D,$A$24,'Pupils Insert Table'!E:E,"PUPIL_CEN_11")) | J57: =IF($A$24="","",H57-I57) | K57: =IF($A$24="","",SUMIFS('Pupils Insert Table'!J:J,'Pupils Insert Table'!D:D,$A$24,'Pupils Insert Table'!E:E,"PUPIL_CEN_12")+SUMIFS('Pupils Insert Table'!J:J,'Pupils Insert Table'!D:D,$A$24,'Pupils Insert Table'!E:E,"PUPIL_CEN_13")) | M57: =IF($A$24="","",K57-L57) | N57: =IF($A$24="","",IF(AND(ABS(D57)<=10,ABS(G57)<=10,ABS(J57)<=10,ABS(M57)<=10),"PASS","FAIL"))
A58: =IF($A$25="","",$A$25) | B58: =IF($A$25="","",SUMIFS('Pupils Insert Table'!J:J,'Pupils Insert Table'!D:D,$A$25,'Pupils Insert Table'!E:E,"PUPIL_CEN_00")+SUMIFS('Pupils Insert Table'!J:J,'Pupils Insert Table'!D:D,$A$25,'Pupils Insert Table'!E:E,"PUPIL_CEN_01")+SUMIFS('Pupils Insert Table'!J:J,'Pupils Insert Table'!D:D,$A$25,'Pupils Insert Table'!E:E,"PUPIL_CEN_02")+SUMIFS('Pupils Insert Table'!J:J,'Pupils Insert Table'!D:D,$A$25,'Pupils Insert Table'!E:E,"PUPIL_CEN_03")+SUMIFS('Pupils Insert Table'!J:J,'Pupils Insert Table'!D:D,$A$25,'Pupils Insert Table'!E:E,"PUPIL_CEN_04")+SUMIFS('Pupils Insert Table'!J:J,'Pupils Insert Table'!D:D,$A$25,'Pupils Insert Table'!E:E,"PUPIL_CEN_05")+SUMIFS('Pupils Insert Table'!J:J,'Pupils Insert Table'!D:D,$A$25,'Pupils Insert Table'!E:E,"PUPIL_CEN_06")) | D58: =IF($A$25="","",B58-C58) | E58: =IF($A$25="","",SUMIFS('Pupils Insert Table'!J:J,'Pupils Insert Table'!D:D,$A$25,'Pupils Insert Table'!E:E,"PUPIL_CEN_07")+SUMIFS('Pupils Insert Table'!J:J,'Pupils Insert Table'!D:D,$A$25,'Pupils Insert Table'!E:E,"PUPIL_CEN_08")+SUMIFS('Pupils Insert Table'!J:J,'Pupils Insert Table'!D:D,$A$25,'Pupils Insert Table'!E:E,"PUPIL_CEN_09")) | G58: =IF($A$25="","",E58-F58) | H58: =IF($A$25="","",SUMIFS('Pupils Insert Table'!J:J,'Pupils Insert Table'!D:D,$A$25,'Pupils Insert Table'!E:E,"PUPIL_CEN_10")+SUMIFS('Pupils Insert Table'!J:J,'Pupils Insert Table'!D:D,$A$25,'Pupils Insert Table'!E:E,"PUPIL_CEN_11")) | J58: =IF($A$25="","",H58-I58) | K58: =IF($A$25="","",SUMIFS('Pupils Insert Table'!J:J,'Pupils Insert Table'!D:D,$A$25,'Pupils Insert Table'!E:E,"PUPIL_CEN_12")+SUMIFS('Pupils Insert Table'!J:J,'Pupils Insert Table'!D:D,$A$25,'Pupils Insert Table'!E:E,"PUPIL_CEN_13")) | M58: =IF($A$25="","",K58-L58) | N58: =IF($A$25="","",IF(AND(ABS(D58)<=10,ABS(G58)<=10,ABS(J58)<=10,ABS(M58)<=10),"PASS","FAIL"))
A59: =IF($A$26="","",$A$26) | B59: =IF($A$26="","",SUMIFS('Pupils Insert Table'!J:J,'Pupils Insert Table'!D:D,$A$26,'Pupils Insert Table'!E:E,"PUPIL_CEN_00")+SUMIFS('Pupils Insert Table'!J:J,'Pupils Insert Table'!D:D,$A$26,'Pupils Insert Table'!E:E,"PUPIL_CEN_01")+SUMIFS('Pupils Insert Table'!J:J,'Pupils Insert Table'!D:D,$A$26,'Pupils Insert Table'!E:E,"PUPIL_CEN_02")+SUMIFS('Pupils Insert Table'!J:J,'Pupils Insert Table'!D:D,$A$26,'Pupils Insert Table'!E:E,"PUPIL_CEN_03")+SUMIFS('Pupils Insert Table'!J:J,'Pupils Insert Table'!D:D,$A$26,'Pupils Insert Table'!E:E,"PUPIL_CEN_04")+SUMIFS('Pupils Insert Table'!J:J,'Pupils Insert Table'!D:D,$A$26,'Pupils Insert Table'!E:E,"PUPIL_CEN_05")+SUMIFS('Pupils Insert Table'!J:J,'Pupils Insert Table'!D:D,$A$26,'Pupils Insert Table'!E:E,"PUPIL_CEN_06")) | D59: =IF($A$26="","",B59-C59) | E59: =IF($A$26="","",SUMIFS('Pupils Insert Table'!J:J,'Pupils Insert Table'!D:D,$A$26,'Pupils Insert Table'!E:E,"PUPIL_CEN_07")+SUMIFS('Pupils Insert Table'!J:J,'Pupils Insert Table'!D:D,$A$26,'Pupils Insert Table'!E:E,"PUPIL_CEN_08")+SUMIFS('Pupils Insert Table'!J:J,'Pupils Insert Table'!D:D,$A$26,'Pupils Insert Table'!E:E,"PUPIL_CEN_09")) | G59: =IF($A$26="","",E59-F59) | H59: =IF($A$26="","",SUMIFS('Pupils Insert Table'!J:J,'Pupils Insert Table'!D:D,$A$26,'Pupils Insert Table'!E:E,"PUPIL_CEN_10")+SUMIFS('Pupils Insert Table'!J:J,'Pupils Insert Table'!D:D,$A$26,'Pupils Insert Table'!E:E,"PUPIL_CEN_11")) | J59: =IF($A$26="","",H59-I59) | K59: =IF($A$26="","",SUMIFS('Pupils Insert Table'!J:J,'Pupils Insert Table'!D:D,$A$26,'Pupils Insert Table'!E:E,"PUPIL_CEN_12")+SUMIFS('Pupils Insert Table'!J:J,'Pupils Insert Table'!D:D,$A$26,'Pupils Insert Table'!E:E,"PUPIL_CEN_13")) | M59: =IF($A$26="","",K59-L59) | N59: =IF($A$26="","",IF(AND(ABS(D59)<=10,ABS(G59)<=10,ABS(J59)<=10,ABS(M59)<=10),"PASS","FAIL"))
A62: 2. PUPIL TOTALS BY SECTION (vs Customer Document Totals)
A64: School | B64: Section | C64: 24/25 Calc | D64: 25/26 Calc | E64: 26/27 Calc | F64: 24/25 Cust | G64: 25/26 Cust | H64: 26/27 Cust | I64: 24/25 Var | J64: 25/26 Var | K64: 26/27 Var | L64: Status
A65: =IF($A$7="","",$A$7) -> TLT | B65: =IF($A$7="","","Census") -> Census | C65: =IF($A$7="","",SUMIFS('Pupils Insert Table'!J:J,'Pupils Insert Table'!D:D,$A$7,'Pupils Insert Table'!E:E,"PUPIL_CEN*")) -> 0 | D65: =IF($A$7="","",SUMIFS('Pupils Insert Table'!K:K,'Pupils Insert Table'!D:D,$A$7,'Pupils Insert Table'!E:E,"PUPIL_CEN*")) -> 0 | E65: =IF($A$7="","",SUMIFS('Pupils Insert Table'!L:L,'Pupils Insert Table'!D:D,$A$7,'Pupils Insert Table'!E:E,"PUPIL_CEN*")) -> 0 | I65: =IF($A$7="","",C65-F65) -> 0 | J65: =IF($A$7="","",D65-G65) -> 0 | K65: =IF($A$7="","",E65-H65) -> 0 | L65: =IF($A$7="","",IF(AND(ABS(I65)<=10,ABS(J65)<=10,ABS(K65)<=10),"PASS","FAIL")) -> PASS
B66: =IF($A$7="","","Spring") -> Spring | C66: =IF($A$7="","",SUMIFS('Pupils Insert Table'!J:J,'Pupils Insert Table'!D:D,$A$7,'Pupils Insert Table'!E:E,"PUPIL_SPRING*")) -> 0 | D66: =IF($A$7="","",SUMIFS('Pupils Insert Table'!K:K,'Pupils Insert Table'!D:D,$A$7,'Pupils Insert Table'!E:E,"PUPIL_SPRING*")) -> 0 | E66: =IF($A$7="","",SUMIFS('Pupils Insert Table'!L:L,'Pupils Insert Table'!D:D,$A$7,'Pupils Insert Table'!E:E,"PUPIL_SPRING*")) -> 0 | I66: =IF($A$7="","",C66-F66) -> 0 | J66: =IF($A$7="","",D66-G66) -> 0 | K66: =IF($A$7="","",E66-H66) -> 0 | L66: =IF($A$7="","",IF(AND(ABS(I66)<=10,ABS(J66)<=10,ABS(K66)<=10),"PASS","FAIL")) -> PASS
B67: =IF($A$7="","","UIFSM") -> UIFSM | C67: =IF($A$7="","",SUMIFS('Pupils Insert Table'!J:J,'Pupils Insert Table'!D:D,$A$7,'Pupils Insert Table'!E:E,"PUPIL_UIFSM*")) -> 0 | D67: =IF($A$7="","",SUMIFS('Pupils Insert Table'!K:K,'Pupils Insert Table'!D:D,$A$7,'Pupils Insert Table'!E:E,"PUPIL_UIFSM*")) -> 0 | E67: =IF($A$7="","",SUMIFS('Pupils Insert Table'!L:L,'Pupils Insert Table'!D:D,$A$7,'Pupils Insert Table'!E:E,"PUPIL_UIFSM*")) -> 0 | I67: =IF($A$7="","",C67-F67) -> 0 | J67: =IF($A$7="","",D67-G67) -> 0 | K67: =IF($A$7="","",E67-H67) -> 0 | L67: =IF($A$7="","",IF(AND(ABS(I67)<=10,ABS(J67)<=10,ABS(K67)<=10),"PASS","FAIL")) -> PASS
B68: =IF($A$7="","","PP") -> PP | C68: =IF($A$7="","",SUMIFS('Pupils Insert Table'!J:J,'Pupils Insert Table'!D:D,$A$7,'Pupils Insert Table'!E:E,"PUPILPREMIUM*")) -> 0 | D68: =IF($A$7="","",SUMIFS('Pupils Insert Table'!K:K,'Pupils Insert Table'!D:D,$A$7,'Pupils Insert Table'!E:E,"PUPILPREMIUM*")) -> 0 | E68: =IF($A$7="","",SUMIFS('Pupils Insert Table'!L:L,'Pupils Insert Table'!D:D,$A$7,'Pupils Insert Table'!E:E,"PUPILPREMIUM*")) -> 0 | I68: =IF($A$7="","",C68-F68) -> 0 | J68: =IF($A$7="","",D68-G68) -> 0 | K68: =IF($A$7="","",E68-H68) -> 0 | L68: =IF($A$7="","",IF(AND(ABS(I68)<=10,ABS(J68)<=10,ABS(K68)<=10),"PASS","FAIL")) -> PASS
A69: =IF($A$8="","",$A$8) -> BBP | B69: =IF($A$8="","","Census") -> Census | C69: =IF($A$8="","",SUMIFS('Pupils Insert Table'!J:J,'Pupils Insert Table'!D:D,$A$8,'Pupils Insert Table'!E:E,"PUPIL_CEN*")) -> 0 | D69: =IF($A$8="","",SUMIFS('Pupils Insert Table'!K:K,'Pupils Insert Table'!D:D,$A$8,'Pupils Insert Table'!E:E,"PUPIL_CEN*")) -> 0 | E69: =IF($A$8="","",SUMIFS('Pupils Insert Table'!L:L,'Pupils Insert Table'!D:D,$A$8,'Pupils Insert Table'!E:E,"PUPIL_CEN*")) -> 0 | I69: =IF($A$8="","",C69-F69) -> 0 | J69: =IF($A$8="","",D69-G69) -> 0 | K69: =IF($A$8="","",E69-H69) -> 0 | L69: =IF($A$8="","",IF(AND(ABS(I69)<=10,ABS(J69)<=10,ABS(K69)<=10),"PASS","FAIL")) -> PASS
B70: =IF($A$8="","","Spring") -> Spring | C70: =IF($A$8="","",SUMIFS('Pupils Insert Table'!J:J,'Pupils Insert Table'!D:D,$A$8,'Pupils Insert Table'!E:E,"PUPIL_SPRING*")) -> 0 | D70: =IF($A$8="","",SUMIFS('Pupils Insert Table'!K:K,'Pupils Insert Table'!D:D,$A$8,'Pupils Insert Table'!E:E,"PUPIL_SPRING*")) -> 0 | E70: =IF($A$8="","",SUMIFS('Pupils Insert Table'!L:L,'Pupils Insert Table'!D:D,$A$8,'Pupils Insert Table'!E:E,"PUPIL_SPRING*")) -> 0 | I70: =IF($A$8="","",C70-F70) -> 0 | J70: =IF($A$8="","",D70-G70) -> 0 | K70: =IF($A$8="","",E70-H70) -> 0 | L70: =IF($A$8="","",IF(AND(ABS(I70)<=10,ABS(J70)<=10,ABS(K70)<=10),"PASS","FAIL")) -> PASS
B71: =IF($A$8="","","UIFSM") -> UIFSM | C71: =IF($A$8="","",SUMIFS('Pupils Insert Table'!J:J,'Pupils Insert Table'!D:D,$A$8,'Pupils Insert Table'!E:E,"PUPIL_UIFSM*")) -> 0 | D71: =IF($A$8="","",SUMIFS('Pupils Insert Table'!K:K,'Pupils Insert Table'!D:D,$A$8,'Pupils Insert Table'!E:E,"PUPIL_UIFSM*")) -> 0 | E71: =IF($A$8="","",SUMIFS('Pupils Insert Table'!L:L,'Pupils Insert Table'!D:D,$A$8,'Pupils Insert Table'!E:E,"PUPIL_UIFSM*")) -> 0 | I71: =IF($A$8="","",C71-F71) -> 0 | J71: =IF($A$8="","",D71-G71) -> 0 | K71: =IF($A$8="","",E71-H71) -> 0 | L71: =IF($A$8="","",IF(AND(ABS(I71)<=10,ABS(J71)<=10,ABS(K71)<=10),"PASS","FAIL")) -> PASS
B72: =IF($A$8="","","PP") -> PP | C72: =IF($A$8="","",SUMIFS('Pupils Insert Table'!J:J,'Pupils Insert Table'!D:D,$A$8,'Pupils Insert Table'!E:E,"PUPILPREMIUM*")) -> 0 | D72: =IF($A$8="","",SUMIFS('Pupils Insert Table'!K:K,'Pupils Insert Table'!D:D,$A$8,'Pupils Insert Table'!E:E,"PUPILPREMIUM*")) -> 0 | E72: =IF($A$8="","",SUMIFS('Pupils Insert Table'!L:L,'Pupils Insert Table'!D:D,$A$8,'Pupils Insert Table'!E:E,"PUPILPREMIUM*")) -> 0 | I72: =IF($A$8="","",C72-F72) -> 0 | J72: =IF($A$8="","",D72-G72) -> 0 | K72: =IF($A$8="","",E72-H72) -> 0 | L72: =IF($A$8="","",IF(AND(ABS(I72)<=10,ABS(J72)<=10,ABS(K72)<=10),"PASS","FAIL")) -> PASS
A73: =IF($A$9="","",$A$9) -> LCP | B73: =IF($A$9="","","Census") -> Census | C73: =IF($A$9="","",SUMIFS('Pupils Insert Table'!J:J,'Pupils Insert Table'!D:D,$A$9,'Pupils Insert Table'!E:E,"PUPIL_CEN*")) -> 0 | D73: =IF($A$9="","",SUMIFS('Pupils Insert Table'!K:K,'Pupils Insert Table'!D:D,$A$9,'Pupils Insert Table'!E:E,"PUPIL_CEN*")) -> 0 | E73: =IF($A$9="","",SUMIFS('Pupils Insert Table'!L:L,'Pupils Insert Table'!D:D,$A$9,'Pupils Insert Table'!E:E,"PUPIL_CEN*")) -> 0 | I73: =IF($A$9="","",C73-F73) -> 0 | J73: =IF($A$9="","",D73-G73) -> 0 | K73: =IF($A$9="","",E73-H73) -> 0 | L73: =IF($A$9="","",IF(AND(ABS(I73)<=10,ABS(J73)<=10,ABS(K73)<=10),"PASS","FAIL")) -> PASS
B74: =IF($A$9="","","Spring") -> Spring | C74: =IF($A$9="","",SUMIFS('Pupils Insert Table'!J:J,'Pupils Insert Table'!D:D,$A$9,'Pupils Insert Table'!E:E,"PUPIL_SPRING*")) -> 0 | D74: =IF($A$9="","",SUMIFS('Pupils Insert Table'!K:K,'Pupils Insert Table'!D:D,$A$9,'Pupils Insert Table'!E:E,"PUPIL_SPRING*")) -> 0 | E74: =IF($A$9="","",SUMIFS('Pupils Insert Table'!L:L,'Pupils Insert Table'!D:D,$A$9,'Pupils Insert Table'!E:E,"PUPIL_SPRING*")) -> 0 | I74: =IF($A$9="","",C74-F74) -> 0 | J74: =IF($A$9="","",D74-G74) -> 0 | K74: =IF($A$9="","",E74-H74) -> 0 | L74: =IF($A$9="","",IF(AND(ABS(I74)<=10,ABS(J74)<=10,ABS(K74)<=10),"PASS","FAIL")) -> PASS
B75: =IF($A$9="","","UIFSM") -> UIFSM | C75: =IF($A$9="","",SUMIFS('Pupils Insert Table'!J:J,'Pupils Insert Table'!D:D,$A$9,'Pupils Insert Table'!E:E,"PUPIL_UIFSM*")) -> 0 | D75: =IF($A$9="","",SUMIFS('Pupils Insert Table'!K:K,'Pupils Insert Table'!D:D,$A$9,'Pupils Insert Table'!E:E,"PUPIL_UIFSM*")) -> 0 | E75: =IF($A$9="","",SUMIFS('Pupils Insert Table'!L:L,'Pupils Insert Table'!D:D,$A$9,'Pupils Insert Table'!E:E,"PUPIL_UIFSM*")) -> 0 | I75: =IF($A$9="","",C75-F75) -> 0 | J75: =IF($A$9="","",D75-G75) -> 0 | K75: =IF($A$9="","",E75-H75) -> 0 | L75: =IF($A$9="","",IF(AND(ABS(I75)<=10,ABS(J75)<=10,ABS(K75)<=10),"PASS","FAIL")) -> PASS
B76: =IF($A$9="","","PP") -> PP | C76: =IF($A$9="","",SUMIFS('Pupils Insert Table'!J:J,'Pupils Insert Table'!D:D,$A$9,'Pupils Insert Table'!E:E,"PUPILPREMIUM*")) -> 0 | D76: =IF($A$9="","",SUMIFS('Pupils Insert Table'!K:K,'Pupils Insert Table'!D:D,$A$9,'Pupils Insert Table'!E:E,"PUPILPREMIUM*")) -> 0 | E76: =IF($A$9="","",SUMIFS('Pupils Insert Table'!L:L,'Pupils Insert Table'!D:D,$A$9,'Pupils Insert Table'!E:E,"PUPILPREMIUM*")) -> 0 | I76: =IF($A$9="","",C76-F76) -> 0 | J76: =IF($A$9="","",D76-G76) -> 0 | K76: =IF($A$9="","",E76-H76) -> 0 | L76: =IF($A$9="","",IF(AND(ABS(I76)<=10,ABS(J76)<=10,ABS(K76)<=10),"PASS","FAIL")) -> PASS
A77: =IF($A$10="","",$A$10) -> MMP | B77: =IF($A$10="","","Census") -> Census | C77: =IF($A$10="","",SUMIFS('Pupils Insert Table'!J:J,'Pupils Insert Table'!D:D,$A$10,'Pupils Insert Table'!E:E,"PUPIL_CEN*")) -> 0 | D77: =IF($A$10="","",SUMIFS('Pupils Insert Table'!K:K,'Pupils Insert Table'!D:D,$A$10,'Pupils Insert Table'!E:E,"PUPIL_CEN*")) -> 0 | E77: =IF($A$10="","",SUMIFS('Pupils Insert Table'!L:L,'Pupils Insert Table'!D:D,$A$10,'Pupils Insert Table'!E:E,"PUPIL_CEN*")) -> 0 | I77: =IF($A$10="","",C77-F77) -> 0 | J77: =IF($A$10="","",D77-G77) -> 0 | K77: =IF($A$10="","",E77-H77) -> 0 | L77: =IF($A$10="","",IF(AND(ABS(I77)<=10,ABS(J77)<=10,ABS(K77)<=10),"PASS","FAIL")) -> PASS
B78: =IF($A$10="","","Spring") -> Spring | C78: =IF($A$10="","",SUMIFS('Pupils Insert Table'!J:J,'Pupils Insert Table'!D:D,$A$10,'Pupils Insert Table'!E:E,"PUPIL_SPRING*")) -> 0 | D78: =IF($A$10="","",SUMIFS('Pupils Insert Table'!K:K,'Pupils Insert Table'!D:D,$A$10,'Pupils Insert Table'!E:E,"PUPIL_SPRING*")) -> 0 | E78: =IF($A$10="","",SUMIFS('Pupils Insert Table'!L:L,'Pupils Insert Table'!D:D,$A$10,'Pupils Insert Table'!E:E,"PUPIL_SPRING*")) -> 0 | I78: =IF($A$10="","",C78-F78) -> 0 | J78: =IF($A$10="","",D78-G78) -> 0 | K78: =IF($A$10="","",E78-H78) -> 0 | L78: =IF($A$10="","",IF(AND(ABS(I78)<=10,ABS(J78)<=10,ABS(K78)<=10),"PASS","FAIL")) -> PASS
B79: =IF($A$10="","","UIFSM") -> UIFSM | C79: =IF($A$10="","",SUMIFS('Pupils Insert Table'!J:J,'Pupils Insert Table'!D:D,$A$10,'Pupils Insert Table'!E:E,"PUPIL_UIFSM*")) -> 0 | D79: =IF($A$10="","",SUMIFS('Pupils Insert Table'!K:K,'Pupils Insert Table'!D:D,$A$10,'Pupils Insert Table'!E:E,"PUPIL_UIFSM*")) -> 0 | E79: =IF($A$10="","",SUMIFS('Pupils Insert Table'!L:L,'Pupils Insert Table'!D:D,$A$10,'Pupils Insert Table'!E:E,"PUPIL_UIFSM*")) -> 0 | I79: =IF($A$10="","",C79-F79) -> 0 | J79: =IF($A$10="","",D79-G79) -> 0 | K79: =IF($A$10="","",E79-H79) -> 0 | L79: =IF($A$10="","",IF(AND(ABS(I79)<=10,ABS(J79)<=10,ABS(K79)<=10),"PASS","FAIL")) -> PASS
B80: =IF($A$10="","","PP") -> PP | C80: =IF($A$10="","",SUMIFS('Pupils Insert Table'!J:J,'Pupils Insert Table'!D:D,$A$10,'Pupils Insert Table'!E:E,"PUPILPREMIUM*")) -> 0 | D80: =IF($A$10="","",SUMIFS('Pupils Insert Table'!K:K,'Pupils Insert Table'!D:D,$A$10,'Pupils Insert Table'!E:E,"PUPILPREMIUM*")) -> 0 | E80: =IF($A$10="","",SUMIFS('Pupils Insert Table'!L:L,'Pupils Insert Table'!D:D,$A$10,'Pupils Insert Table'!E:E,"PUPILPREMIUM*")) -> 0 | I80: =IF($A$10="","",C80-F80) -> 0 | J80: =IF($A$10="","",D80-G80) -> 0 | K80: =IF($A$10="","",E80-H80) -> 0 | L80: =IF($A$10="","",IF(AND(ABS(I80)<=10,ABS(J80)<=10,ABS(K80)<=10),"PASS","FAIL")) -> PASS
A81: =IF($A$11="","",$A$11) -> NIN | B81: =IF($A$11="","","Census") -> Census | C81: =IF($A$11="","",SUMIFS('Pupils Insert Table'!J:J,'Pupils Insert Table'!D:D,$A$11,'Pupils Insert Table'!E:E,"PUPIL_CEN*")) -> 0 | D81: =IF($A$11="","",SUMIFS('Pupils Insert Table'!K:K,'Pupils Insert Table'!D:D,$A$11,'Pupils Insert Table'!E:E,"PUPIL_CEN*")) -> 0 | E81: =IF($A$11="","",SUMIFS('Pupils Insert Table'!L:L,'Pupils Insert Table'!D:D,$A$11,'Pupils Insert Table'!E:E,"PUPIL_CEN*")) -> 0 | I81: =IF($A$11="","",C81-F81) -> 0 | J81: =IF($A$11="","",D81-G81) -> 0 | K81: =IF($A$11="","",E81-H81) -> 0 | L81: =IF($A$11="","",IF(AND(ABS(I81)<=10,ABS(J81)<=10,ABS(K81)<=10),"PASS","FAIL")) -> PASS
B82: =IF($A$11="","","Spring") -> Spring | C82: =IF($A$11="","",SUMIFS('Pupils Insert Table'!J:J,'Pupils Insert Table'!D:D,$A$11,'Pupils Insert Table'!E:E,"PUPIL_SPRING*")) -> 0 | D82: =IF($A$11="","",SUMIFS('Pupils Insert Table'!K:K,'Pupils Insert Table'!D:D,$A$11,'Pupils Insert Table'!E:E,"PUPIL_SPRING*")) -> 0 | E82: =IF($A$11="","",SUMIFS('Pupils Insert Table'!L:L,'Pupils Insert Table'!D:D,$A$11,'Pupils Insert Table'!E:E,"PUPIL_SPRING*")) -> 0 | I82: =IF($A$11="","",C82-F82) -> 0 | J82: =IF($A$11="","",D82-G82) -> 0 | K82: =IF($A$11="","",E82-H82) -> 0 | L82: =IF($A$11="","",IF(AND(ABS(I82)<=10,ABS(J82)<=10,ABS(K82)<=10),"PASS","FAIL")) -> PASS
B83: =IF($A$11="","","UIFSM") -> UIFSM | C83: =IF($A$11="","",SUMIFS('Pupils Insert Table'!J:J,'Pupils Insert Table'!D:D,$A$11,'Pupils Insert Table'!E:E,"PUPIL_UIFSM*")) -> 0 | D83: =IF($A$11="","",SUMIFS('Pupils Insert Table'!K:K,'Pupils Insert Table'!D:D,$A$11,'Pupils Insert Table'!E:E,"PUPIL_UIFSM*")) -> 0 | E83: =IF($A$11="","",SUMIFS('Pupils Insert Table'!L:L,'Pupils Insert Table'!D:D,$A$11,'Pupils Insert Table'!E:E,"PUPIL_UIFSM*")) -> 0 | I83: =IF($A$11="","",C83-F83) -> 0 | J83: =IF($A$11="","",D83-G83) -> 0 | K83: =IF($A$11="","",E83-H83) -> 0 | L83: =IF($A$11="","",IF(AND(ABS(I83)<=10,ABS(J83)<=10,ABS(K83)<=10),"PASS","FAIL")) -> PASS
B84: =IF($A$11="","","PP") -> PP | C84: =IF($A$11="","",SUMIFS('Pupils Insert Table'!J:J,'Pupils Insert Table'!D:D,$A$11,'Pupils Insert Table'!E:E,"PUPILPREMIUM*")) -> 0 | D84: =IF($A$11="","",SUMIFS('Pupils Insert Table'!K:K,'Pupils Insert Table'!D:D,$A$11,'Pupils Insert Table'!E:E,"PUPILPREMIUM*")) -> 0 | E84: =IF($A$11="","",SUMIFS('Pupils Insert Table'!L:L,'Pupils Insert Table'!D:D,$A$11,'Pupils Insert Table'!E:E,"PUPILPREMIUM*")) -> 0 | I84: =IF($A$11="","",C84-F84) -> 0 | J84: =IF($A$11="","",D84-G84) -> 0 | K84: =IF($A$11="","",E84-H84) -> 0 | L84: =IF($A$11="","",IF(AND(ABS(I84)<=10,ABS(J84)<=10,ABS(K84)<=10),"PASS","FAIL")) -> PASS
A85: =IF($A$12="","",$A$12) -> SRA | B85: =IF($A$12="","","Census") -> Census | C85: =IF($A$12="","",SUMIFS('Pupils Insert Table'!J:J,'Pupils Insert Table'!D:D,$A$12,'Pupils Insert Table'!E:E,"PUPIL_CEN*")) -> 0 | D85: =IF($A$12="","",SUMIFS('Pupils Insert Table'!K:K,'Pupils Insert Table'!D:D,$A$12,'Pupils Insert Table'!E:E,"PUPIL_CEN*")) -> 0 | E85: =IF($A$12="","",SUMIFS('Pupils Insert Table'!L:L,'Pupils Insert Table'!D:D,$A$12,'Pupils Insert Table'!E:E,"PUPIL_CEN*")) -> 0 | I85: =IF($A$12="","",C85-F85) -> 0 | J85: =IF($A$12="","",D85-G85) -> 0 | K85: =IF($A$12="","",E85-H85) -> 0 | L85: =IF($A$12="","",IF(AND(ABS(I85)<=10,ABS(J85)<=10,ABS(K85)<=10),"PASS","FAIL")) -> PASS
B86: =IF($A$12="","","Spring") -> Spring | C86: =IF($A$12="","",SUMIFS('Pupils Insert Table'!J:J,'Pupils Insert Table'!D:D,$A$12,'Pupils Insert Table'!E:E,"PUPIL_SPRING*")) -> 0 | D86: =IF($A$12="","",SUMIFS('Pupils Insert Table'!K:K,'Pupils Insert Table'!D:D,$A$12,'Pupils Insert Table'!E:E,"PUPIL_SPRING*")) -> 0 | E86: =IF($A$12="","",SUMIFS('Pupils Insert Table'!L:L,'Pupils Insert Table'!D:D,$A$12,'Pupils Insert Table'!E:E,"PUPIL_SPRING*")) -> 0 | I86: =IF($A$12="","",C86-F86) -> 0 | J86: =IF($A$12="","",D86-G86) -> 0 | K86: =IF($A$12="","",E86-H86) -> 0 | L86: =IF($A$12="","",IF(AND(ABS(I86)<=10,ABS(J86)<=10,ABS(K86)<=10),"PASS","FAIL")) -> PASS
B87: =IF($A$12="","","UIFSM") -> UIFSM | C87: =IF($A$12="","",SUMIFS('Pupils Insert Table'!J:J,'Pupils Insert Table'!D:D,$A$12,'Pupils Insert Table'!E:E,"PUPIL_UIFSM*")) -> 0 | D87: =IF($A$12="","",SUMIFS('Pupils Insert Table'!K:K,'Pupils Insert Table'!D:D,$A$12,'Pupils Insert Table'!E:E,"PUPIL_UIFSM*")) -> 0 | E87: =IF($A$12="","",SUMIFS('Pupils Insert Table'!L:L,'Pupils Insert Table'!D:D,$A$12,'Pupils Insert Table'!E:E,"PUPIL_UIFSM*")) -> 0 | I87: =IF($A$12="","",C87-F87) -> 0 | J87: =IF($A$12="","",D87-G87) -> 0 | K87: =IF($A$12="","",E87-H87) -> 0 | L87: =IF($A$12="","",IF(AND(ABS(I87)<=10,ABS(J87)<=10,ABS(K87)<=10),"PASS","FAIL")) -> PASS
B88: =IF($A$12="","","PP") -> PP | C88: =IF($A$12="","",SUMIFS('Pupils Insert Table'!J:J,'Pupils Insert Table'!D:D,$A$12,'Pupils Insert Table'!E:E,"PUPILPREMIUM*")) -> 0 | D88: =IF($A$12="","",SUMIFS('Pupils Insert Table'!K:K,'Pupils Insert Table'!D:D,$A$12,'Pupils Insert Table'!E:E,"PUPILPREMIUM*")) -> 0 | E88: =IF($A$12="","",SUMIFS('Pupils Insert Table'!L:L,'Pupils Insert Table'!D:D,$A$12,'Pupils Insert Table'!E:E,"PUPILPREMIUM*")) -> 0 | I88: =IF($A$12="","",C88-F88) -> 0 | J88: =IF($A$12="","",D88-G88) -> 0 | K88: =IF($A$12="","",E88-H88) -> 0 | L88: =IF($A$12="","",IF(AND(ABS(I88)<=10,ABS(J88)<=10,ABS(K88)<=10),"PASS","FAIL")) -> PASS
A89: =IF($A$13="","",$A$13) -> BBS | B89: =IF($A$13="","","Census") -> Census | C89: =IF($A$13="","",SUMIFS('Pupils Insert Table'!J:J,'Pupils Insert Table'!D:D,$A$13,'Pupils Insert Table'!E:E,"PUPIL_CEN*")) -> 0 | D89: =IF($A$13="","",SUMIFS('Pupils Insert Table'!K:K,'Pupils Insert Table'!D:D,$A$13,'Pupils Insert Table'!E:E,"PUPIL_CEN*")) -> 0 | E89: =IF($A$13="","",SUMIFS('Pupils Insert Table'!L:L,'Pupils Insert Table'!D:D,$A$13,'Pupils Insert Table'!E:E,"PUPIL_CEN*")) -> 0 | I89: =IF($A$13="","",C89-F89) -> 0 | J89: =IF($A$13="","",D89-G89) -> 0 | K89: =IF($A$13="","",E89-H89) -> 0 | L89: =IF($A$13="","",IF(AND(ABS(I89)<=10,ABS(J89)<=10,ABS(K89)<=10),"PASS","FAIL")) -> PASS
B90: =IF($A$13="","","Spring") -> Spring | C90: =IF($A$13="","",SUMIFS('Pupils Insert Table'!J:J,'Pupils Insert Table'!D:D,$A$13,'Pupils Insert Table'!E:E,"PUPIL_SPRING*")) -> 0 | D90: =IF($A$13="","",SUMIFS('Pupils Insert Table'!K:K,'Pupils Insert Table'!D:D,$A$13,'Pupils Insert Table'!E:E,"PUPIL_SPRING*")) -> 0 | E90: =IF($A$13="","",SUMIFS('Pupils Insert Table'!L:L,'Pupils Insert Table'!D:D,$A$13,'Pupils Insert Table'!E:E,"PUPIL_SPRING*")) -> 0 | I90: =IF($A$13="","",C90-F90) -> 0 | J90: =IF($A$13="","",D90-G90) -> 0 | K90: =IF($A$13="","",E90-H90) -> 0 | L90: =IF($A$13="","",IF(AND(ABS(I90)<=10,ABS(J90)<=10,ABS(K90)<=10),"PASS","FAIL")) -> PASS
B91: =IF($A$13="","","UIFSM") -> UIFSM | C91: =IF($A$13="","",SUMIFS('Pupils Insert Table'!J:J,'Pupils Insert Table'!D:D,$A$13,'Pupils Insert Table'!E:E,"PUPIL_UIFSM*")) -> 0 | D91: =IF($A$13="","",SUMIFS('Pupils Insert Table'!K:K,'Pupils Insert Table'!D:D,$A$13,'Pupils Insert Table'!E:E,"PUPIL_UIFSM*")) -> 0 | E91: =IF($A$13="","",SUMIFS('Pupils Insert Table'!L:L,'Pupils Insert Table'!D:D,$A$13,'Pupils Insert Table'!E:E,"PUPIL_UIFSM*")) -> 0 | I91: =IF($A$13="","",C91-F91) -> 0 | J91: =IF($A$13="","",D91-G91) -> 0 | K91: =IF($A$13="","",E91-H91) -> 0 | L91: =IF($A$13="","",IF(AND(ABS(I91)<=10,ABS(J91)<=10,ABS(K91)<=10),"PASS","FAIL")) -> PASS
B92: =IF($A$13="","","PP") -> PP | C92: =IF($A$13="","",SUMIFS('Pupils Insert Table'!J:J,'Pupils Insert Table'!D:D,$A$13,'Pupils Insert Table'!E:E,"PUPILPREMIUM*")) -> 0 | D92: =IF($A$13="","",SUMIFS('Pupils Insert Table'!K:K,'Pupils Insert Table'!D:D,$A$13,'Pupils Insert Table'!E:E,"PUPILPREMIUM*")) -> 0 | E92: =IF($A$13="","",SUMIFS('Pupils Insert Table'!L:L,'Pupils Insert Table'!D:D,$A$13,'Pupils Insert Table'!E:E,"PUPILPREMIUM*")) -> 0 | I92: =IF($A$13="","",C92-F92) -> 0 | J92: =IF($A$13="","",D92-G92) -> 0 | K92: =IF($A$13="","",E92-H92) -> 0 | L92: =IF($A$13="","",IF(AND(ABS(I92)<=10,ABS(J92)<=10,ABS(K92)<=10),"PASS","FAIL")) -> PASS
A93: =IF($A$14="","",$A$14) -> HHS | B93: =IF($A$14="","","Census") -> Census | C93: =IF($A$14="","",SUMIFS('Pupils Insert Table'!J:J,'Pupils Insert Table'!D:D,$A$14,'Pupils Insert Table'!E:E,"PUPIL_CEN*")) -> 0 | D93: =IF($A$14="","",SUMIFS('Pupils Insert Table'!K:K,'Pupils Insert Table'!D:D,$A$14,'Pupils Insert Table'!E:E,"PUPIL_CEN*")) -> 0 | E93: =IF($A$14="","",SUMIFS('Pupils Insert Table'!L:L,'Pupils Insert Table'!D:D,$A$14,'Pupils Insert Table'!E:E,"PUPIL_CEN*")) -> 0 | I93: =IF($A$14="","",C93-F93) -> 0 | J93: =IF($A$14="","",D93-G93) -> 0 | K93: =IF($A$14="","",E93-H93) -> 0 | L93: =IF($A$14="","",IF(AND(ABS(I93)<=10,ABS(J93)<=10,ABS(K93)<=10),"PASS","FAIL")) -> PASS
B94: =IF($A$14="","","Spring") -> Spring | C94: =IF($A$14="","",SUMIFS('Pupils Insert Table'!J:J,'Pupils Insert Table'!D:D,$A$14,'Pupils Insert Table'!E:E,"PUPIL_SPRING*")) -> 0 | D94: =IF($A$14="","",SUMIFS('Pupils Insert Table'!K:K,'Pupils Insert Table'!D:D,$A$14,'Pupils Insert Table'!E:E,"PUPIL_SPRING*")) -> 0 | E94: =IF($A$14="","",SUMIFS('Pupils Insert Table'!L:L,'Pupils Insert Table'!D:D,$A$14,'Pupils Insert Table'!E:E,"PUPIL_SPRING*")) -> 0 | I94: =IF($A$14="","",C94-F94) -> 0 | J94: =IF($A$14="","",D94-G94) -> 0 | K94: =IF($A$14="","",E94-H94) -> 0 | L94: =IF($A$14="","",IF(AND(ABS(I94)<=10,ABS(J94)<=10,ABS(K94)<=10),"PASS","FAIL")) -> PASS
B95: =IF($A$14="","","UIFSM") -> UIFSM | C95: =IF($A$14="","",SUMIFS('Pupils Insert Table'!J:J,'Pupils Insert Table'!D:D,$A$14,'Pupils Insert Table'!E:E,"PUPIL_UIFSM*")) -> 0 | D95: =IF($A$14="","",SUMIFS('Pupils Insert Table'!K:K,'Pupils Insert Table'!D:D,$A$14,'Pupils Insert Table'!E:E,"PUPIL_UIFSM*")) -> 0 | E95: =IF($A$14="","",SUMIFS('Pupils Insert Table'!L:L,'Pupils Insert Table'!D:D,$A$14,'Pupils Insert Table'!E:E,"PUPIL_UIFSM*")) -> 0 | I95: =IF($A$14="","",C95-F95) -> 0 | J95: =IF($A$14="","",D95-G95) -> 0 | K95: =IF($A$14="","",E95-H95) -> 0 | L95: =IF($A$14="","",IF(AND(ABS(I95)<=10,ABS(J95)<=10,ABS(K95)<=10),"PASS","FAIL")) -> PASS
B96: =IF($A$14="","","PP") -> PP | C96: =IF($A$14="","",SUMIFS('Pupils Insert Table'!J:J,'Pupils Insert Table'!D:D,$A$14,'Pupils Insert Table'!E:E,"PUPILPREMIUM*")) -> 0 | D96: =IF($A$14="","",SUMIFS('Pupils Insert Table'!K:K,'Pupils Insert Table'!D:D,$A$14,'Pupils Insert Table'!E:E,"PUPILPREMIUM*")) -> 0 | E96: =IF($A$14="","",SUMIFS('Pupils Insert Table'!L:L,'Pupils Insert Table'!D:D,$A$14,'Pupils Insert Table'!E:E,"PUPILPREMIUM*")) -> 0 | I96: =IF($A$14="","",C96-F96) -> 0 | J96: =IF($A$14="","",D96-G96) -> 0 | K96: =IF($A$14="","",E96-H96) -> 0 | L96: =IF($A$14="","",IF(AND(ABS(I96)<=10,ABS(J96)<=10,ABS(K96)<=10),"PASS","FAIL")) -> PASS
A97: =IF($A$15="","",$A$15) -> RVS | B97: =IF($A$15="","","Census") -> Census | C97: =IF($A$15="","",SUMIFS('Pupils Insert Table'!J:J,'Pupils Insert Table'!D:D,$A$15,'Pupils Insert Table'!E:E,"PUPIL_CEN*")) -> 0 | D97: =IF($A$15="","",SUMIFS('Pupils Insert Table'!K:K,'Pupils Insert Table'!D:D,$A$15,'Pupils Insert Table'!E:E,"PUPIL_CEN*")) -> 0 | E97: =IF($A$15="","",SUMIFS('Pupils Insert Table'!L:L,'Pupils Insert Table'!D:D,$A$15,'Pupils Insert Table'!E:E,"PUPIL_CEN*")) -> 0 | I97: =IF($A$15="","",C97-F97) -> 0 | J97: =IF($A$15="","",D97-G97) -> 0 | K97: =IF($A$15="","",E97-H97) -> 0 | L97: =IF($A$15="","",IF(AND(ABS(I97)<=10,ABS(J97)<=10,ABS(K97)<=10),"PASS","FAIL")) -> PASS
B98: =IF($A$15="","","Spring") -> Spring | C98: =IF($A$15="","",SUMIFS('Pupils Insert Table'!J:J,'Pupils Insert Table'!D:D,$A$15,'Pupils Insert Table'!E:E,"PUPIL_SPRING*")) -> 0 | D98: =IF($A$15="","",SUMIFS('Pupils Insert Table'!K:K,'Pupils Insert Table'!D:D,$A$15,'Pupils Insert Table'!E:E,"PUPIL_SPRING*")) -> 0 | E98: =IF($A$15="","",SUMIFS('Pupils Insert Table'!L:L,'Pupils Insert Table'!D:D,$A$15,'Pupils Insert Table'!E:E,"PUPIL_SPRING*")) -> 0 | I98: =IF($A$15="","",C98-F98) -> 0 | J98: =IF($A$15="","",D98-G98) -> 0 | K98: =IF($A$15="","",E98-H98) -> 0 | L98: =IF($A$15="","",IF(AND(ABS(I98)<=10,ABS(J98)<=10,ABS(K98)<=10),"PASS","FAIL")) -> PASS
B99: =IF($A$15="","","UIFSM") -> UIFSM | C99: =IF($A$15="","",SUMIFS('Pupils Insert Table'!J:J,'Pupils Insert Table'!D:D,$A$15,'Pupils Insert Table'!E:E,"PUPIL_UIFSM*")) -> 0 | D99: =IF($A$15="","",SUMIFS('Pupils Insert Table'!K:K,'Pupils Insert Table'!D:D,$A$15,'Pupils Insert Table'!E:E,"PUPIL_UIFSM*")) -> 0 | E99: =IF($A$15="","",SUMIFS('Pupils Insert Table'!L:L,'Pupils Insert Table'!D:D,$A$15,'Pupils Insert Table'!E:E,"PUPIL_UIFSM*")) -> 0 | I99: =IF($A$15="","",C99-F99) -> 0 | J99: =IF($A$15="","",D99-G99) -> 0 | K99: =IF($A$15="","",E99-H99) -> 0 | L99: =IF($A$15="","",IF(AND(ABS(I99)<=10,ABS(J99)<=10,ABS(K99)<=10),"PASS","FAIL")) -> PASS
B100: =IF($A$15="","","PP") -> PP | C100: =IF($A$15="","",SUMIFS('Pupils Insert Table'!J:J,'Pupils Insert Table'!D:D,$A$15,'Pupils Insert Table'!E:E,"PUPILPREMIUM*")) -> 0 | D100: =IF($A$15="","",SUMIFS('Pupils Insert Table'!K:K,'Pupils Insert Table'!D:D,$A$15,'Pupils Insert Table'!E:E,"PUPILPREMIUM*")) -> 0 | E100: =IF($A$15="","",SUMIFS('Pupils Insert Table'!L:L,'Pupils Insert Table'!D:D,$A$15,'Pupils Insert Table'!E:E,"PUPILPREMIUM*")) -> 0 | I100: =IF($A$15="","",C100-F100) -> 0 | J100: =IF($A$15="","",D100-G100) -> 0 | K100: =IF($A$15="","",E100-H100) -> 0 | L100: =IF($A$15="","",IF(AND(ABS(I100)<=10,ABS(J100)<=10,ABS(K100)<=10),"PASS","FAIL")) -> PASS
A101: =IF($A$16="","",$A$16) -> CHS | B101: =IF($A$16="","","Census") -> Census | C101: =IF($A$16="","",SUMIFS('Pupils Insert Table'!J:J,'Pupils Insert Table'!D:D,$A$16,'Pupils Insert Table'!E:E,"PUPIL_CEN*")) -> 0 | D101: =IF($A$16="","",SUMIFS('Pupils Insert Table'!K:K,'Pupils Insert Table'!D:D,$A$16,'Pupils Insert Table'!E:E,"PUPIL_CEN*")) -> 0 | E101: =IF($A$16="","",SUMIFS('Pupils Insert Table'!L:L,'Pupils Insert Table'!D:D,$A$16,'Pupils Insert Table'!E:E,"PUPIL_CEN*")) -> 0 | I101: =IF($A$16="","",C101-F101) -> 0 | J101: =IF($A$16="","",D101-G101) -> 0 | K101: =IF($A$16="","",E101-H101) -> 0 | L101: =IF($A$16="","",IF(AND(ABS(I101)<=10,ABS(J101)<=10,ABS(K101)<=10),"PASS","FAIL")) -> PASS
B102: =IF($A$16="","","Spring") -> Spring | C102: =IF($A$16="","",SUMIFS('Pupils Insert Table'!J:J,'Pupils Insert Table'!D:D,$A$16,'Pupils Insert Table'!E:E,"PUPIL_SPRING*")) -> 0 | D102: =IF($A$16="","",SUMIFS('Pupils Insert Table'!K:K,'Pupils Insert Table'!D:D,$A$16,'Pupils Insert Table'!E:E,"PUPIL_SPRING*")) -> 0 | E102: =IF($A$16="","",SUMIFS('Pupils Insert Table'!L:L,'Pupils Insert Table'!D:D,$A$16,'Pupils Insert Table'!E:E,"PUPIL_SPRING*")) -> 0 | I102: =IF($A$16="","",C102-F102) -> 0 | J102: =IF($A$16="","",D102-G102) -> 0 | K102: =IF($A$16="","",E102-H102) -> 0 | L102: =IF($A$16="","",IF(AND(ABS(I102)<=10,ABS(J102)<=10,ABS(K102)<=10),"PASS","FAIL")) -> PASS
B103: =IF($A$16="","","UIFSM") -> UIFSM | C103: =IF($A$16="","",SUMIFS('Pupils Insert Table'!J:J,'Pupils Insert Table'!D:D,$A$16,'Pupils Insert Table'!E:E,"PUPIL_UIFSM*")) -> 0 | D103: =IF($A$16="","",SUMIFS('Pupils Insert Table'!K:K,'Pupils Insert Table'!D:D,$A$16,'Pupils Insert Table'!E:E,"PUPIL_UIFSM*")) -> 0 | E103: =IF($A$16="","",SUMIFS('Pupils Insert Table'!L:L,'Pupils Insert Table'!D:D,$A$16,'Pupils Insert Table'!E:E,"PUPIL_UIFSM*")) -> 0 | I103: =IF($A$16="","",C103-F103) -> 0 | J103: =IF($A$16="","",D103-G103) -> 0 | K103: =IF($A$16="","",E103-H103) -> 0 | L103: =IF($A$16="","",IF(AND(ABS(I103)<=10,ABS(J103)<=10,ABS(K103)<=10),"PASS","FAIL")) -> PASS
B104: =IF($A$16="","","PP") -> PP | C104: =IF($A$16="","",SUMIFS('Pupils Insert Table'!J:J,'Pupils Insert Table'!D:D,$A$16,'Pupils Insert Table'!E:E,"PUPILPREMIUM*")) -> 0 | D104: =IF($A$16="","",SUMIFS('Pupils Insert Table'!K:K,'Pupils Insert Table'!D:D,$A$16,'Pupils Insert Table'!E:E,"PUPILPREMIUM*")) -> 0 | E104: =IF($A$16="","",SUMIFS('Pupils Insert Table'!L:L,'Pupils Insert Table'!D:D,$A$16,'Pupils Insert Table'!E:E,"PUPILPREMIUM*")) -> 0 | I104: =IF($A$16="","",C104-F104) -> 0 | J104: =IF($A$16="","",D104-G104) -> 0 | K104: =IF($A$16="","",E104-H104) -> 0 | L104: =IF($A$16="","",IF(AND(ABS(I104)<=10,ABS(J104)<=10,ABS(K104)<=10),"PASS","FAIL")) -> PASS
A105: =IF($A$17="","",$A$17) | B105: =IF($A$17="","","Census") | C105: =IF($A$17="","",SUMIFS('Pupils Insert Table'!J:J,'Pupils Insert Table'!D:D,$A$17,'Pupils Insert Table'!E:E,"PUPIL_CEN*")) | D105: =IF($A$17="","",SUMIFS('Pupils Insert Table'!K:K,'Pupils Insert Table'!D:D,$A$17,'Pupils Insert Table'!E:E,"PUPIL_CEN*")) | E105: =IF($A$17="","",SUMIFS('Pupils Insert Table'!L:L,'Pupils Insert Table'!D:D,$A$17,'Pupils Insert Table'!E:E,"PUPIL_CEN*")) | I105: =IF($A$17="","",C105-F105) | J105: =IF($A$17="","",D105-G105) | K105: =IF($A$17="","",E105-H105) | L105: =IF($A$17="","",IF(AND(ABS(I105)<=10,ABS(J105)<=10,ABS(K105)<=10),"PASS","FAIL"))
B106: =IF($A$17="","","Spring") | C106: =IF($A$17="","",SUMIFS('Pupils Insert Table'!J:J,'Pupils Insert Table'!D:D,$A$17,'Pupils Insert Table'!E:E,"PUPIL_SPRING*")) | D106: =IF($A$17="","",SUMIFS('Pupils Insert Table'!K:K,'Pupils Insert Table'!D:D,$A$17,'Pupils Insert Table'!E:E,"PUPIL_SPRING*")) | E106: =IF($A$17="","",SUMIFS('Pupils Insert Table'!L:L,'Pupils Insert Table'!D:D,$A$17,'Pupils Insert Table'!E:E,"PUPIL_SPRING*")) | I106: =IF($A$17="","",C106-F106) | J106: =IF($A$17="","",D106-G106) | K106: =IF($A$17="","",E106-H106) | L106: =IF($A$17="","",IF(AND(ABS(I106)<=10,ABS(J106)<=10,ABS(K106)<=10),"PASS","FAIL"))
B107: =IF($A$17="","","UIFSM") | C107: =IF($A$17="","",SUMIFS('Pupils Insert Table'!J:J,'Pupils Insert Table'!D:D,$A$17,'Pupils Insert Table'!E:E,"PUPIL_UIFSM*")) | D107: =IF($A$17="","",SUMIFS('Pupils Insert Table'!K:K,'Pupils Insert Table'!D:D,$A$17,'Pupils Insert Table'!E:E,"PUPIL_UIFSM*")) | E107: =IF($A$17="","",SUMIFS('Pupils Insert Table'!L:L,'Pupils Insert Table'!D:D,$A$17,'Pupils Insert Table'!E:E,"PUPIL_UIFSM*")) | I107: =IF($A$17="","",C107-F107) | J107: =IF($A$17="","",D107-G107) | K107: =IF($A$17="","",E107-H107) | L107: =IF($A$17="","",IF(AND(ABS(I107)<=10,ABS(J107)<=10,ABS(K107)<=10),"PASS","FAIL"))
B108: =IF($A$17="","","PP") | C108: =IF($A$17="","",SUMIFS('Pupils Insert Table'!J:J,'Pupils Insert Table'!D:D,$A$17,'Pupils Insert Table'!E:E,"PUPILPREMIUM*")) | D108: =IF($A$17="","",SUMIFS('Pupils Insert Table'!K:K,'Pupils Insert Table'!D:D,$A$17,'Pupils Insert Table'!E:E,"PUPILPREMIUM*")) | E108: =IF($A$17="","",SUMIFS('Pupils Insert Table'!L:L,'Pupils Insert Table'!D:D,$A$17,'Pupils Insert Table'!E:E,"PUPILPREMIUM*")) | I108: =IF($A$17="","",C108-F108) | J108: =IF($A$17="","",D108-G108) | K108: =IF($A$17="","",E108-H108) | L108: =IF($A$17="","",IF(AND(ABS(I108)<=10,ABS(J108)<=10,ABS(K108)<=10),"PASS","FAIL"))
...

Sheet Import Checklist
A1: Checklist
A2: Task | B2: Number of Rows to Import | C2: Number of Rows Imported | D2: Import Checked | E2: LC Import Notes | F2: Builder Import Notes | G2: Importer Notes/Issues
A3: If this is not zero - return to builder | B3: =SUM('Strand 3 Checklist'!C16) -> #N/A
A4: Finance codes S3 | B4: =COUNTA(FC_import[FinanceCode]) -> 75 | D4: =IF(B4=C4,TRUE,FALSE) -> FALSE
A5: Calculators | B5: =COUNTA(Calculators[CalculatorEnabled]) -> 94 | D5: =IF(B5=C5,TRUE,FALSE) -> FALSE
A6: Month Profiles | B6: =COUNTA(MONTHPRF[Code]) -> 23 | D6: =IF(B6=C6,TRUE,FALSE) -> FALSE
A7: ScenarioRows | B7: =COUNTA(ScenarioRows[FinanceCode]) -> 58 | D7: =IF(B7=C7,TRUE,FALSE) -> FALSE
A8: ScenarioYearValue | B8: =COUNTA(ScenarioYearValues[FinanceCode]) -> 91 | D8: =IF(B8=C8,TRUE,FALSE) -> FALSE
A9: Set up Scenario for Approved Budget | D9: =IF(B9=C9,TRUE,FALSE) -> TRUE

Sheet System Grouping Codes
A1: groupingCodeCode | B1: title | C1: groupingCodeTypeCode
A2: 510100 | B2: IN: DfE Revenue Grants: GAG (not stud supp and trust grants) | C2: A
A3: 510110 | B3: IN: DfE Revenue Grants: GAG (student support) | C3: A
A4: 510120 | B4: IN: DfE Revenue Grants: GAG (start up grants) | C4: A
A5: 510130 | B5: IN: DfE Revenue Grants: Trust level grants | C5: A
A6: 510140 | B6: IN: DfE Revenue Grants: Pupil number adjustment | C6: A
A7: 510150 | B7: IN: DfE Revenue Grants: Rates reclaim | C7: A
A8: 510200 | B8: IN: DfE Revenue Grants: Pupil Premium | C8: A
A9: 510250 | B9: IN: DfE Revenue Grants: Universal Inf Free School Meals | C9: A
A10: 510300 | B10: IN: DfE Revenue Grants: Insurance top up | C10: A
A11: 510350 | B11: IN: DfE Revenue Grants: Sponsor capacity grant | C11: A
A12: 510400 | B12: IN: DfE Revenue Grants: PE & Sports grant | C12: A
... A509: ZZZ | B509: Not Applicable | C509: ZZZ

Sheet Funds
G1: API - Do not edit
A2: Code is Blank | B2: Title is Blank | C2: Enabled is blank | D2: Code length Check | E2: Title length check | F2: Will import if zero | G2: FundCode | H2: Title | I2: FundEnabled
A3: =ISBLANK(FUNDS[[#This Row],[FundCode]]) -> TRUE | B3: =ISBLANK(FUNDS[[#This Row],[Title]]) -> TRUE | C3: =ISBLANK(FUNDS[[#This Row],[FundEnabled]]) -> FALSE | D3: =IF(LEN(FUNDS[[#This Row],[FundCode]])<100,FALSE,TRUE) -> FALSE | E3: =IF(LEN(FUNDS[[#This Row],[Title]])<100,FALSE,TRUE) -> FALSE | F3: =COUNTIF(FUNDS[[#This Row],[Code is Blank]:[Title length check]],"TRUE") -> 2 | I3: TRUE

Sheet Activity
G1: API - Do not edit
A2: Code is Blank | B2: Title is Blank | C2: Code length Check | D2: Title length check | E2: Enabled is blank | F2: Will import if zero | G2: ActivityCode | H2: Title | I2: ActivityEnabled
A3: =ISBLANK(ACTIVITIES[[#This Row],[ActivityCode]]) -> TRUE | B3: =ISBLANK(ACTIVITIES[[#This Row],[Title]]) -> TRUE | C3: =IF(LEN(ACTIVITIES[[#This Row],[ActivityCode]])<100,FALSE,TRUE) -> FALSE | D3: =IF(LEN(ACTIVITIES[[#This Row],[Title]])<100,FALSE,TRUE) -> FALSE | E3: =ISBLANK(ACTIVITIES[[#This Row],[ActivityEnabled]]) -> FALSE | F3: =COUNTIF(ACTIVITIES[[#This Row],[Code is Blank]:[Enabled is blank]],"TRUE") -> 2 | I3: TRUE

Sheet Ledger
G1: API - Do not edit
A2: Code is Blank | B2: Title is Blank | C2: Enabled is blank | D2: Code length Check | E2: Title length check | F2: Will import if zero | G2: LedgerCode | H2: Title | I2: LedgerEnabled
A3: =ISBLANK(LEDGER[[#This Row],[LedgerCode]]) -> FALSE | B3: =ISBLANK(LEDGER[[#This Row],[Title]]) -> FALSE | C3: =ISBLANK(LEDGER[[#This Row],[LedgerEnabled]]) -> FALSE | D3: =IF(LEN(LEDGER[[#This Row],[LedgerCode]])<100,FALSE,TRUE) -> FALSE | E3: =IF(LEN(LEDGER[[#This Row],[Title]])<100,FALSE,TRUE) -> FALSE | F3: =COUNTIF(LEDGER[[#This Row],[Code is Blank]:[Title length check]],"TRUE") -> 0 | G3: DEFAULT | H3: Default (no) Ledger | I3: TRUE
A4: =ISBLANK(LEDGER[[#This Row],[LedgerCode]]) -> FALSE | B4: =ISBLANK(LEDGER[[#This Row],[Title]]) -> FALSE | C4: =ISBLANK(LEDGER[[#This Row],[LedgerEnabled]]) -> FALSE | D4: =IF(LEN(LEDGER[[#This Row],[LedgerCode]])<100,FALSE,TRUE) -> FALSE | E4: =IF(LEN(LEDGER[[#This Row],[Title]])<100,FALSE,TRUE) -> FALSE | F4: =COUNTIF(LEDGER[[#This Row],[Code is Blank]:[Title length check]],"TRUE") -> 0 | G4: DEPARTMENTS | H4: Departments Ledger | I4: TRUE

Sheet CustGroup
G1: API - Do not edit
A2: Code is Blank | B2: Title is Blank | C2: Code length Check | D2: Title length check | E2: Enabled is blank | F2: Will import if zero | G2: CustomGroupingCode | H2: Title | I2: CustomGroupingEnabled
A3: =ISBLANK(CUSTGROUP[[#This Row],[CustomGroupingCode]]) -> TRUE | B3: =ISBLANK(CUSTGROUP[[#This Row],[Title]]) -> TRUE | C3: =IF(LEN(CUSTGROUP[[#This Row],[CustomGroupingCode]])<100,FALSE,TRUE) -> FALSE | D3: =IF(LEN(CUSTGROUP[[#This Row],[Title]])<100,FALSE,TRUE) -> FALSE | E3: =ISBLANK(CUSTGROUP[[#This Row],[CustomGroupingEnabled]]) -> FALSE | F3: =COUNTIF(CUSTGROUP[[#This Row],[Code is Blank]:[Enabled is blank]],"TRUE") -> 2 | I3: TRUE

Sheet SchHub
G1: API - Do not edit
A2: Code is Blank | B2: Title is Blank | C2: Enabled is blank | D2: Code length Check | E2: Title length check | F2: Will import if zero | G2: SchoolHubCode | H2: Title | I2: SchoolHubEnabled
A3: =ISBLANK(SCHHUB[[#This Row],[SchoolHubCode]]) -> FALSE | B3: =ISBLANK(SCHHUB[[#This Row],[Title]]) -> FALSE | C3: =ISBLANK(SCHHUB[[#This Row],[SchoolHubEnabled]]) -> FALSE | D3: =IF(LEN(SCHHUB[[#This Row],[SchoolHubCode]])<100,FALSE,TRUE) -> FALSE | E3: =IF(LEN(SCHHUB[[#This Row],[Title]])<100,FALSE,TRUE) -> FALSE | F3: =COUNTIF(SCHHUB[[#This Row],[Code is Blank]:[Title length check]],"TRUE") -> 0 | G3: ACADEMY | H3: Academy Schools | I3: TRUE

Sheet SchType
G1: API - Do not edit
A2: Code is Blank | B2: Title is Blank | C2: Enabled is blank | D2: Code length Check | E2: Title length check | F2: Will import if zero | G2: SchoolTypeCode | H2: Title | I2: SchoolTypeEnabled
A3: =ISBLANK(SCHTYPE[[#This Row],[SchoolTypeCode]]) -> FALSE | B3: =ISBLANK(SCHTYPE[[#This Row],[Title]]) -> FALSE | C3: =ISBLANK(SCHTYPE[[#This Row],[SchoolTypeEnabled]]) -> FALSE | D3: =IF(LEN(SCHTYPE[[#This Row],[SchoolTypeCode]])<100,FALSE,TRUE) -> FALSE | E3: =IF(LEN(SCHTYPE[[#This Row],[Title]])<100,FALSE,TRUE) -> FALSE | F3: =COUNTIF(SCHTYPE[[#This Row],[Code is Blank]:[Title length check]],"TRUE") -> 0 | G3: ALLTHROUGH | H3: Allthrough | I3: TRUE
A4: =ISBLANK(SCHTYPE[[#This Row],[SchoolTypeCode]]) -> FALSE | B4: =ISBLANK(SCHTYPE[[#This Row],[Title]]) -> FALSE | C4: =ISBLANK(SCHTYPE[[#This Row],[SchoolTypeEnabled]]) -> FALSE | D4: =IF(LEN(SCHTYPE[[#This Row],[SchoolTypeCode]])<100,FALSE,TRUE) -> FALSE | E4: =IF(LEN(SCHTYPE[[#This Row],[Title]])<100,FALSE,TRUE) -> FALSE | F4: =COUNTIF(SCHTYPE[[#This Row],[Code is Blank]:[Title length check]],"TRUE") -> 0 | G4: CENTRAL | H4: Central Services | I4: TRUE
A5: =ISBLANK(SCHTYPE[[#This Row],[SchoolTypeCode]]) -> FALSE | B5: =ISBLANK(SCHTYPE[[#This Row],[Title]]) -> FALSE | C5: =ISBLANK(SCHTYPE[[#This Row],[SchoolTypeEnabled]]) -> FALSE | D5: =IF(LEN(SCHTYPE[[#This Row],[SchoolTypeCode]])<100,FALSE,TRUE) -> FALSE | E5: =IF(LEN(SCHTYPE[[#This Row],[Title]])<100,FALSE,TRUE) -> FALSE | F5: =COUNTIF(SCHTYPE[[#This Row],[Code is Blank]:[Title length check]],"TRUE") -> 0 | G5: SECONDARY | H5: Secondary | I5: TRUE

Sheet LocalAuth
G1: This grey section can be edited | H1: API - Do not edit
A2: Code is Blank | B2: Title is Blank | C2: Enabled is blank | D2: Code length Check | E2: Title length check | F2: Will import if zero | G2: LA | H2: SchoolLocalAuthorityCode | I2: Title | J2: SchoolLocalAuthorityEnabled | K2: Index
A3: =ISBLANK(LA[[#This Row],[SchoolLocalAuthorityCode]]) -> FALSE | B3: =ISBLANK(LA[[#This Row],[Title]]) -> FALSE | C3: =ISBLANK(LA[[#This Row],[SchoolLocalAuthorityEnabled]]) -> FALSE | D3: =IF(LEN(LA[[#This Row],[SchoolLocalAuthorityCode]])<100,FALSE,TRUE) -> FALSE | E3: =IF(LEN(LA[[#This Row],[Title]])<100,FALSE,TRUE) -> FALSE | F3: =COUNTIF(LA[[#This Row],[Code is Blank]:[Title length check]],"TRUE") -> 0 | G3: =IF(LA[[#This Row],[SchoolLocalAuthorityCode]]="DEFAULT","LA0","LA"&LA[[#This Row],[Index]]) -> LA1 | H3: CLD | I3: Calderdale | J3: TRUE | K3: 1
A4: =ISBLANK(LA[[#This Row],[SchoolLocalAuthorityCode]]) -> FALSE | B4: =ISBLANK(LA[[#This Row],[Title]]) -> FALSE | C4: =ISBLANK(LA[[#This Row],[SchoolLocalAuthorityEnabled]]) -> FALSE | D4: =IF(LEN(LA[[#This Row],[SchoolLocalAuthorityCode]])<100,FALSE,TRUE) -> FALSE | E4: =IF(LEN(LA[[#This Row],[Title]])<100,FALSE,TRUE) -> FALSE | F4: =COUNTIF(LA[[#This Row],[Code is Blank]:[Title length check]],"TRUE") -> 0 | G4: =IF(LA[[#This Row],[SchoolLocalAuthorityCode]]="DEFAULT","LA0","LA"&LA[[#This Row],[Index]]) -> LA0 | H4: DEFAULT | I4: Default (no) Local Authority | J4: TRUE | K4: 2
A5: =ISBLANK(LA[[#This Row],[SchoolLocalAuthorityCode]]) -> FALSE | B5: =ISBLANK(LA[[#This Row],[Title]]) -> FALSE | C5: =ISBLANK(LA[[#This Row],[SchoolLocalAuthorityEnabled]]) -> FALSE | D5: =IF(LEN(LA[[#This Row],[SchoolLocalAuthorityCode]])<100,FALSE,TRUE) -> FALSE | E5: =IF(LEN(LA[[#This Row],[Title]])<100,FALSE,TRUE) -> FALSE | F5: =COUNTIF(LA[[#This Row],[Code is Blank]:[Title length check]],"TRUE") -> 0 | G5: =IF(LA[[#This Row],[SchoolLocalAuthorityCode]]="DEFAULT","LA0","LA"&LA[[#This Row],[Index]]) -> LA3 | H5: KKL | I5: Kirklees | J5: TRUE | K5: 3

Sheet Schools
G1: This grey section can be edited | J1: API - Do not edit
A2: HubIssues | B2: SchTypeIssue | C2: Blank Data | D2: Code length Check | E2: Title length check | F2: Will Import if 0 | G2: London Weighting Type | H2: LA | I2: School Type | J2: SchoolLocalAuthority | K2: SchoolCode | L2: SchoolHub | M2: SchoolType | N2: Title | O2: LondonWeighting | P2: UniqueReferenceNumber | Q2: TeachingHours | R2: SchoolEnabled
A3: =IF(COUNTIF(SCHHUB[SchoolHubCode],SCHOOLS[[#This Row],[SchoolHub]])>0,0,1) -> 1 | B3: =IF(COUNTIF(SCHTYPE[SchoolTypeCode],SCHOOLS[[#This Row],[SchoolType]])>0,0,1) -> 0 | C3: =COUNTBLANK(SCHOOLS[[#This Row],[SchoolLocalAuthority]:[SchoolEnabled]]) -> 0 | D3: =IF(LEN(SCHOOLS[[#This Row],[SchoolCode]])<100,0,1) -> 0 | E3: =IF(LEN(SCHOOLS[[#This Row],[Title]])<100,0,1) -> 0 | F3: =SUM(SCHOOLS[[#This Row],[HubIssues]:[Title length check]]) -> 1 | H3: =_xlfn.XLOOKUP(SCHOOLS[[#This Row],[SchoolLocalAuthority]],LA[SchoolLocalAuthorityCode],LA[LA]) -> LA1 | I3: Central | J3: CLD | K3: TLT | L3: DEFAULT | M3: CENTRAL | N3: Together Learning Trust | O3: FALSE | P3: 1 | Q3: 32.5 | R3: TRUE
A4: =IF(COUNTIF(SCHHUB[SchoolHubCode],SCHOOLS[[#This Row],[SchoolHub]])>0,0,1) -> 1 | B4: =IF(COUNTIF(SCHTYPE[SchoolTypeCode],SCHOOLS[[#This Row],[SchoolType]])>0,0,1) -> 1 | C4: =COUNTBLANK(SCHOOLS[[#This Row],[SchoolLocalAuthority]:[SchoolEnabled]]) -> 0 | D4: =IF(LEN(SCHOOLS[[#This Row],[SchoolCode]])<100,0,1) -> 0 | E4: =IF(LEN(SCHOOLS[[#This Row],[Title]])<100,0,1) -> 0 | F4: =SUM(SCHOOLS[[#This Row],[HubIssues]:[Title length check]]) -> 2 | H4: =_xlfn.XLOOKUP(SCHOOLS[[#This Row],[SchoolLocalAuthority]],LA[SchoolLocalAuthorityCode],LA[LA]) -> LA1 | I4: Primary | J4: CLD | K4: BBP | L4: DEFAULT | M4: PRIMARY | N4: Bolton Brow Primary Academy | O4: FALSE | P4: 137392 | Q4: 32.5 | R4: TRUE
A5: =IF(COUNTIF(SCHHUB[SchoolHubCode],SCHOOLS[[#This Row],[SchoolHub]])>0,0,1) -> 1 | B5: =IF(COUNTIF(SCHTYPE[SchoolTypeCode],SCHOOLS[[#This Row],[SchoolType]])>0,0,1) -> 1 | C5: =COUNTBLANK(SCHOOLS[[#This Row],[SchoolLocalAuthority]:[SchoolEnabled]]) -> 0 | D5: =IF(LEN(SCHOOLS[[#This Row],[SchoolCode]])<100,0,1) -> 0 | E5: =IF(LEN(SCHOOLS[[#This Row],[Title]])<100,0,1) -> 0 | F5: =SUM(SCHOOLS[[#This Row],[HubIssues]:[Title length check]]) -> 2 | H5: =_xlfn.XLOOKUP(SCHOOLS[[#This Row],[SchoolLocalAuthority]],LA[SchoolLocalAuthorityCode],LA[LA]) -> LA3 | I5: Primary | J5: KKL | K5: LCP | L5: DEFAULT | M5: PRIMARY | N5: Linthwaite Clough Primary School | O5: FALSE | P5: 150960 | Q5: 32.5 | R5: TRUE
A6: =IF(COUNTIF(SCHHUB[SchoolHubCode],SCHOOLS[[#This Row],[SchoolHub]])>0,0,1) -> 1 | B6: =IF(COUNTIF(SCHTYPE[SchoolTypeCode],SCHOOLS[[#This Row],[SchoolType]])>0,0,1) -> 1 | C6: =COUNTBLANK(SCHOOLS[[#This Row],[SchoolLocalAuthority]:[SchoolEnabled]]) -> 0 | D6: =IF(LEN(SCHOOLS[[#This Row],[SchoolCode]])<100,0,1) -> 0 | E6: =IF(LEN(SCHOOLS[[#This Row],[Title]])<100,0,1) -> 0 | F6: =SUM(SCHOOLS[[#This Row],[HubIssues]:[Title length check]]) -> 2 | H6: =_xlfn.XLOOKUP(SCHOOLS[[#This Row],[SchoolLocalAuthority]],LA[SchoolLocalAuthorityCode],LA[LA]) -> LA3 | I6: Primary | J6: KKL | K6: MMP | L6: DEFAULT | M6: PRIMARY | N6: Meltham Moor Primary School | O6: FALSE | P6: 146890 | Q6: 32.5 | R6: TRUE
A7: =IF(COUNTIF(SCHHUB[SchoolHubCode],SCHOOLS[[#This Row],[SchoolHub]])>0,0,1) -> 1 | B7: =IF(COUNTIF(SCHTYPE[SchoolTypeCode],SCHOOLS[[#This Row],[SchoolType]])>0,0,1) -> 1 | C7: =COUNTBLANK(SCHOOLS[[#This Row],[SchoolLocalAuthority]:[SchoolEnabled]]) -> 0 | D7: =IF(LEN(SCHOOLS[[#This Row],[SchoolCode]])<100,0,1) -> 0 | E7: =IF(LEN(SCHOOLS[[#This Row],[Title]])<100,0,1) -> 0 | F7: =SUM(SCHOOLS[[#This Row],[HubIssues]:[Title length check]]) -> 2 | H7: =_xlfn.XLOOKUP(SCHOOLS[[#This Row],[SchoolLocalAuthority]],LA[SchoolLocalAuthorityCode],LA[LA]) -> LA3 | I7: Primary | J7: KKL | K7: NIN | L7: DEFAULT | M7: PRIMARY | N7: Netherton Infant and Nursery School | O7: FALSE | P7: 146861 | Q7: 32.5 | R7: TRUE
A8: =IF(COUNTIF(SCHHUB[SchoolHubCode],SCHOOLS[[#This Row],[SchoolHub]])>0,0,1) -> 1 | B8: =IF(COUNTIF(SCHTYPE[SchoolTypeCode],SCHOOLS[[#This Row],[SchoolType]])>0,0,1) -> 1 | C8: =COUNTBLANK(SCHOOLS[[#This Row],[SchoolLocalAuthority]:[SchoolEnabled]]) -> 0 | D8: =IF(LEN(SCHOOLS[[#This Row],[SchoolCode]])<100,0,1) -> 0 | E8: =IF(LEN(SCHOOLS[[#This Row],[Title]])<100,0,1) -> 0 | F8: =SUM(SCHOOLS[[#This Row],[HubIssues]:[Title length check]]) -> 2 | H8: =_xlfn.XLOOKUP(SCHOOLS[[#This Row],[SchoolLocalAuthority]],LA[SchoolLocalAuthorityCode],LA[LA]) -> LA1 | I8: Primary | J8: CLD | K8: SRA | L8: DEFAULT | M8: PRIMARY | N8: Scout Road Academy | O8: FALSE | P8: 137341 | Q8: 32.5 | R8: TRUE
A9: =IF(COUNTIF(SCHHUB[SchoolHubCode],SCHOOLS[[#This Row],[SchoolHub]])>0,0,1) -> 1 | B9: =IF(COUNTIF(SCHTYPE[SchoolTypeCode],SCHOOLS[[#This Row],[SchoolType]])>0,0,1) -> 0 | C9: =COUNTBLANK(SCHOOLS[[#This Row],[SchoolLocalAuthority]:[SchoolEnabled]]) -> 0 | D9: =IF(LEN(SCHOOLS[[#This Row],[SchoolCode]])<100,0,1) -> 0 | E9: =IF(LEN(SCHOOLS[[#This Row],[Title]])<100,0,1) -> 0 | F9: =SUM(SCHOOLS[[#This Row],[HubIssues]:[Title length check]]) -> 1 | H9: =_xlfn.XLOOKUP(SCHOOLS[[#This Row],[SchoolLocalAuthority]],LA[SchoolLocalAuthorityCode],LA[LA]) -> LA1 | I9: Secondary | J9: CLD | K9: BBS | L9: DEFAULT | M9: SECONDARY | N9: The Brooksbank School | O9: FALSE | P9: 149531 | Q9: 32.5 | R9: TRUE
A10: =IF(COUNTIF(SCHHUB[SchoolHubCode],SCHOOLS[[#This Row],[SchoolHub]])>0,0,1) -> 1 | B10: =IF(COUNTIF(SCHTYPE[SchoolTypeCode],SCHOOLS[[#This Row],[SchoolType]])>0,0,1) -> 0 | C10: =COUNTBLANK(SCHOOLS[[#This Row],[SchoolLocalAuthority]:[SchoolEnabled]]) -> 0 | D10: =IF(LEN(SCHOOLS[[#This Row],[SchoolCode]])<100,0,1) -> 0 | E10: =IF(LEN(SCHOOLS[[#This Row],[Title]])<100,0,1) -> 0 | F10: =SUM(SCHOOLS[[#This Row],[HubIssues]:[Title length check]]) -> 1 | H10: =_xlfn.XLOOKUP(SCHOOLS[[#This Row],[SchoolLocalAuthority]],LA[SchoolLocalAuthorityCode],LA[LA]) -> LA3 | I10: Secondary | J10: KKL | K10: HHS | L10: DEFAULT | M10: SECONDARY | N10: Honley High School | O10: FALSE | P10: 146906 | Q10: 32.5 | R10: TRUE
A11: =IF(COUNTIF(SCHHUB[SchoolHubCode],SCHOOLS[[#This Row],[SchoolHub]])>0,0,1) -> 1 | B11: =IF(COUNTIF(SCHTYPE[SchoolTypeCode],SCHOOLS[[#This Row],[SchoolType]])>0,0,1) -> 0 | C11: =COUNTBLANK(SCHOOLS[[#This Row],[SchoolLocalAuthority]:[SchoolEnabled]]) -> 0 | D11: =IF(LEN(SCHOOLS[[#This Row],[SchoolCode]])<100,0,1) -> 0 | E11: =IF(LEN(SCHOOLS[[#This Row],[Title]])<100,0,1) -> 0 | F11: =SUM(SCHOOLS[[#This Row],[HubIssues]:[Title length check]]) -> 1 | H11: =_xlfn.XLOOKUP(SCHOOLS[[#This Row],[SchoolLocalAuthority]],LA[SchoolLocalAuthorityCode],LA[LA]) -> LA1 | I11: Secondary | J11: CLD | K11: RVS | L11: DEFAULT | M11: SECONDARY | N11: Ryburn Valley High School | O11: FALSE | P11: 141307 | Q11: 32.5 | R11: TRUE
A12: =IF(COUNTIF(SCHHUB[SchoolHubCode],SCHOOLS[[#This Row],[SchoolHub]])>0,0,1) -> 1 | B12: =IF(COUNTIF(SCHTYPE[SchoolTypeCode],SCHOOLS[[#This Row],[SchoolType]])>0,0,1) -> 1 | C12: =COUNTBLANK(SCHOOLS[[#This Row],[SchoolLocalAuthority]:[SchoolEnabled]]) -> 0 | D12: =IF(LEN(SCHOOLS[[#This Row],[SchoolCode]])<100,0,1) -> 0 | E12: =IF(LEN(SCHOOLS[[#This Row],[Title]])<100,0,1) -> 0 | F12: =SUM(SCHOOLS[[#This Row],[HubIssues]:[Title length check]]) -> 2 | H12: =_xlfn.XLOOKUP(SCHOOLS[[#This Row],[SchoolLocalAuthority]],LA[SchoolLocalAuthorityCode],LA[LA]) -> LA3 | I12: Special | J12: KKL | K12: CHS | L12: DEFAULT | M12: SPECIAL | N12: Castle Hill School | O12: FALSE | P12: 142420 | Q12: 32.5 | R12: TRUE

Sheet Depts
G1: API - Do not edit
A2: FundIssue | B2: ActivityIssue | C2: LedgerIssue | D2: Code length Check | E2: Title length check | F2: Will Import if 0 | G2: DepartmentCode | H2: Title | I2: AvailableToAllSchools | J2: SchoolCodes | K2: ActivityCode | L2: FundCode | M2: LedgerCode | N2: DefaultFinanceCode | O2: DepartmentEnabled

Sheet 11_Finance Codes S3
A1: LedgerIssue | B1: GroupingCodeIssue | C1: CustGrIssue | D1: SchCodeIssue | E1: DupCode | F1: DupDesc | G1: FCTypeIss | H1: Code length Check | I1: Code Blank Check | J1: Title Blank Check | K1: Title length check | L1: Balance to Scenario Blank | M1: Code is Uppercase | N1: Space in Code | O1: Will Import if 0 | P1: FinanceCode | Q1: Title | R1: FinanceCodeTypeCode | S1: GroupingCode | T1: CustomGrouping | U1: LedgerCode | V1: AvailableToAllSchools | W1: SchoolCodes | X1: FinanceCodeEnabled | Y1: BalanceToScenario | Z1: IsBalanceSheet
A2: =IF(COUNTIF(LEDGER[LedgerCode],FC_import[[#This Row],[LedgerCode]])>0,0,1) -> 0 | B2: =IF(COUNTIF(Table_System_Grouping_Codes[groupingCodeCode],FC_import[[#This Row],[GroupingCode]])>0,0,1) -> 0 | C2: =IF(COUNTIF(CUSTGROUP[CustomGroupingCode],FC_import[[#This Row],[CustomGrouping]])>0,0,1) -> 1 | D2: {=IF(FC_import[[#This Row],[AvailableToAllSchools]]=TRUE,0,COUNTA(_xlfn.TEXTSPLIT(FC_import[[#This Row],[SchoolCodes]],",",,TRUE))-SUM(COUNTIF(SCHOOLS[SchoolCode],_xlfn.TEXTSPLIT(FC_import[[#This Row],[SchoolCodes]],",",,TRUE))))} -> 0 | E2: =IF(FC_import[[#This Row],[FinanceCodeTypeCode]]="BUDGET",0,COUNTIF(P:P,P2)-1) -> 0 | F2: =IF(FC_import[[#This Row],[FinanceCodeTypeCode]]="BUDGET",0,COUNTIF(Q:Q,Q2)-1) -> 0 | G2: =COUNTIF(Lookup!$A$2:$A$7,R2)-1 -> 0 | H2: =IF(LEN(FC_import[[#This Row],[FinanceCode]])<100,0,1) -> 0 | I2: =IF(TRIM(FC_import[[#This Row],[FinanceCode]])="",1,0) -> 0 | J2: =IF(TRIM(FC_import[[#This Row],[Title]])="",1,0) -> 0 | K2: =IF(LEN(FC_import[[#This Row],[Title]])<100,0,1) -> 0 | L2: =IF(ISBLANK(FC_import[[#This Row],[BalanceToScenario]]),1,0) -> 0 | M2: =IF(EXACT(FC_import[[#This Row],[FinanceCode]],UPPER(FC_import[[#This Row],[FinanceCode]])),0,1) -> 0 | N2: =IF(SUBSTITUTE(TEXT(FC_import[[#This Row],[FinanceCode]],10)," ","")=TEXT(FC_import[[#This Row],[FinanceCode]],10),0,1) -> 0 | O2: =SUM(FC_import[[#This Row],[LedgerIssue]:[CustGrIssue]],FC_import[[#This Row],[DupCode]:[Space in Code]]) -> 1 | P2: CAP_BFWD_RES | Q2: Fixed Capital Fund B/F Balances | R2: CAPITALFUND | S2: Z06 | T2: ZZZ | U2: DEFAULT | V2: TRUE | X2: TRUE | Y2: FALSE | Z2: FALSE
A3: =IF(COUNTIF(LEDGER[LedgerCode],FC_import[[#This Row],[LedgerCode]])>0,0,1) -> 0 | B3: =IF(COUNTIF(Table_System_Grouping_Codes[groupingCodeCode],FC_import[[#This Row],[GroupingCode]])>0,0,1) -> 0 | C3: =IF(COUNTIF(CUSTGROUP[CustomGroupingCode],FC_import[[#This Row],[CustomGrouping]])>0,0,1) -> 1 | D3: {=IF(FC_import[[#This Row],[AvailableToAllSchools]]=TRUE,0,COUNTA(_xlfn.TEXTSPLIT(FC_import[[#This Row],[SchoolCodes]],",",,TRUE))-SUM(COUNTIF(SCHOOLS[SchoolCode],_xlfn.TEXTSPLIT(FC_import[[#This Row],[SchoolCodes]],",",,TRUE))))} -> 0 | E3: =IF(FC_import[[#This Row],[FinanceCodeTypeCode]]="BUDGET",0,COUNTIF(P:P,P3)-1) -> 0 | F3: =IF(FC_import[[#This Row],[FinanceCodeTypeCode]]="BUDGET",0,COUNTIF(Q:Q,Q3)-1) -> 0 | G3: =COUNTIF(Lookup!$A$2:$A$7,R3)-1 -> 0 | H3: =IF(LEN(FC_import[[#This Row],[FinanceCode]])<100,0,1) -> 0 | I3: =IF(TRIM(FC_import[[#This Row],[FinanceCode]])="",1,0) -> 0 | J3: =IF(TRIM(FC_import[[#This Row],[Title]])="",1,0) -> 0 | K3: =IF(LEN(FC_import[[#This Row],[Title]])<100,0,1) -> 0 | L3: =IF(ISBLANK(FC_import[[#This Row],[BalanceToScenario]]),1,0) -> 0 | M3: =IF(EXACT(FC_import[[#This Row],[FinanceCode]],UPPER(FC_import[[#This Row],[FinanceCode]])),0,1) -> 0 | N3: =IF(SUBSTITUTE(TEXT(FC_import[[#This Row],[FinanceCode]],10)," ","")=TEXT(FC_import[[#This Row],[FinanceCode]],10),0,1) -> 0 | O3: =SUM(FC_import[[#This Row],[LedgerIssue]:[CustGrIssue]],FC_import[[#This Row],[DupCode]:[Space in Code]]) -> 1 | P3: DFC | Q3: DFC Funding | R3: FUNDING | S3: ZZZ | T3: ZZZ | U3: DEFAULT | V3: TRUE | X3: TRUE | Y3: FALSE | Z3: FALSE
A4: =IF(COUNTIF(LEDGER[LedgerCode],FC_import[[#This Row],[LedgerCode]])>0,0,1) -> 0 | B4: =IF(COUNTIF(Table_System_Grouping_Codes[groupingCodeCode],FC_import[[#This Row],[GroupingCode]])>0,0,1) -> 0 | C4: =IF(COUNTIF(CUSTGROUP[CustomGroupingCode],FC_import[[#This Row],[CustomGrouping]])>0,0,1) -> 1 | D4: {=IF(FC_import[[#This Row],[AvailableToAllSchools]]=TRUE,0,COUNTA(_xlfn.TEXTSPLIT(FC_import[[#This Row],[SchoolCodes]],",",,TRUE))-SUM(COUNTIF(SCHOOLS[SchoolCode],_xlfn.TEXTSPLIT(FC_import[[#This Row],[SchoolCodes]],",",,TRUE))))} -> 0 | E4: =IF(FC_import[[#This Row],[FinanceCodeTypeCode]]="BUDGET",0,COUNTIF(P:P,P4)-1) -> 0 | F4: =IF(FC_import[[#This Row],[FinanceCodeTypeCode]]="BUDGET",0,COUNTIF(Q:Q,Q4)-1) -> 0 | G4: =COUNTIF(Lookup!$A$2:$A$7,R4)-1 -> 0 | H4: =IF(LEN(FC_import[[#This Row],[FinanceCode]])<100,0,1) -> 0 | I4: =IF(TRIM(FC_import[[#This Row],[FinanceCode]])="",1,0) -> 0 | J4: =IF(TRIM(FC_import[[#This Row],[Title]])="",1,0) -> 0 | K4: =IF(LEN(FC_import[[#This Row],[Title]])<100,0,1) -> 0 | L4: =IF(ISBLANK(FC_import[[#This Row],[BalanceToScenario]]),1,0) -> 0 | M4: =IF(EXACT(FC_import[[#This Row],[FinanceCode]],UPPER(FC_import[[#This Row],[FinanceCode]])),0,1) -> 0 | N4: =IF(SUBSTITUTE(TEXT(FC_import[[#This Row],[FinanceCode]],10)," ","")=TEXT(FC_import[[#This Row],[FinanceCode]],10),0,1) -> 0 | O4: =SUM(FC_import[[#This Row],[LedgerIssue]:[CustGrIssue]],FC_import[[#This Row],[DupCode]:[Space in Code]]) -> 1 | P4: DFE_TOTAL | Q4: Total DFE Pre 16 Funding Statement | R4: FUNDING | S4: ZZZ | T4: ZZZ | U4: DEFAULT | V4: TRUE | X4: TRUE | Y4: FALSE | Z4: FALSE
A5: =IF(COUNTIF(LEDGER[LedgerCode],FC_import[[#This Row],[LedgerCode]])>0,0,1) -> 0 | B5: =IF(COUNTIF(Table_System_Grouping_Codes[groupingCodeCode],FC_import[[#This Row],[GroupingCode]])>0,0,1) -> 0 | C5: =IF(COUNTIF(CUSTGROUP[CustomGroupingCode],FC_import[[#This Row],[CustomGrouping]])>0,0,1) -> 1 | D5: {=IF(FC_import[[#This Row],[AvailableToAllSchools]]=TRUE,0,COUNTA(_xlfn.TEXTSPLIT(FC_import[[#This Row],[SchoolCodes]],",",,TRUE))-SUM(COUNTIF(SCHOOLS[SchoolCode],_xlfn.TEXTSPLIT(FC_import[[#This Row],[SchoolCodes]],",",,TRUE))))} -> 0 | E5: =IF(FC_import[[#This Row],[FinanceCodeTypeCode]]="BUDGET",0,COUNTIF(P:P,P5)-1) -> 0 | F5: =IF(FC_import[[#This Row],[FinanceCodeTypeCode]]="BUDGET",0,COUNTIF(Q:Q,Q5)-1) -> 0 | G5: =COUNTIF(Lookup!$A$2:$A$7,R5)-1 -> 0 | H5: =IF(LEN(FC_import[[#This Row],[FinanceCode]])<100,0,1) -> 0 | I5: =IF(TRIM(FC_import[[#This Row],[FinanceCode]])="",1,0) -> 0 | J5: =IF(TRIM(FC_import[[#This Row],[Title]])="",1,0) -> 0 | K5: =IF(LEN(FC_import[[#This Row],[Title]])<100,0,1) -> 0 | L5: =IF(ISBLANK(FC_import[[#This Row],[BalanceToScenario]]),1,0) -> 0 | M5: =IF(EXACT(FC_import[[#This Row],[FinanceCode]],UPPER(FC_import[[#This Row],[FinanceCode]])),0,1) -> 0 | N5: =IF(SUBSTITUTE(TEXT(FC_import[[#This Row],[FinanceCode]],10)," ","")=TEXT(FC_import[[#This Row],[FinanceCode]],10),0,1) -> 0 | O5: =SUM(FC_import[[#This Row],[LedgerIssue]:[CustGrIssue]],FC_import[[#This Row],[DupCode]:[Space in Code]]) -> 1 | P5: FUNDING_GAG | Q5: Funding GAG | R5: FUNDING | S5: ZZZ | T5: ZZZ | U5: DEFAULT | V5: TRUE | X5: TRUE | Y5: FALSE | Z5: FALSE
A6: =IF(COUNTIF(LEDGER[LedgerCode],FC_import[[#This Row],[LedgerCode]])>0,0,1) -> 0 | B6: =IF(COUNTIF(Table_System_Grouping_Codes[groupingCodeCode],FC_import[[#This Row],[GroupingCode]])>0,0,1) -> 0 | C6: =IF(COUNTIF(CUSTGROUP[CustomGroupingCode],FC_import[[#This Row],[CustomGrouping]])>0,0,1) -> 1 | D6: {=IF(FC_import[[#This Row],[AvailableToAllSchools]]=TRUE,0,COUNTA(_xlfn.TEXTSPLIT(FC_import[[#This Row],[SchoolCodes]],",",,TRUE))-SUM(COUNTIF(SCHOOLS[SchoolCode],_xlfn.TEXTSPLIT(FC_import[[#This Row],[SchoolCodes]],",",,TRUE))))} -> 0 | E6: =IF(FC_import[[#This Row],[FinanceCodeTypeCode]]="BUDGET",0,COUNTIF(P:P,P6)-1) -> 0 | F6: =IF(FC_import[[#This Row],[FinanceCodeTypeCode]]="BUDGET",0,COUNTIF(Q:Q,Q6)-1) -> 0 | G6: =COUNTIF(Lookup!$A$2:$A$7,R6)-1 -> 0 | H6: =IF(LEN(FC_import[[#This Row],[FinanceCode]])<100,0,1) -> 0 | I6: =IF(TRIM(FC_import[[#This Row],[FinanceCode]])="",1,0) -> 0 | J6: =IF(TRIM(FC_import[[#This Row],[Title]])="",1,0) -> 0 | K6: =IF(LEN(FC_import[[#This Row],[Title]])<100,0,1) -> 0 | L6: =IF(ISBLANK(FC_import[[#This Row],[BalanceToScenario]]),1,0) -> 0 | M6: =IF(EXACT(FC_import[[#This Row],[FinanceCode]],UPPER(FC_import[[#This Row],[FinanceCode]])),0,1) -> 0 | N6: =IF(SUBSTITUTE(TEXT(FC_import[[#This Row],[FinanceCode]],10)," ","")=TEXT(FC_import[[#This Row],[FinanceCode]],10),0,1) -> 0 | O6: =SUM(FC_import[[#This Row],[LedgerIssue]:[CustGrIssue]],FC_import[[#This Row],[DupCode]:[Space in Code]]) -> 1 | P6: FUNDING_HNPRE16 | Q6: Funding Statement Unoccupied Pre 16 Special Provision | R6: FUNDING | S6: ZZZ | T6: ZZZ | U6: DEFAULT | V6: TRUE | X6: TRUE | Y6: FALSE | Z6: FALSE
A7: =IF(COUNTIF(LEDGER[LedgerCode],FC_import[[#This Row],[LedgerCode]])>0,0,1) -> 0 | B7: =IF(COUNTIF(Table_System_Grouping_Codes[groupingCodeCode],FC_import[[#This Row],[GroupingCode]])>0,0,1) -> 0 | C7: =IF(COUNTIF(CUSTGROUP[CustomGroupingCode],FC_import[[#This Row],[CustomGrouping]])>0,0,1) -> 1 | D7: {=IF(FC_import[[#This Row],[AvailableToAllSchools]]=TRUE,0,COUNTA(_xlfn.TEXTSPLIT(FC_import[[#This Row],[SchoolCodes]],",",,TRUE))-SUM(COUNTIF(SCHOOLS[SchoolCode],_xlfn.TEXTSPLIT(FC_import[[#This Row],[SchoolCodes]],",",,TRUE))))} -> 0 | E7: =IF(FC_import[[#This Row],[FinanceCodeTypeCode]]="BUDGET",0,COUNTIF(P:P,P7)-1) -> 0 | F7: =IF(FC_import[[#This Row],[FinanceCodeTypeCode]]="BUDGET",0,COUNTIF(Q:Q,Q7)-1) -> 0 | G7: =COUNTIF(Lookup!$A$2:$A$7,R7)-1 -> 0 | H7: =IF(LEN(FC_import[[#This Row],[FinanceCode]])<100,0,1) -> 0 | I7: =IF(TRIM(FC_import[[#This Row],[FinanceCode]])="",1,0) -> 0 | J7: =IF(TRIM(FC_import[[#This Row],[Title]])="",1,0) -> 0 | K7: =IF(LEN(FC_import[[#This Row],[Title]])<100,0,1) -> 0 | L7: =IF(ISBLANK(FC_import[[#This Row],[BalanceToScenario]]),1,0) -> 0 | M7: =IF(EXACT(FC_import[[#This Row],[FinanceCode]],UPPER(FC_import[[#This Row],[FinanceCode]])),0,1) -> 0 | N7: =IF(SUBSTITUTE(TEXT(FC_import[[#This Row],[FinanceCode]],10)," ","")=TEXT(FC_import[[#This Row],[FinanceCode]],10),0,1) -> 0 | O7: =SUM(FC_import[[#This Row],[LedgerIssue]:[CustGrIssue]],FC_import[[#This Row],[DupCode]:[Space in Code]]) -> 1 | P7: FUNDING_HNPRE16O | Q7: Funding Statement Occupied Pre 16 Special Provision | R7: FUNDING | S7: ZZZ | T7: ZZZ | U7: DEFAULT | V7: TRUE | X7: TRUE | Y7: FALSE | Z7: FALSE
A8: =IF(COUNTIF(LEDGER[LedgerCode],FC_import[[#This Row],[LedgerCode]])>0,0,1) -> 0 | B8: =IF(COUNTIF(Table_System_Grouping_Codes[groupingCodeCode],FC_import[[#This Row],[GroupingCode]])>0,0,1) -> 0 | C8: =IF(COUNTIF(CUSTGROUP[CustomGroupingCode],FC_import[[#This Row],[CustomGrouping]])>0,0,1) -> 1 | D8: {=IF(FC_import[[#This Row],[AvailableToAllSchools]]=TRUE,0,COUNTA(_xlfn.TEXTSPLIT(FC_import[[#This Row],[SchoolCodes]],",",,TRUE))-SUM(COUNTIF(SCHOOLS[SchoolCode],_xlfn.TEXTSPLIT(FC_import[[#This Row],[SchoolCodes]],",",,TRUE))))} -> 0 | E8: =IF(FC_import[[#This Row],[FinanceCodeTypeCode]]="BUDGET",0,COUNTIF(P:P,P8)-1) -> 0 | F8: =IF(FC_import[[#This Row],[FinanceCodeTypeCode]]="BUDGET",0,COUNTIF(Q:Q,Q8)-1) -> 0 | G8: =COUNTIF(Lookup!$A$2:$A$7,R8)-1 -> 0 | H8: =IF(LEN(FC_import[[#This Row],[FinanceCode]])<100,0,1) -> 0 | I8: =IF(TRIM(FC_import[[#This Row],[FinanceCode]])="",1,0) -> 0 | J8: =IF(TRIM(FC_import[[#This Row],[Title]])="",1,0) -> 0 | K8: =IF(LEN(FC_import[[#This Row],[Title]])<100,0,1) -> 0 | L8: =IF(ISBLANK(FC_import[[#This Row],[BalanceToScenario]]),1,0) -> 0 | M8: =IF(EXACT(FC_import[[#This Row],[FinanceCode]],UPPER(FC_import[[#This Row],[FinanceCode]])),0,1) -> 0 | N8: =IF(SUBSTITUTE(TEXT(FC_import[[#This Row],[FinanceCode]],10)," ","")=TEXT(FC_import[[#This Row],[FinanceCode]],10),0,1) -> 0 | O8: =SUM(FC_import[[#This Row],[LedgerIssue]:[CustGrIssue]],FC_import[[#This Row],[DupCode]:[Space in Code]]) -> 1 | P8: FUNDING_PUPPREM_PLAC | Q8: Pupil Premium Post Looked After Children Income | R8: FUNDING | S8: ZZZ | T8: ZZZ | U8: DEFAULT | V8: TRUE | X8: TRUE | Y8: FALSE | Z8: FALSE
A9: =IF(COUNTIF(LEDGER[LedgerCode],FC_import[[#This Row],[LedgerCode]])>0,0,1) -> 0 | B9: =IF(COUNTIF(Table_System_Grouping_Codes[groupingCodeCode],FC_import[[#This Row],[GroupingCode]])>0,0,1) -> 0 | C9: =IF(COUNTIF(CUSTGROUP[CustomGroupingCode],FC_import[[#This Row],[CustomGrouping]])>0,0,1) -> 1 | D9: {=IF(FC_import[[#This Row],[AvailableToAllSchools]]=TRUE,0,COUNTA(_xlfn.TEXTSPLIT(FC_import[[#This Row],[SchoolCodes]],",",,TRUE))-SUM(COUNTIF(SCHOOLS[SchoolCode],_xlfn.TEXTSPLIT(FC_import[[#This Row],[SchoolCodes]],",",,TRUE))))} -> 0 | E9: =IF(FC_import[[#This Row],[FinanceCodeTypeCode]]="BUDGET",0,COUNTIF(P:P,P9)-1) -> 0 | F9: =IF(FC_import[[#This Row],[FinanceCodeTypeCode]]="BUDGET",0,COUNTIF(Q:Q,Q9)-1) -> 0 | G9: =COUNTIF(Lookup!$A$2:$A$7,R9)-1 -> 0 | H9: =IF(LEN(FC_import[[#This Row],[FinanceCode]])<100,0,1) -> 0 | I9: =IF(TRIM(FC_import[[#This Row],[FinanceCode]])="",1,0) -> 0 | J9: =IF(TRIM(FC_import[[#This Row],[Title]])="",1,0) -> 0 | K9: =IF(LEN(FC_import[[#This Row],[Title]])<100,0,1) -> 0 | L9: =IF(ISBLANK(FC_import[[#This Row],[BalanceToScenario]]),1,0) -> 0 | M9: =IF(EXACT(FC_import[[#This Row],[FinanceCode]],UPPER(FC_import[[#This Row],[FinanceCode]])),0,1) -> 0 | N9: =IF(SUBSTITUTE(TEXT(FC_import[[#This Row],[FinanceCode]],10)," ","")=TEXT(FC_import[[#This Row],[FinanceCode]],10),0,1) -> 0 | O9: =SUM(FC_import[[#This Row],[LedgerIssue]:[CustGrIssue]],FC_import[[#This Row],[DupCode]:[Space in Code]]) -> 1 | P9: FUNDING_PUPPREM_PRI | Q9: Pupil Premium Income Primary | R9: FUNDING | S9: ZZZ | T9: ZZZ | U9: DEFAULT | V9: TRUE | X9: TRUE | Y9: FALSE | Z9: FALSE
A10: =IF(COUNTIF(LEDGER[LedgerCode],FC_import[[#This Row],[LedgerCode]])>0,0,1) -> 0 | B10: =IF(COUNTIF(Table_System_Grouping_Codes[groupingCodeCode],FC_import[[#This Row],[GroupingCode]])>0,0,1) -> 0 | C10: =IF(COUNTIF(CUSTGROUP[CustomGroupingCode],FC_import[[#This Row],[CustomGrouping]])>0,0,1) -> 1 | D10: {=IF(FC_import[[#This Row],[AvailableToAllSchools]]=TRUE,0,COUNTA(_xlfn.TEXTSPLIT(FC_import[[#This Row],[SchoolCodes]],",",,TRUE))-SUM(COUNTIF(SCHOOLS[SchoolCode],_xlfn.TEXTSPLIT(FC_import[[#This Row],[SchoolCodes]],",",,TRUE))))} -> 0 | E10: =IF(FC_import[[#This Row],[FinanceCodeTypeCode]]="BUDGET",0,COUNTIF(P:P,P10)-1) -> 0 | F10: =IF(FC_import[[#This Row],[FinanceCodeTypeCode]]="BUDGET",0,COUNTIF(Q:Q,Q10)-1) -> 0 | G10: =COUNTIF(Lookup!$A$2:$A$7,R10)-1 -> 0 | H10: =IF(LEN(FC_import[[#This Row],[FinanceCode]])<100,0,1) -> 0 | I10: =IF(TRIM(FC_import[[#This Row],[FinanceCode]])="",1,0) -> 0 | J10: =IF(TRIM(FC_import[[#This Row],[Title]])="",1,0) -> 0 | K10: =IF(LEN(FC_import[[#This Row],[Title]])<100,0,1) -> 0 | L10: =IF(ISBLANK(FC_import[[#This Row],[BalanceToScenario]]),1,0) -> 0 | M10: =IF(EXACT(FC_import[[#This Row],[FinanceCode]],UPPER(FC_import[[#This Row],[FinanceCode]])),0,1) -> 0 | N10: =IF(SUBSTITUTE(TEXT(FC_import[[#This Row],[FinanceCode]],10)," ","")=TEXT(FC_import[[#This Row],[FinanceCode]],10),0,1) -> 0 | O10: =SUM(FC_import[[#This Row],[LedgerIssue]:[CustGrIssue]],FC_import[[#This Row],[DupCode]:[Space in Code]]) -> 1 | P10: FUNDING_PUPPREM_SER | Q10: Pupil Premium Service Children Income | R10: FUNDING | S10: ZZZ | T10: ZZZ | U10: DEFAULT | V10: TRUE | X10: TRUE | Y10: FALSE | Z10: FALSE
A11: =IF(COUNTIF(LEDGER[LedgerCode],FC_import[[#This Row],[LedgerCode]])>0,0,1) -> 0 | B11: =IF(COUNTIF(Table_System_Grouping_Codes[groupingCodeCode],FC_import[[#This Row],[GroupingCode]])>0,0,1) -> 0 | C11: =IF(COUNTIF(CUSTGROUP[CustomGroupingCode],FC_import[[#This Row],[CustomGrouping]])>0,0,1) -> 1 | D11: {=IF(FC_import[[#This Row],[AvailableToAllSchools]]=TRUE,0,COUNTA(_xlfn.TEXTSPLIT(FC_import[[#This Row],[SchoolCodes]],",",,TRUE))-SUM(COUNTIF(SCHOOLS[SchoolCode],_xlfn.TEXTSPLIT(FC_import[[#This Row],[SchoolCodes]],",",,TRUE))))} -> 0 | E11: =IF(FC_import[[#This Row],[FinanceCodeTypeCode]]="BUDGET",0,COUNTIF(P:P,P11)-1) -> 0 | F11: =IF(FC_import[[#This Row],[FinanceCodeTypeCode]]="BUDGET",0,COUNTIF(Q:Q,Q11)-1) -> 0 | G11: =COUNTIF(Lookup!$A$2:$A$7,R11)-1 -> 0 | H11: =IF(LEN(FC_import[[#This Row],[FinanceCode]])<100,0,1) -> 0 | I11: =IF(TRIM(FC_import[[#This Row],[FinanceCode]])="",1,0) -> 0 | J11: =IF(TRIM(FC_import[[#This Row],[Title]])="",1,0) -> 0 | K11: =IF(LEN(FC_import[[#This Row],[Title]])<100,0,1) -> 0 | L11: =IF(ISBLANK(FC_import[[#This Row],[BalanceToScenario]]),1,0) -> 0 | M11: =IF(EXACT(FC_import[[#This Row],[FinanceCode]],UPPER(FC_import[[#This Row],[FinanceCode]])),0,1) -> 0 | N11: =IF(SUBSTITUTE(TEXT(FC_import[[#This Row],[FinanceCode]],10)," ","")=TEXT(FC_import[[#This Row],[FinanceCode]],10),0,1) -> 0 | O11: =SUM(FC_import[[#This Row],[LedgerIssue]:[CustGrIssue]],FC_import[[#This Row],[DupCode]:[Space in Code]]) -> 1 | P11: PE_GRANT | Q11: PE Grant Allocation | R11: FUNDING | S11: ZZZ | T11: ZZZ | U11: DEFAULT | V11: TRUE | X11: TRUE | Y11: FALSE | Z11: FALSE
A12: =IF(COUNTIF(LEDGER[LedgerCode],FC_import[[#This Row],[LedgerCode]])>0,0,1) -> 0 | B12: =IF(COUNTIF(Table_System_Grouping_Codes[groupingCodeCode],FC_import[[#This Row],[GroupingCode]])>0,0,1) -> 0 | C12: =IF(COUNTIF(CUSTGROUP[CustomGroupingCode],FC_import[[#This Row],[CustomGrouping]])>0,0,1) -> 1 | D12: {=IF(FC_import[[#This Row],[AvailableToAllSchools]]=TRUE,0,COUNTA(_xlfn.TEXTSPLIT(FC_import[[#This Row],[SchoolCodes]],",",,TRUE))-SUM(COUNTIF(SCHOOLS[SchoolCode],_xlfn.TEXTSPLIT(FC_import[[#This Row],[SchoolCodes]],",",,TRUE))))} -> 0 | E12: =IF(FC_import[[#This Row],[FinanceCodeTypeCode]]="BUDGET",0,COUNTIF(P:P,P12)-1) -> 0 | F12: =IF(FC_import[[#This Row],[FinanceCodeTypeCode]]="BUDGET",0,COUNTIF(Q:Q,Q12)-1) -> 0 | G12: =COUNTIF(Lookup!$A$2:$A$7,R12)-1 -> 0 | H12: =IF(LEN(FC_import[[#This Row],[FinanceCode]])<100,0,1) -> 0 | I12: =IF(TRIM(FC_import[[#This Row],[FinanceCode]])="",1,0) -> 0 | J12: =IF(TRIM(FC_import[[#This Row],[Title]])="",1,0) -> 0 | K12: =IF(LEN(FC_import[[#This Row],[Title]])<100,0,1) -> 0 | L12: =IF(ISBLANK(FC_import[[#This Row],[BalanceToScenario]]),1,0) -> 0 | M12: =IF(EXACT(FC_import[[#This Row],[FinanceCode]],UPPER(FC_import[[#This Row],[FinanceCode]])),0,1) -> 0 | N12: =IF(SUBSTITUTE(TEXT(FC_import[[#This Row],[FinanceCode]],10)," ","")=TEXT(FC_import[[#This Row],[FinanceCode]],10),0,1) -> 0 | O12: =SUM(FC_import[[#This Row],[LedgerIssue]:[CustGrIssue]],FC_import[[#This Row],[DupCode]:[Space in Code]]) -> 1 | P12: UIFSM_ANNUAL | Q12: UIFSM - Annual calc | R12: FUNDING | S12: ZZZ | T12: ZZZ | U12: DEFAULT | V12: TRUE | X12: TRUE | Y12: FALSE | Z12: FALSE
A13: =IF(COUNTIF(LEDGER[LedgerCode],FC_import[[#This Row],[LedgerCode]])>0,0,1) -> 0 | B13: =IF(COUNTIF(Table_System_Grouping_Codes[groupingCodeCode],FC_import[[#This Row],[GroupingCode]])>0,0,1) -> 0 | C13: =IF(COUNTIF(CUSTGROUP[CustomGroupingCode],FC_import[[#This Row],[CustomGrouping]])>0,0,1) -> 1 | D13: {=IF(FC_import[[#This Row],[AvailableToAllSchools]]=TRUE,0,COUNTA(_xlfn.TEXTSPLIT(FC_import[[#This Row],[SchoolCodes]],",",,TRUE))-SUM(COUNTIF(SCHOOLS[SchoolCode],_xlfn.TEXTSPLIT(FC_import[[#This Row],[SchoolCodes]],",",,TRUE))))} -> 0 | E13: =IF(FC_import[[#This Row],[FinanceCodeTypeCode]]="BUDGET",0,COUNTIF(P:P,P13)-1) -> 0 | F13: =IF(FC_import[[#This Row],[FinanceCodeTypeCode]]="BUDGET",0,COUNTIF(Q:Q,Q13)-1) -> 0 | G13: =COUNTIF(Lookup!$A$2:$A$7,R13)-1 -> 0 | H13: =IF(LEN(FC_import[[#This Row],[FinanceCode]])<100,0,1) -> 0 | I13: =IF(TRIM(FC_import[[#This Row],[FinanceCode]])="",1,0) -> 0 | J13: =IF(TRIM(FC_import[[#This Row],[Title]])="",1,0) -> 0 | K13: =IF(LEN(FC_import[[#This Row],[Title]])<100,0,1) -> 0 | L13: =IF(ISBLANK(FC_import[[#This Row],[BalanceToScenario]]),1,0) -> 0 | M13: =IF(EXACT(FC_import[[#This Row],[FinanceCode]],UPPER(FC_import[[#This Row],[FinanceCode]])),0,1) -> 0 | N13: =IF(SUBSTITUTE(TEXT(FC_import[[#This Row],[FinanceCode]],10)," ","")=TEXT(FC_import[[#This Row],[FinanceCode]],10),0,1) -> 0 | O13: =SUM(FC_import[[#This Row],[LedgerIssue]:[CustGrIssue]],FC_import[[#This Row],[DupCode]:[Space in Code]]) -> 1 | P13: UIFSM_FIN | Q13: UIFSM - Final Payment | R13: FUNDING | S13: ZZZ | T13: ZZZ | U13: DEFAULT | V13: TRUE | X13: TRUE | Y13: FALSE | Z13: FALSE
... A76: =IF(COUNTIF(LEDGER[LedgerCode],FC_import[[#This Row],[LedgerCode]])>0,0,1) -> 0 | B76: =IF(COUNTIF(Table_System_Grouping_Codes[groupingCodeCode],FC_import[[#This Row],[GroupingCode]])>0,0,1) -> 0 | C76: =IF(COUNTIF(CUSTGROUP[CustomGroupingCode],FC_import[[#This Row],[CustomGrouping]])>0,0,1) -> 1 | D76: {=IF(FC_import[[#This Row],[AvailableToAllSchools]]=TRUE,0,COUNTA(_xlfn.TEXTSPLIT(FC_import[[#This Row],[SchoolCodes]],",",,TRUE))-SUM(COUNTIF(SCHOOLS[SchoolCode],_xlfn.TEXTSPLIT(FC_import[[#This Row],[SchoolCodes]],",",,TRUE))))} -> 0 | E76: =IF(FC_import[[#This Row],[FinanceCodeTypeCode]]="BUDGET",0,COUNTIF(P:P,P76)-1) -> 0 | F76: =IF(FC_import[[#This Row],[FinanceCodeTypeCode]]="BUDGET",0,COUNTIF(Q:Q,Q76)-1) -> 0 | G76: =COUNTIF(Lookup!$A$2:$A$7,R76)-1 -> 0 | H76: =IF(LEN(FC_import[[#This Row],[FinanceCode]])<100,0,1) -> 0 | I76: =IF(TRIM(FC_import[[#This Row],[FinanceCode]])="",1,0) -> 0 | J76: =IF(TRIM(FC_import[[#This Row],[Title]])="",1,0) -> 0 | K76: =IF(LEN(FC_import[[#This Row],[Title]])<100,0,1) -> 0 | L76: =IF(ISBLANK(FC_import[[#This Row],[BalanceToScenario]]),1,0) -> 0 | M76: =IF(EXACT(FC_import[[#This Row],[FinanceCode]],UPPER(FC_import[[#This Row],[FinanceCode]])),0,1) -> 0 | N76: =IF(SUBSTITUTE(TEXT(FC_import[[#This Row],[FinanceCode]],10)," ","")=TEXT(FC_import[[#This Row],[FinanceCode]],10),0,1) -> 0 | O76: =SUM(FC_import[[#This Row],[LedgerIssue]:[CustGrIssue]],FC_import[[#This Row],[DupCode]:[Space in Code]]) -> 1 | P76: UPLIFT_TEACH | Q76: Teacher Uplifts | R76: STATISTICS | S76: ZZZ | T76: ZZZ | U76: DEFAULT | V76: TRUE | X76: TRUE | Y76: FALSE | Z76: FALSE

Sheet SourceFinanceCodes
A1: School Type | B1: LA | C1: London Weighting | D1: Key stage | E1: FinanceCode | F1: Title | G1: FinanceCodeTypeCode | H1: GroupingCode2 | I1: CustomGrouping | J1: LedgerCode | K1: AvailableToAllSchools | L1: SchoolCodes | M1: FinanceCodeEnabled | N1: BalanceToScenario | O1: IsBalanceSheet
A2: All | E2: CAP_BFWD_RES | F2: Fixed Capital Fund B/F Balances | G2: CAPITALFUND | H2: Z06 | I2: ZZZ | J2: DEFAULT | K2: TRUE | M2: TRUE | N2: FALSE | O2: FALSE
A3: All | E3: DFC | F3: DFC Funding | G3: FUNDING | H3: ZZZ | I3: ZZZ | J3: DEFAULT | K3: TRUE | M3: TRUE | N3: FALSE | O3: FALSE
A4: All | E4: DFE_TOTAL | F4: Total DFE Pre 16 Funding Statement | G4: FUNDING | H4: ZZZ | I4: ZZZ | J4: DEFAULT | K4: TRUE | M4: TRUE | N4: FALSE | O4: FALSE
A5: All | E5: FUNDING_GAG | F5: Funding GAG | G5: FUNDING | H5: ZZZ | I5: ZZZ | J5: DEFAULT | K5: TRUE | M5: TRUE | N5: FALSE | O5: FALSE
A6: All | E6: FUNDING_HNPRE16 | F6: Funding Statement Unoccupied Pre 16 Special Provision | G6: FUNDING | H6: ZZZ | I6: ZZZ | J6: DEFAULT | K6: TRUE | M6: TRUE | N6: FALSE | O6: FALSE
A7: All | E7: FUNDING_HNPRE16O | F7: Funding Statement Occupied Pre 16 Special Provision | G7: FUNDING | H7: ZZZ | I7: ZZZ | J7: DEFAULT | K7: TRUE | M7: TRUE | N7: FALSE | O7: FALSE
A8: All | E8: FUNDING_PUPPREM_PLAC | F8: Pupil Premium Post Looked After Children Income | G8: FUNDING | H8: ZZZ | I8: ZZZ | J8: DEFAULT | K8: TRUE | M8: TRUE | N8: FALSE | O8: FALSE
A9: All | E9: FUNDING_PUPPREM_SER | F9: Pupil Premium Service Children Income | G9: FUNDING | H9: ZZZ | I9: ZZZ | J9: DEFAULT | K9: TRUE | M9: TRUE | N9: FALSE | O9: FALSE
A10: All | E10: PUPILPREMIUMPLAC | F10: Pupil Premium Post Looked After Children Numbers | G10: PUPILNUMBERS | H10: Z12 | I10: ZZZ | J10: DEFAULT | K10: TRUE | M10: TRUE | N10: FALSE | O10: FALSE
A11: All | E11: PUPILPREMIUMSER | F11: Pupil Premium Service Children Numbers | G11: PUPILNUMBERS | H11: Z12 | I11: ZZZ | J11: DEFAULT | K11: TRUE | M11: TRUE | N11: FALSE | O11: FALSE
A12: All | E12: REV_BFWD_RES | F12: Fixed Revenue Fund B/F Balances | G12: REVENUEFUND | H12: Z06 | I12: ZZZ | J12: DEFAULT | K12: TRUE | M12: TRUE | N12: FALSE | O12: FALSE
A13: All | E13: BFWD_RES | F13: Brought Forward Reserves | G13: STATISTICS | H13: Z01 | I13: ZZZ | J13: DEFAULT | K13: TRUE | M13: TRUE | N13: FALSE | O13: FALSE
... A91: AllThrough | E91: PUPILPREMIUM_SEC | F91: Pupil Premium Numbers Secondary | G91: PUPILNUMBERS | H91: Z12 | I91: ZZZ | J91: DEFAULT | K91: TRUE | M91: TRUE | N91: FALSE | O91: FALSE
A92: AllThrough | B92: LA1 | D92: PRI | E92: AWPU01 | F92: AWPU-PRI- | G92: STATISTICS | H92: ZZZ | I92: ZZZ | J92: DEFAULT | K92: TRUE | M92: TRUE | N92: FALSE | O92: FALSE
A93: AllThrough | B93: LA2 | D93: PRI | E93: AWPU01 | F93: AWPU-PRI- | G93: STATISTICS | H93: ZZZ | I93: ZZZ | J93: DEFAULT | K93: TRUE | M93: TRUE | N93: FALSE | O93: FALSE
A94: AllThrough | B94: LA3 | D94: PRI | E94: AWPU01 | F94: AWPU-PRI- | G94: STATISTICS | H94: ZZZ | I94: ZZZ | J94: DEFAULT | K94: TRUE | M94: TRUE | N94: FALSE | O94: FALSE
A95: AllThrough | B95: LA4 | D95: PRI | E95: AWPU01 | F95: AWPU-PRI- | G95: STATISTICS | H95: ZZZ | I95: ZZZ | J95: DEFAULT | K95: TRUE | M95: TRUE | N95: FALSE | O95: FALSE
A96: AllThrough | B96: LA5 | D96: PRI | E96: AWPU01 | F96: AWPU-PRI- | G96: STATISTICS | H96: ZZZ | I96: ZZZ | J96: DEFAULT | K96: TRUE | M96: TRUE | N96: FALSE | O96: FALSE
A97: AllThrough | B97: LA6 | D97: PRI | E97: AWPU01 | F97: AWPU-PRI- | G97: STATISTICS | H97: ZZZ | I97: ZZZ | J97: DEFAULT | K97: TRUE | M97: TRUE | N97: FALSE | O97: FALSE
A98: AllThrough | B98: LA7 | D98: PRI | E98: AWPU01 | F98: AWPU-PRI- | G98: STATISTICS | H98: ZZZ | I98: ZZZ | J98: DEFAULT | K98: TRUE | M98: TRUE | N98: FALSE | O98: FALSE
A99: AllThrough | B99: LA8 | D99: PRI | E99: AWPU01 | F99: AWPU-PRI- | G99: STATISTICS | H99: ZZZ | I99: ZZZ | J99: DEFAULT | K99: TRUE | M99: TRUE | N99: FALSE | O99: FALSE
A100: AllThrough | B100: LA9 | D100: PRI | E100: AWPU01 | F100: AWPU-PRI- | G100: STATISTICS | H100: ZZZ | I100: ZZZ | J100: DEFAULT | K100: TRUE | M100: TRUE | N100: FALSE | O100: FALSE
A101: AllThrough | B101: LA10 | D101: PRI | E101: AWPU01 | F101: AWPU-PRI- | G101: STATISTICS | H101: ZZZ | I101: ZZZ | J101: DEFAULT | K101: TRUE | M101: TRUE | N101: FALSE | O101: FALSE
A102: AllThrough | B102: LA11 | D102: PRI | E102: AWPU01 | F102: AWPU-PRI- | G102: STATISTICS | H102: ZZZ | I102: ZZZ | J102: DEFAULT | K102: TRUE | M102: TRUE | N102: FALSE | O102: FALSE
A103: AllThrough | B103: LA12 | D103: PRI | E103: AWPU01 | F103: AWPU-PRI- | G103: STATISTICS | H103: ZZZ | I103: ZZZ | J103: DEFAULT | K103: TRUE | M103: TRUE | N103: FALSE | O103: FALSE
... A127: AllThrough | B127: LA12 | D127: KS4 | E127: AWPU03 | F127: AWPU-KS4 - | G127: STATISTICS | H127: ZZZ | I127: ZZZ | J127: DEFAULT | K127: TRUE | M127: TRUE | N127: FALSE | O127: FALSE
A128: AllThrough | E128: DFC_PUPIL_NUR | F128: DFC Primary Nursery | G128: STATISTICS | H128: ZZZ | I128: ZZZ | J128: DEFAULT | K128: TRUE | M128: TRUE | N128: FALSE | O128: FALSE
A129: AllThrough | E129: DFC_PUPIL_POST16 | F129: DFC Post16 Pupil | G129: STATISTICS | H129: ZZZ | I129: ZZZ | J129: DEFAULT | K129: TRUE | M129: TRUE | N129: FALSE | O129: FALSE
A130: AllThrough | E130: DFC_PUPIL_PRI | F130: DFC Primary Pupil | G130: STATISTICS | H130: ZZZ | I130: ZZZ | J130: DEFAULT | K130: TRUE | M130: TRUE | N130: FALSE | O130: FALSE
A131: AllThrough | E131: DFC_PUPIL_SEC | F131: DFC Secondary Pupil | G131: STATISTICS | H131: ZZZ | I131: ZZZ | J131: DEFAULT | K131: TRUE | M131: TRUE | N131: FALSE | O131: FALSE
A132: AllThrough | B132: LA1 | D132: PRI | E132: LUMP | F132: Lump Sum Primary | G132: STATISTICS | H132: ZZZ | I132: ZZZ | J132: DEFAULT | K132: TRUE | M132: TRUE | N132: FALSE | O132: FALSE
A133: AllThrough | B133: LA2 | D133: PRI | E133: LUMP | F133: Lump Sum Primary | G133: STATISTICS | H133: ZZZ | I133: ZZZ | J133: DEFAULT | K133: TRUE | M133: TRUE | N133: FALSE | O133: FALSE
A134: AllThrough | B134: LA3 | D134: PRI | E134: LUMP | F134: Lump Sum Primary | G134: STATISTICS | H134: ZZZ | I134: ZZZ | J134: DEFAULT | K134: TRUE | M134: TRUE | N134: FALSE | O134: FALSE
A135: AllThrough | B135: LA4 | D135: PRI | E135: LUMP | F135: Lump Sum Primary | G135: STATISTICS | H135: ZZZ | I135: ZZZ | J135: DEFAULT | K135: TRUE | M135: TRUE | N135: FALSE | O135: FALSE
A136: AllThrough | B136: LA5 | D136: PRI | E136: LUMP | F136: Lump Sum Primary | G136: STATISTICS | H136: ZZZ | I136: ZZZ | J136: DEFAULT | K136: TRUE | M136: TRUE | N136: FALSE | O136: FALSE
A137: AllThrough | B137: LA6 | D137: PRI | E137: LUMP | F137: Lump Sum Primary | G137: STATISTICS | H137: ZZZ | I137: ZZZ | J137: DEFAULT | K137: TRUE | M137: TRUE | N137: FALSE | O137: FALSE
A138: AllThrough | B138: LA1 | D138: SEC | E138: LUMP | F138: Lump Sum Secondary | G138: STATISTICS | H138: ZZZ | I138: ZZZ | J138: DEFAULT | K138: TRUE | M138: TRUE | N138: FALSE | O138: FALSE
A139: AllThrough | B139: LA2 | D139: SEC | E139: LUMP | F139: Lump Sum Secondary | G139: STATISTICS | H139: ZZZ | I139: ZZZ | J139: DEFAULT | K139: TRUE | M139: TRUE | N139: FALSE | O139: FALSE
A140: AllThrough | B140: LA3 | D140: SEC | E140: LUMP | F140: Lump Sum Secondary | G140: STATISTICS | H140: ZZZ | I140: ZZZ | J140: DEFAULT | K140: TRUE | M140: TRUE | N140: FALSE | O140: FALSE
A141: AllThrough | B141: LA4 | D141: SEC | E141: LUMP | F141: Lump Sum Secondary | G141: STATISTICS | H141: ZZZ | I141: ZZZ | J141: DEFAULT | K141: TRUE | M141: TRUE | N141: FALSE | O141: FALSE
A142: AllThrough | B142: LA5 | D142: SEC | E142: LUMP | F142: Lump Sum Secondary | G142: STATISTICS | H142: ZZZ | I142: ZZZ | J142: DEFAULT | K142: TRUE | M142: TRUE | N142: FALSE | O142: FALSE
A143: AllThrough | B143: LA6 | D143: SEC | E143: LUMP | F143: Lump Sum Secondary | G143: STATISTICS | H143: ZZZ | I143: ZZZ | J143: DEFAULT | K143: TRUE | M143: TRUE | N143: FALSE | O143: FALSE
... A155: AllThrough | B155: LA12 | D155: SEC | E155: LUMP | F155: Lump Sum Secondary | G155: STATISTICS | H155: ZZZ | I155: ZZZ | J155: DEFAULT | K155: TRUE | M155: TRUE | N155: FALSE | O155: FALSE
A156: AllThrough | E156: PEG_CORE | F156: PE Grant Core Amount | G156: STATISTICS | H156: ZZZ | I156: ZZZ | J156: DEFAULT | K156: TRUE | M156: TRUE | N156: FALSE | O156: FALSE
A157: AllThrough | E157: PEG_PUPIL | F157: PE Grant Per Pupil | G157: STATISTICS | H157: ZZZ | I157: ZZZ | J157: DEFAULT | K157: TRUE | M157: TRUE | N157: FALSE | O157: FALSE
A158: AllThrough | C158: England & Wales | E158: PENS_KS5_APR_EW | F158: Teachers Pensions Grant Post 16 Rate April - August (EW) | G158: STATISTICS | H158: ZZZ | I158: ZZZ | J158: DEFAULT | K158: TRUE | M158: TRUE | N158: FALSE | O158: FALSE
A159: AllThrough | C159: Fringe | E159: PENS_KS5_APR_FRI | F159: Teachers Pensions Grant Post 16 Rate April - August (Fringe) | G159: STATISTICS | H159: ZZZ | I159: ZZZ | J159: DEFAULT | K159: TRUE | M159: TRUE | N159: FALSE | O159: FALSE
A160: AllThrough | C160: Inner | E160: PENS_KS5_APR_INN | F160: Teachers Pensions Grant Post 16 Rate April - August (Inner) | G160: STATISTICS | H160: ZZZ | I160: ZZZ | J160: DEFAULT | K160: TRUE | M160: TRUE | N160: FALSE | O160: FALSE
A161: AllThrough | C161: Outer | E161: PENS_KS5_APR_OUT | F161: Teachers Pensions Grant Post 16 Rate April - August (Outer) | G161: STATISTICS | H161: ZZZ | I161: ZZZ | J161: DEFAULT | K161: TRUE | M161: TRUE | N161: FALSE | O161: FALSE
A162: AllThrough | C162: England & Wales | E162: PENS_KS5_SEP_EW | F162: Teachers Pensions Grant Post 16 Rate September - March (EW) | G162: STATISTICS | H162: ZZZ | I162: ZZZ | J162: DEFAULT | K162: TRUE | M162: TRUE | N162: FALSE | O162: FALSE
A163: AllThrough | C163: Fringe | E163: PENS_KS5_SEP_FRI | F163: Teachers Pensions Grant Post 16 Rate September - March (Fringe) | G163: STATISTICS | H163: ZZZ | I163: ZZZ | J163: DEFAULT | K163: TRUE | M163: TRUE | N163: FALSE | O163: FALSE
A164: AllThrough | C164: Inner | E164: PENS_KS5_SEP_INN | F164: Teachers Pensions Grant Post 16 Rate September - March (Inner) | G164: STATISTICS | H164: ZZZ | I164: ZZZ | J164: DEFAULT | K164: TRUE | M164: TRUE | N164: FALSE | O164: FALSE
A165: AllThrough | C165: Outer | E165: PENS_KS5_SEP_OUT | F165: Teachers Pensions Grant Post 16 Rate September - March (Outer) | G165: STATISTICS | H165: ZZZ | I165: ZZZ | J165: DEFAULT | K165: TRUE | M165: TRUE | N165: FALSE | O165: FALSE
A166: AllThrough | E166: PUPPRI_RATE | F166: Pupil Premium Rate Primary | G166: STATISTICS | H166: ZZZ | I166: ZZZ | J166: DEFAULT | K166: TRUE | M166: TRUE | N166: FALSE | O166: FALSE
A167: AllThrough | E167: PUPSEC_RATE | F167: Pupil Premium Rate Secondary | G167: STATISTICS | H167: ZZZ | I167: ZZZ | J167: DEFAULT | K167: TRUE | M167: TRUE | N167: FALSE | O167: FALSE
A168: AllThrough | E168: UIFSM_RATE_FIN | F168: UIFSM Per Pupil Per Annum (Final) | G168: STATISTICS | H168: ZZZ | I168: ZZZ | J168: DEFAULT | K168: TRUE | M168: TRUE | N168: FALSE | O168: FALSE
A169: AllThrough | E169: UIFSM_RATE_PRO | F169: UIFSM Per Pupil Per Annum (Provisional) | G169: STATISTICS | H169: ZZZ | I169: ZZZ | J169: DEFAULT | K169: TRUE | M169: TRUE | N169: FALSE | O169: FALSE
A170: AllThrough | E170: UPLIFT_POST16 | F170: Post 16 GAG Uplifts | G170: STATISTICS | H170: ZZZ | I170: ZZZ | J170: DEFAULT | K170: TRUE | M170: TRUE | N170: FALSE | O170: FALSE
A171: AllThrough | E171: DFE_POST16_TOTAL | F171: Total DFE Post 16 Funding Statement | G171: FUNDING | H171: ZZZ | I171: ZZZ | J171: DEFAULT | K171: TRUE | M171: TRUE | N171: FALSE | O171: FALSE
A172: AllThrough | E172: FUNDING_HNPOST16 | F172: Funding Statement Unoccupied Post 16 Special Provision | G172: FUNDING | H172: ZZZ | I172: ZZZ | J172: DEFAULT | K172: TRUE | M172: TRUE | N172: FALSE | O172: FALSE
A173: AllThrough | E173: FUNDING_HNPOST16O | F173: Funding Statement Occupied Post 16 Special Provision | G173: FUNDING | H173: ZZZ | I173: ZZZ | J173: DEFAULT | K173: TRUE | M173: TRUE | N173: FALSE | O173: FALSE
A174: College | E174: FUNDING_16_19 | F174: Funding GAG - Post 16 | G174: FUNDING | H174: ZZZ | I174: ZZZ | J174: DEFAULT | K174: TRUE | M174: TRUE | N174: FALSE | O174: FALSE
A175: College | E175: FUNDING_SFS | F175: Funding Student Financial Support | G175: FUNDING | H175: ZZZ | I175: ZZZ | J175: DEFAULT | K175: TRUE | M175: TRUE | N175: FALSE | O175: FALSE
A176: College | E176: FTE_KS5 | F176: FTE for Post 16 Pupils | G176: PUPILNUMBERS | H176: ZZZ | I176: ZZZ | J176: DEFAULT | K176: TRUE | M176: TRUE | N176: FALSE | O176: FALSE
A177: College | E177: FUNDED_KS5 | F177: Funded Pupil Numbers KS5 | G177: PUPILNUMBERS | H177: ZZZ | I177: ZZZ | J177: DEFAULT | K177: TRUE | M177: TRUE | N177: FALSE | O177: FALSE
... A185: College | E185: DFC_PUPIL_POST16 | F185: DFC Post16 Pupil | G185: STATISTICS | H185: ZZZ | I185: ZZZ | J185: DEFAULT | K185: TRUE | M185: TRUE | N185: FALSE | O185: FALSE
A186: College | C186: England & Wales | E186: PENS_KS5_APR_EW | F186: Teachers Pensions Grant Post 16 Rate April - August (EW) | G186: STATISTICS | H186: ZZZ | I186: ZZZ | J186: DEFAULT | K186: TRUE | M186: TRUE | N186: FALSE | O186: FALSE
A187: College | C187: Fringe | E187: PENS_KS5_APR_FRI | F187: Teachers Pensions Grant Post 16 Rate April - August (Fringe) | G187: STATISTICS | H187: ZZZ | I187: ZZZ | J187: DEFAULT | K187: TRUE | M187: TRUE | N187: FALSE | O187: FALSE
A188: College | C188: Inner | E188: PENS_KS5_APR_INN | F188: Teachers Pensions Grant Post 16 Rate April - August (Inner) | G188: STATISTICS | H188: ZZZ | I188: ZZZ | J188: DEFAULT | K188: TRUE | M188: TRUE | N188: FALSE | O188: FALSE
A189: College | C189: Outer | E189: PENS_KS5_APR_OUT | F189: Teachers Pensions Grant Post 16 Rate April - August (Outer) | G189: STATISTICS | H189: ZZZ | I189: ZZZ | J189: DEFAULT | K189: TRUE | M189: TRUE | N189: FALSE | O189: FALSE
A190: College | C190: England & Wales | E190: PENS_KS5_SEP_EW | F190: Teachers Pensions Grant Post 16 Rate September - March (EW) | G190: STATISTICS | H190: ZZZ | I190: ZZZ | J190: DEFAULT | K190: TRUE | M190: TRUE | N190: FALSE | O190: FALSE
A191: College | C191: Fringe | E191: PENS_KS5_SEP_FRI | F191: Teachers Pensions Grant Post 16 Rate September - March (Fringe) | G191: STATISTICS | H191: ZZZ | I191: ZZZ | J191: DEFAULT | K191: TRUE | M191: TRUE | N191: FALSE | O191: FALSE
A192: College | C192: Inner | E192: PENS_KS5_SEP_INN | F192: Teachers Pensions Grant Post 16 Rate September - March (Inner) | G192: STATISTICS | H192: ZZZ | I192: ZZZ | J192: DEFAULT | K192: TRUE | M192: TRUE | N192: FALSE | O192: FALSE
A193: College | C193: Outer | E193: PENS_KS5_SEP_OUT | F193: Teachers Pensions Grant Post 16 Rate September - March (Outer) | G193: STATISTICS | H193: ZZZ | I193: ZZZ | J193: DEFAULT | K193: TRUE | M193: TRUE | N193: FALSE | O193: FALSE
A194: College | E194: UPLIFT_POST16 | F194: Post 16 GAG Uplifts | G194: STATISTICS | H194: ZZZ | I194: ZZZ | J194: DEFAULT | K194: TRUE | M194: TRUE | N194: FALSE | O194: FALSE
A195: College | E195: DFE_POST16_TOTAL | F195: Total DFE Post 16 Funding Statement | G195: FUNDING | H195: ZZZ | I195: ZZZ | J195: DEFAULT | K195: TRUE | M195: TRUE | N195: FALSE | O195: FALSE
A196: College | E196: FUNDING_HNPOST16 | F196: Funding Statement Unoccupied Post 16 Special Provision | G196: FUNDING | H196: ZZZ | I196: ZZZ | J196: DEFAULT | K196: TRUE | M196: TRUE | N196: FALSE | O196: FALSE
A197: College | E197: FUNDING_HNPOST16O | F197: Funding Statement Occupied Post 16 Special Provision | G197: FUNDING | H197: ZZZ | I197: ZZZ | J197: DEFAULT | K197: TRUE | M197: TRUE | N197: FALSE | O197: FALSE
A198: Infant | E198: FUNDING_PUPPREM_PRI | F198: Pupil Premium Income Primary | G198: FUNDING | H198: ZZZ | I198: ZZZ | J198: DEFAULT | K198: TRUE | M198: TRUE | N198: FALSE | O198: FALSE
A199: Infant | E199: PE_GRANT | F199: PE Grant Allocation | G199: FUNDING | H199: ZZZ | I199: ZZZ | J199: DEFAULT | K199: TRUE | M199: TRUE | N199: FALSE | O199: FALSE
A200: Infant | E200: UIFSM_ANNUAL | F200: UIFSM - Annual calc | G200: FUNDING | H200: ZZZ | I200: ZZZ | J200: DEFAULT | K200: TRUE | M200: TRUE | N200: FALSE | O200: FALSE
A201: Infant | E201: UIFSM_FIN | F201: UIFSM - Final Payment | G201: FUNDING | H201: ZZZ | I201: ZZZ | J201: DEFAULT | K201: TRUE | M201: TRUE | N201: FALSE | O201: FALSE
A202: Infant | E202: UIFSM_PRO | F202: UIFSM Provisional Allocation | G202: FUNDING | H202: ZZZ | I202: ZZZ | J202: DEFAULT | K202: TRUE | M202: TRUE | N202: FALSE | O202: FALSE
A203: Infant | E203: UIFSM_PRO_CALC | F203: UIFSM - Provisional calc | G203: FUNDING | H203: ZZZ | I203: ZZZ | J203: DEFAULT | K203: TRUE | M203: TRUE | N203: FALSE | O203: FALSE
A204: Infant | E204: FTE_NUR | F204: FTE for Nursery Pupils | G204: PUPILNUMBERS | H204: ZZZ | I204: ZZZ | J204: DEFAULT | K204: TRUE | M204: TRUE | N204: FALSE | O204: FALSE
A205: Infant | E205: FUNDED_FS | F205: Funded Pupil Numbers Foundation | G205: PUPILNUMBERS | H205: ZZZ | I205: ZZZ | J205: DEFAULT | K205: TRUE | M205: TRUE | N205: FALSE | O205: FALSE
... A221: Infant | E221: PUPILPREMIUM_PRI | F221: Pupil Premium Numbers Primary | G221: PUPILNUMBERS | H221: Z12 | I221: ZZZ | J221: DEFAULT | K221: TRUE | M221: TRUE | N221: FALSE | O221: FALSE
A222: Infant | B222: LA1 | D222: PRI | E222: AWPU01 | F222: AWPU-PRI- | G222: STATISTICS | H222: ZZZ | I222: ZZZ | J222: DEFAULT | K222: TRUE | M222: TRUE | N222: FALSE | O222: FALSE
A223: Infant | B223: LA2 | D223: PRI | E223: AWPU01 | F223: AWPU-PRI- | G223: STATISTICS | H223: ZZZ | I223: ZZZ | J223: DEFAULT | K223: TRUE | M223: TRUE | N223: FALSE | O223: FALSE
A224: Infant | B224: LA3 | D224: PRI | E224: AWPU01 | F224: AWPU-PRI- | G224: STATISTICS | H224: ZZZ | I224: ZZZ | J224: DEFAULT | K224: TRUE | M224: TRUE | N224: FALSE | O224: FALSE
A225: Infant | B225: LA4 | D225: PRI | E225: AWPU01 | F225: AWPU-PRI- | G225: STATISTICS | H225: ZZZ | I225: ZZZ | J225: DEFAULT | K225: TRUE | M225: TRUE | N225: FALSE | O225: FALSE
A226: Infant | B226: LA5 | D226: PRI | E226: AWPU01 | F226: AWPU-PRI- | G226: STATISTICS | H226: ZZZ | I226: ZZZ | J226: DEFAULT | K226: TRUE | M226: TRUE | N226: FALSE | O226: FALSE
A227: Infant | B227: LA6 | D227: PRI | E227: AWPU01 | F227: AWPU-PRI- | G227: STATISTICS | H227: ZZZ | I227: ZZZ | J227: DEFAULT | K227: TRUE | M227: TRUE | N227: FALSE | O227: FALSE
A228: Infant | B228: LA7 | D228: PRI | E228: AWPU01 | F228: AWPU-PRI- | G228: STATISTICS | H228: ZZZ | I228: ZZZ | J228: DEFAULT | K228: TRUE | M228: TRUE | N228: FALSE | O228: FALSE
A229: Infant | B229: LA8 | D229: PRI | E229: AWPU01 | F229: AWPU-PRI- | G229: STATISTICS | H229: ZZZ | I229: ZZZ | J229: DEFAULT | K229: TRUE | M229: TRUE | N229: FALSE | O229: FALSE
A230: Infant | B230: LA9 | D230: PRI | E230: AWPU01 | F230: AWPU-PRI- | G230: STATISTICS | H230: ZZZ | I230: ZZZ | J230: DEFAULT | K230: TRUE | M230: TRUE | N230: FALSE | O230: FALSE
A231: Infant | B231: LA10 | D231: PRI | E231: AWPU01 | F231: AWPU-PRI- | G231: STATISTICS | H231: ZZZ | I231: ZZZ | J231: DEFAULT | K231: TRUE | M231: TRUE | N231: FALSE | O231: FALSE
A232: Infant | B232: LA11 | D232: PRI | E232: AWPU01 | F232: AWPU-PRI- | G232: STATISTICS | H232: ZZZ | I232: ZZZ | J232: DEFAULT | K232: TRUE | M232: TRUE | N232: FALSE | O232: FALSE
A233: Infant | B233: LA12 | D233: PRI | E233: AWPU01 | F233: AWPU-PRI- | G233: STATISTICS | H233: ZZZ | I233: ZZZ | J233: DEFAULT | K233: TRUE | M233: TRUE | N233: FALSE | O233: FALSE
...

Sheet FinanceCodes Budget
N1: API - Do not edit
A2: LedgerIssue | B2: GroupingCodeIssue | C2: CustGrIssue | D2: SchCodeIssue | E2: DupCode | F2: DupDesc | G2: FCTypeIss | H2: Code length Check | I2: Blank Code | J2: Blank Title | K2: Title length check | L2: Balance to Scenario Blank | M2: Will Import if 0 | N2: FinanceCode | O2: Title | P2: GroupingCode | Q2: CustomGrouping | R2: AvailableToAllSchools | S2: SchoolCodes | T2: FinanceCodeTypeCode | U2: LedgerCode | V2: FinanceCodeEnabled | W2: BalanceToScenario

Sheet CalculatorsTempl
A1: School Type | B1: London Weighting | C1: LA | D1: KeyStage | E1: CalculatorCode | F1: Title | G1: SourceSelectAllSchools | H1: SourceSelectAllFunds | I1: SourceSelectAllDepartments | J1: SourceDepartmentsAcrossLedgers | K1: SourceIncludeScenarioRow | L1: SourceUseLastYear | M1: SourceSchoolLocalAuthority | N1: SourceConstant | O1: SourceSchoolHubSelectedScenarioRow | P1: SourceSchoolTypeSelectedScenarioRow | Q1: DivisorSelectAllSchools | R1: DivisorSelectAllFunds | S1: DivisorSelectAllDepartments | T1: DivisorDepartmentsAcrossLedgers | U1: DivisorIncludeScenarioRow | V1: DivisorUseLastYear | W1: DivisorSchoolLocalAuthority | X1: DivisorConstant | Y1: DivisorSchoolHubSelectedScenarioRow | Z1: DivisorSchoolTypeSelectedScenarioRow | AA1: MultiplierSelectAllSchools | AB1: MultiplierSelectAllFunds | AC1: MultiplierSelectAllDepartments | AD1: MultiplierDepartmentsAcrossLedgers | AE1: MultiplierIncludeScenarioRow | AF1: MultiplierUseLastYear | AG1: MultiplierSchoolLocalAuthority | AH1: MultiplierConstant | AI1: MultiplierSchoolHubSelectedScenarioRow | AJ1: MultiplierSchoolTypeSelectedScenarioRow | AK1: CalculatorEnabled | AL1: CalculatorLockRows | AM1: CalculatorTypeCode | AN1: LockCheck
A2: All | E2: 0%_CALC | F2: No Uplift | G2: FALSE | H2: FALSE | I2: FALSE | J2: TRUE | K2: TRUE | L2: TRUE | M2: FALSE | N2: 0 | O2: FALSE | P2: FALSE | Q2: FALSE | R2: FALSE | S2: FALSE | T2: TRUE | U2: FALSE | V2: TRUE | W2: FALSE | X2: 1 | Y2: FALSE | Z2: FALSE | AA2: FALSE | AB2: FALSE | AC2: FALSE | AD2: TRUE | AE2: FALSE | AF2: TRUE | AG2: FALSE | AH2: 1 | AI2: FALSE | AJ2: FALSE | AK2: TRUE | AL2: 0 | AM2: DEFAULT | AN2: 0
A3: All | E3: 1%_CALC | F3: 1% Uplift | G3: FALSE | H3: FALSE | I3: FALSE | J3: TRUE | K3: TRUE | L3: TRUE | M3: FALSE | N3: 0 | O3: FALSE | P3: FALSE | Q3: FALSE | R3: FALSE | S3: FALSE | T3: TRUE | U3: FALSE | V3: TRUE | W3: FALSE | X3: 1 | Y3: FALSE | Z3: FALSE | AA3: FALSE | AB3: FALSE | AC3: FALSE | AD3: TRUE | AE3: FALSE | AF3: TRUE | AG3: FALSE | AH3: 1.01 | AI3: FALSE | AJ3: FALSE | AK3: TRUE | AL3: 0 | AM3: DEFAULT | AN3: 0
A4: All | E4: 2%_CALC | F4: 2% Uplift | G4: FALSE | H4: FALSE | I4: FALSE | J4: TRUE | K4: TRUE | L4: TRUE | M4: FALSE | N4: 0 | O4: FALSE | P4: FALSE | Q4: FALSE | R4: FALSE | S4: FALSE | T4: TRUE | U4: FALSE | V4: TRUE | W4: FALSE | X4: 1 | Y4: FALSE | Z4: FALSE | AA4: FALSE | AB4: FALSE | AC4: FALSE | AD4: TRUE | AE4: FALSE | AF4: TRUE | AG4: FALSE | AH4: 1.02 | AI4: FALSE | AJ4: FALSE | AK4: TRUE | AL4: 0 | AM4: DEFAULT | AN4: 0
A5: All | E5: 3%_CALC | F5: 3% Uplift | G5: FALSE | H5: FALSE | I5: FALSE | J5: TRUE | K5: TRUE | L5: FALSE | M5: FALSE | N5: 0 | O5: FALSE | P5: FALSE | Q5: FALSE | R5: FALSE | S5: FALSE | T5: TRUE | U5: FALSE | V5: TRUE | W5: FALSE | X5: 1 | Y5: FALSE | Z5: FALSE | AA5: FALSE | AB5: FALSE | AC5: FALSE | AD5: TRUE | AE5: FALSE | AF5: TRUE | AG5: FALSE | AH5: 1.03 | AI5: FALSE | AJ5: FALSE | AK5: TRUE | AL5: 0 | AM5: DEFAULT | AN5: 0
A6: All | E6: 4%_CALC | F6: 4% Uplift | G6: FALSE | H6: FALSE | I6: FALSE | J6: TRUE | K6: TRUE | L6: TRUE | M6: FALSE | N6: 0 | O6: FALSE | P6: FALSE | Q6: FALSE | R6: FALSE | S6: FALSE | T6: TRUE | U6: FALSE | V6: TRUE | W6: FALSE | X6: 1 | Y6: FALSE | Z6: FALSE | AA6: FALSE | AB6: FALSE | AC6: FALSE | AD6: TRUE | AE6: FALSE | AF6: TRUE | AG6: FALSE | AH6: 1.04 | AI6: FALSE | AJ6: FALSE | AK6: TRUE | AL6: 0 | AM6: DEFAULT | AN6: 0
A7: All | E7: 5%_CALC | F7: 5% Uplift | G7: FALSE | H7: FALSE | I7: FALSE | J7: TRUE | K7: TRUE | L7: TRUE | M7: FALSE | N7: 0 | O7: FALSE | P7: FALSE | Q7: FALSE | R7: FALSE | S7: FALSE | T7: TRUE | U7: FALSE | V7: TRUE | W7: FALSE | X7: 1 | Y7: FALSE | Z7: FALSE | AA7: FALSE | AB7: FALSE | AC7: FALSE | AD7: TRUE | AE7: FALSE | AF7: TRUE | AG7: FALSE | AH7: 1.05 | AI7: FALSE | AJ7: FALSE | AK7: TRUE | AL7: 0 | AM7: DEFAULT | AN7: 0
A8: All | E8: CENTRALCHG_MAT | F8: Central Charge MAT | G8: TRUE | H8: TRUE | I8: TRUE | J8: TRUE | K8: FALSE | L8: FALSE | M8: FALSE | N8: 0 | O8: FALSE | P8: FALSE | Q8: FALSE | R8: FALSE | S8: FALSE | T8: TRUE | U8: FALSE | V8: TRUE | W8: FALSE | X8: 1 | Y8: FALSE | Z8: FALSE | AA8: TRUE | AB8: TRUE | AC8: TRUE | AD8: TRUE | AE8: FALSE | AF8: FALSE | AG8: FALSE | AH8: -1 | AI8: FALSE | AJ8: FALSE | AK8: TRUE | AL8: 1 | AM8: BUDGET | AN8: 1
A9: All | E9: CENTRALCHG_SCH | F9: Central Charge SCH | G9: FALSE | H9: TRUE | I9: TRUE | J9: TRUE | K9: FALSE | L9: FALSE | M9: FALSE | N9: 0 | O9: FALSE | P9: FALSE | Q9: FALSE | R9: FALSE | S9: FALSE | T9: TRUE | U9: FALSE | V9: TRUE | W9: FALSE | X9: -100 | Y9: FALSE | Z9: FALSE | AA9: TRUE | AB9: TRUE | AC9: TRUE | AD9: TRUE | AE9: FALSE | AF9: FALSE | AG9: FALSE | AH9: 0 | AI9: FALSE | AJ9: FALSE | AK9: TRUE | AL9: 1 | AM9: BUDGET | AN9: 1
A10: All | E10: DFC_CORE | F10: DFC Core funding | G10: TRUE | H10: TRUE | I10: TRUE | J10: TRUE | K10: FALSE | L10: FALSE | M10: FALSE | N10: 0 | O10: FALSE | P10: FALSE | Q10: FALSE | R10: FALSE | S10: FALSE | T10: TRUE | U10: FALSE | V10: TRUE | W10: FALSE | X10: 1 | Y10: FALSE | Z10: FALSE | AA10: FALSE | AB10: FALSE | AC10: FALSE | AD10: TRUE | AE10: FALSE | AF10: TRUE | AG10: FALSE | AH10: 1 | AI10: FALSE | AJ10: FALSE | AK10: TRUE | AL10: 1 | AM10: FUNDING | AN10: 1
A11: All | E11: DFC_EXP | F11: DFC Expenditure | G11: FALSE | H11: TRUE | I11: TRUE | J11: TRUE | K11: FALSE | L11: FALSE | M11: FALSE | N11: 0 | O11: FALSE | P11: FALSE | Q11: FALSE | R11: TRUE | S11: TRUE | T11: TRUE | U11: FALSE | V11: TRUE | W11: FALSE | X11: 1 | Y11: FALSE | Z11: FALSE | AA11: TRUE | AB11: TRUE | AC11: TRUE | AD11: TRUE | AE11: FALSE | AF11: FALSE | AG11: FALSE | AH11: -1 | AI11: FALSE | AJ11: FALSE | AK11: TRUE | AL11: 1 | AM11: BUDGET | AN11: 1
A12: All | E12: DFE_TOTAL | F12: Total DFE - Pre 16 | G12: FALSE | H12: TRUE | I12: TRUE | J12: TRUE | K12: FALSE | L12: FALSE | M12: FALSE | N12: 0 | O12: FALSE | P12: FALSE | Q12: FALSE | R12: TRUE | S12: TRUE | T12: TRUE | U12: FALSE | V12: FALSE | W12: FALSE | X12: -1 | Y12: FALSE | Z12: FALSE | AA12: FALSE | AB12: FALSE | AC12: FALSE | AD12: TRUE | AE12: FALSE | AF12: TRUE | AG12: FALSE | AH12: 1 | AI12: FALSE | AJ12: FALSE | AK12: TRUE | AL12: 1 | AM12: FUNDING | AN12: 1
A13: All | E13: FUNDING_GAG | F13: Funding GAG | G13: FALSE | H13: TRUE | I13: TRUE | J13: TRUE | K13: FALSE | L13: FALSE | M13: FALSE | N13: 0 | O13: FALSE | P13: FALSE | Q13: FALSE | R13: TRUE | S13: TRUE | T13: TRUE | U13: FALSE | V13: FALSE | W13: FALSE | X13: 1 | Y13: FALSE | Z13: FALSE | AA13: FALSE | AB13: FALSE | AC13: FALSE | AD13: TRUE | AE13: FALSE | AF13: TRUE | AG13: FALSE | AH13: 1 | AI13: FALSE | AJ13: FALSE | AK13: TRUE | AL13: 1 | AM13: BUDGET | AN13: 1
... A49: All | E49: LEVY_ALL_TEA | F49: Levy Allowance - Teaching | G49: TRUE | H49: TRUE | I49: TRUE | J49: TRUE | K49: FALSE | L49: FALSE | M49: FALSE | N49: 0 | O49: FALSE | P49: FALSE | Q49: TRUE | R49: TRUE | S49: TRUE | T49: TRUE | U49: FALSE | V49: FALSE | W49: FALSE | X49: 0 | Y49: FALSE | Z49: FALSE | AA49: FALSE | AB49: TRUE | AC49: TRUE | AD49: TRUE | AE49: FALSE | AF49: FALSE | AG49: FALSE | AH49: 0 | AI49: FALSE | AJ49: FALSE | AK49: TRUE | AL49: 1 | AM49: BUDGET | AN49: 1
A50: AllThrough | C50: LA1 | D50: PRI | E50: AWPU01 | F50: Total AWPU PRI | G50: FALSE | H50: TRUE | I50: TRUE | J50: TRUE | K50: FALSE | L50: FALSE | M50: FALSE | N50: 0 | O50: FALSE | P50: FALSE | Q50: FALSE | R50: FALSE | S50: FALSE | T50: TRUE | U50: FALSE | V50: TRUE | W50: FALSE | X50: 1 | Y50: FALSE | Z50: FALSE | AA50: TRUE | AB50: TRUE | AC50: TRUE | AD50: TRUE | AE50: FALSE | AF50: FALSE | AG50: FALSE | AH50: 0 | AI50: FALSE | AJ50: FALSE | AK50: TRUE | AL50: 1 | AM50: FUNDING | AN50: 1
A51: AllThrough | C51: LA2 | D51: PRI | E51: AWPU01 | F51: Total AWPU PRI | G51: FALSE | H51: TRUE | I51: TRUE | J51: TRUE | K51: FALSE | L51: FALSE | M51: FALSE | N51: 0 | O51: FALSE | P51: FALSE | Q51: FALSE | R51: FALSE | S51: FALSE | T51: TRUE | U51: FALSE | V51: TRUE | W51: FALSE | X51: 1 | Y51: FALSE | Z51: FALSE | AA51: TRUE | AB51: TRUE | AC51: TRUE | AD51: TRUE | AE51: FALSE | AF51: FALSE | AG51: FALSE | AH51: 0 | AI51: FALSE | AJ51: FALSE | AK51: TRUE | AL51: 1 | AM51: FUNDING | AN51: 1
A52: AllThrough | C52: LA3 | D52: PRI | E52: AWPU01 | F52: Total AWPU PRI | G52: FALSE | H52: TRUE | I52: TRUE | J52: TRUE | K52: FALSE | L52: FALSE | M52: FALSE | N52: 0 | O52: FALSE | P52: FALSE | Q52: FALSE | R52: FALSE | S52: FALSE | T52: TRUE | U52: FALSE | V52: TRUE | W52: FALSE | X52: 1 | Y52: FALSE | Z52: FALSE | AA52: TRUE | AB52: TRUE | AC52: TRUE | AD52: TRUE | AE52: FALSE | AF52: FALSE | AG52: FALSE | AH52: 0 | AI52: FALSE | AJ52: FALSE | AK52: TRUE | AL52: 1 | AM52: FUNDING | AN52: 1
A53: AllThrough | C53: LA4 | D53: PRI | E53: AWPU01 | F53: Total AWPU PRI | G53: FALSE | H53: TRUE | I53: TRUE | J53: TRUE | K53: FALSE | L53: FALSE | M53: FALSE | N53: 0 | O53: FALSE | P53: FALSE | Q53: FALSE | R53: FALSE | S53: FALSE | T53: TRUE | U53: FALSE | V53: TRUE | W53: FALSE | X53: 1 | Y53: FALSE | Z53: FALSE | AA53: TRUE | AB53: TRUE | AC53: TRUE | AD53: TRUE | AE53: FALSE | AF53: FALSE | AG53: FALSE | AH53: 0 | AI53: FALSE | AJ53: FALSE | AK53: TRUE | AL53: 1 | AM53: FUNDING | AN53: 1
A54: AllThrough | C54: LA5 | D54: PRI | E54: AWPU01 | F54: Total AWPU PRI | G54: FALSE | H54: TRUE | I54: TRUE | J54: TRUE | K54: FALSE | L54: FALSE | M54: FALSE | N54: 0 | O54: FALSE | P54: FALSE | Q54: FALSE | R54: FALSE | S54: FALSE | T54: TRUE | U54: FALSE | V54: TRUE | W54: FALSE | X54: 1 | Y54: FALSE | Z54: FALSE | AA54: TRUE | AB54: TRUE | AC54: TRUE | AD54: TRUE | AE54: FALSE | AF54: FALSE | AG54: FALSE | AH54: 0 | AI54: FALSE | AJ54: FALSE | AK54: TRUE | AL54: 1 | AM54: FUNDING | AN54: 1
A55: AllThrough | C55: LA6 | D55: PRI | E55: AWPU01 | F55: Total AWPU PRI | G55: FALSE | H55: TRUE | I55: TRUE | J55: TRUE | K55: FALSE | L55: FALSE | M55: FALSE | N55: 0 | O55: FALSE | P55: FALSE | Q55: FALSE | R55: FALSE | S55: FALSE | T55: TRUE | U55: FALSE | V55: TRUE | W55: FALSE | X55: 1 | Y55: FALSE | Z55: FALSE | AA55: TRUE | AB55: TRUE | AC55: TRUE | AD55: TRUE | AE55: FALSE | AF55: FALSE | AG55: FALSE | AH55: 0 | AI55: FALSE | AJ55: FALSE | AK55: TRUE | AL55: 1 | AM55: FUNDING | AN55: 1
A56: AllThrough | C56: LA7 | D56: PRI | E56: AWPU01 | F56: Total AWPU PRI | G56: FALSE | H56: TRUE | I56: TRUE | J56: TRUE | K56: FALSE | L56: FALSE | M56: FALSE | N56: 0 | O56: FALSE | P56: FALSE | Q56: FALSE | R56: FALSE | S56: FALSE | T56: TRUE | U56: FALSE | V56: TRUE | W56: FALSE | X56: 1 | Y56: FALSE | Z56: FALSE | AA56: TRUE | AB56: TRUE | AC56: TRUE | AD56: TRUE | AE56: FALSE | AF56: FALSE | AG56: FALSE | AH56: 0 | AI56: FALSE | AJ56: FALSE | AK56: TRUE | AL56: 1 | AM56: FUNDING | AN56: 1
A57: AllThrough | C57: LA8 | D57: PRI | E57: AWPU01 | F57: Total AWPU PRI | G57: FALSE | H57: TRUE | I57: TRUE | J57: TRUE | K57: FALSE | L57: FALSE | M57: FALSE | N57: 0 | O57: FALSE | P57: FALSE | Q57: FALSE | R57: FALSE | S57: FALSE | T57: TRUE | U57: FALSE | V57: TRUE | W57: FALSE | X57: 1 | Y57: FALSE | Z57: FALSE | AA57: TRUE | AB57: TRUE | AC57: TRUE | AD57: TRUE | AE57: FALSE | AF57: FALSE | AG57: FALSE | AH57: 0 | AI57: FALSE | AJ57: FALSE | AK57: TRUE | AL57: 1 | AM57: FUNDING | AN57: 1
A58: AllThrough | C58: LA9 | D58: PRI | E58: AWPU01 | F58: Total AWPU PRI | G58: FALSE | H58: TRUE | I58: TRUE | J58: TRUE | K58: FALSE | L58: FALSE | M58: FALSE | N58: 0 | O58: FALSE | P58: FALSE | Q58: FALSE | R58: FALSE | S58: FALSE | T58: TRUE | U58: FALSE | V58: TRUE | W58: FALSE | X58: 1 | Y58: FALSE | Z58: FALSE | AA58: TRUE | AB58: TRUE | AC58: TRUE | AD58: TRUE | AE58: FALSE | AF58: FALSE | AG58: FALSE | AH58: 0 | AI58: FALSE | AJ58: FALSE | AK58: TRUE | AL58: 1 | AM58: FUNDING | AN58: 1
A59: AllThrough | C59: LA10 | D59: PRI | E59: AWPU01 | F59: Total AWPU PRI | G59: FALSE | H59: TRUE | I59: TRUE | J59: TRUE | K59: FALSE | L59: FALSE | M59: FALSE | N59: 0 | O59: FALSE | P59: FALSE | Q59: FALSE | R59: FALSE | S59: FALSE | T59: TRUE | U59: FALSE | V59: TRUE | W59: FALSE | X59: 1 | Y59: FALSE | Z59: FALSE | AA59: TRUE | AB59: TRUE | AC59: TRUE | AD59: TRUE | AE59: FALSE | AF59: FALSE | AG59: FALSE | AH59: 0 | AI59: FALSE | AJ59: FALSE | AK59: TRUE | AL59: 1 | AM59: FUNDING | AN59: 1
A60: AllThrough | C60: LA11 | D60: PRI | E60: AWPU01 | F60: Total AWPU PRI | G60: FALSE | H60: TRUE | I60: TRUE | J60: TRUE | K60: FALSE | L60: FALSE | M60: FALSE | N60: 0 | O60: FALSE | P60: FALSE | Q60: FALSE | R60: FALSE | S60: FALSE | T60: TRUE | U60: FALSE | V60: TRUE | W60: FALSE | X60: 1 | Y60: FALSE | Z60: FALSE | AA60: TRUE | AB60: TRUE | AC60: TRUE | AD60: TRUE | AE60: FALSE | AF60: FALSE | AG60: FALSE | AH60: 0 | AI60: FALSE | AJ60: FALSE | AK60: TRUE | AL60: 1 | AM60: FUNDING | AN60: 1
A61: AllThrough | C61: LA12 | D61: PRI | E61: AWPU01 | F61: Total AWPU PRI | G61: FALSE | H61: TRUE | I61: TRUE | J61: TRUE | K61: FALSE | L61: FALSE | M61: FALSE | N61: 0 | O61: FALSE | P61: FALSE | Q61: FALSE | R61: FALSE | S61: FALSE | T61: TRUE | U61: FALSE | V61: TRUE | W61: FALSE | X61: 1 | Y61: FALSE | Z61: FALSE | AA61: TRUE | AB61: TRUE | AC61: TRUE | AD61: TRUE | AE61: FALSE | AF61: FALSE | AG61: FALSE | AH61: 0 | AI61: FALSE | AJ61: FALSE | AK61: TRUE | AL61: 1 | AM61: FUNDING | AN61: 1
... A85: AllThrough | C85: LA12 | D85: KS4 | E85: AWPU03 | F85: Total AWPU KS4 | G85: FALSE | H85: TRUE | I85: TRUE | J85: TRUE | K85: FALSE | L85: FALSE | M85: FALSE | N85: 0 | O85: FALSE | P85: FALSE | Q85: FALSE | R85: FALSE | S85: FALSE | T85: TRUE | U85: FALSE | V85: TRUE | W85: FALSE | X85: 1 | Y85: FALSE | Z85: FALSE | AA85: TRUE | AB85: TRUE | AC85: TRUE | AD85: TRUE | AE85: FALSE | AF85: FALSE | AG85: FALSE | AH85: 0 | AI85: FALSE | AJ85: FALSE | AK85: TRUE | AL85: 1 | AM85: FUNDING | AN85: 1
A86: AllThrough | E86: DFC_PUPIL_NUR | F86: DFC Nursery Per pupil | G86: FALSE | H86: TRUE | I86: TRUE | J86: TRUE | K86: FALSE | L86: TRUE | M86: FALSE | N86: 0 | O86: FALSE | P86: FALSE | Q86: FALSE | R86: FALSE | S86: FALSE | T86: TRUE | U86: FALSE | V86: TRUE | W86: FALSE | X86: 1 | Y86: FALSE | Z86: FALSE | AA86: TRUE | AB86: TRUE | AC86: TRUE | AD86: TRUE | AE86: FALSE | AF86: FALSE | AG86: FALSE | AH86: 0 | AI86: FALSE | AJ86: FALSE | AK86: TRUE | AL86: 0 | AM86: FUNDING | AN86: 0
A87: AllThrough | E87: DFC_PUPIL_POST16 | F87: DFC Post 16 Per pupil | G87: FALSE | H87: TRUE | I87: TRUE | J87: TRUE | K87: FALSE | L87: TRUE | M87: FALSE | N87: 0 | O87: FALSE | P87: FALSE | Q87: FALSE | R87: FALSE | S87: FALSE | T87: TRUE | U87: FALSE | V87: TRUE | W87: FALSE | X87: 1 | Y87: FALSE | Z87: FALSE | AA87: TRUE | AB87: TRUE | AC87: TRUE | AD87: TRUE | AE87: FALSE | AF87: FALSE | AG87: FALSE | AH87: 0 | AI87: FALSE | AJ87: FALSE | AK87: TRUE | AL87: 0 | AM87: FUNDING | AN87: 0
A88: AllThrough | E88: DFC_PUPIL_PRI | F88: DFC Primary Per pupil | G88: FALSE | H88: TRUE | I88: TRUE | J88: TRUE | K88: FALSE | L88: TRUE | M88: FALSE | N88: 0 | O88: FALSE | P88: FALSE | Q88: FALSE | R88: FALSE | S88: FALSE | T88: TRUE | U88: FALSE | V88: TRUE | W88: FALSE | X88: 1 | Y88: FALSE | Z88: FALSE | AA88: TRUE | AB88: TRUE | AC88: TRUE | AD88: TRUE | AE88: FALSE | AF88: FALSE | AG88: FALSE | AH88: 0 | AI88: FALSE | AJ88: FALSE | AK88: TRUE | AL88: 0 | AM88: FUNDING | AN88: 0
A89: AllThrough | E89: DFC_PUPIL_SEC | F89: DFC Secondary Per pupil | G89: FALSE | H89: TRUE | I89: TRUE | J89: TRUE | K89: FALSE | L89: TRUE | M89: FALSE | N89: 0 | O89: FALSE | P89: FALSE | Q89: FALSE | R89: FALSE | S89: FALSE | T89: TRUE | U89: FALSE | V89: TRUE | W89: FALSE | X89: 1 | Y89: FALSE | Z89: FALSE | AA89: TRUE | AB89: TRUE | AC89: TRUE | AD89: TRUE | AE89: FALSE | AF89: FALSE | AG89: FALSE | AH89: 0 | AI89: FALSE | AJ89: FALSE | AK89: TRUE | AL89: 0 | AM89: FUNDING | AN89: 0
A90: AllThrough | E90: FTE_KS5 | F90: Funded Pupils KS5 | G90: FALSE | H90: FALSE | I90: FALSE | J90: TRUE | K90: FALSE | L90: TRUE | M90: FALSE | N90: 0 | O90: FALSE | P90: FALSE | Q90: FALSE | R90: FALSE | S90: FALSE | T90: TRUE | U90: FALSE | V90: TRUE | W90: FALSE | X90: 1 | Y90: FALSE | Z90: FALSE | AA90: FALSE | AB90: FALSE | AC90: FALSE | AD90: TRUE | AE90: FALSE | AF90: TRUE | AG90: FALSE | AH90: 1 | AI90: FALSE | AJ90: FALSE | AK90: TRUE | AL90: 0 | AM90: PUPILNUMBERS | AN90: 0
A91: AllThrough | E91: FTE_NUR | F91: Funded Pupils Nursery | G91: FALSE | H91: FALSE | I91: FALSE | J91: TRUE | K91: FALSE | L91: TRUE | M91: FALSE | N91: 0 | O91: FALSE | P91: FALSE | Q91: FALSE | R91: FALSE | S91: FALSE | T91: TRUE | U91: FALSE | V91: TRUE | W91: FALSE | X91: 1 | Y91: FALSE | Z91: FALSE | AA91: FALSE | AB91: FALSE | AC91: FALSE | AD91: TRUE | AE91: FALSE | AF91: TRUE | AG91: FALSE | AH91: 1 | AI91: FALSE | AJ91: FALSE | AK91: TRUE | AL91: 0 | AM91: PUPILNUMBERS | AN91: 0
A92: AllThrough | E92: FUNDED_FS | F92: Funded Pupils Foundation | G92: FALSE | H92: FALSE | I92: FALSE | J92: TRUE | K92: FALSE | L92: TRUE | M92: FALSE | N92: 0 | O92: FALSE | P92: FALSE | Q92: FALSE | R92: FALSE | S92: FALSE | T92: TRUE | U92: FALSE | V92: TRUE | W92: FALSE | X92: 1 | Y92: FALSE | Z92: FALSE | AA92: FALSE | AB92: FALSE | AC92: FALSE | AD92: TRUE | AE92: FALSE | AF92: TRUE | AG92: FALSE | AH92: 1 | AI92: FALSE | AJ92: FALSE | AK92: TRUE | AL92: 1 | AM92: PUPILNUMBERS | AN92: 1
A93: AllThrough | E93: FUNDED_KS1 | F93: Funded Pupils KS1 | G93: FALSE | H93: FALSE | I93: FALSE | J93: TRUE | K93: FALSE | L93: TRUE | M93: FALSE | N93: 0 | O93: FALSE | P93: FALSE | Q93: FALSE | R93: FALSE | S93: FALSE | T93: TRUE | U93: FALSE | V93: TRUE | W93: FALSE | X93: 1 | Y93: FALSE | Z93: FALSE | AA93: FALSE | AB93: FALSE | AC93: FALSE | AD93: TRUE | AE93: FALSE | AF93: TRUE | AG93: FALSE | AH93: 1 | AI93: FALSE | AJ93: FALSE | AK93: TRUE | AL93: 1 | AM93: PUPILNUMBERS | AN93: 1
A94: AllThrough | E94: FUNDED_KS2 | F94: Funded Pupils KS2 | G94: FALSE | H94: FALSE | I94: FALSE | J94: TRUE | K94: FALSE | L94: TRUE | M94: FALSE | N94: 0 | O94: FALSE | P94: FALSE | Q94: FALSE | R94: FALSE | S94: FALSE | T94: TRUE | U94: FALSE | V94: TRUE | W94: FALSE | X94: 1 | Y94: FALSE | Z94: FALSE | AA94: FALSE | AB94: FALSE | AC94: FALSE | AD94: TRUE | AE94: FALSE | AF94: TRUE | AG94: FALSE | AH94: 1 | AI94: FALSE | AJ94: FALSE | AK94: TRUE | AL94: 1 | AM94: PUPILNUMBERS | AN94: 1
A95: AllThrough | E95: FUNDED_KS3 | F95: Funded Pupils KS3 | G95: FALSE | H95: FALSE | I95: FALSE | J95: TRUE | K95: FALSE | L95: TRUE | M95: FALSE | N95: 0 | O95: FALSE | P95: FALSE | Q95: FALSE | R95: FALSE | S95: FALSE | T95: TRUE | U95: FALSE | V95: TRUE | W95: FALSE | X95: 1 | Y95: FALSE | Z95: FALSE | AA95: FALSE | AB95: FALSE | AC95: FALSE | AD95: TRUE | AE95: FALSE | AF95: TRUE | AG95: FALSE | AH95: 1 | AI95: FALSE | AJ95: FALSE | AK95: TRUE | AL95: 1 | AM95: PUPILNUMBERS | AN95: 1
A96: AllThrough | E96: FUNDED_KS4 | F96: Funded Pupils KS4 | G96: FALSE | H96: FALSE | I96: FALSE | J96: TRUE | K96: FALSE | L96: TRUE | M96: FALSE | N96: 0 | O96: FALSE | P96: FALSE | Q96: FALSE | R96: FALSE | S96: FALSE | T96: TRUE | U96: FALSE | V96: TRUE | W96: FALSE | X96: 1 | Y96: FALSE | Z96: FALSE | AA96: FALSE | AB96: FALSE | AC96: FALSE | AD96: TRUE | AE96: FALSE | AF96: TRUE | AG96: FALSE | AH96: 1 | AI96: FALSE | AJ96: FALSE | AK96: TRUE | AL96: 1 | AM96: PUPILNUMBERS | AN96: 1
A97: AllThrough | E97: FUNDED_KS5 | F97: Funded Pupils KS5 | G97: FALSE | H97: FALSE | I97: FALSE | J97: TRUE | K97: FALSE | L97: TRUE | M97: FALSE | N97: 0 | O97: FALSE | P97: FALSE | Q97: FALSE | R97: FALSE | S97: FALSE | T97: TRUE | U97: FALSE | V97: TRUE | W97: FALSE | X97: 1 | Y97: FALSE | Z97: FALSE | AA97: FALSE | AB97: FALSE | AC97: FALSE | AD97: TRUE | AE97: FALSE | AF97: TRUE | AG97: FALSE | AH97: 1 | AI97: FALSE | AJ97: FALSE | AK97: TRUE | AL97: 1 | AM97: PUPILNUMBERS | AN97: 1
... A108: AllThrough | E108: HNPF_PRE16O | F108: Total HN Place Pre 16 Occupied | G108: FALSE | H108: TRUE | I108: TRUE | J108: TRUE | K108: FALSE | L108: FALSE | M108: FALSE | N108: 0 | O108: FALSE | P108: FALSE | Q108: FALSE | R108: FALSE | S108: FALSE | T108: TRUE | U108: FALSE | V108: TRUE | W108: FALSE | X108: 1 | Y108: FALSE | Z108: FALSE | AA108: TRUE | AB108: TRUE | AC108: TRUE | AD108: TRUE | AE108: FALSE | AF108: FALSE | AG108: FALSE | AH108: 0 | AI108: FALSE | AJ108: FALSE | AK108: TRUE | AL108: 1 | AM108: FUNDING | AN108: 1
A109: AllThrough | C109: LA1 | D109: PRI | E109: LUMP | F109: Lump Sum Primary | G109: TRUE | H109: TRUE | I109: TRUE | J109: TRUE | K109: FALSE | L109: FALSE | M109: FALSE | N109: 0 | O109: FALSE | P109: FALSE | Q109: FALSE | R109: FALSE | S109: FALSE | T109: TRUE | U109: FALSE | V109: TRUE | W109: FALSE | X109: 1 | Y109: FALSE | Z109: FALSE | AA109: FALSE | AB109: FALSE | AC109: FALSE | AD109: TRUE | AE109: FALSE | AF109: TRUE | AG109: TRUE | AH109: 1 | AI109: FALSE | AJ109: FALSE | AK109: TRUE | AL109: 1 | AM109: FUNDING | AN109: 1
A110: AllThrough | C110: LA2 | D110: PRI | E110: LUMP | F110: Lump Sum Primary | G110: TRUE | H110: TRUE | I110: TRUE | J110: TRUE | K110: FALSE | L110: FALSE | M110: FALSE | N110: 0 | O110: FALSE | P110: FALSE | Q110: FALSE | R110: FALSE | S110: FALSE | T110: TRUE | U110: FALSE | V110: TRUE | W110: FALSE | X110: 1 | Y110: FALSE | Z110: FALSE | AA110: FALSE | AB110: FALSE | AC110: FALSE | AD110: TRUE | AE110: FALSE | AF110: TRUE | AG110: TRUE | AH110: 1 | AI110: FALSE | AJ110: FALSE | AK110: TRUE | AL110: 1 | AM110: FUNDING | AN110: 1
A111: AllThrough | C111: LA3 | D111: PRI | E111: LUMP | F111: Lump Sum Primary | G111: TRUE | H111: TRUE | I111: TRUE | J111: TRUE | K111: FALSE | L111: FALSE | M111: FALSE | N111: 0 | O111: FALSE | P111: FALSE | Q111: FALSE | R111: FALSE | S111: FALSE | T111: TRUE | U111: FALSE | V111: TRUE | W111: FALSE | X111: 1 | Y111: FALSE | Z111: FALSE | AA111: FALSE | AB111: FALSE | AC111: FALSE | AD111: TRUE | AE111: FALSE | AF111: TRUE | AG111: TRUE | AH111: 1 | AI111: FALSE | AJ111: FALSE | AK111: TRUE | AL111: 1 | AM111: FUNDING | AN111: 1
A112: AllThrough | C112: LA4 | D112: PRI | E112: LUMP | F112: Lump Sum Primary | G112: TRUE | H112: TRUE | I112: TRUE | J112: TRUE | K112: FALSE | L112: FALSE | M112: FALSE | N112: 0 | O112: FALSE | P112: FALSE | Q112: FALSE | R112: FALSE | S112: FALSE | T112: TRUE | U112: FALSE | V112: TRUE | W112: FALSE | X112: 1 | Y112: FALSE | Z112: FALSE | AA112: FALSE | AB112: FALSE | AC112: FALSE | AD112: TRUE | AE112: FALSE | AF112: TRUE | AG112: TRUE | AH112: 1 | AI112: FALSE | AJ112: FALSE | AK112: TRUE | AL112: 1 | AM112: FUNDING | AN112: 1
A113: AllThrough | C113: LA5 | D113: PRI | E113: LUMP | F113: Lump Sum Primary | G113: TRUE | H113: TRUE | I113: TRUE | J113: TRUE | K113: FALSE | L113: FALSE | M113: FALSE | N113: 0 | O113: FALSE | P113: FALSE | Q113: FALSE | R113: FALSE | S113: FALSE | T113: TRUE | U113: FALSE | V113: TRUE | W113: FALSE | X113: 1 | Y113: FALSE | Z113: FALSE | AA113: FALSE | AB113: FALSE | AC113: FALSE | AD113: TRUE | AE113: FALSE | AF113: TRUE | AG113: TRUE | AH113: 1 | AI113: FALSE | AJ113: FALSE | AK113: TRUE | AL113: 1 | AM113: FUNDING | AN113: 1
A114: AllThrough | C114: LA6 | D114: PRI | E114: LUMP | F114: Lump Sum Primary | G114: TRUE | H114: TRUE | I114: TRUE | J114: TRUE | K114: FALSE | L114: FALSE | M114: FALSE | N114: 0 | O114: FALSE | P114: FALSE | Q114: FALSE | R114: FALSE | S114: FALSE | T114: TRUE | U114: FALSE | V114: TRUE | W114: FALSE | X114: 1 | Y114: FALSE | Z114: FALSE | AA114: FALSE | AB114: FALSE | AC114: FALSE | AD114: TRUE | AE114: FALSE | AF114: TRUE | AG114: TRUE | AH114: 1 | AI114: FALSE | AJ114: FALSE | AK114: TRUE | AL114: 1 | AM114: FUNDING | AN114: 1
A115: AllThrough | C115: LA1 | D115: SEC | E115: LUMP | F115: Lump Sum Secondary | G115: TRUE | H115: TRUE | I115: TRUE | J115: TRUE | K115: FALSE | L115: FALSE | M115: FALSE | N115: 0 | O115: FALSE | P115: FALSE | Q115: FALSE | R115: FALSE | S115: FALSE | T115: TRUE | U115: FALSE | V115: TRUE | W115: FALSE | X115: 1 | Y115: FALSE | Z115: FALSE | AA115: FALSE | AB115: FALSE | AC115: FALSE | AD115: TRUE | AE115: FALSE | AF115: TRUE | AG115: TRUE | AH115: 1 | AI115: FALSE | AJ115: FALSE | AK115: TRUE | AL115: 1 | AM115: FUNDING | AN115: 1
A116: AllThrough | C116: LA2 | D116: SEC | E116: LUMP | F116: Lump Sum Secondary | G116: TRUE | H116: TRUE | I116: TRUE | J116: TRUE | K116: FALSE | L116: FALSE | M116: FALSE | N116: 0 | O116: FALSE | P116: FALSE | Q116: FALSE | R116: FALSE | S116: FALSE | T116: TRUE | U116: FALSE | V116: TRUE | W116: FALSE | X116: 1 | Y116: FALSE | Z116: FALSE | AA116: FALSE | AB116: FALSE | AC116: FALSE | AD116: TRUE | AE116: FALSE | AF116: TRUE | AG116: TRUE | AH116: 1 | AI116: FALSE | AJ116: FALSE | AK116: TRUE | AL116: 1 | AM116: FUNDING | AN116: 1
A117: AllThrough | C117: LA3 | D117: SEC | E117: LUMP | F117: Lump Sum Secondary | G117: TRUE | H117: TRUE | I117: TRUE | J117: TRUE | K117: FALSE | L117: FALSE | M117: FALSE | N117: 0 | O117: FALSE | P117: FALSE | Q117: FALSE | R117: FALSE | S117: FALSE | T117: TRUE | U117: FALSE | V117: TRUE | W117: FALSE | X117: 1 | Y117: FALSE | Z117: FALSE | AA117: FALSE | AB117: FALSE | AC117: FALSE | AD117: TRUE | AE117: FALSE | AF117: TRUE | AG117: TRUE | AH117: 1 | AI117: FALSE | AJ117: FALSE | AK117: TRUE | AL117: 1 | AM117: FUNDING | AN117: 1
A118: AllThrough | C118: LA4 | D118: SEC | E118: LUMP | F118: Lump Sum Secondary | G118: TRUE | H118: TRUE | I118: TRUE | J118: TRUE | K118: FALSE | L118: FALSE | M118: FALSE | N118: 0 | O118: FALSE | P118: FALSE | Q118: FALSE | R118: FALSE | S118: FALSE | T118: TRUE | U118: FALSE | V118: TRUE | W118: FALSE | X118: 1 | Y118: FALSE | Z118: FALSE | AA118: FALSE | AB118: FALSE | AC118: FALSE | AD118: TRUE | AE118: FALSE | AF118: TRUE | AG118: TRUE | AH118: 1 | AI118: FALSE | AJ118: FALSE | AK118: TRUE | AL118: 1 | AM118: FUNDING | AN118: 1
A119: AllThrough | C119: LA5 | D119: SEC | E119: LUMP | F119: Lump Sum Secondary | G119: TRUE | H119: TRUE | I119: TRUE | J119: TRUE | K119: FALSE | L119: FALSE | M119: FALSE | N119: 0 | O119: FALSE | P119: FALSE | Q119: FALSE | R119: FALSE | S119: FALSE | T119: TRUE | U119: FALSE | V119: TRUE | W119: FALSE | X119: 1 | Y119: FALSE | Z119: FALSE | AA119: FALSE | AB119: FALSE | AC119: FALSE | AD119: TRUE | AE119: FALSE | AF119: TRUE | AG119: TRUE | AH119: 1 | AI119: FALSE | AJ119: FALSE | AK119: TRUE | AL119: 1 | AM119: FUNDING | AN119: 1
A120: AllThrough | C120: LA6 | D120: SEC | E120: LUMP | F120: Lump Sum Secondary | G120: TRUE | H120: TRUE | I120: TRUE | J120: TRUE | K120: FALSE | L120: FALSE | M120: FALSE | N120: 0 | O120: FALSE | P120: FALSE | Q120: FALSE | R120: FALSE | S120: FALSE | T120: TRUE | U120: FALSE | V120: TRUE | W120: FALSE | X120: 1 | Y120: FALSE | Z120: FALSE | AA120: FALSE | AB120: FALSE | AC120: FALSE | AD120: TRUE | AE120: FALSE | AF120: TRUE | AG120: TRUE | AH120: 1 | AI120: FALSE | AJ120: FALSE | AK120: TRUE | AL120: 1 | AM120: FUNDING | AN120: 1
... A132: AllThrough | C132: LA12 | D132: SEC | E132: LUMP | F132: Lump Sum Secondary | G132: TRUE | H132: TRUE | I132: TRUE | J132: TRUE | K132: FALSE | L132: FALSE | M132: FALSE | N132: 0 | O132: FALSE | P132: FALSE | Q132: FALSE | R132: FALSE | S132: FALSE | T132: TRUE | U132: FALSE | V132: TRUE | W132: FALSE | X132: 1 | Y132: FALSE | Z132: FALSE | AA132: FALSE | AB132: FALSE | AC132: FALSE | AD132: TRUE | AE132: FALSE | AF132: TRUE | AG132: TRUE | AH132: 1 | AI132: FALSE | AJ132: FALSE | AK132: TRUE | AL132: 1 | AM132: FUNDING | AN132: 1
A133: AllThrough | E133: PEG_CORE | F133: PE Grant Core | G133: TRUE | H133: TRUE | I133: TRUE | J133: TRUE | K133: FALSE | L133: FALSE | M133: FALSE | N133: 0 | O133: FALSE | P133: FALSE | Q133: FALSE | R133: FALSE | S133: FALSE | T133: TRUE | U133: FALSE | V133: TRUE | W133: FALSE | X133: 1 | Y133: FALSE | Z133: FALSE | AA133: FALSE | AB133: FALSE | AC133: FALSE | AD133: TRUE | AE133: FALSE | AF133: TRUE | AG133: FALSE | AH133: 1 | AI133: FALSE | AJ133: FALSE | AK133: TRUE | AL133: 1 | AM133: FUNDING | AN133: 1
A134: AllThrough | E134: PEG_PUPIL | F134: PE Grant Per pupil | G134: FALSE | H134: TRUE | I134: TRUE | J134: TRUE | K134: FALSE | L134: TRUE | M134: FALSE | N134: 0 | O134: FALSE | P134: FALSE | Q134: FALSE | R134: FALSE | S134: FALSE | T134: TRUE | U134: FALSE | V134: TRUE | W134: FALSE | X134: 1 | Y134: FALSE | Z134: FALSE | AA134: TRUE | AB134: TRUE | AC134: TRUE | AD134: TRUE | AE134: FALSE | AF134: FALSE | AG134: FALSE | AH134: 0 | AI134: FALSE | AJ134: FALSE | AK134: TRUE | AL134: 1 | AM134: FUNDING | AN134: 1
A135: AllThrough | B135: England & Wales | E135: PENS_EW_5/12 | F135: Teachers Pensions Grant Post 16 April - August (EW) | G135: FALSE | H135: TRUE | I135: TRUE | J135: TRUE | K135: FALSE | L135: FALSE | M135: FALSE | N135: 0 | O135: FALSE | P135: FALSE | Q135: FALSE | R135: FALSE | S135: FALSE | T135: FALSE | U135: FALSE | V135: FALSE | W135: FALSE | X135: 1 | Y135: FALSE | Z135: FALSE | AA135: TRUE | AB135: TRUE | AC135: TRUE | AD135: TRUE | AE135: FALSE | AF135: FALSE | AG135: FALSE | AH135: 0 | AI135: FALSE | AJ135: FALSE | AK135: TRUE | AL135: 1 | AM135: BUDGET | AN135: 1
A136: AllThrough | B136: England & Wales | E136: PENS_EW_7/12 | F136: Teachers Pensions Grant Post 16 September - March (EW) | G136: FALSE | H136: TRUE | I136: TRUE | J136: TRUE | K136: FALSE | L136: FALSE | M136: FALSE | N136: 0 | O136: FALSE | P136: FALSE | Q136: FALSE | R136: FALSE | S136: FALSE | T136: FALSE | U136: FALSE | V136: FALSE | W136: FALSE | X136: 1 | Y136: FALSE | Z136: FALSE | AA136: TRUE | AB136: TRUE | AC136: TRUE | AD136: TRUE | AE136: FALSE | AF136: FALSE | AG136: FALSE | AH136: 0 | AI136: FALSE | AJ136: FALSE | AK136: TRUE | AL136: 1 | AM136: BUDGET | AN136: 1
A137: AllThrough | B137: Fringe | E137: PENS_FRI_5/12 | F137: Teachers Pensions Grant Post 16 April - August (Fringe) | G137: FALSE | H137: TRUE | I137: TRUE | J137: TRUE | K137: FALSE | L137: FALSE | M137: FALSE | N137: 0 | O137: FALSE | P137: FALSE | Q137: FALSE | R137: FALSE | S137: FALSE | T137: FALSE | U137: FALSE | V137: FALSE | W137: FALSE | X137: 1 | Y137: FALSE | Z137: FALSE | AA137: TRUE | AB137: TRUE | AC137: TRUE | AD137: TRUE | AE137: FALSE | AF137: FALSE | AG137: FALSE | AH137: 0 | AI137: FALSE | AJ137: FALSE | AK137: TRUE | AL137: 1 | AM137: BUDGET | AN137: 1
A138: AllThrough | B138: Fringe | E138: PENS_FRI_7/12 | F138: Teachers Pensions Grant Post 16 September - March (Fringe) | G138: FALSE | H138: TRUE | I138: TRUE | J138: TRUE | K138: FALSE | L138: FALSE | M138: FALSE | N138: 0 | O138: FALSE | P138: FALSE | Q138: FALSE | R138: FALSE | S138: FALSE | T138: FALSE | U138: FALSE | V138: FALSE | W138: FALSE | X138: 1 | Y138: FALSE | Z138: FALSE | AA138: TRUE | AB138: TRUE | AC138: TRUE | AD138: TRUE | AE138: FALSE | AF138: FALSE | AG138: FALSE | AH138: 0 | AI138: FALSE | AJ138: FALSE | AK138: TRUE | AL138: 1 | AM138: BUDGET | AN138: 1
A139: AllThrough | B139: Inner | E139: PENS_INN_5/12 | F139: Teachers Pensions Grant Post 16 April - August (Inner) | G139: FALSE | H139: TRUE | I139: TRUE | J139: TRUE | K139: FALSE | L139: FALSE | M139: FALSE | N139: 0 | O139: FALSE | P139: FALSE | Q139: FALSE | R139: FALSE | S139: FALSE | T139: FALSE | U139: FALSE | V139: FALSE | W139: FALSE | X139: 1 | Y139: FALSE | Z139: FALSE | AA139: TRUE | AB139: TRUE | AC139: TRUE | AD139: TRUE | AE139: FALSE | AF139: FALSE | AG139: FALSE | AH139: 0 | AI139: FALSE | AJ139: FALSE | AK139: TRUE | AL139: 1 | AM139: BUDGET | AN139: 1
A140: AllThrough | B140: Inner | E140: PENS_INN_7/12 | F140: Teachers Pensions Grant Post 16 September - March (Inner) | G140: FALSE | H140: TRUE | I140: TRUE | J140: TRUE | K140: FALSE | L140: FALSE | M140: FALSE | N140: 0 | O140: FALSE | P140: FALSE | Q140: FALSE | R140: FALSE | S140: FALSE | T140: FALSE | U140: FALSE | V140: FALSE | W140: FALSE | X140: 1 | Y140: FALSE | Z140: FALSE | AA140: TRUE | AB140: TRUE | AC140: TRUE | AD140: TRUE | AE140: FALSE | AF140: FALSE | AG140: FALSE | AH140: 0 | AI140: FALSE | AJ140: FALSE | AK140: TRUE | AL140: 1 | AM140: BUDGET | AN140: 1
A141: AllThrough | B141: Outer | E141: PENS_OUT_5/12 | F141: Teachers Pensions Grant Post 16 April - August (Outer) | G141: FALSE | H141: TRUE | I141: TRUE | J141: TRUE | K141: FALSE | L141: FALSE | M141: FALSE | N141: 0 | O141: FALSE | P141: FALSE | Q141: FALSE | R141: FALSE | S141: FALSE | T141: FALSE | U141: FALSE | V141: FALSE | W141: FALSE | X141: 1 | Y141: FALSE | Z141: FALSE | AA141: TRUE | AB141: TRUE | AC141: TRUE | AD141: TRUE | AE141: FALSE | AF141: FALSE | AG141: FALSE | AH141: 0 | AI141: FALSE | AJ141: FALSE | AK141: TRUE | AL141: 1 | AM141: BUDGET | AN141: 1
A142: AllThrough | B142: Outer | E142: PENS_OUT_7/12 | F142: Teachers Pensions Grant Post 16 September - March (Outer) | G142: FALSE | H142: TRUE | I142: TRUE | J142: TRUE | K142: FALSE | L142: FALSE | M142: FALSE | N142: 0 | O142: FALSE | P142: FALSE | Q142: FALSE | R142: FALSE | S142: FALSE | T142: FALSE | U142: FALSE | V142: FALSE | W142: FALSE | X142: 1 | Y142: FALSE | Z142: FALSE | AA142: TRUE | AB142: TRUE | AC142: TRUE | AD142: TRUE | AE142: FALSE | AF142: FALSE | AG142: FALSE | AH142: 0 | AI142: FALSE | AJ142: FALSE | AK142: TRUE | AL142: 1 | AM142: BUDGET | AN142: 1
A143: AllThrough | E143: PUP_PREM_PRI_5/12 | F143: Pupil Premium Primary 5/12ths Apr-Aug | G143: FALSE | H143: TRUE | I143: TRUE | J143: TRUE | K143: FALSE | L143: FALSE | M143: FALSE | N143: 0 | O143: FALSE | P143: FALSE | Q143: FALSE | R143: FALSE | S143: FALSE | T143: FALSE | U143: FALSE | V143: FALSE | W143: FALSE | X143: 12 | Y143: FALSE | Z143: FALSE | AA143: FALSE | AB143: FALSE | AC143: FALSE | AD143: FALSE | AE143: FALSE | AF143: FALSE | AG143: FALSE | AH143: 5 | AI143: FALSE | AJ143: FALSE | AK143: TRUE | AL143: 1 | AM143: BUDGET | AN143: 1
A144: AllThrough | E144: PUP_PREM_PRI_7/12 | F144: Pupil Premium Primary 7/12ths Sep-Mar | G144: FALSE | H144: TRUE | I144: TRUE | J144: TRUE | K144: FALSE | L144: TRUE | M144: FALSE | N144: 0 | O144: FALSE | P144: FALSE | Q144: FALSE | R144: FALSE | S144: FALSE | T144: FALSE | U144: FALSE | V144: FALSE | W144: FALSE | X144: 12 | Y144: FALSE | Z144: FALSE | AA144: FALSE | AB144: FALSE | AC144: FALSE | AD144: FALSE | AE144: FALSE | AF144: FALSE | AG144: FALSE | AH144: 7 | AI144: FALSE | AJ144: FALSE | AK144: TRUE | AL144: 1 | AM144: BUDGET | AN144: 1
A145: AllThrough | E145: PUP_PREM_SEC_5/12 | F145: Pupil Premium Secondary 5/12ths Apr-Aug | G145: FALSE | H145: TRUE | I145: TRUE | J145: TRUE | K145: FALSE | L145: FALSE | M145: FALSE | N145: 0 | O145: FALSE | P145: FALSE | Q145: FALSE | R145: FALSE | S145: FALSE | T145: FALSE | U145: FALSE | V145: FALSE | W145: FALSE | X145: 12 | Y145: FALSE | Z145: FALSE | AA145: FALSE | AB145: FALSE | AC145: FALSE | AD145: FALSE | AE145: FALSE | AF145: FALSE | AG145: FALSE | AH145: 5 | AI145: FALSE | AJ145: FALSE | AK145: TRUE | AL145: 1 | AM145: BUDGET | AN145: 1
A146: AllThrough | E146: PUP_PREM_SEC_7/12 | F146: Pupil Premium Secondary 7/12ths Sep-Mar | G146: FALSE | H146: TRUE | I146: TRUE | J146: TRUE | K146: FALSE | L146: TRUE | M146: FALSE | N146: 0 | O146: FALSE | P146: FALSE | Q146: FALSE | R146: FALSE | S146: FALSE | T146: FALSE | U146: FALSE | V146: FALSE | W146: FALSE | X146: 12 | Y146: FALSE | Z146: FALSE | AA146: FALSE | AB146: FALSE | AC146: FALSE | AD146: FALSE | AE146: FALSE | AF146: FALSE | AG146: FALSE | AH146: 7 | AI146: FALSE | AJ146: FALSE | AK146: TRUE | AL146: 1 | AM146: BUDGET | AN146: 1
A147: AllThrough | E147: PUPIL_SPRING_FS | F147: Foundation Spring Census from Oct numbers | G147: FALSE | H147: TRUE | I147: TRUE | J147: TRUE | K147: FALSE | L147: FALSE | M147: FALSE | N147: 0 | O147: FALSE | P147: FALSE | Q147: FALSE | R147: FALSE | S147: FALSE | T147: FALSE | U147: FALSE | V147: FALSE | W147: FALSE | X147: 1 | Y147: FALSE | Z147: FALSE | AA147: TRUE | AB147: TRUE | AC147: TRUE | AD147: TRUE | AE147: FALSE | AF147: FALSE | AG147: FALSE | AH147: 1 | AI147: FALSE | AJ147: FALSE | AK147: TRUE | AL147: 0 | AM147: PUPILNUMBERS | AN147: 0
A148: AllThrough | E148: PUPIL_SPRING_KS1 | F148: KS1 Spring Census from Oct numbers | G148: FALSE | H148: TRUE | I148: TRUE | J148: TRUE | K148: FALSE | L148: FALSE | M148: FALSE | N148: 0 | O148: FALSE | P148: FALSE | Q148: FALSE | R148: FALSE | S148: FALSE | T148: FALSE | U148: FALSE | V148: FALSE | W148: FALSE | X148: 1 | Y148: FALSE | Z148: FALSE | AA148: TRUE | AB148: TRUE | AC148: TRUE | AD148: TRUE | AE148: FALSE | AF148: FALSE | AG148: FALSE | AH148: 1 | AI148: FALSE | AJ148: FALSE | AK148: TRUE | AL148: 0 | AM148: PUPILNUMBERS | AN148: 0
A149: AllThrough | E149: PUPIL_SPRING_KS2 | F149: KS2 Spring Census from Oct numbers | G149: FALSE | H149: TRUE | I149: TRUE | J149: TRUE | K149: FALSE | L149: FALSE | M149: FALSE | N149: 0 | O149: FALSE | P149: FALSE | Q149: FALSE | R149: FALSE | S149: FALSE | T149: FALSE | U149: FALSE | V149: FALSE | W149: FALSE | X149: 1 | Y149: FALSE | Z149: FALSE | AA149: TRUE | AB149: TRUE | AC149: TRUE | AD149: TRUE | AE149: FALSE | AF149: FALSE | AG149: FALSE | AH149: 1 | AI149: FALSE | AJ149: FALSE | AK149: TRUE | AL149: 0 | AM149: PUPILNUMBERS | AN149: 0
A150: AllThrough | E150: PUPIL_SPRING_KS3 | F150: KS3 Spring Census from Oct numbers | G150: FALSE | H150: TRUE | I150: TRUE | J150: TRUE | K150: FALSE | L150: FALSE | M150: FALSE | N150: 0 | O150: FALSE | P150: FALSE | Q150: FALSE | R150: FALSE | S150: FALSE | T150: FALSE | U150: FALSE | V150: FALSE | W150: FALSE | X150: 1 | Y150: FALSE | Z150: FALSE | AA150: TRUE | AB150: TRUE | AC150: TRUE | AD150: TRUE | AE150: FALSE | AF150: FALSE | AG150: FALSE | AH150: 1 | AI150: FALSE | AJ150: FALSE | AK150: TRUE | AL150: 0 | AM150: PUPILNUMBERS | AN150: 0
A151: AllThrough | E151: PUPIL_SPRING_KS4 | F151: KS4 Spring Census from Oct numbers | G151: FALSE | H151: TRUE | I151: TRUE | J151: TRUE | K151: FALSE | L151: FALSE | M151: FALSE | N151: 0 | O151: FALSE | P151: FALSE | Q151: FALSE | R151: FALSE | S151: FALSE | T151: FALSE | U151: FALSE | V151: FALSE | W151: FALSE | X151: 1 | Y151: FALSE | Z151: FALSE | AA151: TRUE | AB151: TRUE | AC151: TRUE | AD151: TRUE | AE151: FALSE | AF151: FALSE | AG151: FALSE | AH151: 1 | AI151: FALSE | AJ151: FALSE | AK151: TRUE | AL151: 0 | AM151: PUPILNUMBERS | AN151: 0
A152: AllThrough | E152: PUPIL_SPRING_KS5 | F152: KS5 Spring Census from Oct numbers | G152: FALSE | H152: TRUE | I152: TRUE | J152: TRUE | K152: FALSE | L152: FALSE | M152: FALSE | N152: 0 | O152: FALSE | P152: FALSE | Q152: FALSE | R152: FALSE | S152: FALSE | T152: FALSE | U152: FALSE | V152: FALSE | W152: FALSE | X152: 1 | Y152: FALSE | Z152: FALSE | AA152: TRUE | AB152: TRUE | AC152: TRUE | AD152: TRUE | AE152: FALSE | AF152: FALSE | AG152: FALSE | AH152: 1 | AI152: FALSE | AJ152: FALSE | AK152: TRUE | AL152: 0 | AM152: PUPILNUMBERS | AN152: 0
A153: AllThrough | E153: PUPIL_SPRING_NUR | F153: Nursery Spring Census from Oct numbers | G153: FALSE | H153: TRUE | I153: TRUE | J153: TRUE | K153: FALSE | L153: FALSE | M153: FALSE | N153: 0 | O153: FALSE | P153: FALSE | Q153: FALSE | R153: FALSE | S153: FALSE | T153: FALSE | U153: FALSE | V153: FALSE | W153: FALSE | X153: 1 | Y153: FALSE | Z153: FALSE | AA153: TRUE | AB153: TRUE | AC153: TRUE | AD153: TRUE | AE153: FALSE | AF153: FALSE | AG153: FALSE | AH153: 1 | AI153: FALSE | AJ153: FALSE | AK153: TRUE | AL153: 0 | AM153: PUPILNUMBERS | AN153: 0
A154: AllThrough | E154: PUPILY00_LY | F154: Reception Pupils LY | G154: FALSE | H154: FALSE | I154: FALSE | J154: TRUE | K154: FALSE | L154: TRUE | M154: FALSE | N154: 0 | O154: FALSE | P154: FALSE | Q154: FALSE | R154: FALSE | S154: FALSE | T154: TRUE | U154: FALSE | V154: TRUE | W154: FALSE | X154: 1 | Y154: FALSE | Z154: FALSE | AA154: FALSE | AB154: FALSE | AC154: FALSE | AD154: TRUE | AE154: FALSE | AF154: TRUE | AG154: FALSE | AH154: 1 | AI154: FALSE | AJ154: FALSE | AK154: TRUE | AL154: 0 | AM154: PUPILNUMBERS | AN154: 0
... A206: College | E206: HNPF_POST16O | F206: Total HN Place Post 16 Occupied | G206: FALSE | H206: TRUE | I206: TRUE | J206: TRUE | K206: FALSE | L206: FALSE | M206: FALSE | N206: 0 | O206: FALSE | P206: FALSE | Q206: FALSE | R206: FALSE | S206: FALSE | T206: TRUE | U206: FALSE | V206: TRUE | W206: FALSE | X206: 1 | Y206: FALSE | Z206: FALSE | AA206: TRUE | AB206: TRUE | AC206: TRUE | AD206: TRUE | AE206: FALSE | AF206: FALSE | AG206: FALSE | AH206: 0 | AI206: FALSE | AJ206: FALSE | AK206: TRUE | AL206: 1 | AM206: FUNDING | AN206: 1
A207: College | B207: England & Wales | E207: PENS_EW_5/12 | F207: Teachers Pensions Grant Post 16 April - August (EW) | G207: FALSE | H207: TRUE | I207: TRUE | J207: TRUE | K207: FALSE | L207: FALSE | M207: FALSE | N207: 0 | O207: FALSE | P207: FALSE | Q207: FALSE | R207: FALSE | S207: FALSE | T207: FALSE | U207: FALSE | V207: FALSE | W207: FALSE | X207: 1 | Y207: FALSE | Z207: FALSE | AA207: TRUE | AB207: TRUE | AC207: TRUE | AD207: TRUE | AE207: FALSE | AF207: FALSE | AG207: FALSE | AH207: 0 | AI207: FALSE | AJ207: FALSE | AK207: TRUE | AL207: 1 | AM207: BUDGET | AN207: 1
A208: College | B208: England & Wales | E208: PENS_EW_7/12 | F208: Teachers Pensions Grant Post 16 September - March (EW) | G208: FALSE | H208: TRUE | I208: TRUE | J208: TRUE | K208: FALSE | L208: FALSE | M208: FALSE | N208: 0 | O208: FALSE | P208: FALSE | Q208: FALSE | R208: FALSE | S208: FALSE | T208: FALSE | U208: FALSE | V208: FALSE | W208: FALSE | X208: 1 | Y208: FALSE | Z208: FALSE | AA208: TRUE | AB208: TRUE | AC208: TRUE | AD208: TRUE | AE208: FALSE | AF208: FALSE | AG208: FALSE | AH208: 0 | AI208: FALSE | AJ208: FALSE | AK208: TRUE | AL208: 1 | AM208: BUDGET | AN208: 1
A209: College | B209: Fringe | E209: PENS_FRI_5/12 | F209: Teachers Pensions Grant Post 16 April - August (Fringe) | G209: FALSE | H209: TRUE | I209: TRUE | J209: TRUE | K209: FALSE | L209: FALSE | M209: FALSE | N209: 0 | O209: FALSE | P209: FALSE | Q209: FALSE | R209: FALSE | S209: FALSE | T209: FALSE | U209: FALSE | V209: FALSE | W209: FALSE | X209: 1 | Y209: FALSE | Z209: FALSE | AA209: TRUE | AB209: TRUE | AC209: TRUE | AD209: TRUE | AE209: FALSE | AF209: FALSE | AG209: FALSE | AH209: 0 | AI209: FALSE | AJ209: FALSE | AK209: TRUE | AL209: 1 | AM209: BUDGET | AN209: 1
A210: College | B210: Fringe | E210: PENS_FRI_7/12 | F210: Teachers Pensions Grant Post 16 September - March (Fringe) | G210: FALSE | H210: TRUE | I210: TRUE | J210: TRUE | K210: FALSE | L210: FALSE | M210: FALSE | N210: 0 | O210: FALSE | P210: FALSE | Q210: FALSE | R210: FALSE | S210: FALSE | T210: FALSE | U210: FALSE | V210: FALSE | W210: FALSE | X210: 1 | Y210: FALSE | Z210: FALSE | AA210: TRUE | AB210: TRUE | AC210: TRUE | AD210: TRUE | AE210: FALSE | AF210: FALSE | AG210: FALSE | AH210: 0 | AI210: FALSE | AJ210: FALSE | AK210: TRUE | AL210: 1 | AM210: BUDGET | AN210: 1
A211: College | B211: Inner | E211: PENS_INN_5/12 | F211: Teachers Pensions Grant Post 16 April - August (Inner) | G211: FALSE | H211: TRUE | I211: TRUE | J211: TRUE | K211: FALSE | L211: FALSE | M211: FALSE | N211: 0 | O211: FALSE | P211: FALSE | Q211: FALSE | R211: FALSE | S211: FALSE | T211: FALSE | U211: FALSE | V211: FALSE | W211: FALSE | X211: 1 | Y211: FALSE | Z211: FALSE | AA211: TRUE | AB211: TRUE | AC211: TRUE | AD211: TRUE | AE211: FALSE | AF211: FALSE | AG211: FALSE | AH211: 0 | AI211: FALSE | AJ211: FALSE | AK211: TRUE | AL211: 1 | AM211: BUDGET | AN211: 1
A212: College | B212: Inner | E212: PENS_INN_7/12 | F212: Teachers Pensions Grant Post 16 September - March (Inner) | G212: FALSE | H212: TRUE | I212: TRUE | J212: TRUE | K212: FALSE | L212: FALSE | M212: FALSE | N212: 0 | O212: FALSE | P212: FALSE | Q212: FALSE | R212: FALSE | S212: FALSE | T212: FALSE | U212: FALSE | V212: FALSE | W212: FALSE | X212: 1 | Y212: FALSE | Z212: FALSE | AA212: TRUE | AB212: TRUE | AC212: TRUE | AD212: TRUE | AE212: FALSE | AF212: FALSE | AG212: FALSE | AH212: 0 | AI212: FALSE | AJ212: FALSE | AK212: TRUE | AL212: 1 | AM212: BUDGET | AN212: 1
A213: College | B213: Outer | E213: PENS_OUT_5/12 | F213: Teachers Pensions Grant Post 16 April - August (Outer) | G213: FALSE | H213: TRUE | I213: TRUE | J213: TRUE | K213: FALSE | L213: FALSE | M213: FALSE | N213: 0 | O213: FALSE | P213: FALSE | Q213: FALSE | R213: FALSE | S213: FALSE | T213: FALSE | U213: FALSE | V213: FALSE | W213: FALSE | X213: 1 | Y213: FALSE | Z213: FALSE | AA213: TRUE | AB213: TRUE | AC213: TRUE | AD213: TRUE | AE213: FALSE | AF213: FALSE | AG213: FALSE | AH213: 0 | AI213: FALSE | AJ213: FALSE | AK213: TRUE | AL213: 1 | AM213: BUDGET | AN213: 1
A214: College | B214: Outer | E214: PENS_OUT_7/12 | F214: Teachers Pensions Grant Post 16 September - March (Outer) | G214: FALSE | H214: TRUE | I214: TRUE | J214: TRUE | K214: FALSE | L214: FALSE | M214: FALSE | N214: 0 | O214: FALSE | P214: FALSE | Q214: FALSE | R214: FALSE | S214: FALSE | T214: FALSE | U214: FALSE | V214: FALSE | W214: FALSE | X214: 1 | Y214: FALSE | Z214: FALSE | AA214: TRUE | AB214: TRUE | AC214: TRUE | AD214: TRUE | AE214: FALSE | AF214: FALSE | AG214: FALSE | AH214: 0 | AI214: FALSE | AJ214: FALSE | AK214: TRUE | AL214: 1 | AM214: BUDGET | AN214: 1
A215: College | E215: PUPIL_SPRING_KS5 | F215: KS5 Spring Census from Oct numbers | G215: FALSE | H215: TRUE | I215: TRUE | J215: TRUE | K215: FALSE | L215: FALSE | M215: FALSE | N215: 0 | O215: FALSE | P215: FALSE | Q215: FALSE | R215: FALSE | S215: FALSE | T215: FALSE | U215: FALSE | V215: FALSE | W215: FALSE | X215: 1 | Y215: FALSE | Z215: FALSE | AA215: TRUE | AB215: TRUE | AC215: TRUE | AD215: TRUE | AE215: FALSE | AF215: FALSE | AG215: FALSE | AH215: 1 | AI215: FALSE | AJ215: FALSE | AK215: TRUE | AL215: 0 | AM215: PUPILNUMBERS | AN215: 0
A216: College | E216: PUPILY11_LY | F216: Y11 Pupil LY | G216: FALSE | H216: FALSE | I216: FALSE | J216: TRUE | K216: FALSE | L216: TRUE | M216: FALSE | N216: 0 | O216: FALSE | P216: FALSE | Q216: FALSE | R216: FALSE | S216: FALSE | T216: TRUE | U216: FALSE | V216: TRUE | W216: FALSE | X216: 1 | Y216: FALSE | Z216: FALSE | AA216: FALSE | AB216: FALSE | AC216: FALSE | AD216: TRUE | AE216: FALSE | AF216: TRUE | AG216: FALSE | AH216: 1 | AI216: FALSE | AJ216: FALSE | AK216: TRUE | AL216: 0 | AM216: PUPILNUMBERS | AN216: 0
A217: College | E217: PUPILY12_LY | F217: Y12 Pupil LY | G217: FALSE | H217: FALSE | I217: FALSE | J217: TRUE | K217: FALSE | L217: TRUE | M217: FALSE | N217: 0 | O217: FALSE | P217: FALSE | Q217: FALSE | R217: FALSE | S217: FALSE | T217: TRUE | U217: FALSE | V217: TRUE | W217: FALSE | X217: 1 | Y217: FALSE | Z217: FALSE | AA217: FALSE | AB217: FALSE | AC217: FALSE | AD217: TRUE | AE217: FALSE | AF217: TRUE | AG217: FALSE | AH217: 1 | AI217: FALSE | AJ217: FALSE | AK217: TRUE | AL217: 0 | AM217: PUPILNUMBERS | AN217: 0
A218: College | E218: PUPILY13_LY | F218: Y13 Pupil LY | G218: FALSE | H218: FALSE | I218: FALSE | J218: TRUE | K218: FALSE | L218: TRUE | M218: FALSE | N218: 0 | O218: FALSE | P218: FALSE | Q218: FALSE | R218: FALSE | S218: FALSE | T218: TRUE | U218: FALSE | V218: TRUE | W218: FALSE | X218: 1 | Y218: FALSE | Z218: FALSE | AA218: FALSE | AB218: FALSE | AC218: FALSE | AD218: TRUE | AE218: FALSE | AF218: TRUE | AG218: FALSE | AH218: 1 | AI218: FALSE | AJ218: FALSE | AK218: TRUE | AL218: 0 | AM218: PUPILNUMBERS | AN218: 0
A219: College | E219: UPLIFT_KS5FUNDED | F219: Uplift by KS5 Funded | G219: FALSE | H219: TRUE | I219: TRUE | J219: TRUE | K219: TRUE | L219: TRUE | M219: FALSE | N219: 0 | O219: FALSE | P219: FALSE | Q219: FALSE | R219: TRUE | S219: TRUE | T219: TRUE | U219: FALSE | V219: TRUE | W219: FALSE | X219: 0 | Y219: FALSE | Z219: FALSE | AA219: FALSE | AB219: TRUE | AC219: TRUE | AD219: TRUE | AE219: FALSE | AF219: FALSE | AG219: FALSE | AH219: 0 | AI219: FALSE | AJ219: FALSE | AK219: TRUE | AL219: 0 | AM219: DEFAULT | AN219: 0
A220: College | E220: UPLIFT_KS5INYR | F220: Uplift by KS5 In Year Pupils | G220: FALSE | H220: TRUE | I220: TRUE | J220: TRUE | K220: TRUE | L220: TRUE | M220: FALSE | N220: 0 | O220: FALSE | P220: FALSE | Q220: FALSE | R220: TRUE | S220: TRUE | T220: TRUE | U220: FALSE | V220: TRUE | W220: FALSE | X220: 0 | Y220: FALSE | Z220: FALSE | AA220: FALSE | AB220: TRUE | AC220: TRUE | AD220: TRUE | AE220: FALSE | AF220: FALSE | AG220: FALSE | AH220: 0 | AI220: FALSE | AJ220: FALSE | AK220: TRUE | AL220: 0 | AM220: DEFAULT | AN220: 0
A221: College | E221: DFE_POST16_TOTAL | F221: Total DFE - Post 16 | G221: FALSE | H221: TRUE | I221: TRUE | J221: TRUE | K221: FALSE | L221: FALSE | M221: FALSE | N221: 0 | O221: FALSE | P221: FALSE | Q221: FALSE | R221: TRUE | S221: TRUE | T221: TRUE | U221: FALSE | V221: FALSE | W221: FALSE | X221: -1 | Y221: FALSE | Z221: FALSE | AA221: FALSE | AB221: FALSE | AC221: FALSE | AD221: TRUE | AE221: FALSE | AF221: TRUE | AG221: FALSE | AH221: 1 | AI221: FALSE | AJ221: FALSE | AK221: TRUE | AL221: 1 | AM221: FUNDING | AN221: 1
A222: College | E222: PUPILPOST16_FACTOR | F222: Pupil and GAG Post 16Factor | G222: FALSE | H222: TRUE | I222: TRUE | J222: TRUE | K222: FALSE | L222: FALSE | M222: FALSE | N222: 0 | O222: FALSE | P222: FALSE | Q222: FALSE | R222: TRUE | S222: TRUE | T222: TRUE | U222: FALSE | V222: TRUE | W222: FALSE | X222: 0 | Y222: FALSE | Z222: FALSE | AA222: TRUE | AB222: TRUE | AC222: TRUE | AD222: TRUE | AE222: FALSE | AF222: FALSE | AG222: FALSE | AH222: 100 | AI222: FALSE | AJ222: FALSE | AK222: TRUE | AL222: 1 | AM222: STATISTICS | AN222: 1
A223: College | E223: UPLIFT_POST16 | F223: Post 16 GAG Uplift % | G223: FALSE | H223: FALSE | I223: FALSE | J223: FALSE | K223: TRUE | L223: TRUE | M223: FALSE | N223: 0 | O223: FALSE | P223: FALSE | Q223: FALSE | R223: FALSE | S223: FALSE | T223: FALSE | U223: FALSE | V223: FALSE | W223: FALSE | X223: 100 | Y223: FALSE | Z223: FALSE | AA223: TRUE | AB223: TRUE | AC223: TRUE | AD223: TRUE | AE223: FALSE | AF223: FALSE | AG223: FALSE | AH223: 100 | AI223: FALSE | AJ223: FALSE | AK223: TRUE | AL223: 0 | AM223: DEFAULT | AN223: 0
A224: College | E224: UPLIFT_POST16_PUPIL | F224: Post 16 GAG Uplift % and Pupils | G224: FALSE | H224: FALSE | I224: FALSE | J224: FALSE | K224: TRUE | L224: TRUE | M224: FALSE | N224: 0 | O224: FALSE | P224: FALSE | Q224: FALSE | R224: FALSE | S224: FALSE | T224: FALSE | U224: FALSE | V224: FALSE | W224: FALSE | X224: 100 | Y224: FALSE | Z224: FALSE | AA224: FALSE | AB224: TRUE | AC224: TRUE | AD224: TRUE | AE224: FALSE | AF224: FALSE | AG224: FALSE | AH224: 0 | AI224: FALSE | AJ224: FALSE | AK224: TRUE | AL224: 0 | AM224: DEFAULT | AN224: 0
A225: Infant | C225: LA1 | D225: PRI | E225: AWPU01 | F225: Total AWPU PRI | G225: FALSE | H225: TRUE | I225: TRUE | J225: TRUE | K225: FALSE | L225: FALSE | M225: FALSE | N225: 0 | O225: FALSE | P225: FALSE | Q225: FALSE | R225: FALSE | S225: FALSE | T225: TRUE | U225: FALSE | V225: TRUE | W225: FALSE | X225: 1 | Y225: FALSE | Z225: FALSE | AA225: TRUE | AB225: TRUE | AC225: TRUE | AD225: TRUE | AE225: FALSE | AF225: FALSE | AG225: FALSE | AH225: 0 | AI225: FALSE | AJ225: FALSE | AK225: TRUE | AL225: 1 | AM225: FUNDING | AN225: 1
A226: Infant | C226: LA2 | D226: PRI | E226: AWPU01 | F226: Total AWPU PRI | G226: FALSE | H226: TRUE | I226: TRUE | J226: TRUE | K226: FALSE | L226: FALSE | M226: FALSE | N226: 0 | O226: FALSE | P226: FALSE | Q226: FALSE | R226: FALSE | S226: FALSE | T226: TRUE | U226: FALSE | V226: TRUE | W226: FALSE | X226: 1 | Y226: FALSE | Z226: FALSE | AA226: TRUE | AB226: TRUE | AC226: TRUE | AD226: TRUE | AE226: FALSE | AF226: FALSE | AG226: FALSE | AH226: 0 | AI226: FALSE | AJ226: FALSE | AK226: TRUE | AL226: 1 | AM226: FUNDING | AN226: 1
A227: Infant | C227: LA3 | D227: PRI | E227: AWPU01 | F227: Total AWPU PRI | G227: FALSE | H227: TRUE | I227: TRUE | J227: TRUE | K227: FALSE | L227: FALSE | M227: FALSE | N227: 0 | O227: FALSE | P227: FALSE | Q227: FALSE | R227: FALSE | S227: FALSE | T227: TRUE | U227: FALSE | V227: TRUE | W227: FALSE | X227: 1 | Y227: FALSE | Z227: FALSE | AA227: TRUE | AB227: TRUE | AC227: TRUE | AD227: TRUE | AE227: FALSE | AF227: FALSE | AG227: FALSE | AH227: 0 | AI227: FALSE | AJ227: FALSE | AK227: TRUE | AL227: 1 | AM227: FUNDING | AN227: 1
A228: Infant | C228: LA4 | D228: PRI | E228: AWPU01 | F228: Total AWPU PRI | G228: FALSE | H228: TRUE | I228: TRUE | J228: TRUE | K228: FALSE | L228: FALSE | M228: FALSE | N228: 0 | O228: FALSE | P228: FALSE | Q228: FALSE | R228: FALSE | S228: FALSE | T228: TRUE | U228: FALSE | V228: TRUE | W228: FALSE | X228: 1 | Y228: FALSE | Z228: FALSE | AA228: TRUE | AB228: TRUE | AC228: TRUE | AD228: TRUE | AE228: FALSE | AF228: FALSE | AG228: FALSE | AH228: 0 | AI228: FALSE | AJ228: FALSE | AK228: TRUE | AL228: 1 | AM228: FUNDING | AN228: 1
A229: Infant | C229: LA5 | D229: PRI | E229: AWPU01 | F229: Total AWPU PRI | G229: FALSE | H229: TRUE | I229: TRUE | J229: TRUE | K229: FALSE | L229: FALSE | M229: FALSE | N229: 0 | O229: FALSE | P229: FALSE | Q229: FALSE | R229: FALSE | S229: FALSE | T229: TRUE | U229: FALSE | V229: TRUE | W229: FALSE | X229: 1 | Y229: FALSE | Z229: FALSE | AA229: TRUE | AB229: TRUE | AC229: TRUE | AD229: TRUE | AE229: FALSE | AF229: FALSE | AG229: FALSE | AH229: 0 | AI229: FALSE | AJ229: FALSE | AK229: TRUE | AL229: 1 | AM229: FUNDING | AN229: 1
A230: Infant | C230: LA6 | D230: PRI | E230: AWPU01 | F230: Total AWPU PRI | G230: FALSE | H230: TRUE | I230: TRUE | J230: TRUE | K230: FALSE | L230: FALSE | M230: FALSE | N230: 0 | O230: FALSE | P230: FALSE | Q230: FALSE | R230: FALSE | S230: FALSE | T230: TRUE | U230: FALSE | V230: TRUE | W230: FALSE | X230: 1 | Y230: FALSE | Z230: FALSE | AA230: TRUE | AB230: TRUE | AC230: TRUE | AD230: TRUE | AE230: FALSE | AF230: FALSE | AG230: FALSE | AH230: 0 | AI230: FALSE | AJ230: FALSE | AK230: TRUE | AL230: 1 | AM230: FUNDING | AN230: 1
...

Sheet CalcFinCodes
A1: LA | B1: London Weighting | C1: School Type | D1: Key Stage | E1: CalculatorCode2 | F1: FinanceCode | G1: Type
C2: All | E2: CENTRALCHG_MAT | G2: SourceFinanceCodes
C3: All | E3: CENTRALCHG_SCH | F3: FUNDING_GAG | G3: SourceFinanceCodes
C4: All | E4: CENTRALCHG_SCH | F4: CENCHG | G4: MultiplierFinanceCodes
C5: All | E5: CENTRALCHG_SCH | F5: FUNDING_16_19 | G5: SourceFinanceCodes
C6: All | E6: CENTRALCHG_SCH | F6: FUNDING_HNPOST16 | G6: SourceFinanceCodes
C7: All | E7: CENTRALCHG_SCH | F7: FUNDING_HNPRE16 | G7: SourceFinanceCodes
C8: All | E8: CENTRALCHG_SCH | F8: FUNDING_SFS | G8: SourceFinanceCodes
C9: All | E9: DFC_CORE | F9: DFC_CORE | G9: SourceFinanceCodes
C10: All | E10: DFC_EXP | F10: 550250 | G10: SourceFinanceCodes
C11: All | E11: DFE_TOTAL | F11: FUNDING_GAG | G11: SourceFinanceCodes
C12: All | E12: DFE_TOTAL | F12: FUNDING_HNPRE16 | G12: SourceFinanceCodes
C13: All | E13: FUNDING_GAG | F13: FUNDING_GAG | G13: SourceFinanceCodes
C14: All | E14: LEVY_ALL_TEA | F14: =_xlfn.TEXTJOIN(",",TRUE,SRG[AnnualFteFinanceCode]) -> A_FTE_LST,A_FTE_LSN,A_FTE_TEA,A_FTE_TA,A_FTE_LIB,A_FTE_TEC,A_FTE_COV,A_FTE_ADM,A_FTE_PRE,A_FTE_CLE,A_FTE_CAT,A_FTE_MDS,A_FTE_NUR,A_FTE_FSW,A_FTE_INV,A_FTE_EXT,A_FTE_OTH | G14: DivisorFinanceCodes
C15: All | E15: LEVY_ALL_TEA | G15: MultiplierFinanceCodes
C16: All | E16: LEVY_ALL_TEA | F16: LEVY_ALL | G16: SourceFinanceCodes
C17: All | E17: LEVY_TEA | F17: LEVY_TEA | G17: MultiplierFinanceCodes
C18: All | E18: PUP_PREM_PLAC_5/12 | F18: FUNDING_PUPPREM_PLAC | G18: SourceFinanceCodes
C19: All | E19: PUP_PREM_PLAC_7/12 | F19: FUNDING_PUPPREM_PLAC | G19: SourceFinanceCodes
C20: All | E20: PUP_PREM_SER_5/12 | F20: FUNDING_PUPPREM_SER | G20: SourceFinanceCodes
C21: All | E21: PUP_PREM_SER_7/12 | F21: FUNDING_PUPPREM_SER | G21: SourceFinanceCodes
C22: All | E22: PUPILASCL_FACTOR | F22: Z10 | G22: SourceGroupingCodes
C23: All | E23: PUPILASCL_FACTOR | F23: Z10 | G23: DivisorGroupingCodes
C24: All | E24: PUPILASCL_FACTOR | F24: UPLIFT_ASCL | G24: MultiplierFinanceCodes
C25: All | E25: PUPILEXP_FACTOR | F25: Z10 | G25: SourceGroupingCodes
C26: All | E26: PUPILEXP_FACTOR | F26: Z10 | G26: DivisorGroupingCodes
C27: All | E27: PUPILEXP_FACTOR | F27: UPLIFT_EXP | G27: MultiplierFinanceCodes
... C78: All | E78: PUPSERINCOME | F78: PUPSER_RATE | G78: MultiplierFinanceCodes
C79: All | E79: REV/CAP_REVERSAL | G79: SourceFinanceCodes
C80: All | E80: RPA_CALC | F80: RPA_RATE | G80: MultiplierFinanceCodes
C81: All | E81: RPI_PUPIL_UPLIFT | F81: UPLIFT_PUPILRPI% | G81: MultiplierFinanceCodes
C82: All | E82: TOTAL_DFC_5/12 | F82: DFC | G82: SourceFinanceCodes
C83: All | E83: TOTAL_DFC_7/12 | F83: DFC | G83: SourceFinanceCodes
C84: All | E84: UIFSM_FACTOR | F84: PUPIL_CEN_00 | G84: DivisorFinanceCodes
C85: All | E85: UIFSM_FACTOR | F85: PUPIL_CEN_00 | G85: MultiplierFinanceCodes
C86: All | E86: UIFSM_FACTOR | F86: PUPIL_CEN_01 | G86: DivisorFinanceCodes
C87: All | E87: UIFSM_FACTOR | F87: PUPIL_CEN_01 | G87: MultiplierFinanceCodes
C88: All | E88: UIFSM_FACTOR | F88: PUPIL_CEN_02 | G88: DivisorFinanceCodes
C89: All | E89: UIFSM_FACTOR | F89: PUPIL_CEN_02 | G89: MultiplierFinanceCodes
C90: All | E90: UPLIFT_ASCL | F90: UPLIFT_ASCL | G90: MultiplierFinanceCodes
C91: All | E91: UPLIFT_ASCL_PUPIL | F91: UPLIFT_PUPILASCL% | G91: MultiplierFinanceCodes
... C106: All | E106: UPLIFT_PUPILFUNDED | F106: FUNDED_KS3 | G106: MultiplierFinanceCodes
C107: =_xlfn.XLOOKUP(CALCFC[[#This Row],[CalculatorCode2]],CALCS[CalculatorCode],CALCS[School Type]) -> All | E107: UPLIFT_PUPILFUNDED | F107: FUNDED_KS3_ADJ | G107: DivisorFinanceCodes
C108: =_xlfn.XLOOKUP(CALCFC[[#This Row],[CalculatorCode2]],CALCS[CalculatorCode],CALCS[School Type]) -> All | E108: UPLIFT_PUPILFUNDED | F108: FUNDED_KS3_ADJ | G108: MultiplierFinanceCodes
C109: All | E109: UPLIFT_PUPILFUNDED | F109: FUNDED_KS4 | G109: DivisorFinanceCodes
C110: All | E110: UPLIFT_PUPILFUNDED | F110: FUNDED_KS4 | G110: MultiplierFinanceCodes
C111: =_xlfn.XLOOKUP(CALCFC[[#This Row],[CalculatorCode2]],CALCS[CalculatorCode],CALCS[School Type]) -> All | E111: UPLIFT_PUPILFUNDED | F111: FUNDED_KS4_ADJ | G111: DivisorFinanceCodes
C112: =_xlfn.XLOOKUP(CALCFC[[#This Row],[CalculatorCode2]],CALCS[CalculatorCode],CALCS[School Type]) -> All | E112: UPLIFT_PUPILFUNDED | F112: FUNDED_KS4_ADJ | G112: MultiplierFinanceCodes
C113: =_xlfn.XLOOKUP(CALCFC[[#This Row],[CalculatorCode2]],CALCS[CalculatorCode],CALCS[School Type]) -> All | E113: UPLIFT_PUPILFUNDED | F113: FUNDED_PRI_ADJ | G113: DivisorFinanceCodes
C114: =_xlfn.XLOOKUP(CALCFC[[#This Row],[CalculatorCode2]],CALCS[CalculatorCode],CALCS[School Type]) -> All | E114: UPLIFT_PUPILFUNDED | F114: FUNDED_PRI_ADJ | G114: MultiplierFinanceCodes
C115: All | E115: UPLIFT_PUPILINYR | F115: PUPIL_CEN_00 | G115: MultiplierFinanceCodes
C116: All | E116: UPLIFT_PUPILINYR | F116: PUPIL_CEN_00 | G116: DivisorFinanceCodes
C117: All | E117: UPLIFT_PUPILINYR | F117: PUPIL_CEN_01 | G117: MultiplierFinanceCodes
C118: All | E118: UPLIFT_PUPILINYR | F118: PUPIL_CEN_01 | G118: DivisorFinanceCodes
C119: All | E119: UPLIFT_PUPILINYR | F119: PUPIL_CEN_02 | G119: MultiplierFinanceCodes
C120: All | E120: UPLIFT_PUPILINYR | F120: PUPIL_CEN_02 | G120: DivisorFinanceCodes
C121: All | E121: UPLIFT_PUPILINYR | F121: PUPIL_CEN_03 | G121: MultiplierFinanceCodes
C122: All | E122: UPLIFT_PUPILINYR | F122: PUPIL_CEN_03 | G122: DivisorFinanceCodes
C123: All | E123: UPLIFT_PUPILINYR | F123: PUPIL_CEN_04 | G123: MultiplierFinanceCodes
C124: All | E124: UPLIFT_PUPILINYR | F124: PUPIL_CEN_04 | G124: DivisorFinanceCodes
C125: All | E125: UPLIFT_PUPILINYR | F125: PUPIL_CEN_05 | G125: MultiplierFinanceCodes
C126: All | E126: UPLIFT_PUPILINYR | F126: PUPIL_CEN_05 | G126: DivisorFinanceCodes
... C145: All | E145: UPLIFT_RPI | F145: UPLIFT_RPI | G145: MultiplierFinanceCodes
C146: =_xlfn.XLOOKUP(CALCFC[[#This Row],[CalculatorCode2]],CALCS[CalculatorCode],CALCS[School Type]) -> All | E146: UPLIFT_SUPSTF | F146: UPLIFT_SUPSTF | G146: MultiplierFinanceCodes
C147: =_xlfn.XLOOKUP(CALCFC[[#This Row],[CalculatorCode2]],CALCS[CalculatorCode],CALCS[School Type]) -> All | E147: UPLIFT_TEACH | F147: UPLIFT_TEACH | G147: MultiplierFinanceCodes
C148: =_xlfn.XLOOKUP(CALCFC[[#This Row],[CalculatorCode2]],CALCS[CalculatorCode],CALCS[School Type]) -> All | E148: LEVY_TEA | F148: 610100 | G148: SourceGroupingCodes
C149: =_xlfn.XLOOKUP(CALCFC[[#This Row],[CalculatorCode2]],CALCS[CalculatorCode],CALCS[School Type]) -> All | E149: LEVY_TEA | F149: 612100 | G149: SourceGroupingCodes
C150: =_xlfn.XLOOKUP(CALCFC[[#This Row],[CalculatorCode2]],CALCS[CalculatorCode],CALCS[School Type]) -> All | E150: LEVY_TEA | F150: 615100 | G150: SourceGroupingCodes
C151: =_xlfn.XLOOKUP(CALCFC[[#This Row],[CalculatorCode2]],CALCS[CalculatorCode],CALCS[School Type]) -> All | E151: LEVY_SUP | F151: LEVY_SUP | G151: MultiplierFinanceCodes
C152: =_xlfn.XLOOKUP(CALCFC[[#This Row],[CalculatorCode2]],CALCS[CalculatorCode],CALCS[School Type]) -> All | E152: LEVY_SUP | F152: 611100 | G152: SourceGroupingCodes
C153: =_xlfn.XLOOKUP(CALCFC[[#This Row],[CalculatorCode2]],CALCS[CalculatorCode],CALCS[School Type]) -> All | E153: LEVY_SUP | F153: 620100 | G153: SourceGroupingCodes
C154: =_xlfn.XLOOKUP(CALCFC[[#This Row],[CalculatorCode2]],CALCS[CalculatorCode],CALCS[School Type]) -> All | E154: LEVY_SUP | F154: 622100 | G154: SourceGroupingCodes
C155: =_xlfn.XLOOKUP(CALCFC[[#This Row],[CalculatorCode2]],CALCS[CalculatorCode],CALCS[School Type]) -> All | E155: LEVY_SUP | F155: 623100 | G155: SourceGroupingCodes
C156: =_xlfn.XLOOKUP(CALCFC[[#This Row],[CalculatorCode2]],CALCS[CalculatorCode],CALCS[School Type]) -> All | E156: LEVY_SUP | F156: 624100 | G156: SourceGroupingCodes
C157: =_xlfn.XLOOKUP(CALCFC[[#This Row],[CalculatorCode2]],CALCS[CalculatorCode],CALCS[School Type]) -> All | E157: LEVY_SUP | F157: 625100 | G157: SourceGroupingCodes
C158: =_xlfn.XLOOKUP(CALCFC[[#This Row],[CalculatorCode2]],CALCS[CalculatorCode],CALCS[School Type]) -> All | E158: LEVY_SUP | F158: 627100 | G158: SourceGroupingCodes
C159: =_xlfn.XLOOKUP(CALCFC[[#This Row],[CalculatorCode2]],CALCS[CalculatorCode],CALCS[School Type]) -> All | E159: LEVY_SUP | F159: 630100 | G159: SourceGroupingCodes
C160: =_xlfn.XLOOKUP(CALCFC[[#This Row],[CalculatorCode2]],CALCS[CalculatorCode],CALCS[School Type]) -> All | E160: LEVY_SUP | F160: 632100 | G160: SourceGroupingCodes
C161: =_xlfn.XLOOKUP(CALCFC[[#This Row],[CalculatorCode2]],CALCS[CalculatorCode],CALCS[School Type]) -> All | E161: LEVY_SUP | F161: 635100 | G161: SourceGroupingCodes
C162: =_xlfn.XLOOKUP(CALCFC[[#This Row],[CalculatorCode2]],CALCS[CalculatorCode],CALCS[School Type]) -> All | E162: LEVY_SUP | F162: 637100 | G162: SourceGroupingCodes
C163: =_xlfn.XLOOKUP(CALCFC[[#This Row],[CalculatorCode2]],CALCS[CalculatorCode],CALCS[School Type]) -> All | E163: LEVY_SUP | F163: 640100 | G163: SourceGroupingCodes
C164: =_xlfn.XLOOKUP(CALCFC[[#This Row],[CalculatorCode2]],CALCS[CalculatorCode],CALCS[School Type]) -> All | E164: LEVY_SUP | F164: 645100 | G164: SourceGroupingCodes
C165: =_xlfn.XLOOKUP(CALCFC[[#This Row],[CalculatorCode2]],CALCS[CalculatorCode],CALCS[School Type]) -> All | E165: LEVY_SUP | F165: 647100 | G165: SourceGroupingCodes
C166: =_xlfn.XLOOKUP(CALCFC[[#This Row],[CalculatorCode2]],CALCS[CalculatorCode],CALCS[School Type]) -> All | E166: LEVY_ALL_SUP | F166: =_xlfn.TEXTJOIN(",",TRUE,SRG[AnnualFteFinanceCode]) -> A_FTE_LST,A_FTE_LSN,A_FTE_TEA,A_FTE_TA,A_FTE_LIB,A_FTE_TEC,A_FTE_COV,A_FTE_ADM,A_FTE_PRE,A_FTE_CLE,A_FTE_CAT,A_FTE_MDS,A_FTE_NUR,A_FTE_FSW,A_FTE_INV,A_FTE_EXT,A_FTE_OTH | G166: DivisorFinanceCodes
C167: =_xlfn.XLOOKUP(CALCFC[[#This Row],[CalculatorCode2]],CALCS[CalculatorCode],CALCS[School Type]) -> All | E167: LEVY_ALL_SUP | G167: MultiplierFinanceCodes
C168: =_xlfn.XLOOKUP(CALCFC[[#This Row],[CalculatorCode2]],CALCS[CalculatorCode],CALCS[School Type]) -> All | E168: LEVY_ALL_SUP | F168: LEVY_ALL | G168: SourceFinanceCodes
