Workbook
Name BuildYear: Parameters!$B$5

Sheet Parameters
A1: VERSION | B1: 1.1
A3: Parameter | B3: Value | D3: Link updated? | E3: Yes
A4: Token | B4: eyJhbGciOiJIUzI1NiIsInR5cCI6IkpXVCJ9.eyJodHRwOi8vc2NoZW1hcy54bWxzb2FwLm9yZy93cy8yMDA1LzA1L2lkZW50aXR5L2NsYWltcy9uYW1laWRlbnRpZmllciI6IjQ1ZDA5ZmY3LWE2NjEtNDUyMy1iMmEyLTIxYWU3OGZhMjZhMSIsImh0dHA6Ly9zY2hlbWFzLnhtbHNvYXAub3JnL3dzLzIwMDUvMDUvaWRlbnRpdHkvY2xhaW1zL25hbWUiOiJDT1IwMDRAaW1wc29mdHdhcmUuY28udWsiLCJhdF9oYXNoIjoiYzg3NzNlODQtOGVjMC00ZDI4LWEzYzUtNzY1M2Y5OGY1OGNjIn0.wg1yILUA9FhHArhosCaiVtXyClwannHe7t7loxLrOCM
A5: Year From | B5: 2025/26
A6: Api Url Root | B6: https://api.impplanner.co.uk
A7: Date Last Amended | B7: 46007 | D7: update to today date (shortcut is CTRL + ;)
A9: Element | B9: Type
A10: CALCULATIONS | B10: SIMPLE

Sheet Notes
A1: Process Notes
A3: Updating API
A5: Step
A6: 1 | B6: Add API code to parameter tab
A28: 2 | B28: Navigate to the queries and connections in Data tab
A51: 3 | B51: This will bring up a side menu
A104: 4 | B104: Right click on the API folder and click "Refresh"
A147: 5 | B147: If the below pop-up appears please tick the "Ignore Privacy Levels" box and then click the "Save" button.
A164: 6 | B164: If the below pop-up appears please click the "Don't Update" button.
A174: Schools
A176: Step
A177: 1 | B177: London Weighting Type needs to be updated with the correct type from the drop down. This is based on the Local authority, whose weighting can be found in column "Teachers IL/OL/FRI" of the "Local Authorities - standard codes" document.
A193: #VALUE!

Sheet Build Checklist
A1: Checklist
A2: Task | B2: Notes | C2: Error Check
A3: Check for PayScale Issues | C3: =SUM(PAYSCALES[Will Import if 0]) -> 0
A4: Check for PayScale Point Issues | C4: =SUM(PSPOINTS[Will Import if 0]) -> 0
A5: Check for PayScale Increase % Issues | C5: =SUM(PS_INCPERC[Will Import if 0]) -> 0
A6: Check for PayScale Grades Issues | C6: =SUM(GRADES[Will Import if 0]) -> 0
A7: Check Allowance Type Issues | C7: =SUM(ALLWCTYPE[Will Import if 0]) -> 0
A8: Check Allowance Point Issues | C8: =SUM(ALLWCPTS[Will import if 0]) -> 0
A9: Check Allowance Increase % Issues | C9: =SUM(AL_INCPERC[Will Import if 0]) -> 0
A10: Check for Pensions Issues | C10: =SUM(PENS[Will import if 0]) -> 0
A11: Check for EQWP Issues | C11: =SUM(EQW[Will import if 0]) -> 0
A12: Check for Staff Members Issues | C12: =SUM(MEMBERS[Will Import if 0]) -> 0
A13: Check for Staff Role Groups Issues | C13: =SUM(SRG[Will Import if 0]) -> 0
A14: Check for Staff Roles Issues | C14: =SUM(ROLES[Will Import if 0]) -> 0
A15: Check for Contract Issues (Teacher) | C15: =SUM(CONT_TEA[Will Import if 0]) -> 336
A16: Check for Contract Issues (Support) | C16: =SUM(CONT_SUP[Will Import if 0]) -> 161
A17: Check Adjustment Type Issues | C17: =SUM(ADJTYPE[Will import if 0]) -> 0
A18: Check Contract Adjustment Issues | C18: =SUM(CONTADJ[Will import if 0]) -> 4
A19: Check Contract Allowance Issues | C19: =SUM(CONTAL[Will import if 0]) -> 0
A20: Check Leave Types Issues | C20: =SUM(LEAVES[Will Import if 0]) -> 0
A21: Check Staff Member Leaves Issues | C21: =SUM(SM_LEAVES[Will Import if 0]) -> 0
A22: Check Finance Codes S2 Issues (Ledger needed?) | C22: =SUM(FC_import[Will Import if 0]) -> 0
A23: Total Tab Check | C23: =SUM(C3:C22) -> 501
A24: Have the Scope Document info / Email Responses been reviewed? | C24: Yes
A25: Do funds need to be assigned at Scenario Row Level? (See Scope Document info) | C25: No
A26: If not standard, did we receive and check Statutory leave types? | C26: Yes
A27: Do contract effective dates match the dates provided in the Scope Document? | C27: Yes
A28: Have we built all the PayScales provided? | C28: Yes
A29: Did we build contracts for all locations? | C29: Yes
A30: Have all pension rates been supplied? | C30: Yes
A31: Do PayScales increment and increase in line with Scope Document info? | B31: Support increment on Anniversary Date | C31: Yes
A32: Are full time hours - for roles/locations - in line with Scope Document info? | C32: Yes
A33: Are notes added to Import Checklist (and against task row, this tab) to explain all 'non-errors' with an Error Check score (Col C)? | C33: NA
A34: Are there any SRG Critical Errors which will prevent successful Import? - if YES - alert LC to issue | C34: No
A35: Excluded contracts/ allowances - Do any excluded lines have budgetary impact (ie. data lines show salary / allowance cost)? | C35: No
A36: Non-Contract staffing data - Has any data been sent to Strand 3 Builder? (Check with Kim if unsure) | C36: No
A37: Review purposes - is (as at) Annual Full-Time Salary provided in the original staffing data? | B37: Except for MLB | C37: Yes
A38: Review purposes - is (as at) Actual Calculated Salary provided in the original staffing data? | B38: Except for MLB | C38: Yes
A39: Review purposes - if either (or both) Salaries in data NO, is the customer / LC already aware? | C39: Yes
A40: Review purposes - If Salaries in data YES, is this part of your Staff Contract Build Reconciliation? If not, please alert LC to any issue | C40: Yes
A42: Reviewed by Builder | B42: Alex C - 13/01/2026
A43: Reviewed by Lead Consultant | B43: Y/N

Sheet Import Checklist
A1: Checklist
A2: Task | B2: Number of Rows to Import | C2: Number of Rows Imported | D2: Import Checked | E2: LC Import Notes | F2: Builder Import Notes | G2: Importer Notes/Issues
A3: If this is not zero - return to builder | B3: =SUM('Build Checklist'!C23) -> 501
A4: Finance codes S2 | B4: =COUNTA(FC_import[FinanceCode]) -> 95 | C4: =631-536 -> 95 | D4: =IF(B4=C4,TRUE,FALSE) -> TRUE
A5: Allowance Type | B5: =COUNTA(ALLWCTYPE[AllowanceTypeCode]) -> 2 | C5: 2 | D5: =IF(B5=C5,TRUE,FALSE) -> TRUE
A6: Allowance Point | B6: =COUNTA(ALLWCPTS[AllowanceTypeCode]) -> 13 | C6: 13 | D6: =IF(B6=C6,TRUE,FALSE) -> TRUE
A7: Allowance Increase % | B7: =COUNTA(AL_INCPERC[AllowanceTypeCode]) -> 2 | C7: 2 | D7: =IF(B7=C7,TRUE,FALSE) -> TRUE
A8: Payscales | B8: =COUNTA(PAYSCALES[PayScaleEnabled]) -> 6 | C8: 6 | D8: =IF(B8=C8,TRUE,FALSE) -> TRUE
A9: Payscale Points | B9: =COUNTIF(PSPOINTS[PayScalePointEnabled],TRUE) -> 111 | C9: 111 | D9: =IF(B9=C9,TRUE,FALSE) -> TRUE
A10: Payscale Increase Percentages | B10: =COUNTA(PS_INCPERC[IncreasePercentage]) -> 5 | C10: 5 | D10: =IF(B10=C10,TRUE,FALSE) -> TRUE
A11: Payscale Grades | B11: =COUNTA(GRADES[PayScaleGradeEnabled]) -> 36 | C11: 36 | D11: =IF(B11=C11,TRUE,FALSE) -> TRUE
A12: Equated Week Patterns | B12: =COUNTA(EQW[EquatedWeekPatternEnabled]) -> 16 | C12: 16 | D12: =IF(B12=C12,TRUE,FALSE) -> TRUE
A13: Pensions | B13: =COUNTA(PENS[PensionEnabled]) -> 3 | C13: 3 | D13: =IF(B13=C13,TRUE,FALSE) -> TRUE
A14: Staff Members | B14: =COUNTA(MEMBERS[StaffMemberEnabled]) -> 829 | C14: 829 | D14: =IF(B14=C14,TRUE,FALSE) -> TRUE
A15: Staff Role Groups | B15: =COUNTA(SRG[StaffRoleGroupEnabled]) -> 15 | C15: 15 | D15: =IF(B15=C15,TRUE,FALSE) -> TRUE
A16: Staff Roles | B16: =COUNTA(ROLES[StaffRoleEnabled]) -> 101 | C16: 101 | D16: =IF(B16=C16,TRUE,FALSE) -> TRUE
A17: Contract (Teacher) | B17: =COUNTA(CONT_TEA[StaffMemberCode]) -> 337 | C17: 337 | D17: =IF(B17=C17,TRUE,FALSE) -> TRUE | E17: If Values are built as FTE - Check that you have selected FTE!
A18: Contract (Support) | B18: =COUNTA(CONT_SUP[StaffMemberCode]) -> 401 | C18: 401 | D18: =IF(B18=C18,TRUE,FALSE) -> TRUE
A19: Leave Types | B19: =COUNTA(LEAVES[LeaveTypeEnabled]) -> 33 | C19: 33 | D19: =IF(B19=C19,TRUE,FALSE) -> TRUE
A20: Adjustments | B20: =COUNTA(ADJTYPE[AdjustmentTypeCode]) -> 8 | C20: 8 | D20: =IF(B20=C20,TRUE,FALSE) -> TRUE
A21: Staff Member Leaves | B21: =COUNTA(SM_LEAVES[StaffMemberCode]) -> 10 | C21: 10 | D21: =IF(B21=C21,TRUE,FALSE) -> TRUE | E21: Imports - Maternity Start must not pre-date contract start. Import as-is for base weekly pay to calc, then manually backdate the Mat From date in Planner if needed.
A22: Contract Adjustments | B22: =COUNTA(CONTADJ[SchoolCode]) -> 82 | C22: 82 | D22: =IF(B22=C22,TRUE,FALSE) -> TRUE
A23: Contract Allowances | B23: =COUNTA(CONTAL[StaffMemberCode]) -> 100 | C23: 100 | D23: =IF(B23=C23,TRUE,FALSE) -> TRUE

Sheet System Grouping Codes
A1: groupingCodeCode | B1: title | C1: groupingCodeTypeCode
A2: 510100 | B2: IN: DfE Revenue Grants: GAG (not stud supp and trust grants) | C2: A
A3: 510110 | B3: IN: DfE Revenue Grants: GAG (student support) | C3: A
A4: 510120 | B4: IN: DfE Revenue Grants: GAG (start up grants) | C4: A
A5: 510130 | B5: IN: DfE Revenue Grants: Trust level grants | C5: A
A6: 510140 | B6: IN: DfE Revenue Grants: Pupil number adjustment | C6: A
A7: 510150 | B7: IN: DfE Revenue Grants: Rates reclaim | C7: A
A8: 510200 | B8: IN: DfE Revenue Grants: Pupil Premium | C8: A
A9: 510250 | B9: IN: DfE Revenue Grants: Universal Inf Free School Meals | C9: A
A10: 510300 | B10: IN: DfE Revenue Grants: Insurance top up | C10: A
A11: 510350 | B11: IN: DfE Revenue Grants: Sponsor capacity grant | C11: A
A12: 510400 | B12: IN: DfE Revenue Grants: PE & Sports grant | C12: A
... A509: ZZZ | B509: Not Applicable | C509: ZZZ

Sheet Funds
G1: API - Do not edit
A2: Code is Blank | B2: Title is Blank | C2: Enabled is blank | D2: Code length Check | E2: Title length check | F2: Will import if zero | G2: FundCode | H2: Title | I2: FundEnabled
A3: =ISBLANK(FUNDS[[#This Row],[FundCode]]) -> FALSE | B3: =ISBLANK(FUNDS[[#This Row],[Title]]) -> FALSE | C3: =ISBLANK(FUNDS[[#This Row],[FundEnabled]]) -> FALSE | D3: =IF(LEN(FUNDS[[#This Row],[FundCode]])<100,FALSE,TRUE) -> FALSE | E3: =IF(LEN(FUNDS[[#This Row],[Title]])<100,FALSE,TRUE) -> FALSE | F3: =COUNTIF(FUNDS[[#This Row],[Code is Blank]:[Title length check]],"TRUE") -> 0 | G3: ACT | H3: Alsager Community Trust | I3: TRUE
A4: =ISBLANK(FUNDS[[#This Row],[FundCode]]) -> FALSE | B4: =ISBLANK(FUNDS[[#This Row],[Title]]) -> FALSE | C4: =ISBLANK(FUNDS[[#This Row],[FundEnabled]]) -> FALSE | D4: =IF(LEN(FUNDS[[#This Row],[FundCode]])<100,FALSE,TRUE) -> FALSE | E4: =IF(LEN(FUNDS[[#This Row],[Title]])<100,FALSE,TRUE) -> FALSE | F4: =COUNTIF(FUNDS[[#This Row],[Code is Blank]:[Title length check]],"TRUE") -> 0 | G4: COV19 | H4: Covid Catch Up Fund | I4: TRUE
A5: =ISBLANK(FUNDS[[#This Row],[FundCode]]) -> FALSE | B5: =ISBLANK(FUNDS[[#This Row],[Title]]) -> FALSE | C5: =ISBLANK(FUNDS[[#This Row],[FundEnabled]]) -> FALSE | D5: =IF(LEN(FUNDS[[#This Row],[FundCode]])<100,FALSE,TRUE) -> FALSE | E5: =IF(LEN(FUNDS[[#This Row],[Title]])<100,FALSE,TRUE) -> FALSE | F5: =COUNTIF(FUNDS[[#This Row],[Code is Blank]:[Title length check]],"TRUE") -> 0 | G5: DEFAULT | H5: Default (no) Fund | I5: TRUE
A6: =ISBLANK(FUNDS[[#This Row],[FundCode]]) -> FALSE | B6: =ISBLANK(FUNDS[[#This Row],[Title]]) -> FALSE | C6: =ISBLANK(FUNDS[[#This Row],[FundEnabled]]) -> FALSE | D6: =IF(LEN(FUNDS[[#This Row],[FundCode]])<100,FALSE,TRUE) -> FALSE | E6: =IF(LEN(FUNDS[[#This Row],[Title]])<100,FALSE,TRUE) -> FALSE | F6: =COUNTIF(FUNDS[[#This Row],[Code is Blank]:[Title length check]],"TRUE") -> 0 | G6: DESF | H6: Designated Funds | I6: TRUE
A7: =ISBLANK(FUNDS[[#This Row],[FundCode]]) -> FALSE | B7: =ISBLANK(FUNDS[[#This Row],[Title]]) -> FALSE | C7: =ISBLANK(FUNDS[[#This Row],[FundEnabled]]) -> FALSE | D7: =IF(LEN(FUNDS[[#This Row],[FundCode]])<100,FALSE,TRUE) -> FALSE | E7: =IF(LEN(FUNDS[[#This Row],[Title]])<100,FALSE,TRUE) -> FALSE | F7: =COUNTIF(FUNDS[[#This Row],[Code is Blank]:[Title length check]],"TRUE") -> 0 | G7: GAG | H7: General Annual Grant | I7: TRUE
A8: =ISBLANK(FUNDS[[#This Row],[FundCode]]) -> FALSE | B8: =ISBLANK(FUNDS[[#This Row],[Title]]) -> FALSE | C8: =ISBLANK(FUNDS[[#This Row],[FundEnabled]]) -> FALSE | D8: =IF(LEN(FUNDS[[#This Row],[FundCode]])<100,FALSE,TRUE) -> FALSE | E8: =IF(LEN(FUNDS[[#This Row],[Title]])<100,FALSE,TRUE) -> FALSE | F8: =COUNTIF(FUNDS[[#This Row],[Code is Blank]:[Title length check]],"TRUE") -> 0 | G8: HUB | H8: Maths HUB | I8: TRUE
A9: =ISBLANK(FUNDS[[#This Row],[FundCode]]) -> FALSE | B9: =ISBLANK(FUNDS[[#This Row],[Title]]) -> FALSE | C9: =ISBLANK(FUNDS[[#This Row],[FundEnabled]]) -> FALSE | D9: =IF(LEN(FUNDS[[#This Row],[FundCode]])<100,FALSE,TRUE) -> FALSE | E9: =IF(LEN(FUNDS[[#This Row],[Title]])<100,FALSE,TRUE) -> FALSE | F9: =COUNTIF(FUNDS[[#This Row],[Code is Blank]:[Title length check]],"TRUE") -> 0 | G9: OTHINC | H9: Other Income | I9: TRUE
A10: =ISBLANK(FUNDS[[#This Row],[FundCode]]) -> FALSE | B10: =ISBLANK(FUNDS[[#This Row],[Title]]) -> FALSE | C10: =ISBLANK(FUNDS[[#This Row],[FundEnabled]]) -> FALSE | D10: =IF(LEN(FUNDS[[#This Row],[FundCode]])<100,FALSE,TRUE) -> FALSE | E10: =IF(LEN(FUNDS[[#This Row],[Title]])<100,FALSE,TRUE) -> FALSE | F10: =COUNTIF(FUNDS[[#This Row],[Code is Blank]:[Title length check]],"TRUE") -> 0 | G10: PPREM | H10: Pupil Premium | I10: TRUE
A11: =ISBLANK(FUNDS[[#This Row],[FundCode]]) -> FALSE | B11: =ISBLANK(FUNDS[[#This Row],[Title]]) -> FALSE | C11: =ISBLANK(FUNDS[[#This Row],[FundEnabled]]) -> FALSE | D11: =IF(LEN(FUNDS[[#This Row],[FundCode]])<100,FALSE,TRUE) -> FALSE | E11: =IF(LEN(FUNDS[[#This Row],[Title]])<100,FALSE,TRUE) -> FALSE | F11: =COUNTIF(FUNDS[[#This Row],[Code is Blank]:[Title length check]],"TRUE") -> 0 | G11: REST | H11: Restricted Fund | I11: TRUE
A12: =ISBLANK(FUNDS[[#This Row],[FundCode]]) -> FALSE | B12: =ISBLANK(FUNDS[[#This Row],[Title]]) -> FALSE | C12: =ISBLANK(FUNDS[[#This Row],[FundEnabled]]) -> FALSE | D12: =IF(LEN(FUNDS[[#This Row],[FundCode]])<100,FALSE,TRUE) -> FALSE | E12: =IF(LEN(FUNDS[[#This Row],[Title]])<100,FALSE,TRUE) -> FALSE | F12: =COUNTIF(FUNDS[[#This Row],[Code is Blank]:[Title length check]],"TRUE") -> 0 | G12: RESTFA | H12: Restricted Fixed Asset | I12: TRUE
A13: =ISBLANK(FUNDS[[#This Row],[FundCode]]) -> FALSE | B13: =ISBLANK(FUNDS[[#This Row],[Title]]) -> FALSE | C13: =ISBLANK(FUNDS[[#This Row],[FundEnabled]]) -> FALSE | D13: =IF(LEN(FUNDS[[#This Row],[FundCode]])<100,FALSE,TRUE) -> FALSE | E13: =IF(LEN(FUNDS[[#This Row],[Title]])<100,FALSE,TRUE) -> FALSE | F13: =COUNTIF(FUNDS[[#This Row],[Code is Blank]:[Title length check]],"TRUE") -> 0 | G13: UNRF | H13: Unrestricted Fund | I13: TRUE

Sheet Activity
G1: API - Do not edit
A2: Code is Blank | B2: Title is Blank | C2: Code length Check | D2: Title length check | E2: Enabled is blank | F2: Will import if zero | G2: ActivityCode | H2: Title | I2: ActivityEnabled
A3: =ISBLANK(ACTIVITIES[[#This Row],[ActivityCode]]) -> FALSE | B3: =ISBLANK(ACTIVITIES[[#This Row],[Title]]) -> FALSE | C3: =IF(LEN(ACTIVITIES[[#This Row],[ActivityCode]])<100,FALSE,TRUE) -> FALSE | D3: =IF(LEN(ACTIVITIES[[#This Row],[Title]])<100,FALSE,TRUE) -> FALSE | E3: =ISBLANK(ACTIVITIES[[#This Row],[ActivityEnabled]]) -> FALSE | F3: =COUNTIF(ACTIVITIES[[#This Row],[Code is Blank]:[Enabled is blank]],"TRUE") -> 0 | G3: COMM | H3: Community | I3: TRUE
A4: =ISBLANK(ACTIVITIES[[#This Row],[ActivityCode]]) -> FALSE | B4: =ISBLANK(ACTIVITIES[[#This Row],[Title]]) -> FALSE | C4: =IF(LEN(ACTIVITIES[[#This Row],[ActivityCode]])<100,FALSE,TRUE) -> FALSE | D4: =IF(LEN(ACTIVITIES[[#This Row],[Title]])<100,FALSE,TRUE) -> FALSE | E4: =ISBLANK(ACTIVITIES[[#This Row],[ActivityEnabled]]) -> FALSE | F4: =COUNTIF(ACTIVITIES[[#This Row],[Code is Blank]:[Enabled is blank]],"TRUE") -> 0 | G4: DEFAULT | H4: Default (no) Activity | I4: TRUE
A5: =ISBLANK(ACTIVITIES[[#This Row],[ActivityCode]]) -> FALSE | B5: =ISBLANK(ACTIVITIES[[#This Row],[Title]]) -> FALSE | C5: =IF(LEN(ACTIVITIES[[#This Row],[ActivityCode]])<100,FALSE,TRUE) -> FALSE | D5: =IF(LEN(ACTIVITIES[[#This Row],[Title]])<100,FALSE,TRUE) -> FALSE | E5: =ISBLANK(ACTIVITIES[[#This Row],[ActivityEnabled]]) -> FALSE | F5: =COUNTIF(ACTIVITIES[[#This Row],[Code is Blank]:[Enabled is blank]],"TRUE") -> 0 | G5: EXTENDED | H5: Extended | I5: TRUE
A6: =ISBLANK(ACTIVITIES[[#This Row],[ActivityCode]]) -> FALSE | B6: =ISBLANK(ACTIVITIES[[#This Row],[Title]]) -> FALSE | C6: =IF(LEN(ACTIVITIES[[#This Row],[ActivityCode]])<100,FALSE,TRUE) -> FALSE | D6: =IF(LEN(ACTIVITIES[[#This Row],[Title]])<100,FALSE,TRUE) -> FALSE | E6: =ISBLANK(ACTIVITIES[[#This Row],[ActivityEnabled]]) -> FALSE | F6: =COUNTIF(ACTIVITIES[[#This Row],[Code is Blank]:[Enabled is blank]],"TRUE") -> 0 | G6: LETTINGS | H6: Lettings | I6: TRUE
A7: =ISBLANK(ACTIVITIES[[#This Row],[ActivityCode]]) -> FALSE | B7: =ISBLANK(ACTIVITIES[[#This Row],[Title]]) -> FALSE | C7: =IF(LEN(ACTIVITIES[[#This Row],[ActivityCode]])<100,FALSE,TRUE) -> FALSE | D7: =IF(LEN(ACTIVITIES[[#This Row],[Title]])<100,FALSE,TRUE) -> FALSE | E7: =ISBLANK(ACTIVITIES[[#This Row],[ActivityEnabled]]) -> FALSE | F7: =COUNTIF(ACTIVITIES[[#This Row],[Code is Blank]:[Enabled is blank]],"TRUE") -> 0 | G7: MATHS | H7: Maths Hub | I7: TRUE
A8: =ISBLANK(ACTIVITIES[[#This Row],[ActivityCode]]) -> FALSE | B8: =ISBLANK(ACTIVITIES[[#This Row],[Title]]) -> FALSE | C8: =IF(LEN(ACTIVITIES[[#This Row],[ActivityCode]])<100,FALSE,TRUE) -> FALSE | D8: =IF(LEN(ACTIVITIES[[#This Row],[Title]])<100,FALSE,TRUE) -> FALSE | E8: =ISBLANK(ACTIVITIES[[#This Row],[ActivityEnabled]]) -> FALSE | F8: =COUNTIF(ACTIVITIES[[#This Row],[Code is Blank]:[Enabled is blank]],"TRUE") -> 0 | G8: NURSERY | H8: Nursery | I8: TRUE
A9: =ISBLANK(ACTIVITIES[[#This Row],[ActivityCode]]) -> FALSE | B9: =ISBLANK(ACTIVITIES[[#This Row],[Title]]) -> FALSE | C9: =IF(LEN(ACTIVITIES[[#This Row],[ActivityCode]])<100,FALSE,TRUE) -> FALSE | D9: =IF(LEN(ACTIVITIES[[#This Row],[Title]])<100,FALSE,TRUE) -> FALSE | E9: =ISBLANK(ACTIVITIES[[#This Row],[ActivityEnabled]]) -> FALSE | F9: =COUNTIF(ACTIVITIES[[#This Row],[Code is Blank]:[Enabled is blank]],"TRUE") -> 0 | G9: SCHFUND | H9: School Fund | I9: TRUE
A10: =ISBLANK(ACTIVITIES[[#This Row],[ActivityCode]]) -> FALSE | B10: =ISBLANK(ACTIVITIES[[#This Row],[Title]]) -> FALSE | C10: =IF(LEN(ACTIVITIES[[#This Row],[ActivityCode]])<100,FALSE,TRUE) -> FALSE | D10: =IF(LEN(ACTIVITIES[[#This Row],[Title]])<100,FALSE,TRUE) -> FALSE | E10: =ISBLANK(ACTIVITIES[[#This Row],[ActivityEnabled]]) -> FALSE | F10: =COUNTIF(ACTIVITIES[[#This Row],[Code is Blank]:[Enabled is blank]],"TRUE") -> 0 | G10: SCHOOL | H10: School | I10: TRUE

Sheet Ledger
G1: API - Do not edit
A2: Code is Blank | B2: Title is Blank | C2: Enabled is blank | D2: Code length Check | E2: Title length check | F2: Will import if zero | G2: LedgerCode | H2: Title | I2: LedgerEnabled
A3: =ISBLANK(LEDGER[[#This Row],[LedgerCode]]) -> FALSE | B3: =ISBLANK(LEDGER[[#This Row],[Title]]) -> FALSE | C3: =ISBLANK(LEDGER[[#This Row],[LedgerEnabled]]) -> FALSE | D3: =IF(LEN(LEDGER[[#This Row],[LedgerCode]])<100,FALSE,TRUE) -> FALSE | E3: =IF(LEN(LEDGER[[#This Row],[Title]])<100,FALSE,TRUE) -> FALSE | F3: =COUNTIF(LEDGER[[#This Row],[Code is Blank]:[Title length check]],"TRUE") -> 0 | G3: CAPITAL | H3: CAPITAL | I3: TRUE
A4: =ISBLANK(LEDGER[[#This Row],[LedgerCode]]) -> FALSE | B4: =ISBLANK(LEDGER[[#This Row],[Title]]) -> FALSE | C4: =ISBLANK(LEDGER[[#This Row],[LedgerEnabled]]) -> FALSE | D4: =IF(LEN(LEDGER[[#This Row],[LedgerCode]])<100,FALSE,TRUE) -> FALSE | E4: =IF(LEN(LEDGER[[#This Row],[Title]])<100,FALSE,TRUE) -> FALSE | F4: =COUNTIF(LEDGER[[#This Row],[Code is Blank]:[Title length check]],"TRUE") -> 0 | G4: COSTCENTRES | H4: COSTCENTRES | I4: TRUE
A5: =ISBLANK(LEDGER[[#This Row],[LedgerCode]]) -> FALSE | B5: =ISBLANK(LEDGER[[#This Row],[Title]]) -> FALSE | C5: =ISBLANK(LEDGER[[#This Row],[LedgerEnabled]]) -> FALSE | D5: =IF(LEN(LEDGER[[#This Row],[LedgerCode]])<100,FALSE,TRUE) -> FALSE | E5: =IF(LEN(LEDGER[[#This Row],[Title]])<100,FALSE,TRUE) -> FALSE | F5: =COUNTIF(LEDGER[[#This Row],[Code is Blank]:[Title length check]],"TRUE") -> 0 | G5: COSTCTR | H5: COSTCTR | I5: TRUE
A6: =ISBLANK(LEDGER[[#This Row],[LedgerCode]]) -> FALSE | B6: =ISBLANK(LEDGER[[#This Row],[Title]]) -> FALSE | C6: =ISBLANK(LEDGER[[#This Row],[LedgerEnabled]]) -> FALSE | D6: =IF(LEN(LEDGER[[#This Row],[LedgerCode]])<100,FALSE,TRUE) -> FALSE | E6: =IF(LEN(LEDGER[[#This Row],[Title]])<100,FALSE,TRUE) -> FALSE | F6: =COUNTIF(LEDGER[[#This Row],[Code is Blank]:[Title length check]],"TRUE") -> 0 | G6: DEFAULT | H6: Default (no) Ledger | I6: TRUE
A7: =ISBLANK(LEDGER[[#This Row],[LedgerCode]]) -> FALSE | B7: =ISBLANK(LEDGER[[#This Row],[Title]]) -> FALSE | C7: =ISBLANK(LEDGER[[#This Row],[LedgerEnabled]]) -> FALSE | D7: =IF(LEN(LEDGER[[#This Row],[LedgerCode]])<100,FALSE,TRUE) -> FALSE | E7: =IF(LEN(LEDGER[[#This Row],[Title]])<100,FALSE,TRUE) -> FALSE | F7: =COUNTIF(LEDGER[[#This Row],[Code is Blank]:[Title length check]],"TRUE") -> 0 | G7: SALARY | H7: SALARY | I7: TRUE
A8: =ISBLANK(LEDGER[[#This Row],[LedgerCode]]) -> FALSE | B8: =ISBLANK(LEDGER[[#This Row],[Title]]) -> FALSE | C8: =ISBLANK(LEDGER[[#This Row],[LedgerEnabled]]) -> FALSE | D8: =IF(LEN(LEDGER[[#This Row],[LedgerCode]])<100,FALSE,TRUE) -> FALSE | E8: =IF(LEN(LEDGER[[#This Row],[Title]])<100,FALSE,TRUE) -> FALSE | F8: =COUNTIF(LEDGER[[#This Row],[Code is Blank]:[Title length check]],"TRUE") -> 0 | G8: TRIPS | H8: TRIPS | I8: TRUE

Sheet CustGroup
G1: API - Do not edit
A2: Code is Blank | B2: Title is Blank | C2: Code length Check | D2: Title length check | E2: Enabled is blank | F2: Will import if zero | G2: CustomGroupingCode | H2: Title | I2: CustomGroupingEnabled
A3: =ISBLANK(CUSTGROUP[[#This Row],[CustomGroupingCode]]) -> FALSE | B3: =ISBLANK(CUSTGROUP[[#This Row],[Title]]) -> FALSE | C3: =IF(LEN(CUSTGROUP[[#This Row],[CustomGroupingCode]])<100,FALSE,TRUE) -> FALSE | D3: =IF(LEN(CUSTGROUP[[#This Row],[Title]])<100,FALSE,TRUE) -> FALSE | E3: =ISBLANK(CUSTGROUP[[#This Row],[CustomGroupingEnabled]]) -> FALSE | F3: =COUNTIF(CUSTGROUP[[#This Row],[Code is Blank]:[Enabled is blank]],"TRUE") -> 0 | G3: A0 | H3: GAG funding | I3: TRUE
A4: =ISBLANK(CUSTGROUP[[#This Row],[CustomGroupingCode]]) -> FALSE | B4: =ISBLANK(CUSTGROUP[[#This Row],[Title]]) -> FALSE | C4: =IF(LEN(CUSTGROUP[[#This Row],[CustomGroupingCode]])<100,FALSE,TRUE) -> FALSE | D4: =IF(LEN(CUSTGROUP[[#This Row],[Title]])<100,FALSE,TRUE) -> FALSE | E4: =ISBLANK(CUSTGROUP[[#This Row],[CustomGroupingEnabled]]) -> FALSE | F4: =COUNTIF(CUSTGROUP[[#This Row],[Code is Blank]:[Enabled is blank]],"TRUE") -> 0 | G4: A1 | H4: Other DfE Grants - Standards Funds | I4: TRUE
A5: =ISBLANK(CUSTGROUP[[#This Row],[CustomGroupingCode]]) -> FALSE | B5: =ISBLANK(CUSTGROUP[[#This Row],[Title]]) -> FALSE | C5: =IF(LEN(CUSTGROUP[[#This Row],[CustomGroupingCode]])<100,FALSE,TRUE) -> FALSE | D5: =IF(LEN(CUSTGROUP[[#This Row],[Title]])<100,FALSE,TRUE) -> FALSE | E5: =ISBLANK(CUSTGROUP[[#This Row],[CustomGroupingEnabled]]) -> FALSE | F5: =COUNTIF(CUSTGROUP[[#This Row],[Code is Blank]:[Enabled is blank]],"TRUE") -> 0 | G5: A2 | H5: Other Govt Grants | I5: TRUE
A6: =ISBLANK(CUSTGROUP[[#This Row],[CustomGroupingCode]]) -> FALSE | B6: =ISBLANK(CUSTGROUP[[#This Row],[Title]]) -> FALSE | C6: =IF(LEN(CUSTGROUP[[#This Row],[CustomGroupingCode]])<100,FALSE,TRUE) -> FALSE | D6: =IF(LEN(CUSTGROUP[[#This Row],[Title]])<100,FALSE,TRUE) -> FALSE | E6: =ISBLANK(CUSTGROUP[[#This Row],[CustomGroupingEnabled]]) -> FALSE | F6: =COUNTIF(CUSTGROUP[[#This Row],[Code is Blank]:[Enabled is blank]],"TRUE") -> 0 | G6: A3 | H6: Private Sector Funding | I6: TRUE
A7: =ISBLANK(CUSTGROUP[[#This Row],[CustomGroupingCode]]) -> FALSE | B7: =ISBLANK(CUSTGROUP[[#This Row],[Title]]) -> FALSE | C7: =IF(LEN(CUSTGROUP[[#This Row],[CustomGroupingCode]])<100,FALSE,TRUE) -> FALSE | D7: =IF(LEN(CUSTGROUP[[#This Row],[Title]])<100,FALSE,TRUE) -> FALSE | E7: =ISBLANK(CUSTGROUP[[#This Row],[CustomGroupingEnabled]]) -> FALSE | F7: =COUNTIF(CUSTGROUP[[#This Row],[Code is Blank]:[Enabled is blank]],"TRUE") -> 0 | G7: A4 | H7: Other Income | I7: TRUE
A8: =ISBLANK(CUSTGROUP[[#This Row],[CustomGroupingCode]]) -> FALSE | B8: =ISBLANK(CUSTGROUP[[#This Row],[Title]]) -> FALSE | C8: =IF(LEN(CUSTGROUP[[#This Row],[CustomGroupingCode]])<100,FALSE,TRUE) -> FALSE | D8: =IF(LEN(CUSTGROUP[[#This Row],[Title]])<100,FALSE,TRUE) -> FALSE | E8: =ISBLANK(CUSTGROUP[[#This Row],[CustomGroupingEnabled]]) -> FALSE | F8: =COUNTIF(CUSTGROUP[[#This Row],[Code is Blank]:[Enabled is blank]],"TRUE") -> 0 | G8: B0 | H8: Teaching Staff | I8: TRUE
A9: =ISBLANK(CUSTGROUP[[#This Row],[CustomGroupingCode]]) -> FALSE | B9: =ISBLANK(CUSTGROUP[[#This Row],[Title]]) -> FALSE | C9: =IF(LEN(CUSTGROUP[[#This Row],[CustomGroupingCode]])<100,FALSE,TRUE) -> FALSE | D9: =IF(LEN(CUSTGROUP[[#This Row],[Title]])<100,FALSE,TRUE) -> FALSE | E9: =ISBLANK(CUSTGROUP[[#This Row],[CustomGroupingEnabled]]) -> FALSE | F9: =COUNTIF(CUSTGROUP[[#This Row],[Code is Blank]:[Enabled is blank]],"TRUE") -> 0 | G9: B1 | H9: Educational Support Staff | I9: TRUE
A10: =ISBLANK(CUSTGROUP[[#This Row],[CustomGroupingCode]]) -> FALSE | B10: =ISBLANK(CUSTGROUP[[#This Row],[Title]]) -> FALSE | C10: =IF(LEN(CUSTGROUP[[#This Row],[CustomGroupingCode]])<100,FALSE,TRUE) -> FALSE | D10: =IF(LEN(CUSTGROUP[[#This Row],[Title]])<100,FALSE,TRUE) -> FALSE | E10: =ISBLANK(CUSTGROUP[[#This Row],[CustomGroupingEnabled]]) -> FALSE | F10: =COUNTIF(CUSTGROUP[[#This Row],[Code is Blank]:[Enabled is blank]],"TRUE") -> 0 | G10: B2 | H10: Premises Staffing | I10: TRUE
A11: =ISBLANK(CUSTGROUP[[#This Row],[CustomGroupingCode]]) -> FALSE | B11: =ISBLANK(CUSTGROUP[[#This Row],[Title]]) -> FALSE | C11: =IF(LEN(CUSTGROUP[[#This Row],[CustomGroupingCode]])<100,FALSE,TRUE) -> FALSE | D11: =IF(LEN(CUSTGROUP[[#This Row],[Title]])<100,FALSE,TRUE) -> FALSE | E11: =ISBLANK(CUSTGROUP[[#This Row],[CustomGroupingEnabled]]) -> FALSE | F11: =COUNTIF(CUSTGROUP[[#This Row],[Code is Blank]:[Enabled is blank]],"TRUE") -> 0 | G11: B3 | H11: Admin Staffing | I11: TRUE
A12: =ISBLANK(CUSTGROUP[[#This Row],[CustomGroupingCode]]) -> FALSE | B12: =ISBLANK(CUSTGROUP[[#This Row],[Title]]) -> FALSE | C12: =IF(LEN(CUSTGROUP[[#This Row],[CustomGroupingCode]])<100,FALSE,TRUE) -> FALSE | D12: =IF(LEN(CUSTGROUP[[#This Row],[Title]])<100,FALSE,TRUE) -> FALSE | E12: =ISBLANK(CUSTGROUP[[#This Row],[CustomGroupingEnabled]]) -> FALSE | F12: =COUNTIF(CUSTGROUP[[#This Row],[Code is Blank]:[Enabled is blank]],"TRUE") -> 0 | G12: B4 | H12: Other Staff | I12: TRUE
A13: =ISBLANK(CUSTGROUP[[#This Row],[CustomGroupingCode]]) -> FALSE | B13: =ISBLANK(CUSTGROUP[[#This Row],[Title]]) -> FALSE | C13: =IF(LEN(CUSTGROUP[[#This Row],[CustomGroupingCode]])<100,FALSE,TRUE) -> FALSE | D13: =IF(LEN(CUSTGROUP[[#This Row],[Title]])<100,FALSE,TRUE) -> FALSE | E13: =ISBLANK(CUSTGROUP[[#This Row],[CustomGroupingEnabled]]) -> FALSE | F13: =COUNTIF(CUSTGROUP[[#This Row],[Code is Blank]:[Enabled is blank]],"TRUE") -> 0 | G13: B5 | H13: Agency Staff | I13: TRUE
A14: =ISBLANK(CUSTGROUP[[#This Row],[CustomGroupingCode]]) -> FALSE | B14: =ISBLANK(CUSTGROUP[[#This Row],[Title]]) -> FALSE | C14: =IF(LEN(CUSTGROUP[[#This Row],[CustomGroupingCode]])<100,FALSE,TRUE) -> FALSE | D14: =IF(LEN(CUSTGROUP[[#This Row],[Title]])<100,FALSE,TRUE) -> FALSE | E14: =ISBLANK(CUSTGROUP[[#This Row],[CustomGroupingEnabled]]) -> FALSE | F14: =COUNTIF(CUSTGROUP[[#This Row],[Code is Blank]:[Enabled is blank]],"TRUE") -> 0 | G14: B6 | H14: SLT Staff Costs | I14: TRUE
... A55: =ISBLANK(CUSTGROUP[[#This Row],[CustomGroupingCode]]) -> FALSE | B55: =ISBLANK(CUSTGROUP[[#This Row],[Title]]) -> FALSE | C55: =IF(LEN(CUSTGROUP[[#This Row],[CustomGroupingCode]])<100,FALSE,TRUE) -> FALSE | D55: =IF(LEN(CUSTGROUP[[#This Row],[Title]])<100,FALSE,TRUE) -> FALSE | E55: =ISBLANK(CUSTGROUP[[#This Row],[CustomGroupingEnabled]]) -> FALSE | F55: =COUNTIF(CUSTGROUP[[#This Row],[Code is Blank]:[Enabled is blank]],"TRUE") -> 0 | G55: ZZZ | H55: Not Applicable | I55: TRUE

Sheet SchHub
G1: API - Do not edit
A2: Code is Blank | B2: Title is Blank | C2: Enabled is blank | D2: Code length Check | E2: Title length check | F2: Will import if zero | G2: SchoolHubCode | H2: Title | I2: SchoolHubEnabled
A3: =ISBLANK(SCHHUB[[#This Row],[SchoolHubCode]]) -> FALSE | B3: =ISBLANK(SCHHUB[[#This Row],[Title]]) -> FALSE | C3: =ISBLANK(SCHHUB[[#This Row],[SchoolHubEnabled]]) -> FALSE | D3: =IF(LEN(SCHHUB[[#This Row],[SchoolHubCode]])<100,FALSE,TRUE) -> FALSE | E3: =IF(LEN(SCHHUB[[#This Row],[Title]])<100,FALSE,TRUE) -> FALSE | F3: =COUNTIF(SCHHUB[[#This Row],[Code is Blank]:[Title length check]],"TRUE") -> 0 | G3: CENTRAL | H3: Central Hub | I3: TRUE
A4: =ISBLANK(SCHHUB[[#This Row],[SchoolHubCode]]) -> FALSE | B4: =ISBLANK(SCHHUB[[#This Row],[Title]]) -> FALSE | C4: =ISBLANK(SCHHUB[[#This Row],[SchoolHubEnabled]]) -> FALSE | D4: =IF(LEN(SCHHUB[[#This Row],[SchoolHubCode]])<100,FALSE,TRUE) -> FALSE | E4: =IF(LEN(SCHHUB[[#This Row],[Title]])<100,FALSE,TRUE) -> FALSE | F4: =COUNTIF(SCHHUB[[#This Row],[Code is Blank]:[Title length check]],"TRUE") -> 0 | G4: DEFAULT | H4: Default (no) Hub | I4: TRUE
A5: =ISBLANK(SCHHUB[[#This Row],[SchoolHubCode]]) -> FALSE | B5: =ISBLANK(SCHHUB[[#This Row],[Title]]) -> FALSE | C5: =ISBLANK(SCHHUB[[#This Row],[SchoolHubEnabled]]) -> FALSE | D5: =IF(LEN(SCHHUB[[#This Row],[SchoolHubCode]])<100,FALSE,TRUE) -> FALSE | E5: =IF(LEN(SCHHUB[[#This Row],[Title]])<100,FALSE,TRUE) -> FALSE | F5: =COUNTIF(SCHHUB[[#This Row],[Code is Blank]:[Title length check]],"TRUE") -> 0 | G5: EAST | H5: East Hub | I5: TRUE
A6: =ISBLANK(SCHHUB[[#This Row],[SchoolHubCode]]) -> FALSE | B6: =ISBLANK(SCHHUB[[#This Row],[Title]]) -> FALSE | C6: =ISBLANK(SCHHUB[[#This Row],[SchoolHubEnabled]]) -> FALSE | D6: =IF(LEN(SCHHUB[[#This Row],[SchoolHubCode]])<100,FALSE,TRUE) -> FALSE | E6: =IF(LEN(SCHHUB[[#This Row],[Title]])<100,FALSE,TRUE) -> FALSE | F6: =COUNTIF(SCHHUB[[#This Row],[Code is Blank]:[Title length check]],"TRUE") -> 0 | G6: NORTH | H6: North Hub | I6: TRUE
A7: =ISBLANK(SCHHUB[[#This Row],[SchoolHubCode]]) -> FALSE | B7: =ISBLANK(SCHHUB[[#This Row],[Title]]) -> FALSE | C7: =ISBLANK(SCHHUB[[#This Row],[SchoolHubEnabled]]) -> FALSE | D7: =IF(LEN(SCHHUB[[#This Row],[SchoolHubCode]])<100,FALSE,TRUE) -> FALSE | E7: =IF(LEN(SCHHUB[[#This Row],[Title]])<100,FALSE,TRUE) -> FALSE | F7: =COUNTIF(SCHHUB[[#This Row],[Code is Blank]:[Title length check]],"TRUE") -> 0 | G7: SOUTH | H7: South Hub | I7: TRUE
A8: =ISBLANK(SCHHUB[[#This Row],[SchoolHubCode]]) -> FALSE | B8: =ISBLANK(SCHHUB[[#This Row],[Title]]) -> FALSE | C8: =ISBLANK(SCHHUB[[#This Row],[SchoolHubEnabled]]) -> FALSE | D8: =IF(LEN(SCHHUB[[#This Row],[SchoolHubCode]])<100,FALSE,TRUE) -> FALSE | E8: =IF(LEN(SCHHUB[[#This Row],[Title]])<100,FALSE,TRUE) -> FALSE | F8: =COUNTIF(SCHHUB[[#This Row],[Code is Blank]:[Title length check]],"TRUE") -> 0 | G8: WEST | H8: West Hub | I8: TRUE

Sheet SchType
G1: API - Do not edit
A2: Code is Blank | B2: Title is Blank | C2: Enabled is blank | D2: Code length Check | E2: Title length check | F2: Will import if zero | G2: SchoolTypeCode | H2: Title | I2: SchoolTypeEnabled
A3: =ISBLANK(SCHTYPE[[#This Row],[SchoolTypeCode]]) -> FALSE | B3: =ISBLANK(SCHTYPE[[#This Row],[Title]]) -> FALSE | C3: =ISBLANK(SCHTYPE[[#This Row],[SchoolTypeEnabled]]) -> FALSE | D3: =IF(LEN(SCHTYPE[[#This Row],[SchoolTypeCode]])<100,FALSE,TRUE) -> FALSE | E3: =IF(LEN(SCHTYPE[[#This Row],[Title]])<100,FALSE,TRUE) -> FALSE | F3: =COUNTIF(SCHTYPE[[#This Row],[Code is Blank]:[Title length check]],"TRUE") -> 0 | G3: ALLTHROUGH | H3: All Through School | I3: TRUE
A4: =ISBLANK(SCHTYPE[[#This Row],[SchoolTypeCode]]) -> FALSE | B4: =ISBLANK(SCHTYPE[[#This Row],[Title]]) -> FALSE | C4: =ISBLANK(SCHTYPE[[#This Row],[SchoolTypeEnabled]]) -> FALSE | D4: =IF(LEN(SCHTYPE[[#This Row],[SchoolTypeCode]])<100,FALSE,TRUE) -> FALSE | E4: =IF(LEN(SCHTYPE[[#This Row],[Title]])<100,FALSE,TRUE) -> FALSE | F4: =COUNTIF(SCHTYPE[[#This Row],[Code is Blank]:[Title length check]],"TRUE") -> 0 | G4: CENTRAL | H4: Central | I4: TRUE
A5: =ISBLANK(SCHTYPE[[#This Row],[SchoolTypeCode]]) -> FALSE | B5: =ISBLANK(SCHTYPE[[#This Row],[Title]]) -> FALSE | C5: =ISBLANK(SCHTYPE[[#This Row],[SchoolTypeEnabled]]) -> FALSE | D5: =IF(LEN(SCHTYPE[[#This Row],[SchoolTypeCode]])<100,FALSE,TRUE) -> FALSE | E5: =IF(LEN(SCHTYPE[[#This Row],[Title]])<100,FALSE,TRUE) -> FALSE | F5: =COUNTIF(SCHTYPE[[#This Row],[Code is Blank]:[Title length check]],"TRUE") -> 0 | G5: DEFAULT | H5: Default (no) Type | I5: TRUE
A6: =ISBLANK(SCHTYPE[[#This Row],[SchoolTypeCode]]) -> FALSE | B6: =ISBLANK(SCHTYPE[[#This Row],[Title]]) -> FALSE | C6: =ISBLANK(SCHTYPE[[#This Row],[SchoolTypeEnabled]]) -> FALSE | D6: =IF(LEN(SCHTYPE[[#This Row],[SchoolTypeCode]])<100,FALSE,TRUE) -> FALSE | E6: =IF(LEN(SCHTYPE[[#This Row],[Title]])<100,FALSE,TRUE) -> FALSE | F6: =COUNTIF(SCHTYPE[[#This Row],[Code is Blank]:[Title length check]],"TRUE") -> 0 | G6: OTHER | H6: Other | I6: TRUE
A7: =ISBLANK(SCHTYPE[[#This Row],[SchoolTypeCode]]) -> FALSE | B7: =ISBLANK(SCHTYPE[[#This Row],[Title]]) -> FALSE | C7: =ISBLANK(SCHTYPE[[#This Row],[SchoolTypeEnabled]]) -> FALSE | D7: =IF(LEN(SCHTYPE[[#This Row],[SchoolTypeCode]])<100,FALSE,TRUE) -> FALSE | E7: =IF(LEN(SCHTYPE[[#This Row],[Title]])<100,FALSE,TRUE) -> FALSE | F7: =COUNTIF(SCHTYPE[[#This Row],[Code is Blank]:[Title length check]],"TRUE") -> 0 | G7: PRIMARY | H7: Primary School | I7: TRUE
A8: =ISBLANK(SCHTYPE[[#This Row],[SchoolTypeCode]]) -> FALSE | B8: =ISBLANK(SCHTYPE[[#This Row],[Title]]) -> FALSE | C8: =ISBLANK(SCHTYPE[[#This Row],[SchoolTypeEnabled]]) -> FALSE | D8: =IF(LEN(SCHTYPE[[#This Row],[SchoolTypeCode]])<100,FALSE,TRUE) -> FALSE | E8: =IF(LEN(SCHTYPE[[#This Row],[Title]])<100,FALSE,TRUE) -> FALSE | F8: =COUNTIF(SCHTYPE[[#This Row],[Code is Blank]:[Title length check]],"TRUE") -> 0 | G8: SECONDARY | H8: Secondary School | I8: TRUE

Sheet LocalAuth
G1: This grey section can be edited | H1: API - Do not edit
A2: Code is Blank | B2: Title is Blank | C2: Enabled is blank | D2: Code length Check | E2: Title length check | F2: Will import if zero | G2: LA | H2: SchoolLocalAuthorityCode | I2: Title | J2: SchoolLocalAuthorityEnabled
A3: =ISBLANK(LocalAuth[[#This Row],[SchoolLocalAuthorityCode]]) -> FALSE | B3: =ISBLANK(LocalAuth[[#This Row],[Title]]) -> FALSE | C3: =ISBLANK(LocalAuth[[#This Row],[SchoolLocalAuthorityEnabled]]) -> FALSE | D3: =IF(LEN(LocalAuth[[#This Row],[SchoolLocalAuthorityCode]])<100,FALSE,TRUE) -> FALSE | E3: =IF(LEN(LocalAuth[[#This Row],[Title]])<100,FALSE,TRUE) -> FALSE | F3: =COUNTIF(LocalAuth[[#This Row],[Code is Blank]:[Title length check]],"TRUE") -> 0 | G3: LA0 | H3: CHE | I3: Cheshire East | J3: TRUE
A4: =ISBLANK(LocalAuth[[#This Row],[SchoolLocalAuthorityCode]]) -> FALSE | B4: =ISBLANK(LocalAuth[[#This Row],[Title]]) -> FALSE | C4: =ISBLANK(LocalAuth[[#This Row],[SchoolLocalAuthorityEnabled]]) -> FALSE | D4: =IF(LEN(LocalAuth[[#This Row],[SchoolLocalAuthorityCode]])<100,FALSE,TRUE) -> FALSE | E4: =IF(LEN(LocalAuth[[#This Row],[Title]])<100,FALSE,TRUE) -> FALSE | F4: =COUNTIF(LocalAuth[[#This Row],[Code is Blank]:[Title length check]],"TRUE") -> 0 | G4: LA2 | H4: DEFAULT | I4: Default (no) Local Authority | J4: TRUE

Sheet Schools
G1: This grey section can be edited | J1: API - Do not edit
A2: HubIssues | B2: SchTypeIssue | C2: Blank Data | D2: Code length Check | E2: Title length check | F2: Will Import if 0 | G2: London Weighting Type | H2: LA | I2: School Type | J2: SchoolLocalAuthority | K2: SchoolCode | L2: SchoolHub | M2: SchoolType | N2: Title | O2: LondonWeighting | P2: UniqueReferenceNumber | Q2: TeachingHours | R2: SchoolEnabled
A3: =IF(COUNTIF(SCHHUB[SchoolHubCode],SCHOOLS[[#This Row],[SchoolHub]])>0,0,1) -> 0 | B3: =IF(COUNTIF(SCHTYPE[SchoolTypeCode],SCHOOLS[[#This Row],[SchoolType]])>0,0,1) -> 0 | C3: =COUNTBLANK(SCHOOLS[[#This Row],[SchoolLocalAuthority]:[SchoolEnabled]]) -> 0 | D3: =IF(LEN(SCHOOLS[[#This Row],[SchoolCode]])<100,0,1) -> 0 | E3: =IF(LEN(SCHOOLS[[#This Row],[Title]])<100,0,1) -> 0 | F3: =SUM(SCHOOLS[[#This Row],[HubIssues]:[Title length check]]) -> 0 | G3: England & Wales | H3: =_xlfn.XLOOKUP(SCHOOLS[[#This Row],[SchoolLocalAuthority]],LocalAuth[SchoolLocalAuthorityCode],LocalAuth[LA]) -> LA0 | I3: Central | J3: CHE | K3: ALS | L3: DEFAULT | M3: SECONDARY | N3: Alsager School | O3: FALSE | P3: 140108 | Q3: 32.436 | R3: TRUE
A4: =IF(COUNTIF(SCHHUB[SchoolHubCode],SCHOOLS[[#This Row],[SchoolHub]])>0,0,1) -> 0 | B4: =IF(COUNTIF(SCHTYPE[SchoolTypeCode],SCHOOLS[[#This Row],[SchoolType]])>0,0,1) -> 0 | C4: =COUNTBLANK(SCHOOLS[[#This Row],[SchoolLocalAuthority]:[SchoolEnabled]]) -> 0 | D4: =IF(LEN(SCHOOLS[[#This Row],[SchoolCode]])<100,0,1) -> 0 | E4: =IF(LEN(SCHOOLS[[#This Row],[Title]])<100,0,1) -> 0 | F4: =SUM(SCHOOLS[[#This Row],[HubIssues]:[Title length check]]) -> 0 | G4: England & Wales | H4: =_xlfn.XLOOKUP(SCHOOLS[[#This Row],[SchoolLocalAuthority]],LocalAuth[SchoolLocalAuthorityCode],LocalAuth[LA]) -> LA0 | I4: Secondary | J4: CHE | K4: AUD | L4: DEFAULT | M4: PRIMARY | N4: Audlem St James' CofE Primary | O4: FALSE | P4: 148489 | Q4: 32.436 | R4: TRUE
A5: =IF(COUNTIF(SCHHUB[SchoolHubCode],SCHOOLS[[#This Row],[SchoolHub]])>0,0,1) -> 0 | B5: =IF(COUNTIF(SCHTYPE[SchoolTypeCode],SCHOOLS[[#This Row],[SchoolType]])>0,0,1) -> 0 | C5: =COUNTBLANK(SCHOOLS[[#This Row],[SchoolLocalAuthority]:[SchoolEnabled]]) -> 0 | D5: =IF(LEN(SCHOOLS[[#This Row],[SchoolCode]])<100,0,1) -> 0 | E5: =IF(LEN(SCHOOLS[[#This Row],[Title]])<100,0,1) -> 0 | F5: =SUM(SCHOOLS[[#This Row],[HubIssues]:[Title length check]]) -> 0 | G5: England & Wales | H5: =_xlfn.XLOOKUP(SCHOOLS[[#This Row],[SchoolLocalAuthority]],LocalAuth[SchoolLocalAuthorityCode],LocalAuth[LA]) -> LA0 | I5: Primary | J5: CHE | K5: BLS | L5: DEFAULT | M5: SECONDARY | N5: Brine Leas School | O5: FALSE | P5: 136279 | Q5: 32.436 | R5: TRUE
A6: =IF(COUNTIF(SCHHUB[SchoolHubCode],SCHOOLS[[#This Row],[SchoolHub]])>0,0,1) -> 0 | B6: =IF(COUNTIF(SCHTYPE[SchoolTypeCode],SCHOOLS[[#This Row],[SchoolType]])>0,0,1) -> 0 | C6: =COUNTBLANK(SCHOOLS[[#This Row],[SchoolLocalAuthority]:[SchoolEnabled]]) -> 0 | D6: =IF(LEN(SCHOOLS[[#This Row],[SchoolCode]])<100,0,1) -> 0 | E6: =IF(LEN(SCHOOLS[[#This Row],[Title]])<100,0,1) -> 0 | F6: =SUM(SCHOOLS[[#This Row],[HubIssues]:[Title length check]]) -> 0 | G6: England & Wales | H6: =_xlfn.XLOOKUP(SCHOOLS[[#This Row],[SchoolLocalAuthority]],LocalAuth[SchoolLocalAuthorityCode],LocalAuth[LA]) -> LA0 | I6: AllThrough | J6: CHE | K6: HIG | L6: DEFAULT | M6: PRIMARY | N6: Alsager Highfields Primary School | O6: FALSE | P6: 148136 | Q6: 32.436 | R6: TRUE
A7: =IF(COUNTIF(SCHHUB[SchoolHubCode],SCHOOLS[[#This Row],[SchoolHub]])>0,0,1) -> 0 | B7: =IF(COUNTIF(SCHTYPE[SchoolTypeCode],SCHOOLS[[#This Row],[SchoolType]])>0,0,1) -> 0 | C7: =COUNTBLANK(SCHOOLS[[#This Row],[SchoolLocalAuthority]:[SchoolEnabled]]) -> 0 | D7: =IF(LEN(SCHOOLS[[#This Row],[SchoolCode]])<100,0,1) -> 0 | E7: =IF(LEN(SCHOOLS[[#This Row],[Title]])<100,0,1) -> 0 | F7: =SUM(SCHOOLS[[#This Row],[HubIssues]:[Title length check]]) -> 0 | G7: England & Wales | H7: =_xlfn.XLOOKUP(SCHOOLS[[#This Row],[SchoolLocalAuthority]],LocalAuth[SchoolLocalAuthorityCode],LocalAuth[LA]) -> LA2 | J7: DEFAULT | K7: HUB | L7: DEFAULT | M7: DEFAULT | N7: Maths Hub | O7: FALSE | P7: 0 | Q7: 0 | R7: TRUE
A8: =IF(COUNTIF(SCHHUB[SchoolHubCode],SCHOOLS[[#This Row],[SchoolHub]])>0,0,1) -> 0 | B8: =IF(COUNTIF(SCHTYPE[SchoolTypeCode],SCHOOLS[[#This Row],[SchoolType]])>0,0,1) -> 0 | C8: =COUNTBLANK(SCHOOLS[[#This Row],[SchoolLocalAuthority]:[SchoolEnabled]]) -> 0 | D8: =IF(LEN(SCHOOLS[[#This Row],[SchoolCode]])<100,0,1) -> 0 | E8: =IF(LEN(SCHOOLS[[#This Row],[Title]])<100,0,1) -> 0 | F8: =SUM(SCHOOLS[[#This Row],[HubIssues]:[Title length check]]) -> 0 | G8: England & Wales | H8: =_xlfn.XLOOKUP(SCHOOLS[[#This Row],[SchoolLocalAuthority]],LocalAuth[SchoolLocalAuthorityCode],LocalAuth[LA]) -> LA0 | J8: CHE | K8: MAT | L8: DEFAULT | M8: CENTRAL | N8: The Cornovii Trust | O8: FALSE | P8: 1 | Q8: 32.436 | R8: TRUE
A9: =IF(COUNTIF(SCHHUB[SchoolHubCode],SCHOOLS[[#This Row],[SchoolHub]])>0,0,1) -> 0 | B9: =IF(COUNTIF(SCHTYPE[SchoolTypeCode],SCHOOLS[[#This Row],[SchoolType]])>0,0,1) -> 0 | C9: =COUNTBLANK(SCHOOLS[[#This Row],[SchoolLocalAuthority]:[SchoolEnabled]]) -> 0 | D9: =IF(LEN(SCHOOLS[[#This Row],[SchoolCode]])<100,0,1) -> 0 | E9: =IF(LEN(SCHOOLS[[#This Row],[Title]])<100,0,1) -> 0 | F9: =SUM(SCHOOLS[[#This Row],[HubIssues]:[Title length check]]) -> 0 | G9: England & Wales | H9: =_xlfn.XLOOKUP(SCHOOLS[[#This Row],[SchoolLocalAuthority]],LocalAuth[SchoolLocalAuthorityCode],LocalAuth[LA]) -> LA0 | J9: CHE | K9: MLB | L9: DEFAULT | M9: SECONDARY | N9: Malbank School and Sixth Form College | O9: FALSE | P9: 111419 | Q9: 32.436 | R9: TRUE
A10: =IF(COUNTIF(SCHHUB[SchoolHubCode],SCHOOLS[[#This Row],[SchoolHub]])>0,0,1) -> 0 | B10: =IF(COUNTIF(SCHTYPE[SchoolTypeCode],SCHOOLS[[#This Row],[SchoolType]])>0,0,1) -> 0 | C10: =COUNTBLANK(SCHOOLS[[#This Row],[SchoolLocalAuthority]:[SchoolEnabled]]) -> 0 | D10: =IF(LEN(SCHOOLS[[#This Row],[SchoolCode]])<100,0,1) -> 0 | E10: =IF(LEN(SCHOOLS[[#This Row],[Title]])<100,0,1) -> 0 | F10: =SUM(SCHOOLS[[#This Row],[HubIssues]:[Title length check]]) -> 0 | G10: England & Wales | H10: =_xlfn.XLOOKUP(SCHOOLS[[#This Row],[SchoolLocalAuthority]],LocalAuth[SchoolLocalAuthorityCode],LocalAuth[LA]) -> LA0 | J10: CHE | K10: PTP | L10: DEFAULT | M10: PRIMARY | N10: Pear Tree Primary School | O10: FALSE | P10: 140740 | Q10: 32.436 | R10: TRUE
A11: =IF(COUNTIF(SCHHUB[SchoolHubCode],SCHOOLS[[#This Row],[SchoolHub]])>0,0,1) -> 0 | B11: =IF(COUNTIF(SCHTYPE[SchoolTypeCode],SCHOOLS[[#This Row],[SchoolType]])>0,0,1) -> 0 | C11: =COUNTBLANK(SCHOOLS[[#This Row],[SchoolLocalAuthority]:[SchoolEnabled]]) -> 0 | D11: =IF(LEN(SCHOOLS[[#This Row],[SchoolCode]])<100,0,1) -> 0 | E11: =IF(LEN(SCHOOLS[[#This Row],[Title]])<100,0,1) -> 0 | F11: =SUM(SCHOOLS[[#This Row],[HubIssues]:[Title length check]]) -> 0 | G11: England & Wales | H11: =_xlfn.XLOOKUP(SCHOOLS[[#This Row],[SchoolLocalAuthority]],LocalAuth[SchoolLocalAuthorityCode],LocalAuth[LA]) -> LA0 | J11: CHE | K11: SBL | L11: DEFAULT | M11: PRIMARY | N11: Stapeley Broad Lane CofE Primary School | O11: FALSE | P11: 139539 | Q11: 32.436 | R11: TRUE
A12: =IF(COUNTIF(SCHHUB[SchoolHubCode],SCHOOLS[[#This Row],[SchoolHub]])>0,0,1) -> 0 | B12: =IF(COUNTIF(SCHTYPE[SchoolTypeCode],SCHOOLS[[#This Row],[SchoolType]])>0,0,1) -> 0 | C12: =COUNTBLANK(SCHOOLS[[#This Row],[SchoolLocalAuthority]:[SchoolEnabled]]) -> 0 | D12: =IF(LEN(SCHOOLS[[#This Row],[SchoolCode]])<100,0,1) -> 0 | E12: =IF(LEN(SCHOOLS[[#This Row],[Title]])<100,0,1) -> 0 | F12: =SUM(SCHOOLS[[#This Row],[HubIssues]:[Title length check]]) -> 0 | G12: England & Wales | H12: =_xlfn.XLOOKUP(SCHOOLS[[#This Row],[SchoolLocalAuthority]],LocalAuth[SchoolLocalAuthorityCode],LocalAuth[LA]) -> LA0 | J12: CHE | K12: WVP | L12: DEFAULT | M12: PRIMARY | N12: Weston Village Primary School | O12: FALSE | P12: 145587 | Q12: 32.436 | R12: TRUE

Sheet Depts
G1: API - Do not edit
A2: FundIssue | B2: ActivityIssue | C2: LedgerIssue | D2: Code length Check | E2: Title length check | F2: Will Import if 0 | G2: DepartmentCode | H2: Title | I2: AvailableToAllSchools | J2: SchoolCodes | K2: ActivityCode | L2: FundCode | M2: LedgerCode | N2: DefaultFinanceCode | O2: DepartmentEnabled
A3: =IF(COUNTIF(FUNDS[FundCode],DEPTS[[#This Row],[FundCode]])>0,0,1) -> 0 | B3: =IF(COUNTIF(ACTIVITIES[ActivityCode],DEPTS[[#This Row],[ActivityCode]])>0,0,1) -> 0 | C3: =IF(COUNTIF(LEDGER[LedgerCode],DEPTS[[#This Row],[LedgerCode]])>0,0,1) -> 0 | D3: =IF(LEN(DEPTS[[#This Row],[DepartmentCode]])<100,0,1) -> 0 | E3: =IF(LEN(DEPTS[[#This Row],[Title]])<100,0,1) -> 0 | F3: =SUM(DEPTS[[#This Row],[FundIssue]:[Title length check]]) -> 0 | G3: ACHIEVE | H3: Keep on Track / Achievement | I3: FALSE | J3: MAT | K3: SCHOOL | L3: GAG | M3: COSTCENTRES | O3: TRUE
A4: =IF(COUNTIF(FUNDS[FundCode],DEPTS[[#This Row],[FundCode]])>0,0,1) -> 0 | B4: =IF(COUNTIF(ACTIVITIES[ActivityCode],DEPTS[[#This Row],[ActivityCode]])>0,0,1) -> 0 | C4: =IF(COUNTIF(LEDGER[LedgerCode],DEPTS[[#This Row],[LedgerCode]])>0,0,1) -> 0 | D4: =IF(LEN(DEPTS[[#This Row],[DepartmentCode]])<100,0,1) -> 0 | E4: =IF(LEN(DEPTS[[#This Row],[Title]])<100,0,1) -> 0 | F4: =SUM(DEPTS[[#This Row],[FundIssue]:[Title length check]]) -> 0 | G4: ACHIEVE | H4: Keep on Track / Achievement | I4: FALSE | J4: ALS | K4: SCHOOL | L4: GAG | M4: COSTCTR | O4: TRUE
A5: =IF(COUNTIF(FUNDS[FundCode],DEPTS[[#This Row],[FundCode]])>0,0,1) -> 0 | B5: =IF(COUNTIF(ACTIVITIES[ActivityCode],DEPTS[[#This Row],[ActivityCode]])>0,0,1) -> 0 | C5: =IF(COUNTIF(LEDGER[LedgerCode],DEPTS[[#This Row],[LedgerCode]])>0,0,1) -> 0 | D5: =IF(LEN(DEPTS[[#This Row],[DepartmentCode]])<100,0,1) -> 0 | E5: =IF(LEN(DEPTS[[#This Row],[Title]])<100,0,1) -> 0 | F5: =SUM(DEPTS[[#This Row],[FundIssue]:[Title length check]]) -> 0 | G5: ACT | H5: Alsager Community Trust | I5: FALSE | J5: MAT | K5: COMM | L5: ACT | M5: COSTCENTRES | O5: TRUE
A6: =IF(COUNTIF(FUNDS[FundCode],DEPTS[[#This Row],[FundCode]])>0,0,1) -> 0 | B6: =IF(COUNTIF(ACTIVITIES[ActivityCode],DEPTS[[#This Row],[ActivityCode]])>0,0,1) -> 0 | C6: =IF(COUNTIF(LEDGER[LedgerCode],DEPTS[[#This Row],[LedgerCode]])>0,0,1) -> 0 | D6: =IF(LEN(DEPTS[[#This Row],[DepartmentCode]])<100,0,1) -> 0 | E6: =IF(LEN(DEPTS[[#This Row],[Title]])<100,0,1) -> 0 | F6: =SUM(DEPTS[[#This Row],[FundIssue]:[Title length check]]) -> 0 | G6: ACT | H6: Alsager Community Trust | I6: FALSE | J6: ALS | K6: COMM | L6: ACT | M6: COSTCTR | O6: TRUE
A7: =IF(COUNTIF(FUNDS[FundCode],DEPTS[[#This Row],[FundCode]])>0,0,1) -> 0 | B7: =IF(COUNTIF(ACTIVITIES[ActivityCode],DEPTS[[#This Row],[ActivityCode]])>0,0,1) -> 0 | C7: =IF(COUNTIF(LEDGER[LedgerCode],DEPTS[[#This Row],[LedgerCode]])>0,0,1) -> 0 | D7: =IF(LEN(DEPTS[[#This Row],[DepartmentCode]])<100,0,1) -> 0 | E7: =IF(LEN(DEPTS[[#This Row],[Title]])<100,0,1) -> 0 | F7: =SUM(DEPTS[[#This Row],[FundIssue]:[Title length check]]) -> 0 | G7: ADMIN | H7: Administration | I7: FALSE | J7: MAT | K7: DEFAULT | L7: DEFAULT | M7: COSTCENTRES | O7: TRUE
A8: =IF(COUNTIF(FUNDS[FundCode],DEPTS[[#This Row],[FundCode]])>0,0,1) -> 0 | B8: =IF(COUNTIF(ACTIVITIES[ActivityCode],DEPTS[[#This Row],[ActivityCode]])>0,0,1) -> 0 | C8: =IF(COUNTIF(LEDGER[LedgerCode],DEPTS[[#This Row],[LedgerCode]])>0,0,1) -> 0 | D8: =IF(LEN(DEPTS[[#This Row],[DepartmentCode]])<100,0,1) -> 0 | E8: =IF(LEN(DEPTS[[#This Row],[Title]])<100,0,1) -> 0 | F8: =SUM(DEPTS[[#This Row],[FundIssue]:[Title length check]]) -> 0 | G8: ADMIN | H8: Administration | I8: FALSE | J8: AUD,BLS,MLB,PTP | K8: DEFAULT | L8: DEFAULT | M8: COSTCTR | O8: TRUE
A9: =IF(COUNTIF(FUNDS[FundCode],DEPTS[[#This Row],[FundCode]])>0,0,1) -> 0 | B9: =IF(COUNTIF(ACTIVITIES[ActivityCode],DEPTS[[#This Row],[ActivityCode]])>0,0,1) -> 0 | C9: =IF(COUNTIF(LEDGER[LedgerCode],DEPTS[[#This Row],[LedgerCode]])>0,0,1) -> 0 | D9: =IF(LEN(DEPTS[[#This Row],[DepartmentCode]])<100,0,1) -> 0 | E9: =IF(LEN(DEPTS[[#This Row],[Title]])<100,0,1) -> 0 | F9: =SUM(DEPTS[[#This Row],[FundIssue]:[Title length check]]) -> 0 | G9: ADMIN | H9: Administration | I9: FALSE | J9: ALS,WVP,HIG,SBL | K9: SCHOOL | L9: DEFAULT | M9: COSTCTR | O9: TRUE
A10: =IF(COUNTIF(FUNDS[FundCode],DEPTS[[#This Row],[FundCode]])>0,0,1) -> 0 | B10: =IF(COUNTIF(ACTIVITIES[ActivityCode],DEPTS[[#This Row],[ActivityCode]])>0,0,1) -> 0 | C10: =IF(COUNTIF(LEDGER[LedgerCode],DEPTS[[#This Row],[LedgerCode]])>0,0,1) -> 0 | D10: =IF(LEN(DEPTS[[#This Row],[DepartmentCode]])<100,0,1) -> 0 | E10: =IF(LEN(DEPTS[[#This Row],[Title]])<100,0,1) -> 0 | F10: =SUM(DEPTS[[#This Row],[FundIssue]:[Title length check]]) -> 0 | G10: ADMINSER | H10: MAT contribution | I10: FALSE | J10: MAT | K10: DEFAULT | L10: DEFAULT | M10: COSTCENTRES | O10: TRUE
A11: =IF(COUNTIF(FUNDS[FundCode],DEPTS[[#This Row],[FundCode]])>0,0,1) -> 0 | B11: =IF(COUNTIF(ACTIVITIES[ActivityCode],DEPTS[[#This Row],[ActivityCode]])>0,0,1) -> 0 | C11: =IF(COUNTIF(LEDGER[LedgerCode],DEPTS[[#This Row],[LedgerCode]])>0,0,1) -> 0 | D11: =IF(LEN(DEPTS[[#This Row],[DepartmentCode]])<100,0,1) -> 0 | E11: =IF(LEN(DEPTS[[#This Row],[Title]])<100,0,1) -> 0 | F11: =SUM(DEPTS[[#This Row],[FundIssue]:[Title length check]]) -> 0 | G11: ADMINSER | H11: MAT contribution | I11: FALSE | J11: WVP,HIG,AUD,BLS,MLB,PTP,SBL | K11: DEFAULT | L11: DEFAULT | M11: COSTCTR | O11: TRUE
A12: =IF(COUNTIF(FUNDS[FundCode],DEPTS[[#This Row],[FundCode]])>0,0,1) -> 0 | B12: =IF(COUNTIF(ACTIVITIES[ActivityCode],DEPTS[[#This Row],[ActivityCode]])>0,0,1) -> 0 | C12: =IF(COUNTIF(LEDGER[LedgerCode],DEPTS[[#This Row],[LedgerCode]])>0,0,1) -> 0 | D12: =IF(LEN(DEPTS[[#This Row],[DepartmentCode]])<100,0,1) -> 0 | E12: =IF(LEN(DEPTS[[#This Row],[Title]])<100,0,1) -> 0 | F12: =SUM(DEPTS[[#This Row],[FundIssue]:[Title length check]]) -> 0 | G12: ADMINSER | H12: MAT contribution | I12: FALSE | J12: ALS | K12: SCHOOL | L12: DEFAULT | M12: COSTCTR | O12: TRUE
A13: =IF(COUNTIF(FUNDS[FundCode],DEPTS[[#This Row],[FundCode]])>0,0,1) -> 0 | B13: =IF(COUNTIF(ACTIVITIES[ActivityCode],DEPTS[[#This Row],[ActivityCode]])>0,0,1) -> 0 | C13: =IF(COUNTIF(LEDGER[LedgerCode],DEPTS[[#This Row],[LedgerCode]])>0,0,1) -> 0 | D13: =IF(LEN(DEPTS[[#This Row],[DepartmentCode]])<100,0,1) -> 0 | E13: =IF(LEN(DEPTS[[#This Row],[Title]])<100,0,1) -> 0 | F13: =SUM(DEPTS[[#This Row],[FundIssue]:[Title length check]]) -> 0 | G13: ADSER | H13: Admin Services | I13: FALSE | J13: AUD | K13: DEFAULT | L13: DEFAULT | M13: COSTCTR | O13: TRUE
A14: =IF(COUNTIF(FUNDS[FundCode],DEPTS[[#This Row],[FundCode]])>0,0,1) -> 0 | B14: =IF(COUNTIF(ACTIVITIES[ActivityCode],DEPTS[[#This Row],[ActivityCode]])>0,0,1) -> 0 | C14: =IF(COUNTIF(LEDGER[LedgerCode],DEPTS[[#This Row],[LedgerCode]])>0,0,1) -> 0 | D14: =IF(LEN(DEPTS[[#This Row],[DepartmentCode]])<100,0,1) -> 0 | E14: =IF(LEN(DEPTS[[#This Row],[Title]])<100,0,1) -> 0 | F14: =SUM(DEPTS[[#This Row],[FundIssue]:[Title length check]]) -> 0 | G14: ADSER | H14: Admin Services | I14: FALSE | J14: WVP,HIG,SBL | K14: SCHOOL | L14: DEFAULT | M14: COSTCTR | O14: TRUE
... A195: =IF(COUNTIF(FUNDS[FundCode],DEPTS[[#This Row],[FundCode]])>0,0,1) -> 0 | B195: =IF(COUNTIF(ACTIVITIES[ActivityCode],DEPTS[[#This Row],[ActivityCode]])>0,0,1) -> 0 | C195: =IF(COUNTIF(LEDGER[LedgerCode],DEPTS[[#This Row],[LedgerCode]])>0,0,1) -> 0 | D195: =IF(LEN(DEPTS[[#This Row],[DepartmentCode]])<100,0,1) -> 0 | E195: =IF(LEN(DEPTS[[#This Row],[Title]])<100,0,1) -> 0 | F195: =SUM(DEPTS[[#This Row],[FundIssue]:[Title length check]]) -> 0 | G195: CWARWICK | H195: Warwick | I195: FALSE | J195: BLS | K195: DEFAULT | L195: DEFAULT | M195: COSTCTR | O195: TRUE
A196: =IF(COUNTIF(FUNDS[FundCode],DEPTS[[#This Row],[FundCode]])>0,0,1) -> 0 | B196: =IF(COUNTIF(ACTIVITIES[ActivityCode],DEPTS[[#This Row],[ActivityCode]])>0,0,1) -> 0 | C196: =IF(COUNTIF(LEDGER[LedgerCode],DEPTS[[#This Row],[LedgerCode]])>0,0,1) -> 0 | D196: =IF(LEN(DEPTS[[#This Row],[DepartmentCode]])<100,0,1) -> 0 | E196: =IF(LEN(DEPTS[[#This Row],[Title]])<100,0,1) -> 0 | F196: =SUM(DEPTS[[#This Row],[FundIssue]:[Title length check]]) -> 0 | G196: DEFAULT | H196: Default (no) Department | I196: TRUE | K196: DEFAULT | L196: DEFAULT | M196: DEFAULT | O196: TRUE
A197: =IF(COUNTIF(FUNDS[FundCode],DEPTS[[#This Row],[FundCode]])>0,0,1) -> 0 | B197: =IF(COUNTIF(ACTIVITIES[ActivityCode],DEPTS[[#This Row],[ActivityCode]])>0,0,1) -> 0 | C197: =IF(COUNTIF(LEDGER[LedgerCode],DEPTS[[#This Row],[LedgerCode]])>0,0,1) -> 0 | D197: =IF(LEN(DEPTS[[#This Row],[DepartmentCode]])<100,0,1) -> 0 | E197: =IF(LEN(DEPTS[[#This Row],[Title]])<100,0,1) -> 0 | F197: =SUM(DEPTS[[#This Row],[FundIssue]:[Title length check]]) -> 0 | G197: DEP | H197: Depreciation | I197: FALSE | J197: ALS,WVP,MLB,MAT | K197: DEFAULT | L197: DEFAULT | M197: CAPITAL | O197: TRUE
A198: =IF(COUNTIF(FUNDS[FundCode],DEPTS[[#This Row],[FundCode]])>0,0,1) -> 0 | B198: =IF(COUNTIF(ACTIVITIES[ActivityCode],DEPTS[[#This Row],[ActivityCode]])>0,0,1) -> 0 | C198: =IF(COUNTIF(LEDGER[LedgerCode],DEPTS[[#This Row],[LedgerCode]])>0,0,1) -> 0 | D198: =IF(LEN(DEPTS[[#This Row],[DepartmentCode]])<100,0,1) -> 0 | E198: =IF(LEN(DEPTS[[#This Row],[Title]])<100,0,1) -> 0 | F198: =SUM(DEPTS[[#This Row],[FundIssue]:[Title length check]]) -> 0 | G198: DEP | H198: Depreciation | I198: FALSE | J198: HIG | K198: DEFAULT | L198: RESTFA | M198: CAPITAL | O198: TRUE
A199: =IF(COUNTIF(FUNDS[FundCode],DEPTS[[#This Row],[FundCode]])>0,0,1) -> 0 | B199: =IF(COUNTIF(ACTIVITIES[ActivityCode],DEPTS[[#This Row],[ActivityCode]])>0,0,1) -> 0 | C199: =IF(COUNTIF(LEDGER[LedgerCode],DEPTS[[#This Row],[LedgerCode]])>0,0,1) -> 0 | D199: =IF(LEN(DEPTS[[#This Row],[DepartmentCode]])<100,0,1) -> 0 | E199: =IF(LEN(DEPTS[[#This Row],[Title]])<100,0,1) -> 0 | F199: =SUM(DEPTS[[#This Row],[FundIssue]:[Title length check]]) -> 0 | G199: EXAGSS | H199: Agency Supply Staff | I199: FALSE | J199: MAT | K199: DEFAULT | L199: DEFAULT | M199: COSTCENTRES | O199: TRUE
A200: =IF(COUNTIF(FUNDS[FundCode],DEPTS[[#This Row],[FundCode]])>0,0,1) -> 0 | B200: =IF(COUNTIF(ACTIVITIES[ActivityCode],DEPTS[[#This Row],[ActivityCode]])>0,0,1) -> 0 | C200: =IF(COUNTIF(LEDGER[LedgerCode],DEPTS[[#This Row],[LedgerCode]])>0,0,1) -> 0 | D200: =IF(LEN(DEPTS[[#This Row],[DepartmentCode]])<100,0,1) -> 0 | E200: =IF(LEN(DEPTS[[#This Row],[Title]])<100,0,1) -> 0 | F200: =SUM(DEPTS[[#This Row],[FundIssue]:[Title length check]]) -> 0 | G200: EXAGSS | H200: Agency Supply Staff | I200: FALSE | J200: AUD,BLS,MLB,PTP | K200: DEFAULT | L200: DEFAULT | M200: COSTCTR | O200: TRUE
A201: =IF(COUNTIF(FUNDS[FundCode],DEPTS[[#This Row],[FundCode]])>0,0,1) -> 0 | B201: =IF(COUNTIF(ACTIVITIES[ActivityCode],DEPTS[[#This Row],[ActivityCode]])>0,0,1) -> 0 | C201: =IF(COUNTIF(LEDGER[LedgerCode],DEPTS[[#This Row],[LedgerCode]])>0,0,1) -> 0 | D201: =IF(LEN(DEPTS[[#This Row],[DepartmentCode]])<100,0,1) -> 0 | E201: =IF(LEN(DEPTS[[#This Row],[Title]])<100,0,1) -> 0 | F201: =SUM(DEPTS[[#This Row],[FundIssue]:[Title length check]]) -> 0 | G201: EXAGSS | H201: Agency Supply Staff | I201: FALSE | J201: ALS,WVP,HIG,SBL | K201: SCHOOL | L201: DEFAULT | M201: COSTCTR | O201: TRUE
A202: =IF(COUNTIF(FUNDS[FundCode],DEPTS[[#This Row],[FundCode]])>0,0,1) -> 0 | B202: =IF(COUNTIF(ACTIVITIES[ActivityCode],DEPTS[[#This Row],[ActivityCode]])>0,0,1) -> 0 | C202: =IF(COUNTIF(LEDGER[LedgerCode],DEPTS[[#This Row],[LedgerCode]])>0,0,1) -> 0 | D202: =IF(LEN(DEPTS[[#This Row],[DepartmentCode]])<100,0,1) -> 0 | E202: =IF(LEN(DEPTS[[#This Row],[Title]])<100,0,1) -> 0 | F202: =SUM(DEPTS[[#This Row],[FundIssue]:[Title length check]]) -> 0 | G202: EXAM | H202: Examinations | I202: FALSE | J202: MAT | K202: DEFAULT | L202: DEFAULT | M202: COSTCENTRES | O202: TRUE
A203: =IF(COUNTIF(FUNDS[FundCode],DEPTS[[#This Row],[FundCode]])>0,0,1) -> 0 | B203: =IF(COUNTIF(ACTIVITIES[ActivityCode],DEPTS[[#This Row],[ActivityCode]])>0,0,1) -> 0 | C203: =IF(COUNTIF(LEDGER[LedgerCode],DEPTS[[#This Row],[LedgerCode]])>0,0,1) -> 0 | D203: =IF(LEN(DEPTS[[#This Row],[DepartmentCode]])<100,0,1) -> 0 | E203: =IF(LEN(DEPTS[[#This Row],[Title]])<100,0,1) -> 0 | F203: =SUM(DEPTS[[#This Row],[FundIssue]:[Title length check]]) -> 0 | G203: EXAM | H203: Examinations | I203: FALSE | J203: BLS,MLB | K203: DEFAULT | L203: DEFAULT | M203: COSTCTR | O203: TRUE
A204: =IF(COUNTIF(FUNDS[FundCode],DEPTS[[#This Row],[FundCode]])>0,0,1) -> 0 | B204: =IF(COUNTIF(ACTIVITIES[ActivityCode],DEPTS[[#This Row],[ActivityCode]])>0,0,1) -> 0 | C204: =IF(COUNTIF(LEDGER[LedgerCode],DEPTS[[#This Row],[LedgerCode]])>0,0,1) -> 0 | D204: =IF(LEN(DEPTS[[#This Row],[DepartmentCode]])<100,0,1) -> 0 | E204: =IF(LEN(DEPTS[[#This Row],[Title]])<100,0,1) -> 0 | F204: =SUM(DEPTS[[#This Row],[FundIssue]:[Title length check]]) -> 0 | G204: EXAM | H204: Examinations | I204: FALSE | J204: ALS | K204: SCHOOL | L204: DEFAULT | M204: COSTCTR | O204: TRUE
A205: =IF(COUNTIF(FUNDS[FundCode],DEPTS[[#This Row],[FundCode]])>0,0,1) -> 0 | B205: =IF(COUNTIF(ACTIVITIES[ActivityCode],DEPTS[[#This Row],[ActivityCode]])>0,0,1) -> 0 | C205: =IF(COUNTIF(LEDGER[LedgerCode],DEPTS[[#This Row],[LedgerCode]])>0,0,1) -> 0 | D205: =IF(LEN(DEPTS[[#This Row],[DepartmentCode]])<100,0,1) -> 0 | E205: =IF(LEN(DEPTS[[#This Row],[Title]])<100,0,1) -> 0 | F205: =SUM(DEPTS[[#This Row],[FundIssue]:[Title length check]]) -> 0 | G205: EXASTRO | H205: Astro Turf | I205: FALSE | J205: ALS | K205: SCHOOL | L205: RESTFA | M205: CAPITAL | O205: TRUE
A206: =IF(COUNTIF(FUNDS[FundCode],DEPTS[[#This Row],[FundCode]])>0,0,1) -> 0 | B206: =IF(COUNTIF(ACTIVITIES[ActivityCode],DEPTS[[#This Row],[ActivityCode]])>0,0,1) -> 0 | C206: =IF(COUNTIF(LEDGER[LedgerCode],DEPTS[[#This Row],[LedgerCode]])>0,0,1) -> 0 | D206: =IF(LEN(DEPTS[[#This Row],[DepartmentCode]])<100,0,1) -> 0 | E206: =IF(LEN(DEPTS[[#This Row],[Title]])<100,0,1) -> 0 | F206: =SUM(DEPTS[[#This Row],[FundIssue]:[Title length check]]) -> 0 | G206: EXCAPCIF19 | H206: CIF 2019/20 | I206: FALSE | J206: WVP | K206: SCHOOL | L206: RESTFA | M206: CAPITAL | O206: TRUE
A207: =IF(COUNTIF(FUNDS[FundCode],DEPTS[[#This Row],[FundCode]])>0,0,1) -> 0 | B207: =IF(COUNTIF(ACTIVITIES[ActivityCode],DEPTS[[#This Row],[ActivityCode]])>0,0,1) -> 0 | C207: =IF(COUNTIF(LEDGER[LedgerCode],DEPTS[[#This Row],[LedgerCode]])>0,0,1) -> 0 | D207: =IF(LEN(DEPTS[[#This Row],[DepartmentCode]])<100,0,1) -> 0 | E207: =IF(LEN(DEPTS[[#This Row],[Title]])<100,0,1) -> 0 | F207: =SUM(DEPTS[[#This Row],[FundIssue]:[Title length check]]) -> 0 | G207: EXCAPCIF20 | H207: CIF 2020/21 | I207: FALSE | J207: ALS,WVP | K207: SCHOOL | L207: RESTFA | M207: CAPITAL | O207: TRUE
A208: =IF(COUNTIF(FUNDS[FundCode],DEPTS[[#This Row],[FundCode]])>0,0,1) -> 0 | B208: =IF(COUNTIF(ACTIVITIES[ActivityCode],DEPTS[[#This Row],[ActivityCode]])>0,0,1) -> 0 | C208: =IF(COUNTIF(LEDGER[LedgerCode],DEPTS[[#This Row],[LedgerCode]])>0,0,1) -> 0 | D208: =IF(LEN(DEPTS[[#This Row],[DepartmentCode]])<100,0,1) -> 0 | E208: =IF(LEN(DEPTS[[#This Row],[Title]])<100,0,1) -> 0 | F208: =SUM(DEPTS[[#This Row],[FundIssue]:[Title length check]]) -> 0 | G208: EXCAPCIF20 | H208: CIF 2020/21 | I208: FALSE | J208: MAT | K208: SCHOOL | L208: RESTFA | M208: COSTCENTRES | O208: TRUE
... A454: =IF(COUNTIF(FUNDS[FundCode],DEPTS[[#This Row],[FundCode]])>0,0,1) -> 0 | B454: =IF(COUNTIF(ACTIVITIES[ActivityCode],DEPTS[[#This Row],[ActivityCode]])>0,0,1) -> 0 | C454: =IF(COUNTIF(LEDGER[LedgerCode],DEPTS[[#This Row],[LedgerCode]])>0,0,1) -> 0 | D454: =IF(LEN(DEPTS[[#This Row],[DepartmentCode]])<100,0,1) -> 0 | E454: =IF(LEN(DEPTS[[#This Row],[Title]])<100,0,1) -> 0 | F454: =SUM(DEPTS[[#This Row],[FundIssue]:[Title length check]]) -> 0 | G454: WORK | H454: Core Enrichment | I454: FALSE | J454: ALS | K454: SCHOOL | L454: DEFAULT | M454: COSTCTR | O454: TRUE

Sheet SourceFinanceCodes
A1: School Type | B1: LA | C1: London Weighting | D1: Key stage | E1: FinanceCode | F1: Title | G1: FinanceCodeTypeCode | H1: GroupingCode2 | I1: CustomGrouping | J1: LedgerCode | K1: AvailableToAllSchools | L1: SchoolCodes | M1: FinanceCodeEnabled | N1: BalanceToScenario
A2: All | E2: A_FTE_ADM | F2: Finance Admin Annual FTE | G2: STATISTICS | H2: Z05 | I2: ZZZ | K2: TRUE | M2: TRUE | N2: FALSE
A3: All | E3: A_FTE_CAT | F3: Catering Annual FTE | G3: STATISTICS | H3: Z05 | I3: ZZZ | K3: TRUE | M3: TRUE | N3: FALSE
A4: All | E4: A_FTE_CLE | F4: Cleaning Annual FTE | G4: STATISTICS | H4: Z05 | I4: ZZZ | K4: TRUE | M4: TRUE | N4: FALSE
A5: All | E5: A_FTE_COM | F5: Community Facilities Annual FTE | G5: STATISTICS | H5: Z05 | I5: ZZZ | K5: TRUE | M5: TRUE | N5: FALSE
A6: All | E6: A_FTE_COV | F6: Cover Annual FTE | G6: STATISTICS | H6: Z05 | I6: ZZZ | K6: TRUE | M6: TRUE | N6: FALSE
A7: All | E7: A_FTE_EDS | F7: Education Support Annual FTE | G7: STATISTICS | H7: Z05 | I7: ZZZ | K7: TRUE | M7: TRUE | N7: FALSE
A8: All | E8: A_FTE_ESTF | F8: External Staff Annual FTE | G8: STATISTICS | H8: ZZZ | I8: ZZZ | K8: TRUE | M8: TRUE | N8: FALSE
A9: All | E9: A_FTE_EXT | F9: Extended Schools Annual FTE | G9: STATISTICS | H9: Z05 | I9: ZZZ | K9: TRUE | M9: TRUE | N9: FALSE
A10: All | E10: A_FTE_FLA | F10: FLA Annual FTE | G10: STATISTICS | H10: Z05 | I10: ZZZ | K10: TRUE | M10: TRUE | N10: FALSE
A11: All | E11: A_FTE_FSW | F11: Family Support Annual FTE | G11: STATISTICS | H11: Z05 | I11: ZZZ | K11: TRUE | M11: TRUE | N11: FALSE
A12: All | E12: A_FTE_INV | F12: Invigilator Annual FTE | G12: STATISTICS | H12: Z05 | I12: ZZZ | K12: TRUE | M12: TRUE | N12: FALSE
A13: All | E13: A_FTE_LEAVE_ADJ_ADM | F13: Finance Admin Annual FTE Leave Adjustment | G13: STATISTICS | H13: Z17 | I13: ZZZ | K13: TRUE | M13: TRUE | N13: FALSE
... A92: All | E92: WK_FTE_TEC | F92: Technicians Weekly FTE | G92: STATISTICS | H92: Z03 | I92: ZZZ | K92: TRUE | M92: TRUE | N92: FALSE

Sheet Finance Codes S2
A1: LedgerIssue | B1: GroupingCodeIssue | C1: CustGrIssue | D1: SchCodeIssue | E1: DupCode | F1: DupDesc | G1: FCTypeIss | H1: TRUE/FALSE Check | I1: Code length Check | J1: Blank Title Check | K1: Blank Code Check | L1: Title length check | M1: Balance to Scenario Blank | N1: Space in code | O1: Will Import if 0 | P1: FinanceCode | Q1: Title | R1: FinanceCodeTypeCode | S1: GroupingCode | T1: CustomGrouping | U1: LedgerCode | V1: AvailableToAllSchools | W1: SchoolCodes | X1: FinanceCodeEnabled | Y1: BalanceToScenario | Z1: IsBalanceSheet
A2: =IF(COUNTIF(LEDGER[LedgerCode],FC_import[[#This Row],[LedgerCode]])>0,0,1) -> 0 | B2: =IF(COUNTIF(Table_System_Grouping_Codes[groupingCodeCode],FC_import[[#This Row],[GroupingCode]])>0,0,1) -> 0 | C2: =IF(COUNTIF(CUSTGROUP[CustomGroupingCode],FC_import[[#This Row],[CustomGrouping]])>0,0,1) -> 0 | D2: {=IF(FC_import[[#This Row],[AvailableToAllSchools]]=TRUE,0,COUNTA(_xlfn.TEXTSPLIT(FC_import[[#This Row],[SchoolCodes]],",",,TRUE))-SUM(COUNTIF(SCHOOLS[SchoolCode],_xlfn.TEXTSPLIT(FC_import[[#This Row],[SchoolCodes]],",",,TRUE))))} -> 0 | E2: =IF(FC_import[[#This Row],[FinanceCodeTypeCode]]="BUDGET",0,COUNTIF(P:P,P2)-1) -> 0 | F2: =IF(FC_import[[#This Row],[FinanceCodeTypeCode]]="BUDGET",0,COUNTIF(Q:Q,Q2)-1) -> 0 | G2: =COUNTIF(Lookup!$A$2:$A$7,R2)-1 -> 0 | H2: =IF(OR(FC_import[[#This Row],[FinanceCodeEnabled]]=TRUE,FC_import[[#This Row],[FinanceCodeEnabled]]=FALSE),0,1) -> 0 | I2: =IF(LEN(FC_import[[#This Row],[FinanceCode]])<100,0,1) -> 0 | J2: =IF(TRIM(FC_import[[#This Row],[Title]])="",1,0) -> 0 | K2: =IF(TRIM(FC_import[[#This Row],[FinanceCode]])="",1,0) -> 0 | L2: =IF(LEN(FC_import[[#This Row],[Title]])<100,0,1) -> 0 | M2: =IF(ISBLANK(FC_import[[#This Row],[BalanceToScenario]]),1,0) -> 0 | N2: =IF(SUBSTITUTE(TEXT(FC_import[[#This Row],[FinanceCode]],10)," ","")=TEXT(FC_import[[#This Row],[FinanceCode]],10),0,1) -> 0 | O2: =SUM(A2:C2,E2:N2) -> 0 | P2: A_FTE_ADM | Q2: Finance Admin Annual FTE | R2: STATISTICS | S2: Z05 | T2: ZZZ | U2: COSTCTR | V2: TRUE | X2: TRUE | Y2: FALSE | Z2: =FALSE -> FALSE
A3: =IF(COUNTIF(LEDGER[LedgerCode],FC_import[[#This Row],[LedgerCode]])>0,0,1) -> 0 | B3: =IF(COUNTIF(Table_System_Grouping_Codes[groupingCodeCode],FC_import[[#This Row],[GroupingCode]])>0,0,1) -> 0 | C3: =IF(COUNTIF(CUSTGROUP[CustomGroupingCode],FC_import[[#This Row],[CustomGrouping]])>0,0,1) -> 0 | D3: {=IF(FC_import[[#This Row],[AvailableToAllSchools]]=TRUE,0,COUNTA(_xlfn.TEXTSPLIT(FC_import[[#This Row],[SchoolCodes]],",",,TRUE))-SUM(COUNTIF(SCHOOLS[SchoolCode],_xlfn.TEXTSPLIT(FC_import[[#This Row],[SchoolCodes]],",",,TRUE))))} -> 0 | E3: =IF(FC_import[[#This Row],[FinanceCodeTypeCode]]="BUDGET",0,COUNTIF(P:P,P3)-1) -> 0 | F3: =IF(FC_import[[#This Row],[FinanceCodeTypeCode]]="BUDGET",0,COUNTIF(Q:Q,Q3)-1) -> 0 | G3: =COUNTIF(Lookup!$A$2:$A$7,R3)-1 -> 0 | H3: =IF(OR(FC_import[[#This Row],[FinanceCodeEnabled]]=TRUE,FC_import[[#This Row],[FinanceCodeEnabled]]=FALSE),0,1) -> 0 | I3: =IF(LEN(FC_import[[#This Row],[FinanceCode]])<100,0,1) -> 0 | J3: =IF(TRIM(FC_import[[#This Row],[Title]])="",1,0) -> 0 | K3: =IF(TRIM(FC_import[[#This Row],[FinanceCode]])="",1,0) -> 0 | L3: =IF(LEN(FC_import[[#This Row],[Title]])<100,0,1) -> 0 | M3: =IF(ISBLANK(FC_import[[#This Row],[BalanceToScenario]]),1,0) -> 0 | N3: =IF(SUBSTITUTE(TEXT(FC_import[[#This Row],[FinanceCode]],10)," ","")=TEXT(FC_import[[#This Row],[FinanceCode]],10),0,1) -> 0 | O3: =SUM(A3:C3,E3:N3) -> 0 | P3: A_FTE_CAT | Q3: Catering Annual FTE | R3: STATISTICS | S3: Z05 | T3: ZZZ | U3: COSTCTR | V3: TRUE | X3: TRUE | Y3: FALSE | Z3: =FALSE -> FALSE
A4: =IF(COUNTIF(LEDGER[LedgerCode],FC_import[[#This Row],[LedgerCode]])>0,0,1) -> 0 | B4: =IF(COUNTIF(Table_System_Grouping_Codes[groupingCodeCode],FC_import[[#This Row],[GroupingCode]])>0,0,1) -> 0 | C4: =IF(COUNTIF(CUSTGROUP[CustomGroupingCode],FC_import[[#This Row],[CustomGrouping]])>0,0,1) -> 0 | D4: {=IF(FC_import[[#This Row],[AvailableToAllSchools]]=TRUE,0,COUNTA(_xlfn.TEXTSPLIT(FC_import[[#This Row],[SchoolCodes]],",",,TRUE))-SUM(COUNTIF(SCHOOLS[SchoolCode],_xlfn.TEXTSPLIT(FC_import[[#This Row],[SchoolCodes]],",",,TRUE))))} -> 0 | E4: =IF(FC_import[[#This Row],[FinanceCodeTypeCode]]="BUDGET",0,COUNTIF(P:P,P4)-1) -> 0 | F4: =IF(FC_import[[#This Row],[FinanceCodeTypeCode]]="BUDGET",0,COUNTIF(Q:Q,Q4)-1) -> 0 | G4: =COUNTIF(Lookup!$A$2:$A$7,R4)-1 -> 0 | H4: =IF(OR(FC_import[[#This Row],[FinanceCodeEnabled]]=TRUE,FC_import[[#This Row],[FinanceCodeEnabled]]=FALSE),0,1) -> 0 | I4: =IF(LEN(FC_import[[#This Row],[FinanceCode]])<100,0,1) -> 0 | J4: =IF(TRIM(FC_import[[#This Row],[Title]])="",1,0) -> 0 | K4: =IF(TRIM(FC_import[[#This Row],[FinanceCode]])="",1,0) -> 0 | L4: =IF(LEN(FC_import[[#This Row],[Title]])<100,0,1) -> 0 | M4: =IF(ISBLANK(FC_import[[#This Row],[BalanceToScenario]]),1,0) -> 0 | N4: =IF(SUBSTITUTE(TEXT(FC_import[[#This Row],[FinanceCode]],10)," ","")=TEXT(FC_import[[#This Row],[FinanceCode]],10),0,1) -> 0 | O4: =SUM(A4:C4,E4:N4) -> 0 | P4: A_FTE_CLE | Q4: Cleaning Annual FTE | R4: STATISTICS | S4: Z05 | T4: ZZZ | U4: COSTCTR | V4: TRUE | X4: TRUE | Y4: FALSE | Z4: =FALSE -> FALSE
A5: =IF(COUNTIF(LEDGER[LedgerCode],FC_import[[#This Row],[LedgerCode]])>0,0,1) -> 0 | B5: =IF(COUNTIF(Table_System_Grouping_Codes[groupingCodeCode],FC_import[[#This Row],[GroupingCode]])>0,0,1) -> 0 | C5: =IF(COUNTIF(CUSTGROUP[CustomGroupingCode],FC_import[[#This Row],[CustomGrouping]])>0,0,1) -> 0 | D5: {=IF(FC_import[[#This Row],[AvailableToAllSchools]]=TRUE,0,COUNTA(_xlfn.TEXTSPLIT(FC_import[[#This Row],[SchoolCodes]],",",,TRUE))-SUM(COUNTIF(SCHOOLS[SchoolCode],_xlfn.TEXTSPLIT(FC_import[[#This Row],[SchoolCodes]],",",,TRUE))))} -> 0 | E5: =IF(FC_import[[#This Row],[FinanceCodeTypeCode]]="BUDGET",0,COUNTIF(P:P,P5)-1) -> 0 | F5: =IF(FC_import[[#This Row],[FinanceCodeTypeCode]]="BUDGET",0,COUNTIF(Q:Q,Q5)-1) -> 0 | G5: =COUNTIF(Lookup!$A$2:$A$7,R5)-1 -> 0 | H5: =IF(OR(FC_import[[#This Row],[FinanceCodeEnabled]]=TRUE,FC_import[[#This Row],[FinanceCodeEnabled]]=FALSE),0,1) -> 0 | I5: =IF(LEN(FC_import[[#This Row],[FinanceCode]])<100,0,1) -> 0 | J5: =IF(TRIM(FC_import[[#This Row],[Title]])="",1,0) -> 0 | K5: =IF(TRIM(FC_import[[#This Row],[FinanceCode]])="",1,0) -> 0 | L5: =IF(LEN(FC_import[[#This Row],[Title]])<100,0,1) -> 0 | M5: =IF(ISBLANK(FC_import[[#This Row],[BalanceToScenario]]),1,0) -> 0 | N5: =IF(SUBSTITUTE(TEXT(FC_import[[#This Row],[FinanceCode]],10)," ","")=TEXT(FC_import[[#This Row],[FinanceCode]],10),0,1) -> 0 | O5: =SUM(A5:C5,E5:N5) -> 0 | P5: A_FTE_COM | Q5: Community Facilities Annual FTE | R5: STATISTICS | S5: Z05 | T5: ZZZ | U5: COSTCTR | V5: TRUE | X5: TRUE | Y5: FALSE | Z5: =FALSE -> FALSE
A6: =IF(COUNTIF(LEDGER[LedgerCode],FC_import[[#This Row],[LedgerCode]])>0,0,1) -> 0 | B6: =IF(COUNTIF(Table_System_Grouping_Codes[groupingCodeCode],FC_import[[#This Row],[GroupingCode]])>0,0,1) -> 0 | C6: =IF(COUNTIF(CUSTGROUP[CustomGroupingCode],FC_import[[#This Row],[CustomGrouping]])>0,0,1) -> 0 | D6: {=IF(FC_import[[#This Row],[AvailableToAllSchools]]=TRUE,0,COUNTA(_xlfn.TEXTSPLIT(FC_import[[#This Row],[SchoolCodes]],",",,TRUE))-SUM(COUNTIF(SCHOOLS[SchoolCode],_xlfn.TEXTSPLIT(FC_import[[#This Row],[SchoolCodes]],",",,TRUE))))} -> 0 | E6: =IF(FC_import[[#This Row],[FinanceCodeTypeCode]]="BUDGET",0,COUNTIF(P:P,P6)-1) -> 0 | F6: =IF(FC_import[[#This Row],[FinanceCodeTypeCode]]="BUDGET",0,COUNTIF(Q:Q,Q6)-1) -> 0 | G6: =COUNTIF(Lookup!$A$2:$A$7,R6)-1 -> 0 | H6: =IF(OR(FC_import[[#This Row],[FinanceCodeEnabled]]=TRUE,FC_import[[#This Row],[FinanceCodeEnabled]]=FALSE),0,1) -> 0 | I6: =IF(LEN(FC_import[[#This Row],[FinanceCode]])<100,0,1) -> 0 | J6: =IF(TRIM(FC_import[[#This Row],[Title]])="",1,0) -> 0 | K6: =IF(TRIM(FC_import[[#This Row],[FinanceCode]])="",1,0) -> 0 | L6: =IF(LEN(FC_import[[#This Row],[Title]])<100,0,1) -> 0 | M6: =IF(ISBLANK(FC_import[[#This Row],[BalanceToScenario]]),1,0) -> 0 | N6: =IF(SUBSTITUTE(TEXT(FC_import[[#This Row],[FinanceCode]],10)," ","")=TEXT(FC_import[[#This Row],[FinanceCode]],10),0,1) -> 0 | O6: =SUM(A6:C6,E6:N6) -> 0 | P6: A_FTE_COV | Q6: Cover Annual FTE | R6: STATISTICS | S6: Z05 | T6: ZZZ | U6: COSTCTR | V6: TRUE | X6: TRUE | Y6: FALSE | Z6: =FALSE -> FALSE
A7: =IF(COUNTIF(LEDGER[LedgerCode],FC_import[[#This Row],[LedgerCode]])>0,0,1) -> 0 | B7: =IF(COUNTIF(Table_System_Grouping_Codes[groupingCodeCode],FC_import[[#This Row],[GroupingCode]])>0,0,1) -> 0 | C7: =IF(COUNTIF(CUSTGROUP[CustomGroupingCode],FC_import[[#This Row],[CustomGrouping]])>0,0,1) -> 0 | D7: {=IF(FC_import[[#This Row],[AvailableToAllSchools]]=TRUE,0,COUNTA(_xlfn.TEXTSPLIT(FC_import[[#This Row],[SchoolCodes]],",",,TRUE))-SUM(COUNTIF(SCHOOLS[SchoolCode],_xlfn.TEXTSPLIT(FC_import[[#This Row],[SchoolCodes]],",",,TRUE))))} -> 0 | E7: =IF(FC_import[[#This Row],[FinanceCodeTypeCode]]="BUDGET",0,COUNTIF(P:P,P7)-1) -> 0 | F7: =IF(FC_import[[#This Row],[FinanceCodeTypeCode]]="BUDGET",0,COUNTIF(Q:Q,Q7)-1) -> 0 | G7: =COUNTIF(Lookup!$A$2:$A$7,R7)-1 -> 0 | H7: =IF(OR(FC_import[[#This Row],[FinanceCodeEnabled]]=TRUE,FC_import[[#This Row],[FinanceCodeEnabled]]=FALSE),0,1) -> 0 | I7: =IF(LEN(FC_import[[#This Row],[FinanceCode]])<100,0,1) -> 0 | J7: =IF(TRIM(FC_import[[#This Row],[Title]])="",1,0) -> 0 | K7: =IF(TRIM(FC_import[[#This Row],[FinanceCode]])="",1,0) -> 0 | L7: =IF(LEN(FC_import[[#This Row],[Title]])<100,0,1) -> 0 | M7: =IF(ISBLANK(FC_import[[#This Row],[BalanceToScenario]]),1,0) -> 0 | N7: =IF(SUBSTITUTE(TEXT(FC_import[[#This Row],[FinanceCode]],10)," ","")=TEXT(FC_import[[#This Row],[FinanceCode]],10),0,1) -> 0 | O7: =SUM(A7:C7,E7:N7) -> 0 | P7: A_FTE_EDS | Q7: Education Support Annual FTE | R7: STATISTICS | S7: Z05 | T7: ZZZ | U7: COSTCTR | V7: TRUE | X7: TRUE | Y7: FALSE | Z7: =FALSE -> FALSE
A8: =IF(COUNTIF(LEDGER[LedgerCode],FC_import[[#This Row],[LedgerCode]])>0,0,1) -> 0 | B8: =IF(COUNTIF(Table_System_Grouping_Codes[groupingCodeCode],FC_import[[#This Row],[GroupingCode]])>0,0,1) -> 0 | C8: =IF(COUNTIF(CUSTGROUP[CustomGroupingCode],FC_import[[#This Row],[CustomGrouping]])>0,0,1) -> 0 | D8: {=IF(FC_import[[#This Row],[AvailableToAllSchools]]=TRUE,0,COUNTA(_xlfn.TEXTSPLIT(FC_import[[#This Row],[SchoolCodes]],",",,TRUE))-SUM(COUNTIF(SCHOOLS[SchoolCode],_xlfn.TEXTSPLIT(FC_import[[#This Row],[SchoolCodes]],",",,TRUE))))} -> 0 | E8: =IF(FC_import[[#This Row],[FinanceCodeTypeCode]]="BUDGET",0,COUNTIF(P:P,P8)-1) -> 0 | F8: =IF(FC_import[[#This Row],[FinanceCodeTypeCode]]="BUDGET",0,COUNTIF(Q:Q,Q8)-1) -> 0 | G8: =COUNTIF(Lookup!$A$2:$A$7,R8)-1 -> 0 | H8: =IF(OR(FC_import[[#This Row],[FinanceCodeEnabled]]=TRUE,FC_import[[#This Row],[FinanceCodeEnabled]]=FALSE),0,1) -> 0 | I8: =IF(LEN(FC_import[[#This Row],[FinanceCode]])<100,0,1) -> 0 | J8: =IF(TRIM(FC_import[[#This Row],[Title]])="",1,0) -> 0 | K8: =IF(TRIM(FC_import[[#This Row],[FinanceCode]])="",1,0) -> 0 | L8: =IF(LEN(FC_import[[#This Row],[Title]])<100,0,1) -> 0 | M8: =IF(ISBLANK(FC_import[[#This Row],[BalanceToScenario]]),1,0) -> 0 | N8: =IF(SUBSTITUTE(TEXT(FC_import[[#This Row],[FinanceCode]],10)," ","")=TEXT(FC_import[[#This Row],[FinanceCode]],10),0,1) -> 0 | O8: =SUM(A8:C8,E8:N8) -> 0 | P8: A_FTE_ESTF | Q8: External Staff Annual FTE | R8: STATISTICS | S8: ZZZ | T8: ZZZ | U8: COSTCTR | V8: TRUE | X8: TRUE | Y8: FALSE | Z8: =FALSE -> FALSE
A9: =IF(COUNTIF(LEDGER[LedgerCode],FC_import[[#This Row],[LedgerCode]])>0,0,1) -> 0 | B9: =IF(COUNTIF(Table_System_Grouping_Codes[groupingCodeCode],FC_import[[#This Row],[GroupingCode]])>0,0,1) -> 0 | C9: =IF(COUNTIF(CUSTGROUP[CustomGroupingCode],FC_import[[#This Row],[CustomGrouping]])>0,0,1) -> 0 | D9: {=IF(FC_import[[#This Row],[AvailableToAllSchools]]=TRUE,0,COUNTA(_xlfn.TEXTSPLIT(FC_import[[#This Row],[SchoolCodes]],",",,TRUE))-SUM(COUNTIF(SCHOOLS[SchoolCode],_xlfn.TEXTSPLIT(FC_import[[#This Row],[SchoolCodes]],",",,TRUE))))} -> 0 | E9: =IF(FC_import[[#This Row],[FinanceCodeTypeCode]]="BUDGET",0,COUNTIF(P:P,P9)-1) -> 0 | F9: =IF(FC_import[[#This Row],[FinanceCodeTypeCode]]="BUDGET",0,COUNTIF(Q:Q,Q9)-1) -> 0 | G9: =COUNTIF(Lookup!$A$2:$A$7,R9)-1 -> 0 | H9: =IF(OR(FC_import[[#This Row],[FinanceCodeEnabled]]=TRUE,FC_import[[#This Row],[FinanceCodeEnabled]]=FALSE),0,1) -> 0 | I9: =IF(LEN(FC_import[[#This Row],[FinanceCode]])<100,0,1) -> 0 | J9: =IF(TRIM(FC_import[[#This Row],[Title]])="",1,0) -> 0 | K9: =IF(TRIM(FC_import[[#This Row],[FinanceCode]])="",1,0) -> 0 | L9: =IF(LEN(FC_import[[#This Row],[Title]])<100,0,1) -> 0 | M9: =IF(ISBLANK(FC_import[[#This Row],[BalanceToScenario]]),1,0) -> 0 | N9: =IF(SUBSTITUTE(TEXT(FC_import[[#This Row],[FinanceCode]],10)," ","")=TEXT(FC_import[[#This Row],[FinanceCode]],10),0,1) -> 0 | O9: =SUM(A9:C9,E9:N9) -> 0 | P9: A_FTE_EXT | Q9: Extended Schools Annual FTE | R9: STATISTICS | S9: Z05 | T9: ZZZ | U9: COSTCTR | V9: TRUE | X9: TRUE | Y9: FALSE | Z9: =FALSE -> FALSE
A10: =IF(COUNTIF(LEDGER[LedgerCode],FC_import[[#This Row],[LedgerCode]])>0,0,1) -> 0 | B10: =IF(COUNTIF(Table_System_Grouping_Codes[groupingCodeCode],FC_import[[#This Row],[GroupingCode]])>0,0,1) -> 0 | C10: =IF(COUNTIF(CUSTGROUP[CustomGroupingCode],FC_import[[#This Row],[CustomGrouping]])>0,0,1) -> 0 | D10: {=IF(FC_import[[#This Row],[AvailableToAllSchools]]=TRUE,0,COUNTA(_xlfn.TEXTSPLIT(FC_import[[#This Row],[SchoolCodes]],",",,TRUE))-SUM(COUNTIF(SCHOOLS[SchoolCode],_xlfn.TEXTSPLIT(FC_import[[#This Row],[SchoolCodes]],",",,TRUE))))} -> 0 | E10: =IF(FC_import[[#This Row],[FinanceCodeTypeCode]]="BUDGET",0,COUNTIF(P:P,P10)-1) -> 0 | F10: =IF(FC_import[[#This Row],[FinanceCodeTypeCode]]="BUDGET",0,COUNTIF(Q:Q,Q10)-1) -> 0 | G10: =COUNTIF(Lookup!$A$2:$A$7,R10)-1 -> 0 | H10: =IF(OR(FC_import[[#This Row],[FinanceCodeEnabled]]=TRUE,FC_import[[#This Row],[FinanceCodeEnabled]]=FALSE),0,1) -> 0 | I10: =IF(LEN(FC_import[[#This Row],[FinanceCode]])<100,0,1) -> 0 | J10: =IF(TRIM(FC_import[[#This Row],[Title]])="",1,0) -> 0 | K10: =IF(TRIM(FC_import[[#This Row],[FinanceCode]])="",1,0) -> 0 | L10: =IF(LEN(FC_import[[#This Row],[Title]])<100,0,1) -> 0 | M10: =IF(ISBLANK(FC_import[[#This Row],[BalanceToScenario]]),1,0) -> 0 | N10: =IF(SUBSTITUTE(TEXT(FC_import[[#This Row],[FinanceCode]],10)," ","")=TEXT(FC_import[[#This Row],[FinanceCode]],10),0,1) -> 0 | O10: =SUM(A10:C10,E10:N10) -> 0 | P10: A_FTE_FLA | Q10: FLA Annual FTE | R10: STATISTICS | S10: Z05 | T10: ZZZ | U10: COSTCTR | V10: TRUE | X10: TRUE | Y10: FALSE | Z10: =FALSE -> FALSE
A11: =IF(COUNTIF(LEDGER[LedgerCode],FC_import[[#This Row],[LedgerCode]])>0,0,1) -> 0 | B11: =IF(COUNTIF(Table_System_Grouping_Codes[groupingCodeCode],FC_import[[#This Row],[GroupingCode]])>0,0,1) -> 0 | C11: =IF(COUNTIF(CUSTGROUP[CustomGroupingCode],FC_import[[#This Row],[CustomGrouping]])>0,0,1) -> 0 | D11: {=IF(FC_import[[#This Row],[AvailableToAllSchools]]=TRUE,0,COUNTA(_xlfn.TEXTSPLIT(FC_import[[#This Row],[SchoolCodes]],",",,TRUE))-SUM(COUNTIF(SCHOOLS[SchoolCode],_xlfn.TEXTSPLIT(FC_import[[#This Row],[SchoolCodes]],",",,TRUE))))} -> 0 | E11: =IF(FC_import[[#This Row],[FinanceCodeTypeCode]]="BUDGET",0,COUNTIF(P:P,P11)-1) -> 0 | F11: =IF(FC_import[[#This Row],[FinanceCodeTypeCode]]="BUDGET",0,COUNTIF(Q:Q,Q11)-1) -> 0 | G11: =COUNTIF(Lookup!$A$2:$A$7,R11)-1 -> 0 | H11: =IF(OR(FC_import[[#This Row],[FinanceCodeEnabled]]=TRUE,FC_import[[#This Row],[FinanceCodeEnabled]]=FALSE),0,1) -> 0 | I11: =IF(LEN(FC_import[[#This Row],[FinanceCode]])<100,0,1) -> 0 | J11: =IF(TRIM(FC_import[[#This Row],[Title]])="",1,0) -> 0 | K11: =IF(TRIM(FC_import[[#This Row],[FinanceCode]])="",1,0) -> 0 | L11: =IF(LEN(FC_import[[#This Row],[Title]])<100,0,1) -> 0 | M11: =IF(ISBLANK(FC_import[[#This Row],[BalanceToScenario]]),1,0) -> 0 | N11: =IF(SUBSTITUTE(TEXT(FC_import[[#This Row],[FinanceCode]],10)," ","")=TEXT(FC_import[[#This Row],[FinanceCode]],10),0,1) -> 0 | O11: =SUM(A11:C11,E11:N11) -> 0 | P11: A_FTE_FSW | Q11: Family Support Annual FTE | R11: STATISTICS | S11: Z05 | T11: ZZZ | U11: COSTCTR | V11: TRUE | X11: TRUE | Y11: FALSE | Z11: =FALSE -> FALSE
A12: =IF(COUNTIF(LEDGER[LedgerCode],FC_import[[#This Row],[LedgerCode]])>0,0,1) -> 0 | B12: =IF(COUNTIF(Table_System_Grouping_Codes[groupingCodeCode],FC_import[[#This Row],[GroupingCode]])>0,0,1) -> 0 | C12: =IF(COUNTIF(CUSTGROUP[CustomGroupingCode],FC_import[[#This Row],[CustomGrouping]])>0,0,1) -> 0 | D12: {=IF(FC_import[[#This Row],[AvailableToAllSchools]]=TRUE,0,COUNTA(_xlfn.TEXTSPLIT(FC_import[[#This Row],[SchoolCodes]],",",,TRUE))-SUM(COUNTIF(SCHOOLS[SchoolCode],_xlfn.TEXTSPLIT(FC_import[[#This Row],[SchoolCodes]],",",,TRUE))))} -> 0 | E12: =IF(FC_import[[#This Row],[FinanceCodeTypeCode]]="BUDGET",0,COUNTIF(P:P,P12)-1) -> 0 | F12: =IF(FC_import[[#This Row],[FinanceCodeTypeCode]]="BUDGET",0,COUNTIF(Q:Q,Q12)-1) -> 0 | G12: =COUNTIF(Lookup!$A$2:$A$7,R12)-1 -> 0 | H12: =IF(OR(FC_import[[#This Row],[FinanceCodeEnabled]]=TRUE,FC_import[[#This Row],[FinanceCodeEnabled]]=FALSE),0,1) -> 0 | I12: =IF(LEN(FC_import[[#This Row],[FinanceCode]])<100,0,1) -> 0 | J12: =IF(TRIM(FC_import[[#This Row],[Title]])="",1,0) -> 0 | K12: =IF(TRIM(FC_import[[#This Row],[FinanceCode]])="",1,0) -> 0 | L12: =IF(LEN(FC_import[[#This Row],[Title]])<100,0,1) -> 0 | M12: =IF(ISBLANK(FC_import[[#This Row],[BalanceToScenario]]),1,0) -> 0 | N12: =IF(SUBSTITUTE(TEXT(FC_import[[#This Row],[FinanceCode]],10)," ","")=TEXT(FC_import[[#This Row],[FinanceCode]],10),0,1) -> 0 | O12: =SUM(A12:C12,E12:N12) -> 0 | P12: A_FTE_INV | Q12: Invigilator Annual FTE | R12: STATISTICS | S12: Z05 | T12: ZZZ | U12: COSTCTR | V12: TRUE | X12: TRUE | Y12: FALSE | Z12: =FALSE -> FALSE
A13: =IF(COUNTIF(LEDGER[LedgerCode],FC_import[[#This Row],[LedgerCode]])>0,0,1) -> 0 | B13: =IF(COUNTIF(Table_System_Grouping_Codes[groupingCodeCode],FC_import[[#This Row],[GroupingCode]])>0,0,1) -> 0 | C13: =IF(COUNTIF(CUSTGROUP[CustomGroupingCode],FC_import[[#This Row],[CustomGrouping]])>0,0,1) -> 0 | D13: {=IF(FC_import[[#This Row],[AvailableToAllSchools]]=TRUE,0,COUNTA(_xlfn.TEXTSPLIT(FC_import[[#This Row],[SchoolCodes]],",",,TRUE))-SUM(COUNTIF(SCHOOLS[SchoolCode],_xlfn.TEXTSPLIT(FC_import[[#This Row],[SchoolCodes]],",",,TRUE))))} -> 0 | E13: =IF(FC_import[[#This Row],[FinanceCodeTypeCode]]="BUDGET",0,COUNTIF(P:P,P13)-1) -> 0 | F13: =IF(FC_import[[#This Row],[FinanceCodeTypeCode]]="BUDGET",0,COUNTIF(Q:Q,Q13)-1) -> 0 | G13: =COUNTIF(Lookup!$A$2:$A$7,R13)-1 -> 0 | H13: =IF(OR(FC_import[[#This Row],[FinanceCodeEnabled]]=TRUE,FC_import[[#This Row],[FinanceCodeEnabled]]=FALSE),0,1) -> 0 | I13: =IF(LEN(FC_import[[#This Row],[FinanceCode]])<100,0,1) -> 0 | J13: =IF(TRIM(FC_import[[#This Row],[Title]])="",1,0) -> 0 | K13: =IF(TRIM(FC_import[[#This Row],[FinanceCode]])="",1,0) -> 0 | L13: =IF(LEN(FC_import[[#This Row],[Title]])<100,0,1) -> 0 | M13: =IF(ISBLANK(FC_import[[#This Row],[BalanceToScenario]]),1,0) -> 0 | N13: =IF(SUBSTITUTE(TEXT(FC_import[[#This Row],[FinanceCode]],10)," ","")=TEXT(FC_import[[#This Row],[FinanceCode]],10),0,1) -> 0 | O13: =SUM(A13:C13,E13:N13) -> 0 | P13: A_FTE_LEAVE_ADJ_ADM | Q13: Finance Admin Annual FTE Leave Adjustment | R13: STATISTICS | S13: Z17 | T13: ZZZ | U13: COSTCTR | V13: TRUE | X13: TRUE | Y13: FALSE | Z13: =FALSE -> FALSE
... A96: =IF(COUNTIF(LEDGER[LedgerCode],FC_import[[#This Row],[LedgerCode]])>0,0,1) -> 0 | B96: =IF(COUNTIF(Table_System_Grouping_Codes[groupingCodeCode],FC_import[[#This Row],[GroupingCode]])>0,0,1) -> 0 | C96: =IF(COUNTIF(CUSTGROUP[CustomGroupingCode],FC_import[[#This Row],[CustomGrouping]])>0,0,1) -> 0 | D96: {=IF(FC_import[[#This Row],[AvailableToAllSchools]]=TRUE,0,COUNTA(_xlfn.TEXTSPLIT(FC_import[[#This Row],[SchoolCodes]],",",,TRUE))-SUM(COUNTIF(SCHOOLS[SchoolCode],_xlfn.TEXTSPLIT(FC_import[[#This Row],[SchoolCodes]],",",,TRUE))))} -> 0 | E96: =IF(FC_import[[#This Row],[FinanceCodeTypeCode]]="BUDGET",0,COUNTIF(P:P,P96)-1) -> 0 | F96: =IF(FC_import[[#This Row],[FinanceCodeTypeCode]]="BUDGET",0,COUNTIF(Q:Q,Q96)-1) -> 0 | G96: =COUNTIF(Lookup!$A$2:$A$7,R96)-1 -> 0 | H96: =IF(OR(FC_import[[#This Row],[FinanceCodeEnabled]]=TRUE,FC_import[[#This Row],[FinanceCodeEnabled]]=FALSE),0,1) -> 0 | I96: =IF(LEN(FC_import[[#This Row],[FinanceCode]])<100,0,1) -> 0 | J96: =IF(TRIM(FC_import[[#This Row],[Title]])="",1,0) -> 0 | K96: =IF(TRIM(FC_import[[#This Row],[FinanceCode]])="",1,0) -> 0 | L96: =IF(LEN(FC_import[[#This Row],[Title]])<100,0,1) -> 0 | M96: =IF(ISBLANK(FC_import[[#This Row],[BalanceToScenario]]),1,0) -> 0 | N96: =IF(SUBSTITUTE(TEXT(FC_import[[#This Row],[FinanceCode]],10)," ","")=TEXT(FC_import[[#This Row],[FinanceCode]],10),0,1) -> 0 | O96: =SUM(A96:C96,E96:N96) -> 0 | P96: WK_FTE_TEC | Q96: Technicians Weekly FTE | R96: STATISTICS | S96: Z03 | T96: ZZZ | U96: COSTCTR | V96: TRUE | X96: TRUE | Y96: FALSE | Z96: =FALSE -> FALSE

Sheet FinanceCodes Budget
N1: API - Do not edit
A2: LedgerIssue | B2: GroupingCodeIssue | C2: CustGrIssue | D2: SchCodeIssue | E2: DupCode | F2: DupDesc | G2: FCTypeIss | H2: Blank Title Check | I2: Blank Code Check | J2: Code length Check | K2: Title length check | L2: Balance to Scenario Blank | M2: Will Import if 0 | N2: FinanceCode | O2: Title | P2: GroupingCode | Q2: CustomGrouping | R2: AvailableToAllSchools | S2: SchoolCodes | T2: FinanceCodeTypeCode | U2: LedgerCode | V2: FinanceCodeEnabled | W2: BalanceToScenario
A3: =IF(COUNTIF(LEDGER[LedgerCode],FinanceCodesBudget[[#This Row],[LedgerCode]])>0,0,1) -> 0 | B3: =IF(COUNTIF(Table_System_Grouping_Codes[groupingCodeCode],FinanceCodesBudget[[#This Row],[GroupingCode]])>0,0,1) -> 0 | C3: =IF(COUNTIF(CUSTGROUP[CustomGroupingCode],FinanceCodesBudget[[#This Row],[CustomGrouping]])>0,0,1) -> 0 | D3: {=IF(FinanceCodesBudget[[#This Row],[AvailableToAllSchools]]=TRUE,0,COUNTA(_xlfn.TEXTSPLIT(FinanceCodesBudget[[#This Row],[SchoolCodes]],",",,TRUE))-SUM(COUNTIF(SCHOOLS[SchoolCode],_xlfn.TEXTSPLIT(FinanceCodesBudget[[#This Row],[SchoolCodes]],",",,TRUE))))} -> 0 | E3: =IF(FinanceCodesBudget[[#This Row],[FinanceCodeTypeCode]]="BUDGET",0,COUNTIF(FinanceCodesBudget[FinanceCode],FinanceCodesBudget[[#This Row],[FinanceCode]])-1) -> 0 | F3: =IF(FinanceCodesBudget[[#This Row],[FinanceCodeTypeCode]]="BUDGET",0,COUNTIF(FinanceCodesBudget[Title],FinanceCodesBudget[[#This Row],[Title]])-1) -> 0 | G3: =COUNTIF(Lookup!$A$2:$A$7,FinanceCodesBudget[[#This Row],[FinanceCodeTypeCode]])-1 -> 0 | H3: =IF(TRIM(FinanceCodesBudget[[#This Row],[Title]])="",1,0) -> 0 | I3: =IF(TRIM(FinanceCodesBudget[[#This Row],[FinanceCode]])="",1,0) -> 0 | J3: =IF(LEN(FinanceCodesBudget[[#This Row],[FinanceCode]])<100,0,1) -> 0 | K3: =IF(LEN(FinanceCodesBudget[[#This Row],[Title]])<100,0,1) -> 0 | L3: =IF(ISBLANK(FinanceCodesBudget[[#This Row],[BalanceToScenario]]),1,0) -> 0 | M3: =SUM(FinanceCodesBudget[[#This Row],[LedgerIssue]:[CustGrIssue]],FinanceCodesBudget[[#This Row],[DupCode]:[Balance to Scenario Blank]]) -> 0 | N3: 510100 | O3: DfE Rev Grnts-GAG-not stud supp & trst | P3: 510100 | Q3: A0 | R3: FALSE | S3: ALS,AUD,BLS,HIG,MAT,MLB,PTP,SBL,WVP | T3: BUDGET | U3: COSTCTR | V3: TRUE | W3: FALSE
A4: =IF(COUNTIF(LEDGER[LedgerCode],FinanceCodesBudget[[#This Row],[LedgerCode]])>0,0,1) -> 0 | B4: =IF(COUNTIF(Table_System_Grouping_Codes[groupingCodeCode],FinanceCodesBudget[[#This Row],[GroupingCode]])>0,0,1) -> 0 | C4: =IF(COUNTIF(CUSTGROUP[CustomGroupingCode],FinanceCodesBudget[[#This Row],[CustomGrouping]])>0,0,1) -> 0 | D4: {=IF(FinanceCodesBudget[[#This Row],[AvailableToAllSchools]]=TRUE,0,COUNTA(_xlfn.TEXTSPLIT(FinanceCodesBudget[[#This Row],[SchoolCodes]],",",,TRUE))-SUM(COUNTIF(SCHOOLS[SchoolCode],_xlfn.TEXTSPLIT(FinanceCodesBudget[[#This Row],[SchoolCodes]],",",,TRUE))))} -> 0 | E4: =IF(FinanceCodesBudget[[#This Row],[FinanceCodeTypeCode]]="BUDGET",0,COUNTIF(FinanceCodesBudget[FinanceCode],FinanceCodesBudget[[#This Row],[FinanceCode]])-1) -> 0 | F4: =IF(FinanceCodesBudget[[#This Row],[FinanceCodeTypeCode]]="BUDGET",0,COUNTIF(FinanceCodesBudget[Title],FinanceCodesBudget[[#This Row],[Title]])-1) -> 0 | G4: =COUNTIF(Lookup!$A$2:$A$7,FinanceCodesBudget[[#This Row],[FinanceCodeTypeCode]])-1 -> 0 | H4: =IF(TRIM(FinanceCodesBudget[[#This Row],[Title]])="",1,0) -> 0 | I4: =IF(TRIM(FinanceCodesBudget[[#This Row],[FinanceCode]])="",1,0) -> 0 | J4: =IF(LEN(FinanceCodesBudget[[#This Row],[FinanceCode]])<100,0,1) -> 0 | K4: =IF(LEN(FinanceCodesBudget[[#This Row],[Title]])<100,0,1) -> 0 | L4: =IF(ISBLANK(FinanceCodesBudget[[#This Row],[BalanceToScenario]]),1,0) -> 0 | M4: =SUM(FinanceCodesBudget[[#This Row],[LedgerIssue]:[CustGrIssue]],FinanceCodesBudget[[#This Row],[DupCode]:[Balance to Scenario Blank]]) -> 0 | N4: 510110 | O4: DfE Rev Grnts-GAG-student support | P4: 510110 | Q4: A0 | R4: FALSE | S4: ALS,AUD,BLS,HIG,MAT,MLB,PTP,SBL,WVP | T4: BUDGET | U4: COSTCTR | V4: TRUE | W4: FALSE
A5: =IF(COUNTIF(LEDGER[LedgerCode],FinanceCodesBudget[[#This Row],[LedgerCode]])>0,0,1) -> 0 | B5: =IF(COUNTIF(Table_System_Grouping_Codes[groupingCodeCode],FinanceCodesBudget[[#This Row],[GroupingCode]])>0,0,1) -> 0 | C5: =IF(COUNTIF(CUSTGROUP[CustomGroupingCode],FinanceCodesBudget[[#This Row],[CustomGrouping]])>0,0,1) -> 0 | D5: {=IF(FinanceCodesBudget[[#This Row],[AvailableToAllSchools]]=TRUE,0,COUNTA(_xlfn.TEXTSPLIT(FinanceCodesBudget[[#This Row],[SchoolCodes]],",",,TRUE))-SUM(COUNTIF(SCHOOLS[SchoolCode],_xlfn.TEXTSPLIT(FinanceCodesBudget[[#This Row],[SchoolCodes]],",",,TRUE))))} -> 0 | E5: =IF(FinanceCodesBudget[[#This Row],[FinanceCodeTypeCode]]="BUDGET",0,COUNTIF(FinanceCodesBudget[FinanceCode],FinanceCodesBudget[[#This Row],[FinanceCode]])-1) -> 0 | F5: =IF(FinanceCodesBudget[[#This Row],[FinanceCodeTypeCode]]="BUDGET",0,COUNTIF(FinanceCodesBudget[Title],FinanceCodesBudget[[#This Row],[Title]])-1) -> 0 | G5: =COUNTIF(Lookup!$A$2:$A$7,FinanceCodesBudget[[#This Row],[FinanceCodeTypeCode]])-1 -> 0 | H5: =IF(TRIM(FinanceCodesBudget[[#This Row],[Title]])="",1,0) -> 0 | I5: =IF(TRIM(FinanceCodesBudget[[#This Row],[FinanceCode]])="",1,0) -> 0 | J5: =IF(LEN(FinanceCodesBudget[[#This Row],[FinanceCode]])<100,0,1) -> 0 | K5: =IF(LEN(FinanceCodesBudget[[#This Row],[Title]])<100,0,1) -> 0 | L5: =IF(ISBLANK(FinanceCodesBudget[[#This Row],[BalanceToScenario]]),1,0) -> 0 | M5: =SUM(FinanceCodesBudget[[#This Row],[LedgerIssue]:[CustGrIssue]],FinanceCodesBudget[[#This Row],[DupCode]:[Balance to Scenario Blank]]) -> 0 | N5: 510120 | O5: DfE Rev Grnts-GAG-start up grants | P5: 510120 | Q5: A0 | R5: FALSE | S5: ALS,AUD,BLS,HIG,MAT,MLB,PTP,SBL,WVP | T5: BUDGET | U5: COSTCTR | V5: TRUE | W5: FALSE
A6: =IF(COUNTIF(LEDGER[LedgerCode],FinanceCodesBudget[[#This Row],[LedgerCode]])>0,0,1) -> 0 | B6: =IF(COUNTIF(Table_System_Grouping_Codes[groupingCodeCode],FinanceCodesBudget[[#This Row],[GroupingCode]])>0,0,1) -> 0 | C6: =IF(COUNTIF(CUSTGROUP[CustomGroupingCode],FinanceCodesBudget[[#This Row],[CustomGrouping]])>0,0,1) -> 0 | D6: {=IF(FinanceCodesBudget[[#This Row],[AvailableToAllSchools]]=TRUE,0,COUNTA(_xlfn.TEXTSPLIT(FinanceCodesBudget[[#This Row],[SchoolCodes]],",",,TRUE))-SUM(COUNTIF(SCHOOLS[SchoolCode],_xlfn.TEXTSPLIT(FinanceCodesBudget[[#This Row],[SchoolCodes]],",",,TRUE))))} -> 0 | E6: =IF(FinanceCodesBudget[[#This Row],[FinanceCodeTypeCode]]="BUDGET",0,COUNTIF(FinanceCodesBudget[FinanceCode],FinanceCodesBudget[[#This Row],[FinanceCode]])-1) -> 0 | F6: =IF(FinanceCodesBudget[[#This Row],[FinanceCodeTypeCode]]="BUDGET",0,COUNTIF(FinanceCodesBudget[Title],FinanceCodesBudget[[#This Row],[Title]])-1) -> 0 | G6: =COUNTIF(Lookup!$A$2:$A$7,FinanceCodesBudget[[#This Row],[FinanceCodeTypeCode]])-1 -> 0 | H6: =IF(TRIM(FinanceCodesBudget[[#This Row],[Title]])="",1,0) -> 0 | I6: =IF(TRIM(FinanceCodesBudget[[#This Row],[FinanceCode]])="",1,0) -> 0 | J6: =IF(LEN(FinanceCodesBudget[[#This Row],[FinanceCode]])<100,0,1) -> 0 | K6: =IF(LEN(FinanceCodesBudget[[#This Row],[Title]])<100,0,1) -> 0 | L6: =IF(ISBLANK(FinanceCodesBudget[[#This Row],[BalanceToScenario]]),1,0) -> 0 | M6: =SUM(FinanceCodesBudget[[#This Row],[LedgerIssue]:[CustGrIssue]],FinanceCodesBudget[[#This Row],[DupCode]:[Balance to Scenario Blank]]) -> 0 | N6: 510130 | O6: DfE Rev Grnts-Trust level grants | P6: 510130 | Q6: A1 | R6: FALSE | S6: ALS,AUD,BLS,HIG,MAT,MLB,PTP,SBL,WVP | T6: BUDGET | U6: COSTCTR | V6: TRUE | W6: FALSE
A7: =IF(COUNTIF(LEDGER[LedgerCode],FinanceCodesBudget[[#This Row],[LedgerCode]])>0,0,1) -> 0 | B7: =IF(COUNTIF(Table_System_Grouping_Codes[groupingCodeCode],FinanceCodesBudget[[#This Row],[GroupingCode]])>0,0,1) -> 0 | C7: =IF(COUNTIF(CUSTGROUP[CustomGroupingCode],FinanceCodesBudget[[#This Row],[CustomGrouping]])>0,0,1) -> 0 | D7: {=IF(FinanceCodesBudget[[#This Row],[AvailableToAllSchools]]=TRUE,0,COUNTA(_xlfn.TEXTSPLIT(FinanceCodesBudget[[#This Row],[SchoolCodes]],",",,TRUE))-SUM(COUNTIF(SCHOOLS[SchoolCode],_xlfn.TEXTSPLIT(FinanceCodesBudget[[#This Row],[SchoolCodes]],",",,TRUE))))} -> 0 | E7: =IF(FinanceCodesBudget[[#This Row],[FinanceCodeTypeCode]]="BUDGET",0,COUNTIF(FinanceCodesBudget[FinanceCode],FinanceCodesBudget[[#This Row],[FinanceCode]])-1) -> 0 | F7: =IF(FinanceCodesBudget[[#This Row],[FinanceCodeTypeCode]]="BUDGET",0,COUNTIF(FinanceCodesBudget[Title],FinanceCodesBudget[[#This Row],[Title]])-1) -> 0 | G7: =COUNTIF(Lookup!$A$2:$A$7,FinanceCodesBudget[[#This Row],[FinanceCodeTypeCode]])-1 -> 0 | H7: =IF(TRIM(FinanceCodesBudget[[#This Row],[Title]])="",1,0) -> 0 | I7: =IF(TRIM(FinanceCodesBudget[[#This Row],[FinanceCode]])="",1,0) -> 0 | J7: =IF(LEN(FinanceCodesBudget[[#This Row],[FinanceCode]])<100,0,1) -> 0 | K7: =IF(LEN(FinanceCodesBudget[[#This Row],[Title]])<100,0,1) -> 0 | L7: =IF(ISBLANK(FinanceCodesBudget[[#This Row],[BalanceToScenario]]),1,0) -> 0 | M7: =SUM(FinanceCodesBudget[[#This Row],[LedgerIssue]:[CustGrIssue]],FinanceCodesBudget[[#This Row],[DupCode]:[Balance to Scenario Blank]]) -> 0 | N7: 510140 | O7: DfE Rev Grnts-Pupil number adjustment | P7: 510140 | Q7: A1 | R7: FALSE | S7: ALS,AUD,BLS,HIG,MAT,MLB,PTP,SBL,WVP | T7: BUDGET | U7: COSTCTR | V7: TRUE | W7: FALSE
A8: =IF(COUNTIF(LEDGER[LedgerCode],FinanceCodesBudget[[#This Row],[LedgerCode]])>0,0,1) -> 0 | B8: =IF(COUNTIF(Table_System_Grouping_Codes[groupingCodeCode],FinanceCodesBudget[[#This Row],[GroupingCode]])>0,0,1) -> 0 | C8: =IF(COUNTIF(CUSTGROUP[CustomGroupingCode],FinanceCodesBudget[[#This Row],[CustomGrouping]])>0,0,1) -> 0 | D8: {=IF(FinanceCodesBudget[[#This Row],[AvailableToAllSchools]]=TRUE,0,COUNTA(_xlfn.TEXTSPLIT(FinanceCodesBudget[[#This Row],[SchoolCodes]],",",,TRUE))-SUM(COUNTIF(SCHOOLS[SchoolCode],_xlfn.TEXTSPLIT(FinanceCodesBudget[[#This Row],[SchoolCodes]],",",,TRUE))))} -> 0 | E8: =IF(FinanceCodesBudget[[#This Row],[FinanceCodeTypeCode]]="BUDGET",0,COUNTIF(FinanceCodesBudget[FinanceCode],FinanceCodesBudget[[#This Row],[FinanceCode]])-1) -> 0 | F8: =IF(FinanceCodesBudget[[#This Row],[FinanceCodeTypeCode]]="BUDGET",0,COUNTIF(FinanceCodesBudget[Title],FinanceCodesBudget[[#This Row],[Title]])-1) -> 0 | G8: =COUNTIF(Lookup!$A$2:$A$7,FinanceCodesBudget[[#This Row],[FinanceCodeTypeCode]])-1 -> 0 | H8: =IF(TRIM(FinanceCodesBudget[[#This Row],[Title]])="",1,0) -> 0 | I8: =IF(TRIM(FinanceCodesBudget[[#This Row],[FinanceCode]])="",1,0) -> 0 | J8: =IF(LEN(FinanceCodesBudget[[#This Row],[FinanceCode]])<100,0,1) -> 0 | K8: =IF(LEN(FinanceCodesBudget[[#This Row],[Title]])<100,0,1) -> 0 | L8: =IF(ISBLANK(FinanceCodesBudget[[#This Row],[BalanceToScenario]]),1,0) -> 0 | M8: =SUM(FinanceCodesBudget[[#This Row],[LedgerIssue]:[CustGrIssue]],FinanceCodesBudget[[#This Row],[DupCode]:[Balance to Scenario Blank]]) -> 0 | N8: 510150 | O8: DfE Rev Grnts-Rates reclaim | P8: 510150 | Q8: A1 | R8: FALSE | S8: ALS,AUD,BLS,HIG,MAT,MLB,PTP,SBL,WVP | T8: BUDGET | U8: COSTCTR | V8: TRUE | W8: FALSE
A9: =IF(COUNTIF(LEDGER[LedgerCode],FinanceCodesBudget[[#This Row],[LedgerCode]])>0,0,1) -> 0 | B9: =IF(COUNTIF(Table_System_Grouping_Codes[groupingCodeCode],FinanceCodesBudget[[#This Row],[GroupingCode]])>0,0,1) -> 0 | C9: =IF(COUNTIF(CUSTGROUP[CustomGroupingCode],FinanceCodesBudget[[#This Row],[CustomGrouping]])>0,0,1) -> 0 | D9: {=IF(FinanceCodesBudget[[#This Row],[AvailableToAllSchools]]=TRUE,0,COUNTA(_xlfn.TEXTSPLIT(FinanceCodesBudget[[#This Row],[SchoolCodes]],",",,TRUE))-SUM(COUNTIF(SCHOOLS[SchoolCode],_xlfn.TEXTSPLIT(FinanceCodesBudget[[#This Row],[SchoolCodes]],",",,TRUE))))} -> 0 | E9: =IF(FinanceCodesBudget[[#This Row],[FinanceCodeTypeCode]]="BUDGET",0,COUNTIF(FinanceCodesBudget[FinanceCode],FinanceCodesBudget[[#This Row],[FinanceCode]])-1) -> 0 | F9: =IF(FinanceCodesBudget[[#This Row],[FinanceCodeTypeCode]]="BUDGET",0,COUNTIF(FinanceCodesBudget[Title],FinanceCodesBudget[[#This Row],[Title]])-1) -> 0 | G9: =COUNTIF(Lookup!$A$2:$A$7,FinanceCodesBudget[[#This Row],[FinanceCodeTypeCode]])-1 -> 0 | H9: =IF(TRIM(FinanceCodesBudget[[#This Row],[Title]])="",1,0) -> 0 | I9: =IF(TRIM(FinanceCodesBudget[[#This Row],[FinanceCode]])="",1,0) -> 0 | J9: =IF(LEN(FinanceCodesBudget[[#This Row],[FinanceCode]])<100,0,1) -> 0 | K9: =IF(LEN(FinanceCodesBudget[[#This Row],[Title]])<100,0,1) -> 0 | L9: =IF(ISBLANK(FinanceCodesBudget[[#This Row],[BalanceToScenario]]),1,0) -> 0 | M9: =SUM(FinanceCodesBudget[[#This Row],[LedgerIssue]:[CustGrIssue]],FinanceCodesBudget[[#This Row],[DupCode]:[Balance to Scenario Blank]]) -> 0 | N9: 510200 | O9: DfE Rev Grnts-Pupil Premium | P9: 510200 | Q9: A0 | R9: FALSE | S9: ALS,AUD,BLS,HIG,MAT,MLB,PTP,SBL,WVP | T9: BUDGET | U9: COSTCTR | V9: TRUE | W9: FALSE
A10: =IF(COUNTIF(LEDGER[LedgerCode],FinanceCodesBudget[[#This Row],[LedgerCode]])>0,0,1) -> 0 | B10: =IF(COUNTIF(Table_System_Grouping_Codes[groupingCodeCode],FinanceCodesBudget[[#This Row],[GroupingCode]])>0,0,1) -> 0 | C10: =IF(COUNTIF(CUSTGROUP[CustomGroupingCode],FinanceCodesBudget[[#This Row],[CustomGrouping]])>0,0,1) -> 0 | D10: {=IF(FinanceCodesBudget[[#This Row],[AvailableToAllSchools]]=TRUE,0,COUNTA(_xlfn.TEXTSPLIT(FinanceCodesBudget[[#This Row],[SchoolCodes]],",",,TRUE))-SUM(COUNTIF(SCHOOLS[SchoolCode],_xlfn.TEXTSPLIT(FinanceCodesBudget[[#This Row],[SchoolCodes]],",",,TRUE))))} -> 0 | E10: =IF(FinanceCodesBudget[[#This Row],[FinanceCodeTypeCode]]="BUDGET",0,COUNTIF(FinanceCodesBudget[FinanceCode],FinanceCodesBudget[[#This Row],[FinanceCode]])-1) -> 0 | F10: =IF(FinanceCodesBudget[[#This Row],[FinanceCodeTypeCode]]="BUDGET",0,COUNTIF(FinanceCodesBudget[Title],FinanceCodesBudget[[#This Row],[Title]])-1) -> 0 | G10: =COUNTIF(Lookup!$A$2:$A$7,FinanceCodesBudget[[#This Row],[FinanceCodeTypeCode]])-1 -> 0 | H10: =IF(TRIM(FinanceCodesBudget[[#This Row],[Title]])="",1,0) -> 0 | I10: =IF(TRIM(FinanceCodesBudget[[#This Row],[FinanceCode]])="",1,0) -> 0 | J10: =IF(LEN(FinanceCodesBudget[[#This Row],[FinanceCode]])<100,0,1) -> 0 | K10: =IF(LEN(FinanceCodesBudget[[#This Row],[Title]])<100,0,1) -> 0 | L10: =IF(ISBLANK(FinanceCodesBudget[[#This Row],[BalanceToScenario]]),1,0) -> 0 | M10: =SUM(FinanceCodesBudget[[#This Row],[LedgerIssue]:[CustGrIssue]],FinanceCodesBudget[[#This Row],[DupCode]:[Balance to Scenario Blank]]) -> 0 | N10: 510250 | O10: DfE Rev Grnts-Univ'l Inf Free Schl Meals | P10: 510250 | Q10: A1 | R10: FALSE | S10: ALS,AUD,BLS,HIG,MAT,MLB,PTP,SBL,WVP | T10: BUDGET | U10: COSTCTR | V10: TRUE | W10: FALSE
A11: =IF(COUNTIF(LEDGER[LedgerCode],FinanceCodesBudget[[#This Row],[LedgerCode]])>0,0,1) -> 0 | B11: =IF(COUNTIF(Table_System_Grouping_Codes[groupingCodeCode],FinanceCodesBudget[[#This Row],[GroupingCode]])>0,0,1) -> 0 | C11: =IF(COUNTIF(CUSTGROUP[CustomGroupingCode],FinanceCodesBudget[[#This Row],[CustomGrouping]])>0,0,1) -> 0 | D11: {=IF(FinanceCodesBudget[[#This Row],[AvailableToAllSchools]]=TRUE,0,COUNTA(_xlfn.TEXTSPLIT(FinanceCodesBudget[[#This Row],[SchoolCodes]],",",,TRUE))-SUM(COUNTIF(SCHOOLS[SchoolCode],_xlfn.TEXTSPLIT(FinanceCodesBudget[[#This Row],[SchoolCodes]],",",,TRUE))))} -> 0 | E11: =IF(FinanceCodesBudget[[#This Row],[FinanceCodeTypeCode]]="BUDGET",0,COUNTIF(FinanceCodesBudget[FinanceCode],FinanceCodesBudget[[#This Row],[FinanceCode]])-1) -> 0 | F11: =IF(FinanceCodesBudget[[#This Row],[FinanceCodeTypeCode]]="BUDGET",0,COUNTIF(FinanceCodesBudget[Title],FinanceCodesBudget[[#This Row],[Title]])-1) -> 0 | G11: =COUNTIF(Lookup!$A$2:$A$7,FinanceCodesBudget[[#This Row],[FinanceCodeTypeCode]])-1 -> 0 | H11: =IF(TRIM(FinanceCodesBudget[[#This Row],[Title]])="",1,0) -> 0 | I11: =IF(TRIM(FinanceCodesBudget[[#This Row],[FinanceCode]])="",1,0) -> 0 | J11: =IF(LEN(FinanceCodesBudget[[#This Row],[FinanceCode]])<100,0,1) -> 0 | K11: =IF(LEN(FinanceCodesBudget[[#This Row],[Title]])<100,0,1) -> 0 | L11: =IF(ISBLANK(FinanceCodesBudget[[#This Row],[BalanceToScenario]]),1,0) -> 0 | M11: =SUM(FinanceCodesBudget[[#This Row],[LedgerIssue]:[CustGrIssue]],FinanceCodesBudget[[#This Row],[DupCode]:[Balance to Scenario Blank]]) -> 0 | N11: 510300 | O11: DfE Rev Grnts-Insurance top up | P11: 510300 | Q11: A1 | R11: FALSE | S11: ALS,AUD,BLS,HIG,MAT,MLB,PTP,SBL,WVP | T11: BUDGET | U11: COSTCTR | V11: TRUE | W11: FALSE
A12: =IF(COUNTIF(LEDGER[LedgerCode],FinanceCodesBudget[[#This Row],[LedgerCode]])>0,0,1) -> 0 | B12: =IF(COUNTIF(Table_System_Grouping_Codes[groupingCodeCode],FinanceCodesBudget[[#This Row],[GroupingCode]])>0,0,1) -> 0 | C12: =IF(COUNTIF(CUSTGROUP[CustomGroupingCode],FinanceCodesBudget[[#This Row],[CustomGrouping]])>0,0,1) -> 0 | D12: {=IF(FinanceCodesBudget[[#This Row],[AvailableToAllSchools]]=TRUE,0,COUNTA(_xlfn.TEXTSPLIT(FinanceCodesBudget[[#This Row],[SchoolCodes]],",",,TRUE))-SUM(COUNTIF(SCHOOLS[SchoolCode],_xlfn.TEXTSPLIT(FinanceCodesBudget[[#This Row],[SchoolCodes]],",",,TRUE))))} -> 0 | E12: =IF(FinanceCodesBudget[[#This Row],[FinanceCodeTypeCode]]="BUDGET",0,COUNTIF(FinanceCodesBudget[FinanceCode],FinanceCodesBudget[[#This Row],[FinanceCode]])-1) -> 0 | F12: =IF(FinanceCodesBudget[[#This Row],[FinanceCodeTypeCode]]="BUDGET",0,COUNTIF(FinanceCodesBudget[Title],FinanceCodesBudget[[#This Row],[Title]])-1) -> 0 | G12: =COUNTIF(Lookup!$A$2:$A$7,FinanceCodesBudget[[#This Row],[FinanceCodeTypeCode]])-1 -> 0 | H12: =IF(TRIM(FinanceCodesBudget[[#This Row],[Title]])="",1,0) -> 0 | I12: =IF(TRIM(FinanceCodesBudget[[#This Row],[FinanceCode]])="",1,0) -> 0 | J12: =IF(LEN(FinanceCodesBudget[[#This Row],[FinanceCode]])<100,0,1) -> 0 | K12: =IF(LEN(FinanceCodesBudget[[#This Row],[Title]])<100,0,1) -> 0 | L12: =IF(ISBLANK(FinanceCodesBudget[[#This Row],[BalanceToScenario]]),1,0) -> 0 | M12: =SUM(FinanceCodesBudget[[#This Row],[LedgerIssue]:[CustGrIssue]],FinanceCodesBudget[[#This Row],[DupCode]:[Balance to Scenario Blank]]) -> 0 | N12: 510350 | O12: DfE Rev Grnts-Sponsor capacity grant | P12: 510350 | Q12: A1 | R12: FALSE | S12: ALS,AUD,BLS,HIG,MAT,MLB,PTP,SBL,WVP | T12: BUDGET | U12: COSTCTR | V12: TRUE | W12: FALSE
A13: =IF(COUNTIF(LEDGER[LedgerCode],FinanceCodesBudget[[#This Row],[LedgerCode]])>0,0,1) -> 0 | B13: =IF(COUNTIF(Table_System_Grouping_Codes[groupingCodeCode],FinanceCodesBudget[[#This Row],[GroupingCode]])>0,0,1) -> 0 | C13: =IF(COUNTIF(CUSTGROUP[CustomGroupingCode],FinanceCodesBudget[[#This Row],[CustomGrouping]])>0,0,1) -> 0 | D13: {=IF(FinanceCodesBudget[[#This Row],[AvailableToAllSchools]]=TRUE,0,COUNTA(_xlfn.TEXTSPLIT(FinanceCodesBudget[[#This Row],[SchoolCodes]],",",,TRUE))-SUM(COUNTIF(SCHOOLS[SchoolCode],_xlfn.TEXTSPLIT(FinanceCodesBudget[[#This Row],[SchoolCodes]],",",,TRUE))))} -> 0 | E13: =IF(FinanceCodesBudget[[#This Row],[FinanceCodeTypeCode]]="BUDGET",0,COUNTIF(FinanceCodesBudget[FinanceCode],FinanceCodesBudget[[#This Row],[FinanceCode]])-1) -> 0 | F13: =IF(FinanceCodesBudget[[#This Row],[FinanceCodeTypeCode]]="BUDGET",0,COUNTIF(FinanceCodesBudget[Title],FinanceCodesBudget[[#This Row],[Title]])-1) -> 0 | G13: =COUNTIF(Lookup!$A$2:$A$7,FinanceCodesBudget[[#This Row],[FinanceCodeTypeCode]])-1 -> 0 | H13: =IF(TRIM(FinanceCodesBudget[[#This Row],[Title]])="",1,0) -> 0 | I13: =IF(TRIM(FinanceCodesBudget[[#This Row],[FinanceCode]])="",1,0) -> 0 | J13: =IF(LEN(FinanceCodesBudget[[#This Row],[FinanceCode]])<100,0,1) -> 0 | K13: =IF(LEN(FinanceCodesBudget[[#This Row],[Title]])<100,0,1) -> 0 | L13: =IF(ISBLANK(FinanceCodesBudget[[#This Row],[BalanceToScenario]]),1,0) -> 0 | M13: =SUM(FinanceCodesBudget[[#This Row],[LedgerIssue]:[CustGrIssue]],FinanceCodesBudget[[#This Row],[DupCode]:[Balance to Scenario Blank]]) -> 0 | N13: 510400 | O13: DfE Rev Grnts-PE & Sports grant | P13: 510400 | Q13: A1 | R13: FALSE | S13: ALS,AUD,BLS,HIG,MAT,MLB,PTP,SBL,WVP | T13: BUDGET | U13: COSTCTR | V13: TRUE | W13: FALSE
A14: =IF(COUNTIF(LEDGER[LedgerCode],FinanceCodesBudget[[#This Row],[LedgerCode]])>0,0,1) -> 0 | B14: =IF(COUNTIF(Table_System_Grouping_Codes[groupingCodeCode],FinanceCodesBudget[[#This Row],[GroupingCode]])>0,0,1) -> 0 | C14: =IF(COUNTIF(CUSTGROUP[CustomGroupingCode],FinanceCodesBudget[[#This Row],[CustomGrouping]])>0,0,1) -> 0 | D14: {=IF(FinanceCodesBudget[[#This Row],[AvailableToAllSchools]]=TRUE,0,COUNTA(_xlfn.TEXTSPLIT(FinanceCodesBudget[[#This Row],[SchoolCodes]],",",,TRUE))-SUM(COUNTIF(SCHOOLS[SchoolCode],_xlfn.TEXTSPLIT(FinanceCodesBudget[[#This Row],[SchoolCodes]],",",,TRUE))))} -> 0 | E14: =IF(FinanceCodesBudget[[#This Row],[FinanceCodeTypeCode]]="BUDGET",0,COUNTIF(FinanceCodesBudget[FinanceCode],FinanceCodesBudget[[#This Row],[FinanceCode]])-1) -> 0 | F14: =IF(FinanceCodesBudget[[#This Row],[FinanceCodeTypeCode]]="BUDGET",0,COUNTIF(FinanceCodesBudget[Title],FinanceCodesBudget[[#This Row],[Title]])-1) -> 0 | G14: =COUNTIF(Lookup!$A$2:$A$7,FinanceCodesBudget[[#This Row],[FinanceCodeTypeCode]])-1 -> 0 | H14: =IF(TRIM(FinanceCodesBudget[[#This Row],[Title]])="",1,0) -> 0 | I14: =IF(TRIM(FinanceCodesBudget[[#This Row],[FinanceCode]])="",1,0) -> 0 | J14: =IF(LEN(FinanceCodesBudget[[#This Row],[FinanceCode]])<100,0,1) -> 0 | K14: =IF(LEN(FinanceCodesBudget[[#This Row],[Title]])<100,0,1) -> 0 | L14: =IF(ISBLANK(FinanceCodesBudget[[#This Row],[BalanceToScenario]]),1,0) -> 0 | M14: =SUM(FinanceCodesBudget[[#This Row],[LedgerIssue]:[CustGrIssue]],FinanceCodesBudget[[#This Row],[DupCode]:[Balance to Scenario Blank]]) -> 0 | N14: 510450 | O14: DfE Rev Grnts-Year 7 catch up | P14: 510450 | Q14: A1 | R14: FALSE | S14: ALS,AUD,BLS,HIG,MAT,MLB,PTP,SBL,WVP | T14: BUDGET | U14: COSTCTR | V14: TRUE | W14: FALSE
... A536: =IF(COUNTIF(LEDGER[LedgerCode],FinanceCodesBudget[[#This Row],[LedgerCode]])>0,0,1) -> 0 | B536: =IF(COUNTIF(Table_System_Grouping_Codes[groupingCodeCode],FinanceCodesBudget[[#This Row],[GroupingCode]])>0,0,1) -> 0 | C536: =IF(COUNTIF(CUSTGROUP[CustomGroupingCode],FinanceCodesBudget[[#This Row],[CustomGrouping]])>0,0,1) -> 0 | D536: {=IF(FinanceCodesBudget[[#This Row],[AvailableToAllSchools]]=TRUE,0,COUNTA(_xlfn.TEXTSPLIT(FinanceCodesBudget[[#This Row],[SchoolCodes]],",",,TRUE))-SUM(COUNTIF(SCHOOLS[SchoolCode],_xlfn.TEXTSPLIT(FinanceCodesBudget[[#This Row],[SchoolCodes]],",",,TRUE))))} -> 0 | E536: =IF(FinanceCodesBudget[[#This Row],[FinanceCodeTypeCode]]="BUDGET",0,COUNTIF(FinanceCodesBudget[FinanceCode],FinanceCodesBudget[[#This Row],[FinanceCode]])-1) -> 0 | F536: =IF(FinanceCodesBudget[[#This Row],[FinanceCodeTypeCode]]="BUDGET",0,COUNTIF(FinanceCodesBudget[Title],FinanceCodesBudget[[#This Row],[Title]])-1) -> 0 | G536: =COUNTIF(Lookup!$A$2:$A$7,FinanceCodesBudget[[#This Row],[FinanceCodeTypeCode]])-1 -> 0 | H536: =IF(TRIM(FinanceCodesBudget[[#This Row],[Title]])="",1,0) -> 0 | I536: =IF(TRIM(FinanceCodesBudget[[#This Row],[FinanceCode]])="",1,0) -> 0 | J536: =IF(LEN(FinanceCodesBudget[[#This Row],[FinanceCode]])<100,0,1) -> 0 | K536: =IF(LEN(FinanceCodesBudget[[#This Row],[Title]])<100,0,1) -> 0 | L536: =IF(ISBLANK(FinanceCodesBudget[[#This Row],[BalanceToScenario]]),1,0) -> 0 | M536: =SUM(FinanceCodesBudget[[#This Row],[LedgerIssue]:[CustGrIssue]],FinanceCodesBudget[[#This Row],[DupCode]:[Balance to Scenario Blank]]) -> 0 | N536: 895850 | O536: B'ding Supps-Impair't-b'ding | P536: 895850 | Q536: E0 | R536: FALSE | S536: ALS,AUD,BLS,HIG,MAT,MLB,PTP,SBL | T536: BUDGET | U536: CAPITAL | V536: TRUE | W536: FALSE

Sheet PayScales
A1: Duplicate Scale Code | B1: Schools Check | C1: School Code Exists | D1: TRUE /FALSE Typo | E1: Code Length | F1: Title Length | G1: Blank in column | H1: Space in Code | I1: Will Import if 0 | J1: London Weighting | K1: Increment Date | L1: Increase Date | M1: ScenarioCode | N1: PayScaleCode | O1: PayScaleTitle | P1: ServiceIncrementDateEnabled | Q1: IncrementDate | R1: IncreaseDate | S1: IncreasePercentage | T1: AvailableToAllSchools | U1: SchoolCodes | V1: PayScaleEnabled | W1: ExcludeNationalInsurance | X1: ExcludePension
A2: =COUNTIF(PAYSCALES[PayScaleCode],PAYSCALES[[#This Row],[PayScaleCode]])-1 -> 0 | B2: =IF(PAYSCALES[[#This Row],[AvailableToAllSchools]]=FALSE,IF(ISBLANK(PAYSCALES[[#This Row],[SchoolCodes]]),1,0),IF(PAYSCALES[[#This Row],[AvailableToAllSchools]]=TRUE,IF(ISBLANK(PAYSCALES[[#This Row],[SchoolCodes]]),0,1))) -> 0 | C2: {=IF(PAYSCALES[[#This Row],[AvailableToAllSchools]]=TRUE,0,COUNTA(_xlfn.TEXTSPLIT(PAYSCALES[[#This Row],[SchoolCodes]],",",,TRUE))-SUM(COUNTIF(SCHOOLS[SchoolCode],_xlfn.TEXTSPLIT(PAYSCALES[[#This Row],[SchoolCodes]],",",,TRUE))))} -> 0 | D2: =IF(OR(PAYSCALES[[#This Row],[PayScaleEnabled]]=TRUE,PAYSCALES[[#This Row],[PayScaleEnabled]]=FALSE),IF(OR(PAYSCALES[[#This Row],[ServiceIncrementDateEnabled]]=TRUE,PAYSCALES[[#This Row],[ServiceIncrementDateEnabled]]=FALSE),IF(OR(PAYSCALES[[#This Row],[AvailableToAllSchools]]=TRUE,PAYSCALES[[#This Row],[AvailableToAllSchools]]=FALSE),IF(OR(PAYSCALES[[#This Row],[ExcludeNationalInsurance]]=TRUE,PAYSCALES[[#This Row],[ExcludeNationalInsurance]]=FALSE),IF(OR(PAYSCALES[[#This Row],[ExcludePension]]=TRUE,PAYSCALES[[#This Row],[ExcludePension]]=FALSE),0,1),1),1),1),1) -> 0 | E2: =IF(LEN(PAYSCALES[[#This Row],[PayScaleCode]])<100,0,1) -> 0 | F2: =IF(LEN(PAYSCALES[[#This Row],[PayScaleTitle]])<100,0,1) -> 0 | G2: =COUNTBLANK(PAYSCALES[[#This Row],[PayScaleCode]:[AvailableToAllSchools]])+COUNTBLANK(PAYSCALES[[#This Row],[PayScaleEnabled]:[ExcludePension]]) -> 0 | H2: =IF(SUBSTITUTE(TEXT(PAYSCALES[[#This Row],[PayScaleCode]],10)," ","")=TEXT(PAYSCALES[[#This Row],[PayScaleCode]],10),0,1) -> 0 | I2: =SUM(PAYSCALES[[#This Row],[Duplicate Scale Code]:[Space in Code]]) -> 0 | J2: England & Wales | K2: =PAYSCALES[[#This Row],[IncrementDate]] -> 44440 | L2: =PAYSCALES[[#This Row],[IncreaseDate]] -> 44440 | N2: MAIN | O2: Teachers Main | P2: FALSE | Q2: 44440 | R2: 44440 | S2: 2 | T2: TRUE | V2: TRUE | W2: FALSE | X2: FALSE
A3: =COUNTIF(PAYSCALES[PayScaleCode],PAYSCALES[[#This Row],[PayScaleCode]])-1 -> 0 | B3: =IF(PAYSCALES[[#This Row],[AvailableToAllSchools]]=FALSE,IF(ISBLANK(PAYSCALES[[#This Row],[SchoolCodes]]),1,0),IF(PAYSCALES[[#This Row],[AvailableToAllSchools]]=TRUE,IF(ISBLANK(PAYSCALES[[#This Row],[SchoolCodes]]),0,1))) -> 0 | C3: {=IF(PAYSCALES[[#This Row],[AvailableToAllSchools]]=TRUE,0,COUNTA(_xlfn.TEXTSPLIT(PAYSCALES[[#This Row],[SchoolCodes]],",",,TRUE))-SUM(COUNTIF(SCHOOLS[SchoolCode],_xlfn.TEXTSPLIT(PAYSCALES[[#This Row],[SchoolCodes]],",",,TRUE))))} -> 0 | D3: =IF(OR(PAYSCALES[[#This Row],[PayScaleEnabled]]=TRUE,PAYSCALES[[#This Row],[PayScaleEnabled]]=FALSE),IF(OR(PAYSCALES[[#This Row],[ServiceIncrementDateEnabled]]=TRUE,PAYSCALES[[#This Row],[ServiceIncrementDateEnabled]]=FALSE),IF(OR(PAYSCALES[[#This Row],[AvailableToAllSchools]]=TRUE,PAYSCALES[[#This Row],[AvailableToAllSchools]]=FALSE),IF(OR(PAYSCALES[[#This Row],[ExcludeNationalInsurance]]=TRUE,PAYSCALES[[#This Row],[ExcludeNationalInsurance]]=FALSE),IF(OR(PAYSCALES[[#This Row],[ExcludePension]]=TRUE,PAYSCALES[[#This Row],[ExcludePension]]=FALSE),0,1),1),1),1),1) -> 0 | E3: =IF(LEN(PAYSCALES[[#This Row],[PayScaleCode]])<100,0,1) -> 0 | F3: =IF(LEN(PAYSCALES[[#This Row],[PayScaleTitle]])<100,0,1) -> 0 | G3: =COUNTBLANK(PAYSCALES[[#This Row],[PayScaleCode]:[AvailableToAllSchools]])+COUNTBLANK(PAYSCALES[[#This Row],[PayScaleEnabled]:[ExcludePension]]) -> 0 | H3: =IF(SUBSTITUTE(TEXT(PAYSCALES[[#This Row],[PayScaleCode]],10)," ","")=TEXT(PAYSCALES[[#This Row],[PayScaleCode]],10),0,1) -> 0 | I3: =SUM(PAYSCALES[[#This Row],[Duplicate Scale Code]:[Space in Code]]) -> 0 | J3: England & Wales | K3: =PAYSCALES[[#This Row],[IncrementDate]] -> 44440 | L3: =PAYSCALES[[#This Row],[IncreaseDate]] -> 44440 | N3: UQ | O3: Teachers Unqualified | P3: FALSE | Q3: 44440 | R3: 44440 | S3: 2 | T3: TRUE | V3: TRUE | W3: FALSE | X3: FALSE
A4: =COUNTIF(PAYSCALES[PayScaleCode],PAYSCALES[[#This Row],[PayScaleCode]])-1 -> 0 | B4: =IF(PAYSCALES[[#This Row],[AvailableToAllSchools]]=FALSE,IF(ISBLANK(PAYSCALES[[#This Row],[SchoolCodes]]),1,0),IF(PAYSCALES[[#This Row],[AvailableToAllSchools]]=TRUE,IF(ISBLANK(PAYSCALES[[#This Row],[SchoolCodes]]),0,1))) -> 0 | C4: {=IF(PAYSCALES[[#This Row],[AvailableToAllSchools]]=TRUE,0,COUNTA(_xlfn.TEXTSPLIT(PAYSCALES[[#This Row],[SchoolCodes]],",",,TRUE))-SUM(COUNTIF(SCHOOLS[SchoolCode],_xlfn.TEXTSPLIT(PAYSCALES[[#This Row],[SchoolCodes]],",",,TRUE))))} -> 0 | D4: =IF(OR(PAYSCALES[[#This Row],[PayScaleEnabled]]=TRUE,PAYSCALES[[#This Row],[PayScaleEnabled]]=FALSE),IF(OR(PAYSCALES[[#This Row],[ServiceIncrementDateEnabled]]=TRUE,PAYSCALES[[#This Row],[ServiceIncrementDateEnabled]]=FALSE),IF(OR(PAYSCALES[[#This Row],[AvailableToAllSchools]]=TRUE,PAYSCALES[[#This Row],[AvailableToAllSchools]]=FALSE),IF(OR(PAYSCALES[[#This Row],[ExcludeNationalInsurance]]=TRUE,PAYSCALES[[#This Row],[ExcludeNationalInsurance]]=FALSE),IF(OR(PAYSCALES[[#This Row],[ExcludePension]]=TRUE,PAYSCALES[[#This Row],[ExcludePension]]=FALSE),0,1),1),1),1),1) -> 0 | E4: =IF(LEN(PAYSCALES[[#This Row],[PayScaleCode]])<100,0,1) -> 0 | F4: =IF(LEN(PAYSCALES[[#This Row],[PayScaleTitle]])<100,0,1) -> 0 | G4: =COUNTBLANK(PAYSCALES[[#This Row],[PayScaleCode]:[AvailableToAllSchools]])+COUNTBLANK(PAYSCALES[[#This Row],[PayScaleEnabled]:[ExcludePension]]) -> 0 | H4: =IF(SUBSTITUTE(TEXT(PAYSCALES[[#This Row],[PayScaleCode]],10)," ","")=TEXT(PAYSCALES[[#This Row],[PayScaleCode]],10),0,1) -> 0 | I4: =SUM(PAYSCALES[[#This Row],[Duplicate Scale Code]:[Space in Code]]) -> 0 | J4: England & Wales | K4: =PAYSCALES[[#This Row],[IncrementDate]] -> 44440 | L4: =PAYSCALES[[#This Row],[IncreaseDate]] -> 44440 | N4: LS | O4: Leadership Group | P4: FALSE | Q4: 44440 | R4: 44440 | S4: 2 | T4: TRUE | V4: TRUE | W4: FALSE | X4: FALSE
A5: =COUNTIF(PAYSCALES[PayScaleCode],PAYSCALES[[#This Row],[PayScaleCode]])-1 -> 0 | B5: =IF(PAYSCALES[[#This Row],[AvailableToAllSchools]]=FALSE,IF(ISBLANK(PAYSCALES[[#This Row],[SchoolCodes]]),1,0),IF(PAYSCALES[[#This Row],[AvailableToAllSchools]]=TRUE,IF(ISBLANK(PAYSCALES[[#This Row],[SchoolCodes]]),0,1))) -> 0 | C5: {=IF(PAYSCALES[[#This Row],[AvailableToAllSchools]]=TRUE,0,COUNTA(_xlfn.TEXTSPLIT(PAYSCALES[[#This Row],[SchoolCodes]],",",,TRUE))-SUM(COUNTIF(SCHOOLS[SchoolCode],_xlfn.TEXTSPLIT(PAYSCALES[[#This Row],[SchoolCodes]],",",,TRUE))))} -> 0 | D5: =IF(OR(PAYSCALES[[#This Row],[PayScaleEnabled]]=TRUE,PAYSCALES[[#This Row],[PayScaleEnabled]]=FALSE),IF(OR(PAYSCALES[[#This Row],[ServiceIncrementDateEnabled]]=TRUE,PAYSCALES[[#This Row],[ServiceIncrementDateEnabled]]=FALSE),IF(OR(PAYSCALES[[#This Row],[AvailableToAllSchools]]=TRUE,PAYSCALES[[#This Row],[AvailableToAllSchools]]=FALSE),IF(OR(PAYSCALES[[#This Row],[ExcludeNationalInsurance]]=TRUE,PAYSCALES[[#This Row],[ExcludeNationalInsurance]]=FALSE),IF(OR(PAYSCALES[[#This Row],[ExcludePension]]=TRUE,PAYSCALES[[#This Row],[ExcludePension]]=FALSE),0,1),1),1),1),1) -> 0 | E5: =IF(LEN(PAYSCALES[[#This Row],[PayScaleCode]])<100,0,1) -> 0 | F5: =IF(LEN(PAYSCALES[[#This Row],[PayScaleTitle]])<100,0,1) -> 0 | G5: =COUNTBLANK(PAYSCALES[[#This Row],[PayScaleCode]:[AvailableToAllSchools]])+COUNTBLANK(PAYSCALES[[#This Row],[PayScaleEnabled]:[ExcludePension]]) -> 0 | H5: =IF(SUBSTITUTE(TEXT(PAYSCALES[[#This Row],[PayScaleCode]],10)," ","")=TEXT(PAYSCALES[[#This Row],[PayScaleCode]],10),0,1) -> 0 | I5: =SUM(PAYSCALES[[#This Row],[Duplicate Scale Code]:[Space in Code]]) -> 0 | J5: England & Wales | K5: =PAYSCALES[[#This Row],[IncrementDate]] -> 44440 | L5: =PAYSCALES[[#This Row],[IncreaseDate]] -> 44440 | N5: CEO | O5: CEO Scale | P5: FALSE | Q5: 44440 | R5: 44440 | S5: 2 | T5: FALSE | U5: MAT | V5: TRUE | W5: FALSE | X5: FALSE
A6: =COUNTIF(PAYSCALES[PayScaleCode],PAYSCALES[[#This Row],[PayScaleCode]])-1 -> 0 | B6: =IF(PAYSCALES[[#This Row],[AvailableToAllSchools]]=FALSE,IF(ISBLANK(PAYSCALES[[#This Row],[SchoolCodes]]),1,0),IF(PAYSCALES[[#This Row],[AvailableToAllSchools]]=TRUE,IF(ISBLANK(PAYSCALES[[#This Row],[SchoolCodes]]),0,1))) -> 0 | C6: {=IF(PAYSCALES[[#This Row],[AvailableToAllSchools]]=TRUE,0,COUNTA(_xlfn.TEXTSPLIT(PAYSCALES[[#This Row],[SchoolCodes]],",",,TRUE))-SUM(COUNTIF(SCHOOLS[SchoolCode],_xlfn.TEXTSPLIT(PAYSCALES[[#This Row],[SchoolCodes]],",",,TRUE))))} -> 0 | D6: =IF(OR(PAYSCALES[[#This Row],[PayScaleEnabled]]=TRUE,PAYSCALES[[#This Row],[PayScaleEnabled]]=FALSE),IF(OR(PAYSCALES[[#This Row],[ServiceIncrementDateEnabled]]=TRUE,PAYSCALES[[#This Row],[ServiceIncrementDateEnabled]]=FALSE),IF(OR(PAYSCALES[[#This Row],[AvailableToAllSchools]]=TRUE,PAYSCALES[[#This Row],[AvailableToAllSchools]]=FALSE),IF(OR(PAYSCALES[[#This Row],[ExcludeNationalInsurance]]=TRUE,PAYSCALES[[#This Row],[ExcludeNationalInsurance]]=FALSE),IF(OR(PAYSCALES[[#This Row],[ExcludePension]]=TRUE,PAYSCALES[[#This Row],[ExcludePension]]=FALSE),0,1),1),1),1),1) -> 0 | E6: =IF(LEN(PAYSCALES[[#This Row],[PayScaleCode]])<100,0,1) -> 0 | F6: =IF(LEN(PAYSCALES[[#This Row],[PayScaleTitle]])<100,0,1) -> 0 | G6: =COUNTBLANK(PAYSCALES[[#This Row],[PayScaleCode]:[AvailableToAllSchools]])+COUNTBLANK(PAYSCALES[[#This Row],[PayScaleEnabled]:[ExcludePension]]) -> 0 | H6: =IF(SUBSTITUTE(TEXT(PAYSCALES[[#This Row],[PayScaleCode]],10)," ","")=TEXT(PAYSCALES[[#This Row],[PayScaleCode]],10),0,1) -> 0 | I6: =SUM(PAYSCALES[[#This Row],[Duplicate Scale Code]:[Space in Code]]) -> 0 | J6: England & Wales | K6: =PAYSCALES[[#This Row],[IncrementDate]] -> 44287 | L6: =PAYSCALES[[#This Row],[IncreaseDate]] -> 44287 | N6: NJC_CHE | O6: NJC - Cheshire East | P6: TRUE | Q6: 44287 | R6: 44287 | S6: 2 | T6: TRUE | V6: TRUE | W6: FALSE | X6: FALSE
A7: =COUNTIF(PAYSCALES[PayScaleCode],PAYSCALES[[#This Row],[PayScaleCode]])-1 -> 0 | B7: =IF(PAYSCALES[[#This Row],[AvailableToAllSchools]]=FALSE,IF(ISBLANK(PAYSCALES[[#This Row],[SchoolCodes]]),1,0),IF(PAYSCALES[[#This Row],[AvailableToAllSchools]]=TRUE,IF(ISBLANK(PAYSCALES[[#This Row],[SchoolCodes]]),0,1))) -> 0 | C7: {=IF(PAYSCALES[[#This Row],[AvailableToAllSchools]]=TRUE,0,COUNTA(_xlfn.TEXTSPLIT(PAYSCALES[[#This Row],[SchoolCodes]],",",,TRUE))-SUM(COUNTIF(SCHOOLS[SchoolCode],_xlfn.TEXTSPLIT(PAYSCALES[[#This Row],[SchoolCodes]],",",,TRUE))))} -> 0 | D7: =IF(OR(PAYSCALES[[#This Row],[PayScaleEnabled]]=TRUE,PAYSCALES[[#This Row],[PayScaleEnabled]]=FALSE),IF(OR(PAYSCALES[[#This Row],[ServiceIncrementDateEnabled]]=TRUE,PAYSCALES[[#This Row],[ServiceIncrementDateEnabled]]=FALSE),IF(OR(PAYSCALES[[#This Row],[AvailableToAllSchools]]=TRUE,PAYSCALES[[#This Row],[AvailableToAllSchools]]=FALSE),IF(OR(PAYSCALES[[#This Row],[ExcludeNationalInsurance]]=TRUE,PAYSCALES[[#This Row],[ExcludeNationalInsurance]]=FALSE),IF(OR(PAYSCALES[[#This Row],[ExcludePension]]=TRUE,PAYSCALES[[#This Row],[ExcludePension]]=FALSE),0,1),1),1),1),1) -> 0 | E7: =IF(LEN(PAYSCALES[[#This Row],[PayScaleCode]])<100,0,1) -> 0 | F7: =IF(LEN(PAYSCALES[[#This Row],[PayScaleTitle]])<100,0,1) -> 0 | G7: =COUNTBLANK(PAYSCALES[[#This Row],[PayScaleCode]:[AvailableToAllSchools]])+COUNTBLANK(PAYSCALES[[#This Row],[PayScaleEnabled]:[ExcludePension]]) -> 0 | H7: =IF(SUBSTITUTE(TEXT(PAYSCALES[[#This Row],[PayScaleCode]],10)," ","")=TEXT(PAYSCALES[[#This Row],[PayScaleCode]],10),0,1) -> 0 | I7: =SUM(PAYSCALES[[#This Row],[Duplicate Scale Code]:[Space in Code]]) -> 0 | J7: England & Wales | K7: =PAYSCALES[[#This Row],[IncrementDate]] -> 44652 | L7: =PAYSCALES[[#This Row],[IncreaseDate]] -> 44652 | N7: APP_NMW | O7: Apprentice / NMW Scale | P7: FALSE | Q7: 44652 | R7: 44652 | S7: 2 | T7: TRUE | V7: TRUE | W7: FALSE | X7: FALSE

Sheet PayScalePoints
A1: Pay Scale String | B1: Scale Point Issue | C1: Pay Scale String Duplicates | D1: Duplicate Scale Check | E1: Rate Date From Issue | F1: Dates From/To Issue | G1: Date Format Issue | H1: TRUE /FALSE Typo | I1: Code Length | J1: Title Length | K1: Blank in column | L1: Space in Code | M1: Will Import if 0 | N1: London Weighting | O1: ScenarioCode | P1: PayScaleCode | Q1: PayScaleTitle | R1: PayScalePointCode | S1: PayScalePointTitle | T1: ScalePointNumber | U1: Hourly | V1: PayScalePointEnabled | W1: RateDateFrom | X1: RateDateTo | Y1: PayScaleRate
A2: =PSPOINTS[[#This Row],[PayScaleCode]]&PSPOINTS[[#This Row],[RateDateFrom]] -> MAIN45901 | B2: =IF(A2=A1,SUM(T2-T1)-1,T2-1) -> 0 | C2: =PSPOINTS[[#This Row],[PayScaleCode]]&PSPOINTS[[#This Row],[PayScalePointCode]]&PSPOINTS[[#This Row],[RateDateFrom]] -> MAINM145901 | D2: =COUNTIF(PSPOINTS[Pay Scale String Duplicates],PSPOINTS[[#This Row],[Pay Scale String Duplicates]])-1 -> 0 | E2: =IF((MONTH(_xlfn.XLOOKUP(PSPOINTS[[#This Row],[PayScaleCode]],PayScales!N:N,PayScales!R:R)))=MONTH(PSPOINTS[[#This Row],[RateDateFrom]]),0,1) -> 0 | F2: =IF(ISBLANK(PSPOINTS[[#This Row],[RateDateTo]]),0,IF(PSPOINTS[[#This Row],[RateDateFrom]]<PSPOINTS[[#This Row],[RateDateTo]],0,1)) -> 0 | G2: {=IF(CELL("format",PSPOINTS[[#This Row],[RateDateFrom]])="D1",0,1)+IF(CELL("format",PSPOINTS[[#This Row],[RateDateTo]])="D1",0,1)} -> 0 | H2: =IF(OR(PSPOINTS[[#This Row],[Hourly]]=TRUE,PSPOINTS[[#This Row],[Hourly]]=FALSE),IF(OR(PSPOINTS[[#This Row],[PayScalePointEnabled]]=TRUE,PSPOINTS[[#This Row],[PayScalePointEnabled]]=FALSE),0,1),1) -> 0 | I2: =IF(LEN(PSPOINTS[[#This Row],[PayScalePointCode]])<100,0,1) -> 0 | J2: =IF(LEN(PSPOINTS[[#This Row],[PayScalePointTitle]])<100,0,1) -> 0 | K2: =(COUNTBLANK(PSPOINTS[[#This Row],[PayScalePointCode]:[RateDateFrom]])+COUNTBLANK(PSPOINTS[[#This Row],[PayScaleRate]])) -> 0 | L2: =IF(SUBSTITUTE(TEXT(PSPOINTS[[#This Row],[PayScaleCode]],10)," ","")=TEXT(PSPOINTS[[#This Row],[PayScaleCode]],10),0,1)+IF(SUBSTITUTE(TEXT(PSPOINTS[[#This Row],[PayScalePointCode]],10)," ","")=TEXT(PSPOINTS[[#This Row],[PayScalePointCode]],10),0,1) -> 0 | M2: =SUM(PSPOINTS[[#This Row],[Scale Point Issue]:[Space in Code]]) -> 0 | N2: England & Wales | P2: MAIN | Q2: =_xlfn.XLOOKUP(PSPOINTS[[#This Row],[PayScaleCode]],PayScales!N:N,PayScales!O:O) -> Teachers Main | R2: M1 | S2: M1 | T2: 1 | U2: FALSE | V2: TRUE | W2: 45901 | Y2: 32916
A3: =PSPOINTS[[#This Row],[PayScaleCode]]&PSPOINTS[[#This Row],[RateDateFrom]] -> MAIN45901 | B3: =IF(A3=A2,SUM(T3-T2)-1,T3-1) -> 0 | C3: =PSPOINTS[[#This Row],[PayScaleCode]]&PSPOINTS[[#This Row],[PayScalePointCode]]&PSPOINTS[[#This Row],[RateDateFrom]] -> MAINM245901 | D3: =COUNTIF(PSPOINTS[Pay Scale String Duplicates],PSPOINTS[[#This Row],[Pay Scale String Duplicates]])-1 -> 0 | E3: =IF((MONTH(_xlfn.XLOOKUP(PSPOINTS[[#This Row],[PayScaleCode]],PayScales!N:N,PayScales!R:R)))=MONTH(PSPOINTS[[#This Row],[RateDateFrom]]),0,1) -> 0 | F3: =IF(ISBLANK(PSPOINTS[[#This Row],[RateDateTo]]),0,IF(PSPOINTS[[#This Row],[RateDateFrom]]<PSPOINTS[[#This Row],[RateDateTo]],0,1)) -> 0 | G3: {=IF(CELL("format",PSPOINTS[[#This Row],[RateDateFrom]])="D1",0,1)+IF(CELL("format",PSPOINTS[[#This Row],[RateDateTo]])="D1",0,1)} -> 0 | H3: =IF(OR(PSPOINTS[[#This Row],[Hourly]]=TRUE,PSPOINTS[[#This Row],[Hourly]]=FALSE),IF(OR(PSPOINTS[[#This Row],[PayScalePointEnabled]]=TRUE,PSPOINTS[[#This Row],[PayScalePointEnabled]]=FALSE),0,1),1) -> 0 | I3: =IF(LEN(PSPOINTS[[#This Row],[PayScalePointCode]])<100,0,1) -> 0 | J3: =IF(LEN(PSPOINTS[[#This Row],[PayScalePointTitle]])<100,0,1) -> 0 | K3: =(COUNTBLANK(PSPOINTS[[#This Row],[PayScalePointCode]:[RateDateFrom]])+COUNTBLANK(PSPOINTS[[#This Row],[PayScaleRate]])) -> 0 | L3: =IF(SUBSTITUTE(TEXT(PSPOINTS[[#This Row],[PayScaleCode]],10)," ","")=TEXT(PSPOINTS[[#This Row],[PayScaleCode]],10),0,1)+IF(SUBSTITUTE(TEXT(PSPOINTS[[#This Row],[PayScalePointCode]],10)," ","")=TEXT(PSPOINTS[[#This Row],[PayScalePointCode]],10),0,1) -> 0 | M3: =SUM(PSPOINTS[[#This Row],[Scale Point Issue]:[Space in Code]]) -> 0 | N3: England & Wales | P3: MAIN | Q3: =_xlfn.XLOOKUP(PSPOINTS[[#This Row],[PayScaleCode]],PayScales!N:N,PayScales!O:O) -> Teachers Main | R3: M2 | S3: M2 | T3: 2 | U3: FALSE | V3: TRUE | W3: 45901 | Y3: 34823
A4: =PSPOINTS[[#This Row],[PayScaleCode]]&PSPOINTS[[#This Row],[RateDateFrom]] -> MAIN45901 | B4: =IF(A4=A3,SUM(T4-T3)-1,T4-1) -> 0 | C4: =PSPOINTS[[#This Row],[PayScaleCode]]&PSPOINTS[[#This Row],[PayScalePointCode]]&PSPOINTS[[#This Row],[RateDateFrom]] -> MAINM345901 | D4: =COUNTIF(PSPOINTS[Pay Scale String Duplicates],PSPOINTS[[#This Row],[Pay Scale String Duplicates]])-1 -> 0 | E4: =IF((MONTH(_xlfn.XLOOKUP(PSPOINTS[[#This Row],[PayScaleCode]],PayScales!N:N,PayScales!R:R)))=MONTH(PSPOINTS[[#This Row],[RateDateFrom]]),0,1) -> 0 | F4: =IF(ISBLANK(PSPOINTS[[#This Row],[RateDateTo]]),0,IF(PSPOINTS[[#This Row],[RateDateFrom]]<PSPOINTS[[#This Row],[RateDateTo]],0,1)) -> 0 | G4: {=IF(CELL("format",PSPOINTS[[#This Row],[RateDateFrom]])="D1",0,1)+IF(CELL("format",PSPOINTS[[#This Row],[RateDateTo]])="D1",0,1)} -> 0 | H4: =IF(OR(PSPOINTS[[#This Row],[Hourly]]=TRUE,PSPOINTS[[#This Row],[Hourly]]=FALSE),IF(OR(PSPOINTS[[#This Row],[PayScalePointEnabled]]=TRUE,PSPOINTS[[#This Row],[PayScalePointEnabled]]=FALSE),0,1),1) -> 0 | I4: =IF(LEN(PSPOINTS[[#This Row],[PayScalePointCode]])<100,0,1) -> 0 | J4: =IF(LEN(PSPOINTS[[#This Row],[PayScalePointTitle]])<100,0,1) -> 0 | K4: =(COUNTBLANK(PSPOINTS[[#This Row],[PayScalePointCode]:[RateDateFrom]])+COUNTBLANK(PSPOINTS[[#This Row],[PayScaleRate]])) -> 0 | L4: =IF(SUBSTITUTE(TEXT(PSPOINTS[[#This Row],[PayScaleCode]],10)," ","")=TEXT(PSPOINTS[[#This Row],[PayScaleCode]],10),0,1)+IF(SUBSTITUTE(TEXT(PSPOINTS[[#This Row],[PayScalePointCode]],10)," ","")=TEXT(PSPOINTS[[#This Row],[PayScalePointCode]],10),0,1) -> 0 | M4: =SUM(PSPOINTS[[#This Row],[Scale Point Issue]:[Space in Code]]) -> 0 | N4: England & Wales | P4: MAIN | Q4: =_xlfn.XLOOKUP(PSPOINTS[[#This Row],[PayScaleCode]],PayScales!N:N,PayScales!O:O) -> Teachers Main | R4: M3 | S4: M3 | T4: 3 | U4: FALSE | V4: TRUE | W4: 45901 | Y4: 37101
A5: =PSPOINTS[[#This Row],[PayScaleCode]]&PSPOINTS[[#This Row],[RateDateFrom]] -> MAIN45901 | B5: =IF(A5=A4,SUM(T5-T4)-1,T5-1) -> 0 | C5: =PSPOINTS[[#This Row],[PayScaleCode]]&PSPOINTS[[#This Row],[PayScalePointCode]]&PSPOINTS[[#This Row],[RateDateFrom]] -> MAINM445901 | D5: =COUNTIF(PSPOINTS[Pay Scale String Duplicates],PSPOINTS[[#This Row],[Pay Scale String Duplicates]])-1 -> 0 | E5: =IF((MONTH(_xlfn.XLOOKUP(PSPOINTS[[#This Row],[PayScaleCode]],PayScales!N:N,PayScales!R:R)))=MONTH(PSPOINTS[[#This Row],[RateDateFrom]]),0,1) -> 0 | F5: =IF(ISBLANK(PSPOINTS[[#This Row],[RateDateTo]]),0,IF(PSPOINTS[[#This Row],[RateDateFrom]]<PSPOINTS[[#This Row],[RateDateTo]],0,1)) -> 0 | G5: {=IF(CELL("format",PSPOINTS[[#This Row],[RateDateFrom]])="D1",0,1)+IF(CELL("format",PSPOINTS[[#This Row],[RateDateTo]])="D1",0,1)} -> 0 | H5: =IF(OR(PSPOINTS[[#This Row],[Hourly]]=TRUE,PSPOINTS[[#This Row],[Hourly]]=FALSE),IF(OR(PSPOINTS[[#This Row],[PayScalePointEnabled]]=TRUE,PSPOINTS[[#This Row],[PayScalePointEnabled]]=FALSE),0,1),1) -> 0 | I5: =IF(LEN(PSPOINTS[[#This Row],[PayScalePointCode]])<100,0,1) -> 0 | J5: =IF(LEN(PSPOINTS[[#This Row],[PayScalePointTitle]])<100,0,1) -> 0 | K5: =(COUNTBLANK(PSPOINTS[[#This Row],[PayScalePointCode]:[RateDateFrom]])+COUNTBLANK(PSPOINTS[[#This Row],[PayScaleRate]])) -> 0 | L5: =IF(SUBSTITUTE(TEXT(PSPOINTS[[#This Row],[PayScaleCode]],10)," ","")=TEXT(PSPOINTS[[#This Row],[PayScaleCode]],10),0,1)+IF(SUBSTITUTE(TEXT(PSPOINTS[[#This Row],[PayScalePointCode]],10)," ","")=TEXT(PSPOINTS[[#This Row],[PayScalePointCode]],10),0,1) -> 0 | M5: =SUM(PSPOINTS[[#This Row],[Scale Point Issue]:[Space in Code]]) -> 0 | N5: England & Wales | P5: MAIN | Q5: =_xlfn.XLOOKUP(PSPOINTS[[#This Row],[PayScaleCode]],PayScales!N:N,PayScales!O:O) -> Teachers Main | R5: M4 | S5: M4 | T5: 4 | U5: FALSE | V5: TRUE | W5: 45901 | Y5: 39556
A6: =PSPOINTS[[#This Row],[PayScaleCode]]&PSPOINTS[[#This Row],[RateDateFrom]] -> MAIN45901 | B6: =IF(A6=A5,SUM(T6-T5)-1,T6-1) -> 0 | C6: =PSPOINTS[[#This Row],[PayScaleCode]]&PSPOINTS[[#This Row],[PayScalePointCode]]&PSPOINTS[[#This Row],[RateDateFrom]] -> MAINM545901 | D6: =COUNTIF(PSPOINTS[Pay Scale String Duplicates],PSPOINTS[[#This Row],[Pay Scale String Duplicates]])-1 -> 0 | E6: =IF((MONTH(_xlfn.XLOOKUP(PSPOINTS[[#This Row],[PayScaleCode]],PayScales!N:N,PayScales!R:R)))=MONTH(PSPOINTS[[#This Row],[RateDateFrom]]),0,1) -> 0 | F6: =IF(ISBLANK(PSPOINTS[[#This Row],[RateDateTo]]),0,IF(PSPOINTS[[#This Row],[RateDateFrom]]<PSPOINTS[[#This Row],[RateDateTo]],0,1)) -> 0 | G6: {=IF(CELL("format",PSPOINTS[[#This Row],[RateDateFrom]])="D1",0,1)+IF(CELL("format",PSPOINTS[[#This Row],[RateDateTo]])="D1",0,1)} -> 0 | H6: =IF(OR(PSPOINTS[[#This Row],[Hourly]]=TRUE,PSPOINTS[[#This Row],[Hourly]]=FALSE),IF(OR(PSPOINTS[[#This Row],[PayScalePointEnabled]]=TRUE,PSPOINTS[[#This Row],[PayScalePointEnabled]]=FALSE),0,1),1) -> 0 | I6: =IF(LEN(PSPOINTS[[#This Row],[PayScalePointCode]])<100,0,1) -> 0 | J6: =IF(LEN(PSPOINTS[[#This Row],[PayScalePointTitle]])<100,0,1) -> 0 | K6: =(COUNTBLANK(PSPOINTS[[#This Row],[PayScalePointCode]:[RateDateFrom]])+COUNTBLANK(PSPOINTS[[#This Row],[PayScaleRate]])) -> 0 | L6: =IF(SUBSTITUTE(TEXT(PSPOINTS[[#This Row],[PayScaleCode]],10)," ","")=TEXT(PSPOINTS[[#This Row],[PayScaleCode]],10),0,1)+IF(SUBSTITUTE(TEXT(PSPOINTS[[#This Row],[PayScalePointCode]],10)," ","")=TEXT(PSPOINTS[[#This Row],[PayScalePointCode]],10),0,1) -> 0 | M6: =SUM(PSPOINTS[[#This Row],[Scale Point Issue]:[Space in Code]]) -> 0 | N6: England & Wales | P6: MAIN | Q6: =_xlfn.XLOOKUP(PSPOINTS[[#This Row],[PayScaleCode]],PayScales!N:N,PayScales!O:O) -> Teachers Main | R6: M5 | S6: M5 | T6: 5 | U6: FALSE | V6: TRUE | W6: 45901 | Y6: 42057
A7: =PSPOINTS[[#This Row],[PayScaleCode]]&PSPOINTS[[#This Row],[RateDateFrom]] -> MAIN45901 | B7: =IF(A7=A6,SUM(T7-T6)-1,T7-1) -> 0 | C7: =PSPOINTS[[#This Row],[PayScaleCode]]&PSPOINTS[[#This Row],[PayScalePointCode]]&PSPOINTS[[#This Row],[RateDateFrom]] -> MAINM645901 | D7: =COUNTIF(PSPOINTS[Pay Scale String Duplicates],PSPOINTS[[#This Row],[Pay Scale String Duplicates]])-1 -> 0 | E7: =IF((MONTH(_xlfn.XLOOKUP(PSPOINTS[[#This Row],[PayScaleCode]],PayScales!N:N,PayScales!R:R)))=MONTH(PSPOINTS[[#This Row],[RateDateFrom]]),0,1) -> 0 | F7: =IF(ISBLANK(PSPOINTS[[#This Row],[RateDateTo]]),0,IF(PSPOINTS[[#This Row],[RateDateFrom]]<PSPOINTS[[#This Row],[RateDateTo]],0,1)) -> 0 | G7: {=IF(CELL("format",PSPOINTS[[#This Row],[RateDateFrom]])="D1",0,1)+IF(CELL("format",PSPOINTS[[#This Row],[RateDateTo]])="D1",0,1)} -> 0 | H7: =IF(OR(PSPOINTS[[#This Row],[Hourly]]=TRUE,PSPOINTS[[#This Row],[Hourly]]=FALSE),IF(OR(PSPOINTS[[#This Row],[PayScalePointEnabled]]=TRUE,PSPOINTS[[#This Row],[PayScalePointEnabled]]=FALSE),0,1),1) -> 0 | I7: =IF(LEN(PSPOINTS[[#This Row],[PayScalePointCode]])<100,0,1) -> 0 | J7: =IF(LEN(PSPOINTS[[#This Row],[PayScalePointTitle]])<100,0,1) -> 0 | K7: =(COUNTBLANK(PSPOINTS[[#This Row],[PayScalePointCode]:[RateDateFrom]])+COUNTBLANK(PSPOINTS[[#This Row],[PayScaleRate]])) -> 0 | L7: =IF(SUBSTITUTE(TEXT(PSPOINTS[[#This Row],[PayScaleCode]],10)," ","")=TEXT(PSPOINTS[[#This Row],[PayScaleCode]],10),0,1)+IF(SUBSTITUTE(TEXT(PSPOINTS[[#This Row],[PayScalePointCode]],10)," ","")=TEXT(PSPOINTS[[#This Row],[PayScalePointCode]],10),0,1) -> 0 | M7: =SUM(PSPOINTS[[#This Row],[Scale Point Issue]:[Space in Code]]) -> 0 | N7: England & Wales | P7: MAIN | Q7: =_xlfn.XLOOKUP(PSPOINTS[[#This Row],[PayScaleCode]],PayScales!N:N,PayScales!O:O) -> Teachers Main | R7: M6 | S7: M6 | T7: 6 | U7: FALSE | V7: TRUE | W7: 45901 | Y7: 45352
A8: =PSPOINTS[[#This Row],[PayScaleCode]]&PSPOINTS[[#This Row],[RateDateFrom]] -> MAIN45901 | B8: =IF(A8=A7,SUM(T8-T7)-1,T8-1) -> 0 | C8: =PSPOINTS[[#This Row],[PayScaleCode]]&PSPOINTS[[#This Row],[PayScalePointCode]]&PSPOINTS[[#This Row],[RateDateFrom]] -> MAINU145901 | D8: =COUNTIF(PSPOINTS[Pay Scale String Duplicates],PSPOINTS[[#This Row],[Pay Scale String Duplicates]])-1 -> 0 | E8: =IF((MONTH(_xlfn.XLOOKUP(PSPOINTS[[#This Row],[PayScaleCode]],PayScales!N:N,PayScales!R:R)))=MONTH(PSPOINTS[[#This Row],[RateDateFrom]]),0,1) -> 0 | F8: =IF(ISBLANK(PSPOINTS[[#This Row],[RateDateTo]]),0,IF(PSPOINTS[[#This Row],[RateDateFrom]]<PSPOINTS[[#This Row],[RateDateTo]],0,1)) -> 0 | G8: {=IF(CELL("format",PSPOINTS[[#This Row],[RateDateFrom]])="D1",0,1)+IF(CELL("format",PSPOINTS[[#This Row],[RateDateTo]])="D1",0,1)} -> 0 | H8: =IF(OR(PSPOINTS[[#This Row],[Hourly]]=TRUE,PSPOINTS[[#This Row],[Hourly]]=FALSE),IF(OR(PSPOINTS[[#This Row],[PayScalePointEnabled]]=TRUE,PSPOINTS[[#This Row],[PayScalePointEnabled]]=FALSE),0,1),1) -> 0 | I8: =IF(LEN(PSPOINTS[[#This Row],[PayScalePointCode]])<100,0,1) -> 0 | J8: =IF(LEN(PSPOINTS[[#This Row],[PayScalePointTitle]])<100,0,1) -> 0 | K8: =(COUNTBLANK(PSPOINTS[[#This Row],[PayScalePointCode]:[RateDateFrom]])+COUNTBLANK(PSPOINTS[[#This Row],[PayScaleRate]])) -> 0 | L8: =IF(SUBSTITUTE(TEXT(PSPOINTS[[#This Row],[PayScaleCode]],10)," ","")=TEXT(PSPOINTS[[#This Row],[PayScaleCode]],10),0,1)+IF(SUBSTITUTE(TEXT(PSPOINTS[[#This Row],[PayScalePointCode]],10)," ","")=TEXT(PSPOINTS[[#This Row],[PayScalePointCode]],10),0,1) -> 0 | M8: =SUM(PSPOINTS[[#This Row],[Scale Point Issue]:[Space in Code]]) -> 0 | N8: England & Wales | P8: MAIN | Q8: =_xlfn.XLOOKUP(PSPOINTS[[#This Row],[PayScaleCode]],PayScales!N:N,PayScales!O:O) -> Teachers Main | R8: U1 | S8: U1 | T8: 7 | U8: FALSE | V8: TRUE | W8: 45901 | Y8: 47472
A9: =PSPOINTS[[#This Row],[PayScaleCode]]&PSPOINTS[[#This Row],[RateDateFrom]] -> MAIN45901 | B9: =IF(A9=A8,SUM(T9-T8)-1,T9-1) -> 0 | C9: =PSPOINTS[[#This Row],[PayScaleCode]]&PSPOINTS[[#This Row],[PayScalePointCode]]&PSPOINTS[[#This Row],[RateDateFrom]] -> MAINU245901 | D9: =COUNTIF(PSPOINTS[Pay Scale String Duplicates],PSPOINTS[[#This Row],[Pay Scale String Duplicates]])-1 -> 0 | E9: =IF((MONTH(_xlfn.XLOOKUP(PSPOINTS[[#This Row],[PayScaleCode]],PayScales!N:N,PayScales!R:R)))=MONTH(PSPOINTS[[#This Row],[RateDateFrom]]),0,1) -> 0 | F9: =IF(ISBLANK(PSPOINTS[[#This Row],[RateDateTo]]),0,IF(PSPOINTS[[#This Row],[RateDateFrom]]<PSPOINTS[[#This Row],[RateDateTo]],0,1)) -> 0 | G9: {=IF(CELL("format",PSPOINTS[[#This Row],[RateDateFrom]])="D1",0,1)+IF(CELL("format",PSPOINTS[[#This Row],[RateDateTo]])="D1",0,1)} -> 0 | H9: =IF(OR(PSPOINTS[[#This Row],[Hourly]]=TRUE,PSPOINTS[[#This Row],[Hourly]]=FALSE),IF(OR(PSPOINTS[[#This Row],[PayScalePointEnabled]]=TRUE,PSPOINTS[[#This Row],[PayScalePointEnabled]]=FALSE),0,1),1) -> 0 | I9: =IF(LEN(PSPOINTS[[#This Row],[PayScalePointCode]])<100,0,1) -> 0 | J9: =IF(LEN(PSPOINTS[[#This Row],[PayScalePointTitle]])<100,0,1) -> 0 | K9: =(COUNTBLANK(PSPOINTS[[#This Row],[PayScalePointCode]:[RateDateFrom]])+COUNTBLANK(PSPOINTS[[#This Row],[PayScaleRate]])) -> 0 | L9: =IF(SUBSTITUTE(TEXT(PSPOINTS[[#This Row],[PayScaleCode]],10)," ","")=TEXT(PSPOINTS[[#This Row],[PayScaleCode]],10),0,1)+IF(SUBSTITUTE(TEXT(PSPOINTS[[#This Row],[PayScalePointCode]],10)," ","")=TEXT(PSPOINTS[[#This Row],[PayScalePointCode]],10),0,1) -> 0 | M9: =SUM(PSPOINTS[[#This Row],[Scale Point Issue]:[Space in Code]]) -> 0 | N9: England & Wales | P9: MAIN | Q9: =_xlfn.XLOOKUP(PSPOINTS[[#This Row],[PayScaleCode]],PayScales!N:N,PayScales!O:O) -> Teachers Main | R9: U2 | S9: U2 | T9: 8 | U9: FALSE | V9: TRUE | W9: 45901 | Y9: 49232
A10: =PSPOINTS[[#This Row],[PayScaleCode]]&PSPOINTS[[#This Row],[RateDateFrom]] -> MAIN45901 | B10: =IF(A10=A9,SUM(T10-T9)-1,T10-1) -> 0 | C10: =PSPOINTS[[#This Row],[PayScaleCode]]&PSPOINTS[[#This Row],[PayScalePointCode]]&PSPOINTS[[#This Row],[RateDateFrom]] -> MAINU345901 | D10: =COUNTIF(PSPOINTS[Pay Scale String Duplicates],PSPOINTS[[#This Row],[Pay Scale String Duplicates]])-1 -> 0 | E10: =IF((MONTH(_xlfn.XLOOKUP(PSPOINTS[[#This Row],[PayScaleCode]],PayScales!N:N,PayScales!R:R)))=MONTH(PSPOINTS[[#This Row],[RateDateFrom]]),0,1) -> 0 | F10: =IF(ISBLANK(PSPOINTS[[#This Row],[RateDateTo]]),0,IF(PSPOINTS[[#This Row],[RateDateFrom]]<PSPOINTS[[#This Row],[RateDateTo]],0,1)) -> 0 | G10: {=IF(CELL("format",PSPOINTS[[#This Row],[RateDateFrom]])="D1",0,1)+IF(CELL("format",PSPOINTS[[#This Row],[RateDateTo]])="D1",0,1)} -> 0 | H10: =IF(OR(PSPOINTS[[#This Row],[Hourly]]=TRUE,PSPOINTS[[#This Row],[Hourly]]=FALSE),IF(OR(PSPOINTS[[#This Row],[PayScalePointEnabled]]=TRUE,PSPOINTS[[#This Row],[PayScalePointEnabled]]=FALSE),0,1),1) -> 0 | I10: =IF(LEN(PSPOINTS[[#This Row],[PayScalePointCode]])<100,0,1) -> 0 | J10: =IF(LEN(PSPOINTS[[#This Row],[PayScalePointTitle]])<100,0,1) -> 0 | K10: =(COUNTBLANK(PSPOINTS[[#This Row],[PayScalePointCode]:[RateDateFrom]])+COUNTBLANK(PSPOINTS[[#This Row],[PayScaleRate]])) -> 0 | L10: =IF(SUBSTITUTE(TEXT(PSPOINTS[[#This Row],[PayScaleCode]],10)," ","")=TEXT(PSPOINTS[[#This Row],[PayScaleCode]],10),0,1)+IF(SUBSTITUTE(TEXT(PSPOINTS[[#This Row],[PayScalePointCode]],10)," ","")=TEXT(PSPOINTS[[#This Row],[PayScalePointCode]],10),0,1) -> 0 | M10: =SUM(PSPOINTS[[#This Row],[Scale Point Issue]:[Space in Code]]) -> 0 | N10: England & Wales | P10: MAIN | Q10: =_xlfn.XLOOKUP(PSPOINTS[[#This Row],[PayScaleCode]],PayScales!N:N,PayScales!O:O) -> Teachers Main | R10: U3 | S10: U3 | T10: 9 | U10: FALSE | V10: TRUE | W10: 45901 | Y10: 51048
A11: =PSPOINTS[[#This Row],[PayScaleCode]]&PSPOINTS[[#This Row],[RateDateFrom]] -> UQ45901 | B11: =IF(A11=A10,SUM(T11-T10)-1,T11-1) -> 0 | C11: =PSPOINTS[[#This Row],[PayScaleCode]]&PSPOINTS[[#This Row],[PayScalePointCode]]&PSPOINTS[[#This Row],[RateDateFrom]] -> UQUQ145901 | D11: =COUNTIF(PSPOINTS[Pay Scale String Duplicates],PSPOINTS[[#This Row],[Pay Scale String Duplicates]])-1 -> 0 | E11: =IF((MONTH(_xlfn.XLOOKUP(PSPOINTS[[#This Row],[PayScaleCode]],PayScales!N:N,PayScales!R:R)))=MONTH(PSPOINTS[[#This Row],[RateDateFrom]]),0,1) -> 0 | F11: =IF(ISBLANK(PSPOINTS[[#This Row],[RateDateTo]]),0,IF(PSPOINTS[[#This Row],[RateDateFrom]]<PSPOINTS[[#This Row],[RateDateTo]],0,1)) -> 0 | G11: {=IF(CELL("format",PSPOINTS[[#This Row],[RateDateFrom]])="D1",0,1)+IF(CELL("format",PSPOINTS[[#This Row],[RateDateTo]])="D1",0,1)} -> 0 | H11: =IF(OR(PSPOINTS[[#This Row],[Hourly]]=TRUE,PSPOINTS[[#This Row],[Hourly]]=FALSE),IF(OR(PSPOINTS[[#This Row],[PayScalePointEnabled]]=TRUE,PSPOINTS[[#This Row],[PayScalePointEnabled]]=FALSE),0,1),1) -> 0 | I11: =IF(LEN(PSPOINTS[[#This Row],[PayScalePointCode]])<100,0,1) -> 0 | J11: =IF(LEN(PSPOINTS[[#This Row],[PayScalePointTitle]])<100,0,1) -> 0 | K11: =(COUNTBLANK(PSPOINTS[[#This Row],[PayScalePointCode]:[RateDateFrom]])+COUNTBLANK(PSPOINTS[[#This Row],[PayScaleRate]])) -> 0 | L11: =IF(SUBSTITUTE(TEXT(PSPOINTS[[#This Row],[PayScaleCode]],10)," ","")=TEXT(PSPOINTS[[#This Row],[PayScaleCode]],10),0,1)+IF(SUBSTITUTE(TEXT(PSPOINTS[[#This Row],[PayScalePointCode]],10)," ","")=TEXT(PSPOINTS[[#This Row],[PayScalePointCode]],10),0,1) -> 0 | M11: =SUM(PSPOINTS[[#This Row],[Scale Point Issue]:[Space in Code]]) -> 0 | N11: England & Wales | P11: UQ | Q11: =_xlfn.XLOOKUP(PSPOINTS[[#This Row],[PayScaleCode]],PayScales!N:N,PayScales!O:O) -> Teachers Unqualified | R11: UQ1 | S11: UQ1 | T11: 1 | U11: FALSE | V11: TRUE | W11: 45901 | Y11: 22601
A12: =PSPOINTS[[#This Row],[PayScaleCode]]&PSPOINTS[[#This Row],[RateDateFrom]] -> UQ45901 | B12: =IF(A12=A11,SUM(T12-T11)-1,T12-1) -> 0 | C12: =PSPOINTS[[#This Row],[PayScaleCode]]&PSPOINTS[[#This Row],[PayScalePointCode]]&PSPOINTS[[#This Row],[RateDateFrom]] -> UQUQ245901 | D12: =COUNTIF(PSPOINTS[Pay Scale String Duplicates],PSPOINTS[[#This Row],[Pay Scale String Duplicates]])-1 -> 0 | E12: =IF((MONTH(_xlfn.XLOOKUP(PSPOINTS[[#This Row],[PayScaleCode]],PayScales!N:N,PayScales!R:R)))=MONTH(PSPOINTS[[#This Row],[RateDateFrom]]),0,1) -> 0 | F12: =IF(ISBLANK(PSPOINTS[[#This Row],[RateDateTo]]),0,IF(PSPOINTS[[#This Row],[RateDateFrom]]<PSPOINTS[[#This Row],[RateDateTo]],0,1)) -> 0 | G12: {=IF(CELL("format",PSPOINTS[[#This Row],[RateDateFrom]])="D1",0,1)+IF(CELL("format",PSPOINTS[[#This Row],[RateDateTo]])="D1",0,1)} -> 0 | H12: =IF(OR(PSPOINTS[[#This Row],[Hourly]]=TRUE,PSPOINTS[[#This Row],[Hourly]]=FALSE),IF(OR(PSPOINTS[[#This Row],[PayScalePointEnabled]]=TRUE,PSPOINTS[[#This Row],[PayScalePointEnabled]]=FALSE),0,1),1) -> 0 | I12: =IF(LEN(PSPOINTS[[#This Row],[PayScalePointCode]])<100,0,1) -> 0 | J12: =IF(LEN(PSPOINTS[[#This Row],[PayScalePointTitle]])<100,0,1) -> 0 | K12: =(COUNTBLANK(PSPOINTS[[#This Row],[PayScalePointCode]:[RateDateFrom]])+COUNTBLANK(PSPOINTS[[#This Row],[PayScaleRate]])) -> 0 | L12: =IF(SUBSTITUTE(TEXT(PSPOINTS[[#This Row],[PayScaleCode]],10)," ","")=TEXT(PSPOINTS[[#This Row],[PayScaleCode]],10),0,1)+IF(SUBSTITUTE(TEXT(PSPOINTS[[#This Row],[PayScalePointCode]],10)," ","")=TEXT(PSPOINTS[[#This Row],[PayScalePointCode]],10),0,1) -> 0 | M12: =SUM(PSPOINTS[[#This Row],[Scale Point Issue]:[Space in Code]]) -> 0 | N12: England & Wales | P12: UQ | Q12: =_xlfn.XLOOKUP(PSPOINTS[[#This Row],[PayScaleCode]],PayScales!N:N,PayScales!O:O) -> Teachers Unqualified | R12: UQ2 | S12: UQ2 | T12: 2 | U12: FALSE | V12: TRUE | W12: 45901 | Y12: 25193
A13: =PSPOINTS[[#This Row],[PayScaleCode]]&PSPOINTS[[#This Row],[RateDateFrom]] -> UQ45901 | B13: =IF(A13=A12,SUM(T13-T12)-1,T13-1) -> 0 | C13: =PSPOINTS[[#This Row],[PayScaleCode]]&PSPOINTS[[#This Row],[PayScalePointCode]]&PSPOINTS[[#This Row],[RateDateFrom]] -> UQUQ345901 | D13: =COUNTIF(PSPOINTS[Pay Scale String Duplicates],PSPOINTS[[#This Row],[Pay Scale String Duplicates]])-1 -> 0 | E13: =IF((MONTH(_xlfn.XLOOKUP(PSPOINTS[[#This Row],[PayScaleCode]],PayScales!N:N,PayScales!R:R)))=MONTH(PSPOINTS[[#This Row],[RateDateFrom]]),0,1) -> 0 | F13: =IF(ISBLANK(PSPOINTS[[#This Row],[RateDateTo]]),0,IF(PSPOINTS[[#This Row],[RateDateFrom]]<PSPOINTS[[#This Row],[RateDateTo]],0,1)) -> 0 | G13: {=IF(CELL("format",PSPOINTS[[#This Row],[RateDateFrom]])="D1",0,1)+IF(CELL("format",PSPOINTS[[#This Row],[RateDateTo]])="D1",0,1)} -> 0 | H13: =IF(OR(PSPOINTS[[#This Row],[Hourly]]=TRUE,PSPOINTS[[#This Row],[Hourly]]=FALSE),IF(OR(PSPOINTS[[#This Row],[PayScalePointEnabled]]=TRUE,PSPOINTS[[#This Row],[PayScalePointEnabled]]=FALSE),0,1),1) -> 0 | I13: =IF(LEN(PSPOINTS[[#This Row],[PayScalePointCode]])<100,0,1) -> 0 | J13: =IF(LEN(PSPOINTS[[#This Row],[PayScalePointTitle]])<100,0,1) -> 0 | K13: =(COUNTBLANK(PSPOINTS[[#This Row],[PayScalePointCode]:[RateDateFrom]])+COUNTBLANK(PSPOINTS[[#This Row],[PayScaleRate]])) -> 0 | L13: =IF(SUBSTITUTE(TEXT(PSPOINTS[[#This Row],[PayScaleCode]],10)," ","")=TEXT(PSPOINTS[[#This Row],[PayScaleCode]],10),0,1)+IF(SUBSTITUTE(TEXT(PSPOINTS[[#This Row],[PayScalePointCode]],10)," ","")=TEXT(PSPOINTS[[#This Row],[PayScalePointCode]],10),0,1) -> 0 | M13: =SUM(PSPOINTS[[#This Row],[Scale Point Issue]:[Space in Code]]) -> 0 | N13: England & Wales | P13: UQ | Q13: =_xlfn.XLOOKUP(PSPOINTS[[#This Row],[PayScaleCode]],PayScales!N:N,PayScales!O:O) -> Teachers Unqualified | R13: UQ3 | S13: UQ3 | T13: 3 | U13: FALSE | V13: TRUE | W13: 45901 | Y13: 27785
... A64: =PSPOINTS[[#This Row],[PayScaleCode]]&PSPOINTS[[#This Row],[RateDateFrom]] -> CEO45901 | B64: =IF(A64=A63,SUM(T64-T63)-1,T64-1) -> 0 | C64: =PSPOINTS[[#This Row],[PayScaleCode]]&PSPOINTS[[#This Row],[PayScalePointCode]]&PSPOINTS[[#This Row],[RateDateFrom]] -> CEOL0545901 | D64: =COUNTIF(PSPOINTS[Pay Scale String Duplicates],PSPOINTS[[#This Row],[Pay Scale String Duplicates]])-1 -> 0 | E64: =IF((MONTH(_xlfn.XLOOKUP(PSPOINTS[[#This Row],[PayScaleCode]],PayScales!N:N,PayScales!R:R)))=MONTH(PSPOINTS[[#This Row],[RateDateFrom]]),0,1) -> 0 | F64: =IF(ISBLANK(PSPOINTS[[#This Row],[RateDateTo]]),0,IF(PSPOINTS[[#This Row],[RateDateFrom]]<PSPOINTS[[#This Row],[RateDateTo]],0,1)) -> 0 | G64: {=IF(CELL("format",PSPOINTS[[#This Row],[RateDateFrom]])="D1",0,1)+IF(CELL("format",PSPOINTS[[#This Row],[RateDateTo]])="D1",0,1)} -> 0 | H64: =IF(OR(PSPOINTS[[#This Row],[Hourly]]=TRUE,PSPOINTS[[#This Row],[Hourly]]=FALSE),IF(OR(PSPOINTS[[#This Row],[PayScalePointEnabled]]=TRUE,PSPOINTS[[#This Row],[PayScalePointEnabled]]=FALSE),0,1),1) -> 0 | I64: =IF(LEN(PSPOINTS[[#This Row],[PayScalePointCode]])<100,0,1) -> 0 | J64: =IF(LEN(PSPOINTS[[#This Row],[PayScalePointTitle]])<100,0,1) -> 0 | K64: =(COUNTBLANK(PSPOINTS[[#This Row],[PayScalePointCode]:[RateDateFrom]])+COUNTBLANK(PSPOINTS[[#This Row],[PayScaleRate]])) -> 0 | L64: =IF(SUBSTITUTE(TEXT(PSPOINTS[[#This Row],[PayScaleCode]],10)," ","")=TEXT(PSPOINTS[[#This Row],[PayScaleCode]],10),0,1)+IF(SUBSTITUTE(TEXT(PSPOINTS[[#This Row],[PayScalePointCode]],10)," ","")=TEXT(PSPOINTS[[#This Row],[PayScalePointCode]],10),0,1) -> 0 | M64: =SUM(PSPOINTS[[#This Row],[Scale Point Issue]:[Space in Code]]) -> 0 | N64: England & Wales | P64: CEO | Q64: =_xlfn.XLOOKUP(PSPOINTS[[#This Row],[PayScaleCode]],PayScales!N:N,PayScales!O:O) -> CEO Scale | R64: L05 | S64: L05 | T64: 5 | U64: FALSE | V64: TRUE | W64: 45901 | Y64: 155432
A65: =PSPOINTS[[#This Row],[PayScaleCode]]&PSPOINTS[[#This Row],[RateDateFrom]] -> NJC_CHE45748 | B65: =IF(A65=A64,SUM(T65-T64)-1,T65-1) -> 0 | C65: =PSPOINTS[[#This Row],[PayScaleCode]]&PSPOINTS[[#This Row],[PayScalePointCode]]&PSPOINTS[[#This Row],[RateDateFrom]] -> NJC_CHE145748 | D65: =COUNTIF(PSPOINTS[Pay Scale String Duplicates],PSPOINTS[[#This Row],[Pay Scale String Duplicates]])-1 -> 0 | E65: =IF((MONTH(_xlfn.XLOOKUP(PSPOINTS[[#This Row],[PayScaleCode]],PayScales!N:N,PayScales!R:R)))=MONTH(PSPOINTS[[#This Row],[RateDateFrom]]),0,1) -> 0 | F65: =IF(ISBLANK(PSPOINTS[[#This Row],[RateDateTo]]),0,IF(PSPOINTS[[#This Row],[RateDateFrom]]<PSPOINTS[[#This Row],[RateDateTo]],0,1)) -> 0 | G65: {=IF(CELL("format",PSPOINTS[[#This Row],[RateDateFrom]])="D1",0,1)+IF(CELL("format",PSPOINTS[[#This Row],[RateDateTo]])="D1",0,1)} -> 0 | H65: =IF(OR(PSPOINTS[[#This Row],[Hourly]]=TRUE,PSPOINTS[[#This Row],[Hourly]]=FALSE),IF(OR(PSPOINTS[[#This Row],[PayScalePointEnabled]]=TRUE,PSPOINTS[[#This Row],[PayScalePointEnabled]]=FALSE),0,1),1) -> 0 | I65: =IF(LEN(PSPOINTS[[#This Row],[PayScalePointCode]])<100,0,1) -> 0 | J65: =IF(LEN(PSPOINTS[[#This Row],[PayScalePointTitle]])<100,0,1) -> 0 | K65: =(COUNTBLANK(PSPOINTS[[#This Row],[PayScalePointCode]:[RateDateFrom]])+COUNTBLANK(PSPOINTS[[#This Row],[PayScaleRate]])) -> 0 | L65: =IF(SUBSTITUTE(TEXT(PSPOINTS[[#This Row],[PayScaleCode]],10)," ","")=TEXT(PSPOINTS[[#This Row],[PayScaleCode]],10),0,1)+IF(SUBSTITUTE(TEXT(PSPOINTS[[#This Row],[PayScalePointCode]],10)," ","")=TEXT(PSPOINTS[[#This Row],[PayScalePointCode]],10),0,1) -> 0 | M65: =SUM(PSPOINTS[[#This Row],[Scale Point Issue]:[Space in Code]]) -> 0 | N65: England & Wales | P65: NJC_CHE | Q65: =_xlfn.XLOOKUP(PSPOINTS[[#This Row],[PayScaleCode]],PayScales!N:N,PayScales!O:O) -> NJC - Cheshire East | R65: 1 | S65: 1 | T65: 1 | U65: FALSE | V65: FALSE | W65: 45748 | Y65: 0
A66: =PSPOINTS[[#This Row],[PayScaleCode]]&PSPOINTS[[#This Row],[RateDateFrom]] -> NJC_CHE45748 | B66: =IF(A66=A65,SUM(T66-T65)-1,T66-1) -> 0 | C66: =PSPOINTS[[#This Row],[PayScaleCode]]&PSPOINTS[[#This Row],[PayScalePointCode]]&PSPOINTS[[#This Row],[RateDateFrom]] -> NJC_CHE245748 | D66: =COUNTIF(PSPOINTS[Pay Scale String Duplicates],PSPOINTS[[#This Row],[Pay Scale String Duplicates]])-1 -> 0 | E66: =IF((MONTH(_xlfn.XLOOKUP(PSPOINTS[[#This Row],[PayScaleCode]],PayScales!N:N,PayScales!R:R)))=MONTH(PSPOINTS[[#This Row],[RateDateFrom]]),0,1) -> 0 | F66: =IF(ISBLANK(PSPOINTS[[#This Row],[RateDateTo]]),0,IF(PSPOINTS[[#This Row],[RateDateFrom]]<PSPOINTS[[#This Row],[RateDateTo]],0,1)) -> 0 | G66: {=IF(CELL("format",PSPOINTS[[#This Row],[RateDateFrom]])="D1",0,1)+IF(CELL("format",PSPOINTS[[#This Row],[RateDateTo]])="D1",0,1)} -> 0 | H66: =IF(OR(PSPOINTS[[#This Row],[Hourly]]=TRUE,PSPOINTS[[#This Row],[Hourly]]=FALSE),IF(OR(PSPOINTS[[#This Row],[PayScalePointEnabled]]=TRUE,PSPOINTS[[#This Row],[PayScalePointEnabled]]=FALSE),0,1),1) -> 0 | I66: =IF(LEN(PSPOINTS[[#This Row],[PayScalePointCode]])<100,0,1) -> 0 | J66: =IF(LEN(PSPOINTS[[#This Row],[PayScalePointTitle]])<100,0,1) -> 0 | K66: =(COUNTBLANK(PSPOINTS[[#This Row],[PayScalePointCode]:[RateDateFrom]])+COUNTBLANK(PSPOINTS[[#This Row],[PayScaleRate]])) -> 0 | L66: =IF(SUBSTITUTE(TEXT(PSPOINTS[[#This Row],[PayScaleCode]],10)," ","")=TEXT(PSPOINTS[[#This Row],[PayScaleCode]],10),0,1)+IF(SUBSTITUTE(TEXT(PSPOINTS[[#This Row],[PayScalePointCode]],10)," ","")=TEXT(PSPOINTS[[#This Row],[PayScalePointCode]],10),0,1) -> 0 | M66: =SUM(PSPOINTS[[#This Row],[Scale Point Issue]:[Space in Code]]) -> 0 | N66: England & Wales | P66: NJC_CHE | Q66: =_xlfn.XLOOKUP(PSPOINTS[[#This Row],[PayScaleCode]],PayScales!N:N,PayScales!O:O) -> NJC - Cheshire East | R66: 2 | S66: 2 | T66: 2 | U66: FALSE | V66: TRUE | W66: 45748 | Y66: 24413
A67: =PSPOINTS[[#This Row],[PayScaleCode]]&PSPOINTS[[#This Row],[RateDateFrom]] -> NJC_CHE45748 | B67: =IF(A67=A66,SUM(T67-T66)-1,T67-1) -> 0 | C67: =PSPOINTS[[#This Row],[PayScaleCode]]&PSPOINTS[[#This Row],[PayScalePointCode]]&PSPOINTS[[#This Row],[RateDateFrom]] -> NJC_CHE345748 | D67: =COUNTIF(PSPOINTS[Pay Scale String Duplicates],PSPOINTS[[#This Row],[Pay Scale String Duplicates]])-1 -> 0 | E67: =IF((MONTH(_xlfn.XLOOKUP(PSPOINTS[[#This Row],[PayScaleCode]],PayScales!N:N,PayScales!R:R)))=MONTH(PSPOINTS[[#This Row],[RateDateFrom]]),0,1) -> 0 | F67: =IF(ISBLANK(PSPOINTS[[#This Row],[RateDateTo]]),0,IF(PSPOINTS[[#This Row],[RateDateFrom]]<PSPOINTS[[#This Row],[RateDateTo]],0,1)) -> 0 | G67: {=IF(CELL("format",PSPOINTS[[#This Row],[RateDateFrom]])="D1",0,1)+IF(CELL("format",PSPOINTS[[#This Row],[RateDateTo]])="D1",0,1)} -> 0 | H67: =IF(OR(PSPOINTS[[#This Row],[Hourly]]=TRUE,PSPOINTS[[#This Row],[Hourly]]=FALSE),IF(OR(PSPOINTS[[#This Row],[PayScalePointEnabled]]=TRUE,PSPOINTS[[#This Row],[PayScalePointEnabled]]=FALSE),0,1),1) -> 0 | I67: =IF(LEN(PSPOINTS[[#This Row],[PayScalePointCode]])<100,0,1) -> 0 | J67: =IF(LEN(PSPOINTS[[#This Row],[PayScalePointTitle]])<100,0,1) -> 0 | K67: =(COUNTBLANK(PSPOINTS[[#This Row],[PayScalePointCode]:[RateDateFrom]])+COUNTBLANK(PSPOINTS[[#This Row],[PayScaleRate]])) -> 0 | L67: =IF(SUBSTITUTE(TEXT(PSPOINTS[[#This Row],[PayScaleCode]],10)," ","")=TEXT(PSPOINTS[[#This Row],[PayScaleCode]],10),0,1)+IF(SUBSTITUTE(TEXT(PSPOINTS[[#This Row],[PayScalePointCode]],10)," ","")=TEXT(PSPOINTS[[#This Row],[PayScalePointCode]],10),0,1) -> 0 | M67: =SUM(PSPOINTS[[#This Row],[Scale Point Issue]:[Space in Code]]) -> 0 | N67: England & Wales | P67: NJC_CHE | Q67: =_xlfn.XLOOKUP(PSPOINTS[[#This Row],[PayScaleCode]],PayScales!N:N,PayScales!O:O) -> NJC - Cheshire East | R67: 3 | S67: 3 | T67: 3 | U67: FALSE | V67: TRUE | W67: 45748 | Y67: 24796
A68: =PSPOINTS[[#This Row],[PayScaleCode]]&PSPOINTS[[#This Row],[RateDateFrom]] -> NJC_CHE45748 | B68: =IF(A68=A67,SUM(T68-T67)-1,T68-1) -> 0 | C68: =PSPOINTS[[#This Row],[PayScaleCode]]&PSPOINTS[[#This Row],[PayScalePointCode]]&PSPOINTS[[#This Row],[RateDateFrom]] -> NJC_CHE445748 | D68: =COUNTIF(PSPOINTS[Pay Scale String Duplicates],PSPOINTS[[#This Row],[Pay Scale String Duplicates]])-1 -> 0 | E68: =IF((MONTH(_xlfn.XLOOKUP(PSPOINTS[[#This Row],[PayScaleCode]],PayScales!N:N,PayScales!R:R)))=MONTH(PSPOINTS[[#This Row],[RateDateFrom]]),0,1) -> 0 | F68: =IF(ISBLANK(PSPOINTS[[#This Row],[RateDateTo]]),0,IF(PSPOINTS[[#This Row],[RateDateFrom]]<PSPOINTS[[#This Row],[RateDateTo]],0,1)) -> 0 | G68: {=IF(CELL("format",PSPOINTS[[#This Row],[RateDateFrom]])="D1",0,1)+IF(CELL("format",PSPOINTS[[#This Row],[RateDateTo]])="D1",0,1)} -> 0 | H68: =IF(OR(PSPOINTS[[#This Row],[Hourly]]=TRUE,PSPOINTS[[#This Row],[Hourly]]=FALSE),IF(OR(PSPOINTS[[#This Row],[PayScalePointEnabled]]=TRUE,PSPOINTS[[#This Row],[PayScalePointEnabled]]=FALSE),0,1),1) -> 0 | I68: =IF(LEN(PSPOINTS[[#This Row],[PayScalePointCode]])<100,0,1) -> 0 | J68: =IF(LEN(PSPOINTS[[#This Row],[PayScalePointTitle]])<100,0,1) -> 0 | K68: =(COUNTBLANK(PSPOINTS[[#This Row],[PayScalePointCode]:[RateDateFrom]])+COUNTBLANK(PSPOINTS[[#This Row],[PayScaleRate]])) -> 0 | L68: =IF(SUBSTITUTE(TEXT(PSPOINTS[[#This Row],[PayScaleCode]],10)," ","")=TEXT(PSPOINTS[[#This Row],[PayScaleCode]],10),0,1)+IF(SUBSTITUTE(TEXT(PSPOINTS[[#This Row],[PayScalePointCode]],10)," ","")=TEXT(PSPOINTS[[#This Row],[PayScalePointCode]],10),0,1) -> 0 | M68: =SUM(PSPOINTS[[#This Row],[Scale Point Issue]:[Space in Code]]) -> 0 | N68: England & Wales | P68: NJC_CHE | Q68: =_xlfn.XLOOKUP(PSPOINTS[[#This Row],[PayScaleCode]],PayScales!N:N,PayScales!O:O) -> NJC - Cheshire East | R68: 4 | S68: 4 | T68: 4 | U68: FALSE | V68: TRUE | W68: 45748 | Y68: 25185
A69: =PSPOINTS[[#This Row],[PayScaleCode]]&PSPOINTS[[#This Row],[RateDateFrom]] -> NJC_CHE45748 | B69: =IF(A69=A68,SUM(T69-T68)-1,T69-1) -> 0 | C69: =PSPOINTS[[#This Row],[PayScaleCode]]&PSPOINTS[[#This Row],[PayScalePointCode]]&PSPOINTS[[#This Row],[RateDateFrom]] -> NJC_CHE545748 | D69: =COUNTIF(PSPOINTS[Pay Scale String Duplicates],PSPOINTS[[#This Row],[Pay Scale String Duplicates]])-1 -> 0 | E69: =IF((MONTH(_xlfn.XLOOKUP(PSPOINTS[[#This Row],[PayScaleCode]],PayScales!N:N,PayScales!R:R)))=MONTH(PSPOINTS[[#This Row],[RateDateFrom]]),0,1) -> 0 | F69: =IF(ISBLANK(PSPOINTS[[#This Row],[RateDateTo]]),0,IF(PSPOINTS[[#This Row],[RateDateFrom]]<PSPOINTS[[#This Row],[RateDateTo]],0,1)) -> 0 | G69: {=IF(CELL("format",PSPOINTS[[#This Row],[RateDateFrom]])="D1",0,1)+IF(CELL("format",PSPOINTS[[#This Row],[RateDateTo]])="D1",0,1)} -> 0 | H69: =IF(OR(PSPOINTS[[#This Row],[Hourly]]=TRUE,PSPOINTS[[#This Row],[Hourly]]=FALSE),IF(OR(PSPOINTS[[#This Row],[PayScalePointEnabled]]=TRUE,PSPOINTS[[#This Row],[PayScalePointEnabled]]=FALSE),0,1),1) -> 0 | I69: =IF(LEN(PSPOINTS[[#This Row],[PayScalePointCode]])<100,0,1) -> 0 | J69: =IF(LEN(PSPOINTS[[#This Row],[PayScalePointTitle]])<100,0,1) -> 0 | K69: =(COUNTBLANK(PSPOINTS[[#This Row],[PayScalePointCode]:[RateDateFrom]])+COUNTBLANK(PSPOINTS[[#This Row],[PayScaleRate]])) -> 0 | L69: =IF(SUBSTITUTE(TEXT(PSPOINTS[[#This Row],[PayScaleCode]],10)," ","")=TEXT(PSPOINTS[[#This Row],[PayScaleCode]],10),0,1)+IF(SUBSTITUTE(TEXT(PSPOINTS[[#This Row],[PayScalePointCode]],10)," ","")=TEXT(PSPOINTS[[#This Row],[PayScalePointCode]],10),0,1) -> 0 | M69: =SUM(PSPOINTS[[#This Row],[Scale Point Issue]:[Space in Code]]) -> 0 | N69: England & Wales | P69: NJC_CHE | Q69: =_xlfn.XLOOKUP(PSPOINTS[[#This Row],[PayScaleCode]],PayScales!N:N,PayScales!O:O) -> NJC - Cheshire East | R69: 5 | S69: 5 | T69: 5 | U69: FALSE | V69: TRUE | W69: 45748 | Y69: 25583
A70: =PSPOINTS[[#This Row],[PayScaleCode]]&PSPOINTS[[#This Row],[RateDateFrom]] -> NJC_CHE45748 | B70: =IF(A70=A69,SUM(T70-T69)-1,T70-1) -> 0 | C70: =PSPOINTS[[#This Row],[PayScaleCode]]&PSPOINTS[[#This Row],[PayScalePointCode]]&PSPOINTS[[#This Row],[RateDateFrom]] -> NJC_CHE645748 | D70: =COUNTIF(PSPOINTS[Pay Scale String Duplicates],PSPOINTS[[#This Row],[Pay Scale String Duplicates]])-1 -> 0 | E70: =IF((MONTH(_xlfn.XLOOKUP(PSPOINTS[[#This Row],[PayScaleCode]],PayScales!N:N,PayScales!R:R)))=MONTH(PSPOINTS[[#This Row],[RateDateFrom]]),0,1) -> 0 | F70: =IF(ISBLANK(PSPOINTS[[#This Row],[RateDateTo]]),0,IF(PSPOINTS[[#This Row],[RateDateFrom]]<PSPOINTS[[#This Row],[RateDateTo]],0,1)) -> 0 | G70: {=IF(CELL("format",PSPOINTS[[#This Row],[RateDateFrom]])="D1",0,1)+IF(CELL("format",PSPOINTS[[#This Row],[RateDateTo]])="D1",0,1)} -> 0 | H70: =IF(OR(PSPOINTS[[#This Row],[Hourly]]=TRUE,PSPOINTS[[#This Row],[Hourly]]=FALSE),IF(OR(PSPOINTS[[#This Row],[PayScalePointEnabled]]=TRUE,PSPOINTS[[#This Row],[PayScalePointEnabled]]=FALSE),0,1),1) -> 0 | I70: =IF(LEN(PSPOINTS[[#This Row],[PayScalePointCode]])<100,0,1) -> 0 | J70: =IF(LEN(PSPOINTS[[#This Row],[PayScalePointTitle]])<100,0,1) -> 0 | K70: =(COUNTBLANK(PSPOINTS[[#This Row],[PayScalePointCode]:[RateDateFrom]])+COUNTBLANK(PSPOINTS[[#This Row],[PayScaleRate]])) -> 0 | L70: =IF(SUBSTITUTE(TEXT(PSPOINTS[[#This Row],[PayScaleCode]],10)," ","")=TEXT(PSPOINTS[[#This Row],[PayScaleCode]],10),0,1)+IF(SUBSTITUTE(TEXT(PSPOINTS[[#This Row],[PayScalePointCode]],10)," ","")=TEXT(PSPOINTS[[#This Row],[PayScalePointCode]],10),0,1) -> 0 | M70: =SUM(PSPOINTS[[#This Row],[Scale Point Issue]:[Space in Code]]) -> 0 | N70: England & Wales | P70: NJC_CHE | Q70: =_xlfn.XLOOKUP(PSPOINTS[[#This Row],[PayScaleCode]],PayScales!N:N,PayScales!O:O) -> NJC - Cheshire East | R70: 6 | S70: 6 | T70: 6 | U70: FALSE | V70: TRUE | W70: 45748 | Y70: 25989
A71: =PSPOINTS[[#This Row],[PayScaleCode]]&PSPOINTS[[#This Row],[RateDateFrom]] -> NJC_CHE45748 | B71: =IF(A71=A70,SUM(T71-T70)-1,T71-1) -> 0 | C71: =PSPOINTS[[#This Row],[PayScaleCode]]&PSPOINTS[[#This Row],[PayScalePointCode]]&PSPOINTS[[#This Row],[RateDateFrom]] -> NJC_CHE745748 | D71: =COUNTIF(PSPOINTS[Pay Scale String Duplicates],PSPOINTS[[#This Row],[Pay Scale String Duplicates]])-1 -> 0 | E71: =IF((MONTH(_xlfn.XLOOKUP(PSPOINTS[[#This Row],[PayScaleCode]],PayScales!N:N,PayScales!R:R)))=MONTH(PSPOINTS[[#This Row],[RateDateFrom]]),0,1) -> 0 | F71: =IF(ISBLANK(PSPOINTS[[#This Row],[RateDateTo]]),0,IF(PSPOINTS[[#This Row],[RateDateFrom]]<PSPOINTS[[#This Row],[RateDateTo]],0,1)) -> 0 | G71: {=IF(CELL("format",PSPOINTS[[#This Row],[RateDateFrom]])="D1",0,1)+IF(CELL("format",PSPOINTS[[#This Row],[RateDateTo]])="D1",0,1)} -> 0 | H71: =IF(OR(PSPOINTS[[#This Row],[Hourly]]=TRUE,PSPOINTS[[#This Row],[Hourly]]=FALSE),IF(OR(PSPOINTS[[#This Row],[PayScalePointEnabled]]=TRUE,PSPOINTS[[#This Row],[PayScalePointEnabled]]=FALSE),0,1),1) -> 0 | I71: =IF(LEN(PSPOINTS[[#This Row],[PayScalePointCode]])<100,0,1) -> 0 | J71: =IF(LEN(PSPOINTS[[#This Row],[PayScalePointTitle]])<100,0,1) -> 0 | K71: =(COUNTBLANK(PSPOINTS[[#This Row],[PayScalePointCode]:[RateDateFrom]])+COUNTBLANK(PSPOINTS[[#This Row],[PayScaleRate]])) -> 0 | L71: =IF(SUBSTITUTE(TEXT(PSPOINTS[[#This Row],[PayScaleCode]],10)," ","")=TEXT(PSPOINTS[[#This Row],[PayScaleCode]],10),0,1)+IF(SUBSTITUTE(TEXT(PSPOINTS[[#This Row],[PayScalePointCode]],10)," ","")=TEXT(PSPOINTS[[#This Row],[PayScalePointCode]],10),0,1) -> 0 | M71: =SUM(PSPOINTS[[#This Row],[Scale Point Issue]:[Space in Code]]) -> 0 | N71: England & Wales | P71: NJC_CHE | Q71: =_xlfn.XLOOKUP(PSPOINTS[[#This Row],[PayScaleCode]],PayScales!N:N,PayScales!O:O) -> NJC - Cheshire East | R71: 7 | S71: 7 | T71: 7 | U71: FALSE | V71: TRUE | W71: 45748 | Y71: 26403
A72: =PSPOINTS[[#This Row],[PayScaleCode]]&PSPOINTS[[#This Row],[RateDateFrom]] -> NJC_CHE45748 | B72: =IF(A72=A71,SUM(T72-T71)-1,T72-1) -> 0 | C72: =PSPOINTS[[#This Row],[PayScaleCode]]&PSPOINTS[[#This Row],[PayScalePointCode]]&PSPOINTS[[#This Row],[RateDateFrom]] -> NJC_CHE845748 | D72: =COUNTIF(PSPOINTS[Pay Scale String Duplicates],PSPOINTS[[#This Row],[Pay Scale String Duplicates]])-1 -> 0 | E72: =IF((MONTH(_xlfn.XLOOKUP(PSPOINTS[[#This Row],[PayScaleCode]],PayScales!N:N,PayScales!R:R)))=MONTH(PSPOINTS[[#This Row],[RateDateFrom]]),0,1) -> 0 | F72: =IF(ISBLANK(PSPOINTS[[#This Row],[RateDateTo]]),0,IF(PSPOINTS[[#This Row],[RateDateFrom]]<PSPOINTS[[#This Row],[RateDateTo]],0,1)) -> 0 | G72: {=IF(CELL("format",PSPOINTS[[#This Row],[RateDateFrom]])="D1",0,1)+IF(CELL("format",PSPOINTS[[#This Row],[RateDateTo]])="D1",0,1)} -> 0 | H72: =IF(OR(PSPOINTS[[#This Row],[Hourly]]=TRUE,PSPOINTS[[#This Row],[Hourly]]=FALSE),IF(OR(PSPOINTS[[#This Row],[PayScalePointEnabled]]=TRUE,PSPOINTS[[#This Row],[PayScalePointEnabled]]=FALSE),0,1),1) -> 0 | I72: =IF(LEN(PSPOINTS[[#This Row],[PayScalePointCode]])<100,0,1) -> 0 | J72: =IF(LEN(PSPOINTS[[#This Row],[PayScalePointTitle]])<100,0,1) -> 0 | K72: =(COUNTBLANK(PSPOINTS[[#This Row],[PayScalePointCode]:[RateDateFrom]])+COUNTBLANK(PSPOINTS[[#This Row],[PayScaleRate]])) -> 0 | L72: =IF(SUBSTITUTE(TEXT(PSPOINTS[[#This Row],[PayScaleCode]],10)," ","")=TEXT(PSPOINTS[[#This Row],[PayScaleCode]],10),0,1)+IF(SUBSTITUTE(TEXT(PSPOINTS[[#This Row],[PayScalePointCode]],10)," ","")=TEXT(PSPOINTS[[#This Row],[PayScalePointCode]],10),0,1) -> 0 | M72: =SUM(PSPOINTS[[#This Row],[Scale Point Issue]:[Space in Code]]) -> 0 | N72: England & Wales | P72: NJC_CHE | Q72: =_xlfn.XLOOKUP(PSPOINTS[[#This Row],[PayScaleCode]],PayScales!N:N,PayScales!O:O) -> NJC - Cheshire East | R72: 8 | S72: 8 | T72: 8 | U72: FALSE | V72: TRUE | W72: 45748 | Y72: 26824
A73: =PSPOINTS[[#This Row],[PayScaleCode]]&PSPOINTS[[#This Row],[RateDateFrom]] -> NJC_CHE45748 | B73: =IF(A73=A72,SUM(T73-T72)-1,T73-1) -> 0 | C73: =PSPOINTS[[#This Row],[PayScaleCode]]&PSPOINTS[[#This Row],[PayScalePointCode]]&PSPOINTS[[#This Row],[RateDateFrom]] -> NJC_CHE945748 | D73: =COUNTIF(PSPOINTS[Pay Scale String Duplicates],PSPOINTS[[#This Row],[Pay Scale String Duplicates]])-1 -> 0 | E73: =IF((MONTH(_xlfn.XLOOKUP(PSPOINTS[[#This Row],[PayScaleCode]],PayScales!N:N,PayScales!R:R)))=MONTH(PSPOINTS[[#This Row],[RateDateFrom]]),0,1) -> 0 | F73: =IF(ISBLANK(PSPOINTS[[#This Row],[RateDateTo]]),0,IF(PSPOINTS[[#This Row],[RateDateFrom]]<PSPOINTS[[#This Row],[RateDateTo]],0,1)) -> 0 | G73: {=IF(CELL("format",PSPOINTS[[#This Row],[RateDateFrom]])="D1",0,1)+IF(CELL("format",PSPOINTS[[#This Row],[RateDateTo]])="D1",0,1)} -> 0 | H73: =IF(OR(PSPOINTS[[#This Row],[Hourly]]=TRUE,PSPOINTS[[#This Row],[Hourly]]=FALSE),IF(OR(PSPOINTS[[#This Row],[PayScalePointEnabled]]=TRUE,PSPOINTS[[#This Row],[PayScalePointEnabled]]=FALSE),0,1),1) -> 0 | I73: =IF(LEN(PSPOINTS[[#This Row],[PayScalePointCode]])<100,0,1) -> 0 | J73: =IF(LEN(PSPOINTS[[#This Row],[PayScalePointTitle]])<100,0,1) -> 0 | K73: =(COUNTBLANK(PSPOINTS[[#This Row],[PayScalePointCode]:[RateDateFrom]])+COUNTBLANK(PSPOINTS[[#This Row],[PayScaleRate]])) -> 0 | L73: =IF(SUBSTITUTE(TEXT(PSPOINTS[[#This Row],[PayScaleCode]],10)," ","")=TEXT(PSPOINTS[[#This Row],[PayScaleCode]],10),0,1)+IF(SUBSTITUTE(TEXT(PSPOINTS[[#This Row],[PayScalePointCode]],10)," ","")=TEXT(PSPOINTS[[#This Row],[PayScalePointCode]],10),0,1) -> 0 | M73: =SUM(PSPOINTS[[#This Row],[Scale Point Issue]:[Space in Code]]) -> 0 | N73: England & Wales | P73: NJC_CHE | Q73: =_xlfn.XLOOKUP(PSPOINTS[[#This Row],[PayScaleCode]],PayScales!N:N,PayScales!O:O) -> NJC - Cheshire East | R73: 9 | S73: 9 | T73: 9 | U73: FALSE | V73: TRUE | W73: 45748 | Y73: 27254
A74: =PSPOINTS[[#This Row],[PayScaleCode]]&PSPOINTS[[#This Row],[RateDateFrom]] -> NJC_CHE45748 | B74: =IF(A74=A73,SUM(T74-T73)-1,T74-1) -> 0 | C74: =PSPOINTS[[#This Row],[PayScaleCode]]&PSPOINTS[[#This Row],[PayScalePointCode]]&PSPOINTS[[#This Row],[RateDateFrom]] -> NJC_CHE1045748 | D74: =COUNTIF(PSPOINTS[Pay Scale String Duplicates],PSPOINTS[[#This Row],[Pay Scale String Duplicates]])-1 -> 0 | E74: =IF((MONTH(_xlfn.XLOOKUP(PSPOINTS[[#This Row],[PayScaleCode]],PayScales!N:N,PayScales!R:R)))=MONTH(PSPOINTS[[#This Row],[RateDateFrom]]),0,1) -> 0 | F74: =IF(ISBLANK(PSPOINTS[[#This Row],[RateDateTo]]),0,IF(PSPOINTS[[#This Row],[RateDateFrom]]<PSPOINTS[[#This Row],[RateDateTo]],0,1)) -> 0 | G74: {=IF(CELL("format",PSPOINTS[[#This Row],[RateDateFrom]])="D1",0,1)+IF(CELL("format",PSPOINTS[[#This Row],[RateDateTo]])="D1",0,1)} -> 0 | H74: =IF(OR(PSPOINTS[[#This Row],[Hourly]]=TRUE,PSPOINTS[[#This Row],[Hourly]]=FALSE),IF(OR(PSPOINTS[[#This Row],[PayScalePointEnabled]]=TRUE,PSPOINTS[[#This Row],[PayScalePointEnabled]]=FALSE),0,1),1) -> 0 | I74: =IF(LEN(PSPOINTS[[#This Row],[PayScalePointCode]])<100,0,1) -> 0 | J74: =IF(LEN(PSPOINTS[[#This Row],[PayScalePointTitle]])<100,0,1) -> 0 | K74: =(COUNTBLANK(PSPOINTS[[#This Row],[PayScalePointCode]:[RateDateFrom]])+COUNTBLANK(PSPOINTS[[#This Row],[PayScaleRate]])) -> 0 | L74: =IF(SUBSTITUTE(TEXT(PSPOINTS[[#This Row],[PayScaleCode]],10)," ","")=TEXT(PSPOINTS[[#This Row],[PayScaleCode]],10),0,1)+IF(SUBSTITUTE(TEXT(PSPOINTS[[#This Row],[PayScalePointCode]],10)," ","")=TEXT(PSPOINTS[[#This Row],[PayScalePointCode]],10),0,1) -> 0 | M74: =SUM(PSPOINTS[[#This Row],[Scale Point Issue]:[Space in Code]]) -> 0 | N74: England & Wales | P74: NJC_CHE | Q74: =_xlfn.XLOOKUP(PSPOINTS[[#This Row],[PayScaleCode]],PayScales!N:N,PayScales!O:O) -> NJC - Cheshire East | R74: 10 | S74: 10 | T74: 10 | U74: FALSE | V74: TRUE | W74: 45748 | Y74: 27694
A75: =PSPOINTS[[#This Row],[PayScaleCode]]&PSPOINTS[[#This Row],[RateDateFrom]] -> NJC_CHE45748 | B75: =IF(A75=A74,SUM(T75-T74)-1,T75-1) -> 0 | C75: =PSPOINTS[[#This Row],[PayScaleCode]]&PSPOINTS[[#This Row],[PayScalePointCode]]&PSPOINTS[[#This Row],[RateDateFrom]] -> NJC_CHE1145748 | D75: =COUNTIF(PSPOINTS[Pay Scale String Duplicates],PSPOINTS[[#This Row],[Pay Scale String Duplicates]])-1 -> 0 | E75: =IF((MONTH(_xlfn.XLOOKUP(PSPOINTS[[#This Row],[PayScaleCode]],PayScales!N:N,PayScales!R:R)))=MONTH(PSPOINTS[[#This Row],[RateDateFrom]]),0,1) -> 0 | F75: =IF(ISBLANK(PSPOINTS[[#This Row],[RateDateTo]]),0,IF(PSPOINTS[[#This Row],[RateDateFrom]]<PSPOINTS[[#This Row],[RateDateTo]],0,1)) -> 0 | G75: {=IF(CELL("format",PSPOINTS[[#This Row],[RateDateFrom]])="D1",0,1)+IF(CELL("format",PSPOINTS[[#This Row],[RateDateTo]])="D1",0,1)} -> 0 | H75: =IF(OR(PSPOINTS[[#This Row],[Hourly]]=TRUE,PSPOINTS[[#This Row],[Hourly]]=FALSE),IF(OR(PSPOINTS[[#This Row],[PayScalePointEnabled]]=TRUE,PSPOINTS[[#This Row],[PayScalePointEnabled]]=FALSE),0,1),1) -> 0 | I75: =IF(LEN(PSPOINTS[[#This Row],[PayScalePointCode]])<100,0,1) -> 0 | J75: =IF(LEN(PSPOINTS[[#This Row],[PayScalePointTitle]])<100,0,1) -> 0 | K75: =(COUNTBLANK(PSPOINTS[[#This Row],[PayScalePointCode]:[RateDateFrom]])+COUNTBLANK(PSPOINTS[[#This Row],[PayScaleRate]])) -> 0 | L75: =IF(SUBSTITUTE(TEXT(PSPOINTS[[#This Row],[PayScaleCode]],10)," ","")=TEXT(PSPOINTS[[#This Row],[PayScaleCode]],10),0,1)+IF(SUBSTITUTE(TEXT(PSPOINTS[[#This Row],[PayScalePointCode]],10)," ","")=TEXT(PSPOINTS[[#This Row],[PayScalePointCode]],10),0,1) -> 0 | M75: =SUM(PSPOINTS[[#This Row],[Scale Point Issue]:[Space in Code]]) -> 0 | N75: England & Wales | P75: NJC_CHE | Q75: =_xlfn.XLOOKUP(PSPOINTS[[#This Row],[PayScaleCode]],PayScales!N:N,PayScales!O:O) -> NJC - Cheshire East | R75: 11 | S75: 11 | T75: 11 | U75: FALSE | V75: TRUE | W75: 45748 | Y75: 28142
A76: =PSPOINTS[[#This Row],[PayScaleCode]]&PSPOINTS[[#This Row],[RateDateFrom]] -> NJC_CHE45748 | B76: =IF(A76=A75,SUM(T76-T75)-1,T76-1) -> 0 | C76: =PSPOINTS[[#This Row],[PayScaleCode]]&PSPOINTS[[#This Row],[PayScalePointCode]]&PSPOINTS[[#This Row],[RateDateFrom]] -> NJC_CHE1245748 | D76: =COUNTIF(PSPOINTS[Pay Scale String Duplicates],PSPOINTS[[#This Row],[Pay Scale String Duplicates]])-1 -> 0 | E76: =IF((MONTH(_xlfn.XLOOKUP(PSPOINTS[[#This Row],[PayScaleCode]],PayScales!N:N,PayScales!R:R)))=MONTH(PSPOINTS[[#This Row],[RateDateFrom]]),0,1) -> 0 | F76: =IF(ISBLANK(PSPOINTS[[#This Row],[RateDateTo]]),0,IF(PSPOINTS[[#This Row],[RateDateFrom]]<PSPOINTS[[#This Row],[RateDateTo]],0,1)) -> 0 | G76: {=IF(CELL("format",PSPOINTS[[#This Row],[RateDateFrom]])="D1",0,1)+IF(CELL("format",PSPOINTS[[#This Row],[RateDateTo]])="D1",0,1)} -> 0 | H76: =IF(OR(PSPOINTS[[#This Row],[Hourly]]=TRUE,PSPOINTS[[#This Row],[Hourly]]=FALSE),IF(OR(PSPOINTS[[#This Row],[PayScalePointEnabled]]=TRUE,PSPOINTS[[#This Row],[PayScalePointEnabled]]=FALSE),0,1),1) -> 0 | I76: =IF(LEN(PSPOINTS[[#This Row],[PayScalePointCode]])<100,0,1) -> 0 | J76: =IF(LEN(PSPOINTS[[#This Row],[PayScalePointTitle]])<100,0,1) -> 0 | K76: =(COUNTBLANK(PSPOINTS[[#This Row],[PayScalePointCode]:[RateDateFrom]])+COUNTBLANK(PSPOINTS[[#This Row],[PayScaleRate]])) -> 0 | L76: =IF(SUBSTITUTE(TEXT(PSPOINTS[[#This Row],[PayScaleCode]],10)," ","")=TEXT(PSPOINTS[[#This Row],[PayScaleCode]],10),0,1)+IF(SUBSTITUTE(TEXT(PSPOINTS[[#This Row],[PayScalePointCode]],10)," ","")=TEXT(PSPOINTS[[#This Row],[PayScalePointCode]],10),0,1) -> 0 | M76: =SUM(PSPOINTS[[#This Row],[Scale Point Issue]:[Space in Code]]) -> 0 | N76: England & Wales | P76: NJC_CHE | Q76: =_xlfn.XLOOKUP(PSPOINTS[[#This Row],[PayScaleCode]],PayScales!N:N,PayScales!O:O) -> NJC - Cheshire East | R76: 12 | S76: 12 | T76: 12 | U76: FALSE | V76: TRUE | W76: 45748 | Y76: 28598
... A109: =PSPOINTS[[#This Row],[PayScaleCode]]&PSPOINTS[[#This Row],[RateDateFrom]] -> NJC_CHE45748 | B109: =IF(A109=A108,SUM(T109-T108)-1,T109-1) -> 0 | C109: =PSPOINTS[[#This Row],[PayScaleCode]]&PSPOINTS[[#This Row],[PayScalePointCode]]&PSPOINTS[[#This Row],[RateDateFrom]] -> NJC_CHE4545748 | D109: =COUNTIF(PSPOINTS[Pay Scale String Duplicates],PSPOINTS[[#This Row],[Pay Scale String Duplicates]])-1 -> 0 | E109: =IF((MONTH(_xlfn.XLOOKUP(PSPOINTS[[#This Row],[PayScaleCode]],PayScales!N:N,PayScales!R:R)))=MONTH(PSPOINTS[[#This Row],[RateDateFrom]]),0,1) -> 0 | F109: =IF(ISBLANK(PSPOINTS[[#This Row],[RateDateTo]]),0,IF(PSPOINTS[[#This Row],[RateDateFrom]]<PSPOINTS[[#This Row],[RateDateTo]],0,1)) -> 0 | G109: {=IF(CELL("format",PSPOINTS[[#This Row],[RateDateFrom]])="D1",0,1)+IF(CELL("format",PSPOINTS[[#This Row],[RateDateTo]])="D1",0,1)} -> 0 | H109: =IF(OR(PSPOINTS[[#This Row],[Hourly]]=TRUE,PSPOINTS[[#This Row],[Hourly]]=FALSE),IF(OR(PSPOINTS[[#This Row],[PayScalePointEnabled]]=TRUE,PSPOINTS[[#This Row],[PayScalePointEnabled]]=FALSE),0,1),1) -> 0 | I109: =IF(LEN(PSPOINTS[[#This Row],[PayScalePointCode]])<100,0,1) -> 0 | J109: =IF(LEN(PSPOINTS[[#This Row],[PayScalePointTitle]])<100,0,1) -> 0 | K109: =(COUNTBLANK(PSPOINTS[[#This Row],[PayScalePointCode]:[RateDateFrom]])+COUNTBLANK(PSPOINTS[[#This Row],[PayScaleRate]])) -> 0 | L109: =IF(SUBSTITUTE(TEXT(PSPOINTS[[#This Row],[PayScaleCode]],10)," ","")=TEXT(PSPOINTS[[#This Row],[PayScaleCode]],10),0,1)+IF(SUBSTITUTE(TEXT(PSPOINTS[[#This Row],[PayScalePointCode]],10)," ","")=TEXT(PSPOINTS[[#This Row],[PayScalePointCode]],10),0,1) -> 0 | M109: =SUM(PSPOINTS[[#This Row],[Scale Point Issue]:[Space in Code]]) -> 0 | N109: England & Wales | P109: NJC_CHE | Q109: =_xlfn.XLOOKUP(PSPOINTS[[#This Row],[PayScaleCode]],PayScales!N:N,PayScales!O:O) -> NJC - Cheshire East | R109: 45 | S109: 45 | T109: 45 | U109: FALSE | V109: TRUE | W109: 45748 | Y109: 63688
A110: =PSPOINTS[[#This Row],[PayScaleCode]]&PSPOINTS[[#This Row],[RateDateFrom]] -> APP_NMW45748 | B110: =IF(A110=A109,SUM(T110-T109)-1,T110-1) -> 0 | C110: =PSPOINTS[[#This Row],[PayScaleCode]]&PSPOINTS[[#This Row],[PayScalePointCode]]&PSPOINTS[[#This Row],[RateDateFrom]] -> APP_NMWY145748 | D110: =COUNTIF(PSPOINTS[Pay Scale String Duplicates],PSPOINTS[[#This Row],[Pay Scale String Duplicates]])-1 -> 0 | E110: =IF((MONTH(_xlfn.XLOOKUP(PSPOINTS[[#This Row],[PayScaleCode]],PayScales!N:N,PayScales!R:R)))=MONTH(PSPOINTS[[#This Row],[RateDateFrom]]),0,1) -> 0 | F110: =IF(ISBLANK(PSPOINTS[[#This Row],[RateDateTo]]),0,IF(PSPOINTS[[#This Row],[RateDateFrom]]<PSPOINTS[[#This Row],[RateDateTo]],0,1)) -> 0 | G110: {=IF(CELL("format",PSPOINTS[[#This Row],[RateDateFrom]])="D1",0,1)+IF(CELL("format",PSPOINTS[[#This Row],[RateDateTo]])="D1",0,1)} -> 0 | H110: =IF(OR(PSPOINTS[[#This Row],[Hourly]]=TRUE,PSPOINTS[[#This Row],[Hourly]]=FALSE),IF(OR(PSPOINTS[[#This Row],[PayScalePointEnabled]]=TRUE,PSPOINTS[[#This Row],[PayScalePointEnabled]]=FALSE),0,1),1) -> 0 | I110: =IF(LEN(PSPOINTS[[#This Row],[PayScalePointCode]])<100,0,1) -> 0 | J110: =IF(LEN(PSPOINTS[[#This Row],[PayScalePointTitle]])<100,0,1) -> 0 | K110: =(COUNTBLANK(PSPOINTS[[#This Row],[PayScalePointCode]:[RateDateFrom]])+COUNTBLANK(PSPOINTS[[#This Row],[PayScaleRate]])) -> 0 | L110: =IF(SUBSTITUTE(TEXT(PSPOINTS[[#This Row],[PayScaleCode]],10)," ","")=TEXT(PSPOINTS[[#This Row],[PayScaleCode]],10),0,1)+IF(SUBSTITUTE(TEXT(PSPOINTS[[#This Row],[PayScalePointCode]],10)," ","")=TEXT(PSPOINTS[[#This Row],[PayScalePointCode]],10),0,1) -> 0 | M110: =SUM(PSPOINTS[[#This Row],[Scale Point Issue]:[Space in Code]]) -> 0 | N110: England & Wales | P110: APP_NMW | Q110: =_xlfn.XLOOKUP(PSPOINTS[[#This Row],[PayScaleCode]],PayScales!N:N,PayScales!O:O) -> Apprentice / NMW Scale | R110: Y1 | S110: Y1 | T110: 1 | U110: FALSE | V110: TRUE | W110: 45748 | Y110: 14566 | AA110: £7.55 / hour*37*52.143
A111: =PSPOINTS[[#This Row],[PayScaleCode]]&PSPOINTS[[#This Row],[RateDateFrom]] -> APP_NMW45748 | B111: =IF(A111=A110,SUM(T111-T110)-1,T111-1) -> 0 | C111: =PSPOINTS[[#This Row],[PayScaleCode]]&PSPOINTS[[#This Row],[PayScalePointCode]]&PSPOINTS[[#This Row],[RateDateFrom]] -> APP_NMW<1845748 | D111: =COUNTIF(PSPOINTS[Pay Scale String Duplicates],PSPOINTS[[#This Row],[Pay Scale String Duplicates]])-1 -> 0 | E111: =IF((MONTH(_xlfn.XLOOKUP(PSPOINTS[[#This Row],[PayScaleCode]],PayScales!N:N,PayScales!R:R)))=MONTH(PSPOINTS[[#This Row],[RateDateFrom]]),0,1) -> 0 | F111: =IF(ISBLANK(PSPOINTS[[#This Row],[RateDateTo]]),0,IF(PSPOINTS[[#This Row],[RateDateFrom]]<PSPOINTS[[#This Row],[RateDateTo]],0,1)) -> 0 | G111: {=IF(CELL("format",PSPOINTS[[#This Row],[RateDateFrom]])="D1",0,1)+IF(CELL("format",PSPOINTS[[#This Row],[RateDateTo]])="D1",0,1)} -> 0 | H111: =IF(OR(PSPOINTS[[#This Row],[Hourly]]=TRUE,PSPOINTS[[#This Row],[Hourly]]=FALSE),IF(OR(PSPOINTS[[#This Row],[PayScalePointEnabled]]=TRUE,PSPOINTS[[#This Row],[PayScalePointEnabled]]=FALSE),0,1),1) -> 0 | I111: =IF(LEN(PSPOINTS[[#This Row],[PayScalePointCode]])<100,0,1) -> 0 | J111: =IF(LEN(PSPOINTS[[#This Row],[PayScalePointTitle]])<100,0,1) -> 0 | K111: =(COUNTBLANK(PSPOINTS[[#This Row],[PayScalePointCode]:[RateDateFrom]])+COUNTBLANK(PSPOINTS[[#This Row],[PayScaleRate]])) -> 0 | L111: =IF(SUBSTITUTE(TEXT(PSPOINTS[[#This Row],[PayScaleCode]],10)," ","")=TEXT(PSPOINTS[[#This Row],[PayScaleCode]],10),0,1)+IF(SUBSTITUTE(TEXT(PSPOINTS[[#This Row],[PayScalePointCode]],10)," ","")=TEXT(PSPOINTS[[#This Row],[PayScalePointCode]],10),0,1) -> 0 | M111: =SUM(PSPOINTS[[#This Row],[Scale Point Issue]:[Space in Code]]) -> 0 | N111: England & Wales | P111: APP_NMW | Q111: =_xlfn.XLOOKUP(PSPOINTS[[#This Row],[PayScaleCode]],PayScales!N:N,PayScales!O:O) -> Apprentice / NMW Scale | R111: <18 | S111: <18 | T111: 2 | U111: FALSE | V111: TRUE | W111: 45748 | Y111: 14566 | AA111: £7.55 / hour*37*52.143
A112: =PSPOINTS[[#This Row],[PayScaleCode]]&PSPOINTS[[#This Row],[RateDateFrom]] -> APP_NMW45748 | B112: =IF(A112=A111,SUM(T112-T111)-1,T112-1) -> 0 | C112: =PSPOINTS[[#This Row],[PayScaleCode]]&PSPOINTS[[#This Row],[PayScalePointCode]]&PSPOINTS[[#This Row],[RateDateFrom]] -> APP_NMW18-2045748 | D112: =COUNTIF(PSPOINTS[Pay Scale String Duplicates],PSPOINTS[[#This Row],[Pay Scale String Duplicates]])-1 -> 0 | E112: =IF((MONTH(_xlfn.XLOOKUP(PSPOINTS[[#This Row],[PayScaleCode]],PayScales!N:N,PayScales!R:R)))=MONTH(PSPOINTS[[#This Row],[RateDateFrom]]),0,1) -> 0 | F112: =IF(ISBLANK(PSPOINTS[[#This Row],[RateDateTo]]),0,IF(PSPOINTS[[#This Row],[RateDateFrom]]<PSPOINTS[[#This Row],[RateDateTo]],0,1)) -> 0 | G112: {=IF(CELL("format",PSPOINTS[[#This Row],[RateDateFrom]])="D1",0,1)+IF(CELL("format",PSPOINTS[[#This Row],[RateDateTo]])="D1",0,1)} -> 0 | H112: =IF(OR(PSPOINTS[[#This Row],[Hourly]]=TRUE,PSPOINTS[[#This Row],[Hourly]]=FALSE),IF(OR(PSPOINTS[[#This Row],[PayScalePointEnabled]]=TRUE,PSPOINTS[[#This Row],[PayScalePointEnabled]]=FALSE),0,1),1) -> 0 | I112: =IF(LEN(PSPOINTS[[#This Row],[PayScalePointCode]])<100,0,1) -> 0 | J112: =IF(LEN(PSPOINTS[[#This Row],[PayScalePointTitle]])<100,0,1) -> 0 | K112: =(COUNTBLANK(PSPOINTS[[#This Row],[PayScalePointCode]:[RateDateFrom]])+COUNTBLANK(PSPOINTS[[#This Row],[PayScaleRate]])) -> 0 | L112: =IF(SUBSTITUTE(TEXT(PSPOINTS[[#This Row],[PayScaleCode]],10)," ","")=TEXT(PSPOINTS[[#This Row],[PayScaleCode]],10),0,1)+IF(SUBSTITUTE(TEXT(PSPOINTS[[#This Row],[PayScalePointCode]],10)," ","")=TEXT(PSPOINTS[[#This Row],[PayScalePointCode]],10),0,1) -> 0 | M112: =SUM(PSPOINTS[[#This Row],[Scale Point Issue]:[Space in Code]]) -> 0 | N112: England & Wales | P112: APP_NMW | Q112: =_xlfn.XLOOKUP(PSPOINTS[[#This Row],[PayScaleCode]],PayScales!N:N,PayScales!O:O) -> Apprentice / NMW Scale | R112: 18-20 | S112: 18-20 | T112: 3 | U112: FALSE | V112: TRUE | W112: 45748 | Y112: 19293 | AA112: £10.00 / hour*37*52.143
A113: =PSPOINTS[[#This Row],[PayScaleCode]]&PSPOINTS[[#This Row],[RateDateFrom]] -> APP_NMW45748 | B113: =IF(A113=A112,SUM(T113-T112)-1,T113-1) -> 0 | C113: =PSPOINTS[[#This Row],[PayScaleCode]]&PSPOINTS[[#This Row],[PayScalePointCode]]&PSPOINTS[[#This Row],[RateDateFrom]] -> APP_NMW>2145748 | D113: =COUNTIF(PSPOINTS[Pay Scale String Duplicates],PSPOINTS[[#This Row],[Pay Scale String Duplicates]])-1 -> 0 | E113: =IF((MONTH(_xlfn.XLOOKUP(PSPOINTS[[#This Row],[PayScaleCode]],PayScales!N:N,PayScales!R:R)))=MONTH(PSPOINTS[[#This Row],[RateDateFrom]]),0,1) -> 0 | F113: =IF(ISBLANK(PSPOINTS[[#This Row],[RateDateTo]]),0,IF(PSPOINTS[[#This Row],[RateDateFrom]]<PSPOINTS[[#This Row],[RateDateTo]],0,1)) -> 0 | G113: {=IF(CELL("format",PSPOINTS[[#This Row],[RateDateFrom]])="D1",0,1)+IF(CELL("format",PSPOINTS[[#This Row],[RateDateTo]])="D1",0,1)} -> 0 | H113: =IF(OR(PSPOINTS[[#This Row],[Hourly]]=TRUE,PSPOINTS[[#This Row],[Hourly]]=FALSE),IF(OR(PSPOINTS[[#This Row],[PayScalePointEnabled]]=TRUE,PSPOINTS[[#This Row],[PayScalePointEnabled]]=FALSE),0,1),1) -> 0 | I113: =IF(LEN(PSPOINTS[[#This Row],[PayScalePointCode]])<100,0,1) -> 0 | J113: =IF(LEN(PSPOINTS[[#This Row],[PayScalePointTitle]])<100,0,1) -> 0 | K113: =(COUNTBLANK(PSPOINTS[[#This Row],[PayScalePointCode]:[RateDateFrom]])+COUNTBLANK(PSPOINTS[[#This Row],[PayScaleRate]])) -> 0 | L113: =IF(SUBSTITUTE(TEXT(PSPOINTS[[#This Row],[PayScaleCode]],10)," ","")=TEXT(PSPOINTS[[#This Row],[PayScaleCode]],10),0,1)+IF(SUBSTITUTE(TEXT(PSPOINTS[[#This Row],[PayScalePointCode]],10)," ","")=TEXT(PSPOINTS[[#This Row],[PayScalePointCode]],10),0,1) -> 0 | M113: =SUM(PSPOINTS[[#This Row],[Scale Point Issue]:[Space in Code]]) -> 0 | N113: England & Wales | P113: APP_NMW | Q113: =_xlfn.XLOOKUP(PSPOINTS[[#This Row],[PayScaleCode]],PayScales!N:N,PayScales!O:O) -> Apprentice / NMW Scale | R113: >21 | S113: >21 | T113: 4 | U113: FALSE | V113: TRUE | W113: 45748 | Y113: 23557 | AA113: £12.21 / hour*37*52.143

Sheet PayScaleGrades
A1: Pay Scale issue | B1: Duplicate Grade Code | C1: Schools Check | D1: Scale Point Number From/To Issue | E1: PayScaleGrade and PayScaleCode Available to School | F1: TRUE /FALSE Typo | G1: Blank in column | H1: Code Length | I1: Title Length | J1: Space in Code | K1: Will Import if 0 | L1: London Weighting | M1: ScenarioCode | N1: PayScaleGradeCode | O1: Title | P1: PayScaleCode | Q1: Point From (Check) | R1: Point To (Check) | S1: ScalePointNumberFrom | T1: ScalePointNumberTo | U1: AvailableToAllSchools | V1: SchoolCodes | W1: PayScaleGradeEnabled
A2: =IF(COUNTIF(PayScales!N:N,PayScaleGrades!P2)>0,"0","1") -> 0 | B2: =COUNTIF(GRADES[PayScaleGradeCode],GRADES[[#This Row],[PayScaleGradeCode]])-1 -> 0 | C2: {=IF(GRADES[[#This Row],[AvailableToAllSchools]]=FALSE,IF(ISBLANK(GRADES[[#This Row],[SchoolCodes]]),1,IF(AND(COUNTIF(SCHOOLS[SchoolCode],_xlfn.TEXTSPLIT(GRADES[[#This Row],[SchoolCodes]],","))),0,1)),IF(GRADES[[#This Row],[AvailableToAllSchools]]=TRUE,IF(ISBLANK(GRADES[[#This Row],[SchoolCodes]]),0,1)))} -> 0 | E2: {=IF(_xlfn.XLOOKUP(GRADES[[#This Row],[PayScaleCode]],PAYSCALES[PayScaleCode],PAYSCALES[AvailableToAllSchools])=TRUE,0,IF(GRADES[[#This Row],[AvailableToAllSchools]]=TRUE,1,IF(_xlfn.LET(_xlpm.sourceCodes, _xlfn.TEXTSPLIT(GRADES[[#This Row],[SchoolCodes]], ","),_xlpm.targetCodes, _xlfn.TEXTSPLIT(_xlfn.XLOOKUP(GRADES[[#This Row],[PayScaleCode]],PAYSCALES[PayScaleCode],PAYSCALES[SchoolCodes],1), ","),_xlpm.trimmedSource, TRIM(_xlpm.sourceCodes),_xlpm.trimmedTarget, TRIM(_xlpm.targetCodes),_xlpm.matches, ISNUMBER(MATCH(_xlpm.trimmedSource, _xlpm.trimmedTarget, 0)),AND(_xlpm.matches))=TRUE,0,1)))} -> 0 | F2: =IF(OR(GRADES[[#This Row],[AvailableToAllSchools]]=TRUE,GRADES[[#This Row],[AvailableToAllSchools]]=FALSE),IF(OR(GRADES[[#This Row],[PayScaleGradeEnabled]]=TRUE,GRADES[[#This Row],[PayScaleGradeEnabled]]=FALSE),0,1),1) -> 0 | G2: =(COUNTBLANK(GRADES[[#This Row],[PayScaleGradeCode]:[AvailableToAllSchools]])+COUNTBLANK(GRADES[[#This Row],[PayScaleGradeEnabled]])) -> 0 | H2: =IF(LEN(GRADES[[#This Row],[PayScaleGradeCode]])<100,0,1) -> 0 | I2: =IF(LEN(GRADES[[#This Row],[Title]])<100,0,1) -> 0 | J2: =IF(SUBSTITUTE(TEXT(GRADES[[#This Row],[PayScaleGradeCode]],10)," ","")=TEXT(GRADES[[#This Row],[PayScaleGradeCode]],10),0,1) -> 0 | K2: =SUM(GRADES[[#This Row],[Pay Scale issue]:[Schools Check]],GRADES[[#This Row],[TRUE /FALSE Typo]:[Space in Code]]) -> 0 | L2: =_xlfn.XLOOKUP(GRADES[[#This Row],[PayScaleCode]],PAYSCALES[PayScaleCode],PAYSCALES[London Weighting]) -> England & Wales | N2: MAIN_UPS | O2: Teachers Main through UPS | P2: MAIN | Q2: M1 | R2: U3 | S2: {=LOOKUP(2,1/(PSPOINTS[PayScaleCode]=GRADES[[#This Row],[PayScaleCode]])/(PSPOINTS[PayScalePointCode]=GRADES[[#This Row],[Point From (Check)]]),(PSPOINTS[ScalePointNumber]))} -> 1 | T2: {=LOOKUP(2,1/(PSPOINTS[PayScaleCode]=GRADES[[#This Row],[PayScaleCode]])/(PSPOINTS[PayScalePointCode]=GRADES[[#This Row],[Point To (Check)]]),(PSPOINTS[ScalePointNumber]))} -> 9 | U2: TRUE | W2: TRUE
A3: =IF(COUNTIF(PayScales!N:N,PayScaleGrades!P3)>0,"0","1") -> 0 | B3: =COUNTIF(GRADES[PayScaleGradeCode],GRADES[[#This Row],[PayScaleGradeCode]])-1 -> 0 | C3: {=IF(GRADES[[#This Row],[AvailableToAllSchools]]=FALSE,IF(ISBLANK(GRADES[[#This Row],[SchoolCodes]]),1,IF(AND(COUNTIF(SCHOOLS[SchoolCode],_xlfn.TEXTSPLIT(GRADES[[#This Row],[SchoolCodes]],","))),0,1)),IF(GRADES[[#This Row],[AvailableToAllSchools]]=TRUE,IF(ISBLANK(GRADES[[#This Row],[SchoolCodes]]),0,1)))} -> 0 | E3: {=IF(_xlfn.XLOOKUP(GRADES[[#This Row],[PayScaleCode]],PAYSCALES[PayScaleCode],PAYSCALES[AvailableToAllSchools])=TRUE,0,IF(GRADES[[#This Row],[AvailableToAllSchools]]=TRUE,1,IF(_xlfn.LET(_xlpm.sourceCodes, _xlfn.TEXTSPLIT(GRADES[[#This Row],[SchoolCodes]], ","),_xlpm.targetCodes, _xlfn.TEXTSPLIT(_xlfn.XLOOKUP(GRADES[[#This Row],[PayScaleCode]],PAYSCALES[PayScaleCode],PAYSCALES[SchoolCodes],1), ","),_xlpm.trimmedSource, TRIM(_xlpm.sourceCodes),_xlpm.trimmedTarget, TRIM(_xlpm.targetCodes),_xlpm.matches, ISNUMBER(MATCH(_xlpm.trimmedSource, _xlpm.trimmedTarget, 0)),AND(_xlpm.matches))=TRUE,0,1)))} -> 0 | F3: =IF(OR(GRADES[[#This Row],[AvailableToAllSchools]]=TRUE,GRADES[[#This Row],[AvailableToAllSchools]]=FALSE),IF(OR(GRADES[[#This Row],[PayScaleGradeEnabled]]=TRUE,GRADES[[#This Row],[PayScaleGradeEnabled]]=FALSE),0,1),1) -> 0 | G3: =(COUNTBLANK(GRADES[[#This Row],[PayScaleGradeCode]:[AvailableToAllSchools]])+COUNTBLANK(GRADES[[#This Row],[PayScaleGradeEnabled]])) -> 0 | H3: =IF(LEN(GRADES[[#This Row],[PayScaleGradeCode]])<100,0,1) -> 0 | I3: =IF(LEN(GRADES[[#This Row],[Title]])<100,0,1) -> 0 | J3: =IF(SUBSTITUTE(TEXT(GRADES[[#This Row],[PayScaleGradeCode]],10)," ","")=TEXT(GRADES[[#This Row],[PayScaleGradeCode]],10),0,1) -> 0 | K3: =SUM(GRADES[[#This Row],[Pay Scale issue]:[Schools Check]],GRADES[[#This Row],[TRUE /FALSE Typo]:[Space in Code]]) -> 0 | L3: =_xlfn.XLOOKUP(GRADES[[#This Row],[PayScaleCode]],PAYSCALES[PayScaleCode],PAYSCALES[London Weighting]) -> England & Wales | N3: MAIN | O3: Teachers Main Scale only | P3: MAIN | Q3: M1 | R3: M6 | S3: {=LOOKUP(2,1/(PSPOINTS[PayScaleCode]=GRADES[[#This Row],[PayScaleCode]])/(PSPOINTS[PayScalePointCode]=GRADES[[#This Row],[Point From (Check)]]),(PSPOINTS[ScalePointNumber]))} -> 1 | T3: {=LOOKUP(2,1/(PSPOINTS[PayScaleCode]=GRADES[[#This Row],[PayScaleCode]])/(PSPOINTS[PayScalePointCode]=GRADES[[#This Row],[Point To (Check)]]),(PSPOINTS[ScalePointNumber]))} -> 6 | U3: TRUE | W3: TRUE
A4: =IF(COUNTIF(PayScales!N:N,PayScaleGrades!P4)>0,"0","1") -> 0 | B4: =COUNTIF(GRADES[PayScaleGradeCode],GRADES[[#This Row],[PayScaleGradeCode]])-1 -> 0 | C4: {=IF(GRADES[[#This Row],[AvailableToAllSchools]]=FALSE,IF(ISBLANK(GRADES[[#This Row],[SchoolCodes]]),1,IF(AND(COUNTIF(SCHOOLS[SchoolCode],_xlfn.TEXTSPLIT(GRADES[[#This Row],[SchoolCodes]],","))),0,1)),IF(GRADES[[#This Row],[AvailableToAllSchools]]=TRUE,IF(ISBLANK(GRADES[[#This Row],[SchoolCodes]]),0,1)))} -> 0 | E4: {=IF(_xlfn.XLOOKUP(GRADES[[#This Row],[PayScaleCode]],PAYSCALES[PayScaleCode],PAYSCALES[AvailableToAllSchools])=TRUE,0,IF(GRADES[[#This Row],[AvailableToAllSchools]]=TRUE,1,IF(_xlfn.LET(_xlpm.sourceCodes, _xlfn.TEXTSPLIT(GRADES[[#This Row],[SchoolCodes]], ","),_xlpm.targetCodes, _xlfn.TEXTSPLIT(_xlfn.XLOOKUP(GRADES[[#This Row],[PayScaleCode]],PAYSCALES[PayScaleCode],PAYSCALES[SchoolCodes],1), ","),_xlpm.trimmedSource, TRIM(_xlpm.sourceCodes),_xlpm.trimmedTarget, TRIM(_xlpm.targetCodes),_xlpm.matches, ISNUMBER(MATCH(_xlpm.trimmedSource, _xlpm.trimmedTarget, 0)),AND(_xlpm.matches))=TRUE,0,1)))} -> 0 | F4: =IF(OR(GRADES[[#This Row],[AvailableToAllSchools]]=TRUE,GRADES[[#This Row],[AvailableToAllSchools]]=FALSE),IF(OR(GRADES[[#This Row],[PayScaleGradeEnabled]]=TRUE,GRADES[[#This Row],[PayScaleGradeEnabled]]=FALSE),0,1),1) -> 0 | G4: =(COUNTBLANK(GRADES[[#This Row],[PayScaleGradeCode]:[AvailableToAllSchools]])+COUNTBLANK(GRADES[[#This Row],[PayScaleGradeEnabled]])) -> 0 | H4: =IF(LEN(GRADES[[#This Row],[PayScaleGradeCode]])<100,0,1) -> 0 | I4: =IF(LEN(GRADES[[#This Row],[Title]])<100,0,1) -> 0 | J4: =IF(SUBSTITUTE(TEXT(GRADES[[#This Row],[PayScaleGradeCode]],10)," ","")=TEXT(GRADES[[#This Row],[PayScaleGradeCode]],10),0,1) -> 0 | K4: =SUM(GRADES[[#This Row],[Pay Scale issue]:[Schools Check]],GRADES[[#This Row],[TRUE /FALSE Typo]:[Space in Code]]) -> 0 | L4: =_xlfn.XLOOKUP(GRADES[[#This Row],[PayScaleCode]],PAYSCALES[PayScaleCode],PAYSCALES[London Weighting]) -> England & Wales | N4: UPS | O4: Teachers Upper Scale only | P4: MAIN | Q4: U1 | R4: U3 | S4: {=LOOKUP(2,1/(PSPOINTS[PayScaleCode]=GRADES[[#This Row],[PayScaleCode]])/(PSPOINTS[PayScalePointCode]=GRADES[[#This Row],[Point From (Check)]]),(PSPOINTS[ScalePointNumber]))} -> 7 | T4: {=LOOKUP(2,1/(PSPOINTS[PayScaleCode]=GRADES[[#This Row],[PayScaleCode]])/(PSPOINTS[PayScalePointCode]=GRADES[[#This Row],[Point To (Check)]]),(PSPOINTS[ScalePointNumber]))} -> 9 | U4: TRUE | W4: TRUE
A5: =IF(COUNTIF(PayScales!N:N,PayScaleGrades!P5)>0,"0","1") -> 0 | B5: =COUNTIF(GRADES[PayScaleGradeCode],GRADES[[#This Row],[PayScaleGradeCode]])-1 -> 0 | C5: {=IF(GRADES[[#This Row],[AvailableToAllSchools]]=FALSE,IF(ISBLANK(GRADES[[#This Row],[SchoolCodes]]),1,IF(AND(COUNTIF(SCHOOLS[SchoolCode],_xlfn.TEXTSPLIT(GRADES[[#This Row],[SchoolCodes]],","))),0,1)),IF(GRADES[[#This Row],[AvailableToAllSchools]]=TRUE,IF(ISBLANK(GRADES[[#This Row],[SchoolCodes]]),0,1)))} -> 0 | E5: {=IF(_xlfn.XLOOKUP(GRADES[[#This Row],[PayScaleCode]],PAYSCALES[PayScaleCode],PAYSCALES[AvailableToAllSchools])=TRUE,0,IF(GRADES[[#This Row],[AvailableToAllSchools]]=TRUE,1,IF(_xlfn.LET(_xlpm.sourceCodes, _xlfn.TEXTSPLIT(GRADES[[#This Row],[SchoolCodes]], ","),_xlpm.targetCodes, _xlfn.TEXTSPLIT(_xlfn.XLOOKUP(GRADES[[#This Row],[PayScaleCode]],PAYSCALES[PayScaleCode],PAYSCALES[SchoolCodes],1), ","),_xlpm.trimmedSource, TRIM(_xlpm.sourceCodes),_xlpm.trimmedTarget, TRIM(_xlpm.targetCodes),_xlpm.matches, ISNUMBER(MATCH(_xlpm.trimmedSource, _xlpm.trimmedTarget, 0)),AND(_xlpm.matches))=TRUE,0,1)))} -> 0 | F5: =IF(OR(GRADES[[#This Row],[AvailableToAllSchools]]=TRUE,GRADES[[#This Row],[AvailableToAllSchools]]=FALSE),IF(OR(GRADES[[#This Row],[PayScaleGradeEnabled]]=TRUE,GRADES[[#This Row],[PayScaleGradeEnabled]]=FALSE),0,1),1) -> 0 | G5: =(COUNTBLANK(GRADES[[#This Row],[PayScaleGradeCode]:[AvailableToAllSchools]])+COUNTBLANK(GRADES[[#This Row],[PayScaleGradeEnabled]])) -> 0 | H5: =IF(LEN(GRADES[[#This Row],[PayScaleGradeCode]])<100,0,1) -> 0 | I5: =IF(LEN(GRADES[[#This Row],[Title]])<100,0,1) -> 0 | J5: =IF(SUBSTITUTE(TEXT(GRADES[[#This Row],[PayScaleGradeCode]],10)," ","")=TEXT(GRADES[[#This Row],[PayScaleGradeCode]],10),0,1) -> 0 | K5: =SUM(GRADES[[#This Row],[Pay Scale issue]:[Schools Check]],GRADES[[#This Row],[TRUE /FALSE Typo]:[Space in Code]]) -> 0 | L5: =_xlfn.XLOOKUP(GRADES[[#This Row],[PayScaleCode]],PAYSCALES[PayScaleCode],PAYSCALES[London Weighting]) -> England & Wales | N5: UQ | O5: Teacher Unqualified | P5: UQ | Q5: UQ1 | R5: UQ6 | S5: {=LOOKUP(2,1/(PSPOINTS[PayScaleCode]=GRADES[[#This Row],[PayScaleCode]])/(PSPOINTS[PayScalePointCode]=GRADES[[#This Row],[Point From (Check)]]),(PSPOINTS[ScalePointNumber]))} -> 1 | T5: {=LOOKUP(2,1/(PSPOINTS[PayScaleCode]=GRADES[[#This Row],[PayScaleCode]])/(PSPOINTS[PayScalePointCode]=GRADES[[#This Row],[Point To (Check)]]),(PSPOINTS[ScalePointNumber]))} -> 6 | U5: TRUE | W5: TRUE
A6: =IF(COUNTIF(PayScales!N:N,PayScaleGrades!P6)>0,"0","1") -> 0 | B6: =COUNTIF(GRADES[PayScaleGradeCode],GRADES[[#This Row],[PayScaleGradeCode]])-1 -> 0 | C6: {=IF(GRADES[[#This Row],[AvailableToAllSchools]]=FALSE,IF(ISBLANK(GRADES[[#This Row],[SchoolCodes]]),1,IF(AND(COUNTIF(SCHOOLS[SchoolCode],_xlfn.TEXTSPLIT(GRADES[[#This Row],[SchoolCodes]],","))),0,1)),IF(GRADES[[#This Row],[AvailableToAllSchools]]=TRUE,IF(ISBLANK(GRADES[[#This Row],[SchoolCodes]]),0,1)))} -> 0 | E6: {=IF(_xlfn.XLOOKUP(GRADES[[#This Row],[PayScaleCode]],PAYSCALES[PayScaleCode],PAYSCALES[AvailableToAllSchools])=TRUE,0,IF(GRADES[[#This Row],[AvailableToAllSchools]]=TRUE,1,IF(_xlfn.LET(_xlpm.sourceCodes, _xlfn.TEXTSPLIT(GRADES[[#This Row],[SchoolCodes]], ","),_xlpm.targetCodes, _xlfn.TEXTSPLIT(_xlfn.XLOOKUP(GRADES[[#This Row],[PayScaleCode]],PAYSCALES[PayScaleCode],PAYSCALES[SchoolCodes],1), ","),_xlpm.trimmedSource, TRIM(_xlpm.sourceCodes),_xlpm.trimmedTarget, TRIM(_xlpm.targetCodes),_xlpm.matches, ISNUMBER(MATCH(_xlpm.trimmedSource, _xlpm.trimmedTarget, 0)),AND(_xlpm.matches))=TRUE,0,1)))} -> 0 | F6: =IF(OR(GRADES[[#This Row],[AvailableToAllSchools]]=TRUE,GRADES[[#This Row],[AvailableToAllSchools]]=FALSE),IF(OR(GRADES[[#This Row],[PayScaleGradeEnabled]]=TRUE,GRADES[[#This Row],[PayScaleGradeEnabled]]=FALSE),0,1),1) -> 0 | G6: =(COUNTBLANK(GRADES[[#This Row],[PayScaleGradeCode]:[AvailableToAllSchools]])+COUNTBLANK(GRADES[[#This Row],[PayScaleGradeEnabled]])) -> 0 | H6: =IF(LEN(GRADES[[#This Row],[PayScaleGradeCode]])<100,0,1) -> 0 | I6: =IF(LEN(GRADES[[#This Row],[Title]])<100,0,1) -> 0 | J6: =IF(SUBSTITUTE(TEXT(GRADES[[#This Row],[PayScaleGradeCode]],10)," ","")=TEXT(GRADES[[#This Row],[PayScaleGradeCode]],10),0,1) -> 0 | K6: =SUM(GRADES[[#This Row],[Pay Scale issue]:[Schools Check]],GRADES[[#This Row],[TRUE /FALSE Typo]:[Space in Code]]) -> 0 | L6: =_xlfn.XLOOKUP(GRADES[[#This Row],[PayScaleCode]],PAYSCALES[PayScaleCode],PAYSCALES[London Weighting]) -> England & Wales | N6: L01-L43 | O6: Leadership scp L01-L43 | P6: LS | Q6: L01 | R6: L43 | S6: {=LOOKUP(2,1/(PSPOINTS[PayScaleCode]=GRADES[[#This Row],[PayScaleCode]])/(PSPOINTS[PayScalePointCode]=GRADES[[#This Row],[Point From (Check)]]),(PSPOINTS[ScalePointNumber]))} -> 1 | T6: {=LOOKUP(2,1/(PSPOINTS[PayScaleCode]=GRADES[[#This Row],[PayScaleCode]])/(PSPOINTS[PayScalePointCode]=GRADES[[#This Row],[Point To (Check)]]),(PSPOINTS[ScalePointNumber]))} -> 43 | U6: TRUE | W6: TRUE
A7: =IF(COUNTIF(PayScales!N:N,PayScaleGrades!P23)>0,"0","1") -> 0 | B7: =COUNTIF(GRADES[PayScaleGradeCode],GRADES[[#This Row],[PayScaleGradeCode]])-1 -> 0 | C7: {=IF(GRADES[[#This Row],[AvailableToAllSchools]]=FALSE,IF(ISBLANK(GRADES[[#This Row],[SchoolCodes]]),1,IF(AND(COUNTIF(SCHOOLS[SchoolCode],_xlfn.TEXTSPLIT(GRADES[[#This Row],[SchoolCodes]],","))),0,1)),IF(GRADES[[#This Row],[AvailableToAllSchools]]=TRUE,IF(ISBLANK(GRADES[[#This Row],[SchoolCodes]]),0,1)))} -> 0 | E7: {=IF(_xlfn.XLOOKUP(GRADES[[#This Row],[PayScaleCode]],PAYSCALES[PayScaleCode],PAYSCALES[AvailableToAllSchools])=TRUE,0,IF(GRADES[[#This Row],[AvailableToAllSchools]]=TRUE,1,IF(_xlfn.LET(_xlpm.sourceCodes, _xlfn.TEXTSPLIT(GRADES[[#This Row],[SchoolCodes]], ","),_xlpm.targetCodes, _xlfn.TEXTSPLIT(_xlfn.XLOOKUP(GRADES[[#This Row],[PayScaleCode]],PAYSCALES[PayScaleCode],PAYSCALES[SchoolCodes],1), ","),_xlpm.trimmedSource, TRIM(_xlpm.sourceCodes),_xlpm.trimmedTarget, TRIM(_xlpm.targetCodes),_xlpm.matches, ISNUMBER(MATCH(_xlpm.trimmedSource, _xlpm.trimmedTarget, 0)),AND(_xlpm.matches))=TRUE,0,1)))} -> 0 | F7: =IF(OR(GRADES[[#This Row],[AvailableToAllSchools]]=TRUE,GRADES[[#This Row],[AvailableToAllSchools]]=FALSE),IF(OR(GRADES[[#This Row],[PayScaleGradeEnabled]]=TRUE,GRADES[[#This Row],[PayScaleGradeEnabled]]=FALSE),0,1),1) -> 0 | G7: =(COUNTBLANK(GRADES[[#This Row],[PayScaleGradeCode]:[AvailableToAllSchools]])+COUNTBLANK(GRADES[[#This Row],[PayScaleGradeEnabled]])) -> 0 | H7: =IF(LEN(GRADES[[#This Row],[PayScaleGradeCode]])<100,0,1) -> 0 | I7: =IF(LEN(GRADES[[#This Row],[Title]])<100,0,1) -> 0 | J7: =IF(SUBSTITUTE(TEXT(GRADES[[#This Row],[PayScaleGradeCode]],10)," ","")=TEXT(GRADES[[#This Row],[PayScaleGradeCode]],10),0,1) -> 0 | K7: =SUM(GRADES[[#This Row],[Pay Scale issue]:[Schools Check]],GRADES[[#This Row],[TRUE /FALSE Typo]:[Space in Code]]) -> 0 | L7: =_xlfn.XLOOKUP(GRADES[[#This Row],[PayScaleCode]],PAYSCALES[PayScaleCode],PAYSCALES[London Weighting]) -> England & Wales | N7: L02-L06 | O7: Leadership scp L02-L06 | P7: LS | Q7: L02 | R7: L06 | S7: {=LOOKUP(2,1/(PSPOINTS[PayScaleCode]=GRADES[[#This Row],[PayScaleCode]])/(PSPOINTS[PayScalePointCode]=GRADES[[#This Row],[Point From (Check)]]),(PSPOINTS[ScalePointNumber]))} -> 2 | T7: {=LOOKUP(2,1/(PSPOINTS[PayScaleCode]=GRADES[[#This Row],[PayScaleCode]])/(PSPOINTS[PayScalePointCode]=GRADES[[#This Row],[Point To (Check)]]),(PSPOINTS[ScalePointNumber]))} -> 6 | U7: TRUE | W7: TRUE
A8: =IF(COUNTIF(PayScales!N:N,PayScaleGrades!P34)>0,"0","1") -> 0 | B8: =COUNTIF(GRADES[PayScaleGradeCode],GRADES[[#This Row],[PayScaleGradeCode]])-1 -> 0 | C8: {=IF(GRADES[[#This Row],[AvailableToAllSchools]]=FALSE,IF(ISBLANK(GRADES[[#This Row],[SchoolCodes]]),1,IF(AND(COUNTIF(SCHOOLS[SchoolCode],_xlfn.TEXTSPLIT(GRADES[[#This Row],[SchoolCodes]],","))),0,1)),IF(GRADES[[#This Row],[AvailableToAllSchools]]=TRUE,IF(ISBLANK(GRADES[[#This Row],[SchoolCodes]]),0,1)))} -> 0 | E8: {=IF(_xlfn.XLOOKUP(GRADES[[#This Row],[PayScaleCode]],PAYSCALES[PayScaleCode],PAYSCALES[AvailableToAllSchools])=TRUE,0,IF(GRADES[[#This Row],[AvailableToAllSchools]]=TRUE,1,IF(_xlfn.LET(_xlpm.sourceCodes, _xlfn.TEXTSPLIT(GRADES[[#This Row],[SchoolCodes]], ","),_xlpm.targetCodes, _xlfn.TEXTSPLIT(_xlfn.XLOOKUP(GRADES[[#This Row],[PayScaleCode]],PAYSCALES[PayScaleCode],PAYSCALES[SchoolCodes],1), ","),_xlpm.trimmedSource, TRIM(_xlpm.sourceCodes),_xlpm.trimmedTarget, TRIM(_xlpm.targetCodes),_xlpm.matches, ISNUMBER(MATCH(_xlpm.trimmedSource, _xlpm.trimmedTarget, 0)),AND(_xlpm.matches))=TRUE,0,1)))} -> 0 | F8: =IF(OR(GRADES[[#This Row],[AvailableToAllSchools]]=TRUE,GRADES[[#This Row],[AvailableToAllSchools]]=FALSE),IF(OR(GRADES[[#This Row],[PayScaleGradeEnabled]]=TRUE,GRADES[[#This Row],[PayScaleGradeEnabled]]=FALSE),0,1),1) -> 0 | G8: =(COUNTBLANK(GRADES[[#This Row],[PayScaleGradeCode]:[AvailableToAllSchools]])+COUNTBLANK(GRADES[[#This Row],[PayScaleGradeEnabled]])) -> 0 | H8: =IF(LEN(GRADES[[#This Row],[PayScaleGradeCode]])<100,0,1) -> 0 | I8: =IF(LEN(GRADES[[#This Row],[Title]])<100,0,1) -> 0 | J8: =IF(SUBSTITUTE(TEXT(GRADES[[#This Row],[PayScaleGradeCode]],10)," ","")=TEXT(GRADES[[#This Row],[PayScaleGradeCode]],10),0,1) -> 0 | K8: =SUM(GRADES[[#This Row],[Pay Scale issue]:[Schools Check]],GRADES[[#This Row],[TRUE /FALSE Typo]:[Space in Code]]) -> 0 | L8: =_xlfn.XLOOKUP(GRADES[[#This Row],[PayScaleCode]],PAYSCALES[PayScaleCode],PAYSCALES[London Weighting]) -> England & Wales | N8: L03-L07 | O8: Leadership scp L03-L07 | P8: LS | Q8: L03 | R8: L07 | S8: {=LOOKUP(2,1/(PSPOINTS[PayScaleCode]=GRADES[[#This Row],[PayScaleCode]])/(PSPOINTS[PayScalePointCode]=GRADES[[#This Row],[Point From (Check)]]),(PSPOINTS[ScalePointNumber]))} -> 3 | T8: {=LOOKUP(2,1/(PSPOINTS[PayScaleCode]=GRADES[[#This Row],[PayScaleCode]])/(PSPOINTS[PayScalePointCode]=GRADES[[#This Row],[Point To (Check)]]),(PSPOINTS[ScalePointNumber]))} -> 7 | U8: TRUE | W8: TRUE
A9: =IF(COUNTIF(PayScales!N:N,PayScaleGrades!P35)>0,"0","1") -> 0 | B9: =COUNTIF(GRADES[PayScaleGradeCode],GRADES[[#This Row],[PayScaleGradeCode]])-1 -> 0 | C9: {=IF(GRADES[[#This Row],[AvailableToAllSchools]]=FALSE,IF(ISBLANK(GRADES[[#This Row],[SchoolCodes]]),1,IF(AND(COUNTIF(SCHOOLS[SchoolCode],_xlfn.TEXTSPLIT(GRADES[[#This Row],[SchoolCodes]],","))),0,1)),IF(GRADES[[#This Row],[AvailableToAllSchools]]=TRUE,IF(ISBLANK(GRADES[[#This Row],[SchoolCodes]]),0,1)))} -> 0 | E9: {=IF(_xlfn.XLOOKUP(GRADES[[#This Row],[PayScaleCode]],PAYSCALES[PayScaleCode],PAYSCALES[AvailableToAllSchools])=TRUE,0,IF(GRADES[[#This Row],[AvailableToAllSchools]]=TRUE,1,IF(_xlfn.LET(_xlpm.sourceCodes, _xlfn.TEXTSPLIT(GRADES[[#This Row],[SchoolCodes]], ","),_xlpm.targetCodes, _xlfn.TEXTSPLIT(_xlfn.XLOOKUP(GRADES[[#This Row],[PayScaleCode]],PAYSCALES[PayScaleCode],PAYSCALES[SchoolCodes],1), ","),_xlpm.trimmedSource, TRIM(_xlpm.sourceCodes),_xlpm.trimmedTarget, TRIM(_xlpm.targetCodes),_xlpm.matches, ISNUMBER(MATCH(_xlpm.trimmedSource, _xlpm.trimmedTarget, 0)),AND(_xlpm.matches))=TRUE,0,1)))} -> 0 | F9: =IF(OR(GRADES[[#This Row],[AvailableToAllSchools]]=TRUE,GRADES[[#This Row],[AvailableToAllSchools]]=FALSE),IF(OR(GRADES[[#This Row],[PayScaleGradeEnabled]]=TRUE,GRADES[[#This Row],[PayScaleGradeEnabled]]=FALSE),0,1),1) -> 0 | G9: =(COUNTBLANK(GRADES[[#This Row],[PayScaleGradeCode]:[AvailableToAllSchools]])+COUNTBLANK(GRADES[[#This Row],[PayScaleGradeEnabled]])) -> 0 | H9: =IF(LEN(GRADES[[#This Row],[PayScaleGradeCode]])<100,0,1) -> 0 | I9: =IF(LEN(GRADES[[#This Row],[Title]])<100,0,1) -> 0 | J9: =IF(SUBSTITUTE(TEXT(GRADES[[#This Row],[PayScaleGradeCode]],10)," ","")=TEXT(GRADES[[#This Row],[PayScaleGradeCode]],10),0,1) -> 0 | K9: =SUM(GRADES[[#This Row],[Pay Scale issue]:[Schools Check]],GRADES[[#This Row],[TRUE /FALSE Typo]:[Space in Code]]) -> 0 | L9: =_xlfn.XLOOKUP(GRADES[[#This Row],[PayScaleCode]],PAYSCALES[PayScaleCode],PAYSCALES[London Weighting]) -> England & Wales | N9: L04-L08 | O9: Leadership scp L04-L08 | P9: LS | Q9: L04 | R9: L08 | S9: {=LOOKUP(2,1/(PSPOINTS[PayScaleCode]=GRADES[[#This Row],[PayScaleCode]])/(PSPOINTS[PayScalePointCode]=GRADES[[#This Row],[Point From (Check)]]),(PSPOINTS[ScalePointNumber]))} -> 4 | T9: {=LOOKUP(2,1/(PSPOINTS[PayScaleCode]=GRADES[[#This Row],[PayScaleCode]])/(PSPOINTS[PayScalePointCode]=GRADES[[#This Row],[Point To (Check)]]),(PSPOINTS[ScalePointNumber]))} -> 8 | U9: TRUE | W9: TRUE
A10: =IF(COUNTIF(PayScales!N:N,PayScaleGrades!P36)>0,"0","1") -> 0 | B10: =COUNTIF(GRADES[PayScaleGradeCode],GRADES[[#This Row],[PayScaleGradeCode]])-1 -> 0 | C10: {=IF(GRADES[[#This Row],[AvailableToAllSchools]]=FALSE,IF(ISBLANK(GRADES[[#This Row],[SchoolCodes]]),1,IF(AND(COUNTIF(SCHOOLS[SchoolCode],_xlfn.TEXTSPLIT(GRADES[[#This Row],[SchoolCodes]],","))),0,1)),IF(GRADES[[#This Row],[AvailableToAllSchools]]=TRUE,IF(ISBLANK(GRADES[[#This Row],[SchoolCodes]]),0,1)))} -> 0 | E10: {=IF(_xlfn.XLOOKUP(GRADES[[#This Row],[PayScaleCode]],PAYSCALES[PayScaleCode],PAYSCALES[AvailableToAllSchools])=TRUE,0,IF(GRADES[[#This Row],[AvailableToAllSchools]]=TRUE,1,IF(_xlfn.LET(_xlpm.sourceCodes, _xlfn.TEXTSPLIT(GRADES[[#This Row],[SchoolCodes]], ","),_xlpm.targetCodes, _xlfn.TEXTSPLIT(_xlfn.XLOOKUP(GRADES[[#This Row],[PayScaleCode]],PAYSCALES[PayScaleCode],PAYSCALES[SchoolCodes],1), ","),_xlpm.trimmedSource, TRIM(_xlpm.sourceCodes),_xlpm.trimmedTarget, TRIM(_xlpm.targetCodes),_xlpm.matches, ISNUMBER(MATCH(_xlpm.trimmedSource, _xlpm.trimmedTarget, 0)),AND(_xlpm.matches))=TRUE,0,1)))} -> 0 | F10: =IF(OR(GRADES[[#This Row],[AvailableToAllSchools]]=TRUE,GRADES[[#This Row],[AvailableToAllSchools]]=FALSE),IF(OR(GRADES[[#This Row],[PayScaleGradeEnabled]]=TRUE,GRADES[[#This Row],[PayScaleGradeEnabled]]=FALSE),0,1),1) -> 0 | G10: =(COUNTBLANK(GRADES[[#This Row],[PayScaleGradeCode]:[AvailableToAllSchools]])+COUNTBLANK(GRADES[[#This Row],[PayScaleGradeEnabled]])) -> 0 | H10: =IF(LEN(GRADES[[#This Row],[PayScaleGradeCode]])<100,0,1) -> 0 | I10: =IF(LEN(GRADES[[#This Row],[Title]])<100,0,1) -> 0 | J10: =IF(SUBSTITUTE(TEXT(GRADES[[#This Row],[PayScaleGradeCode]],10)," ","")=TEXT(GRADES[[#This Row],[PayScaleGradeCode]],10),0,1) -> 0 | K10: =SUM(GRADES[[#This Row],[Pay Scale issue]:[Schools Check]],GRADES[[#This Row],[TRUE /FALSE Typo]:[Space in Code]]) -> 0 | L10: =_xlfn.XLOOKUP(GRADES[[#This Row],[PayScaleCode]],PAYSCALES[PayScaleCode],PAYSCALES[London Weighting]) -> England & Wales | N10: L05-L09 | O10: Leadership scp L05-L09 | P10: LS | Q10: L05 | R10: L09 | S10: {=LOOKUP(2,1/(PSPOINTS[PayScaleCode]=GRADES[[#This Row],[PayScaleCode]])/(PSPOINTS[PayScalePointCode]=GRADES[[#This Row],[Point From (Check)]]),(PSPOINTS[ScalePointNumber]))} -> 5 | T10: {=LOOKUP(2,1/(PSPOINTS[PayScaleCode]=GRADES[[#This Row],[PayScaleCode]])/(PSPOINTS[PayScalePointCode]=GRADES[[#This Row],[Point To (Check)]]),(PSPOINTS[ScalePointNumber]))} -> 9 | U10: TRUE | W10: TRUE
A11: =IF(COUNTIF(PayScales!N:N,PayScaleGrades!P37)>0,"0","1") -> 0 | B11: =COUNTIF(GRADES[PayScaleGradeCode],GRADES[[#This Row],[PayScaleGradeCode]])-1 -> 0 | C11: {=IF(GRADES[[#This Row],[AvailableToAllSchools]]=FALSE,IF(ISBLANK(GRADES[[#This Row],[SchoolCodes]]),1,IF(AND(COUNTIF(SCHOOLS[SchoolCode],_xlfn.TEXTSPLIT(GRADES[[#This Row],[SchoolCodes]],","))),0,1)),IF(GRADES[[#This Row],[AvailableToAllSchools]]=TRUE,IF(ISBLANK(GRADES[[#This Row],[SchoolCodes]]),0,1)))} -> 0 | E11: {=IF(_xlfn.XLOOKUP(GRADES[[#This Row],[PayScaleCode]],PAYSCALES[PayScaleCode],PAYSCALES[AvailableToAllSchools])=TRUE,0,IF(GRADES[[#This Row],[AvailableToAllSchools]]=TRUE,1,IF(_xlfn.LET(_xlpm.sourceCodes, _xlfn.TEXTSPLIT(GRADES[[#This Row],[SchoolCodes]], ","),_xlpm.targetCodes, _xlfn.TEXTSPLIT(_xlfn.XLOOKUP(GRADES[[#This Row],[PayScaleCode]],PAYSCALES[PayScaleCode],PAYSCALES[SchoolCodes],1), ","),_xlpm.trimmedSource, TRIM(_xlpm.sourceCodes),_xlpm.trimmedTarget, TRIM(_xlpm.targetCodes),_xlpm.matches, ISNUMBER(MATCH(_xlpm.trimmedSource, _xlpm.trimmedTarget, 0)),AND(_xlpm.matches))=TRUE,0,1)))} -> 0 | F11: =IF(OR(GRADES[[#This Row],[AvailableToAllSchools]]=TRUE,GRADES[[#This Row],[AvailableToAllSchools]]=FALSE),IF(OR(GRADES[[#This Row],[PayScaleGradeEnabled]]=TRUE,GRADES[[#This Row],[PayScaleGradeEnabled]]=FALSE),0,1),1) -> 0 | G11: =(COUNTBLANK(GRADES[[#This Row],[PayScaleGradeCode]:[AvailableToAllSchools]])+COUNTBLANK(GRADES[[#This Row],[PayScaleGradeEnabled]])) -> 0 | H11: =IF(LEN(GRADES[[#This Row],[PayScaleGradeCode]])<100,0,1) -> 0 | I11: =IF(LEN(GRADES[[#This Row],[Title]])<100,0,1) -> 0 | J11: =IF(SUBSTITUTE(TEXT(GRADES[[#This Row],[PayScaleGradeCode]],10)," ","")=TEXT(GRADES[[#This Row],[PayScaleGradeCode]],10),0,1) -> 0 | K11: =SUM(GRADES[[#This Row],[Pay Scale issue]:[Schools Check]],GRADES[[#This Row],[TRUE /FALSE Typo]:[Space in Code]]) -> 0 | L11: =_xlfn.XLOOKUP(GRADES[[#This Row],[PayScaleCode]],PAYSCALES[PayScaleCode],PAYSCALES[London Weighting]) -> England & Wales | N11: L06-L10 | O11: Leadership scp L06-L10 | P11: LS | Q11: L06 | R11: L10 | S11: {=LOOKUP(2,1/(PSPOINTS[PayScaleCode]=GRADES[[#This Row],[PayScaleCode]])/(PSPOINTS[PayScalePointCode]=GRADES[[#This Row],[Point From (Check)]]),(PSPOINTS[ScalePointNumber]))} -> 6 | T11: {=LOOKUP(2,1/(PSPOINTS[PayScaleCode]=GRADES[[#This Row],[PayScaleCode]])/(PSPOINTS[PayScalePointCode]=GRADES[[#This Row],[Point To (Check)]]),(PSPOINTS[ScalePointNumber]))} -> 10 | U11: TRUE | W11: TRUE
