Workbook
Name BuildYear: Parameters!$B$5

Sheet Parameters
A1: VERSION | B1: 1.101
A3: Parameter | B3: Value | D3: Link updated? | E3: No
A4: Token
A5: Year From | B5: 2023/24
A6: Api Url Root | B6: https://api.impplanner.co.uk
A7: Date Last Amended | B7: 45868 | D7: update to today date (shortcut is CTRL + ;)
A9: Element | B9: Type
A10: CALCULATIONS | B10: SIMPLE

Sheet Notes
A1: Process Notes
A3: Updating API
A5: Step
A6: 1 | B6: Add API code to parameter tab
A28: 2 | B28: Navigate to the queries and connections in Data tab
A51: 3 | B51: This will bring up a side menu
A104: 4 | B104: Right click on the API folder and click "Refresh"
A147: 5 | B147: If the below pop-up appears please tick the "Ignore Privacy Levels" box and then click the "Save" button.
A164: 6 | B164: If the below pop-up appears please click the "Don't Update" button.
A174: Schools
A176: Step
A177: 1 | B177: London Weighting Type needs to be updated with the correct type from the drop down. This is based on the Local authority, whose weighting can be found in column "Teachers IL/OL/FRI" of the "Local Authorities - standard codes" document.
A193: #VALUE!

Sheet Build Checklist
A1: Checklist
A2: Task | B2: Notes | C2: Error Check
A3: Check for PayScale Issues | C3: =SUM(PAYSCALES[Will Import if 0]) -> 0
A4: Check for PayScale Point Issues | C4: =SUM(PSPOINTS[Will Import if 0]) -> 0
A5: Check for PayScale Increase % Issues | C5: =SUM(PS_INCPERC[Will Import if 0]) -> 0
A6: Check for PayScale Grades Issues | C6: =SUM(GRADES[Will Import if 0]) -> 0
A7: Check Allowance Type Issues | C7: =SUM(ALLWCTYPE[Will Import if 0]) -> 0
A8: Check Allowance Point Issues | C8: =SUM(ALLWCPTS[Will import if 0]) -> 0
A9: Check Allowance Increase % Issues | C9: =SUM(AL_INCPERC[Will Import if 0]) -> 0
A10: Check for Pensions Issues | C10: =SUM(PENS[Will import if 0]) -> 0
A11: Check for EQWP Issues | C11: =SUM(EQW[Will import if 0]) -> 0
A12: Check for Staff Members Issues | C12: =SUM(MEMBERS[Will Import if 0]) -> 13
A13: Check for Staff Role Groups Issues | C13: =SUM(SRG[Will Import if 0]) -> 221
A14: Check for Staff Roles Issues | C14: =SUM(ROLES[Will Import if 0]) -> 102
A15: Check for Contract Issues (Teacher) | C15: =SUM(CONT_TEA[Will Import if 0]) -> #N/A
A16: Check for Contract Issues (Support) | C16: =SUM(CONT_SUP[Will Import if 0]) -> #N/A
A17: Check Adjustment Type Issues | C17: =SUM(ADJTYPE[Will import if 0]) -> 0
A18: Check Contract Adjustment Issues | C18: =SUM(CONTADJ[Will import if 0]) -> 5
A19: Check Contract Allowance Issues | C19: =SUM(CONTAL[Will import if 0]) -> #N/A
A20: Check Leave Types Issues | C20: =SUM(LEAVES[Will Import if 0]) -> 0
A21: Check Staff Member Leaves Issues | C21: =SUM(SM_LEAVES[Will Import if 0]) -> 10
A22: Check Finance Codes S2 Issues (Ledger needed?) | C22: =SUM(FC_import[Will Import if 0]) -> 91
A23: Total Tab Check | C23: =SUM(C3:C22) -> #N/A
A24: Have the Scope Document info / Email Responses been reviewed?
A25: Do funds need to be assigned at Scenario Row Level? (See Scope Document info)
A26: If not standard, did we receive and check Statutory leave types?
A27: Do contract effective dates match the dates provided in the Scope Document?
A28: Have we built all the PayScales provided?
A29: Did we build contracts for all locations?
A30: Have all pension rates been supplied?
A31: Do PayScales increment and increase in line with Scope Document info?
A32: Are full time hours - for roles/locations - in line with Scope Document info?
A33: Are notes added to Import Checklist (and against task row, this tab) to explain all 'non-errors' with an Error Check score (Col C)?
A34: Are there any SRG Critical Errors which will prevent successful Import? - if YES - alert LC to issue
A35: Excluded contracts/ allowances - Do any excluded lines have budgetary impact (ie. data lines show salary / allowance cost)?
... A40: Review purposes - If Salaries in data YES, is this part of your Staff Contract Build Reconciliation? If not, please alert LC to any issue
A42: Reviewed by Builder | B42: Y/N
A43: Reviewed by Lead Consultant | B43: Y/N

Sheet Import Checklist
B1: Checklist
B2: If this is not zero - return to builder | C2: =SUM('Build Checklist'!C21) -> 10
A3: Column1 | B3: Task | C3: Number of Rows to Import | D3: Number of Rows Imported | E3: Import Checked | F3: LC Import Notes | G3: Builder Import Notes | H3: Importer Notes/Issues
A4: 11 | B4: Finance codes S2 | C4: =COUNTA(FC_import[FinanceCode]) -> 91 | E4: =IF(C4=D4,TRUE,FALSE) -> FALSE
A5: 16 | B5: Allowance Type | C5: =COUNTA(ALLWCTYPE[AllowanceTypeCode]) -> 2 | E5: =IF(C5=D5,TRUE,FALSE) -> FALSE
A6: 17 | B6: Allowance Point | C6: =COUNTA(ALLWCPTS[AllowanceTypeCode]) -> 10 | E6: =IF(C6=D6,TRUE,FALSE) -> FALSE
A7: 18 | B7: Allowance Increase % | C7: =COUNTA(AL_INCPERC[AllowanceTypeCode]) -> 2 | E7: =IF(C7=D7,TRUE,FALSE) -> FALSE
A8: 19 | B8: Payscales | C8: =COUNTA(PAYSCALES[PayScaleEnabled]) -> 22 | E8: =IF(C8=D8,TRUE,FALSE) -> FALSE
A9: 20 | B9: Payscale Points | C9: =COUNTIF(PSPOINTS[PayScalePointEnabled],TRUE) -> 492 | E9: =IF(C9=D9,TRUE,FALSE) -> FALSE
A10: 21 | B10: Payscale Increase Percentages | C10: =COUNTA(PS_INCPERC[IncreasePercentage]) -> 19 | E10: =IF(C10=D10,TRUE,FALSE) -> FALSE
A11: 22 | B11: Payscale Grades | C11: =COUNTA(GRADES[PayScaleGradeEnabled]) -> 33 | E11: =IF(C11=D11,TRUE,FALSE) -> FALSE
A12: 23 | B12: Equated Week Patterns | C12: =COUNTA(EQW[EquatedWeekPatternEnabled]) -> 1 | E12: =IF(C12=D12,TRUE,FALSE) -> FALSE
A13: 24 | B13: Pensions | C13: =COUNTA(PENS[PensionEnabled]) -> 3 | E13: =IF(C13=D13,TRUE,FALSE) -> FALSE
A14: 25 | B14: Staff Members | C14: =COUNTA(MEMBERS[StaffMemberEnabled]) -> 1 | E14: =IF(C14=D14,TRUE,FALSE) -> FALSE
A15: 26 | B15: Staff Role Groups | C15: =COUNTA(SRG[StaffRoleGroupEnabled]) -> 17 | E15: =IF(C15=D15,TRUE,FALSE) -> FALSE
A16: 27 | B16: Staff Roles | C16: =COUNTA(ROLES[StaffRoleEnabled]) -> 34 | E16: =IF(C16=D16,TRUE,FALSE) -> FALSE
A17: 28 | B17: Contract (Teacher) | C17: =COUNTA(CONT_TEA[StaffMemberCode]) -> 1 | E17: =IF(C17=D17,TRUE,FALSE) -> FALSE | F17: If Values are built as FTE - Check that you have selected FTE!
A18: 29 | B18: Contract (Support) | C18: =COUNTA(CONT_SUP[StaffMemberCode]) -> 1 | E18: =IF(C18=D18,TRUE,FALSE) -> FALSE
A19: 30 | B19: Leave Types | C19: =COUNTA(LEAVES[LeaveTypeEnabled]) -> 33 | E19: =IF(C19=D19,TRUE,FALSE) -> FALSE
A20: 31 | B20: Adjustments | C20: =COUNTA(ADJTYPE[AdjustmentTypeCode]) -> 2 | E20: =IF(C20=D20,TRUE,FALSE) -> FALSE
A21: 32 | B21: Staff Member Leaves | C21: =COUNTA(SM_LEAVES[StaffMemberCode]) -> 0 | E21: =IF(C21=D21,TRUE,FALSE) -> TRUE | F21: Imports - Maternity Start must not pre-date contract start. Import as-is for base weekly pay to calc, then manually backdate the Mat From date in Planner if needed.
A22: 33 | B22: Contract Adjustments | C22: =COUNTA(CONTADJ[SchoolCode]) -> 1 | E22: =IF(C22=D22,TRUE,FALSE) -> FALSE
A23: 34 | B23: Contract Allowances | C23: =COUNTA(CONTAL[StaffMemberCode]) -> 1 | E23: =IF(C23=D23,TRUE,FALSE) -> FALSE

Sheet System Grouping Codes
A1: groupingCodeCode | B1: title | C1: groupingCodeTypeCode
A2: 510100 | B2: IN: DfE Revenue Grants: GAG (not stud supp and trust grants) | C2: A
A3: 510110 | B3: IN: DfE Revenue Grants: GAG (student support) | C3: A
A4: 510120 | B4: IN: DfE Revenue Grants: GAG (start up grants) | C4: A
A5: 510130 | B5: IN: DfE Revenue Grants: Trust level grants | C5: A
A6: 510140 | B6: IN: DfE Revenue Grants: Pupil number adjustment | C6: A
A7: 510150 | B7: IN: DfE Revenue Grants: Rates reclaim | C7: A
A8: 510200 | B8: IN: DfE Revenue Grants: Pupil Premium | C8: A
A9: 510250 | B9: IN: DfE Revenue Grants: Universal Inf Free School Meals | C9: A
A10: 510300 | B10: IN: DfE Revenue Grants: Insurance top up | C10: A
A11: 510350 | B11: IN: DfE Revenue Grants: Sponsor capacity grant | C11: A
A12: 510400 | B12: IN: DfE Revenue Grants: PE & Sports grant | C12: A
... A481: ZZZ | B481: Not Applicable | C481: ZZZ

Sheet Funds
G1: API - Do not edit
A2: Code is Blank | B2: Title is Blank | C2: Enabled is blank | D2: Code length Check | E2: Title length check | F2: Will import if zero | G2: FundCode | H2: Title | I2: FundEnabled
A3: =ISBLANK(FUNDS[[#This Row],[FundCode]]) -> FALSE | B3: =ISBLANK(FUNDS[[#This Row],[Title]]) -> FALSE | C3: =ISBLANK(FUNDS[[#This Row],[FundEnabled]]) -> FALSE | D3: =IF(LEN(FUNDS[[#This Row],[FundCode]])<100,FALSE,TRUE) -> FALSE | E3: =IF(LEN(FUNDS[[#This Row],[Title]])<100,FALSE,TRUE) -> FALSE | F3: =COUNTIF(FUNDS[[#This Row],[Code is Blank]:[Title length check]],"TRUE") -> 0 | G3: DEFAULT | H3: DEFAULT | I3: TRUE
A4: =ISBLANK(FUNDS[[#This Row],[FundCode]]) -> FALSE | B4: =ISBLANK(FUNDS[[#This Row],[Title]]) -> FALSE | C4: =ISBLANK(FUNDS[[#This Row],[FundEnabled]]) -> FALSE | D4: =IF(LEN(FUNDS[[#This Row],[FundCode]])<100,FALSE,TRUE) -> FALSE | E4: =IF(LEN(FUNDS[[#This Row],[Title]])<100,FALSE,TRUE) -> FALSE | F4: =COUNTIF(FUNDS[[#This Row],[Code is Blank]:[Title length check]],"TRUE") -> 0 | G4: 01 | H4: title | I4: TRUE

Sheet Activity
G1: API - Do not edit
A2: Code is Blank | B2: Title is Blank | C2: Code length Check | D2: Title length check | E2: Enabled is blank | F2: Will import if zero | G2: ActivityCode | H2: Title | I2: ActivityEnabled
A3: =ISBLANK(ACTIVITIES[[#This Row],[ActivityCode]]) -> FALSE | B3: =ISBLANK(ACTIVITIES[[#This Row],[Title]]) -> FALSE | C3: =IF(LEN(ACTIVITIES[[#This Row],[ActivityCode]])<100,FALSE,TRUE) -> FALSE | D3: =IF(LEN(ACTIVITIES[[#This Row],[Title]])<100,FALSE,TRUE) -> FALSE | E3: =ISBLANK(ACTIVITIES[[#This Row],[ActivityEnabled]]) -> FALSE | F3: =COUNTIF(ACTIVITIES[[#This Row],[Code is Blank]:[Enabled is blank]],"TRUE") -> 0 | G3: DEFAULT | H3: Default (no) Activity | I3: TRUE

Sheet Ledger
G1: API - Do not edit
A2: Code is Blank | B2: Title is Blank | C2: Enabled is blank | D2: Code length Check | E2: Title length check | F2: Will import if zero | G2: LedgerCode | H2: Title | I2: LedgerEnabled
A3: =ISBLANK(LEDGER[[#This Row],[LedgerCode]]) -> FALSE | B3: =ISBLANK(LEDGER[[#This Row],[Title]]) -> FALSE | C3: =ISBLANK(LEDGER[[#This Row],[LedgerEnabled]]) -> FALSE | D3: =IF(LEN(LEDGER[[#This Row],[LedgerCode]])<100,FALSE,TRUE) -> FALSE | E3: =IF(LEN(LEDGER[[#This Row],[Title]])<100,FALSE,TRUE) -> FALSE | F3: =COUNTIF(LEDGER[[#This Row],[Code is Blank]:[Title length check]],"TRUE") -> 0 | G3: DEFAULT | H3: Default (no) Ledger | I3: TRUE
A4: =ISBLANK(LEDGER[[#This Row],[LedgerCode]]) -> FALSE | B4: =ISBLANK(LEDGER[[#This Row],[Title]]) -> FALSE | C4: =ISBLANK(LEDGER[[#This Row],[LedgerEnabled]]) -> FALSE | D4: =IF(LEN(LEDGER[[#This Row],[LedgerCode]])<100,FALSE,TRUE) -> FALSE | E4: =IF(LEN(LEDGER[[#This Row],[Title]])<100,FALSE,TRUE) -> FALSE | F4: =COUNTIF(LEDGER[[#This Row],[Code is Blank]:[Title length check]],"TRUE") -> 0 | G4: DEPARTMENTS | H4: Departments Ledger | I4: TRUE

Sheet CustGroup
G1: API - Do not edit
A2: Code is Blank | B2: Title is Blank | C2: Code length Check | D2: Title length check | E2: Enabled is blank | F2: Will import if zero | G2: CustomGroupingCode | H2: Title | I2: CustomGroupingEnabled
A3: =ISBLANK(CUSTGROUP[[#This Row],[CustomGroupingCode]]) -> FALSE | B3: =ISBLANK(CUSTGROUP[[#This Row],[Title]]) -> FALSE | C3: =IF(LEN(CUSTGROUP[[#This Row],[CustomGroupingCode]])<100,FALSE,TRUE) -> FALSE | D3: =IF(LEN(CUSTGROUP[[#This Row],[Title]])<100,FALSE,TRUE) -> FALSE | E3: =ISBLANK(CUSTGROUP[[#This Row],[CustomGroupingEnabled]]) -> FALSE | F3: =COUNTIF(CUSTGROUP[[#This Row],[Code is Blank]:[Enabled is blank]],"TRUE") -> 0 | G3: ZZZ | H3: Default Custom Group | I3: TRUE

Sheet SchHub
G1: API - Do not edit
A2: Code is Blank | B2: Title is Blank | C2: Enabled is blank | D2: Code length Check | E2: Title length check | F2: Will import if zero | G2: SchoolHubCode | H2: Title | I2: SchoolHubEnabled
A3: =ISBLANK(SCHHUB[[#This Row],[SchoolHubCode]]) -> FALSE | B3: =ISBLANK(SCHHUB[[#This Row],[Title]]) -> FALSE | C3: =ISBLANK(SCHHUB[[#This Row],[SchoolHubEnabled]]) -> FALSE | D3: =IF(LEN(SCHHUB[[#This Row],[SchoolHubCode]])<100,FALSE,TRUE) -> FALSE | E3: =IF(LEN(SCHHUB[[#This Row],[Title]])<100,FALSE,TRUE) -> FALSE | F3: =COUNTIF(SCHHUB[[#This Row],[Code is Blank]:[Title length check]],"TRUE") -> 0 | G3: MAT | H3: Mat Hub | I3: TRUE
A4: =ISBLANK(SCHHUB[[#This Row],[SchoolHubCode]]) -> FALSE | B4: =ISBLANK(SCHHUB[[#This Row],[Title]]) -> FALSE | C4: =ISBLANK(SCHHUB[[#This Row],[SchoolHubEnabled]]) -> FALSE | D4: =IF(LEN(SCHHUB[[#This Row],[SchoolHubCode]])<100,FALSE,TRUE) -> FALSE | E4: =IF(LEN(SCHHUB[[#This Row],[Title]])<100,FALSE,TRUE) -> FALSE | F4: =COUNTIF(SCHHUB[[#This Row],[Code is Blank]:[Title length check]],"TRUE") -> 0 | G4: DEFAULT | H4: Default | I4: TRUE

Sheet SchType
G1: API - Do not edit
A2: Code is Blank | B2: Title is Blank | C2: Enabled is blank | D2: Code length Check | E2: Title length check | F2: Will import if zero | G2: SchoolTypeCode | H2: Title | I2: SchoolTypeEnabled
A3: =ISBLANK(SCHTYPE[[#This Row],[SchoolTypeCode]]) -> FALSE | B3: =ISBLANK(SCHTYPE[[#This Row],[Title]]) -> FALSE | C3: =ISBLANK(SCHTYPE[[#This Row],[SchoolTypeEnabled]]) -> FALSE | D3: =IF(LEN(SCHTYPE[[#This Row],[SchoolTypeCode]])<100,FALSE,TRUE) -> FALSE | E3: =IF(LEN(SCHTYPE[[#This Row],[Title]])<100,FALSE,TRUE) -> FALSE | F3: =COUNTIF(SCHTYPE[[#This Row],[Code is Blank]:[Title length check]],"TRUE") -> 0 | G3: CENTRAL | H3: Central Services | I3: TRUE
A4: =ISBLANK(SCHTYPE[[#This Row],[SchoolTypeCode]]) -> FALSE | B4: =ISBLANK(SCHTYPE[[#This Row],[Title]]) -> FALSE | C4: =ISBLANK(SCHTYPE[[#This Row],[SchoolTypeEnabled]]) -> FALSE | D4: =IF(LEN(SCHTYPE[[#This Row],[SchoolTypeCode]])<100,FALSE,TRUE) -> FALSE | E4: =IF(LEN(SCHTYPE[[#This Row],[Title]])<100,FALSE,TRUE) -> FALSE | F4: =COUNTIF(SCHTYPE[[#This Row],[Code is Blank]:[Title length check]],"TRUE") -> 0 | G4: PRIMARY | H4: Primary | I4: TRUE
A5: =ISBLANK(SCHTYPE[[#This Row],[SchoolTypeCode]]) -> FALSE | B5: =ISBLANK(SCHTYPE[[#This Row],[Title]]) -> FALSE | C5: =ISBLANK(SCHTYPE[[#This Row],[SchoolTypeEnabled]]) -> FALSE | D5: =IF(LEN(SCHTYPE[[#This Row],[SchoolTypeCode]])<100,FALSE,TRUE) -> FALSE | E5: =IF(LEN(SCHTYPE[[#This Row],[Title]])<100,FALSE,TRUE) -> FALSE | F5: =COUNTIF(SCHTYPE[[#This Row],[Code is Blank]:[Title length check]],"TRUE") -> 0 | G5: SECONDARY | H5: Secondary | I5: TRUE
A6: =ISBLANK(SCHTYPE[[#This Row],[SchoolTypeCode]]) -> FALSE | B6: =ISBLANK(SCHTYPE[[#This Row],[Title]]) -> FALSE | C6: =ISBLANK(SCHTYPE[[#This Row],[SchoolTypeEnabled]]) -> FALSE | D6: =IF(LEN(SCHTYPE[[#This Row],[SchoolTypeCode]])<100,FALSE,TRUE) -> FALSE | E6: =IF(LEN(SCHTYPE[[#This Row],[Title]])<100,FALSE,TRUE) -> FALSE | F6: =COUNTIF(SCHTYPE[[#This Row],[Code is Blank]:[Title length check]],"TRUE") -> 0 | G6: ALLTHROUGH | H6: All Through | I6: TRUE
A7: =ISBLANK(SCHTYPE[[#This Row],[SchoolTypeCode]]) -> FALSE | B7: =ISBLANK(SCHTYPE[[#This Row],[Title]]) -> FALSE | C7: =ISBLANK(SCHTYPE[[#This Row],[SchoolTypeEnabled]]) -> FALSE | D7: =IF(LEN(SCHTYPE[[#This Row],[SchoolTypeCode]])<100,FALSE,TRUE) -> FALSE | E7: =IF(LEN(SCHTYPE[[#This Row],[Title]])<100,FALSE,TRUE) -> FALSE | F7: =COUNTIF(SCHTYPE[[#This Row],[Code is Blank]:[Title length check]],"TRUE") -> 0 | G7: TEACHING | H7: Teaching | I7: TRUE
A8: =ISBLANK(SCHTYPE[[#This Row],[SchoolTypeCode]]) -> FALSE | B8: =ISBLANK(SCHTYPE[[#This Row],[Title]]) -> FALSE | C8: =ISBLANK(SCHTYPE[[#This Row],[SchoolTypeEnabled]]) -> FALSE | D8: =IF(LEN(SCHTYPE[[#This Row],[SchoolTypeCode]])<100,FALSE,TRUE) -> FALSE | E8: =IF(LEN(SCHTYPE[[#This Row],[Title]])<100,FALSE,TRUE) -> FALSE | F8: =COUNTIF(SCHTYPE[[#This Row],[Code is Blank]:[Title length check]],"TRUE") -> 0 | G8: SPECIAL | H8: Special | I8: TRUE
A9: =ISBLANK(SCHTYPE[[#This Row],[SchoolTypeCode]]) -> FALSE | B9: =ISBLANK(SCHTYPE[[#This Row],[Title]]) -> FALSE | C9: =ISBLANK(SCHTYPE[[#This Row],[SchoolTypeEnabled]]) -> FALSE | D9: =IF(LEN(SCHTYPE[[#This Row],[SchoolTypeCode]])<100,FALSE,TRUE) -> FALSE | E9: =IF(LEN(SCHTYPE[[#This Row],[Title]])<100,FALSE,TRUE) -> FALSE | F9: =COUNTIF(SCHTYPE[[#This Row],[Code is Blank]:[Title length check]],"TRUE") -> 0 | G9: OTHER | H9: Other | I9: TRUE
A10: =ISBLANK(SCHTYPE[[#This Row],[SchoolTypeCode]]) -> FALSE | B10: =ISBLANK(SCHTYPE[[#This Row],[Title]]) -> FALSE | C10: =ISBLANK(SCHTYPE[[#This Row],[SchoolTypeEnabled]]) -> FALSE | D10: =IF(LEN(SCHTYPE[[#This Row],[SchoolTypeCode]])<100,FALSE,TRUE) -> FALSE | E10: =IF(LEN(SCHTYPE[[#This Row],[Title]])<100,FALSE,TRUE) -> FALSE | F10: =COUNTIF(SCHTYPE[[#This Row],[Code is Blank]:[Title length check]],"TRUE") -> 0 | G10: LA | H10: LA | I10: TRUE

Sheet LocalAuth
G1: This grey section can be edited | H1: API - Do not edit
A2: Code is Blank | B2: Title is Blank | C2: Enabled is blank | D2: Code length Check | E2: Title length check | F2: Will import if zero | G2: LA | H2: SchoolLocalAuthorityCode | I2: Title | J2: SchoolLocalAuthorityEnabled
A3: =ISBLANK(LocalAuth[[#This Row],[SchoolLocalAuthorityCode]]) -> FALSE | B3: =ISBLANK(LocalAuth[[#This Row],[Title]]) -> FALSE | C3: =ISBLANK(LocalAuth[[#This Row],[SchoolLocalAuthorityEnabled]]) -> FALSE | D3: =IF(LEN(LocalAuth[[#This Row],[SchoolLocalAuthorityCode]])<100,FALSE,TRUE) -> FALSE | E3: =IF(LEN(LocalAuth[[#This Row],[Title]])<100,FALSE,TRUE) -> FALSE | F3: =COUNTIF(LocalAuth[[#This Row],[Code is Blank]:[Title length check]],"TRUE") -> 0 | G3: LA0 | H3: DEFAULT | I3: Default (no) Activity | J3: TRUE
A4: =ISBLANK(LocalAuth[[#This Row],[SchoolLocalAuthorityCode]]) -> FALSE | B4: =ISBLANK(LocalAuth[[#This Row],[Title]]) -> FALSE | C4: =ISBLANK(LocalAuth[[#This Row],[SchoolLocalAuthorityEnabled]]) -> FALSE | D4: =IF(LEN(LocalAuth[[#This Row],[SchoolLocalAuthorityCode]])<100,FALSE,TRUE) -> FALSE | E4: =IF(LEN(LocalAuth[[#This Row],[Title]])<100,FALSE,TRUE) -> FALSE | F4: =COUNTIF(LocalAuth[[#This Row],[Code is Blank]:[Title length check]],"TRUE") -> 0 | G4: LA1 | H4: DEV | I4: Devon | J4: TRUE
A5: =ISBLANK(LocalAuth[[#This Row],[SchoolLocalAuthorityCode]]) -> FALSE | B5: =ISBLANK(LocalAuth[[#This Row],[Title]]) -> FALSE | C5: =ISBLANK(LocalAuth[[#This Row],[SchoolLocalAuthorityEnabled]]) -> FALSE | D5: =IF(LEN(LocalAuth[[#This Row],[SchoolLocalAuthorityCode]])<100,FALSE,TRUE) -> FALSE | E5: =IF(LEN(LocalAuth[[#This Row],[Title]])<100,FALSE,TRUE) -> FALSE | F5: =COUNTIF(LocalAuth[[#This Row],[Code is Blank]:[Title length check]],"TRUE") -> 0 | G5: LA2 | H5: COR | I5: Cornwall | J5: TRUE

Sheet Schools
G1: This grey section can be edited | J1: API - Do not edit
A2: HubIssues | B2: SchTypeIssue | C2: Blank Data | D2: Code length Check | E2: Title length check | F2: Will Import if 0 | G2: London Weighting Type | H2: LA | I2: School Type | J2: SchoolLocalAuthority | K2: SchoolCode | L2: SchoolHub | M2: SchoolType | N2: Title | O2: LondonWeighting | P2: UniqueReferenceNumber | Q2: TeachingHours | R2: SchoolEnabled
A3: =IF(COUNTIF(SCHHUB[SchoolHubCode],SCHOOLS[[#This Row],[SchoolHub]])>0,0,1) -> 0 | B3: =IF(COUNTIF(SCHTYPE[SchoolTypeCode],SCHOOLS[[#This Row],[SchoolType]])>0,0,1) -> 0 | C3: =COUNTBLANK(SCHOOLS[[#This Row],[SchoolLocalAuthority]:[SchoolEnabled]]) -> 0 | D3: =IF(LEN(SCHOOLS[[#This Row],[SchoolCode]])<100,0,1) -> 0 | E3: =IF(LEN(SCHOOLS[[#This Row],[Title]])<100,0,1) -> 0 | F3: =SUM(SCHOOLS[[#This Row],[HubIssues]:[Title length check]]) -> 0 | G3: England & Wales | H3: =_xlfn.XLOOKUP(SCHOOLS[[#This Row],[SchoolLocalAuthority]],LocalAuth[SchoolLocalAuthorityCode],LocalAuth[LA]) -> LA2 | I3: Central | J3: COR | K3: ALL | L3: MAT | M3: ALLTHROUGH | N3: Allthrough | O3: FALSE | P3: 0 | Q3: 32.5 | R3: TRUE
A4: =IF(COUNTIF(SCHHUB[SchoolHubCode],SCHOOLS[[#This Row],[SchoolHub]])>0,0,1) -> 0 | B4: =IF(COUNTIF(SCHTYPE[SchoolTypeCode],SCHOOLS[[#This Row],[SchoolType]])>0,0,1) -> 0 | C4: =COUNTBLANK(SCHOOLS[[#This Row],[SchoolLocalAuthority]:[SchoolEnabled]]) -> 0 | D4: =IF(LEN(SCHOOLS[[#This Row],[SchoolCode]])<100,0,1) -> 0 | E4: =IF(LEN(SCHOOLS[[#This Row],[Title]])<100,0,1) -> 0 | F4: =SUM(SCHOOLS[[#This Row],[HubIssues]:[Title length check]]) -> 0 | G4: England & Wales | H4: =_xlfn.XLOOKUP(SCHOOLS[[#This Row],[SchoolLocalAuthority]],LocalAuth[SchoolLocalAuthorityCode],LocalAuth[LA]) -> LA1 | I4: Secondary | J4: DEV | K4: MAT | L4: MAT | M4: CENTRAL | N4: Central Services | O4: FALSE | P4: 0 | Q4: 32.5 | R4: TRUE
A5: =IF(COUNTIF(SCHHUB[SchoolHubCode],SCHOOLS[[#This Row],[SchoolHub]])>0,0,1) -> 0 | B5: =IF(COUNTIF(SCHTYPE[SchoolTypeCode],SCHOOLS[[#This Row],[SchoolType]])>0,0,1) -> 0 | C5: =COUNTBLANK(SCHOOLS[[#This Row],[SchoolLocalAuthority]:[SchoolEnabled]]) -> 0 | D5: =IF(LEN(SCHOOLS[[#This Row],[SchoolCode]])<100,0,1) -> 0 | E5: =IF(LEN(SCHOOLS[[#This Row],[Title]])<100,0,1) -> 0 | F5: =SUM(SCHOOLS[[#This Row],[HubIssues]:[Title length check]]) -> 0 | G5: England & Wales | H5: =_xlfn.XLOOKUP(SCHOOLS[[#This Row],[SchoolLocalAuthority]],LocalAuth[SchoolLocalAuthorityCode],LocalAuth[LA]) -> LA1 | I5: Primary | J5: DEV | K5: PRI | L5: MAT | M5: PRIMARY | N5: Primary | O5: FALSE | P5: 0 | Q5: 32.5 | R5: TRUE
A6: =IF(COUNTIF(SCHHUB[SchoolHubCode],SCHOOLS[[#This Row],[SchoolHub]])>0,0,1) -> 0 | B6: =IF(COUNTIF(SCHTYPE[SchoolTypeCode],SCHOOLS[[#This Row],[SchoolType]])>0,0,1) -> 0 | C6: =COUNTBLANK(SCHOOLS[[#This Row],[SchoolLocalAuthority]:[SchoolEnabled]]) -> 0 | D6: =IF(LEN(SCHOOLS[[#This Row],[SchoolCode]])<100,0,1) -> 0 | E6: =IF(LEN(SCHOOLS[[#This Row],[Title]])<100,0,1) -> 0 | F6: =SUM(SCHOOLS[[#This Row],[HubIssues]:[Title length check]]) -> 0 | G6: England & Wales | H6: =_xlfn.XLOOKUP(SCHOOLS[[#This Row],[SchoolLocalAuthority]],LocalAuth[SchoolLocalAuthorityCode],LocalAuth[LA]) -> LA1 | I6: AllThrough | J6: DEV | K6: SEC | L6: MAT | M6: SECONDARY | N6: Secondary | O6: FALSE | P6: 0 | Q6: 32.5 | R6: TRUE
A7: =IF(COUNTIF(SCHHUB[SchoolHubCode],SCHOOLS[[#This Row],[SchoolHub]])>0,0,1) -> 0 | B7: =IF(COUNTIF(SCHTYPE[SchoolTypeCode],SCHOOLS[[#This Row],[SchoolType]])>0,0,1) -> 0 | C7: =COUNTBLANK(SCHOOLS[[#This Row],[SchoolLocalAuthority]:[SchoolEnabled]]) -> 0 | D7: =IF(LEN(SCHOOLS[[#This Row],[SchoolCode]])<100,0,1) -> 0 | E7: =IF(LEN(SCHOOLS[[#This Row],[Title]])<100,0,1) -> 0 | F7: =SUM(SCHOOLS[[#This Row],[HubIssues]:[Title length check]]) -> 0 | G7: England & Wales | H7: =_xlfn.XLOOKUP(SCHOOLS[[#This Row],[SchoolLocalAuthority]],LocalAuth[SchoolLocalAuthorityCode],LocalAuth[LA]) -> LA2 | J7: COR | K7: SPE | L7: MAT | M7: SPECIAL | N7: Special | O7: FALSE | P7: 0 | Q7: 32.5 | R7: TRUE

Sheet Depts
G1: API - Do not edit
A2: FundIssue | B2: ActivityIssue | C2: LedgerIssue | D2: Code length Check | E2: Title length check | F2: Will Import if 0 | G2: DepartmentCode | H2: Title | I2: AvailableToAllSchools | J2: SchoolCodes | K2: ActivityCode | L2: FundCode | M2: LedgerCode | N2: DefaultFinanceCode | O2: DepartmentEnabled
A3: =IF(COUNTIF(FUNDS[FundCode],DEPTS[[#This Row],[FundCode]])>0,0,1) -> 1 | B3: =IF(COUNTIF(ACTIVITIES[ActivityCode],DEPTS[[#This Row],[ActivityCode]])>0,0,1) -> 0 | C3: =IF(COUNTIF(LEDGER[LedgerCode],DEPTS[[#This Row],[LedgerCode]])>0,0,1) -> 1 | D3: =IF(LEN(DEPTS[[#This Row],[DepartmentCode]])<100,0,1) -> 0 | E3: =IF(LEN(DEPTS[[#This Row],[Title]])<100,0,1) -> 0 | F3: =SUM(DEPTS[[#This Row],[FundIssue]:[Title length check]]) -> 2 | G3: AADM | H3: Academy - Admin | I3: TRUE | K3: DEFAULT | L3: GAG | M3: COSTCTR | O3: TRUE

Sheet SourceFinanceCodes
A1: School Type | B1: LA | C1: London Weighting | D1: Key stage | E1: FinanceCode | F1: Title | G1: FinanceCodeTypeCode | H1: GroupingCode2 | I1: CustomGrouping | J1: LedgerCode | K1: AvailableToAllSchools | L1: SchoolCodes | M1: FinanceCodeEnabled | N1: BalanceToScenario
A2: All | E2: A_FTE_ADM | F2: Finance Admin Annual FTE | G2: STATISTICS | H2: Z05 | I2: ZZZ | K2: TRUE | M2: TRUE | N2: FALSE
A3: All | E3: A_FTE_CAT | F3: Catering Annual FTE | G3: STATISTICS | H3: Z05 | I3: ZZZ | K3: TRUE | M3: TRUE | N3: FALSE
A4: All | E4: A_FTE_CLE | F4: Cleaning Annual FTE | G4: STATISTICS | H4: Z05 | I4: ZZZ | K4: TRUE | M4: TRUE | N4: FALSE
A5: All | E5: A_FTE_COM | F5: Community Facilities Annual FTE | G5: STATISTICS | H5: Z05 | I5: ZZZ | K5: TRUE | M5: TRUE | N5: FALSE
A6: All | E6: A_FTE_COV | F6: Cover Annual FTE | G6: STATISTICS | H6: Z05 | I6: ZZZ | K6: TRUE | M6: TRUE | N6: FALSE
A7: All | E7: A_FTE_EDS | F7: Education Support Annual FTE | G7: STATISTICS | H7: Z05 | I7: ZZZ | K7: TRUE | M7: TRUE | N7: FALSE
A8: All | E8: A_FTE_ESTF | F8: External Staff Annual FTE | G8: STATISTICS | H8: ZZZ | I8: ZZZ | K8: TRUE | M8: TRUE | N8: FALSE
A9: All | E9: A_FTE_EXT | F9: Extended Schools Annual FTE | G9: STATISTICS | H9: Z05 | I9: ZZZ | K9: TRUE | M9: TRUE | N9: FALSE
A10: All | E10: A_FTE_FLA | F10: FLA Annual FTE | G10: STATISTICS | H10: Z05 | I10: ZZZ | K10: TRUE | M10: TRUE | N10: FALSE
A11: All | E11: A_FTE_FSW | F11: Family Support Annual FTE | G11: STATISTICS | H11: Z05 | I11: ZZZ | K11: TRUE | M11: TRUE | N11: FALSE
A12: All | E12: A_FTE_INV | F12: Invigilator Annual FTE | G12: STATISTICS | H12: Z05 | I12: ZZZ | K12: TRUE | M12: TRUE | N12: FALSE
A13: All | E13: A_FTE_LEAVE_ADJ_ADM | F13: Finance Admin Annual FTE Leave Adjustment | G13: STATISTICS | H13: Z17 | I13: ZZZ | K13: TRUE | M13: TRUE | N13: FALSE
... A92: All | E92: WK_FTE_TEC | F92: Technicians Weekly FTE | G92: STATISTICS | H92: Z03 | I92: ZZZ | K92: TRUE | M92: TRUE | N92: FALSE

Sheet 11_Finance Codes S2
A1: LedgerIssue | B1: GroupingCodeIssue | C1: CustGrIssue | D1: SchCodeIssue | E1: DupCode | F1: DupDesc | G1: FCTypeIss | H1: TRUE/FALSE Check | I1: Code length Check | J1: Blank Title Check | K1: Blank Code Check | L1: Title length check | M1: Balance to Scenario Blank | N1: Space in code | O1: Will Import if 0 | P1: FinanceCode | Q1: Title | R1: FinanceCodeTypeCode | S1: GroupingCode | T1: CustomGrouping | U1: LedgerCode | V1: AvailableToAllSchools | W1: SchoolCodes | X1: FinanceCodeEnabled | Y1: BalanceToScenario | Z1: IsBalanceSheet
A2: =IF(COUNTIF(LEDGER[LedgerCode],FC_import[[#This Row],[LedgerCode]])>0,0,1) -> 1 | B2: =IF(COUNTIF(Table_System_Grouping_Codes[groupingCodeCode],FC_import[[#This Row],[GroupingCode]])>0,0,1) -> 0 | C2: =IF(COUNTIF(CUSTGROUP[CustomGroupingCode],FC_import[[#This Row],[CustomGrouping]])>0,0,1) -> 0 | D2: {=IF(FC_import[[#This Row],[AvailableToAllSchools]]=TRUE,0,COUNTA(_xlfn.TEXTSPLIT(FC_import[[#This Row],[SchoolCodes]],",",,TRUE))-SUM(COUNTIF(SCHOOLS[SchoolCode],_xlfn.TEXTSPLIT(FC_import[[#This Row],[SchoolCodes]],",",,TRUE))))} -> 0 | E2: =IF(FC_import[[#This Row],[FinanceCodeTypeCode]]="BUDGET",0,COUNTIF(P:P,P2)-1) -> 0 | F2: =IF(FC_import[[#This Row],[FinanceCodeTypeCode]]="BUDGET",0,COUNTIF(Q:Q,Q2)-1) -> 0 | G2: =COUNTIF(Lookup!$A$2:$A$7,R2)-1 -> 0 | H2: =IF(OR(FC_import[[#This Row],[FinanceCodeEnabled]]=TRUE,FC_import[[#This Row],[FinanceCodeEnabled]]=FALSE),0,1) -> 0 | I2: =IF(LEN(FC_import[[#This Row],[FinanceCode]])<100,0,1) -> 0 | J2: =IF(TRIM(FC_import[[#This Row],[Title]])="",1,0) -> 0 | K2: =IF(TRIM(FC_import[[#This Row],[FinanceCode]])="",1,0) -> 0 | L2: =IF(LEN(FC_import[[#This Row],[Title]])<100,0,1) -> 0 | M2: =IF(ISBLANK(FC_import[[#This Row],[BalanceToScenario]]),1,0) -> 0 | N2: =IF(SUBSTITUTE(TEXT(FC_import[[#This Row],[FinanceCode]],10)," ","")=TEXT(FC_import[[#This Row],[FinanceCode]],10),0,1) -> 0 | O2: =SUM(A2:C2,E2:N2) -> 1 | P2: A_FTE_ADM | Q2: Finance Admin Annual FTE | R2: STATISTICS | S2: Z05 | T2: ZZZ | V2: TRUE | X2: TRUE | Y2: FALSE | Z2: =FALSE -> FALSE
A3: =IF(COUNTIF(LEDGER[LedgerCode],FC_import[[#This Row],[LedgerCode]])>0,0,1) -> 1 | B3: =IF(COUNTIF(Table_System_Grouping_Codes[groupingCodeCode],FC_import[[#This Row],[GroupingCode]])>0,0,1) -> 0 | C3: =IF(COUNTIF(CUSTGROUP[CustomGroupingCode],FC_import[[#This Row],[CustomGrouping]])>0,0,1) -> 0 | D3: {=IF(FC_import[[#This Row],[AvailableToAllSchools]]=TRUE,0,COUNTA(_xlfn.TEXTSPLIT(FC_import[[#This Row],[SchoolCodes]],",",,TRUE))-SUM(COUNTIF(SCHOOLS[SchoolCode],_xlfn.TEXTSPLIT(FC_import[[#This Row],[SchoolCodes]],",",,TRUE))))} -> 0 | E3: =IF(FC_import[[#This Row],[FinanceCodeTypeCode]]="BUDGET",0,COUNTIF(P:P,P3)-1) -> 0 | F3: =IF(FC_import[[#This Row],[FinanceCodeTypeCode]]="BUDGET",0,COUNTIF(Q:Q,Q3)-1) -> 0 | G3: =COUNTIF(Lookup!$A$2:$A$7,R3)-1 -> 0 | H3: =IF(OR(FC_import[[#This Row],[FinanceCodeEnabled]]=TRUE,FC_import[[#This Row],[FinanceCodeEnabled]]=FALSE),0,1) -> 0 | I3: =IF(LEN(FC_import[[#This Row],[FinanceCode]])<100,0,1) -> 0 | J3: =IF(TRIM(FC_import[[#This Row],[Title]])="",1,0) -> 0 | K3: =IF(TRIM(FC_import[[#This Row],[FinanceCode]])="",1,0) -> 0 | L3: =IF(LEN(FC_import[[#This Row],[Title]])<100,0,1) -> 0 | M3: =IF(ISBLANK(FC_import[[#This Row],[BalanceToScenario]]),1,0) -> 0 | N3: =IF(SUBSTITUTE(TEXT(FC_import[[#This Row],[FinanceCode]],10)," ","")=TEXT(FC_import[[#This Row],[FinanceCode]],10),0,1) -> 0 | O3: =SUM(A3:C3,E3:N3) -> 1 | P3: A_FTE_CAT | Q3: Catering Annual FTE | R3: STATISTICS | S3: Z05 | T3: ZZZ | V3: TRUE | X3: TRUE | Y3: FALSE | Z3: =FALSE -> FALSE
A4: =IF(COUNTIF(LEDGER[LedgerCode],FC_import[[#This Row],[LedgerCode]])>0,0,1) -> 1 | B4: =IF(COUNTIF(Table_System_Grouping_Codes[groupingCodeCode],FC_import[[#This Row],[GroupingCode]])>0,0,1) -> 0 | C4: =IF(COUNTIF(CUSTGROUP[CustomGroupingCode],FC_import[[#This Row],[CustomGrouping]])>0,0,1) -> 0 | D4: {=IF(FC_import[[#This Row],[AvailableToAllSchools]]=TRUE,0,COUNTA(_xlfn.TEXTSPLIT(FC_import[[#This Row],[SchoolCodes]],",",,TRUE))-SUM(COUNTIF(SCHOOLS[SchoolCode],_xlfn.TEXTSPLIT(FC_import[[#This Row],[SchoolCodes]],",",,TRUE))))} -> 0 | E4: =IF(FC_import[[#This Row],[FinanceCodeTypeCode]]="BUDGET",0,COUNTIF(P:P,P4)-1) -> 0 | F4: =IF(FC_import[[#This Row],[FinanceCodeTypeCode]]="BUDGET",0,COUNTIF(Q:Q,Q4)-1) -> 0 | G4: =COUNTIF(Lookup!$A$2:$A$7,R4)-1 -> 0 | H4: =IF(OR(FC_import[[#This Row],[FinanceCodeEnabled]]=TRUE,FC_import[[#This Row],[FinanceCodeEnabled]]=FALSE),0,1) -> 0 | I4: =IF(LEN(FC_import[[#This Row],[FinanceCode]])<100,0,1) -> 0 | J4: =IF(TRIM(FC_import[[#This Row],[Title]])="",1,0) -> 0 | K4: =IF(TRIM(FC_import[[#This Row],[FinanceCode]])="",1,0) -> 0 | L4: =IF(LEN(FC_import[[#This Row],[Title]])<100,0,1) -> 0 | M4: =IF(ISBLANK(FC_import[[#This Row],[BalanceToScenario]]),1,0) -> 0 | N4: =IF(SUBSTITUTE(TEXT(FC_import[[#This Row],[FinanceCode]],10)," ","")=TEXT(FC_import[[#This Row],[FinanceCode]],10),0,1) -> 0 | O4: =SUM(A4:C4,E4:N4) -> 1 | P4: A_FTE_CLE | Q4: Cleaning Annual FTE | R4: STATISTICS | S4: Z05 | T4: ZZZ | V4: TRUE | X4: TRUE | Y4: FALSE | Z4: =FALSE -> FALSE
A5: =IF(COUNTIF(LEDGER[LedgerCode],FC_import[[#This Row],[LedgerCode]])>0,0,1) -> 1 | B5: =IF(COUNTIF(Table_System_Grouping_Codes[groupingCodeCode],FC_import[[#This Row],[GroupingCode]])>0,0,1) -> 0 | C5: =IF(COUNTIF(CUSTGROUP[CustomGroupingCode],FC_import[[#This Row],[CustomGrouping]])>0,0,1) -> 0 | D5: {=IF(FC_import[[#This Row],[AvailableToAllSchools]]=TRUE,0,COUNTA(_xlfn.TEXTSPLIT(FC_import[[#This Row],[SchoolCodes]],",",,TRUE))-SUM(COUNTIF(SCHOOLS[SchoolCode],_xlfn.TEXTSPLIT(FC_import[[#This Row],[SchoolCodes]],",",,TRUE))))} -> 0 | E5: =IF(FC_import[[#This Row],[FinanceCodeTypeCode]]="BUDGET",0,COUNTIF(P:P,P5)-1) -> 0 | F5: =IF(FC_import[[#This Row],[FinanceCodeTypeCode]]="BUDGET",0,COUNTIF(Q:Q,Q5)-1) -> 0 | G5: =COUNTIF(Lookup!$A$2:$A$7,R5)-1 -> 0 | H5: =IF(OR(FC_import[[#This Row],[FinanceCodeEnabled]]=TRUE,FC_import[[#This Row],[FinanceCodeEnabled]]=FALSE),0,1) -> 0 | I5: =IF(LEN(FC_import[[#This Row],[FinanceCode]])<100,0,1) -> 0 | J5: =IF(TRIM(FC_import[[#This Row],[Title]])="",1,0) -> 0 | K5: =IF(TRIM(FC_import[[#This Row],[FinanceCode]])="",1,0) -> 0 | L5: =IF(LEN(FC_import[[#This Row],[Title]])<100,0,1) -> 0 | M5: =IF(ISBLANK(FC_import[[#This Row],[BalanceToScenario]]),1,0) -> 0 | N5: =IF(SUBSTITUTE(TEXT(FC_import[[#This Row],[FinanceCode]],10)," ","")=TEXT(FC_import[[#This Row],[FinanceCode]],10),0,1) -> 0 | O5: =SUM(A5:C5,E5:N5) -> 1 | P5: A_FTE_COM | Q5: Community Facilities Annual FTE | R5: STATISTICS | S5: Z05 | T5: ZZZ | V5: TRUE | X5: TRUE | Y5: FALSE | Z5: =FALSE -> FALSE
A6: =IF(COUNTIF(LEDGER[LedgerCode],FC_import[[#This Row],[LedgerCode]])>0,0,1) -> 1 | B6: =IF(COUNTIF(Table_System_Grouping_Codes[groupingCodeCode],FC_import[[#This Row],[GroupingCode]])>0,0,1) -> 0 | C6: =IF(COUNTIF(CUSTGROUP[CustomGroupingCode],FC_import[[#This Row],[CustomGrouping]])>0,0,1) -> 0 | D6: {=IF(FC_import[[#This Row],[AvailableToAllSchools]]=TRUE,0,COUNTA(_xlfn.TEXTSPLIT(FC_import[[#This Row],[SchoolCodes]],",",,TRUE))-SUM(COUNTIF(SCHOOLS[SchoolCode],_xlfn.TEXTSPLIT(FC_import[[#This Row],[SchoolCodes]],",",,TRUE))))} -> 0 | E6: =IF(FC_import[[#This Row],[FinanceCodeTypeCode]]="BUDGET",0,COUNTIF(P:P,P6)-1) -> 0 | F6: =IF(FC_import[[#This Row],[FinanceCodeTypeCode]]="BUDGET",0,COUNTIF(Q:Q,Q6)-1) -> 0 | G6: =COUNTIF(Lookup!$A$2:$A$7,R6)-1 -> 0 | H6: =IF(OR(FC_import[[#This Row],[FinanceCodeEnabled]]=TRUE,FC_import[[#This Row],[FinanceCodeEnabled]]=FALSE),0,1) -> 0 | I6: =IF(LEN(FC_import[[#This Row],[FinanceCode]])<100,0,1) -> 0 | J6: =IF(TRIM(FC_import[[#This Row],[Title]])="",1,0) -> 0 | K6: =IF(TRIM(FC_import[[#This Row],[FinanceCode]])="",1,0) -> 0 | L6: =IF(LEN(FC_import[[#This Row],[Title]])<100,0,1) -> 0 | M6: =IF(ISBLANK(FC_import[[#This Row],[BalanceToScenario]]),1,0) -> 0 | N6: =IF(SUBSTITUTE(TEXT(FC_import[[#This Row],[FinanceCode]],10)," ","")=TEXT(FC_import[[#This Row],[FinanceCode]],10),0,1) -> 0 | O6: =SUM(A6:C6,E6:N6) -> 1 | P6: A_FTE_COV | Q6: Cover Annual FTE | R6: STATISTICS | S6: Z05 | T6: ZZZ | V6: TRUE | X6: TRUE | Y6: FALSE | Z6: =FALSE -> FALSE
A7: =IF(COUNTIF(LEDGER[LedgerCode],FC_import[[#This Row],[LedgerCode]])>0,0,1) -> 1 | B7: =IF(COUNTIF(Table_System_Grouping_Codes[groupingCodeCode],FC_import[[#This Row],[GroupingCode]])>0,0,1) -> 0 | C7: =IF(COUNTIF(CUSTGROUP[CustomGroupingCode],FC_import[[#This Row],[CustomGrouping]])>0,0,1) -> 0 | D7: {=IF(FC_import[[#This Row],[AvailableToAllSchools]]=TRUE,0,COUNTA(_xlfn.TEXTSPLIT(FC_import[[#This Row],[SchoolCodes]],",",,TRUE))-SUM(COUNTIF(SCHOOLS[SchoolCode],_xlfn.TEXTSPLIT(FC_import[[#This Row],[SchoolCodes]],",",,TRUE))))} -> 0 | E7: =IF(FC_import[[#This Row],[FinanceCodeTypeCode]]="BUDGET",0,COUNTIF(P:P,P7)-1) -> 0 | F7: =IF(FC_import[[#This Row],[FinanceCodeTypeCode]]="BUDGET",0,COUNTIF(Q:Q,Q7)-1) -> 0 | G7: =COUNTIF(Lookup!$A$2:$A$7,R7)-1 -> 0 | H7: =IF(OR(FC_import[[#This Row],[FinanceCodeEnabled]]=TRUE,FC_import[[#This Row],[FinanceCodeEnabled]]=FALSE),0,1) -> 0 | I7: =IF(LEN(FC_import[[#This Row],[FinanceCode]])<100,0,1) -> 0 | J7: =IF(TRIM(FC_import[[#This Row],[Title]])="",1,0) -> 0 | K7: =IF(TRIM(FC_import[[#This Row],[FinanceCode]])="",1,0) -> 0 | L7: =IF(LEN(FC_import[[#This Row],[Title]])<100,0,1) -> 0 | M7: =IF(ISBLANK(FC_import[[#This Row],[BalanceToScenario]]),1,0) -> 0 | N7: =IF(SUBSTITUTE(TEXT(FC_import[[#This Row],[FinanceCode]],10)," ","")=TEXT(FC_import[[#This Row],[FinanceCode]],10),0,1) -> 0 | O7: =SUM(A7:C7,E7:N7) -> 1 | P7: A_FTE_EDS | Q7: Education Support Annual FTE | R7: STATISTICS | S7: Z05 | T7: ZZZ | V7: TRUE | X7: TRUE | Y7: FALSE | Z7: =FALSE -> FALSE
A8: =IF(COUNTIF(LEDGER[LedgerCode],FC_import[[#This Row],[LedgerCode]])>0,0,1) -> 1 | B8: =IF(COUNTIF(Table_System_Grouping_Codes[groupingCodeCode],FC_import[[#This Row],[GroupingCode]])>0,0,1) -> 0 | C8: =IF(COUNTIF(CUSTGROUP[CustomGroupingCode],FC_import[[#This Row],[CustomGrouping]])>0,0,1) -> 0 | D8: {=IF(FC_import[[#This Row],[AvailableToAllSchools]]=TRUE,0,COUNTA(_xlfn.TEXTSPLIT(FC_import[[#This Row],[SchoolCodes]],",",,TRUE))-SUM(COUNTIF(SCHOOLS[SchoolCode],_xlfn.TEXTSPLIT(FC_import[[#This Row],[SchoolCodes]],",",,TRUE))))} -> 0 | E8: =IF(FC_import[[#This Row],[FinanceCodeTypeCode]]="BUDGET",0,COUNTIF(P:P,P8)-1) -> 0 | F8: =IF(FC_import[[#This Row],[FinanceCodeTypeCode]]="BUDGET",0,COUNTIF(Q:Q,Q8)-1) -> 0 | G8: =COUNTIF(Lookup!$A$2:$A$7,R8)-1 -> 0 | H8: =IF(OR(FC_import[[#This Row],[FinanceCodeEnabled]]=TRUE,FC_import[[#This Row],[FinanceCodeEnabled]]=FALSE),0,1) -> 0 | I8: =IF(LEN(FC_import[[#This Row],[FinanceCode]])<100,0,1) -> 0 | J8: =IF(TRIM(FC_import[[#This Row],[Title]])="",1,0) -> 0 | K8: =IF(TRIM(FC_import[[#This Row],[FinanceCode]])="",1,0) -> 0 | L8: =IF(LEN(FC_import[[#This Row],[Title]])<100,0,1) -> 0 | M8: =IF(ISBLANK(FC_import[[#This Row],[BalanceToScenario]]),1,0) -> 0 | N8: =IF(SUBSTITUTE(TEXT(FC_import[[#This Row],[FinanceCode]],10)," ","")=TEXT(FC_import[[#This Row],[FinanceCode]],10),0,1) -> 0 | O8: =SUM(A8:C8,E8:N8) -> 1 | P8: A_FTE_ESTF | Q8: External Staff Annual FTE | R8: STATISTICS | S8: ZZZ | T8: ZZZ | V8: TRUE | X8: TRUE | Y8: FALSE | Z8: =FALSE -> FALSE
A9: =IF(COUNTIF(LEDGER[LedgerCode],FC_import[[#This Row],[LedgerCode]])>0,0,1) -> 1 | B9: =IF(COUNTIF(Table_System_Grouping_Codes[groupingCodeCode],FC_import[[#This Row],[GroupingCode]])>0,0,1) -> 0 | C9: =IF(COUNTIF(CUSTGROUP[CustomGroupingCode],FC_import[[#This Row],[CustomGrouping]])>0,0,1) -> 0 | D9: {=IF(FC_import[[#This Row],[AvailableToAllSchools]]=TRUE,0,COUNTA(_xlfn.TEXTSPLIT(FC_import[[#This Row],[SchoolCodes]],",",,TRUE))-SUM(COUNTIF(SCHOOLS[SchoolCode],_xlfn.TEXTSPLIT(FC_import[[#This Row],[SchoolCodes]],",",,TRUE))))} -> 0 | E9: =IF(FC_import[[#This Row],[FinanceCodeTypeCode]]="BUDGET",0,COUNTIF(P:P,P9)-1) -> 0 | F9: =IF(FC_import[[#This Row],[FinanceCodeTypeCode]]="BUDGET",0,COUNTIF(Q:Q,Q9)-1) -> 0 | G9: =COUNTIF(Lookup!$A$2:$A$7,R9)-1 -> 0 | H9: =IF(OR(FC_import[[#This Row],[FinanceCodeEnabled]]=TRUE,FC_import[[#This Row],[FinanceCodeEnabled]]=FALSE),0,1) -> 0 | I9: =IF(LEN(FC_import[[#This Row],[FinanceCode]])<100,0,1) -> 0 | J9: =IF(TRIM(FC_import[[#This Row],[Title]])="",1,0) -> 0 | K9: =IF(TRIM(FC_import[[#This Row],[FinanceCode]])="",1,0) -> 0 | L9: =IF(LEN(FC_import[[#This Row],[Title]])<100,0,1) -> 0 | M9: =IF(ISBLANK(FC_import[[#This Row],[BalanceToScenario]]),1,0) -> 0 | N9: =IF(SUBSTITUTE(TEXT(FC_import[[#This Row],[FinanceCode]],10)," ","")=TEXT(FC_import[[#This Row],[FinanceCode]],10),0,1) -> 0 | O9: =SUM(A9:C9,E9:N9) -> 1 | P9: A_FTE_EXT | Q9: Extended Schools Annual FTE | R9: STATISTICS | S9: Z05 | T9: ZZZ | V9: TRUE | X9: TRUE | Y9: FALSE | Z9: =FALSE -> FALSE
A10: =IF(COUNTIF(LEDGER[LedgerCode],FC_import[[#This Row],[LedgerCode]])>0,0,1) -> 1 | B10: =IF(COUNTIF(Table_System_Grouping_Codes[groupingCodeCode],FC_import[[#This Row],[GroupingCode]])>0,0,1) -> 0 | C10: =IF(COUNTIF(CUSTGROUP[CustomGroupingCode],FC_import[[#This Row],[CustomGrouping]])>0,0,1) -> 0 | D10: {=IF(FC_import[[#This Row],[AvailableToAllSchools]]=TRUE,0,COUNTA(_xlfn.TEXTSPLIT(FC_import[[#This Row],[SchoolCodes]],",",,TRUE))-SUM(COUNTIF(SCHOOLS[SchoolCode],_xlfn.TEXTSPLIT(FC_import[[#This Row],[SchoolCodes]],",",,TRUE))))} -> 0 | E10: =IF(FC_import[[#This Row],[FinanceCodeTypeCode]]="BUDGET",0,COUNTIF(P:P,P10)-1) -> 0 | F10: =IF(FC_import[[#This Row],[FinanceCodeTypeCode]]="BUDGET",0,COUNTIF(Q:Q,Q10)-1) -> 0 | G10: =COUNTIF(Lookup!$A$2:$A$7,R10)-1 -> 0 | H10: =IF(OR(FC_import[[#This Row],[FinanceCodeEnabled]]=TRUE,FC_import[[#This Row],[FinanceCodeEnabled]]=FALSE),0,1) -> 0 | I10: =IF(LEN(FC_import[[#This Row],[FinanceCode]])<100,0,1) -> 0 | J10: =IF(TRIM(FC_import[[#This Row],[Title]])="",1,0) -> 0 | K10: =IF(TRIM(FC_import[[#This Row],[FinanceCode]])="",1,0) -> 0 | L10: =IF(LEN(FC_import[[#This Row],[Title]])<100,0,1) -> 0 | M10: =IF(ISBLANK(FC_import[[#This Row],[BalanceToScenario]]),1,0) -> 0 | N10: =IF(SUBSTITUTE(TEXT(FC_import[[#This Row],[FinanceCode]],10)," ","")=TEXT(FC_import[[#This Row],[FinanceCode]],10),0,1) -> 0 | O10: =SUM(A10:C10,E10:N10) -> 1 | P10: A_FTE_FLA | Q10: FLA Annual FTE | R10: STATISTICS | S10: Z05 | T10: ZZZ | V10: TRUE | X10: TRUE | Y10: FALSE | Z10: =FALSE -> FALSE
A11: =IF(COUNTIF(LEDGER[LedgerCode],FC_import[[#This Row],[LedgerCode]])>0,0,1) -> 1 | B11: =IF(COUNTIF(Table_System_Grouping_Codes[groupingCodeCode],FC_import[[#This Row],[GroupingCode]])>0,0,1) -> 0 | C11: =IF(COUNTIF(CUSTGROUP[CustomGroupingCode],FC_import[[#This Row],[CustomGrouping]])>0,0,1) -> 0 | D11: {=IF(FC_import[[#This Row],[AvailableToAllSchools]]=TRUE,0,COUNTA(_xlfn.TEXTSPLIT(FC_import[[#This Row],[SchoolCodes]],",",,TRUE))-SUM(COUNTIF(SCHOOLS[SchoolCode],_xlfn.TEXTSPLIT(FC_import[[#This Row],[SchoolCodes]],",",,TRUE))))} -> 0 | E11: =IF(FC_import[[#This Row],[FinanceCodeTypeCode]]="BUDGET",0,COUNTIF(P:P,P11)-1) -> 0 | F11: =IF(FC_import[[#This Row],[FinanceCodeTypeCode]]="BUDGET",0,COUNTIF(Q:Q,Q11)-1) -> 0 | G11: =COUNTIF(Lookup!$A$2:$A$7,R11)-1 -> 0 | H11: =IF(OR(FC_import[[#This Row],[FinanceCodeEnabled]]=TRUE,FC_import[[#This Row],[FinanceCodeEnabled]]=FALSE),0,1) -> 0 | I11: =IF(LEN(FC_import[[#This Row],[FinanceCode]])<100,0,1) -> 0 | J11: =IF(TRIM(FC_import[[#This Row],[Title]])="",1,0) -> 0 | K11: =IF(TRIM(FC_import[[#This Row],[FinanceCode]])="",1,0) -> 0 | L11: =IF(LEN(FC_import[[#This Row],[Title]])<100,0,1) -> 0 | M11: =IF(ISBLANK(FC_import[[#This Row],[BalanceToScenario]]),1,0) -> 0 | N11: =IF(SUBSTITUTE(TEXT(FC_import[[#This Row],[FinanceCode]],10)," ","")=TEXT(FC_import[[#This Row],[FinanceCode]],10),0,1) -> 0 | O11: =SUM(A11:C11,E11:N11) -> 1 | P11: A_FTE_FSW | Q11: Family Support Annual FTE | R11: STATISTICS | S11: Z05 | T11: ZZZ | V11: TRUE | X11: TRUE | Y11: FALSE | Z11: =FALSE -> FALSE
A12: =IF(COUNTIF(LEDGER[LedgerCode],FC_import[[#This Row],[LedgerCode]])>0,0,1) -> 1 | B12: =IF(COUNTIF(Table_System_Grouping_Codes[groupingCodeCode],FC_import[[#This Row],[GroupingCode]])>0,0,1) -> 0 | C12: =IF(COUNTIF(CUSTGROUP[CustomGroupingCode],FC_import[[#This Row],[CustomGrouping]])>0,0,1) -> 0 | D12: {=IF(FC_import[[#This Row],[AvailableToAllSchools]]=TRUE,0,COUNTA(_xlfn.TEXTSPLIT(FC_import[[#This Row],[SchoolCodes]],",",,TRUE))-SUM(COUNTIF(SCHOOLS[SchoolCode],_xlfn.TEXTSPLIT(FC_import[[#This Row],[SchoolCodes]],",",,TRUE))))} -> 0 | E12: =IF(FC_import[[#This Row],[FinanceCodeTypeCode]]="BUDGET",0,COUNTIF(P:P,P12)-1) -> 0 | F12: =IF(FC_import[[#This Row],[FinanceCodeTypeCode]]="BUDGET",0,COUNTIF(Q:Q,Q12)-1) -> 0 | G12: =COUNTIF(Lookup!$A$2:$A$7,R12)-1 -> 0 | H12: =IF(OR(FC_import[[#This Row],[FinanceCodeEnabled]]=TRUE,FC_import[[#This Row],[FinanceCodeEnabled]]=FALSE),0,1) -> 0 | I12: =IF(LEN(FC_import[[#This Row],[FinanceCode]])<100,0,1) -> 0 | J12: =IF(TRIM(FC_import[[#This Row],[Title]])="",1,0) -> 0 | K12: =IF(TRIM(FC_import[[#This Row],[FinanceCode]])="",1,0) -> 0 | L12: =IF(LEN(FC_import[[#This Row],[Title]])<100,0,1) -> 0 | M12: =IF(ISBLANK(FC_import[[#This Row],[BalanceToScenario]]),1,0) -> 0 | N12: =IF(SUBSTITUTE(TEXT(FC_import[[#This Row],[FinanceCode]],10)," ","")=TEXT(FC_import[[#This Row],[FinanceCode]],10),0,1) -> 0 | O12: =SUM(A12:C12,E12:N12) -> 1 | P12: A_FTE_INV | Q12: Invigilator Annual FTE | R12: STATISTICS | S12: Z05 | T12: ZZZ | V12: TRUE | X12: TRUE | Y12: FALSE | Z12: =FALSE -> FALSE
A13: =IF(COUNTIF(LEDGER[LedgerCode],FC_import[[#This Row],[LedgerCode]])>0,0,1) -> 1 | B13: =IF(COUNTIF(Table_System_Grouping_Codes[groupingCodeCode],FC_import[[#This Row],[GroupingCode]])>0,0,1) -> 0 | C13: =IF(COUNTIF(CUSTGROUP[CustomGroupingCode],FC_import[[#This Row],[CustomGrouping]])>0,0,1) -> 0 | D13: {=IF(FC_import[[#This Row],[AvailableToAllSchools]]=TRUE,0,COUNTA(_xlfn.TEXTSPLIT(FC_import[[#This Row],[SchoolCodes]],",",,TRUE))-SUM(COUNTIF(SCHOOLS[SchoolCode],_xlfn.TEXTSPLIT(FC_import[[#This Row],[SchoolCodes]],",",,TRUE))))} -> 0 | E13: =IF(FC_import[[#This Row],[FinanceCodeTypeCode]]="BUDGET",0,COUNTIF(P:P,P13)-1) -> 0 | F13: =IF(FC_import[[#This Row],[FinanceCodeTypeCode]]="BUDGET",0,COUNTIF(Q:Q,Q13)-1) -> 0 | G13: =COUNTIF(Lookup!$A$2:$A$7,R13)-1 -> 0 | H13: =IF(OR(FC_import[[#This Row],[FinanceCodeEnabled]]=TRUE,FC_import[[#This Row],[FinanceCodeEnabled]]=FALSE),0,1) -> 0 | I13: =IF(LEN(FC_import[[#This Row],[FinanceCode]])<100,0,1) -> 0 | J13: =IF(TRIM(FC_import[[#This Row],[Title]])="",1,0) -> 0 | K13: =IF(TRIM(FC_import[[#This Row],[FinanceCode]])="",1,0) -> 0 | L13: =IF(LEN(FC_import[[#This Row],[Title]])<100,0,1) -> 0 | M13: =IF(ISBLANK(FC_import[[#This Row],[BalanceToScenario]]),1,0) -> 0 | N13: =IF(SUBSTITUTE(TEXT(FC_import[[#This Row],[FinanceCode]],10)," ","")=TEXT(FC_import[[#This Row],[FinanceCode]],10),0,1) -> 0 | O13: =SUM(A13:C13,E13:N13) -> 1 | P13: A_FTE_LEAVE_ADJ_ADM | Q13: Finance Admin Annual FTE Leave Adjustment | R13: STATISTICS | S13: Z17 | T13: ZZZ | V13: TRUE | X13: TRUE | Y13: FALSE | Z13: =FALSE -> FALSE
... A92: =IF(COUNTIF(LEDGER[LedgerCode],FC_import[[#This Row],[LedgerCode]])>0,0,1) -> 1 | B92: =IF(COUNTIF(Table_System_Grouping_Codes[groupingCodeCode],FC_import[[#This Row],[GroupingCode]])>0,0,1) -> 0 | C92: =IF(COUNTIF(CUSTGROUP[CustomGroupingCode],FC_import[[#This Row],[CustomGrouping]])>0,0,1) -> 0 | D92: {=IF(FC_import[[#This Row],[AvailableToAllSchools]]=TRUE,0,COUNTA(_xlfn.TEXTSPLIT(FC_import[[#This Row],[SchoolCodes]],",",,TRUE))-SUM(COUNTIF(SCHOOLS[SchoolCode],_xlfn.TEXTSPLIT(FC_import[[#This Row],[SchoolCodes]],",",,TRUE))))} -> 0 | E92: =IF(FC_import[[#This Row],[FinanceCodeTypeCode]]="BUDGET",0,COUNTIF(P:P,P92)-1) -> 0 | F92: =IF(FC_import[[#This Row],[FinanceCodeTypeCode]]="BUDGET",0,COUNTIF(Q:Q,Q92)-1) -> 0 | G92: =COUNTIF(Lookup!$A$2:$A$7,R92)-1 -> 0 | H92: =IF(OR(FC_import[[#This Row],[FinanceCodeEnabled]]=TRUE,FC_import[[#This Row],[FinanceCodeEnabled]]=FALSE),0,1) -> 0 | I92: =IF(LEN(FC_import[[#This Row],[FinanceCode]])<100,0,1) -> 0 | J92: =IF(TRIM(FC_import[[#This Row],[Title]])="",1,0) -> 0 | K92: =IF(TRIM(FC_import[[#This Row],[FinanceCode]])="",1,0) -> 0 | L92: =IF(LEN(FC_import[[#This Row],[Title]])<100,0,1) -> 0 | M92: =IF(ISBLANK(FC_import[[#This Row],[BalanceToScenario]]),1,0) -> 0 | N92: =IF(SUBSTITUTE(TEXT(FC_import[[#This Row],[FinanceCode]],10)," ","")=TEXT(FC_import[[#This Row],[FinanceCode]],10),0,1) -> 0 | O92: =SUM(A92:C92,E92:N92) -> 1 | P92: WK_FTE_TEC | Q92: Technicians Weekly FTE | R92: STATISTICS | S92: Z03 | T92: ZZZ | V92: TRUE | X92: TRUE | Y92: FALSE | Z92: =FALSE -> FALSE

Sheet FinanceCodes Budget
N1: API - Do not edit
A2: LedgerIssue | B2: GroupingCodeIssue | C2: CustGrIssue | D2: SchCodeIssue | E2: DupCode | F2: DupDesc | G2: FCTypeIss | H2: Blank Title Check | I2: Blank Code Check | J2: Code length Check | K2: Title length check | L2: Balance to Scenario Blank | M2: Will Import if 0 | N2: FinanceCode | O2: Title | P2: GroupingCode | Q2: CustomGrouping | R2: AvailableToAllSchools | S2: SchoolCodes | T2: FinanceCodeTypeCode | U2: LedgerCode | V2: FinanceCodeEnabled | W2: BalanceToScenario
A3: =IF(COUNTIF(LEDGER[LedgerCode],FinanceCodesBudget[[#This Row],[LedgerCode]])>0,0,1) -> 1 | B3: =IF(COUNTIF(Table_System_Grouping_Codes[groupingCodeCode],FinanceCodesBudget[[#This Row],[GroupingCode]])>0,0,1) -> 0 | C3: =IF(COUNTIF(CUSTGROUP[CustomGroupingCode],FinanceCodesBudget[[#This Row],[CustomGrouping]])>0,0,1) -> 1 | D3: {=IF(FinanceCodesBudget[[#This Row],[AvailableToAllSchools]]=TRUE,0,COUNTA(_xlfn.TEXTSPLIT(FinanceCodesBudget[[#This Row],[SchoolCodes]],",",,TRUE))-SUM(COUNTIF(SCHOOLS[SchoolCode],_xlfn.TEXTSPLIT(FinanceCodesBudget[[#This Row],[SchoolCodes]],",",,TRUE))))} -> 0 | E3: =IF(FinanceCodesBudget[[#This Row],[FinanceCodeTypeCode]]="BUDGET",0,COUNTIF(FinanceCodesBudget[FinanceCode],FinanceCodesBudget[[#This Row],[FinanceCode]])-1) -> 0 | F3: =IF(FinanceCodesBudget[[#This Row],[FinanceCodeTypeCode]]="BUDGET",0,COUNTIF(FinanceCodesBudget[Title],FinanceCodesBudget[[#This Row],[Title]])-1) -> 0 | G3: =COUNTIF(Lookup!$A$2:$A$7,FinanceCodesBudget[[#This Row],[FinanceCodeTypeCode]])-1 -> 0 | H3: =IF(TRIM(FinanceCodesBudget[[#This Row],[Title]])="",1,0) -> 0 | I3: =IF(TRIM(FinanceCodesBudget[[#This Row],[FinanceCode]])="",1,0) -> 0 | J3: =IF(LEN(FinanceCodesBudget[[#This Row],[FinanceCode]])<100,0,1) -> 0 | K3: =IF(LEN(FinanceCodesBudget[[#This Row],[Title]])<100,0,1) -> 0 | L3: =IF(ISBLANK(FinanceCodesBudget[[#This Row],[BalanceToScenario]]),1,0) -> 0 | M3: =SUM(FinanceCodesBudget[[#This Row],[LedgerIssue]:[CustGrIssue]],FinanceCodesBudget[[#This Row],[DupCode]:[Balance to Scenario Blank]]) -> 2 | N3: 510100 | O3: IN: DfE Revenue Grants: GAG (not stud supp and trust grants) | P3: 510100 | Q3: A0 | R3: TRUE | T3: BUDGET | U3: COSTCTR | V3: TRUE | W3: FALSE

Sheet 19_PayScales
A1: Duplicate Scale Code | B1: Schools Check | C1: School Code Exists | D1: TRUE /FALSE Typo | E1: Code Length | F1: Title Length | G1: Blank in column | H1: Space in Code | I1: Will Import if 0 | J1: London Weighting | K1: Increment Date | L1: Increase Date | M1: ScenarioCode | N1: PayScaleCode | O1: PayScaleTitle | P1: ServiceIncrementDateEnabled | Q1: IncrementDate | R1: IncreaseDate | S1: IncreasePercentage | T1: AvailableToAllSchools | U1: SchoolCodes | V1: PayScaleEnabled | W1: ExcludeNationalInsurance | X1: ExcludePension
A2: =COUNTIF(PAYSCALES[PayScaleCode],PAYSCALES[[#This Row],[PayScaleCode]])-1 -> 0 | B2: =IF(PAYSCALES[[#This Row],[AvailableToAllSchools]]=FALSE,IF(ISBLANK(PAYSCALES[[#This Row],[SchoolCodes]]),1,0),IF(PAYSCALES[[#This Row],[AvailableToAllSchools]]=TRUE,IF(ISBLANK(PAYSCALES[[#This Row],[SchoolCodes]]),0,1))) -> 0 | C2: {=IF(PAYSCALES[[#This Row],[AvailableToAllSchools]]=TRUE,0,COUNTA(_xlfn.TEXTSPLIT(PAYSCALES[[#This Row],[SchoolCodes]],",",,TRUE))-SUM(COUNTIF(SCHOOLS[SchoolCode],_xlfn.TEXTSPLIT(PAYSCALES[[#This Row],[SchoolCodes]],",",,TRUE))))} -> 0 | D2: =IF(OR(PAYSCALES[[#This Row],[PayScaleEnabled]]=TRUE,PAYSCALES[[#This Row],[PayScaleEnabled]]=FALSE),IF(OR(PAYSCALES[[#This Row],[ServiceIncrementDateEnabled]]=TRUE,PAYSCALES[[#This Row],[ServiceIncrementDateEnabled]]=FALSE),IF(OR(PAYSCALES[[#This Row],[AvailableToAllSchools]]=TRUE,PAYSCALES[[#This Row],[AvailableToAllSchools]]=FALSE),IF(OR(PAYSCALES[[#This Row],[ExcludeNationalInsurance]]=TRUE,PAYSCALES[[#This Row],[ExcludeNationalInsurance]]=FALSE),IF(OR(PAYSCALES[[#This Row],[ExcludePension]]=TRUE,PAYSCALES[[#This Row],[ExcludePension]]=FALSE),0,1),1),1),1),1) -> 0 | E2: =IF(LEN(PAYSCALES[[#This Row],[PayScaleCode]])<100,0,1) -> 0 | F2: =IF(LEN(PAYSCALES[[#This Row],[PayScaleTitle]])<100,0,1) -> 0 | G2: =COUNTBLANK(PAYSCALES[[#This Row],[PayScaleCode]:[AvailableToAllSchools]])+COUNTBLANK(PAYSCALES[[#This Row],[PayScaleEnabled]:[ExcludePension]]) -> 0 | H2: =IF(SUBSTITUTE(TEXT(PAYSCALES[[#This Row],[PayScaleCode]],10)," ","")=TEXT(PAYSCALES[[#This Row],[PayScaleCode]],10),0,1) -> 0 | I2: =SUM(PAYSCALES[[#This Row],[Duplicate Scale Code]:[Space in Code]]) -> 0 | J2: England & Wales | K2: =PAYSCALES[[#This Row],[IncrementDate]] -> 44440 | L2: =PAYSCALES[[#This Row],[IncreaseDate]] -> 44440 | N2: MAIN_EW | O2: Teachers Main EW | P2: FALSE | Q2: 44440 | R2: 44440 | S2: 2.75 | T2: TRUE | V2: TRUE | W2: FALSE | X2: FALSE | Z2: Note: This tab is for pay scale default % uplift (per scope)
A3: =COUNTIF(PAYSCALES[PayScaleCode],PAYSCALES[[#This Row],[PayScaleCode]])-1 -> 0 | B3: =IF(PAYSCALES[[#This Row],[AvailableToAllSchools]]=FALSE,IF(ISBLANK(PAYSCALES[[#This Row],[SchoolCodes]]),1,0),IF(PAYSCALES[[#This Row],[AvailableToAllSchools]]=TRUE,IF(ISBLANK(PAYSCALES[[#This Row],[SchoolCodes]]),0,1))) -> 0 | C3: {=IF(PAYSCALES[[#This Row],[AvailableToAllSchools]]=TRUE,0,COUNTA(_xlfn.TEXTSPLIT(PAYSCALES[[#This Row],[SchoolCodes]],",",,TRUE))-SUM(COUNTIF(SCHOOLS[SchoolCode],_xlfn.TEXTSPLIT(PAYSCALES[[#This Row],[SchoolCodes]],",",,TRUE))))} -> 0 | D3: =IF(OR(PAYSCALES[[#This Row],[PayScaleEnabled]]=TRUE,PAYSCALES[[#This Row],[PayScaleEnabled]]=FALSE),IF(OR(PAYSCALES[[#This Row],[ServiceIncrementDateEnabled]]=TRUE,PAYSCALES[[#This Row],[ServiceIncrementDateEnabled]]=FALSE),IF(OR(PAYSCALES[[#This Row],[AvailableToAllSchools]]=TRUE,PAYSCALES[[#This Row],[AvailableToAllSchools]]=FALSE),IF(OR(PAYSCALES[[#This Row],[ExcludeNationalInsurance]]=TRUE,PAYSCALES[[#This Row],[ExcludeNationalInsurance]]=FALSE),IF(OR(PAYSCALES[[#This Row],[ExcludePension]]=TRUE,PAYSCALES[[#This Row],[ExcludePension]]=FALSE),0,1),1),1),1),1) -> 0 | E3: =IF(LEN(PAYSCALES[[#This Row],[PayScaleCode]])<100,0,1) -> 0 | F3: =IF(LEN(PAYSCALES[[#This Row],[PayScaleTitle]])<100,0,1) -> 0 | G3: =COUNTBLANK(PAYSCALES[[#This Row],[PayScaleCode]:[AvailableToAllSchools]])+COUNTBLANK(PAYSCALES[[#This Row],[PayScaleEnabled]:[ExcludePension]]) -> 0 | H3: =IF(SUBSTITUTE(TEXT(PAYSCALES[[#This Row],[PayScaleCode]],10)," ","")=TEXT(PAYSCALES[[#This Row],[PayScaleCode]],10),0,1) -> 0 | I3: =SUM(PAYSCALES[[#This Row],[Duplicate Scale Code]:[Space in Code]]) -> 0 | J3: England & Wales | K3: =PAYSCALES[[#This Row],[IncrementDate]] -> 44440 | L3: =PAYSCALES[[#This Row],[IncreaseDate]] -> 44440 | N3: LP_EW | O3: Lead Practitioner EW | P3: FALSE | Q3: 44440 | R3: 44440 | S3: 2.75 | T3: TRUE | V3: TRUE | W3: FALSE | X3: FALSE
A4: =COUNTIF(PAYSCALES[PayScaleCode],PAYSCALES[[#This Row],[PayScaleCode]])-1 -> 0 | B4: =IF(PAYSCALES[[#This Row],[AvailableToAllSchools]]=FALSE,IF(ISBLANK(PAYSCALES[[#This Row],[SchoolCodes]]),1,0),IF(PAYSCALES[[#This Row],[AvailableToAllSchools]]=TRUE,IF(ISBLANK(PAYSCALES[[#This Row],[SchoolCodes]]),0,1))) -> 0 | C4: {=IF(PAYSCALES[[#This Row],[AvailableToAllSchools]]=TRUE,0,COUNTA(_xlfn.TEXTSPLIT(PAYSCALES[[#This Row],[SchoolCodes]],",",,TRUE))-SUM(COUNTIF(SCHOOLS[SchoolCode],_xlfn.TEXTSPLIT(PAYSCALES[[#This Row],[SchoolCodes]],",",,TRUE))))} -> 0 | D4: =IF(OR(PAYSCALES[[#This Row],[PayScaleEnabled]]=TRUE,PAYSCALES[[#This Row],[PayScaleEnabled]]=FALSE),IF(OR(PAYSCALES[[#This Row],[ServiceIncrementDateEnabled]]=TRUE,PAYSCALES[[#This Row],[ServiceIncrementDateEnabled]]=FALSE),IF(OR(PAYSCALES[[#This Row],[AvailableToAllSchools]]=TRUE,PAYSCALES[[#This Row],[AvailableToAllSchools]]=FALSE),IF(OR(PAYSCALES[[#This Row],[ExcludeNationalInsurance]]=TRUE,PAYSCALES[[#This Row],[ExcludeNationalInsurance]]=FALSE),IF(OR(PAYSCALES[[#This Row],[ExcludePension]]=TRUE,PAYSCALES[[#This Row],[ExcludePension]]=FALSE),0,1),1),1),1),1) -> 0 | E4: =IF(LEN(PAYSCALES[[#This Row],[PayScaleCode]])<100,0,1) -> 0 | F4: =IF(LEN(PAYSCALES[[#This Row],[PayScaleTitle]])<100,0,1) -> 0 | G4: =COUNTBLANK(PAYSCALES[[#This Row],[PayScaleCode]:[AvailableToAllSchools]])+COUNTBLANK(PAYSCALES[[#This Row],[PayScaleEnabled]:[ExcludePension]]) -> 0 | H4: =IF(SUBSTITUTE(TEXT(PAYSCALES[[#This Row],[PayScaleCode]],10)," ","")=TEXT(PAYSCALES[[#This Row],[PayScaleCode]],10),0,1) -> 0 | I4: =SUM(PAYSCALES[[#This Row],[Duplicate Scale Code]:[Space in Code]]) -> 0 | J4: England & Wales | K4: =PAYSCALES[[#This Row],[IncrementDate]] -> 44440 | L4: =PAYSCALES[[#This Row],[IncreaseDate]] -> 44440 | N4: UQ_EW | O4: Teachers Unqualified EW | P4: FALSE | Q4: 44440 | R4: 44440 | S4: 2.75 | T4: TRUE | V4: TRUE | W4: FALSE | X4: FALSE
A5: =COUNTIF(PAYSCALES[PayScaleCode],PAYSCALES[[#This Row],[PayScaleCode]])-1 -> 0 | B5: =IF(PAYSCALES[[#This Row],[AvailableToAllSchools]]=FALSE,IF(ISBLANK(PAYSCALES[[#This Row],[SchoolCodes]]),1,0),IF(PAYSCALES[[#This Row],[AvailableToAllSchools]]=TRUE,IF(ISBLANK(PAYSCALES[[#This Row],[SchoolCodes]]),0,1))) -> 0 | C5: {=IF(PAYSCALES[[#This Row],[AvailableToAllSchools]]=TRUE,0,COUNTA(_xlfn.TEXTSPLIT(PAYSCALES[[#This Row],[SchoolCodes]],",",,TRUE))-SUM(COUNTIF(SCHOOLS[SchoolCode],_xlfn.TEXTSPLIT(PAYSCALES[[#This Row],[SchoolCodes]],",",,TRUE))))} -> 0 | D5: =IF(OR(PAYSCALES[[#This Row],[PayScaleEnabled]]=TRUE,PAYSCALES[[#This Row],[PayScaleEnabled]]=FALSE),IF(OR(PAYSCALES[[#This Row],[ServiceIncrementDateEnabled]]=TRUE,PAYSCALES[[#This Row],[ServiceIncrementDateEnabled]]=FALSE),IF(OR(PAYSCALES[[#This Row],[AvailableToAllSchools]]=TRUE,PAYSCALES[[#This Row],[AvailableToAllSchools]]=FALSE),IF(OR(PAYSCALES[[#This Row],[ExcludeNationalInsurance]]=TRUE,PAYSCALES[[#This Row],[ExcludeNationalInsurance]]=FALSE),IF(OR(PAYSCALES[[#This Row],[ExcludePension]]=TRUE,PAYSCALES[[#This Row],[ExcludePension]]=FALSE),0,1),1),1),1),1) -> 0 | E5: =IF(LEN(PAYSCALES[[#This Row],[PayScaleCode]])<100,0,1) -> 0 | F5: =IF(LEN(PAYSCALES[[#This Row],[PayScaleTitle]])<100,0,1) -> 0 | G5: =COUNTBLANK(PAYSCALES[[#This Row],[PayScaleCode]:[AvailableToAllSchools]])+COUNTBLANK(PAYSCALES[[#This Row],[PayScaleEnabled]:[ExcludePension]]) -> 0 | H5: =IF(SUBSTITUTE(TEXT(PAYSCALES[[#This Row],[PayScaleCode]],10)," ","")=TEXT(PAYSCALES[[#This Row],[PayScaleCode]],10),0,1) -> 0 | I5: =SUM(PAYSCALES[[#This Row],[Duplicate Scale Code]:[Space in Code]]) -> 0 | J5: England & Wales | K5: =PAYSCALES[[#This Row],[IncrementDate]] -> 44440 | L5: =PAYSCALES[[#This Row],[IncreaseDate]] -> 44440 | N5: LS_EW | O5: Leadership Group EW | P5: FALSE | Q5: 44440 | R5: 44440 | S5: 2.75 | T5: TRUE | V5: TRUE | W5: FALSE | X5: FALSE
A6: =COUNTIF(PAYSCALES[PayScaleCode],PAYSCALES[[#This Row],[PayScaleCode]])-1 -> 0 | B6: =IF(PAYSCALES[[#This Row],[AvailableToAllSchools]]=FALSE,IF(ISBLANK(PAYSCALES[[#This Row],[SchoolCodes]]),1,0),IF(PAYSCALES[[#This Row],[AvailableToAllSchools]]=TRUE,IF(ISBLANK(PAYSCALES[[#This Row],[SchoolCodes]]),0,1))) -> 0 | C6: {=IF(PAYSCALES[[#This Row],[AvailableToAllSchools]]=TRUE,0,COUNTA(_xlfn.TEXTSPLIT(PAYSCALES[[#This Row],[SchoolCodes]],",",,TRUE))-SUM(COUNTIF(SCHOOLS[SchoolCode],_xlfn.TEXTSPLIT(PAYSCALES[[#This Row],[SchoolCodes]],",",,TRUE))))} -> 0 | D6: =IF(OR(PAYSCALES[[#This Row],[PayScaleEnabled]]=TRUE,PAYSCALES[[#This Row],[PayScaleEnabled]]=FALSE),IF(OR(PAYSCALES[[#This Row],[ServiceIncrementDateEnabled]]=TRUE,PAYSCALES[[#This Row],[ServiceIncrementDateEnabled]]=FALSE),IF(OR(PAYSCALES[[#This Row],[AvailableToAllSchools]]=TRUE,PAYSCALES[[#This Row],[AvailableToAllSchools]]=FALSE),IF(OR(PAYSCALES[[#This Row],[ExcludeNationalInsurance]]=TRUE,PAYSCALES[[#This Row],[ExcludeNationalInsurance]]=FALSE),IF(OR(PAYSCALES[[#This Row],[ExcludePension]]=TRUE,PAYSCALES[[#This Row],[ExcludePension]]=FALSE),0,1),1),1),1),1) -> 0 | E6: =IF(LEN(PAYSCALES[[#This Row],[PayScaleCode]])<100,0,1) -> 0 | F6: =IF(LEN(PAYSCALES[[#This Row],[PayScaleTitle]])<100,0,1) -> 0 | G6: =COUNTBLANK(PAYSCALES[[#This Row],[PayScaleCode]:[AvailableToAllSchools]])+COUNTBLANK(PAYSCALES[[#This Row],[PayScaleEnabled]:[ExcludePension]]) -> 0 | H6: =IF(SUBSTITUTE(TEXT(PAYSCALES[[#This Row],[PayScaleCode]],10)," ","")=TEXT(PAYSCALES[[#This Row],[PayScaleCode]],10),0,1) -> 0 | I6: =SUM(PAYSCALES[[#This Row],[Duplicate Scale Code]:[Space in Code]]) -> 0 | J6: England & Wales | K6: =PAYSCALES[[#This Row],[IncrementDate]] -> 44287 | L6: =PAYSCALES[[#This Row],[IncreaseDate]] -> 44287 | N6: NJC_EW | O6: NJC EW | P6: FALSE | Q6: 44287 | R6: 44287 | S6: 2 | T6: TRUE | V6: TRUE | W6: FALSE | X6: FALSE
A7: =COUNTIF(PAYSCALES[PayScaleCode],PAYSCALES[[#This Row],[PayScaleCode]])-1 -> 0 | B7: =IF(PAYSCALES[[#This Row],[AvailableToAllSchools]]=FALSE,IF(ISBLANK(PAYSCALES[[#This Row],[SchoolCodes]]),1,0),IF(PAYSCALES[[#This Row],[AvailableToAllSchools]]=TRUE,IF(ISBLANK(PAYSCALES[[#This Row],[SchoolCodes]]),0,1))) -> 0 | C7: {=IF(PAYSCALES[[#This Row],[AvailableToAllSchools]]=TRUE,0,COUNTA(_xlfn.TEXTSPLIT(PAYSCALES[[#This Row],[SchoolCodes]],",",,TRUE))-SUM(COUNTIF(SCHOOLS[SchoolCode],_xlfn.TEXTSPLIT(PAYSCALES[[#This Row],[SchoolCodes]],",",,TRUE))))} -> 0 | D7: =IF(OR(PAYSCALES[[#This Row],[PayScaleEnabled]]=TRUE,PAYSCALES[[#This Row],[PayScaleEnabled]]=FALSE),IF(OR(PAYSCALES[[#This Row],[ServiceIncrementDateEnabled]]=TRUE,PAYSCALES[[#This Row],[ServiceIncrementDateEnabled]]=FALSE),IF(OR(PAYSCALES[[#This Row],[AvailableToAllSchools]]=TRUE,PAYSCALES[[#This Row],[AvailableToAllSchools]]=FALSE),IF(OR(PAYSCALES[[#This Row],[ExcludeNationalInsurance]]=TRUE,PAYSCALES[[#This Row],[ExcludeNationalInsurance]]=FALSE),IF(OR(PAYSCALES[[#This Row],[ExcludePension]]=TRUE,PAYSCALES[[#This Row],[ExcludePension]]=FALSE),0,1),1),1),1),1) -> 0 | E7: =IF(LEN(PAYSCALES[[#This Row],[PayScaleCode]])<100,0,1) -> 0 | F7: =IF(LEN(PAYSCALES[[#This Row],[PayScaleTitle]])<100,0,1) -> 0 | G7: =COUNTBLANK(PAYSCALES[[#This Row],[PayScaleCode]:[AvailableToAllSchools]])+COUNTBLANK(PAYSCALES[[#This Row],[PayScaleEnabled]:[ExcludePension]]) -> 0 | H7: =IF(SUBSTITUTE(TEXT(PAYSCALES[[#This Row],[PayScaleCode]],10)," ","")=TEXT(PAYSCALES[[#This Row],[PayScaleCode]],10),0,1) -> 0 | I7: =SUM(PAYSCALES[[#This Row],[Duplicate Scale Code]:[Space in Code]]) -> 0 | J7: Fringe | K7: =PAYSCALES[[#This Row],[IncrementDate]] -> 44440 | L7: =PAYSCALES[[#This Row],[IncreaseDate]] -> 44440 | N7: MAIN_FRI | O7: Teachers Main Fringe | P7: FALSE | Q7: 44440 | R7: 44440 | S7: 2.75 | T7: TRUE | V7: TRUE | W7: FALSE | X7: FALSE
A8: =COUNTIF(PAYSCALES[PayScaleCode],PAYSCALES[[#This Row],[PayScaleCode]])-1 -> 0 | B8: =IF(PAYSCALES[[#This Row],[AvailableToAllSchools]]=FALSE,IF(ISBLANK(PAYSCALES[[#This Row],[SchoolCodes]]),1,0),IF(PAYSCALES[[#This Row],[AvailableToAllSchools]]=TRUE,IF(ISBLANK(PAYSCALES[[#This Row],[SchoolCodes]]),0,1))) -> 0 | C8: {=IF(PAYSCALES[[#This Row],[AvailableToAllSchools]]=TRUE,0,COUNTA(_xlfn.TEXTSPLIT(PAYSCALES[[#This Row],[SchoolCodes]],",",,TRUE))-SUM(COUNTIF(SCHOOLS[SchoolCode],_xlfn.TEXTSPLIT(PAYSCALES[[#This Row],[SchoolCodes]],",",,TRUE))))} -> 0 | D8: =IF(OR(PAYSCALES[[#This Row],[PayScaleEnabled]]=TRUE,PAYSCALES[[#This Row],[PayScaleEnabled]]=FALSE),IF(OR(PAYSCALES[[#This Row],[ServiceIncrementDateEnabled]]=TRUE,PAYSCALES[[#This Row],[ServiceIncrementDateEnabled]]=FALSE),IF(OR(PAYSCALES[[#This Row],[AvailableToAllSchools]]=TRUE,PAYSCALES[[#This Row],[AvailableToAllSchools]]=FALSE),IF(OR(PAYSCALES[[#This Row],[ExcludeNationalInsurance]]=TRUE,PAYSCALES[[#This Row],[ExcludeNationalInsurance]]=FALSE),IF(OR(PAYSCALES[[#This Row],[ExcludePension]]=TRUE,PAYSCALES[[#This Row],[ExcludePension]]=FALSE),0,1),1),1),1),1) -> 0 | E8: =IF(LEN(PAYSCALES[[#This Row],[PayScaleCode]])<100,0,1) -> 0 | F8: =IF(LEN(PAYSCALES[[#This Row],[PayScaleTitle]])<100,0,1) -> 0 | G8: =COUNTBLANK(PAYSCALES[[#This Row],[PayScaleCode]:[AvailableToAllSchools]])+COUNTBLANK(PAYSCALES[[#This Row],[PayScaleEnabled]:[ExcludePension]]) -> 0 | H8: =IF(SUBSTITUTE(TEXT(PAYSCALES[[#This Row],[PayScaleCode]],10)," ","")=TEXT(PAYSCALES[[#This Row],[PayScaleCode]],10),0,1) -> 0 | I8: =SUM(PAYSCALES[[#This Row],[Duplicate Scale Code]:[Space in Code]]) -> 0 | J8: Fringe | K8: =PAYSCALES[[#This Row],[IncrementDate]] -> 44440 | L8: =PAYSCALES[[#This Row],[IncreaseDate]] -> 44440 | N8: LP_FRI | O8: Lead Practitioner Fringe | P8: FALSE | Q8: 44440 | R8: 44440 | S8: 2.75 | T8: TRUE | V8: TRUE | W8: FALSE | X8: FALSE
A9: =COUNTIF(PAYSCALES[PayScaleCode],PAYSCALES[[#This Row],[PayScaleCode]])-1 -> 0 | B9: =IF(PAYSCALES[[#This Row],[AvailableToAllSchools]]=FALSE,IF(ISBLANK(PAYSCALES[[#This Row],[SchoolCodes]]),1,0),IF(PAYSCALES[[#This Row],[AvailableToAllSchools]]=TRUE,IF(ISBLANK(PAYSCALES[[#This Row],[SchoolCodes]]),0,1))) -> 0 | C9: {=IF(PAYSCALES[[#This Row],[AvailableToAllSchools]]=TRUE,0,COUNTA(_xlfn.TEXTSPLIT(PAYSCALES[[#This Row],[SchoolCodes]],",",,TRUE))-SUM(COUNTIF(SCHOOLS[SchoolCode],_xlfn.TEXTSPLIT(PAYSCALES[[#This Row],[SchoolCodes]],",",,TRUE))))} -> 0 | D9: =IF(OR(PAYSCALES[[#This Row],[PayScaleEnabled]]=TRUE,PAYSCALES[[#This Row],[PayScaleEnabled]]=FALSE),IF(OR(PAYSCALES[[#This Row],[ServiceIncrementDateEnabled]]=TRUE,PAYSCALES[[#This Row],[ServiceIncrementDateEnabled]]=FALSE),IF(OR(PAYSCALES[[#This Row],[AvailableToAllSchools]]=TRUE,PAYSCALES[[#This Row],[AvailableToAllSchools]]=FALSE),IF(OR(PAYSCALES[[#This Row],[ExcludeNationalInsurance]]=TRUE,PAYSCALES[[#This Row],[ExcludeNationalInsurance]]=FALSE),IF(OR(PAYSCALES[[#This Row],[ExcludePension]]=TRUE,PAYSCALES[[#This Row],[ExcludePension]]=FALSE),0,1),1),1),1),1) -> 0 | E9: =IF(LEN(PAYSCALES[[#This Row],[PayScaleCode]])<100,0,1) -> 0 | F9: =IF(LEN(PAYSCALES[[#This Row],[PayScaleTitle]])<100,0,1) -> 0 | G9: =COUNTBLANK(PAYSCALES[[#This Row],[PayScaleCode]:[AvailableToAllSchools]])+COUNTBLANK(PAYSCALES[[#This Row],[PayScaleEnabled]:[ExcludePension]]) -> 0 | H9: =IF(SUBSTITUTE(TEXT(PAYSCALES[[#This Row],[PayScaleCode]],10)," ","")=TEXT(PAYSCALES[[#This Row],[PayScaleCode]],10),0,1) -> 0 | I9: =SUM(PAYSCALES[[#This Row],[Duplicate Scale Code]:[Space in Code]]) -> 0 | J9: Fringe | K9: =PAYSCALES[[#This Row],[IncrementDate]] -> 44440 | L9: =PAYSCALES[[#This Row],[IncreaseDate]] -> 44440 | N9: UQ_FRI | O9: Teachers Unqualified Fringe | P9: FALSE | Q9: 44440 | R9: 44440 | S9: 2.75 | T9: TRUE | V9: TRUE | W9: FALSE | X9: FALSE
A10: =COUNTIF(PAYSCALES[PayScaleCode],PAYSCALES[[#This Row],[PayScaleCode]])-1 -> 0 | B10: =IF(PAYSCALES[[#This Row],[AvailableToAllSchools]]=FALSE,IF(ISBLANK(PAYSCALES[[#This Row],[SchoolCodes]]),1,0),IF(PAYSCALES[[#This Row],[AvailableToAllSchools]]=TRUE,IF(ISBLANK(PAYSCALES[[#This Row],[SchoolCodes]]),0,1))) -> 0 | C10: {=IF(PAYSCALES[[#This Row],[AvailableToAllSchools]]=TRUE,0,COUNTA(_xlfn.TEXTSPLIT(PAYSCALES[[#This Row],[SchoolCodes]],",",,TRUE))-SUM(COUNTIF(SCHOOLS[SchoolCode],_xlfn.TEXTSPLIT(PAYSCALES[[#This Row],[SchoolCodes]],",",,TRUE))))} -> 0 | D10: =IF(OR(PAYSCALES[[#This Row],[PayScaleEnabled]]=TRUE,PAYSCALES[[#This Row],[PayScaleEnabled]]=FALSE),IF(OR(PAYSCALES[[#This Row],[ServiceIncrementDateEnabled]]=TRUE,PAYSCALES[[#This Row],[ServiceIncrementDateEnabled]]=FALSE),IF(OR(PAYSCALES[[#This Row],[AvailableToAllSchools]]=TRUE,PAYSCALES[[#This Row],[AvailableToAllSchools]]=FALSE),IF(OR(PAYSCALES[[#This Row],[ExcludeNationalInsurance]]=TRUE,PAYSCALES[[#This Row],[ExcludeNationalInsurance]]=FALSE),IF(OR(PAYSCALES[[#This Row],[ExcludePension]]=TRUE,PAYSCALES[[#This Row],[ExcludePension]]=FALSE),0,1),1),1),1),1) -> 0 | E10: =IF(LEN(PAYSCALES[[#This Row],[PayScaleCode]])<100,0,1) -> 0 | F10: =IF(LEN(PAYSCALES[[#This Row],[PayScaleTitle]])<100,0,1) -> 0 | G10: =COUNTBLANK(PAYSCALES[[#This Row],[PayScaleCode]:[AvailableToAllSchools]])+COUNTBLANK(PAYSCALES[[#This Row],[PayScaleEnabled]:[ExcludePension]]) -> 0 | H10: =IF(SUBSTITUTE(TEXT(PAYSCALES[[#This Row],[PayScaleCode]],10)," ","")=TEXT(PAYSCALES[[#This Row],[PayScaleCode]],10),0,1) -> 0 | I10: =SUM(PAYSCALES[[#This Row],[Duplicate Scale Code]:[Space in Code]]) -> 0 | J10: Fringe | K10: =PAYSCALES[[#This Row],[IncrementDate]] -> 44440 | L10: =PAYSCALES[[#This Row],[IncreaseDate]] -> 44440 | N10: LS_FRI | O10: Leadership Group Fringe | P10: FALSE | Q10: 44440 | R10: 44440 | S10: 2.75 | T10: TRUE | V10: TRUE | W10: FALSE | X10: FALSE
A11: =COUNTIF(PAYSCALES[PayScaleCode],PAYSCALES[[#This Row],[PayScaleCode]])-1 -> 0 | B11: =IF(PAYSCALES[[#This Row],[AvailableToAllSchools]]=FALSE,IF(ISBLANK(PAYSCALES[[#This Row],[SchoolCodes]]),1,0),IF(PAYSCALES[[#This Row],[AvailableToAllSchools]]=TRUE,IF(ISBLANK(PAYSCALES[[#This Row],[SchoolCodes]]),0,1))) -> 0 | C11: {=IF(PAYSCALES[[#This Row],[AvailableToAllSchools]]=TRUE,0,COUNTA(_xlfn.TEXTSPLIT(PAYSCALES[[#This Row],[SchoolCodes]],",",,TRUE))-SUM(COUNTIF(SCHOOLS[SchoolCode],_xlfn.TEXTSPLIT(PAYSCALES[[#This Row],[SchoolCodes]],",",,TRUE))))} -> 0 | D11: =IF(OR(PAYSCALES[[#This Row],[PayScaleEnabled]]=TRUE,PAYSCALES[[#This Row],[PayScaleEnabled]]=FALSE),IF(OR(PAYSCALES[[#This Row],[ServiceIncrementDateEnabled]]=TRUE,PAYSCALES[[#This Row],[ServiceIncrementDateEnabled]]=FALSE),IF(OR(PAYSCALES[[#This Row],[AvailableToAllSchools]]=TRUE,PAYSCALES[[#This Row],[AvailableToAllSchools]]=FALSE),IF(OR(PAYSCALES[[#This Row],[ExcludeNationalInsurance]]=TRUE,PAYSCALES[[#This Row],[ExcludeNationalInsurance]]=FALSE),IF(OR(PAYSCALES[[#This Row],[ExcludePension]]=TRUE,PAYSCALES[[#This Row],[ExcludePension]]=FALSE),0,1),1),1),1),1) -> 0 | E11: =IF(LEN(PAYSCALES[[#This Row],[PayScaleCode]])<100,0,1) -> 0 | F11: =IF(LEN(PAYSCALES[[#This Row],[PayScaleTitle]])<100,0,1) -> 0 | G11: =COUNTBLANK(PAYSCALES[[#This Row],[PayScaleCode]:[AvailableToAllSchools]])+COUNTBLANK(PAYSCALES[[#This Row],[PayScaleEnabled]:[ExcludePension]]) -> 0 | H11: =IF(SUBSTITUTE(TEXT(PAYSCALES[[#This Row],[PayScaleCode]],10)," ","")=TEXT(PAYSCALES[[#This Row],[PayScaleCode]],10),0,1) -> 0 | I11: =SUM(PAYSCALES[[#This Row],[Duplicate Scale Code]:[Space in Code]]) -> 0 | J11: Inner | K11: =PAYSCALES[[#This Row],[IncrementDate]] -> 44440 | L11: =PAYSCALES[[#This Row],[IncreaseDate]] -> 44440 | N11: MAIN_INN | O11: Teachers Main Inner | P11: FALSE | Q11: 44440 | R11: 44440 | S11: 2.75 | T11: TRUE | V11: TRUE | W11: FALSE | X11: FALSE
A12: =COUNTIF(PAYSCALES[PayScaleCode],PAYSCALES[[#This Row],[PayScaleCode]])-1 -> 0 | B12: =IF(PAYSCALES[[#This Row],[AvailableToAllSchools]]=FALSE,IF(ISBLANK(PAYSCALES[[#This Row],[SchoolCodes]]),1,0),IF(PAYSCALES[[#This Row],[AvailableToAllSchools]]=TRUE,IF(ISBLANK(PAYSCALES[[#This Row],[SchoolCodes]]),0,1))) -> 0 | C12: {=IF(PAYSCALES[[#This Row],[AvailableToAllSchools]]=TRUE,0,COUNTA(_xlfn.TEXTSPLIT(PAYSCALES[[#This Row],[SchoolCodes]],",",,TRUE))-SUM(COUNTIF(SCHOOLS[SchoolCode],_xlfn.TEXTSPLIT(PAYSCALES[[#This Row],[SchoolCodes]],",",,TRUE))))} -> 0 | D12: =IF(OR(PAYSCALES[[#This Row],[PayScaleEnabled]]=TRUE,PAYSCALES[[#This Row],[PayScaleEnabled]]=FALSE),IF(OR(PAYSCALES[[#This Row],[ServiceIncrementDateEnabled]]=TRUE,PAYSCALES[[#This Row],[ServiceIncrementDateEnabled]]=FALSE),IF(OR(PAYSCALES[[#This Row],[AvailableToAllSchools]]=TRUE,PAYSCALES[[#This Row],[AvailableToAllSchools]]=FALSE),IF(OR(PAYSCALES[[#This Row],[ExcludeNationalInsurance]]=TRUE,PAYSCALES[[#This Row],[ExcludeNationalInsurance]]=FALSE),IF(OR(PAYSCALES[[#This Row],[ExcludePension]]=TRUE,PAYSCALES[[#This Row],[ExcludePension]]=FALSE),0,1),1),1),1),1) -> 0 | E12: =IF(LEN(PAYSCALES[[#This Row],[PayScaleCode]])<100,0,1) -> 0 | F12: =IF(LEN(PAYSCALES[[#This Row],[PayScaleTitle]])<100,0,1) -> 0 | G12: =COUNTBLANK(PAYSCALES[[#This Row],[PayScaleCode]:[AvailableToAllSchools]])+COUNTBLANK(PAYSCALES[[#This Row],[PayScaleEnabled]:[ExcludePension]]) -> 0 | H12: =IF(SUBSTITUTE(TEXT(PAYSCALES[[#This Row],[PayScaleCode]],10)," ","")=TEXT(PAYSCALES[[#This Row],[PayScaleCode]],10),0,1) -> 0 | I12: =SUM(PAYSCALES[[#This Row],[Duplicate Scale Code]:[Space in Code]]) -> 0 | J12: Inner | K12: =PAYSCALES[[#This Row],[IncrementDate]] -> 44440 | L12: =PAYSCALES[[#This Row],[IncreaseDate]] -> 44440 | N12: LP_INN | O12: Lead Practitioner Inner | P12: FALSE | Q12: 44440 | R12: 44440 | S12: 2.75 | T12: TRUE | V12: TRUE | W12: FALSE | X12: FALSE
A13: =COUNTIF(PAYSCALES[PayScaleCode],PAYSCALES[[#This Row],[PayScaleCode]])-1 -> 0 | B13: =IF(PAYSCALES[[#This Row],[AvailableToAllSchools]]=FALSE,IF(ISBLANK(PAYSCALES[[#This Row],[SchoolCodes]]),1,0),IF(PAYSCALES[[#This Row],[AvailableToAllSchools]]=TRUE,IF(ISBLANK(PAYSCALES[[#This Row],[SchoolCodes]]),0,1))) -> 0 | C13: {=IF(PAYSCALES[[#This Row],[AvailableToAllSchools]]=TRUE,0,COUNTA(_xlfn.TEXTSPLIT(PAYSCALES[[#This Row],[SchoolCodes]],",",,TRUE))-SUM(COUNTIF(SCHOOLS[SchoolCode],_xlfn.TEXTSPLIT(PAYSCALES[[#This Row],[SchoolCodes]],",",,TRUE))))} -> 0 | D13: =IF(OR(PAYSCALES[[#This Row],[PayScaleEnabled]]=TRUE,PAYSCALES[[#This Row],[PayScaleEnabled]]=FALSE),IF(OR(PAYSCALES[[#This Row],[ServiceIncrementDateEnabled]]=TRUE,PAYSCALES[[#This Row],[ServiceIncrementDateEnabled]]=FALSE),IF(OR(PAYSCALES[[#This Row],[AvailableToAllSchools]]=TRUE,PAYSCALES[[#This Row],[AvailableToAllSchools]]=FALSE),IF(OR(PAYSCALES[[#This Row],[ExcludeNationalInsurance]]=TRUE,PAYSCALES[[#This Row],[ExcludeNationalInsurance]]=FALSE),IF(OR(PAYSCALES[[#This Row],[ExcludePension]]=TRUE,PAYSCALES[[#This Row],[ExcludePension]]=FALSE),0,1),1),1),1),1) -> 0 | E13: =IF(LEN(PAYSCALES[[#This Row],[PayScaleCode]])<100,0,1) -> 0 | F13: =IF(LEN(PAYSCALES[[#This Row],[PayScaleTitle]])<100,0,1) -> 0 | G13: =COUNTBLANK(PAYSCALES[[#This Row],[PayScaleCode]:[AvailableToAllSchools]])+COUNTBLANK(PAYSCALES[[#This Row],[PayScaleEnabled]:[ExcludePension]]) -> 0 | H13: =IF(SUBSTITUTE(TEXT(PAYSCALES[[#This Row],[PayScaleCode]],10)," ","")=TEXT(PAYSCALES[[#This Row],[PayScaleCode]],10),0,1) -> 0 | I13: =SUM(PAYSCALES[[#This Row],[Duplicate Scale Code]:[Space in Code]]) -> 0 | J13: Inner | K13: =PAYSCALES[[#This Row],[IncrementDate]] -> 44440 | L13: =PAYSCALES[[#This Row],[IncreaseDate]] -> 44440 | N13: UQ_INN | O13: Teachers Unqualified Inner | P13: FALSE | Q13: 44440 | R13: 44440 | S13: 2.75 | T13: TRUE | V13: TRUE | W13: FALSE | X13: FALSE
A14: =COUNTIF(PAYSCALES[PayScaleCode],PAYSCALES[[#This Row],[PayScaleCode]])-1 -> 0 | B14: =IF(PAYSCALES[[#This Row],[AvailableToAllSchools]]=FALSE,IF(ISBLANK(PAYSCALES[[#This Row],[SchoolCodes]]),1,0),IF(PAYSCALES[[#This Row],[AvailableToAllSchools]]=TRUE,IF(ISBLANK(PAYSCALES[[#This Row],[SchoolCodes]]),0,1))) -> 0 | C14: {=IF(PAYSCALES[[#This Row],[AvailableToAllSchools]]=TRUE,0,COUNTA(_xlfn.TEXTSPLIT(PAYSCALES[[#This Row],[SchoolCodes]],",",,TRUE))-SUM(COUNTIF(SCHOOLS[SchoolCode],_xlfn.TEXTSPLIT(PAYSCALES[[#This Row],[SchoolCodes]],",",,TRUE))))} -> 0 | D14: =IF(OR(PAYSCALES[[#This Row],[PayScaleEnabled]]=TRUE,PAYSCALES[[#This Row],[PayScaleEnabled]]=FALSE),IF(OR(PAYSCALES[[#This Row],[ServiceIncrementDateEnabled]]=TRUE,PAYSCALES[[#This Row],[ServiceIncrementDateEnabled]]=FALSE),IF(OR(PAYSCALES[[#This Row],[AvailableToAllSchools]]=TRUE,PAYSCALES[[#This Row],[AvailableToAllSchools]]=FALSE),IF(OR(PAYSCALES[[#This Row],[ExcludeNationalInsurance]]=TRUE,PAYSCALES[[#This Row],[ExcludeNationalInsurance]]=FALSE),IF(OR(PAYSCALES[[#This Row],[ExcludePension]]=TRUE,PAYSCALES[[#This Row],[ExcludePension]]=FALSE),0,1),1),1),1),1) -> 0 | E14: =IF(LEN(PAYSCALES[[#This Row],[PayScaleCode]])<100,0,1) -> 0 | F14: =IF(LEN(PAYSCALES[[#This Row],[PayScaleTitle]])<100,0,1) -> 0 | G14: =COUNTBLANK(PAYSCALES[[#This Row],[PayScaleCode]:[AvailableToAllSchools]])+COUNTBLANK(PAYSCALES[[#This Row],[PayScaleEnabled]:[ExcludePension]]) -> 0 | H14: =IF(SUBSTITUTE(TEXT(PAYSCALES[[#This Row],[PayScaleCode]],10)," ","")=TEXT(PAYSCALES[[#This Row],[PayScaleCode]],10),0,1) -> 0 | I14: =SUM(PAYSCALES[[#This Row],[Duplicate Scale Code]:[Space in Code]]) -> 0 | J14: Inner | K14: =PAYSCALES[[#This Row],[IncrementDate]] -> 44440 | L14: =PAYSCALES[[#This Row],[IncreaseDate]] -> 44440 | N14: LS_INN | O14: Leadership Group Inner | P14: FALSE | Q14: 44440 | R14: 44440 | S14: 2.75 | T14: TRUE | V14: TRUE | W14: FALSE | X14: FALSE
... A21: =COUNTIF(PAYSCALES[PayScaleCode],PAYSCALES[[#This Row],[PayScaleCode]])-1 -> 0 | B21: =IF(PAYSCALES[[#This Row],[AvailableToAllSchools]]=FALSE,IF(ISBLANK(PAYSCALES[[#This Row],[SchoolCodes]]),1,0),IF(PAYSCALES[[#This Row],[AvailableToAllSchools]]=TRUE,IF(ISBLANK(PAYSCALES[[#This Row],[SchoolCodes]]),0,1))) -> 0 | C21: {=IF(PAYSCALES[[#This Row],[AvailableToAllSchools]]=TRUE,0,COUNTA(_xlfn.TEXTSPLIT(PAYSCALES[[#This Row],[SchoolCodes]],",",,TRUE))-SUM(COUNTIF(SCHOOLS[SchoolCode],_xlfn.TEXTSPLIT(PAYSCALES[[#This Row],[SchoolCodes]],",",,TRUE))))} -> 0 | D21: =IF(OR(PAYSCALES[[#This Row],[PayScaleEnabled]]=TRUE,PAYSCALES[[#This Row],[PayScaleEnabled]]=FALSE),IF(OR(PAYSCALES[[#This Row],[ServiceIncrementDateEnabled]]=TRUE,PAYSCALES[[#This Row],[ServiceIncrementDateEnabled]]=FALSE),IF(OR(PAYSCALES[[#This Row],[AvailableToAllSchools]]=TRUE,PAYSCALES[[#This Row],[AvailableToAllSchools]]=FALSE),IF(OR(PAYSCALES[[#This Row],[ExcludeNationalInsurance]]=TRUE,PAYSCALES[[#This Row],[ExcludeNationalInsurance]]=FALSE),IF(OR(PAYSCALES[[#This Row],[ExcludePension]]=TRUE,PAYSCALES[[#This Row],[ExcludePension]]=FALSE),0,1),1),1),1),1) -> 0 | E21: =IF(LEN(PAYSCALES[[#This Row],[PayScaleCode]])<100,0,1) -> 0 | F21: =IF(LEN(PAYSCALES[[#This Row],[PayScaleTitle]])<100,0,1) -> 0 | G21: =COUNTBLANK(PAYSCALES[[#This Row],[PayScaleCode]:[AvailableToAllSchools]])+COUNTBLANK(PAYSCALES[[#This Row],[PayScaleEnabled]:[ExcludePension]]) -> 0 | H21: =IF(SUBSTITUTE(TEXT(PAYSCALES[[#This Row],[PayScaleCode]],10)," ","")=TEXT(PAYSCALES[[#This Row],[PayScaleCode]],10),0,1) -> 0 | I21: =SUM(PAYSCALES[[#This Row],[Duplicate Scale Code]:[Space in Code]]) -> 0 | J21: England & Wales | K21: =PAYSCALES[[#This Row],[IncrementDate]] -> 44652 | L21: =PAYSCALES[[#This Row],[IncreaseDate]] -> 44652 | N21: APP_NMW | O21: Apprentice / NMW Scale | P21: FALSE | Q21: 44652 | R21: 44652 | S21: 3 | T21: TRUE | V21: TRUE | W21: FALSE | X21: FALSE
A22: =COUNTIF(PAYSCALES[PayScaleCode],PAYSCALES[[#This Row],[PayScaleCode]])-1 -> 0 | B22: =IF(PAYSCALES[[#This Row],[AvailableToAllSchools]]=FALSE,IF(ISBLANK(PAYSCALES[[#This Row],[SchoolCodes]]),1,0),IF(PAYSCALES[[#This Row],[AvailableToAllSchools]]=TRUE,IF(ISBLANK(PAYSCALES[[#This Row],[SchoolCodes]]),0,1))) -> 0 | C22: {=IF(PAYSCALES[[#This Row],[AvailableToAllSchools]]=TRUE,0,COUNTA(_xlfn.TEXTSPLIT(PAYSCALES[[#This Row],[SchoolCodes]],",",,TRUE))-SUM(COUNTIF(SCHOOLS[SchoolCode],_xlfn.TEXTSPLIT(PAYSCALES[[#This Row],[SchoolCodes]],",",,TRUE))))} -> 0 | D22: =IF(OR(PAYSCALES[[#This Row],[PayScaleEnabled]]=TRUE,PAYSCALES[[#This Row],[PayScaleEnabled]]=FALSE),IF(OR(PAYSCALES[[#This Row],[ServiceIncrementDateEnabled]]=TRUE,PAYSCALES[[#This Row],[ServiceIncrementDateEnabled]]=FALSE),IF(OR(PAYSCALES[[#This Row],[AvailableToAllSchools]]=TRUE,PAYSCALES[[#This Row],[AvailableToAllSchools]]=FALSE),IF(OR(PAYSCALES[[#This Row],[ExcludeNationalInsurance]]=TRUE,PAYSCALES[[#This Row],[ExcludeNationalInsurance]]=FALSE),IF(OR(PAYSCALES[[#This Row],[ExcludePension]]=TRUE,PAYSCALES[[#This Row],[ExcludePension]]=FALSE),0,1),1),1),1),1) -> 0 | E22: =IF(LEN(PAYSCALES[[#This Row],[PayScaleCode]])<100,0,1) -> 0 | F22: =IF(LEN(PAYSCALES[[#This Row],[PayScaleTitle]])<100,0,1) -> 0 | G22: =COUNTBLANK(PAYSCALES[[#This Row],[PayScaleCode]:[AvailableToAllSchools]])+COUNTBLANK(PAYSCALES[[#This Row],[PayScaleEnabled]:[ExcludePension]]) -> 0 | H22: =IF(SUBSTITUTE(TEXT(PAYSCALES[[#This Row],[PayScaleCode]],10)," ","")=TEXT(PAYSCALES[[#This Row],[PayScaleCode]],10),0,1) -> 0 | I22: =SUM(PAYSCALES[[#This Row],[Duplicate Scale Code]:[Space in Code]]) -> 0 | K22: =PAYSCALES[[#This Row],[IncrementDate]] -> 44287 | L22: =PAYSCALES[[#This Row],[IncreaseDate]] -> 44287 | N22: SPOT_SUP | O22: Spot Salary Scale - Support | P22: FALSE | Q22: 44287 | R22: 44287 | S22: 2 | T22: TRUE | V22: TRUE | W22: FALSE | X22: FALSE
A23: =COUNTIF(PAYSCALES[PayScaleCode],PAYSCALES[[#This Row],[PayScaleCode]])-1 -> 0 | B23: =IF(PAYSCALES[[#This Row],[AvailableToAllSchools]]=FALSE,IF(ISBLANK(PAYSCALES[[#This Row],[SchoolCodes]]),1,0),IF(PAYSCALES[[#This Row],[AvailableToAllSchools]]=TRUE,IF(ISBLANK(PAYSCALES[[#This Row],[SchoolCodes]]),0,1))) -> 0 | C23: {=IF(PAYSCALES[[#This Row],[AvailableToAllSchools]]=TRUE,0,COUNTA(_xlfn.TEXTSPLIT(PAYSCALES[[#This Row],[SchoolCodes]],",",,TRUE))-SUM(COUNTIF(SCHOOLS[SchoolCode],_xlfn.TEXTSPLIT(PAYSCALES[[#This Row],[SchoolCodes]],",",,TRUE))))} -> 0 | D23: =IF(OR(PAYSCALES[[#This Row],[PayScaleEnabled]]=TRUE,PAYSCALES[[#This Row],[PayScaleEnabled]]=FALSE),IF(OR(PAYSCALES[[#This Row],[ServiceIncrementDateEnabled]]=TRUE,PAYSCALES[[#This Row],[ServiceIncrementDateEnabled]]=FALSE),IF(OR(PAYSCALES[[#This Row],[AvailableToAllSchools]]=TRUE,PAYSCALES[[#This Row],[AvailableToAllSchools]]=FALSE),IF(OR(PAYSCALES[[#This Row],[ExcludeNationalInsurance]]=TRUE,PAYSCALES[[#This Row],[ExcludeNationalInsurance]]=FALSE),IF(OR(PAYSCALES[[#This Row],[ExcludePension]]=TRUE,PAYSCALES[[#This Row],[ExcludePension]]=FALSE),0,1),1),1),1),1) -> 0 | E23: =IF(LEN(PAYSCALES[[#This Row],[PayScaleCode]])<100,0,1) -> 0 | F23: =IF(LEN(PAYSCALES[[#This Row],[PayScaleTitle]])<100,0,1) -> 0 | G23: =COUNTBLANK(PAYSCALES[[#This Row],[PayScaleCode]:[AvailableToAllSchools]])+COUNTBLANK(PAYSCALES[[#This Row],[PayScaleEnabled]:[ExcludePension]]) -> 0 | H23: =IF(SUBSTITUTE(TEXT(PAYSCALES[[#This Row],[PayScaleCode]],10)," ","")=TEXT(PAYSCALES[[#This Row],[PayScaleCode]],10),0,1) -> 0 | I23: =SUM(PAYSCALES[[#This Row],[Duplicate Scale Code]:[Space in Code]]) -> 0 | K23: =PAYSCALES[[#This Row],[IncrementDate]] -> 44440 | L23: =PAYSCALES[[#This Row],[IncreaseDate]] -> 44440 | N23: SPOT_TEA | O23: Spot Salary Scale - Teaching | P23: FALSE | Q23: 44440 | R23: 44440 | S23: 2.75 | T23: TRUE | V23: TRUE | W23: FALSE | X23: FALSE

Sheet 22_PayScaleGrades
A1: Pay Scale issue | B1: Duplicate Grade Code | C1: Schools Check | D1: Scale Point Number From/To Issue | E1: PayScaleGrade and PayScaleCode Available to School | F1: TRUE /FALSE Typo | G1: Blank in column | H1: Code Length | I1: Title Length | J1: Space in Code | K1: Will Import if 0 | L1: London Weighting | M1: ScenarioCode | N1: PayScaleGradeCode | O1: Title | P1: PayScaleCode | Q1: Point From (Check) | R1: Point To (Check) | S1: ScalePointNumberFrom | T1: ScalePointNumberTo | U1: AvailableToAllSchools | V1: SchoolCodes | W1: PayScaleGradeEnabled
A2: =IF(COUNTIF('19_PayScales'!N:N,'22_PayScaleGrades'!P2)>0,"0","1") -> 0 | B2: =COUNTIF(GRADES[PayScaleGradeCode],GRADES[[#This Row],[PayScaleGradeCode]])-1 -> 0 | C2: {=IF(GRADES[[#This Row],[AvailableToAllSchools]]=FALSE,IF(ISBLANK(GRADES[[#This Row],[SchoolCodes]]),1,IF(AND(COUNTIF(SCHOOLS[SchoolCode],_xlfn.TEXTSPLIT(GRADES[[#This Row],[SchoolCodes]],","))),0,1)),IF(GRADES[[#This Row],[AvailableToAllSchools]]=TRUE,IF(ISBLANK(GRADES[[#This Row],[SchoolCodes]]),0,1)))} -> 0 | E2: {=IF(_xlfn.XLOOKUP(GRADES[[#This Row],[PayScaleCode]],PAYSCALES[PayScaleCode],PAYSCALES[AvailableToAllSchools])=TRUE,0,IF(GRADES[[#This Row],[AvailableToAllSchools]]=TRUE,1,IF(_xlfn.LET(_xlpm.sourceCodes, _xlfn.TEXTSPLIT(GRADES[[#This Row],[SchoolCodes]], ","),_xlpm.targetCodes, _xlfn.TEXTSPLIT(_xlfn.XLOOKUP(GRADES[[#This Row],[PayScaleCode]],PAYSCALES[PayScaleCode],PAYSCALES[SchoolCodes],1), ","),_xlpm.trimmedSource, TRIM(_xlpm.sourceCodes),_xlpm.trimmedTarget, TRIM(_xlpm.targetCodes),_xlpm.matches, ISNUMBER(MATCH(_xlpm.trimmedSource, _xlpm.trimmedTarget, 0)),AND(_xlpm.matches))=TRUE,0,1)))} -> 0 | F2: =IF(OR(GRADES[[#This Row],[AvailableToAllSchools]]=TRUE,GRADES[[#This Row],[AvailableToAllSchools]]=FALSE),IF(OR(GRADES[[#This Row],[PayScaleGradeEnabled]]=TRUE,GRADES[[#This Row],[PayScaleGradeEnabled]]=FALSE),0,1),1) -> 0 | G2: =(COUNTBLANK(GRADES[[#This Row],[PayScaleGradeCode]:[AvailableToAllSchools]])+COUNTBLANK(GRADES[[#This Row],[PayScaleGradeEnabled]])) -> 0 | H2: =IF(LEN(GRADES[[#This Row],[PayScaleGradeCode]])<100,0,1) -> 0 | I2: =IF(LEN(GRADES[[#This Row],[Title]])<100,0,1) -> 0 | J2: =IF(SUBSTITUTE(TEXT(GRADES[[#This Row],[PayScaleGradeCode]],10)," ","")=TEXT(GRADES[[#This Row],[PayScaleGradeCode]],10),0,1) -> 0 | K2: =SUM(GRADES[[#This Row],[Pay Scale issue]:[Schools Check]],GRADES[[#This Row],[TRUE /FALSE Typo]:[Space in Code]]) -> 0 | L2: =_xlfn.XLOOKUP(GRADES[[#This Row],[PayScaleCode]],PAYSCALES[PayScaleCode],PAYSCALES[London Weighting]) -> England & Wales | N2: MAIN_UPS | O2: Teachers Main through UPS | P2: MAIN_EW | Q2: M1 | R2: U3 | S2: {=LOOKUP(2,1/(PSPOINTS[PayScaleCode]=GRADES[[#This Row],[PayScaleCode]])/(PSPOINTS[PayScalePointCode]=GRADES[[#This Row],[Point From (Check)]]),(PSPOINTS[ScalePointNumber]))} -> 1 | T2: {=LOOKUP(2,1/(PSPOINTS[PayScaleCode]=GRADES[[#This Row],[PayScaleCode]])/(PSPOINTS[PayScalePointCode]=GRADES[[#This Row],[Point To (Check)]]),(PSPOINTS[ScalePointNumber]))} -> 11 | U2: TRUE | W2: TRUE
A3: =IF(COUNTIF('19_PayScales'!N:N,'22_PayScaleGrades'!P3)>0,"0","1") -> 0 | B3: =COUNTIF(GRADES[PayScaleGradeCode],GRADES[[#This Row],[PayScaleGradeCode]])-1 -> 0 | C3: {=IF(GRADES[[#This Row],[AvailableToAllSchools]]=FALSE,IF(ISBLANK(GRADES[[#This Row],[SchoolCodes]]),1,IF(AND(COUNTIF(SCHOOLS[SchoolCode],_xlfn.TEXTSPLIT(GRADES[[#This Row],[SchoolCodes]],","))),0,1)),IF(GRADES[[#This Row],[AvailableToAllSchools]]=TRUE,IF(ISBLANK(GRADES[[#This Row],[SchoolCodes]]),0,1)))} -> 0 | E3: {=IF(_xlfn.XLOOKUP(GRADES[[#This Row],[PayScaleCode]],PAYSCALES[PayScaleCode],PAYSCALES[AvailableToAllSchools])=TRUE,0,IF(GRADES[[#This Row],[AvailableToAllSchools]]=TRUE,1,IF(_xlfn.LET(_xlpm.sourceCodes, _xlfn.TEXTSPLIT(GRADES[[#This Row],[SchoolCodes]], ","),_xlpm.targetCodes, _xlfn.TEXTSPLIT(_xlfn.XLOOKUP(GRADES[[#This Row],[PayScaleCode]],PAYSCALES[PayScaleCode],PAYSCALES[SchoolCodes],1), ","),_xlpm.trimmedSource, TRIM(_xlpm.sourceCodes),_xlpm.trimmedTarget, TRIM(_xlpm.targetCodes),_xlpm.matches, ISNUMBER(MATCH(_xlpm.trimmedSource, _xlpm.trimmedTarget, 0)),AND(_xlpm.matches))=TRUE,0,1)))} -> 0 | F3: =IF(OR(GRADES[[#This Row],[AvailableToAllSchools]]=TRUE,GRADES[[#This Row],[AvailableToAllSchools]]=FALSE),IF(OR(GRADES[[#This Row],[PayScaleGradeEnabled]]=TRUE,GRADES[[#This Row],[PayScaleGradeEnabled]]=FALSE),0,1),1) -> 0 | G3: =(COUNTBLANK(GRADES[[#This Row],[PayScaleGradeCode]:[AvailableToAllSchools]])+COUNTBLANK(GRADES[[#This Row],[PayScaleGradeEnabled]])) -> 0 | H3: =IF(LEN(GRADES[[#This Row],[PayScaleGradeCode]])<100,0,1) -> 0 | I3: =IF(LEN(GRADES[[#This Row],[Title]])<100,0,1) -> 0 | J3: =IF(SUBSTITUTE(TEXT(GRADES[[#This Row],[PayScaleGradeCode]],10)," ","")=TEXT(GRADES[[#This Row],[PayScaleGradeCode]],10),0,1) -> 0 | K3: =SUM(GRADES[[#This Row],[Pay Scale issue]:[Schools Check]],GRADES[[#This Row],[TRUE /FALSE Typo]:[Space in Code]]) -> 0 | L3: =_xlfn.XLOOKUP(GRADES[[#This Row],[PayScaleCode]],PAYSCALES[PayScaleCode],PAYSCALES[London Weighting]) -> England & Wales | N3: MAIN | O3: Teachers Main Scale only | P3: MAIN_EW | Q3: M1 | R3: M6 | S3: {=LOOKUP(2,1/(PSPOINTS[PayScaleCode]=GRADES[[#This Row],[PayScaleCode]])/(PSPOINTS[PayScalePointCode]=GRADES[[#This Row],[Point From (Check)]]),(PSPOINTS[ScalePointNumber]))} -> 1 | T3: {=LOOKUP(2,1/(PSPOINTS[PayScaleCode]=GRADES[[#This Row],[PayScaleCode]])/(PSPOINTS[PayScalePointCode]=GRADES[[#This Row],[Point To (Check)]]),(PSPOINTS[ScalePointNumber]))} -> 6 | U3: TRUE | W3: TRUE
A4: =IF(COUNTIF('19_PayScales'!N:N,'22_PayScaleGrades'!P4)>0,"0","1") -> 0 | B4: =COUNTIF(GRADES[PayScaleGradeCode],GRADES[[#This Row],[PayScaleGradeCode]])-1 -> 0 | C4: {=IF(GRADES[[#This Row],[AvailableToAllSchools]]=FALSE,IF(ISBLANK(GRADES[[#This Row],[SchoolCodes]]),1,IF(AND(COUNTIF(SCHOOLS[SchoolCode],_xlfn.TEXTSPLIT(GRADES[[#This Row],[SchoolCodes]],","))),0,1)),IF(GRADES[[#This Row],[AvailableToAllSchools]]=TRUE,IF(ISBLANK(GRADES[[#This Row],[SchoolCodes]]),0,1)))} -> 0 | E4: {=IF(_xlfn.XLOOKUP(GRADES[[#This Row],[PayScaleCode]],PAYSCALES[PayScaleCode],PAYSCALES[AvailableToAllSchools])=TRUE,0,IF(GRADES[[#This Row],[AvailableToAllSchools]]=TRUE,1,IF(_xlfn.LET(_xlpm.sourceCodes, _xlfn.TEXTSPLIT(GRADES[[#This Row],[SchoolCodes]], ","),_xlpm.targetCodes, _xlfn.TEXTSPLIT(_xlfn.XLOOKUP(GRADES[[#This Row],[PayScaleCode]],PAYSCALES[PayScaleCode],PAYSCALES[SchoolCodes],1), ","),_xlpm.trimmedSource, TRIM(_xlpm.sourceCodes),_xlpm.trimmedTarget, TRIM(_xlpm.targetCodes),_xlpm.matches, ISNUMBER(MATCH(_xlpm.trimmedSource, _xlpm.trimmedTarget, 0)),AND(_xlpm.matches))=TRUE,0,1)))} -> 0 | F4: =IF(OR(GRADES[[#This Row],[AvailableToAllSchools]]=TRUE,GRADES[[#This Row],[AvailableToAllSchools]]=FALSE),IF(OR(GRADES[[#This Row],[PayScaleGradeEnabled]]=TRUE,GRADES[[#This Row],[PayScaleGradeEnabled]]=FALSE),0,1),1) -> 0 | G4: =(COUNTBLANK(GRADES[[#This Row],[PayScaleGradeCode]:[AvailableToAllSchools]])+COUNTBLANK(GRADES[[#This Row],[PayScaleGradeEnabled]])) -> 0 | H4: =IF(LEN(GRADES[[#This Row],[PayScaleGradeCode]])<100,0,1) -> 0 | I4: =IF(LEN(GRADES[[#This Row],[Title]])<100,0,1) -> 0 | J4: =IF(SUBSTITUTE(TEXT(GRADES[[#This Row],[PayScaleGradeCode]],10)," ","")=TEXT(GRADES[[#This Row],[PayScaleGradeCode]],10),0,1) -> 0 | K4: =SUM(GRADES[[#This Row],[Pay Scale issue]:[Schools Check]],GRADES[[#This Row],[TRUE /FALSE Typo]:[Space in Code]]) -> 0 | L4: =_xlfn.XLOOKUP(GRADES[[#This Row],[PayScaleCode]],PAYSCALES[PayScaleCode],PAYSCALES[London Weighting]) -> England & Wales | N4: UPS | O4: Teachers Upper Scale only | P4: MAIN_EW | Q4: U1Y1 | R4: U3 | S4: {=LOOKUP(2,1/(PSPOINTS[PayScaleCode]=GRADES[[#This Row],[PayScaleCode]])/(PSPOINTS[PayScalePointCode]=GRADES[[#This Row],[Point From (Check)]]),(PSPOINTS[ScalePointNumber]))} -> 7 | T4: {=LOOKUP(2,1/(PSPOINTS[PayScaleCode]=GRADES[[#This Row],[PayScaleCode]])/(PSPOINTS[PayScalePointCode]=GRADES[[#This Row],[Point To (Check)]]),(PSPOINTS[ScalePointNumber]))} -> 11 | U4: TRUE | W4: TRUE
A5: =IF(COUNTIF('19_PayScales'!N:N,'22_PayScaleGrades'!P5)>0,"0","1") -> 0 | B5: =COUNTIF(GRADES[PayScaleGradeCode],GRADES[[#This Row],[PayScaleGradeCode]])-1 -> 0 | C5: {=IF(GRADES[[#This Row],[AvailableToAllSchools]]=FALSE,IF(ISBLANK(GRADES[[#This Row],[SchoolCodes]]),1,IF(AND(COUNTIF(SCHOOLS[SchoolCode],_xlfn.TEXTSPLIT(GRADES[[#This Row],[SchoolCodes]],","))),0,1)),IF(GRADES[[#This Row],[AvailableToAllSchools]]=TRUE,IF(ISBLANK(GRADES[[#This Row],[SchoolCodes]]),0,1)))} -> 0 | E5: {=IF(_xlfn.XLOOKUP(GRADES[[#This Row],[PayScaleCode]],PAYSCALES[PayScaleCode],PAYSCALES[AvailableToAllSchools])=TRUE,0,IF(GRADES[[#This Row],[AvailableToAllSchools]]=TRUE,1,IF(_xlfn.LET(_xlpm.sourceCodes, _xlfn.TEXTSPLIT(GRADES[[#This Row],[SchoolCodes]], ","),_xlpm.targetCodes, _xlfn.TEXTSPLIT(_xlfn.XLOOKUP(GRADES[[#This Row],[PayScaleCode]],PAYSCALES[PayScaleCode],PAYSCALES[SchoolCodes],1), ","),_xlpm.trimmedSource, TRIM(_xlpm.sourceCodes),_xlpm.trimmedTarget, TRIM(_xlpm.targetCodes),_xlpm.matches, ISNUMBER(MATCH(_xlpm.trimmedSource, _xlpm.trimmedTarget, 0)),AND(_xlpm.matches))=TRUE,0,1)))} -> 0 | F5: =IF(OR(GRADES[[#This Row],[AvailableToAllSchools]]=TRUE,GRADES[[#This Row],[AvailableToAllSchools]]=FALSE),IF(OR(GRADES[[#This Row],[PayScaleGradeEnabled]]=TRUE,GRADES[[#This Row],[PayScaleGradeEnabled]]=FALSE),0,1),1) -> 0 | G5: =(COUNTBLANK(GRADES[[#This Row],[PayScaleGradeCode]:[AvailableToAllSchools]])+COUNTBLANK(GRADES[[#This Row],[PayScaleGradeEnabled]])) -> 0 | H5: =IF(LEN(GRADES[[#This Row],[PayScaleGradeCode]])<100,0,1) -> 0 | I5: =IF(LEN(GRADES[[#This Row],[Title]])<100,0,1) -> 0 | J5: =IF(SUBSTITUTE(TEXT(GRADES[[#This Row],[PayScaleGradeCode]],10)," ","")=TEXT(GRADES[[#This Row],[PayScaleGradeCode]],10),0,1) -> 0 | K5: =SUM(GRADES[[#This Row],[Pay Scale issue]:[Schools Check]],GRADES[[#This Row],[TRUE /FALSE Typo]:[Space in Code]]) -> 0 | L5: =_xlfn.XLOOKUP(GRADES[[#This Row],[PayScaleCode]],PAYSCALES[PayScaleCode],PAYSCALES[London Weighting]) -> England & Wales | N5: UQ | O5: Teacher Unqualified | P5: UQ_EW | Q5: UQ1 | R5: UQ6 | S5: {=LOOKUP(2,1/(PSPOINTS[PayScaleCode]=GRADES[[#This Row],[PayScaleCode]])/(PSPOINTS[PayScalePointCode]=GRADES[[#This Row],[Point From (Check)]]),(PSPOINTS[ScalePointNumber]))} -> 1 | T5: {=LOOKUP(2,1/(PSPOINTS[PayScaleCode]=GRADES[[#This Row],[PayScaleCode]])/(PSPOINTS[PayScalePointCode]=GRADES[[#This Row],[Point To (Check)]]),(PSPOINTS[ScalePointNumber]))} -> 6 | U5: TRUE | W5: TRUE
A6: =IF(COUNTIF('19_PayScales'!N:N,'22_PayScaleGrades'!P6)>0,"0","1") -> 0 | B6: =COUNTIF(GRADES[PayScaleGradeCode],GRADES[[#This Row],[PayScaleGradeCode]])-1 -> 0 | C6: {=IF(GRADES[[#This Row],[AvailableToAllSchools]]=FALSE,IF(ISBLANK(GRADES[[#This Row],[SchoolCodes]]),1,IF(AND(COUNTIF(SCHOOLS[SchoolCode],_xlfn.TEXTSPLIT(GRADES[[#This Row],[SchoolCodes]],","))),0,1)),IF(GRADES[[#This Row],[AvailableToAllSchools]]=TRUE,IF(ISBLANK(GRADES[[#This Row],[SchoolCodes]]),0,1)))} -> 0 | E6: {=IF(_xlfn.XLOOKUP(GRADES[[#This Row],[PayScaleCode]],PAYSCALES[PayScaleCode],PAYSCALES[AvailableToAllSchools])=TRUE,0,IF(GRADES[[#This Row],[AvailableToAllSchools]]=TRUE,1,IF(_xlfn.LET(_xlpm.sourceCodes, _xlfn.TEXTSPLIT(GRADES[[#This Row],[SchoolCodes]], ","),_xlpm.targetCodes, _xlfn.TEXTSPLIT(_xlfn.XLOOKUP(GRADES[[#This Row],[PayScaleCode]],PAYSCALES[PayScaleCode],PAYSCALES[SchoolCodes],1), ","),_xlpm.trimmedSource, TRIM(_xlpm.sourceCodes),_xlpm.trimmedTarget, TRIM(_xlpm.targetCodes),_xlpm.matches, ISNUMBER(MATCH(_xlpm.trimmedSource, _xlpm.trimmedTarget, 0)),AND(_xlpm.matches))=TRUE,0,1)))} -> 0 | F6: =IF(OR(GRADES[[#This Row],[AvailableToAllSchools]]=TRUE,GRADES[[#This Row],[AvailableToAllSchools]]=FALSE),IF(OR(GRADES[[#This Row],[PayScaleGradeEnabled]]=TRUE,GRADES[[#This Row],[PayScaleGradeEnabled]]=FALSE),0,1),1) -> 0 | G6: =(COUNTBLANK(GRADES[[#This Row],[PayScaleGradeCode]:[AvailableToAllSchools]])+COUNTBLANK(GRADES[[#This Row],[PayScaleGradeEnabled]])) -> 0 | H6: =IF(LEN(GRADES[[#This Row],[PayScaleGradeCode]])<100,0,1) -> 0 | I6: =IF(LEN(GRADES[[#This Row],[Title]])<100,0,1) -> 0 | J6: =IF(SUBSTITUTE(TEXT(GRADES[[#This Row],[PayScaleGradeCode]],10)," ","")=TEXT(GRADES[[#This Row],[PayScaleGradeCode]],10),0,1) -> 0 | K6: =SUM(GRADES[[#This Row],[Pay Scale issue]:[Schools Check]],GRADES[[#This Row],[TRUE /FALSE Typo]:[Space in Code]]) -> 0 | L6: =_xlfn.XLOOKUP(GRADES[[#This Row],[PayScaleCode]],PAYSCALES[PayScaleCode],PAYSCALES[London Weighting]) -> England & Wales | N6: LS | O6: Leadership Group | P6: LS_EW | Q6: L01 | R6: L43 | S6: {=LOOKUP(2,1/(PSPOINTS[PayScaleCode]=GRADES[[#This Row],[PayScaleCode]])/(PSPOINTS[PayScalePointCode]=GRADES[[#This Row],[Point From (Check)]]),(PSPOINTS[ScalePointNumber]))} -> 1 | T6: {=LOOKUP(2,1/(PSPOINTS[PayScaleCode]=GRADES[[#This Row],[PayScaleCode]])/(PSPOINTS[PayScalePointCode]=GRADES[[#This Row],[Point To (Check)]]),(PSPOINTS[ScalePointNumber]))} -> 43 | U6: TRUE | W6: TRUE
A7: =IF(COUNTIF('19_PayScales'!N:N,'22_PayScaleGrades'!P7)>0,"0","1") -> 0 | B7: =COUNTIF(GRADES[PayScaleGradeCode],GRADES[[#This Row],[PayScaleGradeCode]])-1 -> 0 | C7: {=IF(GRADES[[#This Row],[AvailableToAllSchools]]=FALSE,IF(ISBLANK(GRADES[[#This Row],[SchoolCodes]]),1,IF(AND(COUNTIF(SCHOOLS[SchoolCode],_xlfn.TEXTSPLIT(GRADES[[#This Row],[SchoolCodes]],","))),0,1)),IF(GRADES[[#This Row],[AvailableToAllSchools]]=TRUE,IF(ISBLANK(GRADES[[#This Row],[SchoolCodes]]),0,1)))} -> 0 | E7: {=IF(_xlfn.XLOOKUP(GRADES[[#This Row],[PayScaleCode]],PAYSCALES[PayScaleCode],PAYSCALES[AvailableToAllSchools])=TRUE,0,IF(GRADES[[#This Row],[AvailableToAllSchools]]=TRUE,1,IF(_xlfn.LET(_xlpm.sourceCodes, _xlfn.TEXTSPLIT(GRADES[[#This Row],[SchoolCodes]], ","),_xlpm.targetCodes, _xlfn.TEXTSPLIT(_xlfn.XLOOKUP(GRADES[[#This Row],[PayScaleCode]],PAYSCALES[PayScaleCode],PAYSCALES[SchoolCodes],1), ","),_xlpm.trimmedSource, TRIM(_xlpm.sourceCodes),_xlpm.trimmedTarget, TRIM(_xlpm.targetCodes),_xlpm.matches, ISNUMBER(MATCH(_xlpm.trimmedSource, _xlpm.trimmedTarget, 0)),AND(_xlpm.matches))=TRUE,0,1)))} -> 0 | F7: =IF(OR(GRADES[[#This Row],[AvailableToAllSchools]]=TRUE,GRADES[[#This Row],[AvailableToAllSchools]]=FALSE),IF(OR(GRADES[[#This Row],[PayScaleGradeEnabled]]=TRUE,GRADES[[#This Row],[PayScaleGradeEnabled]]=FALSE),0,1),1) -> 0 | G7: =(COUNTBLANK(GRADES[[#This Row],[PayScaleGradeCode]:[AvailableToAllSchools]])+COUNTBLANK(GRADES[[#This Row],[PayScaleGradeEnabled]])) -> 0 | H7: =IF(LEN(GRADES[[#This Row],[PayScaleGradeCode]])<100,0,1) -> 0 | I7: =IF(LEN(GRADES[[#This Row],[Title]])<100,0,1) -> 0 | J7: =IF(SUBSTITUTE(TEXT(GRADES[[#This Row],[PayScaleGradeCode]],10)," ","")=TEXT(GRADES[[#This Row],[PayScaleGradeCode]],10),0,1) -> 0 | K7: =SUM(GRADES[[#This Row],[Pay Scale issue]:[Schools Check]],GRADES[[#This Row],[TRUE /FALSE Typo]:[Space in Code]]) -> 0 | L7: =_xlfn.XLOOKUP(GRADES[[#This Row],[PayScaleCode]],PAYSCALES[PayScaleCode],PAYSCALES[London Weighting]) -> England & Wales | N7: LP | O7: Lead Practitioner Group | P7: LP_EW | Q7: LP01 | R7: LP18 | S7: {=LOOKUP(2,1/(PSPOINTS[PayScaleCode]=GRADES[[#This Row],[PayScaleCode]])/(PSPOINTS[PayScalePointCode]=GRADES[[#This Row],[Point From (Check)]]),(PSPOINTS[ScalePointNumber]))} -> 1 | T7: {=LOOKUP(2,1/(PSPOINTS[PayScaleCode]=GRADES[[#This Row],[PayScaleCode]])/(PSPOINTS[PayScalePointCode]=GRADES[[#This Row],[Point To (Check)]]),(PSPOINTS[ScalePointNumber]))} -> 18 | U7: TRUE | W7: TRUE
A8: =IF(COUNTIF('19_PayScales'!N:N,'22_PayScaleGrades'!P8)>0,"0","1") -> 0 | B8: =COUNTIF(GRADES[PayScaleGradeCode],GRADES[[#This Row],[PayScaleGradeCode]])-1 -> 0 | C8: {=IF(GRADES[[#This Row],[AvailableToAllSchools]]=FALSE,IF(ISBLANK(GRADES[[#This Row],[SchoolCodes]]),1,IF(AND(COUNTIF(SCHOOLS[SchoolCode],_xlfn.TEXTSPLIT(GRADES[[#This Row],[SchoolCodes]],","))),0,1)),IF(GRADES[[#This Row],[AvailableToAllSchools]]=TRUE,IF(ISBLANK(GRADES[[#This Row],[SchoolCodes]]),0,1)))} -> 0 | E8: {=IF(_xlfn.XLOOKUP(GRADES[[#This Row],[PayScaleCode]],PAYSCALES[PayScaleCode],PAYSCALES[AvailableToAllSchools])=TRUE,0,IF(GRADES[[#This Row],[AvailableToAllSchools]]=TRUE,1,IF(_xlfn.LET(_xlpm.sourceCodes, _xlfn.TEXTSPLIT(GRADES[[#This Row],[SchoolCodes]], ","),_xlpm.targetCodes, _xlfn.TEXTSPLIT(_xlfn.XLOOKUP(GRADES[[#This Row],[PayScaleCode]],PAYSCALES[PayScaleCode],PAYSCALES[SchoolCodes],1), ","),_xlpm.trimmedSource, TRIM(_xlpm.sourceCodes),_xlpm.trimmedTarget, TRIM(_xlpm.targetCodes),_xlpm.matches, ISNUMBER(MATCH(_xlpm.trimmedSource, _xlpm.trimmedTarget, 0)),AND(_xlpm.matches))=TRUE,0,1)))} -> 0 | F8: =IF(OR(GRADES[[#This Row],[AvailableToAllSchools]]=TRUE,GRADES[[#This Row],[AvailableToAllSchools]]=FALSE),IF(OR(GRADES[[#This Row],[PayScaleGradeEnabled]]=TRUE,GRADES[[#This Row],[PayScaleGradeEnabled]]=FALSE),0,1),1) -> 0 | G8: =(COUNTBLANK(GRADES[[#This Row],[PayScaleGradeCode]:[AvailableToAllSchools]])+COUNTBLANK(GRADES[[#This Row],[PayScaleGradeEnabled]])) -> 0 | H8: =IF(LEN(GRADES[[#This Row],[PayScaleGradeCode]])<100,0,1) -> 0 | I8: =IF(LEN(GRADES[[#This Row],[Title]])<100,0,1) -> 0 | J8: =IF(SUBSTITUTE(TEXT(GRADES[[#This Row],[PayScaleGradeCode]],10)," ","")=TEXT(GRADES[[#This Row],[PayScaleGradeCode]],10),0,1) -> 0 | K8: =SUM(GRADES[[#This Row],[Pay Scale issue]:[Schools Check]],GRADES[[#This Row],[TRUE /FALSE Typo]:[Space in Code]]) -> 0 | L8: =_xlfn.XLOOKUP(GRADES[[#This Row],[PayScaleCode]],PAYSCALES[PayScaleCode],PAYSCALES[London Weighting]) -> England & Wales | N8: NJC_EW | O8: NJC EW | P8: NJC_EW | Q8: 1 | R8: 43 | S8: {=LOOKUP(2,1/(PSPOINTS[PayScaleCode]=GRADES[[#This Row],[PayScaleCode]])/(PSPOINTS[PayScalePointCode]=GRADES[[#This Row],[Point From (Check)]]),(PSPOINTS[ScalePointNumber]))} -> 1 | T8: {=LOOKUP(2,1/(PSPOINTS[PayScaleCode]=GRADES[[#This Row],[PayScaleCode]])/(PSPOINTS[PayScalePointCode]=GRADES[[#This Row],[Point To (Check)]]),(PSPOINTS[ScalePointNumber]))} -> 43 | U8: TRUE | W8: TRUE
A9: =IF(COUNTIF('19_PayScales'!N:N,'22_PayScaleGrades'!P9)>0,"0","1") -> 0 | B9: =COUNTIF(GRADES[PayScaleGradeCode],GRADES[[#This Row],[PayScaleGradeCode]])-1 -> 0 | C9: {=IF(GRADES[[#This Row],[AvailableToAllSchools]]=FALSE,IF(ISBLANK(GRADES[[#This Row],[SchoolCodes]]),1,IF(AND(COUNTIF(SCHOOLS[SchoolCode],_xlfn.TEXTSPLIT(GRADES[[#This Row],[SchoolCodes]],","))),0,1)),IF(GRADES[[#This Row],[AvailableToAllSchools]]=TRUE,IF(ISBLANK(GRADES[[#This Row],[SchoolCodes]]),0,1)))} -> 0 | E9: {=IF(_xlfn.XLOOKUP(GRADES[[#This Row],[PayScaleCode]],PAYSCALES[PayScaleCode],PAYSCALES[AvailableToAllSchools])=TRUE,0,IF(GRADES[[#This Row],[AvailableToAllSchools]]=TRUE,1,IF(_xlfn.LET(_xlpm.sourceCodes, _xlfn.TEXTSPLIT(GRADES[[#This Row],[SchoolCodes]], ","),_xlpm.targetCodes, _xlfn.TEXTSPLIT(_xlfn.XLOOKUP(GRADES[[#This Row],[PayScaleCode]],PAYSCALES[PayScaleCode],PAYSCALES[SchoolCodes],1), ","),_xlpm.trimmedSource, TRIM(_xlpm.sourceCodes),_xlpm.trimmedTarget, TRIM(_xlpm.targetCodes),_xlpm.matches, ISNUMBER(MATCH(_xlpm.trimmedSource, _xlpm.trimmedTarget, 0)),AND(_xlpm.matches))=TRUE,0,1)))} -> 0 | F9: =IF(OR(GRADES[[#This Row],[AvailableToAllSchools]]=TRUE,GRADES[[#This Row],[AvailableToAllSchools]]=FALSE),IF(OR(GRADES[[#This Row],[PayScaleGradeEnabled]]=TRUE,GRADES[[#This Row],[PayScaleGradeEnabled]]=FALSE),0,1),1) -> 0 | G9: =(COUNTBLANK(GRADES[[#This Row],[PayScaleGradeCode]:[AvailableToAllSchools]])+COUNTBLANK(GRADES[[#This Row],[PayScaleGradeEnabled]])) -> 0 | H9: =IF(LEN(GRADES[[#This Row],[PayScaleGradeCode]])<100,0,1) -> 0 | I9: =IF(LEN(GRADES[[#This Row],[Title]])<100,0,1) -> 0 | J9: =IF(SUBSTITUTE(TEXT(GRADES[[#This Row],[PayScaleGradeCode]],10)," ","")=TEXT(GRADES[[#This Row],[PayScaleGradeCode]],10),0,1) -> 0 | K9: =SUM(GRADES[[#This Row],[Pay Scale issue]:[Schools Check]],GRADES[[#This Row],[TRUE /FALSE Typo]:[Space in Code]]) -> 0 | L9: =_xlfn.XLOOKUP(GRADES[[#This Row],[PayScaleCode]],PAYSCALES[PayScaleCode],PAYSCALES[London Weighting]) -> England & Wales | N9: NMW_Y1 | O9: Apprentice Y1 | P9: APP_NMW | Q9: Y1 | R9: Y1 | S9: {=LOOKUP(2,1/(PSPOINTS[PayScaleCode]=GRADES[[#This Row],[PayScaleCode]])/(PSPOINTS[PayScalePointCode]=GRADES[[#This Row],[Point From (Check)]]),(PSPOINTS[ScalePointNumber]))} -> 1 | T9: {=LOOKUP(2,1/(PSPOINTS[PayScaleCode]=GRADES[[#This Row],[PayScaleCode]])/(PSPOINTS[PayScalePointCode]=GRADES[[#This Row],[Point To (Check)]]),(PSPOINTS[ScalePointNumber]))} -> 1 | U9: TRUE | W9: TRUE
A10: =IF(COUNTIF('19_PayScales'!N:N,'22_PayScaleGrades'!P10)>0,"0","1") -> 0 | B10: =COUNTIF(GRADES[PayScaleGradeCode],GRADES[[#This Row],[PayScaleGradeCode]])-1 -> 0 | C10: {=IF(GRADES[[#This Row],[AvailableToAllSchools]]=FALSE,IF(ISBLANK(GRADES[[#This Row],[SchoolCodes]]),1,IF(AND(COUNTIF(SCHOOLS[SchoolCode],_xlfn.TEXTSPLIT(GRADES[[#This Row],[SchoolCodes]],","))),0,1)),IF(GRADES[[#This Row],[AvailableToAllSchools]]=TRUE,IF(ISBLANK(GRADES[[#This Row],[SchoolCodes]]),0,1)))} -> 0 | E10: {=IF(_xlfn.XLOOKUP(GRADES[[#This Row],[PayScaleCode]],PAYSCALES[PayScaleCode],PAYSCALES[AvailableToAllSchools])=TRUE,0,IF(GRADES[[#This Row],[AvailableToAllSchools]]=TRUE,1,IF(_xlfn.LET(_xlpm.sourceCodes, _xlfn.TEXTSPLIT(GRADES[[#This Row],[SchoolCodes]], ","),_xlpm.targetCodes, _xlfn.TEXTSPLIT(_xlfn.XLOOKUP(GRADES[[#This Row],[PayScaleCode]],PAYSCALES[PayScaleCode],PAYSCALES[SchoolCodes],1), ","),_xlpm.trimmedSource, TRIM(_xlpm.sourceCodes),_xlpm.trimmedTarget, TRIM(_xlpm.targetCodes),_xlpm.matches, ISNUMBER(MATCH(_xlpm.trimmedSource, _xlpm.trimmedTarget, 0)),AND(_xlpm.matches))=TRUE,0,1)))} -> 0 | F10: =IF(OR(GRADES[[#This Row],[AvailableToAllSchools]]=TRUE,GRADES[[#This Row],[AvailableToAllSchools]]=FALSE),IF(OR(GRADES[[#This Row],[PayScaleGradeEnabled]]=TRUE,GRADES[[#This Row],[PayScaleGradeEnabled]]=FALSE),0,1),1) -> 0 | G10: =(COUNTBLANK(GRADES[[#This Row],[PayScaleGradeCode]:[AvailableToAllSchools]])+COUNTBLANK(GRADES[[#This Row],[PayScaleGradeEnabled]])) -> 0 | H10: =IF(LEN(GRADES[[#This Row],[PayScaleGradeCode]])<100,0,1) -> 0 | I10: =IF(LEN(GRADES[[#This Row],[Title]])<100,0,1) -> 0 | J10: =IF(SUBSTITUTE(TEXT(GRADES[[#This Row],[PayScaleGradeCode]],10)," ","")=TEXT(GRADES[[#This Row],[PayScaleGradeCode]],10),0,1) -> 0 | K10: =SUM(GRADES[[#This Row],[Pay Scale issue]:[Schools Check]],GRADES[[#This Row],[TRUE /FALSE Typo]:[Space in Code]]) -> 0 | L10: =_xlfn.XLOOKUP(GRADES[[#This Row],[PayScaleCode]],PAYSCALES[PayScaleCode],PAYSCALES[London Weighting]) -> England & Wales | N10: NMW_<18 | O10: NMW <18 | P10: APP_NMW | Q10: <18 | R10: <18 | S10: {=LOOKUP(2,1/(PSPOINTS[PayScaleCode]=GRADES[[#This Row],[PayScaleCode]])/(PSPOINTS[PayScalePointCode]=GRADES[[#This Row],[Point From (Check)]]),(PSPOINTS[ScalePointNumber]))} -> 2 | T10: {=LOOKUP(2,1/(PSPOINTS[PayScaleCode]=GRADES[[#This Row],[PayScaleCode]])/(PSPOINTS[PayScalePointCode]=GRADES[[#This Row],[Point To (Check)]]),(PSPOINTS[ScalePointNumber]))} -> 2 | U10: TRUE | W10: TRUE
A11: =IF(COUNTIF('19_PayScales'!N:N,'22_PayScaleGrades'!P11)>0,"0","1") -> 0 | B11: =COUNTIF(GRADES[PayScaleGradeCode],GRADES[[#This Row],[PayScaleGradeCode]])-1 -> 0 | C11: {=IF(GRADES[[#This Row],[AvailableToAllSchools]]=FALSE,IF(ISBLANK(GRADES[[#This Row],[SchoolCodes]]),1,IF(AND(COUNTIF(SCHOOLS[SchoolCode],_xlfn.TEXTSPLIT(GRADES[[#This Row],[SchoolCodes]],","))),0,1)),IF(GRADES[[#This Row],[AvailableToAllSchools]]=TRUE,IF(ISBLANK(GRADES[[#This Row],[SchoolCodes]]),0,1)))} -> 0 | E11: {=IF(_xlfn.XLOOKUP(GRADES[[#This Row],[PayScaleCode]],PAYSCALES[PayScaleCode],PAYSCALES[AvailableToAllSchools])=TRUE,0,IF(GRADES[[#This Row],[AvailableToAllSchools]]=TRUE,1,IF(_xlfn.LET(_xlpm.sourceCodes, _xlfn.TEXTSPLIT(GRADES[[#This Row],[SchoolCodes]], ","),_xlpm.targetCodes, _xlfn.TEXTSPLIT(_xlfn.XLOOKUP(GRADES[[#This Row],[PayScaleCode]],PAYSCALES[PayScaleCode],PAYSCALES[SchoolCodes],1), ","),_xlpm.trimmedSource, TRIM(_xlpm.sourceCodes),_xlpm.trimmedTarget, TRIM(_xlpm.targetCodes),_xlpm.matches, ISNUMBER(MATCH(_xlpm.trimmedSource, _xlpm.trimmedTarget, 0)),AND(_xlpm.matches))=TRUE,0,1)))} -> 0 | F11: =IF(OR(GRADES[[#This Row],[AvailableToAllSchools]]=TRUE,GRADES[[#This Row],[AvailableToAllSchools]]=FALSE),IF(OR(GRADES[[#This Row],[PayScaleGradeEnabled]]=TRUE,GRADES[[#This Row],[PayScaleGradeEnabled]]=FALSE),0,1),1) -> 0 | G11: =(COUNTBLANK(GRADES[[#This Row],[PayScaleGradeCode]:[AvailableToAllSchools]])+COUNTBLANK(GRADES[[#This Row],[PayScaleGradeEnabled]])) -> 0 | H11: =IF(LEN(GRADES[[#This Row],[PayScaleGradeCode]])<100,0,1) -> 0 | I11: =IF(LEN(GRADES[[#This Row],[Title]])<100,0,1) -> 0 | J11: =IF(SUBSTITUTE(TEXT(GRADES[[#This Row],[PayScaleGradeCode]],10)," ","")=TEXT(GRADES[[#This Row],[PayScaleGradeCode]],10),0,1) -> 0 | K11: =SUM(GRADES[[#This Row],[Pay Scale issue]:[Schools Check]],GRADES[[#This Row],[TRUE /FALSE Typo]:[Space in Code]]) -> 0 | L11: =_xlfn.XLOOKUP(GRADES[[#This Row],[PayScaleCode]],PAYSCALES[PayScaleCode],PAYSCALES[London Weighting]) -> England & Wales | N11: NMW_18-20 | O11: NMW 18-20 | P11: APP_NMW | Q11: 18-20 | R11: 18-20 | S11: {=LOOKUP(2,1/(PSPOINTS[PayScaleCode]=GRADES[[#This Row],[PayScaleCode]])/(PSPOINTS[PayScalePointCode]=GRADES[[#This Row],[Point From (Check)]]),(PSPOINTS[ScalePointNumber]))} -> 3 | T11: {=LOOKUP(2,1/(PSPOINTS[PayScaleCode]=GRADES[[#This Row],[PayScaleCode]])/(PSPOINTS[PayScalePointCode]=GRADES[[#This Row],[Point To (Check)]]),(PSPOINTS[ScalePointNumber]))} -> 3 | U11: TRUE | W11: TRUE
A12: =IF(COUNTIF('19_PayScales'!N:N,'22_PayScaleGrades'!P12)>0,"0","1") -> 0 | B12: =COUNTIF(GRADES[PayScaleGradeCode],GRADES[[#This Row],[PayScaleGradeCode]])-1 -> 0 | C12: {=IF(GRADES[[#This Row],[AvailableToAllSchools]]=FALSE,IF(ISBLANK(GRADES[[#This Row],[SchoolCodes]]),1,IF(AND(COUNTIF(SCHOOLS[SchoolCode],_xlfn.TEXTSPLIT(GRADES[[#This Row],[SchoolCodes]],","))),0,1)),IF(GRADES[[#This Row],[AvailableToAllSchools]]=TRUE,IF(ISBLANK(GRADES[[#This Row],[SchoolCodes]]),0,1)))} -> 0 | E12: {=IF(_xlfn.XLOOKUP(GRADES[[#This Row],[PayScaleCode]],PAYSCALES[PayScaleCode],PAYSCALES[AvailableToAllSchools])=TRUE,0,IF(GRADES[[#This Row],[AvailableToAllSchools]]=TRUE,1,IF(_xlfn.LET(_xlpm.sourceCodes, _xlfn.TEXTSPLIT(GRADES[[#This Row],[SchoolCodes]], ","),_xlpm.targetCodes, _xlfn.TEXTSPLIT(_xlfn.XLOOKUP(GRADES[[#This Row],[PayScaleCode]],PAYSCALES[PayScaleCode],PAYSCALES[SchoolCodes],1), ","),_xlpm.trimmedSource, TRIM(_xlpm.sourceCodes),_xlpm.trimmedTarget, TRIM(_xlpm.targetCodes),_xlpm.matches, ISNUMBER(MATCH(_xlpm.trimmedSource, _xlpm.trimmedTarget, 0)),AND(_xlpm.matches))=TRUE,0,1)))} -> 0 | F12: =IF(OR(GRADES[[#This Row],[AvailableToAllSchools]]=TRUE,GRADES[[#This Row],[AvailableToAllSchools]]=FALSE),IF(OR(GRADES[[#This Row],[PayScaleGradeEnabled]]=TRUE,GRADES[[#This Row],[PayScaleGradeEnabled]]=FALSE),0,1),1) -> 0 | G12: =(COUNTBLANK(GRADES[[#This Row],[PayScaleGradeCode]:[AvailableToAllSchools]])+COUNTBLANK(GRADES[[#This Row],[PayScaleGradeEnabled]])) -> 0 | H12: =IF(LEN(GRADES[[#This Row],[PayScaleGradeCode]])<100,0,1) -> 0 | I12: =IF(LEN(GRADES[[#This Row],[Title]])<100,0,1) -> 0 | J12: =IF(SUBSTITUTE(TEXT(GRADES[[#This Row],[PayScaleGradeCode]],10)," ","")=TEXT(GRADES[[#This Row],[PayScaleGradeCode]],10),0,1) -> 0 | K12: =SUM(GRADES[[#This Row],[Pay Scale issue]:[Schools Check]],GRADES[[#This Row],[TRUE /FALSE Typo]:[Space in Code]]) -> 0 | L12: =_xlfn.XLOOKUP(GRADES[[#This Row],[PayScaleCode]],PAYSCALES[PayScaleCode],PAYSCALES[London Weighting]) -> England & Wales | N12: NMW_>21 | O12: NLW >21 | P12: APP_NMW | Q12: >21 | R12: >21 | S12: {=LOOKUP(2,1/(PSPOINTS[PayScaleCode]=GRADES[[#This Row],[PayScaleCode]])/(PSPOINTS[PayScalePointCode]=GRADES[[#This Row],[Point From (Check)]]),(PSPOINTS[ScalePointNumber]))} -> 4 | T12: {=LOOKUP(2,1/(PSPOINTS[PayScaleCode]=GRADES[[#This Row],[PayScaleCode]])/(PSPOINTS[PayScalePointCode]=GRADES[[#This Row],[Point To (Check)]]),(PSPOINTS[ScalePointNumber]))} -> 4 | U12: TRUE | W12: TRUE
A13: =IF(COUNTIF('19_PayScales'!N:N,'22_PayScaleGrades'!P13)>0,"0","1") -> 0 | B13: =COUNTIF(GRADES[PayScaleGradeCode],GRADES[[#This Row],[PayScaleGradeCode]])-1 -> 0 | C13: {=IF(GRADES[[#This Row],[AvailableToAllSchools]]=FALSE,IF(ISBLANK(GRADES[[#This Row],[SchoolCodes]]),1,IF(AND(COUNTIF(SCHOOLS[SchoolCode],_xlfn.TEXTSPLIT(GRADES[[#This Row],[SchoolCodes]],","))),0,1)),IF(GRADES[[#This Row],[AvailableToAllSchools]]=TRUE,IF(ISBLANK(GRADES[[#This Row],[SchoolCodes]]),0,1)))} -> 0 | E13: {=IF(_xlfn.XLOOKUP(GRADES[[#This Row],[PayScaleCode]],PAYSCALES[PayScaleCode],PAYSCALES[AvailableToAllSchools])=TRUE,0,IF(GRADES[[#This Row],[AvailableToAllSchools]]=TRUE,1,IF(_xlfn.LET(_xlpm.sourceCodes, _xlfn.TEXTSPLIT(GRADES[[#This Row],[SchoolCodes]], ","),_xlpm.targetCodes, _xlfn.TEXTSPLIT(_xlfn.XLOOKUP(GRADES[[#This Row],[PayScaleCode]],PAYSCALES[PayScaleCode],PAYSCALES[SchoolCodes],1), ","),_xlpm.trimmedSource, TRIM(_xlpm.sourceCodes),_xlpm.trimmedTarget, TRIM(_xlpm.targetCodes),_xlpm.matches, ISNUMBER(MATCH(_xlpm.trimmedSource, _xlpm.trimmedTarget, 0)),AND(_xlpm.matches))=TRUE,0,1)))} -> 0 | F13: =IF(OR(GRADES[[#This Row],[AvailableToAllSchools]]=TRUE,GRADES[[#This Row],[AvailableToAllSchools]]=FALSE),IF(OR(GRADES[[#This Row],[PayScaleGradeEnabled]]=TRUE,GRADES[[#This Row],[PayScaleGradeEnabled]]=FALSE),0,1),1) -> 0 | G13: =(COUNTBLANK(GRADES[[#This Row],[PayScaleGradeCode]:[AvailableToAllSchools]])+COUNTBLANK(GRADES[[#This Row],[PayScaleGradeEnabled]])) -> 0 | H13: =IF(LEN(GRADES[[#This Row],[PayScaleGradeCode]])<100,0,1) -> 0 | I13: =IF(LEN(GRADES[[#This Row],[Title]])<100,0,1) -> 0 | J13: =IF(SUBSTITUTE(TEXT(GRADES[[#This Row],[PayScaleGradeCode]],10)," ","")=TEXT(GRADES[[#This Row],[PayScaleGradeCode]],10),0,1) -> 0 | K13: =SUM(GRADES[[#This Row],[Pay Scale issue]:[Schools Check]],GRADES[[#This Row],[TRUE /FALSE Typo]:[Space in Code]]) -> 0 | L13: =_xlfn.XLOOKUP(GRADES[[#This Row],[PayScaleCode]],PAYSCALES[PayScaleCode],PAYSCALES[London Weighting]) -> 0 | N13: SUP_01 | O13: Support Spot Salary 1 | P13: SPOT_SUP | Q13: SUP01 | R13: SUP01 | S13: {=LOOKUP(2,1/(PSPOINTS[PayScaleCode]=GRADES[[#This Row],[PayScaleCode]])/(PSPOINTS[PayScalePointCode]=GRADES[[#This Row],[Point From (Check)]]),(PSPOINTS[ScalePointNumber]))} -> 1 | T13: {=LOOKUP(2,1/(PSPOINTS[PayScaleCode]=GRADES[[#This Row],[PayScaleCode]])/(PSPOINTS[PayScalePointCode]=GRADES[[#This Row],[Point To (Check)]]),(PSPOINTS[ScalePointNumber]))} -> 1 | U13: TRUE | W13: TRUE
A14: =IF(COUNTIF('19_PayScales'!N:N,'22_PayScaleGrades'!P14)>0,"0","1") -> 0 | B14: =COUNTIF(GRADES[PayScaleGradeCode],GRADES[[#This Row],[PayScaleGradeCode]])-1 -> 0 | C14: {=IF(GRADES[[#This Row],[AvailableToAllSchools]]=FALSE,IF(ISBLANK(GRADES[[#This Row],[SchoolCodes]]),1,IF(AND(COUNTIF(SCHOOLS[SchoolCode],_xlfn.TEXTSPLIT(GRADES[[#This Row],[SchoolCodes]],","))),0,1)),IF(GRADES[[#This Row],[AvailableToAllSchools]]=TRUE,IF(ISBLANK(GRADES[[#This Row],[SchoolCodes]]),0,1)))} -> 0 | E14: {=IF(_xlfn.XLOOKUP(GRADES[[#This Row],[PayScaleCode]],PAYSCALES[PayScaleCode],PAYSCALES[AvailableToAllSchools])=TRUE,0,IF(GRADES[[#This Row],[AvailableToAllSchools]]=TRUE,1,IF(_xlfn.LET(_xlpm.sourceCodes, _xlfn.TEXTSPLIT(GRADES[[#This Row],[SchoolCodes]], ","),_xlpm.targetCodes, _xlfn.TEXTSPLIT(_xlfn.XLOOKUP(GRADES[[#This Row],[PayScaleCode]],PAYSCALES[PayScaleCode],PAYSCALES[SchoolCodes],1), ","),_xlpm.trimmedSource, TRIM(_xlpm.sourceCodes),_xlpm.trimmedTarget, TRIM(_xlpm.targetCodes),_xlpm.matches, ISNUMBER(MATCH(_xlpm.trimmedSource, _xlpm.trimmedTarget, 0)),AND(_xlpm.matches))=TRUE,0,1)))} -> 0 | F14: =IF(OR(GRADES[[#This Row],[AvailableToAllSchools]]=TRUE,GRADES[[#This Row],[AvailableToAllSchools]]=FALSE),IF(OR(GRADES[[#This Row],[PayScaleGradeEnabled]]=TRUE,GRADES[[#This Row],[PayScaleGradeEnabled]]=FALSE),0,1),1) -> 0 | G14: =(COUNTBLANK(GRADES[[#This Row],[PayScaleGradeCode]:[AvailableToAllSchools]])+COUNTBLANK(GRADES[[#This Row],[PayScaleGradeEnabled]])) -> 0 | H14: =IF(LEN(GRADES[[#This Row],[PayScaleGradeCode]])<100,0,1) -> 0 | I14: =IF(LEN(GRADES[[#This Row],[Title]])<100,0,1) -> 0 | J14: =IF(SUBSTITUTE(TEXT(GRADES[[#This Row],[PayScaleGradeCode]],10)," ","")=TEXT(GRADES[[#This Row],[PayScaleGradeCode]],10),0,1) -> 0 | K14: =SUM(GRADES[[#This Row],[Pay Scale issue]:[Schools Check]],GRADES[[#This Row],[TRUE /FALSE Typo]:[Space in Code]]) -> 0 | L14: =_xlfn.XLOOKUP(GRADES[[#This Row],[PayScaleCode]],PAYSCALES[PayScaleCode],PAYSCALES[London Weighting]) -> 0 | N14: TEA_01 | O14: Teacher Spot Salary 1 | P14: SPOT_TEA | Q14: TEA01 | R14: TEA01 | S14: {=LOOKUP(2,1/(PSPOINTS[PayScaleCode]=GRADES[[#This Row],[PayScaleCode]])/(PSPOINTS[PayScalePointCode]=GRADES[[#This Row],[Point From (Check)]]),(PSPOINTS[ScalePointNumber]))} -> 1 | T14: {=LOOKUP(2,1/(PSPOINTS[PayScaleCode]=GRADES[[#This Row],[PayScaleCode]])/(PSPOINTS[PayScalePointCode]=GRADES[[#This Row],[Point To (Check)]]),(PSPOINTS[ScalePointNumber]))} -> 1 | U14: TRUE | W14: TRUE
A15: =IF(COUNTIF('19_PayScales'!N:N,'22_PayScaleGrades'!P15)>0,"0","1") -> 0 | B15: =COUNTIF(GRADES[PayScaleGradeCode],GRADES[[#This Row],[PayScaleGradeCode]])-1 -> 0 | C15: {=IF(GRADES[[#This Row],[AvailableToAllSchools]]=FALSE,IF(ISBLANK(GRADES[[#This Row],[SchoolCodes]]),1,IF(AND(COUNTIF(SCHOOLS[SchoolCode],_xlfn.TEXTSPLIT(GRADES[[#This Row],[SchoolCodes]],","))),0,1)),IF(GRADES[[#This Row],[AvailableToAllSchools]]=TRUE,IF(ISBLANK(GRADES[[#This Row],[SchoolCodes]]),0,1)))} -> 0 | E15: {=IF(_xlfn.XLOOKUP(GRADES[[#This Row],[PayScaleCode]],PAYSCALES[PayScaleCode],PAYSCALES[AvailableToAllSchools])=TRUE,0,IF(GRADES[[#This Row],[AvailableToAllSchools]]=TRUE,1,IF(_xlfn.LET(_xlpm.sourceCodes, _xlfn.TEXTSPLIT(GRADES[[#This Row],[SchoolCodes]], ","),_xlpm.targetCodes, _xlfn.TEXTSPLIT(_xlfn.XLOOKUP(GRADES[[#This Row],[PayScaleCode]],PAYSCALES[PayScaleCode],PAYSCALES[SchoolCodes],1), ","),_xlpm.trimmedSource, TRIM(_xlpm.sourceCodes),_xlpm.trimmedTarget, TRIM(_xlpm.targetCodes),_xlpm.matches, ISNUMBER(MATCH(_xlpm.trimmedSource, _xlpm.trimmedTarget, 0)),AND(_xlpm.matches))=TRUE,0,1)))} -> 0 | F15: =IF(OR(GRADES[[#This Row],[AvailableToAllSchools]]=TRUE,GRADES[[#This Row],[AvailableToAllSchools]]=FALSE),IF(OR(GRADES[[#This Row],[PayScaleGradeEnabled]]=TRUE,GRADES[[#This Row],[PayScaleGradeEnabled]]=FALSE),0,1),1) -> 0 | G15: =(COUNTBLANK(GRADES[[#This Row],[PayScaleGradeCode]:[AvailableToAllSchools]])+COUNTBLANK(GRADES[[#This Row],[PayScaleGradeEnabled]])) -> 0 | H15: =IF(LEN(GRADES[[#This Row],[PayScaleGradeCode]])<100,0,1) -> 0 | I15: =IF(LEN(GRADES[[#This Row],[Title]])<100,0,1) -> 0 | J15: =IF(SUBSTITUTE(TEXT(GRADES[[#This Row],[PayScaleGradeCode]],10)," ","")=TEXT(GRADES[[#This Row],[PayScaleGradeCode]],10),0,1) -> 0 | K15: =SUM(GRADES[[#This Row],[Pay Scale issue]:[Schools Check]],GRADES[[#This Row],[TRUE /FALSE Typo]:[Space in Code]]) -> 0 | L15: =_xlfn.XLOOKUP(GRADES[[#This Row],[PayScaleCode]],PAYSCALES[PayScaleCode],PAYSCALES[London Weighting]) -> Fringe | N15: MAIN_UPS_FRI | O15: Teachers Main through UPS Fringe | P15: MAIN_FRI | Q15: M1 | R15: U3 | S15: {=LOOKUP(2,1/(PSPOINTS[PayScaleCode]=GRADES[[#This Row],[PayScaleCode]])/(PSPOINTS[PayScalePointCode]=GRADES[[#This Row],[Point From (Check)]]),(PSPOINTS[ScalePointNumber]))} -> 1 | T15: {=LOOKUP(2,1/(PSPOINTS[PayScaleCode]=GRADES[[#This Row],[PayScaleCode]])/(PSPOINTS[PayScalePointCode]=GRADES[[#This Row],[Point To (Check)]]),(PSPOINTS[ScalePointNumber]))} -> 11 | U15: TRUE | W15: TRUE
A16: =IF(COUNTIF('19_PayScales'!N:N,'22_PayScaleGrades'!P16)>0,"0","1") -> 0 | B16: =COUNTIF(GRADES[PayScaleGradeCode],GRADES[[#This Row],[PayScaleGradeCode]])-1 -> 0 | C16: {=IF(GRADES[[#This Row],[AvailableToAllSchools]]=FALSE,IF(ISBLANK(GRADES[[#This Row],[SchoolCodes]]),1,IF(AND(COUNTIF(SCHOOLS[SchoolCode],_xlfn.TEXTSPLIT(GRADES[[#This Row],[SchoolCodes]],","))),0,1)),IF(GRADES[[#This Row],[AvailableToAllSchools]]=TRUE,IF(ISBLANK(GRADES[[#This Row],[SchoolCodes]]),0,1)))} -> 0 | E16: {=IF(_xlfn.XLOOKUP(GRADES[[#This Row],[PayScaleCode]],PAYSCALES[PayScaleCode],PAYSCALES[AvailableToAllSchools])=TRUE,0,IF(GRADES[[#This Row],[AvailableToAllSchools]]=TRUE,1,IF(_xlfn.LET(_xlpm.sourceCodes, _xlfn.TEXTSPLIT(GRADES[[#This Row],[SchoolCodes]], ","),_xlpm.targetCodes, _xlfn.TEXTSPLIT(_xlfn.XLOOKUP(GRADES[[#This Row],[PayScaleCode]],PAYSCALES[PayScaleCode],PAYSCALES[SchoolCodes],1), ","),_xlpm.trimmedSource, TRIM(_xlpm.sourceCodes),_xlpm.trimmedTarget, TRIM(_xlpm.targetCodes),_xlpm.matches, ISNUMBER(MATCH(_xlpm.trimmedSource, _xlpm.trimmedTarget, 0)),AND(_xlpm.matches))=TRUE,0,1)))} -> 0 | F16: =IF(OR(GRADES[[#This Row],[AvailableToAllSchools]]=TRUE,GRADES[[#This Row],[AvailableToAllSchools]]=FALSE),IF(OR(GRADES[[#This Row],[PayScaleGradeEnabled]]=TRUE,GRADES[[#This Row],[PayScaleGradeEnabled]]=FALSE),0,1),1) -> 0 | G16: =(COUNTBLANK(GRADES[[#This Row],[PayScaleGradeCode]:[AvailableToAllSchools]])+COUNTBLANK(GRADES[[#This Row],[PayScaleGradeEnabled]])) -> 0 | H16: =IF(LEN(GRADES[[#This Row],[PayScaleGradeCode]])<100,0,1) -> 0 | I16: =IF(LEN(GRADES[[#This Row],[Title]])<100,0,1) -> 0 | J16: =IF(SUBSTITUTE(TEXT(GRADES[[#This Row],[PayScaleGradeCode]],10)," ","")=TEXT(GRADES[[#This Row],[PayScaleGradeCode]],10),0,1) -> 0 | K16: =SUM(GRADES[[#This Row],[Pay Scale issue]:[Schools Check]],GRADES[[#This Row],[TRUE /FALSE Typo]:[Space in Code]]) -> 0 | L16: =_xlfn.XLOOKUP(GRADES[[#This Row],[PayScaleCode]],PAYSCALES[PayScaleCode],PAYSCALES[London Weighting]) -> Fringe | N16: MAIN_FRI | O16: Teachers Main Scale only Fringe | P16: MAIN_FRI | Q16: M1 | R16: M6 | S16: {=LOOKUP(2,1/(PSPOINTS[PayScaleCode]=GRADES[[#This Row],[PayScaleCode]])/(PSPOINTS[PayScalePointCode]=GRADES[[#This Row],[Point From (Check)]]),(PSPOINTS[ScalePointNumber]))} -> 1 | T16: {=LOOKUP(2,1/(PSPOINTS[PayScaleCode]=GRADES[[#This Row],[PayScaleCode]])/(PSPOINTS[PayScalePointCode]=GRADES[[#This Row],[Point To (Check)]]),(PSPOINTS[ScalePointNumber]))} -> 6 | U16: TRUE | W16: TRUE
A17: =IF(COUNTIF('19_PayScales'!N:N,'22_PayScaleGrades'!P17)>0,"0","1") -> 0 | B17: =COUNTIF(GRADES[PayScaleGradeCode],GRADES[[#This Row],[PayScaleGradeCode]])-1 -> 0 | C17: {=IF(GRADES[[#This Row],[AvailableToAllSchools]]=FALSE,IF(ISBLANK(GRADES[[#This Row],[SchoolCodes]]),1,IF(AND(COUNTIF(SCHOOLS[SchoolCode],_xlfn.TEXTSPLIT(GRADES[[#This Row],[SchoolCodes]],","))),0,1)),IF(GRADES[[#This Row],[AvailableToAllSchools]]=TRUE,IF(ISBLANK(GRADES[[#This Row],[SchoolCodes]]),0,1)))} -> 0 | E17: {=IF(_xlfn.XLOOKUP(GRADES[[#This Row],[PayScaleCode]],PAYSCALES[PayScaleCode],PAYSCALES[AvailableToAllSchools])=TRUE,0,IF(GRADES[[#This Row],[AvailableToAllSchools]]=TRUE,1,IF(_xlfn.LET(_xlpm.sourceCodes, _xlfn.TEXTSPLIT(GRADES[[#This Row],[SchoolCodes]], ","),_xlpm.targetCodes, _xlfn.TEXTSPLIT(_xlfn.XLOOKUP(GRADES[[#This Row],[PayScaleCode]],PAYSCALES[PayScaleCode],PAYSCALES[SchoolCodes],1), ","),_xlpm.trimmedSource, TRIM(_xlpm.sourceCodes),_xlpm.trimmedTarget, TRIM(_xlpm.targetCodes),_xlpm.matches, ISNUMBER(MATCH(_xlpm.trimmedSource, _xlpm.trimmedTarget, 0)),AND(_xlpm.matches))=TRUE,0,1)))} -> 0 | F17: =IF(OR(GRADES[[#This Row],[AvailableToAllSchools]]=TRUE,GRADES[[#This Row],[AvailableToAllSchools]]=FALSE),IF(OR(GRADES[[#This Row],[PayScaleGradeEnabled]]=TRUE,GRADES[[#This Row],[PayScaleGradeEnabled]]=FALSE),0,1),1) -> 0 | G17: =(COUNTBLANK(GRADES[[#This Row],[PayScaleGradeCode]:[AvailableToAllSchools]])+COUNTBLANK(GRADES[[#This Row],[PayScaleGradeEnabled]])) -> 0 | H17: =IF(LEN(GRADES[[#This Row],[PayScaleGradeCode]])<100,0,1) -> 0 | I17: =IF(LEN(GRADES[[#This Row],[Title]])<100,0,1) -> 0 | J17: =IF(SUBSTITUTE(TEXT(GRADES[[#This Row],[PayScaleGradeCode]],10)," ","")=TEXT(GRADES[[#This Row],[PayScaleGradeCode]],10),0,1) -> 0 | K17: =SUM(GRADES[[#This Row],[Pay Scale issue]:[Schools Check]],GRADES[[#This Row],[TRUE /FALSE Typo]:[Space in Code]]) -> 0 | L17: =_xlfn.XLOOKUP(GRADES[[#This Row],[PayScaleCode]],PAYSCALES[PayScaleCode],PAYSCALES[London Weighting]) -> Fringe | N17: UPS_FRI | O17: Teachers Upper Scale only Fringe | P17: MAIN_FRI | Q17: U1Y1 | R17: U3 | S17: {=LOOKUP(2,1/(PSPOINTS[PayScaleCode]=GRADES[[#This Row],[PayScaleCode]])/(PSPOINTS[PayScalePointCode]=GRADES[[#This Row],[Point From (Check)]]),(PSPOINTS[ScalePointNumber]))} -> 7 | T17: {=LOOKUP(2,1/(PSPOINTS[PayScaleCode]=GRADES[[#This Row],[PayScaleCode]])/(PSPOINTS[PayScalePointCode]=GRADES[[#This Row],[Point To (Check)]]),(PSPOINTS[ScalePointNumber]))} -> 11 | U17: TRUE | W17: TRUE
A18: =IF(COUNTIF('19_PayScales'!N:N,'22_PayScaleGrades'!P18)>0,"0","1") -> 0 | B18: =COUNTIF(GRADES[PayScaleGradeCode],GRADES[[#This Row],[PayScaleGradeCode]])-1 -> 0 | C18: {=IF(GRADES[[#This Row],[AvailableToAllSchools]]=FALSE,IF(ISBLANK(GRADES[[#This Row],[SchoolCodes]]),1,IF(AND(COUNTIF(SCHOOLS[SchoolCode],_xlfn.TEXTSPLIT(GRADES[[#This Row],[SchoolCodes]],","))),0,1)),IF(GRADES[[#This Row],[AvailableToAllSchools]]=TRUE,IF(ISBLANK(GRADES[[#This Row],[SchoolCodes]]),0,1)))} -> 0 | E18: {=IF(_xlfn.XLOOKUP(GRADES[[#This Row],[PayScaleCode]],PAYSCALES[PayScaleCode],PAYSCALES[AvailableToAllSchools])=TRUE,0,IF(GRADES[[#This Row],[AvailableToAllSchools]]=TRUE,1,IF(_xlfn.LET(_xlpm.sourceCodes, _xlfn.TEXTSPLIT(GRADES[[#This Row],[SchoolCodes]], ","),_xlpm.targetCodes, _xlfn.TEXTSPLIT(_xlfn.XLOOKUP(GRADES[[#This Row],[PayScaleCode]],PAYSCALES[PayScaleCode],PAYSCALES[SchoolCodes],1), ","),_xlpm.trimmedSource, TRIM(_xlpm.sourceCodes),_xlpm.trimmedTarget, TRIM(_xlpm.targetCodes),_xlpm.matches, ISNUMBER(MATCH(_xlpm.trimmedSource, _xlpm.trimmedTarget, 0)),AND(_xlpm.matches))=TRUE,0,1)))} -> 0 | F18: =IF(OR(GRADES[[#This Row],[AvailableToAllSchools]]=TRUE,GRADES[[#This Row],[AvailableToAllSchools]]=FALSE),IF(OR(GRADES[[#This Row],[PayScaleGradeEnabled]]=TRUE,GRADES[[#This Row],[PayScaleGradeEnabled]]=FALSE),0,1),1) -> 0 | G18: =(COUNTBLANK(GRADES[[#This Row],[PayScaleGradeCode]:[AvailableToAllSchools]])+COUNTBLANK(GRADES[[#This Row],[PayScaleGradeEnabled]])) -> 0 | H18: =IF(LEN(GRADES[[#This Row],[PayScaleGradeCode]])<100,0,1) -> 0 | I18: =IF(LEN(GRADES[[#This Row],[Title]])<100,0,1) -> 0 | J18: =IF(SUBSTITUTE(TEXT(GRADES[[#This Row],[PayScaleGradeCode]],10)," ","")=TEXT(GRADES[[#This Row],[PayScaleGradeCode]],10),0,1) -> 0 | K18: =SUM(GRADES[[#This Row],[Pay Scale issue]:[Schools Check]],GRADES[[#This Row],[TRUE /FALSE Typo]:[Space in Code]]) -> 0 | L18: =_xlfn.XLOOKUP(GRADES[[#This Row],[PayScaleCode]],PAYSCALES[PayScaleCode],PAYSCALES[London Weighting]) -> Fringe | N18: UQ_FRI | O18: Teacher Unqualified Fringe | P18: UQ_FRI | Q18: UQ1 | R18: UQ6 | S18: {=LOOKUP(2,1/(PSPOINTS[PayScaleCode]=GRADES[[#This Row],[PayScaleCode]])/(PSPOINTS[PayScalePointCode]=GRADES[[#This Row],[Point From (Check)]]),(PSPOINTS[ScalePointNumber]))} -> 1 | T18: {=LOOKUP(2,1/(PSPOINTS[PayScaleCode]=GRADES[[#This Row],[PayScaleCode]])/(PSPOINTS[PayScalePointCode]=GRADES[[#This Row],[Point To (Check)]]),(PSPOINTS[ScalePointNumber]))} -> 6 | U18: TRUE | W18: TRUE
A19: =IF(COUNTIF('19_PayScales'!N:N,'22_PayScaleGrades'!P19)>0,"0","1") -> 0 | B19: =COUNTIF(GRADES[PayScaleGradeCode],GRADES[[#This Row],[PayScaleGradeCode]])-1 -> 0 | C19: {=IF(GRADES[[#This Row],[AvailableToAllSchools]]=FALSE,IF(ISBLANK(GRADES[[#This Row],[SchoolCodes]]),1,IF(AND(COUNTIF(SCHOOLS[SchoolCode],_xlfn.TEXTSPLIT(GRADES[[#This Row],[SchoolCodes]],","))),0,1)),IF(GRADES[[#This Row],[AvailableToAllSchools]]=TRUE,IF(ISBLANK(GRADES[[#This Row],[SchoolCodes]]),0,1)))} -> 0 | E19: {=IF(_xlfn.XLOOKUP(GRADES[[#This Row],[PayScaleCode]],PAYSCALES[PayScaleCode],PAYSCALES[AvailableToAllSchools])=TRUE,0,IF(GRADES[[#This Row],[AvailableToAllSchools]]=TRUE,1,IF(_xlfn.LET(_xlpm.sourceCodes, _xlfn.TEXTSPLIT(GRADES[[#This Row],[SchoolCodes]], ","),_xlpm.targetCodes, _xlfn.TEXTSPLIT(_xlfn.XLOOKUP(GRADES[[#This Row],[PayScaleCode]],PAYSCALES[PayScaleCode],PAYSCALES[SchoolCodes],1), ","),_xlpm.trimmedSource, TRIM(_xlpm.sourceCodes),_xlpm.trimmedTarget, TRIM(_xlpm.targetCodes),_xlpm.matches, ISNUMBER(MATCH(_xlpm.trimmedSource, _xlpm.trimmedTarget, 0)),AND(_xlpm.matches))=TRUE,0,1)))} -> 0 | F19: =IF(OR(GRADES[[#This Row],[AvailableToAllSchools]]=TRUE,GRADES[[#This Row],[AvailableToAllSchools]]=FALSE),IF(OR(GRADES[[#This Row],[PayScaleGradeEnabled]]=TRUE,GRADES[[#This Row],[PayScaleGradeEnabled]]=FALSE),0,1),1) -> 0 | G19: =(COUNTBLANK(GRADES[[#This Row],[PayScaleGradeCode]:[AvailableToAllSchools]])+COUNTBLANK(GRADES[[#This Row],[PayScaleGradeEnabled]])) -> 0 | H19: =IF(LEN(GRADES[[#This Row],[PayScaleGradeCode]])<100,0,1) -> 0 | I19: =IF(LEN(GRADES[[#This Row],[Title]])<100,0,1) -> 0 | J19: =IF(SUBSTITUTE(TEXT(GRADES[[#This Row],[PayScaleGradeCode]],10)," ","")=TEXT(GRADES[[#This Row],[PayScaleGradeCode]],10),0,1) -> 0 | K19: =SUM(GRADES[[#This Row],[Pay Scale issue]:[Schools Check]],GRADES[[#This Row],[TRUE /FALSE Typo]:[Space in Code]]) -> 0 | L19: =_xlfn.XLOOKUP(GRADES[[#This Row],[PayScaleCode]],PAYSCALES[PayScaleCode],PAYSCALES[London Weighting]) -> Fringe | N19: LS_FRI | O19: Leadership Group Fringe | P19: LS_FRI | Q19: L01 | R19: L43 | S19: {=LOOKUP(2,1/(PSPOINTS[PayScaleCode]=GRADES[[#This Row],[PayScaleCode]])/(PSPOINTS[PayScalePointCode]=GRADES[[#This Row],[Point From (Check)]]),(PSPOINTS[ScalePointNumber]))} -> 1 | T19: {=LOOKUP(2,1/(PSPOINTS[PayScaleCode]=GRADES[[#This Row],[PayScaleCode]])/(PSPOINTS[PayScalePointCode]=GRADES[[#This Row],[Point To (Check)]]),(PSPOINTS[ScalePointNumber]))} -> 43 | U19: TRUE | W19: TRUE
A20: =IF(COUNTIF('19_PayScales'!N:N,'22_PayScaleGrades'!P20)>0,"0","1") -> 0 | B20: =COUNTIF(GRADES[PayScaleGradeCode],GRADES[[#This Row],[PayScaleGradeCode]])-1 -> 0 | C20: {=IF(GRADES[[#This Row],[AvailableToAllSchools]]=FALSE,IF(ISBLANK(GRADES[[#This Row],[SchoolCodes]]),1,IF(AND(COUNTIF(SCHOOLS[SchoolCode],_xlfn.TEXTSPLIT(GRADES[[#This Row],[SchoolCodes]],","))),0,1)),IF(GRADES[[#This Row],[AvailableToAllSchools]]=TRUE,IF(ISBLANK(GRADES[[#This Row],[SchoolCodes]]),0,1)))} -> 0 | E20: {=IF(_xlfn.XLOOKUP(GRADES[[#This Row],[PayScaleCode]],PAYSCALES[PayScaleCode],PAYSCALES[AvailableToAllSchools])=TRUE,0,IF(GRADES[[#This Row],[AvailableToAllSchools]]=TRUE,1,IF(_xlfn.LET(_xlpm.sourceCodes, _xlfn.TEXTSPLIT(GRADES[[#This Row],[SchoolCodes]], ","),_xlpm.targetCodes, _xlfn.TEXTSPLIT(_xlfn.XLOOKUP(GRADES[[#This Row],[PayScaleCode]],PAYSCALES[PayScaleCode],PAYSCALES[SchoolCodes],1), ","),_xlpm.trimmedSource, TRIM(_xlpm.sourceCodes),_xlpm.trimmedTarget, TRIM(_xlpm.targetCodes),_xlpm.matches, ISNUMBER(MATCH(_xlpm.trimmedSource, _xlpm.trimmedTarget, 0)),AND(_xlpm.matches))=TRUE,0,1)))} -> 0 | F20: =IF(OR(GRADES[[#This Row],[AvailableToAllSchools]]=TRUE,GRADES[[#This Row],[AvailableToAllSchools]]=FALSE),IF(OR(GRADES[[#This Row],[PayScaleGradeEnabled]]=TRUE,GRADES[[#This Row],[PayScaleGradeEnabled]]=FALSE),0,1),1) -> 0 | G20: =(COUNTBLANK(GRADES[[#This Row],[PayScaleGradeCode]:[AvailableToAllSchools]])+COUNTBLANK(GRADES[[#This Row],[PayScaleGradeEnabled]])) -> 0 | H20: =IF(LEN(GRADES[[#This Row],[PayScaleGradeCode]])<100,0,1) -> 0 | I20: =IF(LEN(GRADES[[#This Row],[Title]])<100,0,1) -> 0 | J20: =IF(SUBSTITUTE(TEXT(GRADES[[#This Row],[PayScaleGradeCode]],10)," ","")=TEXT(GRADES[[#This Row],[PayScaleGradeCode]],10),0,1) -> 0 | K20: =SUM(GRADES[[#This Row],[Pay Scale issue]:[Schools Check]],GRADES[[#This Row],[TRUE /FALSE Typo]:[Space in Code]]) -> 0 | L20: =_xlfn.XLOOKUP(GRADES[[#This Row],[PayScaleCode]],PAYSCALES[PayScaleCode],PAYSCALES[London Weighting]) -> Fringe | N20: LP_FRI | O20: Lead Practitioner Group Fringe | P20: LP_FRI | Q20: LP01 | R20: LP18 | S20: {=LOOKUP(2,1/(PSPOINTS[PayScaleCode]=GRADES[[#This Row],[PayScaleCode]])/(PSPOINTS[PayScalePointCode]=GRADES[[#This Row],[Point From (Check)]]),(PSPOINTS[ScalePointNumber]))} -> 1 | T20: {=LOOKUP(2,1/(PSPOINTS[PayScaleCode]=GRADES[[#This Row],[PayScaleCode]])/(PSPOINTS[PayScalePointCode]=GRADES[[#This Row],[Point To (Check)]]),(PSPOINTS[ScalePointNumber]))} -> 18 | U20: TRUE | W20: TRUE
... A26: =IF(COUNTIF('19_PayScales'!N:N,'22_PayScaleGrades'!P26)>0,"0","1") -> 0 | B26: =COUNTIF(GRADES[PayScaleGradeCode],GRADES[[#This Row],[PayScaleGradeCode]])-1 -> 0 | C26: {=IF(GRADES[[#This Row],[AvailableToAllSchools]]=FALSE,IF(ISBLANK(GRADES[[#This Row],[SchoolCodes]]),1,IF(AND(COUNTIF(SCHOOLS[SchoolCode],_xlfn.TEXTSPLIT(GRADES[[#This Row],[SchoolCodes]],","))),0,1)),IF(GRADES[[#This Row],[AvailableToAllSchools]]=TRUE,IF(ISBLANK(GRADES[[#This Row],[SchoolCodes]]),0,1)))} -> 0 | E26: {=IF(_xlfn.XLOOKUP(GRADES[[#This Row],[PayScaleCode]],PAYSCALES[PayScaleCode],PAYSCALES[AvailableToAllSchools])=TRUE,0,IF(GRADES[[#This Row],[AvailableToAllSchools]]=TRUE,1,IF(_xlfn.LET(_xlpm.sourceCodes, _xlfn.TEXTSPLIT(GRADES[[#This Row],[SchoolCodes]], ","),_xlpm.targetCodes, _xlfn.TEXTSPLIT(_xlfn.XLOOKUP(GRADES[[#This Row],[PayScaleCode]],PAYSCALES[PayScaleCode],PAYSCALES[SchoolCodes],1), ","),_xlpm.trimmedSource, TRIM(_xlpm.sourceCodes),_xlpm.trimmedTarget, TRIM(_xlpm.targetCodes),_xlpm.matches, ISNUMBER(MATCH(_xlpm.trimmedSource, _xlpm.trimmedTarget, 0)),AND(_xlpm.matches))=TRUE,0,1)))} -> 0 | F26: =IF(OR(GRADES[[#This Row],[AvailableToAllSchools]]=TRUE,GRADES[[#This Row],[AvailableToAllSchools]]=FALSE),IF(OR(GRADES[[#This Row],[PayScaleGradeEnabled]]=TRUE,GRADES[[#This Row],[PayScaleGradeEnabled]]=FALSE),0,1),1) -> 0 | G26: =(COUNTBLANK(GRADES[[#This Row],[PayScaleGradeCode]:[AvailableToAllSchools]])+COUNTBLANK(GRADES[[#This Row],[PayScaleGradeEnabled]])) -> 0 | H26: =IF(LEN(GRADES[[#This Row],[PayScaleGradeCode]])<100,0,1) -> 0 | I26: =IF(LEN(GRADES[[#This Row],[Title]])<100,0,1) -> 0 | J26: =IF(SUBSTITUTE(TEXT(GRADES[[#This Row],[PayScaleGradeCode]],10)," ","")=TEXT(GRADES[[#This Row],[PayScaleGradeCode]],10),0,1) -> 0 | K26: =SUM(GRADES[[#This Row],[Pay Scale issue]:[Schools Check]],GRADES[[#This Row],[TRUE /FALSE Typo]:[Space in Code]]) -> 0 | L26: =_xlfn.XLOOKUP(GRADES[[#This Row],[PayScaleCode]],PAYSCALES[PayScaleCode],PAYSCALES[London Weighting]) -> Outer | N26: LP_OUT | O26: Lead Practitioner Group Outer | P26: LP_OUT | Q26: LP01 | R26: LP18 | S26: {=LOOKUP(2,1/(PSPOINTS[PayScaleCode]=GRADES[[#This Row],[PayScaleCode]])/(PSPOINTS[PayScalePointCode]=GRADES[[#This Row],[Point From (Check)]]),(PSPOINTS[ScalePointNumber]))} -> 1 | T26: {=LOOKUP(2,1/(PSPOINTS[PayScaleCode]=GRADES[[#This Row],[PayScaleCode]])/(PSPOINTS[PayScalePointCode]=GRADES[[#This Row],[Point To (Check)]]),(PSPOINTS[ScalePointNumber]))} -> 18 | U26: TRUE | W26: TRUE
A27: =IF(COUNTIF('19_PayScales'!N:N,'22_PayScaleGrades'!P27)>0,"0","1") -> 0 | B27: =COUNTIF(GRADES[PayScaleGradeCode],GRADES[[#This Row],[PayScaleGradeCode]])-1 -> 0 | C27: {=IF(GRADES[[#This Row],[AvailableToAllSchools]]=FALSE,IF(ISBLANK(GRADES[[#This Row],[SchoolCodes]]),1,IF(AND(COUNTIF(SCHOOLS[SchoolCode],_xlfn.TEXTSPLIT(GRADES[[#This Row],[SchoolCodes]],","))),0,1)),IF(GRADES[[#This Row],[AvailableToAllSchools]]=TRUE,IF(ISBLANK(GRADES[[#This Row],[SchoolCodes]]),0,1)))} -> 0 | E27: {=IF(_xlfn.XLOOKUP(GRADES[[#This Row],[PayScaleCode]],PAYSCALES[PayScaleCode],PAYSCALES[AvailableToAllSchools])=TRUE,0,IF(GRADES[[#This Row],[AvailableToAllSchools]]=TRUE,1,IF(_xlfn.LET(_xlpm.sourceCodes, _xlfn.TEXTSPLIT(GRADES[[#This Row],[SchoolCodes]], ","),_xlpm.targetCodes, _xlfn.TEXTSPLIT(_xlfn.XLOOKUP(GRADES[[#This Row],[PayScaleCode]],PAYSCALES[PayScaleCode],PAYSCALES[SchoolCodes],1), ","),_xlpm.trimmedSource, TRIM(_xlpm.sourceCodes),_xlpm.trimmedTarget, TRIM(_xlpm.targetCodes),_xlpm.matches, ISNUMBER(MATCH(_xlpm.trimmedSource, _xlpm.trimmedTarget, 0)),AND(_xlpm.matches))=TRUE,0,1)))} -> 0 | F27: =IF(OR(GRADES[[#This Row],[AvailableToAllSchools]]=TRUE,GRADES[[#This Row],[AvailableToAllSchools]]=FALSE),IF(OR(GRADES[[#This Row],[PayScaleGradeEnabled]]=TRUE,GRADES[[#This Row],[PayScaleGradeEnabled]]=FALSE),0,1),1) -> 0 | G27: =(COUNTBLANK(GRADES[[#This Row],[PayScaleGradeCode]:[AvailableToAllSchools]])+COUNTBLANK(GRADES[[#This Row],[PayScaleGradeEnabled]])) -> 0 | H27: =IF(LEN(GRADES[[#This Row],[PayScaleGradeCode]])<100,0,1) -> 0 | I27: =IF(LEN(GRADES[[#This Row],[Title]])<100,0,1) -> 0 | J27: =IF(SUBSTITUTE(TEXT(GRADES[[#This Row],[PayScaleGradeCode]],10)," ","")=TEXT(GRADES[[#This Row],[PayScaleGradeCode]],10),0,1) -> 0 | K27: =SUM(GRADES[[#This Row],[Pay Scale issue]:[Schools Check]],GRADES[[#This Row],[TRUE /FALSE Typo]:[Space in Code]]) -> 0 | L27: =_xlfn.XLOOKUP(GRADES[[#This Row],[PayScaleCode]],PAYSCALES[PayScaleCode],PAYSCALES[London Weighting]) -> Outer | N27: NJC_OUT | O27: NJC Outer London | P27: NJC_OUT | Q27: 1 | R27: 65 | S27: {=LOOKUP(2,1/(PSPOINTS[PayScaleCode]=GRADES[[#This Row],[PayScaleCode]])/(PSPOINTS[PayScalePointCode]=GRADES[[#This Row],[Point From (Check)]]),(PSPOINTS[ScalePointNumber]))} -> 1 | T27: {=LOOKUP(2,1/(PSPOINTS[PayScaleCode]=GRADES[[#This Row],[PayScaleCode]])/(PSPOINTS[PayScalePointCode]=GRADES[[#This Row],[Point To (Check)]]),(PSPOINTS[ScalePointNumber]))} -> 65 | U27: TRUE | W27: TRUE
A28: =IF(COUNTIF('19_PayScales'!N:N,'22_PayScaleGrades'!P28)>0,"0","1") -> 0 | B28: =COUNTIF(GRADES[PayScaleGradeCode],GRADES[[#This Row],[PayScaleGradeCode]])-1 -> 0 | C28: {=IF(GRADES[[#This Row],[AvailableToAllSchools]]=FALSE,IF(ISBLANK(GRADES[[#This Row],[SchoolCodes]]),1,IF(AND(COUNTIF(SCHOOLS[SchoolCode],_xlfn.TEXTSPLIT(GRADES[[#This Row],[SchoolCodes]],","))),0,1)),IF(GRADES[[#This Row],[AvailableToAllSchools]]=TRUE,IF(ISBLANK(GRADES[[#This Row],[SchoolCodes]]),0,1)))} -> 0 | E28: {=IF(_xlfn.XLOOKUP(GRADES[[#This Row],[PayScaleCode]],PAYSCALES[PayScaleCode],PAYSCALES[AvailableToAllSchools])=TRUE,0,IF(GRADES[[#This Row],[AvailableToAllSchools]]=TRUE,1,IF(_xlfn.LET(_xlpm.sourceCodes, _xlfn.TEXTSPLIT(GRADES[[#This Row],[SchoolCodes]], ","),_xlpm.targetCodes, _xlfn.TEXTSPLIT(_xlfn.XLOOKUP(GRADES[[#This Row],[PayScaleCode]],PAYSCALES[PayScaleCode],PAYSCALES[SchoolCodes],1), ","),_xlpm.trimmedSource, TRIM(_xlpm.sourceCodes),_xlpm.trimmedTarget, TRIM(_xlpm.targetCodes),_xlpm.matches, ISNUMBER(MATCH(_xlpm.trimmedSource, _xlpm.trimmedTarget, 0)),AND(_xlpm.matches))=TRUE,0,1)))} -> 0 | F28: =IF(OR(GRADES[[#This Row],[AvailableToAllSchools]]=TRUE,GRADES[[#This Row],[AvailableToAllSchools]]=FALSE),IF(OR(GRADES[[#This Row],[PayScaleGradeEnabled]]=TRUE,GRADES[[#This Row],[PayScaleGradeEnabled]]=FALSE),0,1),1) -> 0 | G28: =(COUNTBLANK(GRADES[[#This Row],[PayScaleGradeCode]:[AvailableToAllSchools]])+COUNTBLANK(GRADES[[#This Row],[PayScaleGradeEnabled]])) -> 0 | H28: =IF(LEN(GRADES[[#This Row],[PayScaleGradeCode]])<100,0,1) -> 0 | I28: =IF(LEN(GRADES[[#This Row],[Title]])<100,0,1) -> 0 | J28: =IF(SUBSTITUTE(TEXT(GRADES[[#This Row],[PayScaleGradeCode]],10)," ","")=TEXT(GRADES[[#This Row],[PayScaleGradeCode]],10),0,1) -> 0 | K28: =SUM(GRADES[[#This Row],[Pay Scale issue]:[Schools Check]],GRADES[[#This Row],[TRUE /FALSE Typo]:[Space in Code]]) -> 0 | L28: =_xlfn.XLOOKUP(GRADES[[#This Row],[PayScaleCode]],PAYSCALES[PayScaleCode],PAYSCALES[London Weighting]) -> Inner | N28: MAIN_UPS_INN | O28: Teachers Main through UPS Inner | P28: MAIN_INN | Q28: M1 | R28: U3 | S28: {=LOOKUP(2,1/(PSPOINTS[PayScaleCode]=GRADES[[#This Row],[PayScaleCode]])/(PSPOINTS[PayScalePointCode]=GRADES[[#This Row],[Point From (Check)]]),(PSPOINTS[ScalePointNumber]))} -> 1 | T28: {=LOOKUP(2,1/(PSPOINTS[PayScaleCode]=GRADES[[#This Row],[PayScaleCode]])/(PSPOINTS[PayScalePointCode]=GRADES[[#This Row],[Point To (Check)]]),(PSPOINTS[ScalePointNumber]))} -> 11 | U28: TRUE | W28: TRUE
A29: =IF(COUNTIF('19_PayScales'!N:N,'22_PayScaleGrades'!P29)>0,"0","1") -> 0 | B29: =COUNTIF(GRADES[PayScaleGradeCode],GRADES[[#This Row],[PayScaleGradeCode]])-1 -> 0 | C29: {=IF(GRADES[[#This Row],[AvailableToAllSchools]]=FALSE,IF(ISBLANK(GRADES[[#This Row],[SchoolCodes]]),1,IF(AND(COUNTIF(SCHOOLS[SchoolCode],_xlfn.TEXTSPLIT(GRADES[[#This Row],[SchoolCodes]],","))),0,1)),IF(GRADES[[#This Row],[AvailableToAllSchools]]=TRUE,IF(ISBLANK(GRADES[[#This Row],[SchoolCodes]]),0,1)))} -> 0 | E29: {=IF(_xlfn.XLOOKUP(GRADES[[#This Row],[PayScaleCode]],PAYSCALES[PayScaleCode],PAYSCALES[AvailableToAllSchools])=TRUE,0,IF(GRADES[[#This Row],[AvailableToAllSchools]]=TRUE,1,IF(_xlfn.LET(_xlpm.sourceCodes, _xlfn.TEXTSPLIT(GRADES[[#This Row],[SchoolCodes]], ","),_xlpm.targetCodes, _xlfn.TEXTSPLIT(_xlfn.XLOOKUP(GRADES[[#This Row],[PayScaleCode]],PAYSCALES[PayScaleCode],PAYSCALES[SchoolCodes],1), ","),_xlpm.trimmedSource, TRIM(_xlpm.sourceCodes),_xlpm.trimmedTarget, TRIM(_xlpm.targetCodes),_xlpm.matches, ISNUMBER(MATCH(_xlpm.trimmedSource, _xlpm.trimmedTarget, 0)),AND(_xlpm.matches))=TRUE,0,1)))} -> 0 | F29: =IF(OR(GRADES[[#This Row],[AvailableToAllSchools]]=TRUE,GRADES[[#This Row],[AvailableToAllSchools]]=FALSE),IF(OR(GRADES[[#This Row],[PayScaleGradeEnabled]]=TRUE,GRADES[[#This Row],[PayScaleGradeEnabled]]=FALSE),0,1),1) -> 0 | G29: =(COUNTBLANK(GRADES[[#This Row],[PayScaleGradeCode]:[AvailableToAllSchools]])+COUNTBLANK(GRADES[[#This Row],[PayScaleGradeEnabled]])) -> 0 | H29: =IF(LEN(GRADES[[#This Row],[PayScaleGradeCode]])<100,0,1) -> 0 | I29: =IF(LEN(GRADES[[#This Row],[Title]])<100,0,1) -> 0 | J29: =IF(SUBSTITUTE(TEXT(GRADES[[#This Row],[PayScaleGradeCode]],10)," ","")=TEXT(GRADES[[#This Row],[PayScaleGradeCode]],10),0,1) -> 0 | K29: =SUM(GRADES[[#This Row],[Pay Scale issue]:[Schools Check]],GRADES[[#This Row],[TRUE /FALSE Typo]:[Space in Code]]) -> 0 | L29: =_xlfn.XLOOKUP(GRADES[[#This Row],[PayScaleCode]],PAYSCALES[PayScaleCode],PAYSCALES[London Weighting]) -> Inner | N29: MAIN_INN | O29: Teachers Main Scale only Inner | P29: MAIN_INN | Q29: M1 | R29: M6 | S29: {=LOOKUP(2,1/(PSPOINTS[PayScaleCode]=GRADES[[#This Row],[PayScaleCode]])/(PSPOINTS[PayScalePointCode]=GRADES[[#This Row],[Point From (Check)]]),(PSPOINTS[ScalePointNumber]))} -> 1 | T29: {=LOOKUP(2,1/(PSPOINTS[PayScaleCode]=GRADES[[#This Row],[PayScaleCode]])/(PSPOINTS[PayScalePointCode]=GRADES[[#This Row],[Point To (Check)]]),(PSPOINTS[ScalePointNumber]))} -> 6 | U29: TRUE | W29: TRUE
A30: =IF(COUNTIF('19_PayScales'!N:N,'22_PayScaleGrades'!P30)>0,"0","1") -> 0 | B30: =COUNTIF(GRADES[PayScaleGradeCode],GRADES[[#This Row],[PayScaleGradeCode]])-1 -> 0 | C30: {=IF(GRADES[[#This Row],[AvailableToAllSchools]]=FALSE,IF(ISBLANK(GRADES[[#This Row],[SchoolCodes]]),1,IF(AND(COUNTIF(SCHOOLS[SchoolCode],_xlfn.TEXTSPLIT(GRADES[[#This Row],[SchoolCodes]],","))),0,1)),IF(GRADES[[#This Row],[AvailableToAllSchools]]=TRUE,IF(ISBLANK(GRADES[[#This Row],[SchoolCodes]]),0,1)))} -> 0 | E30: {=IF(_xlfn.XLOOKUP(GRADES[[#This Row],[PayScaleCode]],PAYSCALES[PayScaleCode],PAYSCALES[AvailableToAllSchools])=TRUE,0,IF(GRADES[[#This Row],[AvailableToAllSchools]]=TRUE,1,IF(_xlfn.LET(_xlpm.sourceCodes, _xlfn.TEXTSPLIT(GRADES[[#This Row],[SchoolCodes]], ","),_xlpm.targetCodes, _xlfn.TEXTSPLIT(_xlfn.XLOOKUP(GRADES[[#This Row],[PayScaleCode]],PAYSCALES[PayScaleCode],PAYSCALES[SchoolCodes],1), ","),_xlpm.trimmedSource, TRIM(_xlpm.sourceCodes),_xlpm.trimmedTarget, TRIM(_xlpm.targetCodes),_xlpm.matches, ISNUMBER(MATCH(_xlpm.trimmedSource, _xlpm.trimmedTarget, 0)),AND(_xlpm.matches))=TRUE,0,1)))} -> 0 | F30: =IF(OR(GRADES[[#This Row],[AvailableToAllSchools]]=TRUE,GRADES[[#This Row],[AvailableToAllSchools]]=FALSE),IF(OR(GRADES[[#This Row],[PayScaleGradeEnabled]]=TRUE,GRADES[[#This Row],[PayScaleGradeEnabled]]=FALSE),0,1),1) -> 0 | G30: =(COUNTBLANK(GRADES[[#This Row],[PayScaleGradeCode]:[AvailableToAllSchools]])+COUNTBLANK(GRADES[[#This Row],[PayScaleGradeEnabled]])) -> 0 | H30: =IF(LEN(GRADES[[#This Row],[PayScaleGradeCode]])<100,0,1) -> 0 | I30: =IF(LEN(GRADES[[#This Row],[Title]])<100,0,1) -> 0 | J30: =IF(SUBSTITUTE(TEXT(GRADES[[#This Row],[PayScaleGradeCode]],10)," ","")=TEXT(GRADES[[#This Row],[PayScaleGradeCode]],10),0,1) -> 0 | K30: =SUM(GRADES[[#This Row],[Pay Scale issue]:[Schools Check]],GRADES[[#This Row],[TRUE /FALSE Typo]:[Space in Code]]) -> 0 | L30: =_xlfn.XLOOKUP(GRADES[[#This Row],[PayScaleCode]],PAYSCALES[PayScaleCode],PAYSCALES[London Weighting]) -> Inner | N30: UPS_INN | O30: Teachers Upper Scale only Inner | P30: MAIN_INN | Q30: U1Y1 | R30: U3 | S30: {=LOOKUP(2,1/(PSPOINTS[PayScaleCode]=GRADES[[#This Row],[PayScaleCode]])/(PSPOINTS[PayScalePointCode]=GRADES[[#This Row],[Point From (Check)]]),(PSPOINTS[ScalePointNumber]))} -> 7 | T30: {=LOOKUP(2,1/(PSPOINTS[PayScaleCode]=GRADES[[#This Row],[PayScaleCode]])/(PSPOINTS[PayScalePointCode]=GRADES[[#This Row],[Point To (Check)]]),(PSPOINTS[ScalePointNumber]))} -> 11 | U30: TRUE | W30: TRUE
A31: =IF(COUNTIF('19_PayScales'!N:N,'22_PayScaleGrades'!P31)>0,"0","1") -> 0 | B31: =COUNTIF(GRADES[PayScaleGradeCode],GRADES[[#This Row],[PayScaleGradeCode]])-1 -> 0 | C31: {=IF(GRADES[[#This Row],[AvailableToAllSchools]]=FALSE,IF(ISBLANK(GRADES[[#This Row],[SchoolCodes]]),1,IF(AND(COUNTIF(SCHOOLS[SchoolCode],_xlfn.TEXTSPLIT(GRADES[[#This Row],[SchoolCodes]],","))),0,1)),IF(GRADES[[#This Row],[AvailableToAllSchools]]=TRUE,IF(ISBLANK(GRADES[[#This Row],[SchoolCodes]]),0,1)))} -> 0 | E31: {=IF(_xlfn.XLOOKUP(GRADES[[#This Row],[PayScaleCode]],PAYSCALES[PayScaleCode],PAYSCALES[AvailableToAllSchools])=TRUE,0,IF(GRADES[[#This Row],[AvailableToAllSchools]]=TRUE,1,IF(_xlfn.LET(_xlpm.sourceCodes, _xlfn.TEXTSPLIT(GRADES[[#This Row],[SchoolCodes]], ","),_xlpm.targetCodes, _xlfn.TEXTSPLIT(_xlfn.XLOOKUP(GRADES[[#This Row],[PayScaleCode]],PAYSCALES[PayScaleCode],PAYSCALES[SchoolCodes],1), ","),_xlpm.trimmedSource, TRIM(_xlpm.sourceCodes),_xlpm.trimmedTarget, TRIM(_xlpm.targetCodes),_xlpm.matches, ISNUMBER(MATCH(_xlpm.trimmedSource, _xlpm.trimmedTarget, 0)),AND(_xlpm.matches))=TRUE,0,1)))} -> 0 | F31: =IF(OR(GRADES[[#This Row],[AvailableToAllSchools]]=TRUE,GRADES[[#This Row],[AvailableToAllSchools]]=FALSE),IF(OR(GRADES[[#This Row],[PayScaleGradeEnabled]]=TRUE,GRADES[[#This Row],[PayScaleGradeEnabled]]=FALSE),0,1),1) -> 0 | G31: =(COUNTBLANK(GRADES[[#This Row],[PayScaleGradeCode]:[AvailableToAllSchools]])+COUNTBLANK(GRADES[[#This Row],[PayScaleGradeEnabled]])) -> 0 | H31: =IF(LEN(GRADES[[#This Row],[PayScaleGradeCode]])<100,0,1) -> 0 | I31: =IF(LEN(GRADES[[#This Row],[Title]])<100,0,1) -> 0 | J31: =IF(SUBSTITUTE(TEXT(GRADES[[#This Row],[PayScaleGradeCode]],10)," ","")=TEXT(GRADES[[#This Row],[PayScaleGradeCode]],10),0,1) -> 0 | K31: =SUM(GRADES[[#This Row],[Pay Scale issue]:[Schools Check]],GRADES[[#This Row],[TRUE /FALSE Typo]:[Space in Code]]) -> 0 | L31: =_xlfn.XLOOKUP(GRADES[[#This Row],[PayScaleCode]],PAYSCALES[PayScaleCode],PAYSCALES[London Weighting]) -> Inner | N31: UQ_INN | O31: Teacher Unqualified Inner | P31: UQ_INN | Q31: UQ1 | R31: UQ6 | S31: {=LOOKUP(2,1/(PSPOINTS[PayScaleCode]=GRADES[[#This Row],[PayScaleCode]])/(PSPOINTS[PayScalePointCode]=GRADES[[#This Row],[Point From (Check)]]),(PSPOINTS[ScalePointNumber]))} -> 1 | T31: {=LOOKUP(2,1/(PSPOINTS[PayScaleCode]=GRADES[[#This Row],[PayScaleCode]])/(PSPOINTS[PayScalePointCode]=GRADES[[#This Row],[Point To (Check)]]),(PSPOINTS[ScalePointNumber]))} -> 6 | U31: TRUE | W31: TRUE
A32: =IF(COUNTIF('19_PayScales'!N:N,'22_PayScaleGrades'!P32)>0,"0","1") -> 0 | B32: =COUNTIF(GRADES[PayScaleGradeCode],GRADES[[#This Row],[PayScaleGradeCode]])-1 -> 0 | C32: {=IF(GRADES[[#This Row],[AvailableToAllSchools]]=FALSE,IF(ISBLANK(GRADES[[#This Row],[SchoolCodes]]),1,IF(AND(COUNTIF(SCHOOLS[SchoolCode],_xlfn.TEXTSPLIT(GRADES[[#This Row],[SchoolCodes]],","))),0,1)),IF(GRADES[[#This Row],[AvailableToAllSchools]]=TRUE,IF(ISBLANK(GRADES[[#This Row],[SchoolCodes]]),0,1)))} -> 0 | E32: {=IF(_xlfn.XLOOKUP(GRADES[[#This Row],[PayScaleCode]],PAYSCALES[PayScaleCode],PAYSCALES[AvailableToAllSchools])=TRUE,0,IF(GRADES[[#This Row],[AvailableToAllSchools]]=TRUE,1,IF(_xlfn.LET(_xlpm.sourceCodes, _xlfn.TEXTSPLIT(GRADES[[#This Row],[SchoolCodes]], ","),_xlpm.targetCodes, _xlfn.TEXTSPLIT(_xlfn.XLOOKUP(GRADES[[#This Row],[PayScaleCode]],PAYSCALES[PayScaleCode],PAYSCALES[SchoolCodes],1), ","),_xlpm.trimmedSource, TRIM(_xlpm.sourceCodes),_xlpm.trimmedTarget, TRIM(_xlpm.targetCodes),_xlpm.matches, ISNUMBER(MATCH(_xlpm.trimmedSource, _xlpm.trimmedTarget, 0)),AND(_xlpm.matches))=TRUE,0,1)))} -> 0 | F32: =IF(OR(GRADES[[#This Row],[AvailableToAllSchools]]=TRUE,GRADES[[#This Row],[AvailableToAllSchools]]=FALSE),IF(OR(GRADES[[#This Row],[PayScaleGradeEnabled]]=TRUE,GRADES[[#This Row],[PayScaleGradeEnabled]]=FALSE),0,1),1) -> 0 | G32: =(COUNTBLANK(GRADES[[#This Row],[PayScaleGradeCode]:[AvailableToAllSchools]])+COUNTBLANK(GRADES[[#This Row],[PayScaleGradeEnabled]])) -> 0 | H32: =IF(LEN(GRADES[[#This Row],[PayScaleGradeCode]])<100,0,1) -> 0 | I32: =IF(LEN(GRADES[[#This Row],[Title]])<100,0,1) -> 0 | J32: =IF(SUBSTITUTE(TEXT(GRADES[[#This Row],[PayScaleGradeCode]],10)," ","")=TEXT(GRADES[[#This Row],[PayScaleGradeCode]],10),0,1) -> 0 | K32: =SUM(GRADES[[#This Row],[Pay Scale issue]:[Schools Check]],GRADES[[#This Row],[TRUE /FALSE Typo]:[Space in Code]]) -> 0 | L32: =_xlfn.XLOOKUP(GRADES[[#This Row],[PayScaleCode]],PAYSCALES[PayScaleCode],PAYSCALES[London Weighting]) -> Inner | N32: LS_INN | O32: Leadership Group Inner | P32: LS_INN | Q32: L01 | R32: L43 | S32: {=LOOKUP(2,1/(PSPOINTS[PayScaleCode]=GRADES[[#This Row],[PayScaleCode]])/(PSPOINTS[PayScalePointCode]=GRADES[[#This Row],[Point From (Check)]]),(PSPOINTS[ScalePointNumber]))} -> 1 | T32: {=LOOKUP(2,1/(PSPOINTS[PayScaleCode]=GRADES[[#This Row],[PayScaleCode]])/(PSPOINTS[PayScalePointCode]=GRADES[[#This Row],[Point To (Check)]]),(PSPOINTS[ScalePointNumber]))} -> 43 | U32: TRUE | W32: TRUE
A33: =IF(COUNTIF('19_PayScales'!N:N,'22_PayScaleGrades'!P33)>0,"0","1") -> 0 | B33: =COUNTIF(GRADES[PayScaleGradeCode],GRADES[[#This Row],[PayScaleGradeCode]])-1 -> 0 | C33: {=IF(GRADES[[#This Row],[AvailableToAllSchools]]=FALSE,IF(ISBLANK(GRADES[[#This Row],[SchoolCodes]]),1,IF(AND(COUNTIF(SCHOOLS[SchoolCode],_xlfn.TEXTSPLIT(GRADES[[#This Row],[SchoolCodes]],","))),0,1)),IF(GRADES[[#This Row],[AvailableToAllSchools]]=TRUE,IF(ISBLANK(GRADES[[#This Row],[SchoolCodes]]),0,1)))} -> 0 | E33: {=IF(_xlfn.XLOOKUP(GRADES[[#This Row],[PayScaleCode]],PAYSCALES[PayScaleCode],PAYSCALES[AvailableToAllSchools])=TRUE,0,IF(GRADES[[#This Row],[AvailableToAllSchools]]=TRUE,1,IF(_xlfn.LET(_xlpm.sourceCodes, _xlfn.TEXTSPLIT(GRADES[[#This Row],[SchoolCodes]], ","),_xlpm.targetCodes, _xlfn.TEXTSPLIT(_xlfn.XLOOKUP(GRADES[[#This Row],[PayScaleCode]],PAYSCALES[PayScaleCode],PAYSCALES[SchoolCodes],1), ","),_xlpm.trimmedSource, TRIM(_xlpm.sourceCodes),_xlpm.trimmedTarget, TRIM(_xlpm.targetCodes),_xlpm.matches, ISNUMBER(MATCH(_xlpm.trimmedSource, _xlpm.trimmedTarget, 0)),AND(_xlpm.matches))=TRUE,0,1)))} -> 0 | F33: =IF(OR(GRADES[[#This Row],[AvailableToAllSchools]]=TRUE,GRADES[[#This Row],[AvailableToAllSchools]]=FALSE),IF(OR(GRADES[[#This Row],[PayScaleGradeEnabled]]=TRUE,GRADES[[#This Row],[PayScaleGradeEnabled]]=FALSE),0,1),1) -> 0 | G33: =(COUNTBLANK(GRADES[[#This Row],[PayScaleGradeCode]:[AvailableToAllSchools]])+COUNTBLANK(GRADES[[#This Row],[PayScaleGradeEnabled]])) -> 0 | H33: =IF(LEN(GRADES[[#This Row],[PayScaleGradeCode]])<100,0,1) -> 0 | I33: =IF(LEN(GRADES[[#This Row],[Title]])<100,0,1) -> 0 | J33: =IF(SUBSTITUTE(TEXT(GRADES[[#This Row],[PayScaleGradeCode]],10)," ","")=TEXT(GRADES[[#This Row],[PayScaleGradeCode]],10),0,1) -> 0 | K33: =SUM(GRADES[[#This Row],[Pay Scale issue]:[Schools Check]],GRADES[[#This Row],[TRUE /FALSE Typo]:[Space in Code]]) -> 0 | L33: =_xlfn.XLOOKUP(GRADES[[#This Row],[PayScaleCode]],PAYSCALES[PayScaleCode],PAYSCALES[London Weighting]) -> Inner | N33: LP_INN | O33: Lead Practioner Group Inner | P33: LP_INN | Q33: LP01 | R33: LP18 | S33: {=LOOKUP(2,1/(PSPOINTS[PayScaleCode]=GRADES[[#This Row],[PayScaleCode]])/(PSPOINTS[PayScalePointCode]=GRADES[[#This Row],[Point From (Check)]]),(PSPOINTS[ScalePointNumber]))} -> 1 | T33: {=LOOKUP(2,1/(PSPOINTS[PayScaleCode]=GRADES[[#This Row],[PayScaleCode]])/(PSPOINTS[PayScalePointCode]=GRADES[[#This Row],[Point To (Check)]]),(PSPOINTS[ScalePointNumber]))} -> 18 | U33: TRUE | W33: TRUE
A34: =IF(COUNTIF('19_PayScales'!N:N,'22_PayScaleGrades'!P34)>0,"0","1") -> 0 | B34: =COUNTIF(GRADES[PayScaleGradeCode],GRADES[[#This Row],[PayScaleGradeCode]])-1 -> 0 | C34: {=IF(GRADES[[#This Row],[AvailableToAllSchools]]=FALSE,IF(ISBLANK(GRADES[[#This Row],[SchoolCodes]]),1,IF(AND(COUNTIF(SCHOOLS[SchoolCode],_xlfn.TEXTSPLIT(GRADES[[#This Row],[SchoolCodes]],","))),0,1)),IF(GRADES[[#This Row],[AvailableToAllSchools]]=TRUE,IF(ISBLANK(GRADES[[#This Row],[SchoolCodes]]),0,1)))} -> 0 | E34: {=IF(_xlfn.XLOOKUP(GRADES[[#This Row],[PayScaleCode]],PAYSCALES[PayScaleCode],PAYSCALES[AvailableToAllSchools])=TRUE,0,IF(GRADES[[#This Row],[AvailableToAllSchools]]=TRUE,1,IF(_xlfn.LET(_xlpm.sourceCodes, _xlfn.TEXTSPLIT(GRADES[[#This Row],[SchoolCodes]], ","),_xlpm.targetCodes, _xlfn.TEXTSPLIT(_xlfn.XLOOKUP(GRADES[[#This Row],[PayScaleCode]],PAYSCALES[PayScaleCode],PAYSCALES[SchoolCodes],1), ","),_xlpm.trimmedSource, TRIM(_xlpm.sourceCodes),_xlpm.trimmedTarget, TRIM(_xlpm.targetCodes),_xlpm.matches, ISNUMBER(MATCH(_xlpm.trimmedSource, _xlpm.trimmedTarget, 0)),AND(_xlpm.matches))=TRUE,0,1)))} -> 0 | F34: =IF(OR(GRADES[[#This Row],[AvailableToAllSchools]]=TRUE,GRADES[[#This Row],[AvailableToAllSchools]]=FALSE),IF(OR(GRADES[[#This Row],[PayScaleGradeEnabled]]=TRUE,GRADES[[#This Row],[PayScaleGradeEnabled]]=FALSE),0,1),1) -> 0 | G34: =(COUNTBLANK(GRADES[[#This Row],[PayScaleGradeCode]:[AvailableToAllSchools]])+COUNTBLANK(GRADES[[#This Row],[PayScaleGradeEnabled]])) -> 0 | H34: =IF(LEN(GRADES[[#This Row],[PayScaleGradeCode]])<100,0,1) -> 0 | I34: =IF(LEN(GRADES[[#This Row],[Title]])<100,0,1) -> 0 | J34: =IF(SUBSTITUTE(TEXT(GRADES[[#This Row],[PayScaleGradeCode]],10)," ","")=TEXT(GRADES[[#This Row],[PayScaleGradeCode]],10),0,1) -> 0 | K34: =SUM(GRADES[[#This Row],[Pay Scale issue]:[Schools Check]],GRADES[[#This Row],[TRUE /FALSE Typo]:[Space in Code]]) -> 0 | L34: =_xlfn.XLOOKUP(GRADES[[#This Row],[PayScaleCode]],PAYSCALES[PayScaleCode],PAYSCALES[London Weighting]) -> Inner | N34: NJC_INN | O34: NJC Inner London | P34: NJC_INN | Q34: 1 | R34: 65 | S34: {=LOOKUP(2,1/(PSPOINTS[PayScaleCode]=GRADES[[#This Row],[PayScaleCode]])/(PSPOINTS[PayScalePointCode]=GRADES[[#This Row],[Point From (Check)]]),(PSPOINTS[ScalePointNumber]))} -> 1 | T34: {=LOOKUP(2,1/(PSPOINTS[PayScaleCode]=GRADES[[#This Row],[PayScaleCode]])/(PSPOINTS[PayScalePointCode]=GRADES[[#This Row],[Point To (Check)]]),(PSPOINTS[ScalePointNumber]))} -> 65 | U34: TRUE | W34: TRUE

Sheet 21_PayScaleIncreasePercen
A1: Pay Scale Code Issue | B1: Blank in column | C1: Space in Code | D1: Will Import if 0 | E1: ScenarioCode | F1: PayScaleCode | G1: FinancialYearsCode | H1: IncreasePercentage
A2: =IF(COUNTIF('19_PayScales'!N:N,F2)>0,0,1) -> 0 | B2: =COUNTBLANK(PS_INCPERC[[#This Row],[PayScaleCode]:[IncreasePercentage]]) -> 0 | C2: =IF(SUBSTITUTE(TEXT(PS_INCPERC[[#This Row],[PayScaleCode]],10)," ","")=TEXT(PS_INCPERC[[#This Row],[PayScaleCode]],10),0,1) -> 0 | D2: =SUM(PS_INCPERC[[#This Row],[Pay Scale Code Issue]:[Space in Code]]) -> 0 | F2: MAIN_EW | G2: 2026/27 | H2: 5 | J2: Note: This tab is for pay scale Year 1 % uplift (per scope)
A3: =IF(COUNTIF('19_PayScales'!N:N,F3)>0,0,1) -> 0 | B3: =COUNTBLANK(PS_INCPERC[[#This Row],[PayScaleCode]:[IncreasePercentage]]) -> 0 | C3: =IF(SUBSTITUTE(TEXT(PS_INCPERC[[#This Row],[PayScaleCode]],10)," ","")=TEXT(PS_INCPERC[[#This Row],[PayScaleCode]],10),0,1) -> 0 | D3: =SUM(PS_INCPERC[[#This Row],[Pay Scale Code Issue]:[Space in Code]]) -> 0 | F3: LP_EW | G3: 2026/27 | H3: 5
A4: =IF(COUNTIF('19_PayScales'!N:N,F4)>0,0,1) -> 0 | B4: =COUNTBLANK(PS_INCPERC[[#This Row],[PayScaleCode]:[IncreasePercentage]]) -> 0 | C4: =IF(SUBSTITUTE(TEXT(PS_INCPERC[[#This Row],[PayScaleCode]],10)," ","")=TEXT(PS_INCPERC[[#This Row],[PayScaleCode]],10),0,1) -> 0 | D4: =SUM(PS_INCPERC[[#This Row],[Pay Scale Code Issue]:[Space in Code]]) -> 0 | F4: UQ_EW | G4: 2026/27 | H4: 5
A5: =IF(COUNTIF('19_PayScales'!N:N,F5)>0,0,1) -> 0 | B5: =COUNTBLANK(PS_INCPERC[[#This Row],[PayScaleCode]:[IncreasePercentage]]) -> 0 | C5: =IF(SUBSTITUTE(TEXT(PS_INCPERC[[#This Row],[PayScaleCode]],10)," ","")=TEXT(PS_INCPERC[[#This Row],[PayScaleCode]],10),0,1) -> 0 | D5: =SUM(PS_INCPERC[[#This Row],[Pay Scale Code Issue]:[Space in Code]]) -> 0 | F5: LS_EW | G5: 2026/27 | H5: 5
A6: =IF(COUNTIF('19_PayScales'!N:N,F6)>0,0,1) -> 0 | B6: =COUNTBLANK(PS_INCPERC[[#This Row],[PayScaleCode]:[IncreasePercentage]]) -> 0 | C6: =IF(SUBSTITUTE(TEXT(PS_INCPERC[[#This Row],[PayScaleCode]],10)," ","")=TEXT(PS_INCPERC[[#This Row],[PayScaleCode]],10),0,1) -> 0 | D6: =SUM(PS_INCPERC[[#This Row],[Pay Scale Code Issue]:[Space in Code]]) -> 0 | F6: NJC_EW | G6: 2025/26 | H6: 5
A7: =IF(COUNTIF('19_PayScales'!N:N,F7)>0,0,1) -> 0 | B7: =COUNTBLANK(PS_INCPERC[[#This Row],[PayScaleCode]:[IncreasePercentage]]) -> 0 | C7: =IF(SUBSTITUTE(TEXT(PS_INCPERC[[#This Row],[PayScaleCode]],10)," ","")=TEXT(PS_INCPERC[[#This Row],[PayScaleCode]],10),0,1) -> 0 | D7: =SUM(PS_INCPERC[[#This Row],[Pay Scale Code Issue]:[Space in Code]]) -> 0 | F7: MAIN_FRI | G7: 2026/27 | H7: 5
A8: =IF(COUNTIF('19_PayScales'!N:N,F8)>0,0,1) -> 0 | B8: =COUNTBLANK(PS_INCPERC[[#This Row],[PayScaleCode]:[IncreasePercentage]]) -> 0 | C8: =IF(SUBSTITUTE(TEXT(PS_INCPERC[[#This Row],[PayScaleCode]],10)," ","")=TEXT(PS_INCPERC[[#This Row],[PayScaleCode]],10),0,1) -> 0 | D8: =SUM(PS_INCPERC[[#This Row],[Pay Scale Code Issue]:[Space in Code]]) -> 0 | F8: LP_FRI | G8: 2026/27 | H8: 5
A9: =IF(COUNTIF('19_PayScales'!N:N,F9)>0,0,1) -> 0 | B9: =COUNTBLANK(PS_INCPERC[[#This Row],[PayScaleCode]:[IncreasePercentage]]) -> 0 | C9: =IF(SUBSTITUTE(TEXT(PS_INCPERC[[#This Row],[PayScaleCode]],10)," ","")=TEXT(PS_INCPERC[[#This Row],[PayScaleCode]],10),0,1) -> 0 | D9: =SUM(PS_INCPERC[[#This Row],[Pay Scale Code Issue]:[Space in Code]]) -> 0 | F9: UQ_FRI | G9: 2026/27 | H9: 5
A10: =IF(COUNTIF('19_PayScales'!N:N,F10)>0,0,1) -> 0 | B10: =COUNTBLANK(PS_INCPERC[[#This Row],[PayScaleCode]:[IncreasePercentage]]) -> 0 | C10: =IF(SUBSTITUTE(TEXT(PS_INCPERC[[#This Row],[PayScaleCode]],10)," ","")=TEXT(PS_INCPERC[[#This Row],[PayScaleCode]],10),0,1) -> 0 | D10: =SUM(PS_INCPERC[[#This Row],[Pay Scale Code Issue]:[Space in Code]]) -> 0 | F10: LS_FRI | G10: 2026/27 | H10: 5
A11: =IF(COUNTIF('19_PayScales'!N:N,F11)>0,0,1) -> 0 | B11: =COUNTBLANK(PS_INCPERC[[#This Row],[PayScaleCode]:[IncreasePercentage]]) -> 0 | C11: =IF(SUBSTITUTE(TEXT(PS_INCPERC[[#This Row],[PayScaleCode]],10)," ","")=TEXT(PS_INCPERC[[#This Row],[PayScaleCode]],10),0,1) -> 0 | D11: =SUM(PS_INCPERC[[#This Row],[Pay Scale Code Issue]:[Space in Code]]) -> 0 | F11: MAIN_INN | G11: 2026/27 | H11: 5
A12: =IF(COUNTIF('19_PayScales'!N:N,F12)>0,0,1) -> 0 | B12: =COUNTBLANK(PS_INCPERC[[#This Row],[PayScaleCode]:[IncreasePercentage]]) -> 0 | C12: =IF(SUBSTITUTE(TEXT(PS_INCPERC[[#This Row],[PayScaleCode]],10)," ","")=TEXT(PS_INCPERC[[#This Row],[PayScaleCode]],10),0,1) -> 0 | D12: =SUM(PS_INCPERC[[#This Row],[Pay Scale Code Issue]:[Space in Code]]) -> 0 | F12: LP_INN | G12: 2026/27 | H12: 5
A13: =IF(COUNTIF('19_PayScales'!N:N,F13)>0,0,1) -> 0 | B13: =COUNTBLANK(PS_INCPERC[[#This Row],[PayScaleCode]:[IncreasePercentage]]) -> 0 | C13: =IF(SUBSTITUTE(TEXT(PS_INCPERC[[#This Row],[PayScaleCode]],10)," ","")=TEXT(PS_INCPERC[[#This Row],[PayScaleCode]],10),0,1) -> 0 | D13: =SUM(PS_INCPERC[[#This Row],[Pay Scale Code Issue]:[Space in Code]]) -> 0 | F13: UQ_INN | G13: 2026/27 | H13: 5
A14: =IF(COUNTIF('19_PayScales'!N:N,F14)>0,0,1) -> 0 | B14: =COUNTBLANK(PS_INCPERC[[#This Row],[PayScaleCode]:[IncreasePercentage]]) -> 0 | C14: =IF(SUBSTITUTE(TEXT(PS_INCPERC[[#This Row],[PayScaleCode]],10)," ","")=TEXT(PS_INCPERC[[#This Row],[PayScaleCode]],10),0,1) -> 0 | D14: =SUM(PS_INCPERC[[#This Row],[Pay Scale Code Issue]:[Space in Code]]) -> 0 | F14: LS_INN | G14: 2026/27 | H14: 5
... A20: =IF(COUNTIF('19_PayScales'!N:N,F20)>0,0,1) -> 0 | B20: =COUNTBLANK(PS_INCPERC[[#This Row],[PayScaleCode]:[IncreasePercentage]]) -> 0 | C20: =IF(SUBSTITUTE(TEXT(PS_INCPERC[[#This Row],[PayScaleCode]],10)," ","")=TEXT(PS_INCPERC[[#This Row],[PayScaleCode]],10),0,1) -> 0 | D20: =SUM(PS_INCPERC[[#This Row],[Pay Scale Code Issue]:[Space in Code]]) -> 0 | F20: NJC_OUT | G20: 2025/26 | H20: 5

Sheet 20_PayScalePoints
A1: Pay Scale String | B1: Scale Point Issue | C1: Pay Scale String Duplicates | D1: Duplicate Scale Check | E1: Rate Date From Issue | F1: Dates From/To Issue | G1: Date Format Issue | H1: TRUE /FALSE Typo | I1: Code Length | J1: Title Length | K1: Blank in column | L1: Space in Code | M1: Will Import if 0 | N1: London Weighting | O1: ScenarioCode | P1: PayScaleCode | Q1: PayScaleTitle | R1: PayScalePointCode | S1: PayScalePointTitle | T1: ScalePointNumber | U1: Hourly | V1: PayScalePointEnabled | W1: RateDateFrom | X1: RateDateTo | Y1: PayScaleRate
A2: =PSPOINTS[[#This Row],[PayScaleCode]]&PSPOINTS[[#This Row],[RateDateFrom]] -> MAIN_EW45901 | B2: =IF(A2=A1,SUM(T2-T1)-1,T2-1) -> 0 | C2: =PSPOINTS[[#This Row],[PayScaleCode]]&PSPOINTS[[#This Row],[PayScalePointCode]]&PSPOINTS[[#This Row],[RateDateFrom]] -> MAIN_EWM145901 | D2: =COUNTIF(PSPOINTS[Pay Scale String Duplicates],PSPOINTS[[#This Row],[Pay Scale String Duplicates]])-1 -> 0 | E2: =IF((MONTH(_xlfn.XLOOKUP(PSPOINTS[[#This Row],[PayScaleCode]],'19_PayScales'!N:N,'19_PayScales'!R:R)))=MONTH(PSPOINTS[[#This Row],[RateDateFrom]]),0,1) -> 0 | F2: =IF(ISBLANK(PSPOINTS[[#This Row],[RateDateTo]]),0,IF(PSPOINTS[[#This Row],[RateDateFrom]]<PSPOINTS[[#This Row],[RateDateTo]],0,1)) -> 0 | G2: {=IF(CELL("format",PSPOINTS[[#This Row],[RateDateFrom]])="D1",0,1)+IF(CELL("format",PSPOINTS[[#This Row],[RateDateTo]])="D1",0,1)} -> 0 | H2: =IF(OR(PSPOINTS[[#This Row],[Hourly]]=TRUE,PSPOINTS[[#This Row],[Hourly]]=FALSE),IF(OR(PSPOINTS[[#This Row],[PayScalePointEnabled]]=TRUE,PSPOINTS[[#This Row],[PayScalePointEnabled]]=FALSE),0,1),1) -> 0 | I2: =IF(LEN(PSPOINTS[[#This Row],[PayScalePointCode]])<100,0,1) -> 0 | J2: =IF(LEN(PSPOINTS[[#This Row],[PayScalePointTitle]])<100,0,1) -> 0 | K2: =(COUNTBLANK(PSPOINTS[[#This Row],[PayScalePointCode]:[RateDateFrom]])+COUNTBLANK(PSPOINTS[[#This Row],[PayScaleRate]])) -> 0 | L2: =IF(SUBSTITUTE(TEXT(PSPOINTS[[#This Row],[PayScaleCode]],10)," ","")=TEXT(PSPOINTS[[#This Row],[PayScaleCode]],10),0,1)+IF(SUBSTITUTE(TEXT(PSPOINTS[[#This Row],[PayScalePointCode]],10)," ","")=TEXT(PSPOINTS[[#This Row],[PayScalePointCode]],10),0,1) -> 0 | M2: =SUM(PSPOINTS[[#This Row],[Scale Point Issue]:[Space in Code]]) -> 0 | N2: England & Wales | P2: MAIN_EW | Q2: =_xlfn.XLOOKUP(PSPOINTS[[#This Row],[PayScaleCode]],'19_PayScales'!N:N,'19_PayScales'!O:O) -> Teachers Main EW | R2: M1 | S2: M1 | T2: 1 | U2: FALSE | V2: TRUE | W2: 45901 | Y2: 32916
A3: =PSPOINTS[[#This Row],[PayScaleCode]]&PSPOINTS[[#This Row],[RateDateFrom]] -> MAIN_EW45901 | B3: =IF(A3=A2,SUM(T3-T2)-1,T3-1) -> 0 | C3: =PSPOINTS[[#This Row],[PayScaleCode]]&PSPOINTS[[#This Row],[PayScalePointCode]]&PSPOINTS[[#This Row],[RateDateFrom]] -> MAIN_EWM245901 | D3: =COUNTIF(PSPOINTS[Pay Scale String Duplicates],PSPOINTS[[#This Row],[Pay Scale String Duplicates]])-1 -> 0 | E3: =IF((MONTH(_xlfn.XLOOKUP(PSPOINTS[[#This Row],[PayScaleCode]],'19_PayScales'!N:N,'19_PayScales'!R:R)))=MONTH(PSPOINTS[[#This Row],[RateDateFrom]]),0,1) -> 0 | F3: =IF(ISBLANK(PSPOINTS[[#This Row],[RateDateTo]]),0,IF(PSPOINTS[[#This Row],[RateDateFrom]]<PSPOINTS[[#This Row],[RateDateTo]],0,1)) -> 0 | G3: {=IF(CELL("format",PSPOINTS[[#This Row],[RateDateFrom]])="D1",0,1)+IF(CELL("format",PSPOINTS[[#This Row],[RateDateTo]])="D1",0,1)} -> 0 | H3: =IF(OR(PSPOINTS[[#This Row],[Hourly]]=TRUE,PSPOINTS[[#This Row],[Hourly]]=FALSE),IF(OR(PSPOINTS[[#This Row],[PayScalePointEnabled]]=TRUE,PSPOINTS[[#This Row],[PayScalePointEnabled]]=FALSE),0,1),1) -> 0 | I3: =IF(LEN(PSPOINTS[[#This Row],[PayScalePointCode]])<100,0,1) -> 0 | J3: =IF(LEN(PSPOINTS[[#This Row],[PayScalePointTitle]])<100,0,1) -> 0 | K3: =(COUNTBLANK(PSPOINTS[[#This Row],[PayScalePointCode]:[RateDateFrom]])+COUNTBLANK(PSPOINTS[[#This Row],[PayScaleRate]])) -> 0 | L3: =IF(SUBSTITUTE(TEXT(PSPOINTS[[#This Row],[PayScaleCode]],10)," ","")=TEXT(PSPOINTS[[#This Row],[PayScaleCode]],10),0,1)+IF(SUBSTITUTE(TEXT(PSPOINTS[[#This Row],[PayScalePointCode]],10)," ","")=TEXT(PSPOINTS[[#This Row],[PayScalePointCode]],10),0,1) -> 0 | M3: =SUM(PSPOINTS[[#This Row],[Scale Point Issue]:[Space in Code]]) -> 0 | N3: England & Wales | P3: MAIN_EW | Q3: =_xlfn.XLOOKUP(PSPOINTS[[#This Row],[PayScaleCode]],'19_PayScales'!N:N,'19_PayScales'!O:O) -> Teachers Main EW | R3: M2 | S3: M2 | T3: 2 | U3: FALSE | V3: TRUE | W3: 45901 | Y3: 34823
A4: =PSPOINTS[[#This Row],[PayScaleCode]]&PSPOINTS[[#This Row],[RateDateFrom]] -> MAIN_EW45901 | B4: =IF(A4=A3,SUM(T4-T3)-1,T4-1) -> 0 | C4: =PSPOINTS[[#This Row],[PayScaleCode]]&PSPOINTS[[#This Row],[PayScalePointCode]]&PSPOINTS[[#This Row],[RateDateFrom]] -> MAIN_EWM345901 | D4: =COUNTIF(PSPOINTS[Pay Scale String Duplicates],PSPOINTS[[#This Row],[Pay Scale String Duplicates]])-1 -> 0 | E4: =IF((MONTH(_xlfn.XLOOKUP(PSPOINTS[[#This Row],[PayScaleCode]],'19_PayScales'!N:N,'19_PayScales'!R:R)))=MONTH(PSPOINTS[[#This Row],[RateDateFrom]]),0,1) -> 0 | F4: =IF(ISBLANK(PSPOINTS[[#This Row],[RateDateTo]]),0,IF(PSPOINTS[[#This Row],[RateDateFrom]]<PSPOINTS[[#This Row],[RateDateTo]],0,1)) -> 0 | G4: {=IF(CELL("format",PSPOINTS[[#This Row],[RateDateFrom]])="D1",0,1)+IF(CELL("format",PSPOINTS[[#This Row],[RateDateTo]])="D1",0,1)} -> 0 | H4: =IF(OR(PSPOINTS[[#This Row],[Hourly]]=TRUE,PSPOINTS[[#This Row],[Hourly]]=FALSE),IF(OR(PSPOINTS[[#This Row],[PayScalePointEnabled]]=TRUE,PSPOINTS[[#This Row],[PayScalePointEnabled]]=FALSE),0,1),1) -> 0 | I4: =IF(LEN(PSPOINTS[[#This Row],[PayScalePointCode]])<100,0,1) -> 0 | J4: =IF(LEN(PSPOINTS[[#This Row],[PayScalePointTitle]])<100,0,1) -> 0 | K4: =(COUNTBLANK(PSPOINTS[[#This Row],[PayScalePointCode]:[RateDateFrom]])+COUNTBLANK(PSPOINTS[[#This Row],[PayScaleRate]])) -> 0 | L4: =IF(SUBSTITUTE(TEXT(PSPOINTS[[#This Row],[PayScaleCode]],10)," ","")=TEXT(PSPOINTS[[#This Row],[PayScaleCode]],10),0,1)+IF(SUBSTITUTE(TEXT(PSPOINTS[[#This Row],[PayScalePointCode]],10)," ","")=TEXT(PSPOINTS[[#This Row],[PayScalePointCode]],10),0,1) -> 0 | M4: =SUM(PSPOINTS[[#This Row],[Scale Point Issue]:[Space in Code]]) -> 0 | N4: England & Wales | P4: MAIN_EW | Q4: =_xlfn.XLOOKUP(PSPOINTS[[#This Row],[PayScaleCode]],'19_PayScales'!N:N,'19_PayScales'!O:O) -> Teachers Main EW | R4: M3 | S4: M3 | T4: 3 | U4: FALSE | V4: TRUE | W4: 45901 | Y4: 37101
A5: =PSPOINTS[[#This Row],[PayScaleCode]]&PSPOINTS[[#This Row],[RateDateFrom]] -> MAIN_EW45901 | B5: =IF(A5=A4,SUM(T5-T4)-1,T5-1) -> 0 | C5: =PSPOINTS[[#This Row],[PayScaleCode]]&PSPOINTS[[#This Row],[PayScalePointCode]]&PSPOINTS[[#This Row],[RateDateFrom]] -> MAIN_EWM445901 | D5: =COUNTIF(PSPOINTS[Pay Scale String Duplicates],PSPOINTS[[#This Row],[Pay Scale String Duplicates]])-1 -> 0 | E5: =IF((MONTH(_xlfn.XLOOKUP(PSPOINTS[[#This Row],[PayScaleCode]],'19_PayScales'!N:N,'19_PayScales'!R:R)))=MONTH(PSPOINTS[[#This Row],[RateDateFrom]]),0,1) -> 0 | F5: =IF(ISBLANK(PSPOINTS[[#This Row],[RateDateTo]]),0,IF(PSPOINTS[[#This Row],[RateDateFrom]]<PSPOINTS[[#This Row],[RateDateTo]],0,1)) -> 0 | G5: {=IF(CELL("format",PSPOINTS[[#This Row],[RateDateFrom]])="D1",0,1)+IF(CELL("format",PSPOINTS[[#This Row],[RateDateTo]])="D1",0,1)} -> 0 | H5: =IF(OR(PSPOINTS[[#This Row],[Hourly]]=TRUE,PSPOINTS[[#This Row],[Hourly]]=FALSE),IF(OR(PSPOINTS[[#This Row],[PayScalePointEnabled]]=TRUE,PSPOINTS[[#This Row],[PayScalePointEnabled]]=FALSE),0,1),1) -> 0 | I5: =IF(LEN(PSPOINTS[[#This Row],[PayScalePointCode]])<100,0,1) -> 0 | J5: =IF(LEN(PSPOINTS[[#This Row],[PayScalePointTitle]])<100,0,1) -> 0 | K5: =(COUNTBLANK(PSPOINTS[[#This Row],[PayScalePointCode]:[RateDateFrom]])+COUNTBLANK(PSPOINTS[[#This Row],[PayScaleRate]])) -> 0 | L5: =IF(SUBSTITUTE(TEXT(PSPOINTS[[#This Row],[PayScaleCode]],10)," ","")=TEXT(PSPOINTS[[#This Row],[PayScaleCode]],10),0,1)+IF(SUBSTITUTE(TEXT(PSPOINTS[[#This Row],[PayScalePointCode]],10)," ","")=TEXT(PSPOINTS[[#This Row],[PayScalePointCode]],10),0,1) -> 0 | M5: =SUM(PSPOINTS[[#This Row],[Scale Point Issue]:[Space in Code]]) -> 0 | N5: England & Wales | P5: MAIN_EW | Q5: =_xlfn.XLOOKUP(PSPOINTS[[#This Row],[PayScaleCode]],'19_PayScales'!N:N,'19_PayScales'!O:O) -> Teachers Main EW | R5: M4 | S5: M4 | T5: 4 | U5: FALSE | V5: TRUE | W5: 45901 | Y5: 39556
A6: =PSPOINTS[[#This Row],[PayScaleCode]]&PSPOINTS[[#This Row],[RateDateFrom]] -> MAIN_EW45901 | B6: =IF(A6=A5,SUM(T6-T5)-1,T6-1) -> 0 | C6: =PSPOINTS[[#This Row],[PayScaleCode]]&PSPOINTS[[#This Row],[PayScalePointCode]]&PSPOINTS[[#This Row],[RateDateFrom]] -> MAIN_EWM545901 | D6: =COUNTIF(PSPOINTS[Pay Scale String Duplicates],PSPOINTS[[#This Row],[Pay Scale String Duplicates]])-1 -> 0 | E6: =IF((MONTH(_xlfn.XLOOKUP(PSPOINTS[[#This Row],[PayScaleCode]],'19_PayScales'!N:N,'19_PayScales'!R:R)))=MONTH(PSPOINTS[[#This Row],[RateDateFrom]]),0,1) -> 0 | F6: =IF(ISBLANK(PSPOINTS[[#This Row],[RateDateTo]]),0,IF(PSPOINTS[[#This Row],[RateDateFrom]]<PSPOINTS[[#This Row],[RateDateTo]],0,1)) -> 0 | G6: {=IF(CELL("format",PSPOINTS[[#This Row],[RateDateFrom]])="D1",0,1)+IF(CELL("format",PSPOINTS[[#This Row],[RateDateTo]])="D1",0,1)} -> 0 | H6: =IF(OR(PSPOINTS[[#This Row],[Hourly]]=TRUE,PSPOINTS[[#This Row],[Hourly]]=FALSE),IF(OR(PSPOINTS[[#This Row],[PayScalePointEnabled]]=TRUE,PSPOINTS[[#This Row],[PayScalePointEnabled]]=FALSE),0,1),1) -> 0 | I6: =IF(LEN(PSPOINTS[[#This Row],[PayScalePointCode]])<100,0,1) -> 0 | J6: =IF(LEN(PSPOINTS[[#This Row],[PayScalePointTitle]])<100,0,1) -> 0 | K6: =(COUNTBLANK(PSPOINTS[[#This Row],[PayScalePointCode]:[RateDateFrom]])+COUNTBLANK(PSPOINTS[[#This Row],[PayScaleRate]])) -> 0 | L6: =IF(SUBSTITUTE(TEXT(PSPOINTS[[#This Row],[PayScaleCode]],10)," ","")=TEXT(PSPOINTS[[#This Row],[PayScaleCode]],10),0,1)+IF(SUBSTITUTE(TEXT(PSPOINTS[[#This Row],[PayScalePointCode]],10)," ","")=TEXT(PSPOINTS[[#This Row],[PayScalePointCode]],10),0,1) -> 0 | M6: =SUM(PSPOINTS[[#This Row],[Scale Point Issue]:[Space in Code]]) -> 0 | N6: England & Wales | P6: MAIN_EW | Q6: =_xlfn.XLOOKUP(PSPOINTS[[#This Row],[PayScaleCode]],'19_PayScales'!N:N,'19_PayScales'!O:O) -> Teachers Main EW | R6: M5 | S6: M5 | T6: 5 | U6: FALSE | V6: TRUE | W6: 45901 | Y6: 42057
A7: =PSPOINTS[[#This Row],[PayScaleCode]]&PSPOINTS[[#This Row],[RateDateFrom]] -> MAIN_EW45901 | B7: =IF(A7=A6,SUM(T7-T6)-1,T7-1) -> 0 | C7: =PSPOINTS[[#This Row],[PayScaleCode]]&PSPOINTS[[#This Row],[PayScalePointCode]]&PSPOINTS[[#This Row],[RateDateFrom]] -> MAIN_EWM645901 | D7: =COUNTIF(PSPOINTS[Pay Scale String Duplicates],PSPOINTS[[#This Row],[Pay Scale String Duplicates]])-1 -> 0 | E7: =IF((MONTH(_xlfn.XLOOKUP(PSPOINTS[[#This Row],[PayScaleCode]],'19_PayScales'!N:N,'19_PayScales'!R:R)))=MONTH(PSPOINTS[[#This Row],[RateDateFrom]]),0,1) -> 0 | F7: =IF(ISBLANK(PSPOINTS[[#This Row],[RateDateTo]]),0,IF(PSPOINTS[[#This Row],[RateDateFrom]]<PSPOINTS[[#This Row],[RateDateTo]],0,1)) -> 0 | G7: {=IF(CELL("format",PSPOINTS[[#This Row],[RateDateFrom]])="D1",0,1)+IF(CELL("format",PSPOINTS[[#This Row],[RateDateTo]])="D1",0,1)} -> 0 | H7: =IF(OR(PSPOINTS[[#This Row],[Hourly]]=TRUE,PSPOINTS[[#This Row],[Hourly]]=FALSE),IF(OR(PSPOINTS[[#This Row],[PayScalePointEnabled]]=TRUE,PSPOINTS[[#This Row],[PayScalePointEnabled]]=FALSE),0,1),1) -> 0 | I7: =IF(LEN(PSPOINTS[[#This Row],[PayScalePointCode]])<100,0,1) -> 0 | J7: =IF(LEN(PSPOINTS[[#This Row],[PayScalePointTitle]])<100,0,1) -> 0 | K7: =(COUNTBLANK(PSPOINTS[[#This Row],[PayScalePointCode]:[RateDateFrom]])+COUNTBLANK(PSPOINTS[[#This Row],[PayScaleRate]])) -> 0 | L7: =IF(SUBSTITUTE(TEXT(PSPOINTS[[#This Row],[PayScaleCode]],10)," ","")=TEXT(PSPOINTS[[#This Row],[PayScaleCode]],10),0,1)+IF(SUBSTITUTE(TEXT(PSPOINTS[[#This Row],[PayScalePointCode]],10)," ","")=TEXT(PSPOINTS[[#This Row],[PayScalePointCode]],10),0,1) -> 0 | M7: =SUM(PSPOINTS[[#This Row],[Scale Point Issue]:[Space in Code]]) -> 0 | N7: England & Wales | P7: MAIN_EW | Q7: =_xlfn.XLOOKUP(PSPOINTS[[#This Row],[PayScaleCode]],'19_PayScales'!N:N,'19_PayScales'!O:O) -> Teachers Main EW | R7: M6 | S7: M6 | T7: 6 | U7: FALSE | V7: TRUE | W7: 45901 | Y7: 45352
A8: =PSPOINTS[[#This Row],[PayScaleCode]]&PSPOINTS[[#This Row],[RateDateFrom]] -> MAIN_EW45901 | B8: =IF(A8=A7,SUM(T8-T7)-1,T8-1) -> 0 | C8: =PSPOINTS[[#This Row],[PayScaleCode]]&PSPOINTS[[#This Row],[PayScalePointCode]]&PSPOINTS[[#This Row],[RateDateFrom]] -> MAIN_EWU1Y145901 | D8: =COUNTIF(PSPOINTS[Pay Scale String Duplicates],PSPOINTS[[#This Row],[Pay Scale String Duplicates]])-1 -> 0 | E8: =IF((MONTH(_xlfn.XLOOKUP(PSPOINTS[[#This Row],[PayScaleCode]],'19_PayScales'!N:N,'19_PayScales'!R:R)))=MONTH(PSPOINTS[[#This Row],[RateDateFrom]]),0,1) -> 0 | F8: =IF(ISBLANK(PSPOINTS[[#This Row],[RateDateTo]]),0,IF(PSPOINTS[[#This Row],[RateDateFrom]]<PSPOINTS[[#This Row],[RateDateTo]],0,1)) -> 0 | G8: {=IF(CELL("format",PSPOINTS[[#This Row],[RateDateFrom]])="D1",0,1)+IF(CELL("format",PSPOINTS[[#This Row],[RateDateTo]])="D1",0,1)} -> 0 | H8: =IF(OR(PSPOINTS[[#This Row],[Hourly]]=TRUE,PSPOINTS[[#This Row],[Hourly]]=FALSE),IF(OR(PSPOINTS[[#This Row],[PayScalePointEnabled]]=TRUE,PSPOINTS[[#This Row],[PayScalePointEnabled]]=FALSE),0,1),1) -> 0 | I8: =IF(LEN(PSPOINTS[[#This Row],[PayScalePointCode]])<100,0,1) -> 0 | J8: =IF(LEN(PSPOINTS[[#This Row],[PayScalePointTitle]])<100,0,1) -> 0 | K8: =(COUNTBLANK(PSPOINTS[[#This Row],[PayScalePointCode]:[RateDateFrom]])+COUNTBLANK(PSPOINTS[[#This Row],[PayScaleRate]])) -> 0 | L8: =IF(SUBSTITUTE(TEXT(PSPOINTS[[#This Row],[PayScaleCode]],10)," ","")=TEXT(PSPOINTS[[#This Row],[PayScaleCode]],10),0,1)+IF(SUBSTITUTE(TEXT(PSPOINTS[[#This Row],[PayScalePointCode]],10)," ","")=TEXT(PSPOINTS[[#This Row],[PayScalePointCode]],10),0,1) -> 0 | M8: =SUM(PSPOINTS[[#This Row],[Scale Point Issue]:[Space in Code]]) -> 0 | N8: England & Wales | P8: MAIN_EW | Q8: =_xlfn.XLOOKUP(PSPOINTS[[#This Row],[PayScaleCode]],'19_PayScales'!N:N,'19_PayScales'!O:O) -> Teachers Main EW | R8: U1Y1 | S8: U1Y1 | T8: 7 | U8: FALSE | V8: TRUE | W8: 45901 | Y8: 47472
A9: =PSPOINTS[[#This Row],[PayScaleCode]]&PSPOINTS[[#This Row],[RateDateFrom]] -> MAIN_EW45901 | B9: =IF(A9=A8,SUM(T9-T8)-1,T9-1) -> 0 | C9: =PSPOINTS[[#This Row],[PayScaleCode]]&PSPOINTS[[#This Row],[PayScalePointCode]]&PSPOINTS[[#This Row],[RateDateFrom]] -> MAIN_EWU1Y245901 | D9: =COUNTIF(PSPOINTS[Pay Scale String Duplicates],PSPOINTS[[#This Row],[Pay Scale String Duplicates]])-1 -> 0 | E9: =IF((MONTH(_xlfn.XLOOKUP(PSPOINTS[[#This Row],[PayScaleCode]],'19_PayScales'!N:N,'19_PayScales'!R:R)))=MONTH(PSPOINTS[[#This Row],[RateDateFrom]]),0,1) -> 0 | F9: =IF(ISBLANK(PSPOINTS[[#This Row],[RateDateTo]]),0,IF(PSPOINTS[[#This Row],[RateDateFrom]]<PSPOINTS[[#This Row],[RateDateTo]],0,1)) -> 0 | G9: {=IF(CELL("format",PSPOINTS[[#This Row],[RateDateFrom]])="D1",0,1)+IF(CELL("format",PSPOINTS[[#This Row],[RateDateTo]])="D1",0,1)} -> 0 | H9: =IF(OR(PSPOINTS[[#This Row],[Hourly]]=TRUE,PSPOINTS[[#This Row],[Hourly]]=FALSE),IF(OR(PSPOINTS[[#This Row],[PayScalePointEnabled]]=TRUE,PSPOINTS[[#This Row],[PayScalePointEnabled]]=FALSE),0,1),1) -> 0 | I9: =IF(LEN(PSPOINTS[[#This Row],[PayScalePointCode]])<100,0,1) -> 0 | J9: =IF(LEN(PSPOINTS[[#This Row],[PayScalePointTitle]])<100,0,1) -> 0 | K9: =(COUNTBLANK(PSPOINTS[[#This Row],[PayScalePointCode]:[RateDateFrom]])+COUNTBLANK(PSPOINTS[[#This Row],[PayScaleRate]])) -> 0 | L9: =IF(SUBSTITUTE(TEXT(PSPOINTS[[#This Row],[PayScaleCode]],10)," ","")=TEXT(PSPOINTS[[#This Row],[PayScaleCode]],10),0,1)+IF(SUBSTITUTE(TEXT(PSPOINTS[[#This Row],[PayScalePointCode]],10)," ","")=TEXT(PSPOINTS[[#This Row],[PayScalePointCode]],10),0,1) -> 0 | M9: =SUM(PSPOINTS[[#This Row],[Scale Point Issue]:[Space in Code]]) -> 0 | N9: England & Wales | P9: MAIN_EW | Q9: =_xlfn.XLOOKUP(PSPOINTS[[#This Row],[PayScaleCode]],'19_PayScales'!N:N,'19_PayScales'!O:O) -> Teachers Main EW | R9: U1Y2 | S9: U1Y2 | T9: 8 | U9: FALSE | V9: TRUE | W9: 45901 | Y9: 47472
A10: =PSPOINTS[[#This Row],[PayScaleCode]]&PSPOINTS[[#This Row],[RateDateFrom]] -> MAIN_EW45901 | B10: =IF(A10=A9,SUM(T10-T9)-1,T10-1) -> 0 | C10: =PSPOINTS[[#This Row],[PayScaleCode]]&PSPOINTS[[#This Row],[PayScalePointCode]]&PSPOINTS[[#This Row],[RateDateFrom]] -> MAIN_EWU2Y145901 | D10: =COUNTIF(PSPOINTS[Pay Scale String Duplicates],PSPOINTS[[#This Row],[Pay Scale String Duplicates]])-1 -> 0 | E10: =IF((MONTH(_xlfn.XLOOKUP(PSPOINTS[[#This Row],[PayScaleCode]],'19_PayScales'!N:N,'19_PayScales'!R:R)))=MONTH(PSPOINTS[[#This Row],[RateDateFrom]]),0,1) -> 0 | F10: =IF(ISBLANK(PSPOINTS[[#This Row],[RateDateTo]]),0,IF(PSPOINTS[[#This Row],[RateDateFrom]]<PSPOINTS[[#This Row],[RateDateTo]],0,1)) -> 0 | G10: {=IF(CELL("format",PSPOINTS[[#This Row],[RateDateFrom]])="D1",0,1)+IF(CELL("format",PSPOINTS[[#This Row],[RateDateTo]])="D1",0,1)} -> 0 | H10: =IF(OR(PSPOINTS[[#This Row],[Hourly]]=TRUE,PSPOINTS[[#This Row],[Hourly]]=FALSE),IF(OR(PSPOINTS[[#This Row],[PayScalePointEnabled]]=TRUE,PSPOINTS[[#This Row],[PayScalePointEnabled]]=FALSE),0,1),1) -> 0 | I10: =IF(LEN(PSPOINTS[[#This Row],[PayScalePointCode]])<100,0,1) -> 0 | J10: =IF(LEN(PSPOINTS[[#This Row],[PayScalePointTitle]])<100,0,1) -> 0 | K10: =(COUNTBLANK(PSPOINTS[[#This Row],[PayScalePointCode]:[RateDateFrom]])+COUNTBLANK(PSPOINTS[[#This Row],[PayScaleRate]])) -> 0 | L10: =IF(SUBSTITUTE(TEXT(PSPOINTS[[#This Row],[PayScaleCode]],10)," ","")=TEXT(PSPOINTS[[#This Row],[PayScaleCode]],10),0,1)+IF(SUBSTITUTE(TEXT(PSPOINTS[[#This Row],[PayScalePointCode]],10)," ","")=TEXT(PSPOINTS[[#This Row],[PayScalePointCode]],10),0,1) -> 0 | M10: =SUM(PSPOINTS[[#This Row],[Scale Point Issue]:[Space in Code]]) -> 0 | N10: England & Wales | P10: MAIN_EW | Q10: =_xlfn.XLOOKUP(PSPOINTS[[#This Row],[PayScaleCode]],'19_PayScales'!N:N,'19_PayScales'!O:O) -> Teachers Main EW | R10: U2Y1 | S10: U2Y1 | T10: 9 | U10: FALSE | V10: TRUE | W10: 45901 | Y10: 49232
A11: =PSPOINTS[[#This Row],[PayScaleCode]]&PSPOINTS[[#This Row],[RateDateFrom]] -> MAIN_EW45901 | B11: =IF(A11=A10,SUM(T11-T10)-1,T11-1) -> 0 | C11: =PSPOINTS[[#This Row],[PayScaleCode]]&PSPOINTS[[#This Row],[PayScalePointCode]]&PSPOINTS[[#This Row],[RateDateFrom]] -> MAIN_EWU2Y245901 | D11: =COUNTIF(PSPOINTS[Pay Scale String Duplicates],PSPOINTS[[#This Row],[Pay Scale String Duplicates]])-1 -> 0 | E11: =IF((MONTH(_xlfn.XLOOKUP(PSPOINTS[[#This Row],[PayScaleCode]],'19_PayScales'!N:N,'19_PayScales'!R:R)))=MONTH(PSPOINTS[[#This Row],[RateDateFrom]]),0,1) -> 0 | F11: =IF(ISBLANK(PSPOINTS[[#This Row],[RateDateTo]]),0,IF(PSPOINTS[[#This Row],[RateDateFrom]]<PSPOINTS[[#This Row],[RateDateTo]],0,1)) -> 0 | G11: {=IF(CELL("format",PSPOINTS[[#This Row],[RateDateFrom]])="D1",0,1)+IF(CELL("format",PSPOINTS[[#This Row],[RateDateTo]])="D1",0,1)} -> 0 | H11: =IF(OR(PSPOINTS[[#This Row],[Hourly]]=TRUE,PSPOINTS[[#This Row],[Hourly]]=FALSE),IF(OR(PSPOINTS[[#This Row],[PayScalePointEnabled]]=TRUE,PSPOINTS[[#This Row],[PayScalePointEnabled]]=FALSE),0,1),1) -> 0 | I11: =IF(LEN(PSPOINTS[[#This Row],[PayScalePointCode]])<100,0,1) -> 0 | J11: =IF(LEN(PSPOINTS[[#This Row],[PayScalePointTitle]])<100,0,1) -> 0 | K11: =(COUNTBLANK(PSPOINTS[[#This Row],[PayScalePointCode]:[RateDateFrom]])+COUNTBLANK(PSPOINTS[[#This Row],[PayScaleRate]])) -> 0 | L11: =IF(SUBSTITUTE(TEXT(PSPOINTS[[#This Row],[PayScaleCode]],10)," ","")=TEXT(PSPOINTS[[#This Row],[PayScaleCode]],10),0,1)+IF(SUBSTITUTE(TEXT(PSPOINTS[[#This Row],[PayScalePointCode]],10)," ","")=TEXT(PSPOINTS[[#This Row],[PayScalePointCode]],10),0,1) -> 0 | M11: =SUM(PSPOINTS[[#This Row],[Scale Point Issue]:[Space in Code]]) -> 0 | N11: England & Wales | P11: MAIN_EW | Q11: =_xlfn.XLOOKUP(PSPOINTS[[#This Row],[PayScaleCode]],'19_PayScales'!N:N,'19_PayScales'!O:O) -> Teachers Main EW | R11: U2Y2 | S11: U2Y2 | T11: 10 | U11: FALSE | V11: TRUE | W11: 45901 | Y11: 49232
A12: =PSPOINTS[[#This Row],[PayScaleCode]]&PSPOINTS[[#This Row],[RateDateFrom]] -> MAIN_EW45901 | B12: =IF(A12=A11,SUM(T12-T11)-1,T12-1) -> 0 | C12: =PSPOINTS[[#This Row],[PayScaleCode]]&PSPOINTS[[#This Row],[PayScalePointCode]]&PSPOINTS[[#This Row],[RateDateFrom]] -> MAIN_EWU345901 | D12: =COUNTIF(PSPOINTS[Pay Scale String Duplicates],PSPOINTS[[#This Row],[Pay Scale String Duplicates]])-1 -> 0 | E12: =IF((MONTH(_xlfn.XLOOKUP(PSPOINTS[[#This Row],[PayScaleCode]],'19_PayScales'!N:N,'19_PayScales'!R:R)))=MONTH(PSPOINTS[[#This Row],[RateDateFrom]]),0,1) -> 0 | F12: =IF(ISBLANK(PSPOINTS[[#This Row],[RateDateTo]]),0,IF(PSPOINTS[[#This Row],[RateDateFrom]]<PSPOINTS[[#This Row],[RateDateTo]],0,1)) -> 0 | G12: {=IF(CELL("format",PSPOINTS[[#This Row],[RateDateFrom]])="D1",0,1)+IF(CELL("format",PSPOINTS[[#This Row],[RateDateTo]])="D1",0,1)} -> 0 | H12: =IF(OR(PSPOINTS[[#This Row],[Hourly]]=TRUE,PSPOINTS[[#This Row],[Hourly]]=FALSE),IF(OR(PSPOINTS[[#This Row],[PayScalePointEnabled]]=TRUE,PSPOINTS[[#This Row],[PayScalePointEnabled]]=FALSE),0,1),1) -> 0 | I12: =IF(LEN(PSPOINTS[[#This Row],[PayScalePointCode]])<100,0,1) -> 0 | J12: =IF(LEN(PSPOINTS[[#This Row],[PayScalePointTitle]])<100,0,1) -> 0 | K12: =(COUNTBLANK(PSPOINTS[[#This Row],[PayScalePointCode]:[RateDateFrom]])+COUNTBLANK(PSPOINTS[[#This Row],[PayScaleRate]])) -> 0 | L12: =IF(SUBSTITUTE(TEXT(PSPOINTS[[#This Row],[PayScaleCode]],10)," ","")=TEXT(PSPOINTS[[#This Row],[PayScaleCode]],10),0,1)+IF(SUBSTITUTE(TEXT(PSPOINTS[[#This Row],[PayScalePointCode]],10)," ","")=TEXT(PSPOINTS[[#This Row],[PayScalePointCode]],10),0,1) -> 0 | M12: =SUM(PSPOINTS[[#This Row],[Scale Point Issue]:[Space in Code]]) -> 0 | N12: England & Wales | P12: MAIN_EW | Q12: =_xlfn.XLOOKUP(PSPOINTS[[#This Row],[PayScaleCode]],'19_PayScales'!N:N,'19_PayScales'!O:O) -> Teachers Main EW | R12: U3 | S12: U3 | T12: 11 | U12: FALSE | V12: TRUE | W12: 45901 | Y12: 51048
A13: =PSPOINTS[[#This Row],[PayScaleCode]]&PSPOINTS[[#This Row],[RateDateFrom]] -> LP_EW45901 | B13: =IF(A13=A12,SUM(T13-T12)-1,T13-1) -> 0 | C13: =PSPOINTS[[#This Row],[PayScaleCode]]&PSPOINTS[[#This Row],[PayScalePointCode]]&PSPOINTS[[#This Row],[RateDateFrom]] -> LP_EWLP0145901 | D13: =COUNTIF(PSPOINTS[Pay Scale String Duplicates],PSPOINTS[[#This Row],[Pay Scale String Duplicates]])-1 -> 0 | E13: =IF((MONTH(_xlfn.XLOOKUP(PSPOINTS[[#This Row],[PayScaleCode]],'19_PayScales'!N:N,'19_PayScales'!R:R)))=MONTH(PSPOINTS[[#This Row],[RateDateFrom]]),0,1) -> 0 | F13: =IF(ISBLANK(PSPOINTS[[#This Row],[RateDateTo]]),0,IF(PSPOINTS[[#This Row],[RateDateFrom]]<PSPOINTS[[#This Row],[RateDateTo]],0,1)) -> 0 | G13: {=IF(CELL("format",PSPOINTS[[#This Row],[RateDateFrom]])="D1",0,1)+IF(CELL("format",PSPOINTS[[#This Row],[RateDateTo]])="D1",0,1)} -> 0 | H13: =IF(OR(PSPOINTS[[#This Row],[Hourly]]=TRUE,PSPOINTS[[#This Row],[Hourly]]=FALSE),IF(OR(PSPOINTS[[#This Row],[PayScalePointEnabled]]=TRUE,PSPOINTS[[#This Row],[PayScalePointEnabled]]=FALSE),0,1),1) -> 0 | I13: =IF(LEN(PSPOINTS[[#This Row],[PayScalePointCode]])<100,0,1) -> 0 | J13: =IF(LEN(PSPOINTS[[#This Row],[PayScalePointTitle]])<100,0,1) -> 0 | K13: =(COUNTBLANK(PSPOINTS[[#This Row],[PayScalePointCode]:[RateDateFrom]])+COUNTBLANK(PSPOINTS[[#This Row],[PayScaleRate]])) -> 0 | L13: =IF(SUBSTITUTE(TEXT(PSPOINTS[[#This Row],[PayScaleCode]],10)," ","")=TEXT(PSPOINTS[[#This Row],[PayScaleCode]],10),0,1)+IF(SUBSTITUTE(TEXT(PSPOINTS[[#This Row],[PayScalePointCode]],10)," ","")=TEXT(PSPOINTS[[#This Row],[PayScalePointCode]],10),0,1) -> 0 | M13: =SUM(PSPOINTS[[#This Row],[Scale Point Issue]:[Space in Code]]) -> 0 | N13: England & Wales | P13: LP_EW | Q13: =_xlfn.XLOOKUP(PSPOINTS[[#This Row],[PayScaleCode]],'19_PayScales'!N:N,'19_PayScales'!O:O) -> Lead Practitioner EW | R13: LP01 | S13: LP01 | T13: 1 | U13: FALSE | V13: TRUE | W13: 45901 | Y13: 52026
... A79: =PSPOINTS[[#This Row],[PayScaleCode]]&PSPOINTS[[#This Row],[RateDateFrom]] -> LS_EW45901 | B79: =IF(A79=A78,SUM(T79-T78)-1,T79-1) -> 0 | C79: =PSPOINTS[[#This Row],[PayScaleCode]]&PSPOINTS[[#This Row],[PayScalePointCode]]&PSPOINTS[[#This Row],[RateDateFrom]] -> LS_EWL4345901 | D79: =COUNTIF(PSPOINTS[Pay Scale String Duplicates],PSPOINTS[[#This Row],[Pay Scale String Duplicates]])-1 -> 0 | E79: =IF((MONTH(_xlfn.XLOOKUP(PSPOINTS[[#This Row],[PayScaleCode]],'19_PayScales'!N:N,'19_PayScales'!R:R)))=MONTH(PSPOINTS[[#This Row],[RateDateFrom]]),0,1) -> 0 | F79: =IF(ISBLANK(PSPOINTS[[#This Row],[RateDateTo]]),0,IF(PSPOINTS[[#This Row],[RateDateFrom]]<PSPOINTS[[#This Row],[RateDateTo]],0,1)) -> 0 | G79: {=IF(CELL("format",PSPOINTS[[#This Row],[RateDateFrom]])="D1",0,1)+IF(CELL("format",PSPOINTS[[#This Row],[RateDateTo]])="D1",0,1)} -> 0 | H79: =IF(OR(PSPOINTS[[#This Row],[Hourly]]=TRUE,PSPOINTS[[#This Row],[Hourly]]=FALSE),IF(OR(PSPOINTS[[#This Row],[PayScalePointEnabled]]=TRUE,PSPOINTS[[#This Row],[PayScalePointEnabled]]=FALSE),0,1),1) -> 0 | I79: =IF(LEN(PSPOINTS[[#This Row],[PayScalePointCode]])<100,0,1) -> 0 | J79: =IF(LEN(PSPOINTS[[#This Row],[PayScalePointTitle]])<100,0,1) -> 0 | K79: =(COUNTBLANK(PSPOINTS[[#This Row],[PayScalePointCode]:[RateDateFrom]])+COUNTBLANK(PSPOINTS[[#This Row],[PayScaleRate]])) -> 0 | L79: =IF(SUBSTITUTE(TEXT(PSPOINTS[[#This Row],[PayScaleCode]],10)," ","")=TEXT(PSPOINTS[[#This Row],[PayScaleCode]],10),0,1)+IF(SUBSTITUTE(TEXT(PSPOINTS[[#This Row],[PayScalePointCode]],10)," ","")=TEXT(PSPOINTS[[#This Row],[PayScalePointCode]],10),0,1) -> 0 | M79: =SUM(PSPOINTS[[#This Row],[Scale Point Issue]:[Space in Code]]) -> 0 | N79: England & Wales | P79: LS_EW | Q79: =_xlfn.XLOOKUP(PSPOINTS[[#This Row],[PayScaleCode]],'19_PayScales'!N:N,'19_PayScales'!O:O) -> Leadership Group EW | R79: L43 | S79: L43 | T79: 43 | U79: FALSE | V79: TRUE | W79: 45901 | Y79: 143796
A80: =PSPOINTS[[#This Row],[PayScaleCode]]&PSPOINTS[[#This Row],[RateDateFrom]] -> NJC_EW45748 | B80: =IF(A80=A79,SUM(T80-T79)-1,T80-1) -> 0 | C80: =PSPOINTS[[#This Row],[PayScaleCode]]&PSPOINTS[[#This Row],[PayScalePointCode]]&PSPOINTS[[#This Row],[RateDateFrom]] -> NJC_EW145748 | D80: =COUNTIF(PSPOINTS[Pay Scale String Duplicates],PSPOINTS[[#This Row],[Pay Scale String Duplicates]])-1 -> 0 | E80: =IF((MONTH(_xlfn.XLOOKUP(PSPOINTS[[#This Row],[PayScaleCode]],'19_PayScales'!N:N,'19_PayScales'!R:R)))=MONTH(PSPOINTS[[#This Row],[RateDateFrom]]),0,1) -> 0 | F80: =IF(ISBLANK(PSPOINTS[[#This Row],[RateDateTo]]),0,IF(PSPOINTS[[#This Row],[RateDateFrom]]<PSPOINTS[[#This Row],[RateDateTo]],0,1)) -> 0 | G80: {=IF(CELL("format",PSPOINTS[[#This Row],[RateDateFrom]])="D1",0,1)+IF(CELL("format",PSPOINTS[[#This Row],[RateDateTo]])="D1",0,1)} -> 0 | H80: =IF(OR(PSPOINTS[[#This Row],[Hourly]]=TRUE,PSPOINTS[[#This Row],[Hourly]]=FALSE),IF(OR(PSPOINTS[[#This Row],[PayScalePointEnabled]]=TRUE,PSPOINTS[[#This Row],[PayScalePointEnabled]]=FALSE),0,1),1) -> 0 | I80: =IF(LEN(PSPOINTS[[#This Row],[PayScalePointCode]])<100,0,1) -> 0 | J80: =IF(LEN(PSPOINTS[[#This Row],[PayScalePointTitle]])<100,0,1) -> 0 | K80: =(COUNTBLANK(PSPOINTS[[#This Row],[PayScalePointCode]:[RateDateFrom]])+COUNTBLANK(PSPOINTS[[#This Row],[PayScaleRate]])) -> 0 | L80: =IF(SUBSTITUTE(TEXT(PSPOINTS[[#This Row],[PayScaleCode]],10)," ","")=TEXT(PSPOINTS[[#This Row],[PayScaleCode]],10),0,1)+IF(SUBSTITUTE(TEXT(PSPOINTS[[#This Row],[PayScalePointCode]],10)," ","")=TEXT(PSPOINTS[[#This Row],[PayScalePointCode]],10),0,1) -> 0 | M80: =SUM(PSPOINTS[[#This Row],[Scale Point Issue]:[Space in Code]]) -> 0 | N80: England & Wales | P80: NJC_EW | Q80: =_xlfn.XLOOKUP(PSPOINTS[[#This Row],[PayScaleCode]],'19_PayScales'!N:N,'19_PayScales'!O:O) -> NJC EW | R80: 1 | S80: 1 | T80: 1 | U80: FALSE | V80: FALSE | W80: 45748 | Y80: 0
A81: =PSPOINTS[[#This Row],[PayScaleCode]]&PSPOINTS[[#This Row],[RateDateFrom]] -> NJC_EW45748 | B81: =IF(A81=A80,SUM(T81-T80)-1,T81-1) -> 0 | C81: =PSPOINTS[[#This Row],[PayScaleCode]]&PSPOINTS[[#This Row],[PayScalePointCode]]&PSPOINTS[[#This Row],[RateDateFrom]] -> NJC_EW245748 | D81: =COUNTIF(PSPOINTS[Pay Scale String Duplicates],PSPOINTS[[#This Row],[Pay Scale String Duplicates]])-1 -> 0 | E81: =IF((MONTH(_xlfn.XLOOKUP(PSPOINTS[[#This Row],[PayScaleCode]],'19_PayScales'!N:N,'19_PayScales'!R:R)))=MONTH(PSPOINTS[[#This Row],[RateDateFrom]]),0,1) -> 0 | F81: =IF(ISBLANK(PSPOINTS[[#This Row],[RateDateTo]]),0,IF(PSPOINTS[[#This Row],[RateDateFrom]]<PSPOINTS[[#This Row],[RateDateTo]],0,1)) -> 0 | G81: {=IF(CELL("format",PSPOINTS[[#This Row],[RateDateFrom]])="D1",0,1)+IF(CELL("format",PSPOINTS[[#This Row],[RateDateTo]])="D1",0,1)} -> 0 | H81: =IF(OR(PSPOINTS[[#This Row],[Hourly]]=TRUE,PSPOINTS[[#This Row],[Hourly]]=FALSE),IF(OR(PSPOINTS[[#This Row],[PayScalePointEnabled]]=TRUE,PSPOINTS[[#This Row],[PayScalePointEnabled]]=FALSE),0,1),1) -> 0 | I81: =IF(LEN(PSPOINTS[[#This Row],[PayScalePointCode]])<100,0,1) -> 0 | J81: =IF(LEN(PSPOINTS[[#This Row],[PayScalePointTitle]])<100,0,1) -> 0 | K81: =(COUNTBLANK(PSPOINTS[[#This Row],[PayScalePointCode]:[RateDateFrom]])+COUNTBLANK(PSPOINTS[[#This Row],[PayScaleRate]])) -> 0 | L81: =IF(SUBSTITUTE(TEXT(PSPOINTS[[#This Row],[PayScaleCode]],10)," ","")=TEXT(PSPOINTS[[#This Row],[PayScaleCode]],10),0,1)+IF(SUBSTITUTE(TEXT(PSPOINTS[[#This Row],[PayScalePointCode]],10)," ","")=TEXT(PSPOINTS[[#This Row],[PayScalePointCode]],10),0,1) -> 0 | M81: =SUM(PSPOINTS[[#This Row],[Scale Point Issue]:[Space in Code]]) -> 0 | N81: England & Wales | P81: NJC_EW | Q81: =_xlfn.XLOOKUP(PSPOINTS[[#This Row],[PayScaleCode]],'19_PayScales'!N:N,'19_PayScales'!O:O) -> NJC EW | R81: 2 | S81: 2 | T81: 2 | U81: FALSE | V81: TRUE | W81: 45748 | Y81: 24413
A82: =PSPOINTS[[#This Row],[PayScaleCode]]&PSPOINTS[[#This Row],[RateDateFrom]] -> NJC_EW45748 | B82: =IF(A82=A81,SUM(T82-T81)-1,T82-1) -> 0 | C82: =PSPOINTS[[#This Row],[PayScaleCode]]&PSPOINTS[[#This Row],[PayScalePointCode]]&PSPOINTS[[#This Row],[RateDateFrom]] -> NJC_EW345748 | D82: =COUNTIF(PSPOINTS[Pay Scale String Duplicates],PSPOINTS[[#This Row],[Pay Scale String Duplicates]])-1 -> 0 | E82: =IF((MONTH(_xlfn.XLOOKUP(PSPOINTS[[#This Row],[PayScaleCode]],'19_PayScales'!N:N,'19_PayScales'!R:R)))=MONTH(PSPOINTS[[#This Row],[RateDateFrom]]),0,1) -> 0 | F82: =IF(ISBLANK(PSPOINTS[[#This Row],[RateDateTo]]),0,IF(PSPOINTS[[#This Row],[RateDateFrom]]<PSPOINTS[[#This Row],[RateDateTo]],0,1)) -> 0 | G82: {=IF(CELL("format",PSPOINTS[[#This Row],[RateDateFrom]])="D1",0,1)+IF(CELL("format",PSPOINTS[[#This Row],[RateDateTo]])="D1",0,1)} -> 0 | H82: =IF(OR(PSPOINTS[[#This Row],[Hourly]]=TRUE,PSPOINTS[[#This Row],[Hourly]]=FALSE),IF(OR(PSPOINTS[[#This Row],[PayScalePointEnabled]]=TRUE,PSPOINTS[[#This Row],[PayScalePointEnabled]]=FALSE),0,1),1) -> 0 | I82: =IF(LEN(PSPOINTS[[#This Row],[PayScalePointCode]])<100,0,1) -> 0 | J82: =IF(LEN(PSPOINTS[[#This Row],[PayScalePointTitle]])<100,0,1) -> 0 | K82: =(COUNTBLANK(PSPOINTS[[#This Row],[PayScalePointCode]:[RateDateFrom]])+COUNTBLANK(PSPOINTS[[#This Row],[PayScaleRate]])) -> 0 | L82: =IF(SUBSTITUTE(TEXT(PSPOINTS[[#This Row],[PayScaleCode]],10)," ","")=TEXT(PSPOINTS[[#This Row],[PayScaleCode]],10),0,1)+IF(SUBSTITUTE(TEXT(PSPOINTS[[#This Row],[PayScalePointCode]],10)," ","")=TEXT(PSPOINTS[[#This Row],[PayScalePointCode]],10),0,1) -> 0 | M82: =SUM(PSPOINTS[[#This Row],[Scale Point Issue]:[Space in Code]]) -> 0 | N82: England & Wales | P82: NJC_EW | Q82: =_xlfn.XLOOKUP(PSPOINTS[[#This Row],[PayScaleCode]],'19_PayScales'!N:N,'19_PayScales'!O:O) -> NJC EW | R82: 3 | S82: 3 | T82: 3 | U82: FALSE | V82: TRUE | W82: 45748 | Y82: 24796
A83: =PSPOINTS[[#This Row],[PayScaleCode]]&PSPOINTS[[#This Row],[RateDateFrom]] -> NJC_EW45748 | B83: =IF(A83=A82,SUM(T83-T82)-1,T83-1) -> 0 | C83: =PSPOINTS[[#This Row],[PayScaleCode]]&PSPOINTS[[#This Row],[PayScalePointCode]]&PSPOINTS[[#This Row],[RateDateFrom]] -> NJC_EW445748 | D83: =COUNTIF(PSPOINTS[Pay Scale String Duplicates],PSPOINTS[[#This Row],[Pay Scale String Duplicates]])-1 -> 0 | E83: =IF((MONTH(_xlfn.XLOOKUP(PSPOINTS[[#This Row],[PayScaleCode]],'19_PayScales'!N:N,'19_PayScales'!R:R)))=MONTH(PSPOINTS[[#This Row],[RateDateFrom]]),0,1) -> 0 | F83: =IF(ISBLANK(PSPOINTS[[#This Row],[RateDateTo]]),0,IF(PSPOINTS[[#This Row],[RateDateFrom]]<PSPOINTS[[#This Row],[RateDateTo]],0,1)) -> 0 | G83: {=IF(CELL("format",PSPOINTS[[#This Row],[RateDateFrom]])="D1",0,1)+IF(CELL("format",PSPOINTS[[#This Row],[RateDateTo]])="D1",0,1)} -> 0 | H83: =IF(OR(PSPOINTS[[#This Row],[Hourly]]=TRUE,PSPOINTS[[#This Row],[Hourly]]=FALSE),IF(OR(PSPOINTS[[#This Row],[PayScalePointEnabled]]=TRUE,PSPOINTS[[#This Row],[PayScalePointEnabled]]=FALSE),0,1),1) -> 0 | I83: =IF(LEN(PSPOINTS[[#This Row],[PayScalePointCode]])<100,0,1) -> 0 | J83: =IF(LEN(PSPOINTS[[#This Row],[PayScalePointTitle]])<100,0,1) -> 0 | K83: =(COUNTBLANK(PSPOINTS[[#This Row],[PayScalePointCode]:[RateDateFrom]])+COUNTBLANK(PSPOINTS[[#This Row],[PayScaleRate]])) -> 0 | L83: =IF(SUBSTITUTE(TEXT(PSPOINTS[[#This Row],[PayScaleCode]],10)," ","")=TEXT(PSPOINTS[[#This Row],[PayScaleCode]],10),0,1)+IF(SUBSTITUTE(TEXT(PSPOINTS[[#This Row],[PayScalePointCode]],10)," ","")=TEXT(PSPOINTS[[#This Row],[PayScalePointCode]],10),0,1) -> 0 | M83: =SUM(PSPOINTS[[#This Row],[Scale Point Issue]:[Space in Code]]) -> 0 | N83: England & Wales | P83: NJC_EW | Q83: =_xlfn.XLOOKUP(PSPOINTS[[#This Row],[PayScaleCode]],'19_PayScales'!N:N,'19_PayScales'!O:O) -> NJC EW | R83: 4 | S83: 4 | T83: 4 | U83: FALSE | V83: TRUE | W83: 45748 | Y83: 25185
A84: =PSPOINTS[[#This Row],[PayScaleCode]]&PSPOINTS[[#This Row],[RateDateFrom]] -> NJC_EW45748 | B84: =IF(A84=A83,SUM(T84-T83)-1,T84-1) -> 0 | C84: =PSPOINTS[[#This Row],[PayScaleCode]]&PSPOINTS[[#This Row],[PayScalePointCode]]&PSPOINTS[[#This Row],[RateDateFrom]] -> NJC_EW545748 | D84: =COUNTIF(PSPOINTS[Pay Scale String Duplicates],PSPOINTS[[#This Row],[Pay Scale String Duplicates]])-1 -> 0 | E84: =IF((MONTH(_xlfn.XLOOKUP(PSPOINTS[[#This Row],[PayScaleCode]],'19_PayScales'!N:N,'19_PayScales'!R:R)))=MONTH(PSPOINTS[[#This Row],[RateDateFrom]]),0,1) -> 0 | F84: =IF(ISBLANK(PSPOINTS[[#This Row],[RateDateTo]]),0,IF(PSPOINTS[[#This Row],[RateDateFrom]]<PSPOINTS[[#This Row],[RateDateTo]],0,1)) -> 0 | G84: {=IF(CELL("format",PSPOINTS[[#This Row],[RateDateFrom]])="D1",0,1)+IF(CELL("format",PSPOINTS[[#This Row],[RateDateTo]])="D1",0,1)} -> 0 | H84: =IF(OR(PSPOINTS[[#This Row],[Hourly]]=TRUE,PSPOINTS[[#This Row],[Hourly]]=FALSE),IF(OR(PSPOINTS[[#This Row],[PayScalePointEnabled]]=TRUE,PSPOINTS[[#This Row],[PayScalePointEnabled]]=FALSE),0,1),1) -> 0 | I84: =IF(LEN(PSPOINTS[[#This Row],[PayScalePointCode]])<100,0,1) -> 0 | J84: =IF(LEN(PSPOINTS[[#This Row],[PayScalePointTitle]])<100,0,1) -> 0 | K84: =(COUNTBLANK(PSPOINTS[[#This Row],[PayScalePointCode]:[RateDateFrom]])+COUNTBLANK(PSPOINTS[[#This Row],[PayScaleRate]])) -> 0 | L84: =IF(SUBSTITUTE(TEXT(PSPOINTS[[#This Row],[PayScaleCode]],10)," ","")=TEXT(PSPOINTS[[#This Row],[PayScaleCode]],10),0,1)+IF(SUBSTITUTE(TEXT(PSPOINTS[[#This Row],[PayScalePointCode]],10)," ","")=TEXT(PSPOINTS[[#This Row],[PayScalePointCode]],10),0,1) -> 0 | M84: =SUM(PSPOINTS[[#This Row],[Scale Point Issue]:[Space in Code]]) -> 0 | N84: England & Wales | P84: NJC_EW | Q84: =_xlfn.XLOOKUP(PSPOINTS[[#This Row],[PayScaleCode]],'19_PayScales'!N:N,'19_PayScales'!O:O) -> NJC EW | R84: 5 | S84: 5 | T84: 5 | U84: FALSE | V84: TRUE | W84: 45748 | Y84: 25583
A85: =PSPOINTS[[#This Row],[PayScaleCode]]&PSPOINTS[[#This Row],[RateDateFrom]] -> NJC_EW45748 | B85: =IF(A85=A84,SUM(T85-T84)-1,T85-1) -> 0 | C85: =PSPOINTS[[#This Row],[PayScaleCode]]&PSPOINTS[[#This Row],[PayScalePointCode]]&PSPOINTS[[#This Row],[RateDateFrom]] -> NJC_EW645748 | D85: =COUNTIF(PSPOINTS[Pay Scale String Duplicates],PSPOINTS[[#This Row],[Pay Scale String Duplicates]])-1 -> 0 | E85: =IF((MONTH(_xlfn.XLOOKUP(PSPOINTS[[#This Row],[PayScaleCode]],'19_PayScales'!N:N,'19_PayScales'!R:R)))=MONTH(PSPOINTS[[#This Row],[RateDateFrom]]),0,1) -> 0 | F85: =IF(ISBLANK(PSPOINTS[[#This Row],[RateDateTo]]),0,IF(PSPOINTS[[#This Row],[RateDateFrom]]<PSPOINTS[[#This Row],[RateDateTo]],0,1)) -> 0 | G85: {=IF(CELL("format",PSPOINTS[[#This Row],[RateDateFrom]])="D1",0,1)+IF(CELL("format",PSPOINTS[[#This Row],[RateDateTo]])="D1",0,1)} -> 0 | H85: =IF(OR(PSPOINTS[[#This Row],[Hourly]]=TRUE,PSPOINTS[[#This Row],[Hourly]]=FALSE),IF(OR(PSPOINTS[[#This Row],[PayScalePointEnabled]]=TRUE,PSPOINTS[[#This Row],[PayScalePointEnabled]]=FALSE),0,1),1) -> 0 | I85: =IF(LEN(PSPOINTS[[#This Row],[PayScalePointCode]])<100,0,1) -> 0 | J85: =IF(LEN(PSPOINTS[[#This Row],[PayScalePointTitle]])<100,0,1) -> 0 | K85: =(COUNTBLANK(PSPOINTS[[#This Row],[PayScalePointCode]:[RateDateFrom]])+COUNTBLANK(PSPOINTS[[#This Row],[PayScaleRate]])) -> 0 | L85: =IF(SUBSTITUTE(TEXT(PSPOINTS[[#This Row],[PayScaleCode]],10)," ","")=TEXT(PSPOINTS[[#This Row],[PayScaleCode]],10),0,1)+IF(SUBSTITUTE(TEXT(PSPOINTS[[#This Row],[PayScalePointCode]],10)," ","")=TEXT(PSPOINTS[[#This Row],[PayScalePointCode]],10),0,1) -> 0 | M85: =SUM(PSPOINTS[[#This Row],[Scale Point Issue]:[Space in Code]]) -> 0 | N85: England & Wales | P85: NJC_EW | Q85: =_xlfn.XLOOKUP(PSPOINTS[[#This Row],[PayScaleCode]],'19_PayScales'!N:N,'19_PayScales'!O:O) -> NJC EW | R85: 6 | S85: 6 | T85: 6 | U85: FALSE | V85: TRUE | W85: 45748 | Y85: 25989
A86: =PSPOINTS[[#This Row],[PayScaleCode]]&PSPOINTS[[#This Row],[RateDateFrom]] -> NJC_EW45748 | B86: =IF(A86=A85,SUM(T86-T85)-1,T86-1) -> 0 | C86: =PSPOINTS[[#This Row],[PayScaleCode]]&PSPOINTS[[#This Row],[PayScalePointCode]]&PSPOINTS[[#This Row],[RateDateFrom]] -> NJC_EW745748 | D86: =COUNTIF(PSPOINTS[Pay Scale String Duplicates],PSPOINTS[[#This Row],[Pay Scale String Duplicates]])-1 -> 0 | E86: =IF((MONTH(_xlfn.XLOOKUP(PSPOINTS[[#This Row],[PayScaleCode]],'19_PayScales'!N:N,'19_PayScales'!R:R)))=MONTH(PSPOINTS[[#This Row],[RateDateFrom]]),0,1) -> 0 | F86: =IF(ISBLANK(PSPOINTS[[#This Row],[RateDateTo]]),0,IF(PSPOINTS[[#This Row],[RateDateFrom]]<PSPOINTS[[#This Row],[RateDateTo]],0,1)) -> 0 | G86: {=IF(CELL("format",PSPOINTS[[#This Row],[RateDateFrom]])="D1",0,1)+IF(CELL("format",PSPOINTS[[#This Row],[RateDateTo]])="D1",0,1)} -> 0 | H86: =IF(OR(PSPOINTS[[#This Row],[Hourly]]=TRUE,PSPOINTS[[#This Row],[Hourly]]=FALSE),IF(OR(PSPOINTS[[#This Row],[PayScalePointEnabled]]=TRUE,PSPOINTS[[#This Row],[PayScalePointEnabled]]=FALSE),0,1),1) -> 0 | I86: =IF(LEN(PSPOINTS[[#This Row],[PayScalePointCode]])<100,0,1) -> 0 | J86: =IF(LEN(PSPOINTS[[#This Row],[PayScalePointTitle]])<100,0,1) -> 0 | K86: =(COUNTBLANK(PSPOINTS[[#This Row],[PayScalePointCode]:[RateDateFrom]])+COUNTBLANK(PSPOINTS[[#This Row],[PayScaleRate]])) -> 0 | L86: =IF(SUBSTITUTE(TEXT(PSPOINTS[[#This Row],[PayScaleCode]],10)," ","")=TEXT(PSPOINTS[[#This Row],[PayScaleCode]],10),0,1)+IF(SUBSTITUTE(TEXT(PSPOINTS[[#This Row],[PayScalePointCode]],10)," ","")=TEXT(PSPOINTS[[#This Row],[PayScalePointCode]],10),0,1) -> 0 | M86: =SUM(PSPOINTS[[#This Row],[Scale Point Issue]:[Space in Code]]) -> 0 | N86: England & Wales | P86: NJC_EW | Q86: =_xlfn.XLOOKUP(PSPOINTS[[#This Row],[PayScaleCode]],'19_PayScales'!N:N,'19_PayScales'!O:O) -> NJC EW | R86: 7 | S86: 7 | T86: 7 | U86: FALSE | V86: TRUE | W86: 45748 | Y86: 26403
A87: =PSPOINTS[[#This Row],[PayScaleCode]]&PSPOINTS[[#This Row],[RateDateFrom]] -> NJC_EW45748 | B87: =IF(A87=A86,SUM(T87-T86)-1,T87-1) -> 0 | C87: =PSPOINTS[[#This Row],[PayScaleCode]]&PSPOINTS[[#This Row],[PayScalePointCode]]&PSPOINTS[[#This Row],[RateDateFrom]] -> NJC_EW845748 | D87: =COUNTIF(PSPOINTS[Pay Scale String Duplicates],PSPOINTS[[#This Row],[Pay Scale String Duplicates]])-1 -> 0 | E87: =IF((MONTH(_xlfn.XLOOKUP(PSPOINTS[[#This Row],[PayScaleCode]],'19_PayScales'!N:N,'19_PayScales'!R:R)))=MONTH(PSPOINTS[[#This Row],[RateDateFrom]]),0,1) -> 0 | F87: =IF(ISBLANK(PSPOINTS[[#This Row],[RateDateTo]]),0,IF(PSPOINTS[[#This Row],[RateDateFrom]]<PSPOINTS[[#This Row],[RateDateTo]],0,1)) -> 0 | G87: {=IF(CELL("format",PSPOINTS[[#This Row],[RateDateFrom]])="D1",0,1)+IF(CELL("format",PSPOINTS[[#This Row],[RateDateTo]])="D1",0,1)} -> 0 | H87: =IF(OR(PSPOINTS[[#This Row],[Hourly]]=TRUE,PSPOINTS[[#This Row],[Hourly]]=FALSE),IF(OR(PSPOINTS[[#This Row],[PayScalePointEnabled]]=TRUE,PSPOINTS[[#This Row],[PayScalePointEnabled]]=FALSE),0,1),1) -> 0 | I87: =IF(LEN(PSPOINTS[[#This Row],[PayScalePointCode]])<100,0,1) -> 0 | J87: =IF(LEN(PSPOINTS[[#This Row],[PayScalePointTitle]])<100,0,1) -> 0 | K87: =(COUNTBLANK(PSPOINTS[[#This Row],[PayScalePointCode]:[RateDateFrom]])+COUNTBLANK(PSPOINTS[[#This Row],[PayScaleRate]])) -> 0 | L87: =IF(SUBSTITUTE(TEXT(PSPOINTS[[#This Row],[PayScaleCode]],10)," ","")=TEXT(PSPOINTS[[#This Row],[PayScaleCode]],10),0,1)+IF(SUBSTITUTE(TEXT(PSPOINTS[[#This Row],[PayScalePointCode]],10)," ","")=TEXT(PSPOINTS[[#This Row],[PayScalePointCode]],10),0,1) -> 0 | M87: =SUM(PSPOINTS[[#This Row],[Scale Point Issue]:[Space in Code]]) -> 0 | N87: England & Wales | P87: NJC_EW | Q87: =_xlfn.XLOOKUP(PSPOINTS[[#This Row],[PayScaleCode]],'19_PayScales'!N:N,'19_PayScales'!O:O) -> NJC EW | R87: 8 | S87: 8 | T87: 8 | U87: FALSE | V87: TRUE | W87: 45748 | Y87: 26824
A88: =PSPOINTS[[#This Row],[PayScaleCode]]&PSPOINTS[[#This Row],[RateDateFrom]] -> NJC_EW45748 | B88: =IF(A88=A87,SUM(T88-T87)-1,T88-1) -> 0 | C88: =PSPOINTS[[#This Row],[PayScaleCode]]&PSPOINTS[[#This Row],[PayScalePointCode]]&PSPOINTS[[#This Row],[RateDateFrom]] -> NJC_EW945748 | D88: =COUNTIF(PSPOINTS[Pay Scale String Duplicates],PSPOINTS[[#This Row],[Pay Scale String Duplicates]])-1 -> 0 | E88: =IF((MONTH(_xlfn.XLOOKUP(PSPOINTS[[#This Row],[PayScaleCode]],'19_PayScales'!N:N,'19_PayScales'!R:R)))=MONTH(PSPOINTS[[#This Row],[RateDateFrom]]),0,1) -> 0 | F88: =IF(ISBLANK(PSPOINTS[[#This Row],[RateDateTo]]),0,IF(PSPOINTS[[#This Row],[RateDateFrom]]<PSPOINTS[[#This Row],[RateDateTo]],0,1)) -> 0 | G88: {=IF(CELL("format",PSPOINTS[[#This Row],[RateDateFrom]])="D1",0,1)+IF(CELL("format",PSPOINTS[[#This Row],[RateDateTo]])="D1",0,1)} -> 0 | H88: =IF(OR(PSPOINTS[[#This Row],[Hourly]]=TRUE,PSPOINTS[[#This Row],[Hourly]]=FALSE),IF(OR(PSPOINTS[[#This Row],[PayScalePointEnabled]]=TRUE,PSPOINTS[[#This Row],[PayScalePointEnabled]]=FALSE),0,1),1) -> 0 | I88: =IF(LEN(PSPOINTS[[#This Row],[PayScalePointCode]])<100,0,1) -> 0 | J88: =IF(LEN(PSPOINTS[[#This Row],[PayScalePointTitle]])<100,0,1) -> 0 | K88: =(COUNTBLANK(PSPOINTS[[#This Row],[PayScalePointCode]:[RateDateFrom]])+COUNTBLANK(PSPOINTS[[#This Row],[PayScaleRate]])) -> 0 | L88: =IF(SUBSTITUTE(TEXT(PSPOINTS[[#This Row],[PayScaleCode]],10)," ","")=TEXT(PSPOINTS[[#This Row],[PayScaleCode]],10),0,1)+IF(SUBSTITUTE(TEXT(PSPOINTS[[#This Row],[PayScalePointCode]],10)," ","")=TEXT(PSPOINTS[[#This Row],[PayScalePointCode]],10),0,1) -> 0 | M88: =SUM(PSPOINTS[[#This Row],[Scale Point Issue]:[Space in Code]]) -> 0 | N88: England & Wales | P88: NJC_EW | Q88: =_xlfn.XLOOKUP(PSPOINTS[[#This Row],[PayScaleCode]],'19_PayScales'!N:N,'19_PayScales'!O:O) -> NJC EW | R88: 9 | S88: 9 | T88: 9 | U88: FALSE | V88: TRUE | W88: 45748 | Y88: 27254
A89: =PSPOINTS[[#This Row],[PayScaleCode]]&PSPOINTS[[#This Row],[RateDateFrom]] -> NJC_EW45748 | B89: =IF(A89=A88,SUM(T89-T88)-1,T89-1) -> 0 | C89: =PSPOINTS[[#This Row],[PayScaleCode]]&PSPOINTS[[#This Row],[PayScalePointCode]]&PSPOINTS[[#This Row],[RateDateFrom]] -> NJC_EW1045748 | D89: =COUNTIF(PSPOINTS[Pay Scale String Duplicates],PSPOINTS[[#This Row],[Pay Scale String Duplicates]])-1 -> 0 | E89: =IF((MONTH(_xlfn.XLOOKUP(PSPOINTS[[#This Row],[PayScaleCode]],'19_PayScales'!N:N,'19_PayScales'!R:R)))=MONTH(PSPOINTS[[#This Row],[RateDateFrom]]),0,1) -> 0 | F89: =IF(ISBLANK(PSPOINTS[[#This Row],[RateDateTo]]),0,IF(PSPOINTS[[#This Row],[RateDateFrom]]<PSPOINTS[[#This Row],[RateDateTo]],0,1)) -> 0 | G89: {=IF(CELL("format",PSPOINTS[[#This Row],[RateDateFrom]])="D1",0,1)+IF(CELL("format",PSPOINTS[[#This Row],[RateDateTo]])="D1",0,1)} -> 0 | H89: =IF(OR(PSPOINTS[[#This Row],[Hourly]]=TRUE,PSPOINTS[[#This Row],[Hourly]]=FALSE),IF(OR(PSPOINTS[[#This Row],[PayScalePointEnabled]]=TRUE,PSPOINTS[[#This Row],[PayScalePointEnabled]]=FALSE),0,1),1) -> 0 | I89: =IF(LEN(PSPOINTS[[#This Row],[PayScalePointCode]])<100,0,1) -> 0 | J89: =IF(LEN(PSPOINTS[[#This Row],[PayScalePointTitle]])<100,0,1) -> 0 | K89: =(COUNTBLANK(PSPOINTS[[#This Row],[PayScalePointCode]:[RateDateFrom]])+COUNTBLANK(PSPOINTS[[#This Row],[PayScaleRate]])) -> 0 | L89: =IF(SUBSTITUTE(TEXT(PSPOINTS[[#This Row],[PayScaleCode]],10)," ","")=TEXT(PSPOINTS[[#This Row],[PayScaleCode]],10),0,1)+IF(SUBSTITUTE(TEXT(PSPOINTS[[#This Row],[PayScalePointCode]],10)," ","")=TEXT(PSPOINTS[[#This Row],[PayScalePointCode]],10),0,1) -> 0 | M89: =SUM(PSPOINTS[[#This Row],[Scale Point Issue]:[Space in Code]]) -> 0 | N89: England & Wales | P89: NJC_EW | Q89: =_xlfn.XLOOKUP(PSPOINTS[[#This Row],[PayScaleCode]],'19_PayScales'!N:N,'19_PayScales'!O:O) -> NJC EW | R89: 10 | S89: 10 | T89: 10 | U89: FALSE | V89: TRUE | W89: 45748 | Y89: 27694
